Workbook
Name Fact: DISTRIBUCIÓN!#REF!
Name Fact: 'DISTRIBUCIÓN (2)'!#REF!
Name Fact: #REF!
Name Marca: #REF!
Name Marca1: #REF!
Name Marcas: #REF!
Name Valor: #REF!
Name Value: #REF!
Name values: #REF!

Sheet Festivos Colombia
A2: FESTIVOS COLOMBIA
A3: 46023
A4: 46034
A5: 46104
A6: 46110
A7: 46114
A8: 46115
A9: 46117
A10: 46143
A11: 46160
A12: 46181
A13: 46188
A14: 46202
... A22: 46381

Sheet DICIEMBRE
E1: 42400
I2: 1
I3: 2
D4: BANCOS | E4: =SUBTOTAL(9,E5:E11) -> 1.339387e+09 | I4: 3
D5: Bancos | E5: 1.1397443e+09 | I5: 4
D6: Devolucion tiquete Cristian Ferney Parada Cabrera | E6: 139474
D7: Ingreso Bancolombia Panamá Pago primas | E7: 183919680
D8: Ingreso Banco Finandina | E8: 5000000
D9: Pago intereses PM | E9: 4808596
D10: devolucion saldo caja menor | E10: 215700
D11: Suramericana Incapacidad | E11: 5559334
D12: CLIENTES | E12: =SUBTOTAL(9,E13:E58) -> 3.4220209e+08
C13: Pagado | D13: ACT&J Consultores Factura 6472-6337-6423 y saldo Factura 6182 $ 77,525 | E13: 4524531.5 | F13: ***
C14: Pagado | D14: ACT&J Consultores Factura 6502-Noviembre Pretalires | E14: 1549380 | F14: ***
C15: Pagado | D15: AECID Factura # 6533-Octubre y noviembre | E15: 51544069
C16: Pagado | D16: AECID Factura #5-132-Octubre y noviembre | E16: 5260000
C17: Pagado | D17: AECID Factura # 6574 | E17: 34362713
C18: Pagado | D18: Clarke Modet factura # 6459 | E18: 2455029.2 | F18: ***
C19: Pagado | D19: Compassion international factura # 6542 | E19: 6563937.3
C20: Pagado | D20: Consorcio HL-AB Factura # 6107-6205 | E20: 9784261
C21: Pagado | D21: Consorcio HL-AB Factura # 6107-6205 | E21: 1880863 | J21: =E20+E21+E23+E40+E41+E42+E43 -> 87943892
C22: Sin Pagar | D22: Consorcio HL-A&D Factura 6478 | E22: =1341880.13*0 -> 0
C23: Pagado | D23: Consorcio HL Gisaico Factura 6432 | E23: =605371 -> 605371
C24: Pagado | D24: Consorcio SK-HL facturas 6422 | E24: =229392 -> 229392 | F24: ***
C25: Pagado | D25: Consorcio SK-HL facturas 6501 | E25: =229392 -> 229392
C26: Sin Pagar | D26: Corporación punto azul factura # 6424 | E26: =1692717.2*0 -> 0 | F26: ***
C27: Sin Pagar | D27: Dinterweb factura # 5646-5725-5805-5892-5974-6061 | E27: =7528323*0 -> 0
C28: Sin Pagar | D28: Distritech facturas # 6235 Llega por Panamá | E28: =5391183.76*0 -> 0
C29: Sin Pagar | D29: Dream Tyme resort Factura # 1-27 | E29: =9781142.24*0 -> 0
C30: Sin Pagar | D30: Dream Tyme resort Factura # 6437 | E30: =1007999.64*0 -> 0
C31: Sin Pagar | D31: Dream Tyme Primera y segunda quincena Diciembre | E31: =9781142.24*2*0 -> 0
C32: Sin Pagar | D32: Dream Tyme Primera y segunda quincena Diciembre | E32: =4713074*0 -> 0
C33: Sin Pagar | D33: Ecohl factura # 6373-6375 | E33: =1228866.62*0 -> 0
C34: Pagado | D34: Gilead Scense Colombia Factura # 5-154 | E34: 821905.26
C35: Pagado | D35: Global CS Colombia SAS -Solutions & payroll-Servicio Noviembre 2025 Factura 6467 | E35: 17406804 | F35: ***
C36: Pagado | D36: Global CS Colombia SAS -Solutions & payroll-Factura 5-93 Reembolso Gastos Nov | E36: 359994 | F36: ***
C37: Pagado | D37: Global Projects service AG facturas # 6268 | E37: 2455134.4 | F37: 2676011 | G37: =(E37-F37) -> -220876.55
C38: Sin Pagar | D38: Global Projects service AG facturas # 6315 | E38: =2709294*0 -> 0
C39: Sin Pagar | D39: HL Gestiones factura # 6395 | E39: =597907.31*0 -> 0 | I39: 4
C40: Pagado | D40: HL Ingenieros factura # 6127 a 6226 | E40: 2568994
C41: Pagado | D41: HL Ingenieros factura # 6280 a 6283 | E41: 383449
C42: Pagado | D42: Hl Infraestructura factura # 6146-6208 | E42: 46541148
C43: Pagado | D43: Hl Infraestructura factura # 6318 | E43: 26179806
C44: Pagado | D44: Inversiones el Bosque factura # 6569 | E44: =1897290 -> 1897290
C45: Sin Pagar | D45: Live Systems technology factura # 6466 | E45: =1202975.28*0 -> 0
C46: Pagado | D46: Ortho Clinical Diagnostics # 6381 | E46: =1380793.13 -> 1380793.1
C47: Pagado | D47: Petrobras Colombia Factura # 6474 | E47: 17383715
C48: Pagado | D48: Petrobras Internacional Baspetro Factura # 6426 | E48: 6565950.1
C49: Pagado | D49: Safeguard por identificar Deel | E49: 3462300
C50: Pagado | D50: Safeguard por identificar Deel | E50: ='MONETIZACIONES PEND'!$R$348+'MONETIZACIONES PEND'!$R$349+'MONETIZACIONES PEND'!$R$350+'MONETIZACIONES PEND'!$R$351 -> 90383091
C51: Sin Pagar | D51: Safeguard Payroll LTD y LLC Julio-(vencio en septiembre) | E51: =87111218.1195*0 -> 0 | F51: 0 | G51: =(E51-F51)*0 -> 0 | J51: 20841.55
C52: Sin Pagar | D52: Safeguard Payroll LTD y LLC Agosto-(vencio en Octubre) | E52: =66875205.9551*0 -> 0 | F52: 0 | G52: =(E52-F52)*0 -> 0 | J52: 16639.39
C53: Sin Pagar | D53: Safeguard Payroll LTD y LLC Septiembre-(vencio en Noviembre) | E53: =63738690.8265*0 -> 0 | F53: 0 | G53: =(E53-F53)*0 -> 0 | J53: 16337.85
C54: Sin Pagar | D54: Rejimetal Factura # 4441-4524-4609-4688-4788-4865-4970-5060-5150-5272-5372-5485-5565-5642-5721-5802-588 | E54: =7370606*0 -> 0 | J54: =SUM(J51:J53) -> 53818.79
C55: Pagado | D55: Sinerware SAS Factura # 6392-6469-6570 | E55: 1843176
C56: Sin Pagar | D56: Soluciones ambientales punto azul Factura # 6504 | E56: =694763.99*0 -> 0
C57: Pagado | D57: TPL Logistics factura # 6478 | E57: =1826568.28 -> 1826568.3
C58: Pagado | D58: TPL Logistics factura # 6568 | E58: 1753029.4
D59: PE | E59: =SUBTOTAL(9,E60:E109) -> #REF! | F59: 1
C60: Sin Pagar | D60: Advancio Factura # 5461 EO Third parties service ADVANCIO - (November) | E60: ='MONETIZACIONES PEND'!#REF!*0 -> #REF! | G60: =(E60-F60)*0 -> #REF!
C61: Pagado | D61: Action Factura # 6561 | E61: 1265173.3 | F61: 1293165.9 | G61: =(E61-F61) -> -27992.594
C62: Pagado | D62: Action Factura # 5-156 | E62: 11501681 | F62: 11756162 | G62: =(E62-F62) -> -254480.46
C63: Pagado | D63: Bubble BPM Factura # 6523 | E63: 484792.18 | F63: 493290.8 | G63: =(E63-F63) -> -8498.6199
C64: Pagado | D64: Bubble BPM Factura # 5-136 | E64: 4407288.8 | F64: 4484550.5 | G64: =(E64-F64) -> -77261.71
C65: Pagado | D65: Edrington Factura # 6363 Octubre | E65: 2235488.1 | F65: 2228468.5 | G65: =(E65-F65) -> 7019.5672
C66: Pagado | D66: Edrington Factura # 5-84 Octubre | E66: 40644343 | F66: 40516717 | G66: =(E66-F66) -> 127625.68
C67: Pagado | D67: Edrington Factura # 6527 Diciembre | E67: 1621642.8 | F67: 1615169.9 | G67: =(E67-F67) -> 6472.872
C68: Pagado | D68: Edrington Factura # 5-139 Diciembre | E68: 29484466 | F68: 29366777 | G68: =(E68-F68) -> 117688.79
C69: Pagado | D69: EPDM Factura # 6541 | E69: 1004663 | G69: =(E69-F69)*0 -> 0
C70: Pagado | D70: EPDM Factura # 5-146 | E70: 10046625 | G70: =(E70-F70)*0 -> 0
C71: Pagado | D71: Equus Global Expansion, LLC Factura # 6524 | E71: 676247.25 | F71: 670058.66 | G71: =(E71-F71) -> 6188.595
C72: Pagado | D72: Equus Global Expansion, LLC Factura # 5-137 | E72: 5928055.4 | F72: 5873805.5 | G72: =(E72-F72) -> 54249.883
C73: Pagado | D73: Europortage Factura # 6525 | E73: 3109612.8 | F73: 3100513.4 | G73: =(E73-F73) -> 9099.3735
C74: Pagado | D74: Europortage Factura # 5-138 | E74: 53099097 | F74: 52943718 | G74: =(E74-F74) -> 155379
C75: Sin Pagar | D75: Hemmebarsch GMBH & Co KG , factura # 6447 Diciembre | E75: =683895.328*0 -> 0 | G75: =(E75-F75)*0 -> 0
C76: Sin Pagar | D76: Hemmebarsch GMBH & Co KG , factura # 5-104 Diciembre | E76: =6838916.456*0 -> 0 | G76: =(E76-F76)*0 -> 0
C77: Sin Pagar | D77: Hemmebarsch GMBH & Co KG , factura # 6448 Diciembre | E77: =427452.992*0 -> 0 | G77: =(E77-F77)*0 -> 0
C78: Sin Pagar | D78: Hemmebarsch GMBH & Co KG , factura # 5-105 Diciembre | E78: =4274640.392*0 -> 0 | G78: =(E78-F78)*0 -> 0
C79: Sin Pagar | D79: Hemmebarsch GMBH & Co KG , factura # 6540 Enero | E79: =427980.3884*0 -> 0 | G79: =(E79-F79)*0 -> 0
C80: Sin Pagar | D80: Hemmebarsch GMBH & Co KG , factura # 5-144 Enero | E80: =4279879.4722*0 -> 0 | G80: =(E80-F80)*0 -> 0
C81: Sin Pagar | D81: Hong kong yonyou xinfushe cloud technology co., limited Factura 6559-(Pendiente monetizar) | E81: =2855434.869*0 -> 0 | G81: =(E81-F81)*0 -> 0
C82: Sin Pagar | D82: Hong kong yonyou xinfushe cloud technology co., limited Factura 5-152 (Pendiente monetizar) | E82: =53276427.2691*0 -> 0 | G82: =(E82-F82)*0 -> 0
C83: Pagado | D83: Flexco Factura # 6558 | E83: 2230013.9 | F83: 2282657.7 | G83: =(E83-F83) -> -52643.886
C84: Pagado | D84: Flexco Factura # 5-151 | E84: 24778065 | F84: 25363000 | G84: =(E84-F84) -> -584935.2
C85: Pagado | D85: Insider factura #5-145 Prima | E85: 1.4449483e+08 | F85: 1.4457083e+08 | G85: =(E85-F85) -> -75999.99
C86: Pagado | D86: Insider factura # 159 | E86: 7.6138947e+08 | F86: 7.8383419e+08 | G86: =(E86-F86) -> -22444717
C87: Sin Pagar | D87: Insider factura # 160 | E87: =3973041.075*0 -> 0 | G87: =(E87-F87)*0 -> 0
C88: Pagado | D88: MKD Factura # 6521 | E88: 645767.34 | F88: 640408.65 | G88: =(E88-F88) -> 5358.6918
C89: Pagado | D89: MKD Factura # 5-134 | E89: 5870456.6 | F89: 5821742.5 | G89: =(E89-F89) -> 48714.088
C90: Pagado | D90: Nazdar Factura # 6538 | E90: 3725117.6 | F90: 3762553.8 | G90: =(E90-F90) -> -37436.272
C91: Pagado | D91: Nazdar Factura # 5-142 | E91: 62084794 | F91: 62708727 | G91: =(E91-F91) -> -623932.86
C92: Pagado | D92: Neo Factura # 6552 | E92: 7560646.5 | F92: 7531872.2 | G92: =(E92-F92) -> 28774.266
C93: Pagado | D93: Neo Factura # FV-5-135 | E93: 96515781 | F93: 96148462 | G93: =(E93-F93) -> 367319.22
C94: Pagado | D94: Neo Factura # 6557 | E94: 160637.12 | F94: 160025.77 | G94: =(E94-F94) -> 611.35187
C95: Pagado | D95: Oncehub Factura # 5-31 | E95: 5028811.9 | F95: 5039027.5 | G95: =(E95-F95) -> -10215.622
C96: Pagado | D96: Oncehub Factura # 6551 | E96: 1062609.7 | F96: 1072405.2 | G96: =(E96-F96) -> -9795.4867
C97: Pagado | D97: Oncehub Factura # 5-156 | E97: 11523622 | F97: 11629851 | G97: =(E97-F97) -> -106228.55
C98: Sin Pagar | D98: Oncehub Factura # 5-160 | E98: =11287082.5151*0 -> 0 | G98: =(E98-F98)*0 -> 0
C99: Sin Pagar | D99: Remofirst Factura # 5-60 Octubre (Pendiente monetizar) | E99: =(3255.57*3890.28)*0 -> 0 | G99: =(E99-F99)*0 -> 0
C100: Sin Pagar | D100: Remofirst Factura # 6338 Octubre (Pendiente monetizar) | E100: =3333190.9*0 -> 0 | G100: =(E100-F100)*0 -> 0
...

Sheet ENERO
E1: 42400
I2: 1
I3: 2
D4: BANCOS | E4: =SUBTOTAL(9,E5:E14) -> 1.0939477e+09 | I4: 3
D5: Bancos | E5: =DICIEMBRE!$E$345 -> 1.0574441e+09 | I5: 4
D6: Incapacidad pendiente por identificar | E6: 800040
D7: Incapacidad pendiente por identificar | E7: 400475
D8: Incapacidad pagada Sandra Milena Bello | E8: 64397
D9: Pago intereses PM | E9: 22670000
D10: Devolución Camara de comercio | E10: 190000
D11: Devolución Camara de comercio | E11: 69000
D12: Transferencia de fondos por Saldo de anticipo People Pass Root capital | E12: 284009
D13: Devolución dinero Root capital | E13: 12000000
D14: Devolución de retención IVA – Factura FEG 1344 Gelcon | E14: 25650
D15: CLIENTES | E15: =SUBTOTAL(9,E16:E55) -> 1.2653437e+08
C16: Pagado | D16: ACT&J Consultores Factura 6555 | E16: 1572392.3
C17: Pagado | D17: ACT&J Consultores Factura 6612 | E17: 1549380
C18: Sin Pagar | D18: AECID Factura # 6640 | E18: =34362712.65*0 -> 0
C19: Sin Pagar | D19: AECID Factura # 5-200 | E19: =2104000*0 -> 0
C20: Pagado | D20: Clarke Modet factura # 6564 | E20: 2373194.9
C21: Pagado | D21: Compassion international factura # 6360 | E21: =6898752.51 -> 6898752.5 | G21: =E22+E23+E24+E30+E37+E38 -> 33574449
C22: Pagado | D22: Consorcio A&D Factura # 6478-6508-6545 | E22: 3254917
C23: Pagado | D23: Consorcio HL-AB Factura # 6357 - 6358 | E23: 498186
C24: Pagado | D24: Consorcio HL Gisaico Factura 6532-6534 | E24: 1568049
C25: Pagado | D25: Monica Londoño Factura 6396 | E25: 177905
C26: Pagado | D26: Corporación punto azul factura # 6424 | E26: =1692717.2 -> 1692717.2
C27: Sin Pagar | D27: Dinterweb factura # 5646-5725-5805-5892-5974-6061 | E27: =7528323*0 -> 0
C28: Sin Pagar | D28: Distritech facturas # 6235 Llega por Panamá | E28: =5391183.76*0 -> 0
C29: Sin Pagar | D29: Dream Tyme resort | E29: =23310881.53*0 -> 0
C30: Pagado | D30: Ecohl facturas 6373-6474-6375 | E30: 1228867
C31: Pagado | D31: Funeravet factura # 6599 | E31: 771364.8
C32: Pagado | D32: Gilead Scense Colombia Factura # 6628 | E32: 915290.76
C33: Sin Pagar | D33: Global CS Colombia SAS factura # 6443 | E33: =17406803.72*0 -> 0
C34: Pagado | D34: Global CS Colombia SAS -factura # 6554 - 163 | E34: 19282040
C35: Sin Pagar | D35: Global Projects service AG facturas # 6315-27-45 (Pendiente monetizar) | E35: =15456075.3468*0 -> 0
C36: Sin Pagar | D36: HL Gestiones factura # 6395 | E36: =1121157.31*0 -> 0 | I36: 4
C37: Pagado | D37: HL Ingenieros factura # 6355 | E37: 217212
C38: Pagado | D38: Hl Infraestructura factura # 6366 -6368 - 6369 - 6371 - 6372 - 6386 - 6387 - 6402 | E38: 26807218
C39: Pagado | D39: Inversiones el Bosque factura # 6391 | E39: 2049073
C40: Pagado | D40: Inversiones el Bosque factura # 6627 | E40: 2013009
C41: Sin Pagar | D41: Live Systems technology factura # 6466 | E41: =1202975.28*0 -> 0
C42: Pagado | D42: Ortho Clinical Diagnostics # 6460 | E42: =1380793.13 -> 1380793.1
C43: Pagado | D43: Ortho Clinical Diagnostics # 6543 | E43: =1380793.13 -> 1380793.1
C44: Pagado | D44: Petrobras Colombia Factura # 6517 | E44: 17383715
C45: Pagado | D45: Petrobras Colombia Factura # 6518 | E45: 17383715
C46: Pagado | D46: Petrobras Internacional Baspetro Factura # 6516 | E46: 6664686.2
C47: Pagado | D47: Petrobras Internacional Baspetro Factura # 6526 | E47: 6714054.2
C48: Sin Pagar | D48: Safeguard por identificar Deel (Pendiente monetizar) | E48: =3462300*0 -> 0
C49: Sin Pagar | D49: Safeguard por identificar Deel (Pendiente monetizar) | E49: =('MONETIZACIONES PEND'!$R$348+'MONETIZACIONES PEND'!$R$349+'MONETIZACIONES PEND'!$R$350+'MONETIZACIONES PEND'!$R$351)*0 -> 0
C50: Sin Pagar | D50: Safeguard Payroll LTD y LLC Julio-(vencio en septiembre) | E50: =87111218.1195*0 -> 0 | F50: 0 | G50: =(E50-F50)*0 -> 0 | J50: 20841.55
C51: Sin Pagar | D51: Safeguard Payroll LTD y LLC Agosto-(vencio en Octubre) | E51: =66875205.9551*0 -> 0 | F51: 0 | G51: =(E51-F51)*0 -> 0 | J51: 16639.39
C52: Sin Pagar | D52: Safeguard Payroll LTD y LLC Septiembre-(vencio en Noviembre) | E52: =63738690.8265*0 -> 0 | F52: 0 | G52: =(E52-F52)*0 -> 0 | J52: 16337.85
C53: Sin Pagar | D53: Rejimetal Factura # 4441-4524-4609-4688-4788-4865-4970-5060-5150-5272-5372-5485-5565-5642-5721-5802-588 | E53: =7370606*0 -> 0 | J53: =SUM(J50:J52) -> 53818.79
C54: Pagado | D54: Soluciones ambientales punto azul Factura # 6504 tiene NC 183 por valor $ 3,214,02 | E54: 691500
C55: Pagado | D55: TPL Logistics factura # 6632 | E55: 2065543.5
D56: PE | E56: =SUBTOTAL(9,E57:E110) -> 1.4862727e+09 | F56: 1
C57: Pagado | D57: Advancio Factura # 5461 EO Third parties service ADVANCIO | E57: 8144748.8 | F57: 8125838 | G57: =(E57-F57) -> 18910.822
C58: Pagado | D58: Action Factura # 6619 | E58: 1302416.6 | F58: 1295534.9 | G58: =(E58-F58) -> 6881.7024
C59: Pagado | D59: Action Factura # 5-187 | E59: 11840204 | F59: 11777643 | G59: =(E59-F59) -> 62561.211
C60: Pagado | D60: Bubble BPM Factura # 6609 | E60: =447027.7908*0 -> 0 | G60: =(E60-F60)*0 -> 0
C61: Pagado | D61: Bubble BPM Factura # 5-175 | E61: =4064001.2694*0 -> 0 | G61: =(E61-F61)*0 -> 0
C62: Pagado | D62: Edrington Factura # 6606 | E62: 3571941.7 | F62: 3547520.9 | G62: =(E62-F62) -> 24420.768 | K62: =E56-E57-E70-E71-E72+E73-E76-E77-E78-E79-E80-E81-E85-E94-E100-E101-E102-E103-E104 -> 1.4433771e+09
C63: Pagado | D63: Edrington Factura # 5-172 | E63: 64944404 | F63: 64500390 | G63: =(E63-F63) -> 444014.02
C64: Pagado | D64: EPDM Factura # 6541 | E64: 1005157.2 | G64: =(E64-F64)*0 -> 0
C65: Pagado | D65: EPDM Factura # 5-146 | E65: 10051573 | G65: =(E65-F65)*0 -> 0
C66: Pagado | D66: Equus Global Expansion, LLC Factura # 6600 | E66: 655634.24 | F66: 653547.41 | G66: =(E66-F66) -> 2086.8398
C67: Pagado | D67: Equus Global Expansion, LLC Factura # 5-165 | E67: 4454897 | F67: 4440717.3 | G67: =(E67-F67) -> 14179.638
C68: Pagado | D68: Europortage Factura # 6607 | E68: 3005458.1 | F68: 2973712 | G68: =(E68-F68) -> 31746.057
C69: Pagado | D69: Europortage Factura # 5-173 | E69: 45096718 | F69: 44620370 | G69: =(E69-F69) -> 476347.68
C70: Pagado | D70: Hemmebarsch GMBH & Co KG , factura # 6447 Diciembre | E70: 674536.9 | F70: 683895.33 | G70: =(E70-F70) -> -9358.4308
C71: Pagado | D71: Hemmebarsch GMBH & Co KG , factura # 5-104 Diciembre | E71: 6745332.7 | F71: 6838916.5 | G71: =(E71-F71) -> -93583.804
C72: Pagado | D72: Hemmebarsch GMBH & Co KG , factura # 6448 Diciembre | E72: 421603.72 | F72: 427452.99 | G72: =(E72-F72) -> -5849.2712
C73: Pagado | D73: Hemmebarsch GMBH & Co KG , factura # 5-105 Diciembre | E73: 4216146.2 | F73: 4274640.4 | G73: =(E73-F73) -> -58494.224
C74: Pagado | D74: Hemmebarsch GMBH & Co KG , factura # 6539 Enero | E74: 656449.49 | F74: 683090.56 | G74: =(E74-F74) -> -26641.076
C75: Pagado | D75: Hemmebarsch GMBH & Co KG , factura # 5-143 Enero | E75: 6564567.5 | F75: 6830981.2 | G75: =(E75-F75) -> -266413.71
C76: Pagado | D76: Hemmebarsch GMBH & Co KG , factura # 6540 Enero | E76: 411288.81 | F76: 427980.39 | G76: =(E76-F76) -> -16691.576
C77: Pagado | D77: Hemmebarsch GMBH & Co KG , factura # 5-144 Enero | E77: 4112960.8 | F77: 4279879.5 | G77: =(E77-F77) -> -166918.71
C78: Sin Pagar | D78: Hong kong yonyou xinfushe cloud technology co., limited Factura 6559-(Pendiente monetizar)Diciembre | E78: =2855434.869*0 -> 0 | G78: =(E78-F78)*0 -> 0
C79: Sin Pagar | D79: Hong kong yonyou xinfushe cloud technology co., limited Factura 5-152 (Pendiente monetizar) Diciembre | E79: =53276427.2691*0 -> 0 | G79: =(E79-F79)*0 -> 0
C80: Sin Pagar | D80: Hong kong yonyou xinfushe cloud technology co., limited Factura 6608- Enero | E80: =2707376.616*0 -> 0 | G80: =(E80-F80)*0 -> 0
C81: Sin Pagar | D81: Hong kong yonyou xinfushe cloud technology co., limited Factura 5-174 Enero | E81: =43507906.9584*0 -> 0 | G81: =(E81-F81)*0 -> 0
C82: Sin Pagar | D82: Hong kong yonyou xinfushe cloud technology co., limited Factura 5-186 Enero | E82: =21217642.2864*0 -> 0 | G82: =(E82-F82)*0 -> 0
C83: Pagado | D83: Flexco Factura # 6603 | E83: 4074854.4 | F83: 4040409 | G83: =(E83-F83) -> 34445.38
C84: Pagado | D84: Flexco Factura # 5-169 | E84: 45275601 | F84: 44892879 | G84: =(E84-F84) -> 382721.72
C85: Sin Pagar | D85: Insider factura # 160 Diciembre (Pendiente monetizar) | E85: =3973041.075*0 -> 0 | G85: =(E85-F85)*0 -> 0
C86: Sin Pagar | D86: Insider factura # 188 expenses | E86: =5737331.7549*0 -> 0 | G86: =(E86-F86)*0 -> 0
C87: Sin Pagar | D87: Insider factura # XXX | E87: =761389470.9*0 -> 0 | G87: =(E87-F87)*0 -> 0
C88: Pagado | D88: MKD Factura # 6602 | E88: 508583.25 | F88: 498246.9 | G88: =(E88-F88) -> 10336.349
C89: Pagado | D89: MKD Factura # 5-168 | E89: 4623113.2 | F89: 4529154 | G89: =(E89-F89) -> 93959.273
C90: Pagado | D90: Nazdar Factura # 6604 | E90: 3239286.4 | F90: 3205708.9 | G90: =(E90-F90) -> 33577.542
C91: Pagado | D91: Nazdar Factura # 5-170 | E91: 53987559 | F91: 53427939 | G91: =(E91-F91) -> 559620.02
C92: Sin Pagar | D92: Neo Factura # 6613 | E92: =5494632.9165*0 -> 0 | G92: =(E92-F92)*0 -> 0
C93: Sin Pagar | D93: Neo Factura # FV-5-181 | E93: =68683476.3615*0 -> 0 | G93: =(E93-F93)*0 -> 0
C94: Sin Pagar | D94: Oncehub Factura # 5-161 ( cesantías) | E94: 10822102 | F94: =11287082.5151 -> 11287083 | G94: =(E94-F94) -> -464980.72
C95: Sin Pagar | D95: Oncehub Factura # 6617 | E95: 1037676.6 | F95: 1031230.2 | G95: =(E95-F95) -> 6446.3603
C96: Sin Pagar | D96: Oncehub Factura # 5-171 | E96: 11831039 | F96: 11757541 | G96: =(E96-F96) -> 73497.987
C97: Pagado | D97: Poc Pharma Limited Factura # 6619 | E97: 1751760 | F97: 1749384 | G97: =(E97-F97) -> 2376
C98: Pagado | D98: Poc Pharma Limited Factura # 5-182 | E98: 5417974.7 | F98: 5410626 | G98: =(E98-F98) -> 7348.671
C99: Pagado | D99: Poc Pharma Limited Factura # 5-183 | E99: 5474250 | F99: 5466825 | G99: =(E99-F99) -> 7425
C100: Pagado | D100: Remofirst Factura # 5-60 Octubre | E100: 11825858 | F100: =(3255.57*3890.28) -> 12665079 | G100: =(E100-F100) -> -839220.83
...

Sheet FEBRERO
E1: 42400
I2: 1
I3: 2
D4: BANCOS | E4: =SUBTOTAL(9,E5:E12) -> 9.2277668e+08 | I4: 3
D5: Bancos | E5: =ENERO!E329+900255200.74 -> 9.0048942e+08 | I5: 4
C6: Pagado | D6: Punto medical | E6: 2670000
C7: Pagado | D7: Devolución de dinero a cuenta BAC panamá para prestamo Nomina global PA USD 2000 | E7: 7200000 | I7: 4
C8: Pagado | D8: Pago incapacidad Suramericana Lina Guio | E8: 539025
C9: Pagado | D9: Pago incapacidad Suramericana Ricardo Arambulo | E9: 10920122
C10: Pagado | D10: Pago Devolución saldo a favor suramericana | E10: 432545
C11: Pagado | D11: Pago Devolución pago tiquete Aereo Ana Guitierrez | E11: 525570
C12: Pagado | D12: Devolucion de dinero de Global Peo Services Panamá para el envio del pago SIPE Enero
D13: CLIENTES | E13: =SUBTOTAL(9,E14:E52) -> 6.3206884e+08
C14: Sin Pagar | D14: ACT&J Consultores Factura 1682 | E14: =1572392.28307*0 -> 0
C15: Pagado | D15: AECID Factura # 6640 | E15: =34362712.65 -> 34362713
C16: Pagado | D16: AECID Factura # 5-200 | E16: =2104000 -> 2104000
C17: Pagado | D17: Clarke Modet factura # 6618 | E17: 2629357.6
C18: Pagado | D18: Compassion international factura # 6717 | E18: 6766084.2
C19: Pagado | D19: Consorcio HL-AB Factura # 6454 | E19: 318616.52
C20: Pagado | D20: Monica Londoño Factura 6719 | E20: =190536 -> 190536
C21: Pagado | D21: Corporación punto azul factura # 6503-6528 | E21: 3808077
C22: Pagado | D22: Deel Facturas # 6407-6408-6409-6410-6411-6412-6413-6491-6492-6493-6494-6495 | E22: 39020834 | F22: 41322268 | G22: =(E22-F22) -> -2301434.4
C23: Pagado | D23: Deel Facturas # 6415-6416-6417-6496-6497-6498-6499-126 | E23: 14229202 | F23: 14859058 | G23: =(E23-F23) -> -629856
C24: Pagado | D24: Deel Facturas #6165-6166-6167-6168-6169-6170-6171-6172-6173-6174-6249-6250-6251-6252-6253-6254-6255-6256-6257-6486-6487-6488-6489-6490-6581-6582-6583-6586-6587-6588-6589 | E24: 1.3794203e+08 | F24: 1.4618867e+08 | G24: =(E24-F24) -> -8246639.2
C25: Pagado | D25: Deel Facturas # 6175-6176-6177-6178-6179-6258-6259-6260-6261-6262-6500-6592-164-6593-6594 | E25: 1.0584899e+08 | F25: 1.1213237e+08 | G25: =(E25-F25) -> -6283381.3 | K25: =E19+E33+E39+E40 -> 35007675
C26: Pagado | D26: Deel Facturas # 6584-6585 | E26: 7843526.4 | F26: 7981254.7 | G26: =(E26-F26) -> -137728.29
C27: Pagado | D27: Deel Facturas # 6590-6591 | E27: 2747269.2 | F27: 2782525.8 | G27: =(E27-F27) -> -35256.621
C28: Pagado | D28: Deel Facturas #6654-6655-6656-201-6657-6658 | E28: 13980796 | F28: 14014539 | G28: =(E28-F28) -> -33743.01
C29: Pagado | D29: Deel Facturas # 6645-6647-6648-6650-6651-6652-6653 | E29: 31640804 | F29: 31747485 | G29: =(E29-F29) -> -106681.36
C30: Sin Pagar | D30: Dinterweb factura # 5646-5725-5805-5892-5974-6061 | E30: =7528323*0 -> 0
C31: Sin Pagar | D31: Distritech facturas # 6631 Llega por Panamá | E31: =5391183.76*0 -> 0
C32: Sin Pagar | D32: Dream Tyme resort | E32: =23310882*0 -> 0
C33: Pagado | D33: Ecohl facturas 6428-6429-6430 | E33: 1276724
C34: Pagado | D34: Gilead Scense Colombia Factura # 6715 | E34: 1359917.2
C35: Pagado | D35: Global CS Colombia SAS -factura # 6605-5-197 | E35: 20139314
C36: Pagado | D36: Global Projects service AG facturas # 6315-27-45 | E36: 14472628 | F36: 15456075 | G36: =(E36-F36) -> -983447.15
C37: Pagado | D37: Global Projects service AG facturas # 6534 | E37: 2543700 | F37: 2739268 | G37: =(E37-F37) -> -195568
C38: Pagado | D38: HL Gestiones factura # 6718 | E38: 1200756 | I38: 4
C39: Pagado | D39: HL Ingenieros factura # 6441-6531-6548 | E39: 1088426
C40: Pagado | D40: Hl Infraestructura factura # 6427-6431-6438-6444-6471-6476-6477 | E40: 32323908
C41: Pagado | D41: Inversiones el Bosque factura # 6714 | E41: 2271097.4
C42: Pagado | D42: Live Systems technology factura # 6466-6567 | E42: 2591024
C43: Pagado | D43: Ortho Clinical Diagnostics # 6635 | E43: 1451213.8
C44: Pagado | D44: Punto medical FV-4-6316-FV-4-6397-FV-4-6473-FV-4-6579 e intereses | E44: 8046831.9
C45: Pagado | D45: Safeguard 6400-6401-6384-6385 | E45: 32219017 | F45: 34120335 | G45: =(E45-F45) -> -1901318.4
C46: Pagado | D46: Safeguard 6482-6483-6484 | E46: 26044853 | F46: 26853239 | G46: =(E46-F46) -> -808386.69
C47: Pagado | D47: S&P Costa Rica factura Nro. 6481-6595-6642-6667 | E47: =4485*3650 -> 16370250
C48: Pagado | D48: S&P Guatemala factura Nro. 6302-6377-6480-6641-6666 | E48: =14122.03*3650 -> 51545410
C49: Pagado | D49: S&P Panamá Pendiente por aclarar las facturas | E49: =3082*3650 -> 11249300
C50: Sin Pagar | D50: Rejimetal Factura # 4441-4524-4609-4688-4788-4865-4970-5060-5150-5272-5372-5485-5565-5642-5721-5802-588 | E50: =7370606*0 -> 0
C51: Sin Pagar | D51: Soluciones ambientales punto azul Factura # 6529 | E51: =659409.77*0 -> 0
C52: Pagado | D52: TPL Logistics factura # 6713 | E52: 2441626.7
D53: PE | E53: =SUBTOTAL(9,E54:E119) -> 2.632108e+09 | F53: 1
C54: Pagado | D54: Action Factura # 6664 | E54: 1244283.5 | F54: 1208258.3 | G54: =(E54-F54) -> 36025.196
C55: Pagado | D55: Action Factura # 5-203 | E55: 11311973 | F55: 10984462 | G55: =(E55-F55) -> 327510.61
C56: Pagado | D56: Bubble BPM Factura # 6609 Enero | E56: 439591.99 | F56: 447027.79 | G56: =(E56-F56) -> -7435.8011
C57: Pagado | D57: Bubble BPM Factura # 5-175 Enero | E57: 3996401.2 | F57: 4064001.3 | G57: =(E57-F57) -> -67600.059
C58: Pagado | D58: Bubble BPM Factura # 6686 | E58: 460095.82 | F58: 447484.62 | G58: =(E58-F58) -> 12611.2
C59: Pagado | D59: Bubble BPM Factura # 5-215 | E59: 4182686 | F59: 4068038.8 | G59: =(E59-F59) -> 114647.18
C60: Pagado | D60: Edrington Factura # 6671 | E60: 2232759.1 | F60: 2169042.8 | G60: =(E60-F60) -> 63716.294
C61: Pagado | D61: Edrington Factura # 5-205 | E61: 40595911 | F61: 39437425 | G61: =(E61-F61) -> 1158486.4
C62: Pagado | D62: EPDM Factura # 6683 | E62: 993693.3 | G62: =(E62-F62)*0 -> 0
C63: Pagado | D63: EPDM Factura # 5-212 | E63: 9936933 | G63: =(E63-F63)*0 -> 0
C64: Pagado | D64: Equus Global Expansion, LLC Factura # 6687 | E64: 657373.96 | F64: 632480.83 | G64: =(E64-F64) -> 24893.124
C65: Pagado | D65: Equus Global Expansion, LLC Factura # 5-216 | E65: 5337655.6 | F65: 5135531.8 | G65: =(E65-F65) -> 202123.8
C66: Pagado | D66: Europortage Factura # 6673 | E66: 3008086.5 | F66: 2931678.9 | G66: =(E66-F66) -> 76407.573
C67: Pagado | D67: Europortage Factura # 5-207 | E67: 49910068 | F67: 48642317 | G67: =(E67-F67) -> 1267751.8
C68: Pagado | D68: Hemmebarsch GMBH & Co KG , factura # 6623 Febrero | E68: 689544.96 | F68: 714384.08 | G68: =(E68-F68) -> -24839.118
C69: Pagado | D69: Hemmebarsch GMBH & Co KG , factura # 6624 Febrero | E69: 460560 | F69: 477150.51 | G69: =(E69-F69) -> -16590.512
C70: Pagado | D70: Hemmebarsch GMBH & Co KG , factura # 5-189 Febrero | E70: 6895632 | F70: 7144029.8 | G70: =(E70-F70) -> -248397.75
C71: Pagado | D71: Hemmebarsch GMBH & Co KG , factura # 5-190 Febrero | E71: 4605527 | F71: 4771429.5 | G71: =(E71-F71) -> -165902.5
C72: Sin Pagar | D72: Hemmebarsch GMBH & Co KG , factura # 6700 Marzo | E72: =337854.6085*0 -> 0 | G72: =(E72-F72) -> 0
C73: Sin Pagar | D73: Hemmebarsch GMBH & Co KG , factura # 6703 Marzo | E73: =2480352.4331*0 -> 0 | G73: =(E73-F73) -> 0
C74: Sin Pagar | D74: Hemmebarsch GMBH & Co KG , factura # 5-224 Marzo | E74: =3378616.9512*0 -> 0 | G74: =(E74-F74) -> 0
C75: Pagado | D75: Hong kong yonyou xinfushe cloud technology co., limited Factura 6559-Diciembre | E75: 2743902 | F75: 2855434.9 | G75: =(E75-F75) -> -111532.87
C76: Pagado | D76: Hong kong yonyou xinfushe cloud technology co., limited Factura 5-152 - Diciembre | E76: 51195458 | F76: 53276427 | G76: =(E76-F76) -> -2080969.5
C77: Pagado | D77: Hong kong yonyou xinfushe cloud technology co., limited Factura 6608- Enero | E77: =2730497.364*0 -> 0 | F77: =707376.616*0 -> 0 | G77: =(E77-F77)*0 -> 0
C78: Pagado | D78: Hong kong yonyou xinfushe cloud technology co., limited Factura 5-174 Enero | E78: =3879460.4936*0 -> 0 | F78: =43507906.9584*0 -> 0 | G78: =(E78-F78)*0 -> 0
C79: Pagado | D79: Hong kong yonyou xinfushe cloud technology co., limited Factura 5-186 Enero | E79: =1398839.0056*0 -> 0 | F79: =21217642.2864*0 -> 0 | G79: =(E79-F79)*0 -> 0
C80: Pagado | D80: Hong kong yonyou xinfushe cloud technology co., limited Factura 6702- Febrero | E80: 2756946.8 | F80: 2687562 | G80: =(E80-F80) -> 69384.735
C81: Pagado | D81: Hong kong yonyou xinfushe cloud technology co., limited Factura 5-226 Febrero | E81: 50970823 | F81: 49688029 | G81: =(E81-F81) -> 1282794.8
C82: Pagado | D82: Flexco Factura # 6680 | E82: 1299786.8 | F82: 1249690 | G82: =(E82-F82) -> 50096.759
C83: Pagado | D83: Flexco Factura # 5-209 | E83: 14442046 | F83: 13885417 | G83: =(E83-F83) -> 556629.55
C84: Pagado | D84: Insider factura # 160 Diciembre | E84: 3791577 | F84: 3973041.1 | G84: =(E84-F84) -> -181464.08
C85: Pagado | D85: Insider factura # 188 expenses | E85: 5675860.9 | F85: 5737325.3 | G85: =(E85-F85) -> -61464.392
C86: Pagado | D86: Insider factura # 6639 | E86: =23056440.5522066*0 -> 0 | F86: =22996377.768*0 -> 0 | G86: =(E86-F86)*0 -> 0
C87: Pagado | D87: Insider factura # 199 | E87: =745415764.649794*0 -> 0 | F87: =743473932.123*0 -> 0 | G87: =(E87-F87)*0 -> 0
C88: Pagado | D88: Insider factura # 6722 | E88: 19962474 | F88: 19662072 | G88: =(E88-F88) -> 300401.73
C89: Pagado | D89: Insider factura # 216 | E89: 7.0329876e+08 | F89: 6.927153e+08 | G89: =(E89-F89) -> 10583466
C90: Pagado | D90: Minudoc OÜ ( SIFFI) Factura # 6689 | E90: 2138606.9 | F90: 2094641.5 | G90: =(E90-F90) -> 43965.346
C91: Pagado | D91: Minudoc OÜ ( SIFFI) Factura # 5-218 | E91: 6054893.4 | F91: 5930417.3 | G91: =(E91-F91) -> 124476.12
C92: Pagado | D92: Minudoc OÜ ( SIFFI) Factura # 5-219 | E92: 9422938.6 | F92: 9229222.4 | G92: =(E92-F92) -> 193716.18
C93: Pagado | D93: MKD Factura # 6679 | E93: 520041.32 | F93: 498827.18 | G93: =(E93-F93) -> 21214.138
C94: Pagado | D94: MKD Factura # 5-208 | E94: 4727618.1 | F94: 4534763.6 | G94: =(E94-F94) -> 192854.57
C95: Pagado | D95: Nazdar Factura # 6701 | E95: 3680038.1 | F95: 3538928.1 | G95: =(E95-F95) -> 141109.98
C96: Pagado | D96: Nazdar Factura # 5-225 | E96: 61333794 | F96: 58981967 | G96: =(E96-F96) -> 2351826.3
C97: Pagado | D97: Neo Factura # 6613 | E97: 5499958.2 | F97: ='MONETIZACIONES PEND'!Q442 -> 5494632.9 | G97: =(E97-F97) -> 5325.3233
C98: Pagado | D98: Neo Factura # FV-5-181 | E98: 59718742 | F98: ='MONETIZACIONES PEND'!Q443 -> 59660919 | G98: =(E98-F98) -> 57822.549
C99: Pagado | D99: Neo Factura # 6638 | E99: 232127.47 | F99: ='MONETIZACIONES PEND'!Q444 -> 231902.72 | G99: =(E99-F99) -> 224.75695
C100: Pagado | D100: Neo Factura # FV-5-196 | E100: 2901356.3 | F100: ='MONETIZACIONES PEND'!Q445 -> 2898547.1 | G100: =(E100-F100) -> 2809.2323
...

Sheet MARZO
E1: 42400
I2: 1
I3: 2
D4: BANCOS | E4: =SUBTOTAL(9,E5:E9) -> 6.9897103e+08 | I4: 3
D5: Bancos | E5: =FEBRERO!E330 -> 6.5971468e+08 | I5: 4
C6: Pagado | D6: Devolucion de dinero de Peo global services | E6: 59698832 | F6: 59489365 | G6: =E6-F6 -> 209466.82
C7: Pagado | D7: Pago Advancio 6644 | E7: 311941
D8: Menos devolución de Panamá para enviarle dinero a Yadira para el pago de SIPE Marzo | E8: =-(6145*3704.87) -> -22766426
C9: Pagado | D9: Por identificar | E9: 2012000
D10: CLIENTES | E10: =SUBTOTAL(9,E11:E45) -> 2.3801491e+08
C11: Pagado | D11: ACT&J Consultores Factura 6695-6792-6598 ( abono) | E11: 4870966.4
C12: Pagado | D12: AECID Factura # 6720 | E12: 34362713
C13: Pagado | D13: AECID Factura # 5-233 | E13: 2104000
C14: Pagado | D14: Clarke Modet factura # 6704 | E14: 2717002.9
C15: Pagado | D15: Compassion international factura # 6799 | E15: 6766084.2
C16: Sin Pagar | D16: Consorcio HL-Gisaico # 6668-6669 | E16: =2503090.56*0 -> 0
C17: Sin Pagar | D17: Monica Londoño Factura 6573 | E17: =177905*0 -> 0
C18: Sin Pagar | D18: Consorcio Gisaico facturas # 6668-6669 | E18: 2015276.2
C19: Sin Pagar | D19: Consorcio SK - HL 6615 - 6659 | E19: 504664
C20: Pagado | D20: Corporación punto azul factura # 6601 | E20: 2015276.2
C21: Pagado | D21: Deel factura # 6658 | E21: 42535444 | F21: 41874833 | G21: =(E21-F21) -> 660611.52
C22: Pagado | D22: Deel facturas # 6646-6649 | E22: 39759248 | F22: 39196672 | G22: =(E22-F22) -> 562575.48
C23: Sin Pagar | D23: Dinterweb factura # 5646-5725-5805-5892-5974-6061 | E23: =7528323*0 -> 0
C24: Sin Pagar | D24: Distritech facturas # 6631 Llega por Panamá | E24: =5391183.76*0 -> 0
C25: Sin Pagar | D25: Dream Tyme resort | E25: =23310882*0 -> 0
C26: Pagado | D26: Ecohl facturas 6509 a 6511-6552-6553 | E26: 3312381
C27: Pagado | D27: Evoluzion talent abono a la factura 6742 | E27: 560489
C28: Pagado | D28: Funeravet Factura # 6699 | E28: 405352
C29: Pagado | D29: Gilead Scense Colombia Factura # 6802 | E29: 920132.14
C30: Pagado | D30: Global CS Colombia SAS -factura # 6696-5-235 | E30: 18921371
C31: Pagado | D31: Global Projects service AG facturas # FV-4-6403-FV-4-6505-FV-5-85-FV-5-123-FV-5-158-FV-5-198 | E31: 30962053 | F31: 31750578 | G31: =+E31-F31 -> -788524.88
C32: Sin Pagar | D32: HL Gestiones factura # 6395-6572 | E32: =1719065*0 -> 0 | I32: 4
C33: Sin Pagar | D33: HL Ingenieros factura # 6441-6531 | E33: =723071*0 -> 0
C34: Pagado | D34: Hl Infraestructura factura # 6515 - 6544 | E34: =7328987 -> 7328987
C35: Sin Pagar | D35: Inversiones el Bosque factura # 6797 | E35: =2013039*0 -> 0
C36: Sin Pagar | D36: Live Systems technology factura # 6626 | E36: =1264316.04*0 -> 0
C37: Pagado | D37: Ortho Clinical Diagnostics # 6705 | E37: 1451213.8
C38: Pagado | D38: Petrobras colombia Factura # 6697 | E38: 18182068
C39: Pagado | D39: Petrobras baspetro Factura # 6660 | E39: 7948929
C40: Pagado | D40: Petrobras baspetro Factura # 6746 | E40: 7402389
C41: Sin Pagar | D41: Punto medical | E41: =19087032.49*0 -> 0
C42: Sin Pagar | D42: Rejimetal | E42: =6463289.78*0 -> 0
C43: Pagado | D43: Sinerware Facturas 6629-6716-6798 | E43: 1955609.6
C44: Pagado | D44: Soluciones ambientales punto azul Factura # 6662 | E44: 1013262.7
C45: Sin Pagar | D45: TPL Logistics factura # 6796 | E45: =2033960.42*0 -> 0
D46: EOR | E46: =SUBTOTAL(9,E47:E95) -> 2.5514533e+09 | F46: 1
C47: Pagado | D47: Action Factura # 6783 | E47: 1287215.8 | F47: 1279036.5 | G47: =(E47-F47) -> 8179.2568
C48: Pagado | D48: Action Factura #5-255 | E48: 11701868 | F48: 11627512 | G48: =(E48-F48) -> 74356.286
C49: Sin Pagar | D49: Bubble BPM Factura # 6686 | E49: =447484.6199*0 -> 0 | G49: =(E49-F49)*0 -> 0
C50: Sin Pagar | D50: Bubble BPM Factura # 5-215 | E50: =4068038.7779*0 -> 0 | G50: =(E50-F50)*0 -> 0
C51: Pagado | D51: Edrington Factura # 6774 | E51: 2413175.2 | F51: 2383548.8 | G51: =(E51-F51) -> 29626.333
C52: Pagado | D52: Edrington Factura # 5-249 | E52: 43875949 | F52: 43337288 | G52: =(E52-F52) -> 538661.05
C53: Pagado | D53: EPDM Factura # 6683 | E53: 1001074.9 | G53: =(E53-F53)*0 -> 0
C54: Pagado | D54: EPDM Factura # 5-212 | E54: 10010749 | G54: =(E54-F54)*0 -> 0
C55: Pagado | D55: Equus Global Expansion, LLC Factura # 6801 | E55: 655391.31 | F55: 648561.9 | G55: =(E55-F55) -> 6829.41
C56: Pagado | D56: Equus Global Expansion, LLC Factura # 5-267 | E56: 1637376.8 | F56: 1620314.7 | G56: =(E56-F56) -> 17062.047
C57: Pagado | D57: Europortage Factura # 6788 | E57: 3927375.7 | F57: 3867163 | G57: =(E57-F57) -> 60212.758
C58: Pagado | D58: Europortage Factura # 5-260 | E58: 62203345 | F58: 61249671 | G58: =(E58-F58) -> 953673.7
C59: Pagado | D59: Hemmebarsch GMBH & Co KG , factura # 6684 Marzo | E59: 717615.65 | F59: 676772.21 | G59: =(E59-F59) -> 40843.44
C60: Pagado | D60: Hemmebarsch GMBH & Co KG , factura # 2-13 Marzo | E60: 7176043.8 | F60: 6767615.8 | G60: =(E60-F60) -> 408427.98
C61: Pagado | D61: Hemmebarsch GMBH & Co KG , factura # 6685 Marzo | E61: 479299.63 | F61: 452020.06 | G61: =(E61-F61) -> 27279.569
C62: Pagado | D62: Hemmebarsch GMBH & Co KG , factura # 2-14 Marzo | E62: 4792883.5 | F62: 4520094.3 | G62: =(E62-F62) -> 272789.27
C63: Pagado | D63: Hemmebarsch GMBH & Co KG , factura # 6700 Marzo | E63: 352448.88 | F63: 337854.61 | G63: =(E63-F63) -> 14594.271
C64: Pagado | D64: Hemmebarsch GMBH & Co KG , factura # 5-224 Marzo | E64: 3524562.7 | F64: 3378617 | G64: =(E64-F64) -> 145945.77
C65: Sin Pagar | D65: Hemmebarsch GMBH & Co KG , factura # 6771 Marzo | E65: 462859.45 | F65: 452558.85 | G65: =(E65-F65) -> 10300.597
C66: Sin Pagar | D66: Hemmebarsch GMBH & Co KG , factura # 5-246 Marzo | E66: 4628742.4 | F66: 4525733.1 | G66: =(E66-F66) -> 103009.26
... C90: Pagado | D90: Remofirst Factura # 5-237 | E90: 37191073 | F90: 36984362 | G90: =(E90-F90) -> 206711.09
C91: Pagado | D91: Rivermate Factura # 6768 | E91: 1285422 | G91: =(E91-F91)*0 -> 0
C92: Pagado | D92: Rivermate Factura # 5-241 | E92: 71495628 | G92: =(E92-F92)*0 -> 0
C93: Pagado | D93: Rivermate Factura # 5-270 | E93: 1893065.1 | G93: =(E93-F93)*0 -> 0
C94: Pagado | D94: Root capital factura # 6775 | E94: 1871058.6 | F94: 1860581 | G94: =(E94-F94) -> 10477.582
C95: Pagado | D95: Root capital # FV-5-250 | E95: 20823086 | F95: 20706480 | G95: =(E95-F95) -> 116605.42
D96: TOTAL INGRESOS | E96: =SUBTOTAL(9,E4:E95) -> 3.4884392e+09 | G96: =SUM(G6:G95) -> 14108744
C99: CUENTAS X PAGAR MES | E99: MARZO | F99: Fecha de Elaboración: | J99: 46082
C100: Factura | D100: PROVEEDOR | E100: VALOR | F100: Fecha vencimiento | G100: Estado | J100: KPI | K100: Objeto
D101: PAGOS ANTICIPADOS | E101: =SUBTOTAL(9,E102:E104) -> 17522648
A102: =G102 -> Cancelado | B102: =IF(I102<=-1,1,IF(I102<=5,2,IF(I102<=15,3,IF(H102<=60,4)))) -> 3 | D102: Anticipo nómina Action | E102: 4360000 | F102: 46094 | G102: Cancelado | H102: =IF(OR(G102="Sin pagar",G102="Pagar"),NETWORKDAYS($J$99,F102,'Festivos Colombia'!$A$3:$A$22),0) -> 0 | I102: =NETWORKDAYS($J$99,F102,'Festivos Colombia'!$A$3:$A$22) -> 10 | J102: =H102 -> 0
A103: =G103 -> Cancelado | B103: =IF(I103<=-1,1,IF(I103<=5,2,IF(I103<=15,3,IF(H103<=60,4)))) -> 3 | D103: Anticipo nómina Nazdar | E103: 9500000 | F103: 46094 | G103: Cancelado | H103: =IF(OR(G103="Sin pagar",G103="Pagar"),NETWORKDAYS($J$99,F103,'Festivos Colombia'!$A$3:$A$22),0) -> 0 | I103: =NETWORKDAYS($J$99,F103,'Festivos Colombia'!$A$3:$A$22) -> 10 | J103: =H103 -> 0
A104: =G104 -> Cancelado | B104: =IF(I104<=-1,1,IF(I104<=5,2,IF(I104<=15,3,IF(H104<=60,4)))) -> 4 | D104: Anticipo nómina Action | E104: 3662648 | F104: 46112 | G104: Cancelado | H104: =IF(OR(G104="Sin pagar",G104="Pagar"),NETWORKDAYS($J$99,F104,'Festivos Colombia'!$A$3:$A$22),0) -> 0 | I104: =NETWORKDAYS($J$99,F104,'Festivos Colombia'!$A$3:$A$22) -> 21 | J104: =H104 -> 0
D105: SEGURIDAD SOCIAL | E105: =SUBTOTAL(9,E106:E106) -> 517318100
A106: =G106 -> Cancelado | B106: =IF(I106<=-1,1,IF(I106<=5,2,IF(I106<=15,3,IF(H106<=60,4)))) -> 3 | C106: 176206200 | D106: Seguridad social | E106: 517318100 | F106: 46092 | G106: Cancelado | H106: =IF(OR(G106="Sin pagar",G106="Pagar"),NETWORKDAYS($J$99,F106,'Festivos Colombia'!$A$3:$A$22),0) -> 0 | I106: =NETWORKDAYS($J$99,F106,'Festivos Colombia'!$A$3:$A$22) -> 8 | J106: =H106 -> 0
D107: AFC´S | E107: =SUBTOTAL(9,E108:E110) -> 14755460
A108: =G108 -> Cancelado | B108: =IF(I108<=-1,1,IF(I108<=5,2,IF(I108<=15,3,IF(H108<=60,4)))) -> 4 | D108: AFC Dafuturo cheque | E108: 1000000 | F108: 46111 | G108: Cancelado | H108: =IF(OR(G108="Sin pagar",G108="Pagar"),NETWORKDAYS($J$99,F108,'Festivos Colombia'!$A$3:$A$22),0) -> 0 | I108: =NETWORKDAYS($J$99,F108,'Festivos Colombia'!$A$3:$A$22) -> 20 | J108: =H108 -> 0
A109: =G109 -> Cancelado | B109: =IF(I109<=-1,1,IF(I109<=5,2,IF(I109<=15,3,IF(H109<=60,4)))) -> 4 | D109: AFC OER electronico | E109: =7600000+4000000 -> 11600000 | F109: 46111 | G109: Cancelado | H109: =IF(OR(G109="Sin pagar",G109="Pagar"),NETWORKDAYS($J$99,F109,'Festivos Colombia'!$A$3:$A$22),0) -> 0 | I109: =NETWORKDAYS($J$99,F109,'Festivos Colombia'!$A$3:$A$22) -> 20 | J109: =H109 -> 0
A110: =G110 -> Cancelado | B110: =IF(I110<=-1,1,IF(I110<=5,2,IF(I110<=15,3,IF(H110<=60,4)))) -> 4 | D110: AFC Edward Forero electronico | E110: 2155460 | F110: 46111 | G110: Cancelado | H110: =IF(OR(G110="Sin pagar",G110="Pagar"),NETWORKDAYS($J$99,F110,'Festivos Colombia'!$A$3:$A$22),0) -> 0 | I110: =NETWORKDAYS($J$99,F110,'Festivos Colombia'!$A$3:$A$22) -> 20 | J110: =H110 -> 0
D111: IMPUESTOS | E111: =SUBTOTAL(9,E112:E114) -> 272937500 | J111: =H111 -> 0
A112: =G112 -> Cancelado | B112: =IF(I112<=-1,1,IF(I112<=5,2,IF(I112<=15,3,IF(H112<=60,4)))) -> 3 | D112: IVA 1er Bimestre | E112: 62607000 | F112: 46097 | G112: Cancelado | H112: =IF(OR(G112="Sin pagar",G112="Pagar"),NETWORKDAYS($J$99,F112,'Festivos Colombia'!$A$3:$A$22),0) -> 0 | I112: =NETWORKDAYS($J$99,F112,'Festivos Colombia'!$A$3:$A$22) -> 11 | J112: =H112 -> 0
A113: =G113 -> Cancelado | B113: =IF(I113<=-1,1,IF(I113<=5,2,IF(I113<=15,3,IF(H113<=60,4)))) -> 3 | D113: RETENCIÓN EN LA FUENTE | E113: 209193000 | F113: 46097 | G113: Cancelado | H113: =IF(OR(G113="Sin pagar",G113="Pagar"),NETWORKDAYS($J$99,F113,'Festivos Colombia'!$A$3:$A$22),0) -> 0 | I113: =NETWORKDAYS($J$99,F113,'Festivos Colombia'!$A$3:$A$22) -> 11 | J113: =H113 -> 0
D114: RTE ICA ( cada dos meses) | E114: =910000*1.25 -> 1137500 | F114: 46097 | G114: Cancelado | H114: =IF(OR(G114="Sin pagar",G114="Pagar"),NETWORKDAYS($J$99,F114,'Festivos Colombia'!$A$3:$A$22),0) -> 0 | I114: =NETWORKDAYS($J$99,F114,'Festivos Colombia'!$A$3:$A$22) -> 11 | J114: =H114 -> 0
D115: ARRIENDO, INTERNET, TELEFONIA Y GASTOS DE OFICINA | E115: =SUBTOTAL(9,E116:E136) -> 10129378 | J115: =H115 -> 0
A116: =G116 -> Cancelado | B116: =IF(I116<=-1,1,IF(I116<=5,2,IF(I116<=15,3,IF(H116<=60,4)))) -> 2 | C116: FE-56934 | D116: BUK colombia SAS-Sucricpión Febrero 2026 Bukplay E-learning - Enero 2026 | 53 empleados | E116: =1244113.7 -> 1244113.7 | F116: 46087 | G116: Cancelado | H116: =IF(OR(G116="Sin pagar",G116="Pagar"),NETWORKDAYS($J$99,F116,'Festivos Colombia'!$A$3:$A$22),0) -> 0 | I116: =NETWORKDAYS($J$99,F116,'Festivos Colombia'!$A$3:$A$22) -> 5 | J116: =H116 -> 0
A117: =G117 -> Cancelado | B117: =IF(I117<=-1,1,IF(I117<=5,2,IF(I117<=15,3,IF(H117<=60,4)))) -> 2 | C117: 580831430799 | D117: Movistar Office 365 | E117: =368688 -> 368688 | F117: 46087 | G117: Cancelado | H117: =IF(OR(G117="Sin pagar",G117="Pagar"),NETWORKDAYS($J$99,F117,'Festivos Colombia'!$A$3:$A$22),0) -> 0 | I117: =NETWORKDAYS($J$99,F117,'Festivos Colombia'!$A$3:$A$22) -> 5 | J117: =H117 -> 0
A118: =G118 -> Cancelado | B118: =IF(I118<=-1,1,IF(I118<=5,2,IF(I118<=15,3,IF(H118<=60,4)))) -> 2 | C118: FEWP-6700 | D118: WORKPLACE SOLUTIONS GROUP SAS (SPACIO) | E118: =358066.76 -> 358066.76 | F118: 46087 | G118: Cancelado | H118: =IF(OR(G118="Sin pagar",G118="Pagar"),NETWORKDAYS($J$99,F118,'Festivos Colombia'!$A$3:$A$22),0) -> 0 | I118: =NETWORKDAYS($J$99,F118,'Festivos Colombia'!$A$3:$A$22) -> 5 | J118: =H118 -> 0
A119: =G119 -> Cancelado | B119: =IF(I119<=-1,1,IF(I119<=5,2,IF(I119<=15,3,IF(H119<=60,4)))) -> 3 | C119: 27768 | D119: Parking remofirst | E119: =926800 -> 926800 | F119: 46091 | G119: Cancelado | H119: =IF(OR(G119="Sin pagar",G119="Pagar"),NETWORKDAYS($J$99,F119,'Festivos Colombia'!$A$3:$A$22),0) -> 0 | I119: =NETWORKDAYS($J$99,F119,'Festivos Colombia'!$A$3:$A$22) -> 7 | J119: =H119 -> 0
A120: =G120 -> Cancelado | B120: =IF(I120<=-1,1,IF(I120<=5,2,IF(I120<=15,3,IF(H120<=60,4)))) -> 2 | C120: 36 | D120: Dario Mendez | E120: 1000000 | F120: 46087 | G120: Cancelado | H120: =IF(OR(G120="Sin pagar",G120="Pagar"),NETWORKDAYS($J$99,F120,'Festivos Colombia'!$A$3:$A$22),0) -> 0 | I120: =NETWORKDAYS($J$99,F120,'Festivos Colombia'!$A$3:$A$22) -> 5 | J120: =H120 -> 0
A121: =G121 -> Cancelado | B121: =IF(I121<=-1,1,IF(I121<=5,2,IF(I121<=15,3,IF(H121<=60,4)))) -> 3 | C121: FEWP-6722 | D121: WORKPLACE SOLUTIONS GROUP SAS (SPACIO) Alquiler sala de juntas | E121: 227700 | F121: 46094 | G121: Cancelado | H121: =IF(OR(G121="Sin pagar",G121="Pagar"),NETWORKDAYS($J$99,F121,'Festivos Colombia'!$A$3:$A$22),0) -> 0 | I121: =NETWORKDAYS($J$99,F121,'Festivos Colombia'!$A$3:$A$22) -> 10 | J121: =H121 -> 0
A122: =G122 -> Cancelado | B122: =IF(I122<=-1,1,IF(I122<=5,2,IF(I122<=15,3,IF(H122<=60,4)))) -> 3 | C122: FEWP-6726 | D122: WORKPLACE SOLUTIONS GROUP SAS (SPACIO) Alquiler sala de juntas | E122: 227700 | F122: 46094 | G122: Cancelado | H122: =IF(OR(G122="Sin pagar",G122="Pagar"),NETWORKDAYS($J$99,F122,'Festivos Colombia'!$A$3:$A$22),0) -> 0 | I122: =NETWORKDAYS($J$99,F122,'Festivos Colombia'!$A$3:$A$22) -> 10 | J122: =H122 -> 0
A123: =G123 -> Cancelado | B123: =IF(I123<=-1,1,IF(I123<=5,2,IF(I123<=15,3,IF(H123<=60,4)))) -> 3 | C123: FEWP-6740 | D123: WORKPLACE SOLUTIONS GROUP SAS (SPACIO) Alquiler sala de juntas 10 Personas | E123: 399119 | F123: 46101 | G123: Cancelado | H123: =IF(OR(G123="Sin pagar",G123="Pagar"),NETWORKDAYS($J$99,F123,'Festivos Colombia'!$A$3:$A$22),0) -> 0 | I123: =NETWORKDAYS($J$99,F123,'Festivos Colombia'!$A$3:$A$22) -> 15 | J123: =H123 -> 0
A124: =G124 -> Cancelado | B124: =IF(I124<=-1,1,IF(I124<=5,2,IF(I124<=15,3,IF(H124<=60,4)))) -> 3 | C124: 37 | D124: Dario Mendez | E124: 1100000 | F124: 46101 | G124: Cancelado | H124: =IF(OR(G124="Sin pagar",G124="Pagar"),NETWORKDAYS($J$99,F124,'Festivos Colombia'!$A$3:$A$22),0) -> 0 | I124: =NETWORKDAYS($J$99,F124,'Festivos Colombia'!$A$3:$A$22) -> 15 | J124: =H124 -> 0
A125: =G125 -> Cancelado | B125: =IF(I125<=-1,1,IF(I125<=5,2,IF(I125<=15,3,IF(H125<=60,4)))) -> 3 | C125: 64 | D125: Rafael Mier (arriendo Bodega para S&P) | E125: 180000 | F125: 46101 | G125: Cancelado | H125: =IF(OR(G125="Sin pagar",G125="Pagar"),NETWORKDAYS($J$99,F125,'Festivos Colombia'!$A$3:$A$22),0) -> 0 | I125: =NETWORKDAYS($J$99,F125,'Festivos Colombia'!$A$3:$A$22) -> 15 | J125: =H125 -> 0
...

Sheet ABRIL
E1: 42400
I2: 1
I3: 2
D4: BANCOS | E4: =SUBTOTAL(9,E5:E5) -> 7.7277487e+08 | I4: 3
D5: Bancos | E5: =MARZO!E294 -> 7.7277487e+08 | I5: 4
D6: CLIENTES | E6: =SUBTOTAL(9,E7:E36) -> 2.771425e+08
C7: Sin Pagar | D7: ACT&J Consultores Factura 6598 | E7: 2031584.6
C8: Sin Pagar | D8: AECID Factura # 6789 | E8: 34362713
C9: Sin Pagar | D9: AECID Factura # 5-262 | E9: 2104000
C10: Pagado | D10: Clarke Modet factura # 6790 | E10: 2804648.1
C11: Sin Pagar | D11: Compassion international factura # XXXX | E11: 6766084.2
C12: Sin Pagar | D12: Consorcio HL-Gisaico # 6785 | E12: =3646434.25*0 -> 0
C13: Sin Pagar | D13: Consorcio SK - HL 6745 | E13: 252331.2
C14: Sin Pagar | D14: Corporación punto azul factura # 6661 | E14: 2015276.2
C15: Sin Pagar | D15: Deel Facturas # 6728-6729-6730-6731-6732-6733-6734-6735-6736 ( Por monetizar) | E15: ='MONETIZACIONES PEND'!$R$14 -> 41243759
C16: Sin Pagar | D16: Deel Facturas # 6737-6738-6739-6740-6741 ( Por monetizar) | E16: ='MONETIZACIONES PEND'!$R$15 -> 21043637
C17: Sin Pagar | D17: Deel Facturas # 6325 ( Por monetizar) | E17: ='MONETIZACIONES PEND'!$R$16 -> 5300165
C18: Sin Pagar | D18: Dinterweb factura # 5646-5725-5805-5892-5974-6061 | E18: =7528323*0 -> 0
C19: Sin Pagar | D19: Distritech facturas # 6631 Llega por Panamá | E19: 987674.51
C20: Sin Pagar | D20: Dream Tyme resort | E20: 12075001
C21: Sin Pagar | D21: Ecohl facturas 6690-6691-6692-6723-6724-6780-6781-6782 | E21: =3182508.68*0 -> 0
C22: Sin Pagar | D22: Gilead Scense Colombia Factura # XXXX | E22: 920132.14
C23: Sin Pagar | D23: Global CS Colombia SAS -factura # 6778-5-272 | E23: 20244754
C24: Sin Pagar | D24: Global Projects service AG facturas factura 6597-6663-6694-6758-221-256 | E24: 24139258
C25: Sin Pagar | D25: Global Upside Factura # 6750 | E25: ='MONETIZACIONES PEND'!$R$12 -> 6825500
C26: Sin Pagar | D26: HL Gestiones factura # 6395-6572 | E26: =1719065*0 -> 0 | I26: 4
C27: Sin Pagar | D27: HL Ingenieros factura # 6678-6757 | E27: =667948.35*0 -> 0
C28: Sin Pagar | D28: Hl Infraestructura factura # 6507-6512-6513-6514-6519 | E28: =24527869*0 -> 0
C29: Sin Pagar | D29: Inversiones el Bosque factura # 6797 | E29: =2013039 -> 2013039
C30: Pagado | D30: Live Systems technology factura # 6626 | E30: =1264316.04 -> 1264316
C31: Sin Pagar | D31: Monica Londoño Factura 6573 | E31: =177905 -> 177905
C32: Sin Pagar | D32: Ortho Clinical Diagnostics # 6794 | E32: 1451213.8
C33: Sin Pagar | D33: Petrobras colombia Factura # 6752 | E33: 18093866
C34: Sin Pagar | D34: TPL Logistics factura # 6796 | E34: =2033960.42 -> 2033960.4
C35: Sin Pagar | D35: Safeguard World Inter Ltd Factura # 6575 a 6577 | E35: =SUM('MONETIZACIONES PEND'!$R$9:$R$11) -> 21070830
C36: Sin Pagar | D36: Solutions ingreso dinero de Panamá | E36: ='MONETIZACIONES PEND'!$R$13 -> 47920850
D37: EOR | E37: =SUBTOTAL(9,E38:E86) -> 2.8285125e+09 | F37: 1
C38: Sin Pagar | D38: Action Factura # XXXX | E38: 1570694.5
C39: Sin Pagar | D39: Action Factura # X-XXX | E39: 14278927
C40: Sin Pagar | D40: Bubble BPM Factura # 6815 | E40: ='MONETIZACIONES PEND'!$Q$18 -> 470071.35
C41: Sin Pagar | D41: Bubble BPM Factura # 5-273 | E41: ='MONETIZACIONES PEND'!$Q$19 -> 4273385.8
C42: Sin Pagar | D42: Bubble BPM Factura # XXXX | E42: 546032.49
C43: Sin Pagar | D43: Bubble BPM Factura # X-XXX | E43: 4963927.8
C44: Sin Pagar | D44: Edrington Factura # XXXX | E44: 2944619.7
C45: Sin Pagar | D45: Edrington Factura # X-XXX | E45: 53538586
C46: Sin Pagar | D46: EPDM Factura # XXXX | E46: 1221537.9
C47: Sin Pagar | D47: EPDM Factura # X-XXX | E47: 12215379
C48: Sin Pagar | D48: Equus Global Expansion, LLC Factura # XXXX | E48: 799725.7
C49: Sin Pagar | D49: Equus Global Expansion, LLC Factura # X-XXX | E49: 1997970.2
C50: Sin Pagar | D50: Europortage Factura # XXXX | E50: 4792287.1
C51: Sin Pagar | D51: Europortage Factura # X-XXX | E51: 75902156
C52: Sin Pagar | D52: Hemmebarsch GMBH & Co KG , factura # 6684 Marzo | E52: 717615.65
C53: Sin Pagar | D53: Hemmebarsch GMBH & Co KG , factura # 2-13 Marzo | E53: 7176043.8
... C86: Sin Pagar | D86: Root capital # FV-5-XXX | E86: 25408876
D87: TOTAL INGRESOS | E87: =SUBTOTAL(9,E4:E86) -> 3.8784299e+09 | G87: =SUM(G6:G86) -> 0
C90: CUENTAS X PAGAR MES | E90: ABRIL | F90: Fecha de Elaboración: | J90: 46113
C91: Factura | D91: PROVEEDOR | E91: VALOR | F91: Fecha vencimiento | G91: Estado | J91: KPI | K91: Objeto
D92: PAGOS ANTICIPADOS | E92: =SUBTOTAL(9,E93:E95) -> 17522648
A93: =G93 -> Sin Pagar | B93: =IF(I93<=-1,1,IF(I93<=5,2,IF(I93<=15,3,IF(H93<=60,4)))) -> 3 | D93: Anticipo nómina Action | E93: 4360000 | F93: 46126 | G93: Sin Pagar | H93: =IF(OR(G93="Sin pagar",G93="Pagar"),NETWORKDAYS($J$90,F93,'Festivos Colombia'!$A$3:$A$22),0) -> 8 | I93: =NETWORKDAYS($J$90,F93,'Festivos Colombia'!$A$3:$A$22) -> 8 | J93: =H93 -> 8
A94: =G94 -> Sin Pagar | B94: =IF(I94<=-1,1,IF(I94<=5,2,IF(I94<=15,3,IF(H94<=60,4)))) -> 3 | D94: Anticipo nómina Nazdar | E94: 9500000 | F94: 46126 | G94: Sin Pagar | H94: =IF(OR(G94="Sin pagar",G94="Pagar"),NETWORKDAYS($J$90,F94,'Festivos Colombia'!$A$3:$A$22),0) -> 8 | I94: =NETWORKDAYS($J$90,F94,'Festivos Colombia'!$A$3:$A$22) -> 8 | J94: =H94 -> 8
A95: =G95 -> Sin Pagar | B95: =IF(I95<=-1,1,IF(I95<=5,2,IF(I95<=15,3,IF(H95<=60,4)))) -> 4 | D95: Anticipo nómina Action | E95: 3662648 | F95: 46142 | G95: Sin Pagar | H95: =IF(OR(G95="Sin pagar",G95="Pagar"),NETWORKDAYS($J$90,F95,'Festivos Colombia'!$A$3:$A$22),0) -> 20 | I95: =NETWORKDAYS($J$90,F95,'Festivos Colombia'!$A$3:$A$22) -> 20 | J95: =H95 -> 20
D96: SEGURIDAD SOCIAL | E96: =SUBTOTAL(9,E97:E97) -> 530117800
A97: =G97 -> Sin Pagar | B97: =IF(I97<=-1,1,IF(I97<=5,2,IF(I97<=15,3,IF(H97<=60,4)))) -> 3 | C97: 176206200 | D97: Seguridad social | E97: 530117800 | F97: 46127 | G97: Sin Pagar | H97: =IF(OR(G97="Sin pagar",G97="Pagar"),NETWORKDAYS($J$90,F97,'Festivos Colombia'!$A$3:$A$22),0) -> 9 | I97: =NETWORKDAYS($J$90,F97,'Festivos Colombia'!$A$3:$A$22) -> 9 | J97: =H97 -> 9
D98: AFC´S | E98: =SUBTOTAL(9,E99:E101) -> 14755460
A99: =G99 -> Sin Pagar | B99: =IF(I99<=-1,1,IF(I99<=5,2,IF(I99<=15,3,IF(H99<=60,4)))) -> 4 | D99: AFC Dafuturo cheque | E99: 1000000 | F99: 46142 | G99: Sin Pagar | H99: =IF(OR(G99="Sin pagar",G99="Pagar"),NETWORKDAYS($J$90,F99,'Festivos Colombia'!$A$3:$A$22),0) -> 20 | I99: =NETWORKDAYS($J$90,F99,'Festivos Colombia'!$A$3:$A$22) -> 20 | J99: =H99 -> 20
A100: =G100 -> Sin Pagar | B100: =IF(I100<=-1,1,IF(I100<=5,2,IF(I100<=15,3,IF(H100<=60,4)))) -> 4 | D100: AFC OER electronico | E100: =7600000+4000000 -> 11600000 | F100: 46142 | G100: Sin Pagar | H100: =IF(OR(G100="Sin pagar",G100="Pagar"),NETWORKDAYS($J$90,F100,'Festivos Colombia'!$A$3:$A$22),0) -> 20 | I100: =NETWORKDAYS($J$90,F100,'Festivos Colombia'!$A$3:$A$22) -> 20 | J100: =H100 -> 20
A101: =G101 -> Sin Pagar | B101: =IF(I101<=-1,1,IF(I101<=5,2,IF(I101<=15,3,IF(H101<=60,4)))) -> 4 | D101: AFC Edward Forero electronico | E101: 2155460 | F101: 46142 | G101: Sin Pagar | H101: =IF(OR(G101="Sin pagar",G101="Pagar"),NETWORKDAYS($J$90,F101,'Festivos Colombia'!$A$3:$A$22),0) -> 20 | I101: =NETWORKDAYS($J$90,F101,'Festivos Colombia'!$A$3:$A$22) -> 20 | J101: =H101 -> 20
D102: IMPUESTOS | E102: =SUBTOTAL(9,E103:E103) -> 239676790 | J102: =H102 -> 0
A103: =G103 -> Sin Pagar | B103: =IF(I103<=-1,1,IF(I103<=5,2,IF(I103<=15,3,IF(H103<=60,4)))) -> 3 | D103: RETENCIÓN EN LA FUENTE | E103: 239676790 | F103: 46132 | G103: Sin Pagar | H103: =IF(OR(G103="Sin pagar",G103="Pagar"),NETWORKDAYS($J$90,F103,'Festivos Colombia'!$A$3:$A$22),0) -> 12 | I103: =NETWORKDAYS($J$90,F103,'Festivos Colombia'!$A$3:$A$22) -> 12 | J103: =H103 -> 12
D104: ARRIENDO, INTERNET, TELEFONIA Y GASTOS DE OFICINA | E104: =SUBTOTAL(9,E105:E115) -> 5605155.4 | J104: =H104 -> 0
A105: =G105 -> Sin Pagar | B105: =IF(I105<=-1,1,IF(I105<=5,2,IF(I105<=15,3,IF(H105<=60,4)))) -> 3 | C105: FE-56934 | D105: BUK colombia SAS-Sucricpión Febrero 2026 Bukplay E-learning - Enero 2026 | 53 empleados | E105: =1244113.7 -> 1244113.7 | F105: 46122 | G105: Sin Pagar | H105: =IF(OR(G105="Sin pagar",G105="Pagar"),NETWORKDAYS($J$90,F105,'Festivos Colombia'!$A$3:$A$22),0) -> 6 | I105: =NETWORKDAYS($J$90,F105,'Festivos Colombia'!$A$3:$A$22) -> 6 | J105: =H105 -> 6 | K105: Sin radicar
A106: =G106 -> Sin Pagar | B106: =IF(I106<=-1,1,IF(I106<=5,2,IF(I106<=15,3,IF(H106<=60,4)))) -> 3 | C106: FEWP-6810 | D106: WORKPLACE SOLUTIONS GROUP SAS (SPACIO) | E106: =358066.76 -> 358066.76 | F106: 46122 | G106: Sin Pagar | H106: =IF(OR(G106="Sin pagar",G106="Pagar"),NETWORKDAYS($J$90,F106,'Festivos Colombia'!$A$3:$A$22),0) -> 6 | I106: =NETWORKDAYS($J$90,F106,'Festivos Colombia'!$A$3:$A$22) -> 6 | J106: =H106 -> 6
A107: =G107 -> Sin Pagar | B107: =IF(I107<=-1,1,IF(I107<=5,2,IF(I107<=15,3,IF(H107<=60,4)))) -> 3 | C107: 28184 | D107: Parking remofirst | E107: =634400 -> 634400 | F107: 46122 | G107: Sin Pagar | H107: =IF(OR(G107="Sin pagar",G107="Pagar"),NETWORKDAYS($J$90,F107,'Festivos Colombia'!$A$3:$A$22),0) -> 6 | I107: =NETWORKDAYS($J$90,F107,'Festivos Colombia'!$A$3:$A$22) -> 6 | J107: =H107 -> 6
A108: =G108 -> Sin Pagar | B108: =IF(I108<=-1,1,IF(I108<=5,2,IF(I108<=15,3,IF(H108<=60,4)))) -> 3 | C108: 580831444002 | D108: Movistar Office 365 | E108: =362715 -> 362715 | F108: 46123 | G108: Sin Pagar | H108: =IF(OR(G108="Sin pagar",G108="Pagar"),NETWORKDAYS($J$90,F108,'Festivos Colombia'!$A$3:$A$22),0) -> 6 | I108: =NETWORKDAYS($J$90,F108,'Festivos Colombia'!$A$3:$A$22) -> 6 | J108: =H108 -> 6
A109: =G109 -> Sin Pagar | B109: =IF(I109<=-1,1,IF(I109<=5,2,IF(I109<=15,3,IF(H109<=60,4)))) -> 3 | C109: BEV24903802 | D109: Movistar Office 365- Linea nueva de SG | E109: =110900 -> 110900 | F109: 46129 | G109: Sin Pagar | H109: =IF(OR(G109="Sin pagar",G109="Pagar"),NETWORKDAYS($J$90,F109,'Festivos Colombia'!$A$3:$A$22),0) -> 11 | I109: =NETWORKDAYS($J$90,F109,'Festivos Colombia'!$A$3:$A$22) -> 11 | J109: =H109 -> 11
A110: =G110 -> Sin Pagar | B110: =IF(I110<=-1,1,IF(I110<=5,2,IF(I110<=15,3,IF(H110<=60,4)))) -> 3 | C110: 64 | D110: Rafael Mier (arriendo Bodega para S&P) | E110: 180000 | F110: 46129 | G110: Sin Pagar | H110: =IF(OR(G110="Sin pagar",G110="Pagar"),NETWORKDAYS($J$90,F110,'Festivos Colombia'!$A$3:$A$22),0) -> 11 | I110: =NETWORKDAYS($J$90,F110,'Festivos Colombia'!$A$3:$A$22) -> 11 | J110: =H110 -> 11 | K110: Sin radicar
A111: =G111 -> Sin Pagar | B111: =IF(I111<=-1,1,IF(I111<=5,2,IF(I111<=15,3,IF(H111<=60,4)))) -> 3 | C111: 003 -292523658 | D111: Claro Office 365 | E111: 1504416 | F111: 46129 | G111: Sin Pagar | H111: =IF(OR(G111="Sin pagar",G111="Pagar"),NETWORKDAYS($J$90,F111,'Festivos Colombia'!$A$3:$A$22),0) -> 11 | I111: =NETWORKDAYS($J$90,F111,'Festivos Colombia'!$A$3:$A$22) -> 11 | J111: =H111 -> 11 | K111: Sin radicar
A112: =G112 -> Sin Pagar | B112: =IF(I112<=-1,1,IF(I112<=5,2,IF(I112<=15,3,IF(H112<=60,4)))) -> 3 | C112: 6038761603 | D112: Claro-Telefonia | E112: 810543.9 | F112: 46129 | G112: Sin Pagar | H112: =IF(OR(G112="Sin pagar",G112="Pagar"),NETWORKDAYS($J$90,F112,'Festivos Colombia'!$A$3:$A$22),0) -> 11 | I112: =NETWORKDAYS($J$90,F112,'Festivos Colombia'!$A$3:$A$22) -> 11 | J112: =H112 -> 11 | K112: Sin radicar
A113: =G113 -> Sin Pagar | B113: =IF(I113<=-1,1,IF(I113<=5,2,IF(I113<=15,3,IF(H113<=60,4)))) -> 4 | C113: 2 | D113: David Alejandro Aguilar Suarez - Custodia de computadores | E113: 300000 | F113: 46142 | G113: Sin Pagar | H113: =IF(OR(G113="Sin pagar",G113="Pagar"),NETWORKDAYS($J$90,F113,'Festivos Colombia'!$A$3:$A$22),0) -> 20 | I113: =NETWORKDAYS($J$90,F113,'Festivos Colombia'!$A$3:$A$22) -> 20 | J113: =H113 -> 20 | K113: Sin radicar
A114: =G114 -> Sin Pagar | B114: =IF(I114<=-1,1,IF(I114<=5,2,IF(I114<=15,3,IF(H114<=60,4)))) -> 4 | C114: 193 | D114: Caja menor | E114: 100000 | F114: 46142 | G114: Sin Pagar | H114: =IF(OR(G114="Sin pagar",G114="Pagar"),NETWORKDAYS($J$90,F114,'Festivos Colombia'!$A$3:$A$22),0) -> 20 | I114: =NETWORKDAYS($J$90,F114,'Festivos Colombia'!$A$3:$A$22) -> 20 | J114: =H114 -> 20 | K114: Sin radicar
A115: =G115 -> Cancelado | B115: =IF(I115<=-1,1,IF(I115<=5,2,IF(I115<=15,3,IF(H115<=60,4)))) -> 2 | C115: 014F18743905 | D115: Seguros mundial -Póliza cumplimiento 100016141 Anexo 3. Certificado 130090786 | E115: =252011.48*0 -> 0 | F115: 46118 | G115: Cancelado | H115: =IF(OR(G115="Sin pagar",G115="Pagar"),NETWORKDAYS($J$90,F115,'Festivos Colombia'!$A$3:$A$22),0) -> 0 | I115: =NETWORKDAYS($J$90,F115,'Festivos Colombia'!$A$3:$A$22) -> 2 | J115: =H115 -> 0
D116: PLANES COMPLEMENTARIOS Y PREPAGADAS | E116: =SUBTOTAL(9,E117:E118) -> 1868879
A117: =G117 -> Sin Pagar | B117: =IF(I117<=-1,1,IF(I117<=5,2,IF(I117<=15,3,IF(H117<=60,4)))) -> 4 | C117: SD01 17795173 | D117: Plan medicina prepagada Eduard Forero | E117: 1064823 | F117: 46139 | G117: Sin Pagar | H117: =IF(OR(G117="Sin pagar",G117="Pagar"),NETWORKDAYS($J$90,F117,'Festivos Colombia'!$A$3:$A$22),0) -> 17 | I117: =NETWORKDAYS($J$90,F117,'Festivos Colombia'!$A$3:$A$22) -> 17 | J117: =H117 -> 17 | K117: Sin radicar
A118: =G118 -> Sin Pagar | B118: =IF(I118<=-1,1,IF(I118<=5,2,IF(I118<=15,3,IF(H118<=60,4)))) -> 4 | C118: 219912177994 | D118: Plan complementario Ricardo Arambulo | E118: =804056 -> 804056 | F118: 46139 | G118: Sin Pagar | H118: =IF(OR(G118="Sin pagar",G118="Pagar"),NETWORKDAYS($J$90,F118,'Festivos Colombia'!$A$3:$A$22),0) -> 17 | I118: =NETWORKDAYS($J$90,F118,'Festivos Colombia'!$A$3:$A$22) -> 17 | J118: =H118 -> 17 | K118: Sin radicar
D119: PÓLIZAS Y SEGUROS | E119: =SUBTOTAL(9,E120:E122) -> 11348818
A120: =G120 -> Sin Pagar | B120: =IF(I120<=-1,1,IF(I120<=5,2,IF(I120<=15,3,IF(H120<=60,4)))) -> 3 | C120: 20833458887 | D120: Poliza Suramericana Póliza # 083004098664 | E120: 726513 | F120: 46122 | G120: Sin Pagar | H120: =IF(OR(G120="Sin pagar",G120="Pagar"),NETWORKDAYS($J$90,F120,'Festivos Colombia'!$A$3:$A$22),0) -> 6 | I120: =NETWORKDAYS($J$90,F120,'Festivos Colombia'!$A$3:$A$22) -> 6 | J120: =H120 -> 6
A121: =G121 -> Sin Pagar | B121: =IF(I121<=-1,1,IF(I121<=5,2,IF(I121<=15,3,IF(H121<=60,4)))) -> 4 | C121: 21341642 | D121: Poliza Suramericana Póliza # 083004098664 | E121: 726513 | F121: 46142 | G121: Sin Pagar | H121: =IF(OR(G121="Sin pagar",G121="Pagar"),NETWORKDAYS($J$90,F121,'Festivos Colombia'!$A$3:$A$22),0) -> 20 | I121: =NETWORKDAYS($J$90,F121,'Festivos Colombia'!$A$3:$A$22) -> 20 | J121: =H121 -> 20
A122: =G122 -> Sin Pagar | B122: =IF(I122<=-1,1,IF(I122<=5,2,IF(I122<=15,3,IF(H122<=60,4)))) -> 4 | C122: 14126873 | D122: Poliza Suramericana Póliza # 091000808492 | E122: =9895792 -> 9895792 | F122: 46142 | G122: Sin Pagar | H122: =IF(OR(G122="Sin pagar",G122="Pagar"),NETWORKDAYS($J$90,F122,'Festivos Colombia'!$A$3:$A$22),0) -> 20 | I122: =NETWORKDAYS($J$90,F122,'Festivos Colombia'!$A$3:$A$22) -> 20 | J122: =H122 -> 20
D123: SERVICIOS DE MENSAJERÍA | E123: =SUBTOTAL(9,E124:E129) -> 670000
A124: =G124 -> Sin Pagar | B124: =IF(I124<=-1,1,IF(I124<=5,2,IF(I124<=15,3,IF(H124<=60,4)))) -> 3 | C124: 23 | D124: Mundo express | E124: 89000 | F124: 46122 | G124: Sin Pagar | H124: =IF(OR(G124="Sin pagar",G124="Pagar"),NETWORKDAYS($J$90,F124,'Festivos Colombia'!$A$3:$A$22),0) -> 6 | I124: =NETWORKDAYS($J$90,F124,'Festivos Colombia'!$A$3:$A$22) -> 6 | J124: =H124 -> 6
A125: =G125 -> Sin Pagar | B125: =IF(I125<=-1,1,IF(I125<=5,2,IF(I125<=15,3,IF(H125<=60,4)))) -> 3 | C125: 66 | D125: Yecid Martin | E125: 39000 | F125: 46122 | G125: Sin Pagar | H125: =IF(OR(G125="Sin pagar",G125="Pagar"),NETWORKDAYS($J$90,F125,'Festivos Colombia'!$A$3:$A$22),0) -> 6 | I125: =NETWORKDAYS($J$90,F125,'Festivos Colombia'!$A$3:$A$22) -> 6 | J125: =H125 -> 6 | K125: Sin radicar
A126: =G126 -> Sin Pagar | B126: =IF(I126<=-1,1,IF(I126<=5,2,IF(I126<=15,3,IF(H126<=60,4)))) -> 3 | C126: 67 | D126: Yecid Martin | E126: 91000 | F126: 46129 | G126: Sin Pagar | H126: =IF(OR(G126="Sin pagar",G126="Pagar"),NETWORKDAYS($J$90,F126,'Festivos Colombia'!$A$3:$A$22),0) -> 11 | I126: =NETWORKDAYS($J$90,F126,'Festivos Colombia'!$A$3:$A$22) -> 11 | J126: =H126 -> 11 | K126: Sin radicar
A127: =G127 -> Sin Pagar | B127: =IF(I127<=-1,1,IF(I127<=5,2,IF(I127<=15,3,IF(H127<=60,4)))) -> 3 | C127: 24 | D127: Mundo express | E127: 81000 | F127: 46129 | G127: Sin Pagar | H127: =IF(OR(G127="Sin pagar",G127="Pagar"),NETWORKDAYS($J$90,F127,'Festivos Colombia'!$A$3:$A$22),0) -> 11 | I127: =NETWORKDAYS($J$90,F127,'Festivos Colombia'!$A$3:$A$22) -> 11 | J127: =H127 -> 11 | K127: Sin radicar
A128: =G128 -> Sin Pagar | B128: =IF(I128<=-1,1,IF(I128<=5,2,IF(I128<=15,3,IF(H128<=60,4)))) -> 4 | C128: 68 | D128: Yecid Martin | E128: 69000 | F128: 46136 | G128: Sin Pagar | H128: =IF(OR(G128="Sin pagar",G128="Pagar"),NETWORKDAYS($J$90,F128,'Festivos Colombia'!$A$3:$A$22),0) -> 16 | I128: =NETWORKDAYS($J$90,F128,'Festivos Colombia'!$A$3:$A$22) -> 16 | J128: =H128 -> 16 | K128: Sin radicar
A129: =G129 -> Sin Pagar | B129: =IF(I129<=-1,1,IF(I129<=5,2,IF(I129<=15,3,IF(H129<=60,4)))) -> 4 | C129: 69 | D129: Yecid Martin | E129: 301000 | F129: 46142 | G129: Sin Pagar | H129: =IF(OR(G129="Sin pagar",G129="Pagar"),NETWORKDAYS($J$90,F129,'Festivos Colombia'!$A$3:$A$22),0) -> 20 | I129: =NETWORKDAYS($J$90,F129,'Festivos Colombia'!$A$3:$A$22) -> 20 | J129: =H129 -> 20 | K129: Sin radicar
D130: REEMBOLSO SAIPEM | E130: =SUBTOTAL(9,E131:E131) -> 2500000
D131: Reembolso previsto | E131: 2500000 | F131: 46142 | G131: Sin Pagar | H131: =IF(OR(G131="Sin pagar",G131="Pagar"),NETWORKDAYS($J$90,F131,'Festivos Colombia'!$A$3:$A$22),0) -> 20 | I131: =NETWORKDAYS($J$90,F131,'Festivos Colombia'!$A$3:$A$22) -> 20 | J131: =H131 -> 20 | K131: Sin radicar
D132: EXAMENES MÉDICOS SAIPEM y OTROS | E132: =SUBTOTAL(9,E133:E133) -> 3800000
D133: Examenes Previsto - SAIPEM | E133: 3800000 | F133: 46142 | G133: Sin Pagar | H133: =IF(OR(G133="Sin pagar",G133="Pagar"),NETWORKDAYS($J$90,F133,'Festivos Colombia'!$A$3:$A$22),0) -> 20 | I133: =NETWORKDAYS($J$90,F133,'Festivos Colombia'!$A$3:$A$22) -> 20 | J133: =H133 -> 20 | K133: Sin radicar
D134: TIQUETES AÉREOS , HOTELES SAIPEM-AECID - ROOT CAPITAL | E134: =SUBTOTAL(9,E135:E136) -> 7000000
...

Sheet DISTRIBUCIÓN
H1: Sin Pagar | I1: Cancelado
B2: Distribución de dinero
B4: Semana | C4: Fecha Inicial | D4: Fecha Final | E4: Descripción | F4: Valor | H4: Sin pagar | I4: Cancelado | J4: Total
B5: 1 | C5: 46113 | D5: 46124 | E5: Pagos a Realizar | F5: =SUMIFS(ABRIL!$E$92:$E$1917,ABRIL!$F$92:$F$1917,">="&C5,ABRIL!$F$92:$F$1917,"<="&D5,ABRIL!$G$92:$G$1917,$H$1) -> 7941408.5 | G5: Proveedores
B6: 2 | C6: 46125 | D6: 46125 | E6: Pagos a Realizar | F6: =SUMIFS(ABRIL!$E$92:$E$1917,ABRIL!$F$92:$F$1917,">="&C6,ABRIL!$F$92:$F$1917,"<="&D6,ABRIL!$G$92:$G$1917,$H$1) -> 0 | G6: - | H6: =SUMIFS(ABRIL!$E$92:$E$1926,ABRIL!$F$92:$F$1926,">="&C5,ABRIL!$F$92:$F$1926,"<="&D13,ABRIL!$G$92:$G$1926,$H$1) -> 3.1346752e+09 | I6: =SUMIFS(ABRIL!$E$92:$E$1926,ABRIL!$F$92:$F$1926,">="&C5,ABRIL!$F$92:$F$1926,"<="&D13,ABRIL!$G$92:$G$1926,$I$1) -> 166600 | J6: =SUM(H6:I6) -> 3.1348418e+09 | L6: =J6-#REF! -> #REF!
B7: 3 | C7: 46126 | D7: 46126 | E7: Pagos a Realizar | F7: =SUMIFS(ABRIL!$E$92:$E$1917,ABRIL!$F$92:$F$1917,">="&C7,ABRIL!$F$92:$F$1917,"<="&D7,ABRIL!$G$92:$G$1917,$H$1) -> 15620964 | G7: Anticipo nómina Nazdar y Action
B8: 4 | C8: 46127 | D8: 46127 | E8: Pagos a Realizar | F8: =SUMIFS(ABRIL!$E$92:$E$1917,ABRIL!$F$92:$F$1917,">="&C8,ABRIL!$F$92:$F$1917,"<="&D8,ABRIL!$G$92:$G$1917,$H$1) -> 530117800 | G8: Seguridad social | I8: Comprobación | J8: =ABRIL!E203 -> 3.1348418e+09
B9: 5 | C9: 46128 | D9: 46128 | E9: Pagos a Realizar | F9: =SUMIFS(ABRIL!$E$92:$E$1917,ABRIL!$F$92:$F$1917,">="&C9,ABRIL!$F$92:$F$1917,"<="&D9,ABRIL!$G$92:$G$1917,$H$1) -> 21127878 | G9: TC Endrington
B10: 6 | C10: 46129 | D10: 46131 | E10: Pagos a Realizar | F10: =SUMIFS(ABRIL!$E$92:$E$1917,ABRIL!$F$92:$F$1917,">="&C10,ABRIL!$F$92:$F$1917,"<="&D10,ABRIL!$G$92:$G$1917,$H$1) -> 85525370 | G10: Proveedores | J10: =J6-J8 -> 0
B11: 7 | C11: 46132 | D11: 46132 | E11: Pagos a Realizar | F11: =SUMIFS(ABRIL!$E$92:$E$1917,ABRIL!$F$92:$F$1917,">="&C11,ABRIL!$F$92:$F$1917,"<="&D11,ABRIL!$G$92:$G$1917,$H$1) -> 239676790 | G11: Rte FTE
B12: 8 | C12: 46133 | D12: 46138 | E12: Pagos a Realizar | F12: =SUMIFS(ABRIL!$E$92:$E$1917,ABRIL!$F$92:$F$1917,">="&C12,ABRIL!$F$92:$F$1917,"<="&D12,ABRIL!$G$92:$G$1917,$H$1) -> 43684726 | G12: Proveedores
B13: 9 | C13: 46139 | D13: 46142 | E13: Pagos a Realizar | F13: =SUMIFS(ABRIL!$E$92:$E$1917,ABRIL!$F$92:$F$1917,">="&C13,ABRIL!$F$92:$F$1917,"<="&D13,ABRIL!$G$92:$G$1917,$H$1) -> 2.1909803e+09 | G13: Nómina-Pagos a tercero-Proveedores
B14: TOTAL | F14: =SUM(F5:F13) -> 3.1346752e+09
E16: Escenario 1
E17: Gastos y costos Periodo 01 al 26 abril | F17: =SUM($F$5:$F$12) -> 9.4369494e+08
E18: 4 X mil | F18: =($F$17*4)/1000 -> 3774779.7
E19: Total | F19: =SUM(F17:F18) -> 9.4746972e+08
E21: Bancos | F21: =ABRIL!$E$221 -> 7.7365012e+08
E22: Bubble Do Brasil | F22: ='MONETIZACIONES PEND'!$Q$18+'MONETIZACIONES PEND'!$Q$19 -> 4743457.2
E23: Action AD | F23: 12600000
E24: AECID | F24: =ABRIL!$E$8+ABRIL!$E$9 -> 36466713
E25: Global Colombia | F25: =ABRIL!E23 -> 20244754
E26: Proveedores Nacionales | F26: =ABRIL!$E$7+ABRIL!$E$10+ABRIL!$E$29+ABRIL!$E$33+ABRIL!$E$34 -> 26977098 | G26: 0
E27: Facturas por monetizar Deel | F27: =ABRIL!$E$15+ABRIL!$E$16+ABRIL!$E$17 -> 67587561
E28: Facturas por monetizar Safeguard | F28: =ABRIL!$E$35+ABRIL!$E$36 -> 68991680
E29: Sobregiro | F29: 0
E30: Total | F30: =SUM(F21:F29) -> 1.0112614e+09
E31: Saldo | F31: =F30-$F$19 -> 63791669
E39: FORECAST MAYO 2026 | H39: FORECAST JUNIO 2026
E41: INGRESO | F41: =SUBTOTAL(9,F42:F50) -> 1.0164382e+09 | H41: INGRESO | I41: =SUBTOTAL(9,I42:I50) -> 1.314082e+09
E42: Bancos Valor previsto | F42: =ABRIL!$E$205 -> 7.4358807e+08 | H42: Bancos Valor previsto | I42: =F111 -> 1.1428106e+09
E43: Safeguard Back office 360 | F43: 63005792 | G43: 1 | H43: Safeguard Back office 360 | I43: 35000000 | J43: 1
E44: Action XXXX | F44: 13000000 | H44: Deel | I44: =15303.2*3650 -> 55856680
E45: Clientes nacionales Previsto -Global Project | F45: 52000000 | H45: Action XXXX | I45: 12500000
E46: Global CS Colombia | F46: 18500000 | H46: Clientes nacionales Previsto -Global Project | I46: 45000000
E47: Deel | F47: =18542.14* 3703.69 -> 68674338 | H47: Grupo HL | I47: 0
E48: Grupo HL | F48: 55000000 | H48: Global CS Colombia | I48: 20244754
E49: Intereses PM | F49: =2670000 -> 2670000 | H49: Intereses PM | I49: =2670000 -> 2670000
E50: Sobregiro | F50: 0 | H50: Sobregiro | I50: 0
E51: PAGOS DEL 1 AL 24 MAYO | F51: =SUM(F52:F82) -> 1.0112007e+09 | H51: PAGOS DEL 1 AL 25 Junio | I51: =SUM(I52:I79) -> 9.6160339e+08
E52: Anticipo nómina Action-primer anticipo | F52: 4360000 | H52: Anticipo nómina Action-primer anticipo | I52: 4360000
E53: Anticipo nómina Nazdar | F53: =9500000 -> 9500000 | H53: Anticipo nómina Nazdar | I53: =9500000 -> 9500000
E54: Plan complementario compensar | F54: 627000 | H54: Plan complementario compensar | I54: 627000
E55: Seguridad social | F55: =530117800*1.05 -> 556623690 | H55: Seguridad social | I55: =556623690*1.03 -> 5.733224e+08
E56: Iva 2do bimestre | F56: 68379580 | H56: RETENCIÓN EN LA FUENTE | I56: =302875920*1.03 -> 3.119622e+08
E57: RETENCIÓN EN LA FUENTE | F57: =252396600*1.2 -> 302875920 | H57: Retención de IVA | I57: =225000*1.03 -> 231750
E58: Retención de IVA | F58: =225000*1.2 -> 270000 | H58: Movistar 365 | I58: 993174
E59: RTE ICA bimestral | F59: =1137500*1.2 -> 1365000 | H59: Poliza Suramericana Póliza # 091000808492 | I59: 7293422
E60: Renta anual | F60: 0 | H60: Poliza Suramericana Póliza # 083004098664 | I60: 437488
E61: Movistar 365 | F61: 993174 | H61: Servicio de mensajería | I61: 500000
E62: Poliza Suramericana Póliza # 091000808492 | F62: 7293422 | H62: WORKPLACE SOLUTIONS GROUP SAS (SPACIO) | I62: =313593.5*1.052 -> 329900.36
E63: Poliza Suramericana Póliza # 083004098664 | F63: 437488 | H63: TC Bancolombia S&P | I63: 4500000
E64: Servicio de mensajería | F64: 500000 | H64: TC Bancolombia-Ramon Esteban Cardona Salazar | I64: 18000000
E65: WORKPLACE SOLUTIONS GROUP SAS (SPACIO) | F65: =313593.5*1.052 -> 329900.36 | H65: Anticipo nómina Action-Segundo anticipo | I65: 4853442
E66: TC Bancolombia S&P | F66: 4500000 | H66: Rafael Mier | I66: 180000
E67: TC Bancolombia-Ramon Esteban Cardona Salazar | F67: 18000000 | H67: Plan complementario Suramericana | I67: 752141
E68: Anticipo nómina Action-Segundo anticipo | F68: 4853442 | H68: Reembolsos Saipem | I68: 3000000
E69: Rafael Mier | F69: 180000 | H69: Exámenes médicos Saipem | I69: 3800000
E70: Plan complementario Suramericana | F70: 804056 | H70: Tiquetes y hoteles Saipem | I70: 3500000
E71: Reembolsos Saipem | F71: 3000000 | H71: Yoana Forero Servicios Costa Rica | I71: 774025
E72: Exámenes médicos Saipem | F72: 3800000 | H72: Cuentas de cobro Eduard Forero | I72: 2980000
E73: Tiquetes y hoteles Saipem | F73: 3500000 | H73: Cuentas de cobro William Romero | I73: 450000
E74: Yoana Forero Servicios Costa Rica | F74: 774025 | H74: Analia Lorena Di Nicola | I74: 475363
E75: Cuentas de cobro Eduard Forero | F75: 2980000 | H75: Emasoc | I75: 1500000
E76: Cuentas de cobro William Romero | F76: 800000 | H76: Praxedes nómina electrónica | I76: 450000
E77: Analia Lorena Di Nicola | F77: 475363 | H77: Praxedes | I77: 3000000
E78: Emasoc | F78: 1500000 | H78: Imprevisto | I78: 0
E79: Praxedes nómina electrónica | F79: 450000 | H79: 4 X mil transacciones | I79: =J79 -> 3831089.2 | J79: =(SUM(I52:I78)*4/1000) -> 3831089.2
E80: Praxedes | F80: 3000000 | H80: Diferencia | I80: =I41-I51 -> 3.5247864e+08
E81: Imprevisto | F81: 5000000
E82: 4 X mil transacciones | F82: =G82 -> 4028688.2 | G82: =(SUM(F52:F81)*4/1000) -> 4028688.2 | H82: Ingreso previsto por EOR | I82: 3320000000
E83: Diferencia | F83: =F41-F51 -> 5237450 | H83: Total | I83: =SUM(I80:I82) -> 3.6724786e+09
E85: Ingreso previsto por EOR | F85: 3200000000 | H85: PAGOS DEL 26 AL 30 JUNIO | I85: =SUM(I86:I106) -> 2.5581607e+09
E86: Total | F86: =SUM(F83:F85) -> 3.2052374e+09 | H86: AFC OE | I86: 16800500
H87: AFC Edward Forero | I87: 2199500
E88: PAGOS DEL 25 AL 31 MAYO | F88: =SUM(F89:F110) -> 2.0624269e+09 | H88: Reembolso caja menor | I88: 300000
D89: 1 | E89: AFC OE | F89: 16800500 | H89: Nixcom | I89: =1276775*1.06 -> 1353381.5
E90: AFC Edward Forero | F90: 2199500 | H90: Carvajal | I90: 75000
E91: Reembolso caja menor | F91: 300000 | H91: Movistar Telefonía | I91: 1002252
E92: Nixcom | F92: =1276775*1.06 -> 1353381.5 | H92: ACT&J Consultores S&P | I92: =3178793*1.06 -> 3369520.6
E93: Carvajal | F93: 75000 | H93: ACT&J Consultores Global | I93: =3484500*1.06 -> 3693570
E94: Movistar Telefonía | F94: 1002252 | H94: Libranza Compensar | I94: 1241772
E95: ACT&J Consultores S&P | F95: 4065250 | H95: Nómina OE | I95: =1731900000*1.29 -> 2234151000
E96: ACT&J Consultores Global | F96: 3665694 | H96: Nomina S&P | I96: =172530460*1.29 -> 2.2256429e+08
E97: Libranza Compensar | F97: 1241772 | H97: People Pass bienestar, medios de transporte y alimentación | I97: 12097393
E98: Nómina OE | F98: 1731900000 | H98: Embargo Fabian Morales | I98: 1009880
E99: Nomina S&P | F99: 172530460 | H99: Reembolsos Remotefisrt | I99: 10000000
E100: People Pass bienestar, medios de transporte y alimentación | F100: 12097393 | H100: Reembolsos Insider | I100: 7000000
E101: Embargo Fabian Morales | F101: 1112000 | H101: Pedro Pablo Oviedo | I101: 1190808
E102: Reembolsos Remotefisrt | F102: 25000000 | H102: Tiquetes Saipem | I102: 1600000
E103: Reembolsos Insider | F103: 15000000 | H103: Novasoft | I103: 13000000
E104: Pedro Pablo Oviedo | F104: 1190808 | H104: Mensajería | I104: 320000
E105: Tiquetes Saipem | F105: 1600000 | H105: Imprevistos | I105: 15000000
E106: Novasoft | F106: 13000000 | H106: Costos Financieros | I106: =J106 -> 10191875 | J106: =(SUM(I86:I105)*4/1000) -> 10191875
E107: Mensajería | F107: 320000 | H107: DIFERENCIA | I107: =I83-I85 -> 1.1143179e+09
E108: Imprevistos | F108: 5000000
E109: Devolucion de anticipo edrington | F109: 44756000
E110: Costos Financieros | F110: =G110 -> 8216840 | G110: =(SUM(F89:F109)*4/1000) -> 8216840
E111: DIFERENCIA | F111: =F86-F88 -> 1.1428106e+09

Sheet MONETIZACIONES PEND
O1: 0
B2: ID | C2: Client | D2: Invoice | E2: Incoming resources | F2: Maximum Date for Monetization | G2: Día | H2: Mes | I2: Días | J2: Progress | K2: Invoiced | L2: Received | M2: Banking taxes | N2: TRM Invoice Cops | O2: TRM Bank (Average) Cops | P2: Difference in exchange rates | Q2: invoicing in COPS | R2: negotiated COPS | S2: difference | T2: KPI | U2: Color KPI
B3: 1 | C3: Safeguard World Inter Ltd | D3: FV-4-6246 | E3: 46085 | F3: 46145 | G3: =(TEXT(F3,"ddd")) -> dom | H3: =(TEXT(F3,"mmm")) -> may | I3: =F3-E3 -> 60 | J3: =IFERROR(IF(TODAY()>=E3,(TODAY()-E3)/I3,0),0) -> 0.6 | K3: 600 | L3: 599.18805 | M3: =K3-L3 -> 0.81194602 | N3: 4019.9 | Q3: =K3*N3 -> 2411940 | R3: =L3*O3 -> 0 | S3: =R3-Q3 -> -2411940 | T3: =IF(R3<= Q3,"No Monetizar","Monetizar") -> No Monetizar
B4: 2 | C4: Safeguard World Inter Ltd | D4: FV-4-6248 | E4: 46085 | F4: 46145 | G4: =(TEXT(F4,"ddd")) -> dom | H4: =(TEXT(F4,"mmm")) -> may | I4: =F4-E4 -> 60 | J4: =IFERROR(IF(TODAY()>=E4,(TODAY()-E4)/I4,0),0) -> 0.6 | K4: 3380 | L4: 3375.426 | M4: =K4-L4 -> 4.5739626 | N4: 4019.09 | Q4: =K4*N4 -> 13584524 | R4: =L4*O4 -> 0 | S4: =R4-Q4 -> -13584524 | T4: =IF(R4<= Q4,"No Monetizar","Monetizar") -> No Monetizar
B5: 3 | C5: Safeguard World Inter Ltd | D5: FV-4-6312 | E5: 46085 | F5: 46145 | G5: =(TEXT(F5,"ddd")) -> dom | H5: =(TEXT(F5,"mmm")) -> may | I5: =F5-E5 -> 60 | J5: =IFERROR(IF(TODAY()>=E5,(TODAY()-E5)/I5,0),0) -> 0.6 | K5: 780 | L5: 778.94447 | M5: =K5-L5 -> 1.0555298 | N5: 3844.47 | Q5: =K5*N5 -> 2998686.6 | R5: =L5*O5 -> 0 | S5: =R5-Q5 -> -2998686.6 | T5: =IF(R5<= Q5,"No Monetizar","Monetizar") -> No Monetizar
B6: 4 | C6: Safeguard World Inter Ltd | D6: FV-4-6620 | E6: 46085 | F6: 46145 | G6: =(TEXT(F6,"ddd")) -> dom | H6: =(TEXT(F6,"mmm")) -> may | I6: =F6-E6 -> 60 | J6: =IFERROR(IF(TODAY()>=E6,(TODAY()-E6)/I6,0),0) -> 0.6 | K6: 2003.42 | L6: 2000.7089 | M6: =K6-L6 -> 2.7111148 | N6: 3682.97 | Q6: =K6*N6 -> 7378535.8 | R6: =L6*O6 -> 0 | S6: =R6-Q6 -> -7378535.8 | T6: =IF(R6<= Q6,"No Monetizar","Monetizar") -> No Monetizar
B7: 5 | C7: Safeguard World Inter Ltd | D7: FV-4-6622 | E7: 46085 | F7: 46145 | G7: =(TEXT(F7,"ddd")) -> dom | H7: =(TEXT(F7,"mmm")) -> may | I7: =F7-E7 -> 60 | J7: =IFERROR(IF(TODAY()>=E7,(TODAY()-E7)/I7,0),0) -> 0.6 | K7: 2280 | L7: 2276.9146 | M7: =K7-L7 -> 3.0853949 | N7: 3682.97 | Q7: =K7*N7 -> 8397171.6 | R7: =L7*O7 -> 0 | S7: =R7-Q7 -> -8397171.6 | T7: =IF(R7<= Q7,"No Monetizar","Monetizar") -> No Monetizar
B8: 6 | C8: Safeguard World Inter Ltd | D8: FV-4-6707 | E8: 46085 | F8: 46145 | G8: =(TEXT(F8,"ddd")) -> dom | H8: =(TEXT(F8,"mmm")) -> may | I8: =F8-E8 -> 60 | J8: =IFERROR(IF(TODAY()>=E8,(TODAY()-E8)/I8,0),0) -> 0.6 | K8: 2055.84 | L8: 2053.0579 | M8: =K8-L8 -> 2.7820518 | N8: 3691.34 | Q8: =K8*N8 -> 7588804.4 | R8: =L8*O8 -> 0 | S8: =R8-Q8 -> -7588804.4 | T8: =IF(R8<= Q8,"No Monetizar","Monetizar") -> No Monetizar
B9: 7 | C9: Safeguard World Inter Ltd | D9: FV-4-6575 | E9: 46080 | F9: 46140 | G9: =(TEXT(F9,"ddd")) -> mar | H9: =(TEXT(F9,"mmm")) -> abr | I9: =F9-E9 -> 60 | J9: =IFERROR(IF(TODAY()>=E9,(TODAY()-E9)/I9,0),0) -> 0.68333333 | K9: 1969.45 | L9: 1969.45 | M9: =K9-L9 -> 0 | N9: 3817.93 | O9: 3650 | Q9: =K9*N9 -> 7519222.2 | R9: =L9*O9 -> 7188492.5 | S9: =R9-Q9 -> -330729.74 | T9: =IF(R9<= Q9,"No Monetizar","Monetizar") -> No Monetizar
B10: 8 | C10: Safeguard World Inter Ltd | D10: FV-4-6576 | E10: 46080 | F10: 46140 | G10: =(TEXT(F10,"ddd")) -> mar | H10: =(TEXT(F10,"mmm")) -> abr | I10: =F10-E10 -> 60 | J10: =IFERROR(IF(TODAY()>=E10,(TODAY()-E10)/I10,0),0) -> 0.68333333 | K10: 1523.38 | L10: 1523.38 | M10: =K10-L10 -> 0 | N10: 3817.93 | O10: 3650 | Q10: =K10*N10 -> 5816158.2 | R10: =L10*O10 -> 5560337 | S10: =R10-Q10 -> -255821.2 | T10: =IF(R10<= Q10,"No Monetizar","Monetizar") -> No Monetizar
B11: 9 | C11: Safeguard World Inter Ltd | D11: FV-4-6577 | E11: 46080 | F11: 46140 | G11: =(TEXT(F11,"ddd")) -> mar | H11: =(TEXT(F11,"mmm")) -> abr | I11: =F11-E11 -> 60 | J11: =IFERROR(IF(TODAY()>=E11,(TODAY()-E11)/I11,0),0) -> 0.68333333 | K11: 2280 | L11: 2280 | M11: =K11-L11 -> 0 | N11: 3817.93 | O11: 3650 | Q11: =K11*N11 -> 8704880.4 | R11: =L11*O11 -> 8322000 | S11: =R11-Q11 -> -382880.4 | T11: =IF(R11<= Q11,"No Monetizar","Monetizar") -> No Monetizar
B12: 10 | C12: Global Upside LLC | D12: 6750 | E12: 46100 | F12: 46160 | G12: =(TEXT(F12,"ddd")) -> lun | H12: =(TEXT(F12,"mmm")) -> may | I12: =F12-E12 -> 60 | J12: =IFERROR(IF(TODAY()>=E12,(TODAY()-E12)/I12,0),0) -> 0.35 | K12: 1870 | L12: 1870 | M12: =K12-L12 -> 0 | N12: 3767.94 | O12: 3650 | Q12: =K12*N12 -> 7046047.8 | R12: =L12*O12 -> 6825500 | S12: =R12-Q12 -> -220547.8 | T12: =IF(R12<= Q12,"No Monetizar","Monetizar") -> No Monetizar
B13: 11 | C13: Solutions & Payroll SAS | D13: Giros Western Union | E13: 46105 | F13: 46165 | G13: =(TEXT(F13,"ddd")) -> sáb | H13: =(TEXT(F13,"mmm")) -> may | I13: =F13-E13 -> 60 | J13: =IFERROR(IF(TODAY()>=E13,(TODAY()-E13)/I13,0),0) -> 0.26666667 | K13: 13129 | L13: 13129 | M13: =K13-L13 -> 0 | N13: 3704.87 | O13: 3650 | Q13: =K13*N13 -> 48641238 | R13: =L13*O13 -> 47920850 | S13: =R13-Q13 -> -720388.23 | T13: =IF(R13<= Q13,"No Monetizar","Monetizar") -> No Monetizar
B14: 12 | C14: Deel | D14: 6728-6729-6730-6731-6732-6733-6734-6735-6736 | E14: 46105 | F14: 46165 | G14: =(TEXT(F14,"ddd")) -> sáb | H14: =(TEXT(F14,"mmm")) -> may | I14: =F14-E14 -> 60 | J14: =IFERROR(IF(TODAY()>=E14,(TODAY()-E14)/I14,0),0) -> 0.26666667 | K14: 11314.66 | L14: 11299.66 | M14: =K14-L14 -> 15 | N14: 3703.69 | O14: 3650 | Q14: =K14*N14 -> 41905993 | R14: =L14*O14 -> 41243759 | S14: =R14-Q14 -> -662234.1 | T14: =IF(R14<= Q14,"No Monetizar","Monetizar") -> No Monetizar
B15: 13 | C15: Deel | D15: 6737-6738-6739-6740-6741 | E15: 46105 | F15: 46165 | G15: =(TEXT(F15,"ddd")) -> sáb | H15: =(TEXT(F15,"mmm")) -> may | I15: =F15-E15 -> 60 | J15: =IFERROR(IF(TODAY()>=E15,(TODAY()-E15)/I15,0),0) -> 0.26666667 | K15: 5765.38 | L15: 5765.38 | M15: =K15-L15 -> 0 | N15: 3703.69 | O15: 3650 | Q15: =K15*N15 -> 21353180 | R15: =L15*O15 -> 21043637 | S15: =R15-Q15 -> -309543.25 | T15: =IF(R15<= Q15,"No Monetizar","Monetizar") -> No Monetizar
B16: 14 | C16: Deel | D16: FV-4-6325 | E16: 46105 | F16: 46165 | G16: =(TEXT(F16,"ddd")) -> sáb | H16: =(TEXT(F16,"mmm")) -> may | I16: =F16-E16 -> 60 | J16: =IFERROR(IF(TODAY()>=E16,(TODAY()-E16)/I16,0),0) -> 0.26666667 | K16: 1462.1 | L16: 1452.1 | M16: =K16-L16 -> 10 | N16: 3901.29 | O16: 3650 | Q16: =K16*N16 -> 5704076.1 | R16: =L16*O16 -> 5300165 | S16: =R16-Q16 -> -403911.11 | T16: =IF(R16<= Q16,"No Monetizar","Monetizar") -> No Monetizar
B18: 4 | C18: Bubble do Brasil | D18: FV-4-6815 | E18: 46112 | F18: 46172 | G18: =(TEXT(F18,"ddd")) -> sáb | H18: =(TEXT(F18,"mmm")) -> may | I18: =F18-E18 -> 60 | J18: =IFERROR(IF(TODAY()>=E18,(TODAY()-E18)/I18,0),0) -> 0.15 | K18: 129.22 | L18: 128.22901 | M18: =K18-L18 -> 0.99098892 | N18: 3637.76 | O18: 3750 | Q18: =K18*N18 -> 470071.35 | R18: =L18*O18 -> 480858.79 | S18: =R18-Q18 -> 10787.444 | T18: =IF(R18<= Q18,"No Monetizar","Monetizar") -> Monetizar
B19: 5 | C19: Bubble do Brasil | D19: FV-5-273 | E19: 46112 | F19: 46172 | G19: =(TEXT(F19,"ddd")) -> sáb | H19: =(TEXT(F19,"mmm")) -> may | I19: =F19-E19 -> 60 | J19: =IFERROR(IF(TODAY()>=E19,(TODAY()-E19)/I19,0),0) -> 0.15 | K19: 1174.73 | L19: 1165.721 | M19: =K19-L19 -> 9.0090111 | N19: 3637.76 | O19: 3750 | Q19: =K19*N19 -> 4273385.8 | R19: =L19*O19 -> 4371453.7 | S19: =R19-Q19 -> 98067.904 | T19: =IF(R19<= Q19,"No Monetizar","Monetizar") -> Monetizar
J20: =IFERROR(IF(TODAY()>=E20,(TODAY()-E20)/I20,0),0) -> 0
J21: =IFERROR(IF(TODAY()>=E21,(TODAY()-E21)/I21,0),0) -> 0 | Q21: =K21*N21 -> 0 | R21: =L21*O21 -> 0 | S21: =R21-Q21 -> 0 | T21: =IF(R21<= Q21,"No Monetizar","Monetizar") -> No Monetizar
Q22: =K22*N22 -> 0 | R22: =L22*O22 -> 0 | S22: =R22-Q22 -> 0 | T22: =IF(R22<= Q22,"No Monetizar","Monetizar") -> No Monetizar
B23: TOTAL | K23: =SUBTOTAL(9,K3:K22) -> 51717.18 | L23: =SUBTOTAL(9,L3:L22) -> 51667.16 | M23: =SUBTOTAL(9,M3:M22) -> 50.02 | Q23: =SUBTOTAL(9,Q3:Q22) -> 1.9379392e+08 | R23: =SUBTOTAL(9,R3:R22) -> 148257053 | S23: =SUBTOTAL(9,S3:S22) -> -45536863 | T23: =S23/Q23 -> -0.23497571
J25: Trm 9/3/2026
K26: 3741.47
Q29: CASH FLOW | Z29: ACCOUNTANT
B31: ID | C31: Client | D31: Invoice | E31: Incoming resources | F31: Maximum Date for Monetization | I31: Días | J31: Progress | K31: Invoiced | L31: Received | M31: Banking taxes | N31: TRm Invoice Cops | O31: TRM Bank (Average) Cops | P31: Difference in exchange rates | Q31: invoicing in COPS | R31: negotiated COPS | S31: difference | T31: KPI | U31: Color KPI | V31: Transaction date | W31: Propuesto | X31: Aprobado | Y31: Observaciones | Z31: negotiated COPS | AA31: difference
B32: 1 | C32: Action AD | D32: 5618 | E32: 45670 | F32: 45730 | J32: =IFERROR(IF(TODAY()>=E32,(TODAY()-E32)/I32,0),0)*0 -> 0 | K32: 6950.93 | L32: 6950.93 | M32: =K32-L32 -> 0 | N32: 4252.31 | O32: 4290.5 | P32: =O32-N32 -> 38.19 | Q32: =K32*N32 -> 29557509 | R32: =L32*O32 -> 29822965 | S32: =R32-Q32 -> 265456.02 | T32: =IF(R32<= Q32,"No Monetizar","Monetizar") -> Monetizar | V32: 45684 | W32: Alfonso Fonseca A | X32: Alfonso Fonseca A | Y32: Se monetiza ya que el valor ofrecido por el banco en cada divisa es superior al valor facturado | Z32: =K32*O32 -> 29822965 | AA32: =Z32-Q32 -> 265456.02
B33: 2 | C33: Remofirst | D33: 5619 | E33: 45684 | F33: 45744 | J33: =IFERROR(IF(TODAY()>=E33,(TODAY()-E33)/I33,0),0)*0 -> 0 | K33: 152785.56 | L33: 152785.56 | M33: =K33-L33 -> 0 | N33: 4235.51 | O33: 4303.83 | P33: =O33-N33 -> 68.32 | Q33: =K33*N33 -> 6.4712477e+08 | R33: =L33*O33 -> 6.5756308e+08 | S33: =R33-Q33 -> 10438309 | T33: =IF(R33<= Q33,"No Monetizar","Monetizar") -> Monetizar | V33: 45684 | W33: Alfonso Fonseca A | X33: Alfonso Fonseca A | Y33: Se monetiza ya que el valor ofrecido por el banco en cada divisa es superior al valor facturado | Z33: =K33*O33 -> 6.5756308e+08 | AA33: =Z33-Q33 -> 10438309
B34: 3 | C34: Endrington | D34: 5629 | E34: 45684 | F34: 45744 | J34: =IFERROR(IF(TODAY()>=E34,(TODAY()-E34)/I34,0),0)*0 -> 0 | K34: 22896.82 | L34: 22896.82 | M34: =K34-L34 -> 0 | N34: 4251.23 | O34: 4303.83 | P34: =O34-N34 -> 52.6 | Q34: =K34*N34 -> 97339648 | R34: =L34*O34 -> 98544021 | S34: =R34-Q34 -> 1204372.7 | T34: =IF(R34<= Q34,"No Monetizar","Monetizar") -> Monetizar | V34: 45684 | W34: Alfonso Fonseca A | X34: Alfonso Fonseca A | Y34: Se monetiza ya que el valor ofrecido por el banco en cada divisa es superior al valor facturado | Z34: =K34*O34 -> 98544021 | AA34: =Z34-Q34 -> 1204372.7
B35: 4 | C35: Marketing Doctors | D35: 5622 | E35: 45684 | F35: 45744 | J35: =IFERROR(IF(TODAY()>=E35,(TODAY()-E35)/I35,0),0)*0 -> 0 | K35: 2660.37 | L35: 2660.37 | M35: =K35-L35 -> 0 | N35: 4231.23 | O35: 4303.83 | P35: =O35-N35 -> 72.6 | Q35: =K35*N35 -> 11256637 | R35: =L35*O35 -> 11449780 | S35: =R35-Q35 -> 193142.86 | T35: =IF(R35<= Q35,"No Monetizar","Monetizar") -> Monetizar | V35: 45684 | W35: Alfonso Fonseca A | X35: Alfonso Fonseca A | Y35: Se monetiza ya que el valor ofrecido por el banco en cada divisa es superior al valor facturado | Z35: =K35*O35 -> 11449780 | AA35: =Z35-Q35 -> 193142.86
B36: 5 | C36: Flexco | D36: 5630 | E36: 45684 | F36: 45744 | J36: =IFERROR(IF(TODAY()>=E36,(TODAY()-E36)/I36,0),0)*0 -> 0 | K36: 12800.27 | L36: 12785.27 | M36: =K36-L36 -> 15 | N36: 4194.11 | O36: 4303.83 | P36: =O36-N36 -> 109.72 | Q36: =K36*N36 -> 53685740 | R36: =L36*O36 -> 55025629 | S36: =R36-Q36 -> 1339888.2 | T36: =IF(R36<= Q36,"No Monetizar","Monetizar") -> Monetizar | V36: 45684 | W36: Alfonso Fonseca A | X36: Alfonso Fonseca A | Y36: Se monetiza ya que el valor ofrecido por el banco en cada divisa es superior al valor facturado | Z36: =K36*O36 -> 55090186 | AA36: =Z36-Q36 -> 1404445.6
B37: 6 | C37: Nazdar ink technologies | D37: 5623 | E37: 45684 | F37: 45744 | J37: =IFERROR(IF(TODAY()>=E37,(TODAY()-E37)/I37,0),0)*0 -> 0 | K37: 18062.89 | L37: 18047.89 | M37: =K37-L37 -> 15 | N37: 4251.23 | O37: 4303.83 | P37: =O37-N37 -> 52.6 | Q37: =K37*N37 -> 76789500 | R37: =L37*O37 -> 77675050 | S37: =R37-Q37 -> 885550.56 | T37: =IF(R37<= Q37,"No Monetizar","Monetizar") -> Monetizar | V37: 45684 | W37: Alfonso Fonseca A | X37: Alfonso Fonseca A | Y37: Se monetiza ya que el valor ofrecido por el banco en cada divisa es superior al valor facturado | Z37: =K37*O37 -> 77739608 | AA37: =Z37-Q37 -> 950108.01
B38: 7 | C38: Oncehub | D38: 5631 | E38: 45684 | F38: 45744 | J38: =IFERROR(IF(TODAY()>=E38,(TODAY()-E38)/I38,0),0)*0 -> 0 | K38: 2833.35 | L38: 2813.35 | M38: =K38-L38 -> 20 | N38: 4231.53 | O38: 4303.83 | P38: =O38-N38 -> 72.3 | Q38: =K38*N38 -> 11989406 | R38: =L38*O38 -> 12108180 | S38: =R38-Q38 -> 118774.61 | T38: =IF(R38<= Q38,"No Monetizar","Monetizar") -> Monetizar | V38: 45684 | W38: Alfonso Fonseca A | X38: Alfonso Fonseca A | Y38: Se monetiza ya que el valor ofrecido por el banco en cada divisa es superior al valor facturado | Z38: =K38*O38 -> 12194257 | AA38: =Z38-Q38 -> 204851.21
B39: 8 | C39: Insider | D39: 5655 | E39: 45685 | F39: 45745 | J39: =IFERROR(IF(TODAY()>=E39,(TODAY()-E39)/I39,0),0)*0 -> 0 | K39: 106150.36 | L39: 106135.36 | M39: =K39-L39 -> 15 | N39: 4070.86 | O39: 4177.7 | P39: =O39-N39 -> 106.84 | Q39: =K39*N39 -> 4.3212325e+08 | R39: =L39*O39 -> 4.4340169e+08 | S39: =R39-Q39 -> 11278439 | T39: =IF(R39<= Q39,"No Monetizar","Monetizar") -> Monetizar | V39: 45686 | W39: Alfonso Fonseca A | X39: Alfonso Fonseca A | Y39: Se monetiza ya que el valor ofrecido por el banco en cada divisa es superior al valor facturado | Z39: =K39*O39 -> 4.4346436e+08 | AA39: =Z39-Q39 -> 11341104
B40: 9 | C40: Safeguard Payroll | D40: 5389 a 5406 | E40: 45680 | F40: 45740 | J40: =IFERROR(IF(TODAY()>=E40,(TODAY()-E40)/I40,0),0)*0 -> 0 | K40: 17192.43 | L40: 17177.43 | M40: =K40-L40 -> 15 | N40: 4367.39 | O40: 4441.62 | P40: =O40-N40 -> 74.23 | Q40: =K40*N40 -> 75086047 | R40: =L40*O40 -> 76295617 | S40: =R40-Q40 -> 1209569.8 | T40: =IF(R40<= Q40,"No Monetizar","Monetizar") -> Monetizar | V40: 45687 | W40: Alfonso Fonseca A | X40: Alfonso Fonseca A | Y40: Se monetiza ya que el valor ofrecido por el banco en cada divisa es superior al valor facturado | Z40: =K40*O40 -> 76362241 | AA40: =Z40-Q40 -> 1276194.1
B41: 10 | C41: Remofirst-Abono | D41: 5656 | E41: 45691 | F41: 45751 | J41: =IFERROR(IF(TODAY()>=E41,(TODAY()-E41)/I41,0),0)*0 -> 0 | K41: 1459.33 | L41: 1459.33 | M41: =K41-L41 -> 0 | N41: 4100.86 | O41: 4136.07 | P41: =O41-N41 -> 35.21 | Q41: =K41*N41 -> 5984508 | R41: =L41*O41 -> 6035891 | S41: =R41-Q41 -> 51383.009 | T41: =IF(R41<= Q41,"No Monetizar","Monetizar") -> Monetizar | V41: 45692 | W41: Alfonso Fonseca A | X41: Alfonso Fonseca A | Y41: Se monetiza ya que el valor ofrecido por el banco en cada divisa es superior al valor facturado | Z41: =K41*O41 -> 6035891 | AA41: =Z41-Q41 -> 51383.009
B42: 11 | C42: Remofirst-Saldo final | D42: 5656 | E42: 45700 | F42: 45760 | J42: =IFERROR(IF(TODAY()>=E42,(TODAY()-E42)/I42,0),0)*0 -> 0 | K42: 593.48 | L42: 593.48 | M42: =K42-L42 -> 0 | N42: 4100.86 | O42: 4147.5 | P42: =O42-N42 -> 46.64 | Q42: =K42*N42 -> 2433778.4 | R42: =L42*O42 -> 2461458.3 | S42: =R42-Q42 -> 27679.907 | T42: =IF(R42<= Q42,"No Monetizar","Monetizar") -> Monetizar | V42: 45700 | W42: Alfonso Fonseca A | X42: Alfonso Fonseca A | Y42: Se monetiza ya que el valor ofrecido por el banco en cada divisa es superior al valor facturado | Z42: =K42*O42 -> 2461458.3 | AA42: =Z42-Q42 -> 27679.907
B43: 12 | C43: Hong kong yonyou xinfushe cloud technology co | D43: 5628 | E43: 45679 | F43: 45739 | J43: =IFERROR(IF(TODAY()>=E43,(TODAY()-E43)/I43,0),0)*0 -> 0 | K43: 4737.5 | L43: 4737.5 | M43: =K43-L43 -> 0 | N43: 4231.23 | O43: 4143.44 | P43: =O43-N43 -> -87.79 | Q43: =K43*N43 -> 20045452 | R43: =L43*O43 -> 19629547 | S43: =R43-Q43 -> -415905.12 | T43: =IF(R43<= Q43,"No Monetizar","Monetizar") -> No Monetizar | V43: 45700 | W43: Alfonso Fonseca A | X43: Eduard Forero | Y43: Se monetizaron estas divisas por debajo del valor facturado debido a que, por el comportamiento del mercado, la TRM ha presentado una reducción notable desde el pasado 25 de enero, producto de factores externos de carácter económico. Desde el 07 de enero se realizó un monitoreo constante del comportamiento de esta divisa. En dicho período, el máximo crecimiento registrado fue el 12 de febrero frente al 07 de febrero, con un incremento de $15,99, alcanzando un valor máximo de $4,143,44. Entre el valor facturado y lo finalmente negociado, se tenía previsto un ingreso de $174 millones, pero el ingreso real fue de $173 millones, reflejando una desviación del 0,9 %. Adicionalmente, era necesario disponer de los recursos para cumplir con obligaciones financieras urgentes, como el pago de seguridad social, impuestos de retención en la fuente y cesantías, programados para el jueves 13 y viernes 14 de febrero. Por esta razón, no era viable esperar un aumento del valor de la divisa por encima del rango facturado, estimado entre $4,251 y $4,294. | Z43: =K43*O43 -> 19629547 | AA43: =Z43-Q43 -> -415905.12
B44: 13 | C44: Hemmebarsch GMBH & Co KG | D44: 5586 | E44: 45679 | F44: 45739 | J44: =IFERROR(IF(TODAY()>=E44,(TODAY()-E44)/I44,0),0)*0 -> 0 | K44: 867.66 | L44: 867.66 | M44: =K44-L44 -> 0 | N44: 4294.64 | O44: 4143.44 | P44: =O44-N44 -> -151.2 | Q44: =K44*N44 -> 3726287.3 | R44: =L44*O44 -> 3595097.2 | S44: =R44-Q44 -> -131190.19 | T44: =IF(R44<= Q44,"No Monetizar","Monetizar") -> No Monetizar | V44: 45700 | W44: Alfonso Fonseca A | X44: Eduard Forero | Y44: Se monetizaron estas divisas por debajo del valor facturado debido a que, por el comportamiento del mercado, la TRM ha presentado una reducción notable desde el pasado 25 de enero, producto de factores externos de carácter económico. Desde el 07 de enero se realizó un monitoreo constante del comportamiento de esta divisa. En dicho período, el máximo crecimiento registrado fue el 12 de febrero frente al 07 de febrero, con un incremento de $15,99, alcanzando un valor máximo de $4,143,44. Entre el valor facturado y lo finalmente negociado, se tenía previsto un ingreso de $174 millones, pero el ingreso real fue de $173 millones, reflejando una desviación del 0,9 %. Adicionalmente, era necesario disponer de los recursos para cumplir con obligaciones financieras urgentes, como el pago de seguridad social, impuestos de retención en la fuente y cesantías, programados para el jueves 13 y viernes 14 de febrero. Por esta razón, no era viable esperar un aumento del valor de la divisa por encima del rango facturado, estimado entre $4,251 y $4,294. | Z44: =K44*O44 -> 3595097.2 | AA44: =Z44-Q44 -> -131190.19
B45: 14 | C45: Neo | D45: 5624 | E45: 45680 | F45: 45740 | J45: =IFERROR(IF(TODAY()>=E45,(TODAY()-E45)/I45,0),0)*0 -> 0 | K45: 22499.23 | L45: 22453.23 | M45: =K45-L45 -> 46 | N45: 4216.23 | O45: 4143.44 | P45: =O45-N45 -> -72.79 | Q45: =K45*N45 -> 94861929 | R45: =L45*O45 -> 93033611 | S45: =R45-Q45 -> -1828317.2 | T45: =IF(R45<= Q45,"No Monetizar","Monetizar") -> No Monetizar | V45: 45700 | W45: Alfonso Fonseca A | X45: Eduard Forero | Y45: Se monetizaron estas divisas por debajo del valor facturado debido a que, por el comportamiento del mercado, la TRM ha presentado una reducción notable desde el pasado 25 de enero, producto de factores externos de carácter económico. Desde el 07 de enero se realizó un monitoreo constante del comportamiento de esta divisa. En dicho período, el máximo crecimiento registrado fue el 12 de febrero frente al 07 de febrero, con un incremento de $15,99, alcanzando un valor máximo de $4,143,44. Entre el valor facturado y lo finalmente negociado, se tenía previsto un ingreso de $174 millones, pero el ingreso real fue de $173 millones, reflejando una desviación del 0,9 %. Adicionalmente, era necesario disponer de los recursos para cumplir con obligaciones financieras urgentes, como el pago de seguridad social, impuestos de retención en la fuente y cesantías, programados para el jueves 13 y viernes 14 de febrero. Por esta razón, no era viable esperar un aumento del valor de la divisa por encima del rango facturado, estimado entre $4,251 y $4,294. | Z45: =K45*O45 -> 93224210 | AA45: =Z45-Q45 -> -1637719
B46: 15 | C46: Hemmebarsch GMBH & Co KG | D46: 5585 | E46: 45687 | F46: 45747 | J46: =IFERROR(IF(TODAY()>=E46,(TODAY()-E46)/I46,0),0)*0 -> 0 | K46: 3469.98 | L46: 3469.98 | M46: =K46-L46 -> 0 | N46: 4294.64 | O46: 4143.44 | P46: =O46-N46 -> -151.2 | Q46: =K46*N46 -> 14902315 | R46: =L46*O46 -> 14377654 | S46: =R46-Q46 -> -524660.98 | T46: =IF(R46<= Q46,"No Monetizar","Monetizar") -> No Monetizar | V46: 45700 | W46: Alfonso Fonseca A | X46: Eduard Forero | Y46: Se monetizaron estas divisas por debajo del valor facturado debido a que, por el comportamiento del mercado, la TRM ha presentado una reducción notable desde el pasado 25 de enero, producto de factores externos de carácter económico. Desde el 07 de enero se realizó un monitoreo constante del comportamiento de esta divisa. En dicho período, el máximo crecimiento registrado fue el 12 de febrero frente al 07 de febrero, con un incremento de $15,99, alcanzando un valor máximo de $4,143,44. Entre el valor facturado y lo finalmente negociado, se tenía previsto un ingreso de $174 millones, pero el ingreso real fue de $173 millones, reflejando una desviación del 0,9 %. Adicionalmente, era necesario disponer de los recursos para cumplir con obligaciones financieras urgentes, como el pago de seguridad social, impuestos de retención en la fuente y cesantías, programados para el jueves 13 y viernes 14 de febrero. Por esta razón, no era viable esperar un aumento del valor de la divisa por encima del rango facturado, estimado entre $4,251 y $4,294. | Z46: =K46*O46 -> 14377654 | AA46: =Z46-Q46 -> -524660.98
B47: 16 | C47: Insider | D47: 5575 | E47: 45691 | F47: 45751 | J47: =IFERROR(IF(TODAY()>=E47,(TODAY()-E47)/I47,0),0)*0 -> 0 | K47: 672.6 | L47: 667.6 | M47: =K47-L47 -> 5 | N47: 4249.11 | O47: 4143.44 | P47: =O47-N47 -> -105.67 | Q47: =K47*N47 -> 2857951.4 | R47: =L47*O47 -> 2766160.5 | S47: =R47-Q47 -> -91790.842 | T47: =IF(R47<= Q47,"No Monetizar","Monetizar") -> No Monetizar | V47: 45700 | W47: Alfonso Fonseca A | X47: Eduard Forero | Y47: Se monetizaron estas divisas por debajo del valor facturado debido a que, por el comportamiento del mercado, la TRM ha presentado una reducción notable desde el pasado 25 de enero, producto de factores externos de carácter económico. Desde el 07 de enero se realizó un monitoreo constante del comportamiento de esta divisa. En dicho período, el máximo crecimiento registrado fue el 12 de febrero frente al 07 de febrero, con un incremento de $15,99, alcanzando un valor máximo de $4,143,44. Entre el valor facturado y lo finalmente negociado, se tenía previsto un ingreso de $174 millones, pero el ingreso real fue de $173 millones, reflejando una desviación del 0,9 %. Adicionalmente, era necesario disponer de los recursos para cumplir con obligaciones financieras urgentes, como el pago de seguridad social, impuestos de retención en la fuente y cesantías, programados para el jueves 13 y viernes 14 de febrero. Por esta razón, no era viable esperar un aumento del valor de la divisa por encima del rango facturado, estimado entre $4,251 y $4,294. | Z47: =K47*O47 -> 2786877.7 | AA47: =Z47-Q47 -> -71073.642
B48: 17 | C48: Hemmebarsch GMBH & Co KG | D48: 5626 | E48: 45695 | F48: 45755 | J48: =IFERROR(IF(TODAY()>=E48,(TODAY()-E48)/I48,0),0)*0 -> 0 | K48: 1107.05 | L48: 1107.05 | M48: =K48-L48 -> 0 | N48: 4231.23 | O48: 4143.44 | P48: =O48-N48 -> -87.79 | Q48: =K48*N48 -> 4684183.2 | R48: =L48*O48 -> 4586995.3 | S48: =R48-Q48 -> -97187.919 | T48: =IF(R48<= Q48,"No Monetizar","Monetizar") -> No Monetizar | V48: 45700 | W48: Alfonso Fonseca A | X48: Eduard Forero | Y48: Se monetizaron estas divisas por debajo del valor facturado debido a que, por el comportamiento del mercado, la TRM ha presentado una reducción notable desde el pasado 25 de enero, producto de factores externos de carácter económico. Desde el 07 de enero se realizó un monitoreo constante del comportamiento de esta divisa. En dicho período, el máximo crecimiento registrado fue el 12 de febrero frente al 07 de febrero, con un incremento de $15,99, alcanzando un valor máximo de $4,143,44. Entre el valor facturado y lo finalmente negociado, se tenía previsto un ingreso de $174 millones, pero el ingreso real fue de $173 millones, reflejando una desviación del 0,9 %. Adicionalmente, era necesario disponer de los recursos para cumplir con obligaciones financieras urgentes, como el pago de seguridad social, impuestos de retención en la fuente y cesantías, programados para el jueves 13 y viernes 14 de febrero. Por esta razón, no era viable esperar un aumento del valor de la divisa por encima del rango facturado, estimado entre $4,251 y $4,294. | Z48: =K48*O48 -> 4586995.3 | AA48: =Z48-Q48 -> -97187.919
B49: 18 | C49: Hemmebarsch GMBH & Co KG | D49: 5627 | E49: 45695 | F49: 45755 | J49: =IFERROR(IF(TODAY()>=E49,(TODAY()-E49)/I49,0),0)*0 -> 0 | K49: 3521.96 | L49: 3521.96 | M49: =K49-L49 -> 0 | N49: 4231.23 | O49: 4143.44 | P49: =O49-N49 -> -87.79 | Q49: =K49*N49 -> 14902223 | R49: =L49*O49 -> 14593030 | S49: =R49-Q49 -> -309192.87 | T49: =IF(R49<= Q49,"No Monetizar","Monetizar") -> No Monetizar | V49: 45700 | W49: Alfonso Fonseca A | X49: Eduard Forero | Y49: Se monetizaron estas divisas por debajo del valor facturado debido a que, por el comportamiento del mercado, la TRM ha presentado una reducción notable desde el pasado 25 de enero, producto de factores externos de carácter económico. Desde el 07 de enero se realizó un monitoreo constante del comportamiento de esta divisa. En dicho período, el máximo crecimiento registrado fue el 12 de febrero frente al 07 de febrero, con un incremento de $15,99, alcanzando un valor máximo de $4,143,44. Entre el valor facturado y lo finalmente negociado, se tenía previsto un ingreso de $174 millones, pero el ingreso real fue de $173 millones, reflejando una desviación del 0,9 %. Adicionalmente, era necesario disponer de los recursos para cumplir con obligaciones financieras urgentes, como el pago de seguridad social, impuestos de retención en la fuente y cesantías, programados para el jueves 13 y viernes 14 de febrero. Por esta razón, no era viable esperar un aumento del valor de la divisa por encima del rango facturado, estimado entre $4,251 y $4,294. | Z49: =K49*O49 -> 14593030 | AA49: =Z49-Q49 -> -309192.87
B50: 19 | C50: Advancio | D50: 5633 | E50: 45695 | F50: 45755 | J50: =IFERROR(IF(TODAY()>=E50,(TODAY()-E50)/I50,0),0)*0 -> 0 | K50: 1250.93 | L50: 1250.93 | M50: =K50-L50 -> 0 | N50: 4194.11 | O50: 4143.44 | P50: =O50-N50 -> -50.67 | Q50: =K50*N50 -> 5246538 | R50: =L50*O50 -> 5183153.4 | S50: =R50-Q50 -> -63384.623 | T50: =IF(R50<= Q50,"No Monetizar","Monetizar") -> No Monetizar | V50: 45700 | W50: Alfonso Fonseca A | X50: Eduard Forero | Y50: Se monetizaron estas divisas por debajo del valor facturado debido a que, por el comportamiento del mercado, la TRM ha presentado una reducción notable desde el pasado 25 de enero, producto de factores externos de carácter económico. Desde el 07 de enero se realizó un monitoreo constante del comportamiento de esta divisa. En dicho período, el máximo crecimiento registrado fue el 12 de febrero frente al 07 de febrero, con un incremento de $15,99, alcanzando un valor máximo de $4,143,44. Entre el valor facturado y lo finalmente negociado, se tenía previsto un ingreso de $174 millones, pero el ingreso real fue de $173 millones, reflejando una desviación del 0,9 %. Adicionalmente, era necesario disponer de los recursos para cumplir con obligaciones financieras urgentes, como el pago de seguridad social, impuestos de retención en la fuente y cesantías, programados para el jueves 13 y viernes 14 de febrero. Por esta razón, no era viable esperar un aumento del valor de la divisa por encima del rango facturado, estimado entre $4,251 y $4,294. | Z50: =K50*O50 -> 5183153.4 | AA50: =Z50-Q50 -> -63384.623
B51: 20 | C51: Action AD | D51: 5678 | E51: 45699 | F51: 45759 | J51: =IFERROR(IF(TODAY()>=E51,(TODAY()-E51)/I51,0),0)*0 -> 0 | K51: 3689.78 | L51: 3689.78 | M51: =(K51-L51)*0 -> 0 | N51: 3980.06 | O51: =O50 -> 4143.44 | P51: =O51-N51 -> 163.38 | Q51: =K51*N51 -> 14685546 | R51: =L51*O51 -> 15288382 | S51: =R51-Q51 -> 602836.26 | T51: =IF(R51<= Q51,"No Monetizar","Monetizar") -> Monetizar | V51: 45700 | W51: Alfonso Fonseca A | X51: Eduard Forero | Y51: Se monetizaron estas divisas por debajo del valor facturado debido a que, por el comportamiento del mercado, la TRM ha presentado una reducción notable desde el pasado 25 de enero, producto de factores externos de carácter económico. Desde el 07 de enero se realizó un monitoreo constante del comportamiento de esta divisa. En dicho período, el máximo crecimiento registrado fue el 12 de febrero frente al 07 de febrero, con un incremento de $15,99, alcanzando un valor máximo de $4,143,44. Entre el valor facturado y lo finalmente negociado, se tenía previsto un ingreso de $174 millones, pero el ingreso real fue de $173 millones, reflejando una desviación del 0,9 %. Adicionalmente, era necesario disponer de los recursos para cumplir con obligaciones financieras urgentes, como el pago de seguridad social, impuestos de retención en la fuente y cesantías, programados para el jueves 13 y viernes 14 de febrero. Por esta razón, no era viable esperar un aumento del valor de la divisa por encima del rango facturado, estimado entre $4,251 y $4,294. | Z51: =K51*O51 -> 15288382 | AA51: =Z51-Q51 -> 602836.26
B52: 21 | C52: Endrington | D52: 5689 | E52: 45706 | F52: 45764 | J52: =IFERROR(IF(TODAY()>=E52,(TODAY()-E52)/I52,0),0)*0 -> 0 | K52: 23626.52 | L52: 23626.52 | M52: =K52-L52 -> 0 | N52: 3953.8 | O52: 4410.1 | P52: =O52-N52 -> 456.3 | Q52: =K52*N52 -> 93414535 | R52: =L52*O52 -> 1.0419532e+08 | S52: =R52-Q52 -> 10780781 | T52: =IF(R52<= Q52,"No Monetizar","Monetizar") -> Monetizar | V52: 45706 | W52: Alfonso Fonseca A | X52: Alfonso Fonseca A | Y52: Se monetiza ya que el valor ofrecido por el banco en cada divisa es superior al valor facturado | Z52: =K52*O52 -> 1.0419532e+08 | AA52: =Z52-Q52 -> 10780781
B53: 22 | C53: Marketing Doctors | D53: 5694 | E53: 45706 | F53: 45764 | J53: =IFERROR(IF(TODAY()>=E53,(TODAY()-E53)/I53,0),0)*0 -> 0 | K53: 2546.09 | L53: 2546.09 | M53: =K53-L53 -> 0 | N53: 3953.8 | O53: 4410.1 | P53: =O53-N53 -> 456.3 | Q53: =K53*N53 -> 10066731 | R53: =L53*O53 -> 11228512 | S53: =R53-Q53 -> 1161780.9 | T53: =IF(R53<= Q53,"No Monetizar","Monetizar") -> Monetizar | V53: 45706 | W53: Alfonso Fonseca A | X53: Alfonso Fonseca A | Y53: Se monetiza ya que el valor ofrecido por el banco en cada divisa es superior al valor facturado | Z53: =K53*O53 -> 11228512 | AA53: =Z53-Q53 -> 1161780.9
B54: 23 | C54: Advancio | D54: 5695 | E54: 45706 | F54: 45764 | J54: =IFERROR(IF(TODAY()>=E54,(TODAY()-E54)/I54,0),0)*0 -> 0 | K54: 1308.12 | L54: 1308.12 | M54: =K54-L54 -> 0 | N54: 3953.8 | O54: 4075.6 | P54: =O54-N54 -> 121.8 | Q54: =K54*N54 -> 5172044.9 | R54: =L54*O54 -> 5331373.9 | S54: =R54-Q54 -> 159329.02 | T54: =IF(R54<= Q54,"No Monetizar","Monetizar") -> Monetizar | V54: 45707 | W54: Alfonso Fonseca A | X54: Alfonso Fonseca A | Y54: Se monetiza ya que el valor ofrecido por el banco en cada divisa es superior al valor facturado | Z54: =K54*O54 -> 5331373.9 | AA54: =Z54-Q54 -> 159329.02
B55: 24 | C55: Oncehub | D55: 5691 | E55: 45706 | F55: 45764 | J55: =IFERROR(IF(TODAY()>=E55,(TODAY()-E55)/I55,0),0)*0 -> 0 | K55: 3069.09 | L55: 3049.09 | M55: =K55-L55 -> 20 | N55: 3953.8 | O55: 4069.15 | P55: =O55-N55 -> 115.35 | Q55: =K55*N55 -> 12134568 | R55: =L55*O55 -> 12407205 | S55: =(R55-Q55)/N55 -> 68.95557 | T55: =IF(R55<= Q55,"No Monetizar","Monetizar") -> Monetizar | V55: 45708 | W55: Alfonso Fonseca A | X55: Alfonso Fonseca A | Y55: Se monetiza ya que el valor ofrecido por el banco en cada divisa es superior al valor facturado | Z55: =K55*O55 -> 12488588 | AA55: =Z55-Q55 -> 354019.53
B56: 25 | C56: Nazdar ink technologies | D56: 5704 | E56: 45706 | F56: 45764 | J56: =IFERROR(IF(TODAY()>=E56,(TODAY()-E56)/I56,0),0)*0 -> 0 | K56: 13815.14 | L56: 13800.14 | M56: =K56-L56 -> 15 | N56: 3800.18 | O56: 4061.2 | P56: =O56-N56 -> 261.02 | Q56: =K56*N56 -> 52500019 | R56: =L56*O56 -> 56045129 | S56: =R56-Q56 -> 3545109.8 | T56: =IF(R56<= Q56,"No Monetizar","Monetizar") -> Monetizar | V56: 45708 | W56: Alfonso Fonseca A | X56: Alfonso Fonseca A | Y56: Se monetiza ya que el valor ofrecido por el banco en cada divisa es superior al valor facturado | Z56: =K56*O56 -> 56106047 | AA56: =Z56-Q56 -> 3606027.8
B57: 26 | C57: Flexco | D57: 5690 | E57: 45706 | F57: 45764 | J57: =IFERROR(IF(TODAY()>=E57,(TODAY()-E57)/I57,0),0)*0 -> 0 | K57: 3827.13 | L57: 3817.13 | M57: =K57-L57 -> 10 | N57: 3953.8 | O57: 4055.15 | P57: =O57-N57 -> 101.35 | Q57: =K57*N57 -> 15131707 | R57: =L57*O57 -> 15479035 | S57: =R57-Q57 -> 347328.13 | T57: =IF(R57<= Q57,"No Monetizar","Monetizar") -> Monetizar | V57: 45708 | W57: Alfonso Fonseca A | X57: Alfonso Fonseca A | Y57: Se monetiza ya que el valor ofrecido por el banco en cada divisa es superior al valor facturado | Z57: =K57*O57 -> 15519586 | AA57: =Z57-Q57 -> 387879.63
B58: 27 | C58: Neo | D58: 5692 | E58: 45706 | F58: 45764 | J58: =IFERROR(IF(TODAY()>=E58,(TODAY()-E58)/I58,0),0)*0 -> 0 | K58: 22597.84 | L58: 22551.84 | M58: =K58-L58 -> 46 | N58: 3953.8 | O58: 4094 | P58: =O58-N58 -> 140.2 | Q58: =K58*N58 -> 89347340 | R58: =L58*O58 -> 92327233 | S58: =R58-Q58 -> 2979893.2 | T58: =IF(R58<= Q58,"No Monetizar","Monetizar") -> Monetizar | V58: 45712 | W58: Alfonso Fonseca A | X58: Alfonso Fonseca A | Y58: Se monetiza ya que el valor ofrecido por el banco en cada divisa es superior al valor facturado | Z58: =K58*O58 -> 92515557 | AA58: =Z58-Q58 -> 3168217.2
B59: 28 | C59: Remofisrt | D59: 5688 | E59: 45706 | F59: 45764 | J59: =IFERROR(IF(TODAY()>=E59,(TODAY()-E59)/I59,0),0)*0 -> 0 | K59: 201884.45 | L59: 201884.45 | M59: =K59-L59 -> 0 | N59: 3850.81 | O59: 4098.61 | P59: =O59-N59 -> 247.8 | Q59: =K59*N59 -> 7.7741866e+08 | R59: =L59*O59 -> 8.2744563e+08 | S59: =R59-Q59 -> 50026967 | T59: =IF(R59<= Q59,"No Monetizar","Monetizar") -> Monetizar | V59: 45712 | W59: Alfonso Fonseca A | X59: Alfonso Fonseca A | Y59: Se monetiza ya que el valor ofrecido por el banco en cada divisa es superior al valor facturado | Z59: =K59*O59 -> 8.2744563e+08 | AA59: =Z59-Q59 -> 50026967
B60: 29 | C60: Insider | D60: 5729 | E60: 45706 | F60: 45764 | J60: =IFERROR(IF(TODAY()>=E60,(TODAY()-E60)/I60,0),0)*0 -> 0 | K60: 97590.24 | L60: 97575.24 | M60: =K60-L60 -> 15 | N60: 3862.63 | O60: 4112.15 | P60: =O60-N60 -> 249.52 | Q60: =K60*N60 -> 3.7695499e+08 | R60: =L60*O60 -> 4.0124402e+08 | S60: =R60-Q60 -> 24289034 | T60: =IF(R60<= Q60,"No Monetizar","Monetizar") -> Monetizar | V60: 45713 | W60: Alfonso Fonseca A | X60: Alfonso Fonseca A | Y60: Se monetiza ya que el valor ofrecido por el banco en cada divisa es superior al valor facturado | Z60: =K60*O60 -> 4.0130571e+08 | AA60: =Z60-Q60 -> 24350717
B61: 30 | C61: Hong kong yonyou xinfushe cloud technology co | D61: 5699 | E61: 45706 | F61: 45764 | J61: =IFERROR(IF(TODAY()>=E61,(TODAY()-E61)/I61,0),0)*0 -> 0 | K61: 6079.63 | L61: 6079.63 | M61: =K61-L61 -> 0 | N61: 3865.07 | O61: 4096.5 | P61: =O61-N61 -> 231.43 | Q61: =K61*N61 -> 23498196 | R61: =L61*O61 -> 24905204 | S61: =R61-Q61 -> 1407008.8 | T61: =IF(R61<= Q61,"No Monetizar","Monetizar") -> Monetizar | V61: 45715 | W61: Alfonso Fonseca A | X61: Alfonso Fonseca A | Y61: Se monetiza ya que el valor ofrecido por el banco en cada divisa es superior al valor facturado | Z61: =K61*O61 -> 24905204 | AA61: =Z61-Q61 -> 1407008.8
B62: 31 | C62: Hong kong yonyou xinfushe cloud technology co | D62: 5715 | E62: 45706 | F62: 45764 | J62: =IFERROR(IF(TODAY()>=E62,(TODAY()-E62)/I62,0),0)*0 -> 0 | K62: 2753.32 | L62: 2753.32 | M62: =K62-L62 -> 0 | N62: 3865.07 | O62: 4096.5 | P62: =O62-N62 -> 231.43 | Q62: =K62*N62 -> 10641775 | R62: =L62*O62 -> 11278975 | S62: =R62-Q62 -> 637200.85 | T62: =IF(R62<= Q62,"No Monetizar","Monetizar") -> Monetizar | V62: 45715 | W62: Alfonso Fonseca A | X62: Alfonso Fonseca A | Y62: Se monetiza ya que el valor ofrecido por el banco en cada divisa es superior al valor facturado | Z62: =K62*O62 -> 11278975 | AA62: =Z62-Q62 -> 637200.85
B63: 32 | C63: Insider | D63: 5730 | E63: 45706 | F63: 45764 | J63: =IFERROR(IF(TODAY()>=E63,(TODAY()-E63)/I63,0),0)*0 -> 0 | K63: 2920.43 | L63: 2910.43 | M63: =K63-L63 -> 10 | N63: 3862.63 | O63: 4134 | P63: =O63-N63 -> 271.37 | Q63: =K63*N63 -> 11280541 | R63: =L63*O63 -> 12031718 | S63: =R63-Q63 -> 751177.09 | T63: =IF(R63<= Q63,"No Monetizar","Monetizar") -> Monetizar | V63: 45716 | W63: Alfonso Fonseca A | X63: Alfonso Fonseca A | Y63: Se monetiza ya que el valor ofrecido por el banco en cada divisa es superior al valor facturado | Z63: =K63*O63 -> 12073058 | AA63: =Z63-Q63 -> 792517.09
B64: 33 | C64: Remofisrt | D64: 5736 | E64: 45706 | F64: 45764 | J64: =IFERROR(IF(TODAY()>=E64,(TODAY()-E64)/I64,0),0)*0 -> 0 | K64: 5905.3 | L64: 6141.42 | M64: =K64-L64 -> -236.12 | N64: 3850.81 | O64: 4119.3 | P64: =O64-N64 -> 268.49 | Q64: =K64*N64 -> 22740188 | R64: =L64*O64 -> 25298351 | S64: =R64-Q64 -> 2558163.1 | T64: =IF(R64<= Q64,"No Monetizar","Monetizar") -> Monetizar | V64: 45721 | W64: Alfonso Fonseca A | X64: Alfonso Fonseca A | Y64: Se monetiza ya que el valor ofrecido por el banco en cada divisa es superior al valor facturado | Z64: =K64*O64 -> 24325702 | AA64: =Z64-Q64 -> 1585514
B65: 34 | C65: Hemmebarsch GMBH & Co KG | D65: 5697 | E65: 45722 | F65: 45782 | J65: =IFERROR(IF(TODAY()>=E65,(TODAY()-E65)/I65,0),0)*0 -> 0 | K65: 3852.15 | L65: 3852.15 | M65: =K65-L65 -> 0 | N65: 3865.07 | O65: 4136.54 | P65: =O65-N65 -> 271.47 | Q65: =K65*N65 -> 14888829 | R65: =L65*O65 -> 15934573 | S65: =R65-Q65 -> 1045743.2 | T65: =IF(R65<= Q65,"No Monetizar","Monetizar") -> Monetizar | V65: 45726 | W65: Alfonso Fonseca A | X65: Alfonso Fonseca A | Y65: Se monetiza ya que el valor ofrecido por el banco en cada divisa es superior al valor facturado | Z65: =K65*O65 -> 15934573 | AA65: =Z65-Q65 -> 1045743.2
B66: 35 | C66: Hemmebarsch GMBH & Co KG | D66: 5698 | E66: 45722 | F66: 45782 | J66: =IFERROR(IF(TODAY()>=E66,(TODAY()-E66)/I66,0),0)*0 -> 0 | K66: 1203.24 | L66: 1203.24 | M66: =K66-L66 -> 0 | N66: 3865.07 | O66: 4136.54 | P66: =O66-N66 -> 271.47 | Q66: =K66*N66 -> 4650606.8 | R66: =L66*O66 -> 4977250.4 | S66: =R66-Q66 -> 326643.56 | T66: =IF(R66<= Q66,"No Monetizar","Monetizar") -> Monetizar | V66: 45726 | W66: Alfonso Fonseca A | X66: Alfonso Fonseca A | Y66: Se monetiza ya que el valor ofrecido por el banco en cada divisa es superior al valor facturado | Z66: =K66*O66 -> 4977250.4 | AA66: =Z66-Q66 -> 326643.56
B67: 36 | C67: Insider | D67: 5760 | E67: 45964 | F67: 45787 | J67: =IFERROR(IF(TODAY()>=E67,(TODAY()-E67)/I67,0),0)*0 -> 0 | K67: 16477.68 | L67: 16462.68 | M67: =K67-L67 -> 15 | N67: 4036.8 | O67: 4146.11 | P67: =O67-N67 -> 109.31 | Q67: =K67*N67 -> 66517099 | R67: =L67*O67 -> 68256082 | S67: =R67-Q67 -> 1738983.6 | T67: =IF(R67<= Q67,"No Monetizar","Monetizar") -> Monetizar | V67: 45727 | W67: Alfonso Fonseca A | X67: Alfonso Fonseca A | Y67: Se monetiza ya que el valor ofrecido por el banco en cada divisa es superior al valor facturado | Z67: =K67*O67 -> 68318274 | AA67: =Z67-Q67 -> 1801175.2
B68: 37 | C68: Global Project | D68: 5411 | E68: 45672 | F68: 45732 | J68: =IFERROR(IF(TODAY()>=E68,(TODAY()-E68)/I68,0),0)*0 -> 0 | K68: =471.97 -> 471.97 | L68: 470.59801 | M68: =K68-L68 -> 1.3719938 | N68: 4414 | O68: 4090.77 | P68: =O68-N68 -> -323.23 | Q68: =K68*N68 -> 2083275.6 | R68: =L68*O68 -> 1925108.2 | S68: =R68-Q68 -> -158167.37 | T68: =IF(R68<= Q68,"No Monetizar","Monetizar") -> No Monetizar | V68: 45729 | W68: Alfonso Fonseca A | X68: Alfonso Fonseca A | Y68: Se ha decidido monetizar estas divisas a pesar de que el valor recibido está por debajo del monto facturado, considerando que la fecha límite para su devolución vencía el próximo domingo 16 de marzo. Adicionalmente, al momento del cobro, la TRM se encontraba en $4,414, mientras que en la actualidad la divisa ha registrado disminuciones sustanciales, sin alcanzar siquiera los $4,100, y mucho menos el valor sobre el cual se generó el documento. Esta situación fue presentada al Director General durante la reunión mensual de revisión de flujos de caja, quien evaluó el escenario y determinó que, pese a la pérdida por diferencia en cambio, no había opción de alcanzar el valor de la divisa facturado en noviembre y diciembre, además de que existía una alta probabilidad de que los recursos tuvieran que ser devueltos al cliente. | Z68: =K68*O68 -> 1930720.7 | AA68: =Z68-Q68 -> -152554.86
B69: 38 | C69: Global Project | D69: 5493 | E69: 45672 | F69: 45732 | J69: =IFERROR(IF(TODAY()>=E69,(TODAY()-E69)/I69,0),0)*0 -> 0 | K69: 2318.06 | L69: 2311.3215 | M69: =K69-L69 -> 6.7384877 | N69: 4418.58 | O69: =O68 -> 4090.77 | P69: =O69-N69 -> -327.81 | Q69: =K69*N69 -> 10242534 | R69: =L69*O69 -> 9455084.7 | S69: =R69-Q69 -> -787448.85 | T69: =IF(R69<= Q69,"No Monetizar","Monetizar") -> No Monetizar | V69: 45729 | W69: Alfonso Fonseca A | X69: Alfonso Fonseca A | Y69: Se ha decidido monetizar estas divisas a pesar de que el valor recibido está por debajo del monto facturado, considerando que la fecha límite para su devolución vencía el próximo domingo 16 de marzo. Adicionalmente, al momento del cobro, la TRM se encontraba en $4,414, mientras que en la actualidad la divisa ha registrado disminuciones sustanciales, sin alcanzar siquiera los $4,100, y mucho menos el valor sobre el cual se generó el documento. Esta situación fue presentada al Director General durante la reunión mensual de revisión de flujos de caja, quien evaluó el escenario y determinó que, pese a la pérdida por diferencia en cambio, no había opción de alcanzar el valor de la divisa facturado en noviembre y diciembre, además de que existía una alta probabilidad de que los recursos tuvieran que ser devueltos al cliente. | Z69: =K69*O69 -> 9482650.3 | AA69: =Z69-Q69 -> -759883.25
B70: 39 | C70: Global Project | D70: 5514 | E70: 45672 | F70: 45732 | J70: =IFERROR(IF(TODAY()>=E70,(TODAY()-E70)/I70,0),0)*0 -> 0 | K70: 650 | L70: 648.11048 | M70: =K70-L70 -> 1.8895184 | N70: 4406.16 | O70: =O69 -> 4090.77 | P70: =O70-N70 -> -315.39 | Q70: =K70*N70 -> 2864004 | R70: =L70*O70 -> 2651270.9 | S70: =R70-Q70 -> -212733.09 | T70: =IF(R70<= Q70,"No Monetizar","Monetizar") -> No Monetizar | V70: 45729 | W70: Alfonso Fonseca A | X70: Alfonso Fonseca A | Y70: Se ha decidido monetizar estas divisas a pesar de que el valor recibido está por debajo del monto facturado, considerando que la fecha límite para su devolución vencía el próximo domingo 16 de marzo. Adicionalmente, al momento del cobro, la TRM se encontraba en $4,414, mientras que en la actualidad la divisa ha registrado disminuciones sustanciales, sin alcanzar siquiera los $4,100, y mucho menos el valor sobre el cual se generó el documento. Esta situación fue presentada al Director General durante la reunión mensual de revisión de flujos de caja, quien evaluó el escenario y determinó que, pese a la pérdida por diferencia en cambio, no había opción de alcanzar el valor de la divisa facturado en noviembre y diciembre, además de que existía una alta probabilidad de que los recursos tuvieran que ser devueltos al cliente. | Z70: =K70*O70 -> 2659000.5 | AA70: =Z70-Q70 -> -205003.5
B71: 40 | C71: Action AD | D71: 5762 | E71: 45733 | F71: 45793 | J71: =IFERROR(IF(TODAY()>=E71,(TODAY()-E71)/I71,0),0)*0 -> 0 | K71: 3149.17 | L71: 3149.17 | M71: =K71-L71 -> 0 | N71: 4101.96 | O71: 4121.65 | P71: =O71-N71 -> 19.69 | Q71: =K71*N71 -> 12917769 | R71: =L71*O71 -> 12979777 | S71: =R71-Q71 -> 62007.157 | T71: =IF(R71<= Q71,"No Monetizar","Monetizar") -> Monetizar | V71: 45733 | W71: Alfonso Fonseca A | X71: Alfonso Fonseca A | Y71: Se monetiza ya que el valor ofrecido por el banco en cada divisa es superior al valor facturado | Z71: =K71*O71 -> 12979777 | AA71: =Z71-Q71 -> 62007.157
B72: 41 | C72: Remofisrt | D72: 5736 | E72: 45735 | F72: 45795 | J72: =IFERROR(IF(TODAY()>=E72,(TODAY()-E72)/I72,0),0)*0 -> 0 | K72: 1120.94 | L72: 1120.94 | M72: =K72-L72 -> 0 | N72: 3850.81 | O72: 4130.05 | P72: =O72-N72 -> 279.24 | Q72: =K72*N72 -> 4316527 | R72: =L72*O72 -> 4629538.2 | S72: =R72-Q72 -> 313011.29 | T72: =IF(R72<= Q72,"No Monetizar","Monetizar") -> Monetizar | V72: 45735 | W72: Alfonso Fonseca A | X72: Alfonso Fonseca A | Y72: Se monetiza ya que el valor ofrecido por el banco en cada divisa es superior al valor facturado | Z72: =K72*O72 -> 4629538.2 | AA72: =Z72-Q72 -> 313011.29
B73: 42 | C73: Marketing Doctors | D73: 5769 | E73: 45735 | F73: 45795 | J73: =IFERROR(IF(TODAY()>=E73,(TODAY()-E73)/I73,0),0)*0 -> 0 | K73: 2513.44 | L73: 2513.44 | M73: =K73-L73 -> 0 | N73: 4010.08 | O73: 4177.22 | P73: =O73-N73 -> 167.14 | Q73: =K73*N73 -> 10079095 | R73: =L73*O73 -> 10499192 | S73: =R73-Q73 -> 420096.36 | T73: =IF(R73<= Q73,"No Monetizar","Monetizar") -> Monetizar | V73: 45736 | W73: Alfonso Fonseca A | X73: Alfonso Fonseca A | Y73: Se monetiza ya que el valor ofrecido por el banco en cada divisa es superior al valor facturado | Z73: =K73*O73 -> 10499192 | AA73: =Z73-Q73 -> 420096.36
B74: 43 | C74: Nazdar ink technologies | D74: 5771 | E74: 45736 | F74: 45796 | J74: =IFERROR(IF(TODAY()>=E74,(TODAY()-E74)/I74,0),0)*0 -> 0 | K74: 13839.49 | L74: 13824.49 | M74: =K74-L74 -> 15 | N74: 4010.08 | O74: 4171.5 | P74: =O74-N74 -> 161.42 | Q74: =K74*N74 -> 55497462 | R74: =L74*O74 -> 57668860 | S74: =R74-Q74 -> 2171398 | T74: =IF(R74<= Q74,"No Monetizar","Monetizar") -> Monetizar | V74: 45736 | W74: Alfonso Fonseca A | X74: Alfonso Fonseca A | Y74: Se monetiza ya que el valor ofrecido por el banco en cada divisa es superior al valor facturado | Z74: =K74*O74 -> 57731433 | AA74: =Z74-Q74 -> 2233970.5
B75: 44 | C75: Endrington | D75: 5776 | E75: 45737 | F75: 45797 | J75: =IFERROR(IF(TODAY()>=E75,(TODAY()-E75)/I75,0),0)*0 -> 0 | K75: 20615.23 | L75: 20615.23 | M75: =K75-L75 -> 0 | N75: 3990.08 | O75: 4159.1 | P75: =O75-N75 -> 169.02 | Q75: =K75*N75 -> 82256417 | R75: =L75*O75 -> 85740803 | S75: =R75-Q75 -> 3484386.2 | T75: =IF(R75<= Q75,"No Monetizar","Monetizar") -> Monetizar | V75: 45737 | W75: Alfonso Fonseca A | X75: Alfonso Fonseca A | Y75: Se monetiza ya que el valor ofrecido por el banco en cada divisa es superior al valor facturado | Z75: =K75*O75 -> 85740803 | AA75: =Z75-Q75 -> 3484386.2
B76: 45 | C76: Global Project | D76: 5521 | E76: 45707 | F76: 45767 | J76: =IFERROR(IF(TODAY()>=E76,(TODAY()-E76)/I76,0),0)*0 -> 0 | K76: 650 | L76: 645 | M76: =K76-L76 -> 5 | N76: 4424.56 | O76: 4130.6 | P76: =O76-N76 -> -293.96 | Q76: =K76*N76 -> 2875964 | R76: =L76*O76 -> 2664237 | S76: =R76-Q76 -> -211727 | T76: =IF(R76<= Q76,"No Monetizar","Monetizar") -> No Monetizar | V76: 45737 | W76: Alfonso Fonseca A | X76: Eduard Forero | Y76: Se ha decidido monetizar estas divisas a pesar de que el valor recibido está por debajo del monto facturado, dado que se requieren recursos de manera inmediata para realizar el préstamo a PM . Inicialmente, se le planteó a Eduard la posibilidad de monetizar estos fondos ayer a una tasa de 4,170, lo que representaba una pérdida de $1.770.452. Sin embargo, no se autorizo la operación . Hoy, debido a la urgencia de disponer de estos recursos, se autorizó la negociación, pero la tasa obtenida fue de 4,130.60, lo que resultó en una pérdida por diferencia en cambio de $1.988.436. | Z76: =K76*O76 -> 2684890 | AA76: =Z76-Q76 -> -191074
B77: 46 | C77: Safeguard LLC Payroll | D77: 5600 al 5609 | E77: 45723 | F77: 45783 | J77: =IFERROR(IF(TODAY()>=E77,(TODAY()-E77)/I77,0),0)*0 -> 0 | K77: 6120.34 | L77: =6120.34-10 -> 6110.34 | M77: =K77-L77 -> 10 | N77: 4375.86 | O77: =O76 -> 4130.6 | P77: =O77-N77 -> -245.26 | Q77: =K77*N77 -> 26781751 | R77: =L77*O77 -> 25239370 | S77: =R77-Q77 -> -1542380.6 | T77: =IF(R77<= Q77,"No Monetizar","Monetizar") -> No Monetizar | V77: 45737 | W77: Alfonso Fonseca A | X77: Eduard Forero | Y77: Se ha decidido monetizar estas divisas a pesar de que el valor recibido está por debajo del monto facturado, dado que se requieren recursos de manera inmediata para realizar el préstamo a PM . Inicialmente, se le planteó a Eduard la posibilidad de monetizar estos fondos ayer a una tasa de 4,170, lo que representaba una pérdida de $1.770.452. Sin embargo, no se autorizo la operación . Hoy, debido a la urgencia de disponer de estos recursos, se autorizó la negociación, pero la tasa obtenida fue de 4,130.60, lo que resultó en una pérdida por diferencia en cambio de $1.988.436. | Z77: =K77*O77 -> 25280676 | AA77: =Z77-Q77 -> -1501074.6
B78: 47 | C78: Safeguard LLC Payroll | D78: 5599 | E78: 45723 | F78: 45783 | J78: =IFERROR(IF(TODAY()>=E78,(TODAY()-E78)/I78,0),0)*0 -> 0 | K78: 955.43 | L78: 955.43 | M78: =K78-L78 -> 0 | N78: 4375.86 | O78: =O77 -> 4130.6 | P78: =O78-N78 -> -245.26 | Q78: =K78*N78 -> 4180827.9 | R78: =L78*O78 -> 3946499.2 | S78: =R78-Q78 -> -234328.76 | T78: =IF(R78<= Q78,"No Monetizar","Monetizar") -> No Monetizar | V78: 45737 | W78: Alfonso Fonseca A | X78: Eduard Forero | Y78: Se ha decidido monetizar estas divisas a pesar de que el valor recibido está por debajo del monto facturado, dado que se requieren recursos de manera inmediata para realizar el préstamo a PM . Inicialmente, se le planteó a Eduard la posibilidad de monetizar estos fondos ayer a una tasa de 4,170, lo que representaba una pérdida de $1.770.452. Sin embargo, no se autorizo la operación . Hoy, debido a la urgencia de disponer de estos recursos, se autorizó la negociación, pero la tasa obtenida fue de 4,130.60, lo que resultó en una pérdida por diferencia en cambio de $1.988.436. | Z78: =K78*O78 -> 3946499.2 | AA78: =Z78-Q78 -> -234328.76
B79: 48 | C79: Remofisrt | D79: 5768 | E79: 45737 | F79: 45797 | J79: =IFERROR(IF(TODAY()>=E79,(TODAY()-E79)/I79,0),0)*0 -> 0 | K79: 185122.81 | L79: 185122.81 | M79: =K79-L79 -> 0 | N79: 3996.8 | O79: 4106 | P79: =O79-N79 -> 109.2 | Q79: =K79*N79 -> 7.3989885e+08 | R79: =L79*O79 -> 7.6011426e+08 | S79: =R79-Q79 -> 20215411 | T79: =IF(R79<= Q79,"No Monetizar","Monetizar") -> Monetizar | V79: 45741 | W79: Alfonso Fonseca A | X79: Alfonso Fonseca A | Y79: Se monetiza ya que el valor ofrecido por el banco en cada divisa es superior al valor facturado | Z79: =K79*O79 -> 7.6011426e+08 | AA79: =Z79-Q79 -> 20215411
B80: 49 | C80: Neo | D80: 5772 | E80: 45741 | F80: 45801 | J80: =IFERROR(IF(TODAY()>=E80,(TODAY()-E80)/I80,0),0)*0 -> 0 | K80: 22511.27 | L80: 22465.27 | M80: =K80-L80 -> 46 | N80: 3980.08 | O80: 4103 | P80: =O80-N80 -> 122.92 | Q80: =K80*N80 -> 89596656 | R80: =L80*O80 -> 92175003 | S80: =R80-Q80 -> 2578347.3 | T80: =IF(R80<= Q80,"No Monetizar","Monetizar") -> Monetizar | V80: 45741 | W80: Alfonso Fonseca A | X80: Alfonso Fonseca A | Y80: Se monetiza ya que el valor ofrecido por el banco en cada divisa es superior al valor facturado | Z80: =K80*O80 -> 92363741 | AA80: =Z80-Q80 -> 2767085.3
B81: 50 | C81: Oncehub | D81: 5787 | E81: 45740 | F81: 45069 | J81: =IFERROR(IF(TODAY()>=E81,(TODAY()-E81)/I81,0),0)*0 -> 0 | K81: 2996.07 | L81: 2976.07 | M81: =K81-L81 -> 20 | N81: 4060.08 | O81: 4100 | P81: =O81-N81 -> 39.92 | Q81: =K81*N81 -> 12164284 | R81: =L81*O81 -> 12201887 | S81: =R81-Q81 -> 37603.114 | T81: =IF(R81<= Q81,"No Monetizar","Monetizar") -> Monetizar | V81: 45741 | W81: Alfonso Fonseca A | X81: Alfonso Fonseca A | Y81: Se monetiza ya que el valor ofrecido por el banco en cada divisa es superior al valor facturado | Z81: =K81*O81 -> 12283887 | AA81: =Z81-Q81 -> 119603.11
B82: 51 | C82: Hong kong yonyou xinfushe cloud technology co | D82: 5775 | E82: 45741 | F82: 45801 | J82: =IFERROR(IF(TODAY()>=E82,(TODAY()-E82)/I82,0),0)*0 -> 0 | K82: 14866.66 | L82: 14866.7 | M82: =K82-L82 -> -0.04 | N82: 4010.08 | O82: 4098 | P82: =O82-N82 -> 87.92 | Q82: =K82*N82 -> 59616496 | R82: =L82*O82 -> 60923737 | S82: =R82-Q82 -> 1307240.7 | T82: =IF(R82<= Q82,"No Monetizar","Monetizar") -> Monetizar | V82: 45741 | W82: Alfonso Fonseca A | X82: Alfonso Fonseca A | Y82: Se monetiza ya que el valor ofrecido por el banco en cada divisa es superior al valor facturado | Z82: =K82*O82 -> 60923573 | AA82: =Z82-Q82 -> 1307076.7
B83: 52 | C83: Flexco | D83: 5770 | E83: 45741 | F83: 45801 | J83: =IFERROR(IF(TODAY()>=E83,(TODAY()-E83)/I83,0),0)*0 -> 0 | K83: 3777.61 | L83: 3767.61 | M83: =K83-L83 -> 10 | N83: 4010.08 | O83: 4096 | P83: =O83-N83 -> 85.92 | Q83: =K83*N83 -> 15148518 | R83: =L83*O83+6028.44 -> 15438159 | S83: =R83-Q83 -> 289640.69 | T83: =IF(R83<= Q83,"No Monetizar","Monetizar") -> Monetizar | V83: 45742 | W83: Alfonso Fonseca A | X83: Alfonso Fonseca A | Y83: Se monetiza ya que el valor ofrecido por el banco en cada divisa es superior al valor facturado | Z83: =K83*O83 -> 15473091 | AA83: =Z83-Q83 -> 324572.25
B84: 53 | C84: Insider | D84: 5816 | E84: 45747 | F84: 45807 | J84: =IFERROR(IF(TODAY()>=E84,(TODAY()-E84)/I84,0),0)*0 -> 0 | K84: 98661.98 | L84: 98646.98 | M84: =K84-L84 -> 15 | N84: 4036.8 | O84: 4168 | P84: =O84-N84 -> 131.2 | Q84: =K84*N84 -> 3.9827868e+08 | R84: =L84*O84 -> 4.1116061e+08 | S84: =R84-Q84 -> 12881932 | T84: =IF(R84<= Q84,"No Monetizar","Monetizar") -> Monetizar | V84: 45747 | W84: Alfonso Fonseca A | X84: Alfonso Fonseca A | Y84: Se monetiza ya que el valor ofrecido por el banco en cada divisa es superior al valor facturado | Z84: =K84*O84 -> 4.1122313e+08 | AA84: =Z84-Q84 -> 12944452
B85: 54 | C85: Hemmebarsch GMBH & Co KG | D85: 5774 | E85: 45749 | F85: 45809 | J85: =IFERROR(IF(TODAY()>=E85,(TODAY()-E85)/I85,0),0)*0 -> 0 | K85: 1162.6 | L85: 1162.6 | M85: =K85-L85 -> 0 | N85: 3865.07 | O85: 4138 | P85: =O85-N85 -> 272.93 | Q85: =K85*N85 -> 4493530.4 | R85: =L85*O85 -> 4810838.8 | S85: =R85-Q85 -> 317308.42 | T85: =IF(R85<= Q85,"No Monetizar","Monetizar") -> Monetizar | V85: 45749 | W85: Alfonso Fonseca A | X85: Alfonso Fonseca A | Y85: Se monetiza ya que el valor ofrecido por el banco en cada divisa es superior al valor facturado | Z85: =K85*O85 -> 4810838.8 | AA85: =Z85-Q85 -> 317308.42
B86: 55 | C86: Safeguard LTD Payroll | D86: 5509-5510-5511-5512-5513 | E86: 45709 | F86: 45769 | J86: =IFERROR(IF(TODAY()>=E86,(TODAY()-E86)/I86,0),0)*0 -> 0 | K86: 5954.34 | L86: 5954.34 | M86: =K86-L86 -> 0 | N86: 4406.16 | O86: 4265 | P86: =O86-N86 -> -141.16 | Q86: =K86*N86 -> 26235775 | R86: =L86*O86 -> 25395260 | S86: =R86-Q86 -> -840514.63 | T86: =IF(R86<= Q86,"No Monetizar","Monetizar") -> No Monetizar | V86: 45751 | W86: Alfonso Fonseca A | X86: Eduard Forero | Y86: Se ha decidido monetizar estas divisas a pesar de que el valor recibido está por debajo del monto facturado, considerando que la fecha límite para su devolución vencía el próximo Martes 22 de abril. Adicionalmente, al momento del cobro, la TRM se encontraba en $4,406,16, mientras que en la actualidad la divisa ha registrado disminuciones sustanciales, sin alcanzar esa equivalencia frente a lo facturado, se ingresa hoy 04 de abril aprovechando la coyuntura del mercado debido al alza de arandeceles por parte EE.UU a sus socios comerciales que genero la devaluación del dolar y caida en las bolsas y se logro un valor de $ 4,265 . el valor que se pierde en esta transacción entre lo facturado y monetizado fue de 3% con un total de mesnos $ 2.187.228,13 Esta situación fue presentada al Director General durante la reunión mensual de revisión de flujos de caja, quien evaluó el escenario y determinó que, pese a la pérdida por diferencia en cambio, no había opción de alcanzar el valor de la divisa facturado , además de que existía una alta probabilidad de que los recursos tuvieran que ser devueltos al cliente. | Z86: =K86*O86 -> 25395260 | AA86: =Z86-Q86 -> -840514.63
B87: 56 | C87: Safeguard LTD Panamá | D87: 5418 | E87: 45709 | F87: 45769 | J87: =IFERROR(IF(TODAY()>=E87,(TODAY()-E87)/I87,0),0)*0 -> 0 | K87: 2634.12 | L87: 2634.12 | M87: =K87-L87 -> 0 | N87: 4344.55 | O87: =O86 -> 4265 | P87: =O87-N87 -> -79.55 | Q87: =K87*N87 -> 11444066 | R87: =L87*O87 -> 11234522 | S87: =R87-Q87 -> -209544.25 | T87: =IF(R87<= Q87,"No Monetizar","Monetizar") -> No Monetizar | V87: 45751 | W87: Alfonso Fonseca A | X87: Eduard Forero | Y87: Se ha decidido monetizar estas divisas a pesar de que el valor recibido está por debajo del monto facturado, considerando que la fecha límite para su devolución vencía el próximo Martes 22 de abril. Adicionalmente, al momento del cobro, la TRM se encontraba en $4,406,16, mientras que en la actualidad la divisa ha registrado disminuciones sustanciales, sin alcanzar esa equivalencia frente a lo facturado, se ingresa hoy 04 de abril aprovechando la coyuntura del mercado debido al alza de arandeceles por parte EE.UU a sus socios comerciales que genero la devaluación del dolar y caida en las bolsas y se logro un valor de $ 4,265 . el valor que se pierde en esta transacción entre lo facturado y monetizado fue de 3% con un total de mesnos $ 2.187.228,13 Esta situación fue presentada al Director General durante la reunión mensual de revisión de flujos de caja, quien evaluó el escenario y determinó que, pese a la pérdida por diferencia en cambio, no había opción de alcanzar el valor de la divisa facturado , además de que existía una alta probabilidad de que los recursos tuvieran que ser devueltos al cliente. | Z87: =K87*O87 -> 11234522 | AA87: =Z87-Q87 -> -209544.25
B88: 57 | C88: Safeguard LLC Payroll | D88: 5497 a 5508 | E88: 45709 | F88: 45769 | J88: =IFERROR(IF(TODAY()>=E88,(TODAY()-E88)/I88,0),0)*0 -> 0 | K88: 7836.92 | L88: =7836.92-10 -> 7826.92 | M88: =K88-L88 -> 10 | N88: 4406.16 | O88: 4266.5 | P88: =O88-N88 -> -139.66 | Q88: =K88*N88 -> 34530723 | R88: =L88*O88 -> 33393554 | S88: =R88-Q88 -> -1137169.2 | T88: =IF(R88<= Q88,"No Monetizar","Monetizar") -> No Monetizar | V88: 45751 | W88: Alfonso Fonseca A | X88: Eduard Forero | Y88: Se ha decidido monetizar estas divisas a pesar de que el valor recibido está por debajo del monto facturado, considerando que la fecha límite para su devolución vencía el próximo Martes 22 de abril. Adicionalmente, al momento del cobro, la TRM se encontraba en $4,406,16, mientras que en la actualidad la divisa ha registrado disminuciones sustanciales, sin alcanzar esa equivalencia frente a lo facturado, se ingresa hoy 04 de abril aprovechando la coyuntura del mercado debido al alza de arandeceles por parte EE.UU a sus socios comerciales que genero la devaluación del dolar y caida en las bolsas y se logro un valor de $ 4,265 . el valor que se pierde en esta transacción entre lo facturado y monetizado fue de 3% con un total de mesnos $ 2.187.228,13 Esta situación fue presentada al Director General durante la reunión mensual de revisión de flujos de caja, quien evaluó el escenario y determinó que, pese a la pérdida por diferencia en cambio, no había opción de alcanzar el valor de la divisa facturado , además de que existía una alta probabilidad de que los recursos tuvieran que ser devueltos al cliente. | Z88: =K88*O88 -> 33436219 | AA88: =Z88-Q88 -> -1094504.2
B89: 58 | C89: Global Project | D89: 5679 | E89: 45742 | F89: 45802 | J89: =IFERROR(IF(TODAY()>=E89,(TODAY()-E89)/I89,0),0) -> 0 | K89: 650 | L89: 645 | M89: =K89-L89 -> 5 | N89: 4150 | O89: 4273.3 | P89: =O89-N89 -> 123.3 | Q89: =K89*N89 -> 2697500 | R89: =L89*O89 -> 2756278.5 | S89: =R89-Q89 -> 58778.5 | T89: =IF(R89<= Q89,"No Monetizar","Monetizar") -> Monetizar | V89: 45751 | W89: Alfonso Fonseca A | X89: Alfonso Fonseca A | Y89: Se monetiza ya que el valor ofrecido por el banco en cada divisa es superior al valor facturado | Z89: =K89*O89 -> 2777645 | AA89: =Z89-Q89 -> 80145
B90: 59 | C90: Safeguard LTD Payroll | D90: 5610 a la 5614 | E90: 45723 | F90: 45783 | J90: =IFERROR(IF(TODAY()>=E90,(TODAY()-E90)/I90,0),0) -> 0 | K90: 6572.35 | L90: 6572.35 | M90: =K90-L90 -> 0 | N90: 4375.86 | O90: 4397.02 | P90: =O90-N90 -> 21.16 | Q90: =K90*N90 -> 28759683 | R90: =L90*O90 -> 28898754 | S90: =R90-Q90 -> 139070.93 | T90: =IF(R90<= Q90,"No Monetizar","Monetizar") -> Monetizar | V90: 45754 | W90: Alfonso Fonseca A | X90: Alfonso Fonseca A | Y90: Se monetiza ya que el valor ofrecido por el banco en cada divisa es superior al valor facturado | Z90: =K90*O90 -> 28898754 | AA90: =Z90-Q90 -> 139070.93
B91: 60 | C91: Global Project | D91: 5616 | E91: 45728 | F91: 45788 | J91: =IFERROR(IF(TODAY()>=E91,(TODAY()-E91)/I91,0),0) -> 0 | K91: 1927.79 | L91: =1927.79-5 -> 1922.79 | M91: =K91-L91 -> 5 | N91: 4401.98 | O91: 4417.43 | P91: =O91-N91 -> 15.45 | Q91: =K91*N91 -> 8486093 | R91: =L91*O91 -> 8493790.2 | S91: =R91-Q91 -> 7697.2055 | T91: =IF(R91<= Q91,"No Monetizar","Monetizar") -> Monetizar | V91: 45756 | W91: Alfonso Fonseca A | X91: Alfonso Fonseca A | Y91: Se monetiza ya que el valor ofrecido por el banco en cada divisa es superior al valor facturado | Z91: =K91*O91 -> 8515877.4 | AA91: =Z91-Q91 -> 29784.356
B92: 61 | C92: Global Project | D92: 5634 | E92: 45728 | F92: 45788 | J92: =IFERROR(IF(TODAY()>=E92,(TODAY()-E92)/I92,0),0) -> 0 | K92: 1405.81 | L92: =1405.81-5 -> 1400.81 | M92: =K92-L92 -> 5 | N92: 4401.98 | O92: =O91 -> 4417.43 | P92: =O92-N92 -> 15.45 | Q92: =K92*N92 -> 6188347.5 | R92: =L92*O92 -> 6187980.1 | S92: =R92-Q92 -> -367.3855 | T92: =IF(R92<= Q92,"No Monetizar","Monetizar") -> No Monetizar | V92: 45756 | W92: Alfonso Fonseca A | X92: Alfonso Fonseca A | Y92: Se monetiza ya que el valor ofrecido por el banco en cada divisa es superior al valor facturado | Z92: =K92*O92 -> 6210067.3 | AA92: =Z92-Q92 -> 21719.765
B93: 62 | C93: Hemmebarsch GMBH & Co KG | D93: 5773 | E93: 45758 | F93: 45818 | J93: =IFERROR(IF(TODAY()>=E93,(TODAY()-E93)/I93,0),0)*0 -> 0 | K93: 1860.99 | L93: 1860.99 | M93: =K93-L93 -> 0 | N93: 4010.08 | O93: 4333 | P93: =O93-N93 -> 322.92 | Q93: =K93*N93 -> 7462718.8 | R93: =L93*O93 -> 8063669.7 | S93: =R93-Q93 -> 600950.89 | T93: =IF(R93<= Q93,"No Monetizar","Monetizar") -> Monetizar | V93: 45758 | W93: Alfonso Fonseca A | X93: Alfonso Fonseca A | Y93: Se monetiza ya que el valor ofrecido por el banco en cada divisa es superior al valor facturado | Z93: =K93*O93 -> 8063669.7 | AA93: =Z93-Q93 -> 600950.89
B94: 63 | C94: Action AD | D94: 5848 | E94: 45761 | F94: 45821 | J94: =IFERROR(IF(TODAY()>=E94,(TODAY()-E94)/I94,0),0)*0 -> 0 | K94: 3028.43 | L94: 3028.43 | M94: =K94-L94 -> 0 | N94: 4316.69 | O94: 4325 | P94: =O94-N94 -> 8.31 | Q94: =K94*N94 -> 13072793 | R94: =L94*O94 -> 13097960 | S94: =R94-Q94 -> 25166.253 | T94: =IF(R94<= Q94,"No Monetizar","Monetizar") -> Monetizar | V94: 45762 | W94: Alfonso Fonseca A | X94: Alfonso Fonseca A | Y94: Se monetiza ya que el valor ofrecido por el banco en cada divisa es superior al valor facturado | Z94: =K94*O94 -> 13097960 | AA94: =Z94-Q94 -> 25166.253
B95: 64 | C95: Global Project | D95: 5737 | E95: 45762 | F95: 45822 | J95: =IFERROR(IF(TODAY()>=E95,(TODAY()-E95)/I95,0),0)*0 -> 0 | K95: 2725.4 | L95: 2715.4 | M95: =K95-L95 -> 10 | N95: 4123.1 | O95: 4335 | P95: =O95-N95 -> 211.9 | Q95: =K95*N95 -> 11237097 | R95: =L95*O95 -> 11771259 | S95: =R95-Q95 -> 534162.26 | T95: =IF(R95<= Q95,"No Monetizar","Monetizar") -> Monetizar | V95: 45762 | W95: Alfonso Fonseca A | X95: Alfonso Fonseca A | Y95: Se monetiza ya que el valor ofrecido por el banco en cada divisa es superior al valor facturado | Z95: =K95*O95 -> 11814609 | AA95: =Z95-Q95 -> 577512.26
B96: 65 | C96: Hemmebarsch GMBH & Co KG | D96: 5714 | E96: 45763 | F96: 45823 | J96: =IFERROR(IF(TODAY()>=E96,(TODAY()-E96)/I96,0),0)*0 -> 0 | K96: 2596.03 | L96: 2596.03 | M96: =K96-L96 -> 0 | N96: 3865.07 | O96: 4272 | P96: =O96-N96 -> 406.93 | Q96: =K96*N96 -> 10033838 | R96: =L96*O96 -> 11090240 | S96: =R96-Q96 -> 1056402.5 | T96: =IF(R96<= Q96,"No Monetizar","Monetizar") -> Monetizar | V96: 45762 | W96: Alfonso Fonseca A | X96: Alfonso Fonseca A | Y96: Se monetiza ya que el valor ofrecido por el banco en cada divisa es superior al valor facturado | Z96: =K96*O96 -> 11090240 | AA96: =Z96-Q96 -> 1056402.5
B97: 66 | C97: Remofisrt | D97: 5835 | E97: 45764 | F97: 45824 | J97: =IFERROR(IF(TODAY()>=E97,(TODAY()-E97)/I97,0),0)*0 -> 0 | K97: 15689.99 | L97: 15689.99 | M97: =K97-L97 -> 0 | N97: 4029.24 | O97: 4247.56 | P97: =O97-N97 -> 218.32 | Q97: =K97*N97 -> 63218735 | R97: =L97*O97 -> 66644174 | S97: =R97-Q97 -> 3425438.6 | T97: =IF(R97<= Q97,"No Monetizar","Monetizar") -> Monetizar | V97: 45768 | W97: Alfonso Fonseca A | X97: Alfonso Fonseca A | Y97: Se monetiza ya que el valor ofrecido por el banco en cada divisa es superior al valor facturado | Z97: =K97*O97 -> 66644174 | AA97: =Z97-Q97 -> 3425438.6
B98: 67 | C98: Remofisrt | D98: 5836 | E98: 45764 | F98: 45824 | J98: =IFERROR(IF(TODAY()>=E98,(TODAY()-E98)/I98,0),0)*0 -> 0 | K98: 264.97 | L98: 264.97 | M98: =K98-L98 -> 0 | N98: 4029.24 | O98: 4247.56 | P98: =O98-N98 -> 218.32 | Q98: =K98*N98 -> 1067627.7 | R98: =L98*O98 -> 1125476 | S98: =R98-Q98 -> 57848.25 | T98: =IF(R98<= Q98,"No Monetizar","Monetizar") -> Monetizar | V98: 45768 | W98: Alfonso Fonseca A | X98: Alfonso Fonseca A | Y98: Se monetiza ya que el valor ofrecido por el banco en cada divisa es superior al valor facturado | Z98: =K98*O98 -> 1125476 | AA98: =Z98-Q98 -> 57848.25
B99: 68 | C99: Flexco | D99: 5860 | E99: 45765 | F99: 45825 | J99: =IFERROR(IF(TODAY()>=E99,(TODAY()-E99)/I99,0),0)*0 -> 0 | K99: 11210.98 | L99: 11195.98 | M99: =K99-L99 -> 15 | N99: 4186.17 | O99: 4249.01 | P99: =O99-N99 -> 62.84 | Q99: =K99*N99 -> 46931068 | R99: =L99*O99 -> 47571831 | S99: =R99-Q99 -> 640762.83 | T99: =IF(R99<= Q99,"No Monetizar","Monetizar") -> Monetizar | V99: 45768 | W99: Alfonso Fonseca A | X99: Alfonso Fonseca A | Y99: Se monetiza ya que el valor ofrecido por el banco en cada divisa es superior al valor facturado | Z99: =K99*O99 -> 47635566 | AA99: =Z99-Q99 -> 704497.98
B100: 69 | C100: Advantage | D100: 5837 | E100: 45765 | F100: 45825 | J100: =IFERROR(IF(TODAY()>=E100,(TODAY()-E100)/I100,0),0)*0 -> 0 | K100: 775.77 | L100: 775.77 | M100: =K100-L100 -> 0 | N100: 4049.24 | O100: 4253.5 | P100: =O100-N100 -> 204.26 | Q100: =K100*N100 -> 3141278.9 | R100: =L100*O100 -> 3299737.7 | S100: =R100-Q100 -> 158458.78 | T100: =IF(R100<= Q100,"No Monetizar","Monetizar") -> Monetizar | V100: 45768 | W100: Alfonso Fonseca A | X100: Alfonso Fonseca A | Y100: Se monetiza ya que el valor ofrecido por el banco en cada divisa es superior al valor facturado | Z100: =K100*O100 -> 3299737.7 | AA100: =Z100-Q100 -> 158458.78
B101: 70 | C101: Marketing Doctors | D101: 5859 | E101: 45768 | F101: 45828 | J101: =IFERROR(IF(TODAY()>=E101,(TODAY()-E101)/I101,0),0)*0 -> 0 | K101: 2410.68 | L101: 2410.68 | M101: =K101-L101 -> 0 | N101: 4186.17 | O101: 4273.91 | P101: =O101-N101 -> 87.74 | Q101: =K101*N101 -> 10091516 | R101: =L101*O101 -> 10303029 | S101: =R101-Q101 -> 211513.06 | T101: =IF(R101<= Q101,"No Monetizar","Monetizar") -> Monetizar | V101: 45769 | W101: Alfonso Fonseca A | X101: Alfonso Fonseca A | Y101: Se monetiza ya que el valor ofrecido por el banco en cada divisa es superior al valor facturado | Z101: =K101*O101 -> 10303029 | AA101: =Z101-Q101 -> 211513.06
B102: 71 | C102: Remofisrt | D102: 5833 | E102: 45768 | F102: 45828 | J102: =IFERROR(IF(TODAY()>=E102,(TODAY()-E102)/I102,0),0)*0 -> 0 | K102: =7876.1-827.72 -> 7048.38 | L102: 7048.38 | M102: =K102-L102 -> 0 | N102: 3996.8 | O102: 4273.91 | P102: =O102-N102 -> 277.11 | Q102: =K102*N102 -> 28170965 | R102: =L102*O102 -> 30124142 | S102: =R102-Q102 -> 1953176.6 | T102: =IF(R102<= Q102,"No Monetizar","Monetizar") -> Monetizar | V102: 45769 | W102: Alfonso Fonseca A | X102: Alfonso Fonseca A | Y102: Se monetiza ya que el valor ofrecido por el banco en cada divisa es superior al valor facturado | Z102: =K102*O102 -> 30124142 | AA102: =Z102-Q102 -> 1953176.6
B103: 72 | C103: Safeguard LLC Payroll | D103: 5658 a la 5669 | E103: 45768 | F103: 45828 | J103: =IFERROR(IF(TODAY()>=E103,(TODAY()-E103)/I103,0),0)*0 -> 0 | K103: 22529.6 | L103: 22514.6 | M103: =K103-L103 -> 15 | N103: 4170.01 | O103: 4278.2 | P103: =O103-N103 -> 108.19 | Q103: =K103*N103 -> 93948657 | R103: =L103*O103 -> 96321962 | S103: =R103-Q103 -> 2373304.4 | T103: =IF(R103<= Q103,"No Monetizar","Monetizar") -> Monetizar | V103: 45769 | W103: Alfonso Fonseca A | X103: Alfonso Fonseca A | Y103: Se monetiza ya que el valor ofrecido por el banco en cada divisa es superior al valor facturado | Z103: =K103*O103 -> 96386135 | AA103: =Z103-Q103 -> 2437477.4
B104: 73 | C104: Safeguard LTD Payroll | D104: 5670 a la 5674 | E104: 45768 | F104: 45828 | J104: =IFERROR(IF(TODAY()>=E104,(TODAY()-E104)/I104,0),0)*0 -> 0 | K104: 19607.61 | L104: 19607.61 | M104: =K104-L104 -> 0 | N104: 4170.01 | O104: 4278.2 | P104: =O104-N104 -> 108.19 | Q104: =K104*N104 -> 81763930 | R104: =L104*O104 -> 83885277 | S104: =R104-Q104 -> 2121347.3 | T104: =IF(R104<= Q104,"No Monetizar","Monetizar") -> Monetizar | V104: 45769 | W104: Alfonso Fonseca A | X104: Alfonso Fonseca A | Y104: Se monetiza ya que el valor ofrecido por el banco en cada divisa es superior al valor facturado | Z104: =K104*O104 -> 83885277 | AA104: =Z104-Q104 -> 2121347.3
B105: 74 | C105: Remofisrt | D105: 5850 | E105: 45770 | F105: 45830 | J105: =IFERROR(IF(TODAY()>=E105,(TODAY()-E105)/I105,0),0)*0 -> 0 | K105: 198689.68 | L105: 198689.68 | M105: =K105-L105 -> 0 | N105: 4237 | O105: 4286.2 | P105: =O105-N105 -> 49.2 | Q105: =K105*N105 -> 8.4184817e+08 | R105: =L105*O105 -> 8.5162371e+08 | S105: =R105-Q105 -> 9775532.3 | T105: =IF(R105<= Q105,"No Monetizar","Monetizar") -> Monetizar | V105: 45770 | W105: Alfonso Fonseca A | X105: Alfonso Fonseca A | Y105: Se monetiza ya que el valor ofrecido por el banco en cada divisa es superior al valor facturado | Z105: =K105*O105 -> 8.5162371e+08 | AA105: =Z105-Q105 -> 9775532.3
...

Sheet DISTRIBUCIÓN (2)
H1: Sin Pagar | I1: Cancelado
B2: Distribución de dinero
B4: Semana | C4: Fecha Inicial | D4: Fecha Final | E4: Descripción | F4: Valor | H4: Sin pagar | I4: Cancelado | J4: Total
B5: 1 | C5: 45992 | D5: 45999 | E5: Pagos a Realizar | F5: =SUMIFS(DICIEMBRE!$E$115:$E$1613,DICIEMBRE!$F$115:$F$1613,">="&C5,DICIEMBRE!$F$115:$F$1613,"<="&D5,DICIEMBRE!$G$115:$G$1613,$H$1) -> 0 | G5: Proveedores
B6: 2 | C6: 46000 | D6: 46002 | E6: Pagos a Realizar | F6: =SUMIFS(DICIEMBRE!$E$115:$E$1613,DICIEMBRE!$F$115:$F$1613,">="&C6,DICIEMBRE!$F$115:$F$1613,"<="&D6,DICIEMBRE!$G$115:$G$1613,$H$1) -> 0 | G6: Proveedores | H6: =SUMIFS(DICIEMBRE!$E$115:$E$1613,DICIEMBRE!$F$115:$F$1613,">="&C5,DICIEMBRE!$F$115:$F$1613,"<="&$D$15,DICIEMBRE!$G$115:$G$1613,$H$1) -> 0 | I6: =SUMIFS(DICIEMBRE!$E$115:$E$1613,DICIEMBRE!$F$115:$F$1613,">="&C5,DICIEMBRE!$F$115:$F$1613,"<="&$D$15,DICIEMBRE!$G$115:$G$1613,$I$1) -> 2.8215259e+09 | J6: =SUM(H6:I6) -> 2.8215259e+09 | L6: =J6-#REF! -> #REF!
B7: 3 | C7: 46003 | D7: 46003 | E7: Pagos a Realizar | F7: =SUMIFS(DICIEMBRE!$E$115:$E$1613,DICIEMBRE!$F$115:$F$1613,">="&C7,DICIEMBRE!$F$115:$F$1613,"<="&D7,DICIEMBRE!$G$115:$G$1613,$H$1) -> 0 | G7: Seguridad social-Anticipo nómina Nazdar y Action
B8: 4 | C8: 46004 | D8: 46005 | E8: Pagos a Realizar | F8: =SUMIFS(DICIEMBRE!$E$115:$E$1613,DICIEMBRE!$F$115:$F$1613,">="&C8,DICIEMBRE!$F$115:$F$1613,"<="&D8,DICIEMBRE!$G$115:$G$1613,$H$1) -> 0 | I8: Comprobación | J8: =DICIEMBRE!E325 -> 2.8872815e+09
B9: 5 | C9: 46006 | D9: 46006 | E9: Pagos a Realizar | F9: =SUMIFS(DICIEMBRE!$E$115:$E$1613,DICIEMBRE!$F$115:$F$1613,">="&C9,DICIEMBRE!$F$115:$F$1613,"<="&D9,DICIEMBRE!$G$115:$G$1613,$H$1) -> 0 | G9: Primas EOR-S&P y Nómina Time Resort
C10: 46007 | D10: 46007 | E10: Pagos a Realizar | F10: =SUMIFS(DICIEMBRE!$E$115:$E$1613,DICIEMBRE!$F$115:$F$1613,">="&C10,DICIEMBRE!$F$115:$F$1613,"<="&D10,DICIEMBRE!$G$115:$G$1613,$H$1) -> 0 | G10: Impuestos Nacionales-TC Endrington
B11: 6 | C11: 46008 | D11: 46012 | E11: Pagos a Realizar | F11: =SUMIFS(DICIEMBRE!$E$115:$E$1613,DICIEMBRE!$F$115:$F$1613,">="&C11,DICIEMBRE!$F$115:$F$1613,"<="&D11,DICIEMBRE!$G$115:$G$1613,$H$1) -> 0
B12: 7 | C12: 46013 | D12: 46016 | E12: Pagos a Realizar | F12: =SUMIFS(DICIEMBRE!$E$115:$E$1613,DICIEMBRE!$F$115:$F$1613,">="&C12,DICIEMBRE!$F$115:$F$1613,"<="&D12,DICIEMBRE!$G$115:$G$1613,$H$1) -> 0 | G12: Proveedores
B13: 8 | C13: 46017 | D13: 46017 | E13: Pagos a Realizar | F13: =SUMIFS(DICIEMBRE!$E$115:$E$1613,DICIEMBRE!$F$115:$F$1613,">="&C13,DICIEMBRE!$F$115:$F$1613,"<="&D13,DICIEMBRE!$G$115:$G$1613,$H$1) -> 0 | G13: Nómina-Pagos a tercero-Proveedores
B14: 9 | C14: 46018 | D14: 46019 | E14: Pagos a Realizar | F14: =SUMIFS(DICIEMBRE!$E$115:$E$1613,DICIEMBRE!$F$115:$F$1613,">="&C14,DICIEMBRE!$F$115:$F$1613,"<="&D14,DICIEMBRE!$G$115:$G$1613,$H$1) -> 0
B15: 10 | C15: 46020 | D15: 46022 | E15: Pagos a Realizar | F15: =SUMIFS(DICIEMBRE!$E$115:$E$1613,DICIEMBRE!$F$115:$F$1613,">="&C15,DICIEMBRE!$F$115:$F$1613,"<="&D15,DICIEMBRE!$G$115:$G$1613,$H$1) -> 0 | G15: Proveedores
B16: TOTAL | F16: =SUM(F5:F15) -> 0
E18: Escenario 1
E19: Gastos y costos Periodo 01 al 17 Diciembre | F19: =SUM($F$5:$F$11) -> 0
E20: 4 X mil | F20: =($F$19*4)/1000 -> 0
E21: Total | F21: =SUM(F19:F20) -> 0
E23: Bancos | F23: =DICIEMBRE!$E$343 -> 1.0574441e+09
E24: Action AD | F24: 13000000
E25: Safeguard -Endrington-Noviembre | F25: ='MONETIZACIONES PEND'!#REF!*3700 -> #REF!
E26: Safeguard por identificar servicios de centro américa | F26: =('MONETIZACIONES PEND'!#REF!)*3700 -> #REF!
E27: Safeguard LTD x identificar | F27: =('MONETIZACIONES PEND'!#REF!)*3700 -> #REF!
E28: Global Project | F28: ='MONETIZACIONES PEND'!#REF!*3700 -> #REF!
E29: Remofirst | F29: ='MONETIZACIONES PEND'!#REF!*3700 -> #REF!
E30: Global CS Colombia SAS factura # 5-61 Reembolso Celulares | F30: 359994
E31: Global CS Colombia SAS -Solutions & payroll-Servicio Noviembre 2025 Factura 2-257 | F31: 19334755
E32: Clientes nacionales | F32: =DICIEMBRE!$E$14+DICIEMBRE!$E$15+DICIEMBRE!$E$26+DICIEMBRE!$E$24+DICIEMBRE!$E$29+DICIEMBRE!$E$30+DICIEMBRE!$E$47+DICIEMBRE!$E$57 -> 72533124
E33: Safeguard Payroll | F33: =SUM(DICIEMBRE!$E$51:$E$53) -> 0
E34: Insider | F34: =DICIEMBRE!$E$85 -> 1.4449483e+08
E35: Sobregiro | F35: 0
E36: Total | F36: =SUM(F23:F35) -> #REF!
E37: Saldo | F37: =F36-$F$21 -> #REF!
E39: Escenario 2
E41: Gastos y costos Periodo 01 al 17 Diciembre | F41: =SUM($F$5:$F$11)-DICIEMBRE!$E$267 -> -144223182
E42: 4 X mil | F42: =($F$19*4)/1000 -> 0
E43: Total | F43: =SUM(F41:F42) -> -144223182
E45: Bancos | F45: =DICIEMBRE!$E$343 -> 1.0574441e+09
E46: Action AD | F46: 13000000
E47: Safeguard -Endrington-Noviembre | F47: ='MONETIZACIONES PEND'!#REF!*3700 -> #REF!
E48: Safeguard por identificar servicios de centro américa | F48: =('MONETIZACIONES PEND'!#REF!)*3700 -> #REF!
E49: Safeguard LTD x identificar | F49: =('MONETIZACIONES PEND'!#REF!)*3700 -> #REF!
E50: Global Project | F50: ='MONETIZACIONES PEND'!#REF!*3700 -> #REF!
E51: Remofirst | F51: ='MONETIZACIONES PEND'!#REF!*3700 -> #REF!
E52: Global CS Colombia SAS factura # 5-61 Reembolso Celulares | F52: 359994
E53: Global CS Colombia SAS -Solutions & payroll-Servicio Noviembre 2025 Factura 2-257 | F53: 19334755
E54: Clientes nacionales | F54: =DICIEMBRE!$E$14+DICIEMBRE!$E$15+DICIEMBRE!$E$26+DICIEMBRE!$E$24+DICIEMBRE!$E$29+DICIEMBRE!$E$30+DICIEMBRE!$E$47+DICIEMBRE!$E$57 -> 72533124
E55: Safeguard Payroll | F55: =SUM(DICIEMBRE!$E$51:$E$53)*0 -> 0
E56: Insider | F56: =DICIEMBRE!$E$85*0 -> 0
E57: Sobregiro | F57: 0
E58: Total | F58: =SUM(F45:F57) -> #REF!
E59: Saldo | F59: =F58-$F$43 -> #REF!
E67: FORECAST DICIEMBRE 2025 | H67: FORECAST ENERO 2026 | L67: FORECAST FEBRERO 2026
E69: INGRESO | F69: =SUBTOTAL(9,F70:F77) -> #REF! | H69: INGRESO | I69: =SUBTOTAL(9,I70:I76) -> #REF! | L69: INGRESO | M69: =SUBTOTAL(9,M70:M76) -> #REF!
E70: Bancos Valor previsto | F70: =#REF! -> #REF! | H70: Bancos Valor previsto | I70: =DICIEMBRE!E327 -> #REF! | L70: Bancos Valor previsto | M70: =$I$141 -> #REF!
E71: Ingreso previsto por EOR | F71: =#REF!*1.7 -> #REF! | H71: Safeguard LTD y LTD Payroll -Octubre | I71: 65083860 | J71: 1 | L71: Safeguard LTD y LTD Payroll -Noviembre | M71: 67000000 | N71: 1
E72: Safeguard LTD y LTD Payroll -Septiembre | F72: 63738691 | G72: =F70+F72+F73+F74+F75+F76 -> #REF! | H72: Action XXXX | I72: 13628765 | L72: Action XXXX | M72: 13628765
E73: Action XXXX | F73: 14000000 | H73: Clientes nacionales Previsto -Global Project | I73: 45000000 | L73: Clientes nacionales Previsto -Global Project | M73: 52000000
E74: Clientes nacionales Previsto -Global Project | F74: 50000000 | H74: Global CS Colombia | I74: 19000000 | L74: Global CS Colombia | M74: 20000000
E75: Global CS Colombia | F75: 19000000 | H75: Intereses PM | I75: 2670000 | L75: Intereses PM | M75: 2670000
E76: Intereses PM | F76: 2670000 | H76: Sobregiro | I76: 0 | L76: Sobregiro | M76: 0
E77: Sobregiro | F77: 0 | H77: PAGOS DEL 1 AL 24 ENERO | I77: =SUM(I78:I111) -> 1.0880895e+09 | L77: PAGOS DEL 1 AL 23 FEBRERO | M77: =SUM(M78:M108) -> 1.2257233e+09
E78: PAGOS DEL 1 AL 20 DICIEMBRE | F78: =SUM(F79:F111) -> 1.3927691e+09 | H78: Anticipo nómina Action-primer anticipo | I78: 3701569 | L78: Anticipo nómina Action-primer anticipo | M78: 3701569
E79: Anticipo nómina Action-primer anticipo | F79: 3701569 | H79: Anticipo nómina Nazdar | I79: =9500000 -> 9500000 | L79: Anticipo nómina Nazdar | M79: =9500000 -> 9500000
E80: Anticipo nómina Nazdar | F80: =9500000 -> 9500000 | H80: Intereses de cesantías | I80: =20000000 -> 20000000 | L80: Cesantías EOR | M80: =336000000*1.05 -> 352800000
E81: Plan complementario compensar | F81: 525000 | G81: =SUM(F79:F88,F92:F109) -> 8.0429095e+08 | H81: Plan complementario compensar | I81: 525000 | L81: Cesantías S&P | M81: =99000000*1.07 -> 105930000
E82: Seguridad social | F82: 535600000 | H82: Seguridad social | I82: 540750000 | L82: Plan complementario compensar | M82: 525000
E83: RETENCIÓN EN LA FUENTE | F83: 183855000 | H83: RETENCIÓN EN LA FUENTE | I83: 150000000 | L83: Seguridad social | M83: 550000000
E84: Retención de IVA | F84: 227114.12 | G84: =F70-G81 -> #REF! | H84: Retención de IVA | I84: 218000 | L84: RETENCIÓN EN LA FUENTE | M84: 145000000
E85: Movistar 365 | F85: 350601 | H85: IVA | I85: =77531000*1.08 -> 83733480 | L85: Retención de IVA | M85: 225000
E86: Poliza Suramericana Póliza # 091000808492 | F86: 7293422 | G86: =G72-F78 -> #REF! | H86: RETENCIÓN EN LA FUENTE | I86: 220626000 | L86: Movistar 365 | M86: 350601
E87: Poliza Suramericana Póliza # 083004098664 | F87: 697487 | H87: Retención de IVA | I87: 686400 | L87: Poliza Suramericana Póliza # 091000808492 | M87: 7293422
E88: Servicio de mensajería | F88: 700000 | H88: RTE ICA ( cada dos meses) | I88: 855750 | L88: Poliza Suramericana Póliza # 083004098664 | M88: 437488
E89: Barrera Palacios | F89: 1693965 | H89: Movistar 365 | I89: 350601 | L89: Servicio de mensajería | M89: 500000
E90: Primas EOR | F90: 500000000 | G90: 150000000 | H90: Poliza Suramericana Póliza # 091000808492 | I90: 7293422 | L90: WORKPLACE SOLUTIONS GROUP SAS (SPACIO) | M90: 313593.5
E91: Primas S&P | F91: =F127*35% -> 61250000 | G91: =F90-G90 -> 350000000 | H91: Poliza Suramericana Póliza # 083004098664 | I91: 437488 | L91: TC Bancolombia S&P | M91: 5000000
E92: WORKPLACE SOLUTIONS GROUP SAS (SPACIO) | F92: 313593.5 | H92: Servicio de mensajería | I92: 500000 | L92: TC Bancolombia-Ramon Esteban Cardona Salazar | M92: 15000000
E93: TC Bancolombia S&P | F93: 5000000 | H93: WORKPLACE SOLUTIONS GROUP SAS (SPACIO) | I93: 313593.5 | L93: Anticipo nómina Action-Segundo anticipo | M93: 4853442
E94: TC Bancolombia-Ramon Esteban Cardona Salazar | F94: 15000000 | H94: TC Bancolombia S&P | I94: 5000000 | L94: Rafael Mier | M94: 170000
E95: Anticipo nómina Action-Segundo anticipo | F95: 4853442 | H95: TC Bancolombia-Ramon Esteban Cardona Salazar | I95: 15000000 | L95: Plan complementario Suramericana | M95: 752141
E96: Rafael Mier | F96: 170000 | H96: Anticipo nómina Action-Segundo anticipo | I96: 4853442 | L96: Allianz | M96: 723370
E97: Simbolo Group | F97: 2376000 | H97: Rafael Mier | I97: 170000 | L97: Reembolsos Saipem | M97: 650000
E98: Plan complementario Suramericana | F98: 752141 | H98: Plan complementario Suramericana | I98: 752141 | L98: Exámenes médicos Saipem | M98: 1200000
E99: Reembolsos Saipem | F99: 2000000 | H99: Allianz | I99: 723370 | L99: Tiquetes y hoteles Saipem | M99: 1500000
E100: Exámenes médicos Saipem | F100: 17500000 | H100: Reembolsos Saipem | I100: 650000 | L100: Yoana Forero Servicios Costa Rica | M100: 774025
E101: Tiquetes y hoteles Saipem | F101: 4000000 | H101: Exámenes médicos Saipem | I101: 1200000 | L101: Cuentas de cobro Eduard Forero | M101: =1287442*2 -> 2574884
E102: Yoana Forero Servicios Costa Rica | F102: 774025 | H102: Tiquetes y hoteles Saipem | I102: 1500000 | L102: Cuentas de cobro William Romero | M102: 640000
E103: Cuentas de cobro Eduard Forero | F103: =1287442*2 -> 2574884 | H103: Yoana Forero Servicios Costa Rica | I103: 774025 | L103: Analia Lorena Di Nicola | M103: 475363
E104: Cuentas de cobro William Romero | F104: 640000 | H104: Cuentas de cobro Eduard Forero | I104: =1287442*2 -> 2574884 | L104: Emasoc | M104: 1500000
E105: Analia Lorena Di Nicola | F105: 475363 | H105: Cuentas de cobro William Romero | I105: 640000 | L105: Praxedes nómina electrónica | M105: 450000
E106: Emasoc | F106: 1200000 | H106: Analia Lorena Di Nicola | I106: 475363 | L106: Praxedes | M106: 3000000
E107: Praxedes nómina electrónica | F107: 450000 | H107: Emasoc | I107: 1500000 | L107: Imprevisto | M107: 5000000
E108: Innovate SAS | F108: 761310 | H108: Praxedes nómina electrónica | I108: 450000 | L108: 4 X mil transacciones | M108: =N108 -> 4883359.6 | N108: =(SUM(M78:M107)*4/1000) -> 4883359.6
E109: Praxedes | F109: 3000000 | H109: Praxedes | I109: 3000000 | L109: Diferencia | M109: =M69-M77 -> #REF!
E110: Imprevisto | F110: 20000000 | H110: Imprevisto | I110: 5000000
E111: 4 X mil transacciones | F111: =G111 -> 5534133.4 | G111: =(SUM(F80:F110)*4/1000) -> 5534133.4 | H111: 4 X mil transacciones | I111: =J112 -> 4335018.1 | L111: Ingreso previsto por EOR | M111: 2600000000
E112: Diferencia | F112: =F69-F78 -> #REF! | H112: Diferencia | I112: =I69-I77 -> #REF! | J112: =(SUM(I78:I110)*4/1000) -> 4335018.1 | L112: Total | M112: =SUM(M109:M111) -> #REF!
E114: Total | F114: =SUM(F112:F113) -> #REF! | H114: Ingreso previsto por EOR | I114: 2400000000 | L114: PAGOS DEL 24 AL 28 FEBRERO | M114: =SUM(M115:M137) -> 1.7711427e+09
H115: Total | I115: =SUM(I112:I114) -> #REF! | L115: AFC OE | M115: 16800500
...

Sheet Balanza DF
D3: Concepto | E3: Ene | F3: Feb | G3: Marzo | H3: Abril | I3: Mayo | J3: Junio | K3: Julio | L3: Agosto | M3: Septiembre | N3: Octubre | O3: Noviembre | P3: Diciembre | Q3: Acumulado
C4: 421020 | D4: Diferencia en cambio ( Ingreso) | E4: 26960712 | F4: 93771698 | G4: 57438103 | H4: =#REF!+#REF!+#REF!+#REF!+#REF!+#REF!+#REF!+#REF!+#REF!+#REF!+#REF!+#REF!+#REF!+#REF!+#REF!+#REF!+#REF!+#REF!+#REF!+#REF!+#REF!+#REF! -> #REF! | Q4: =SUM(E4:P4) -> #REF!
C5: 530525 | D5: Diferencia en cambio ( Gasto) | E5: 19562974 | F5: 6983301 | G5: 1320422 | H5: 2775771 | Q5: =SUM(E5:P5) -> 30642468
D6: Balanza 25 | E6: =E4-E5 -> 7397737.6 | F6: =F4-F5 -> 86788397 | G6: =G4-G5 -> 56117681 | H6: =H4-H5 -> #REF! | I6: =I4-I5 -> 0 | J6: =J4-J5 -> 0 | K6: =K4-K5 -> 0 | L6: =L4-L5 -> 0 | ... Q6: =Q4-Q5 -> #REF!
D8: Diferencia en cambio ( Ingreso) | E8: 20456548 | F8: 20805960 | G8: 2493777 | H8: 52141246 | Q8: =SUM(E8:P8) -> 95897531
D9: Diferencia en cambio ( Gasto) | E9: 593328 | F9: 9336021.7 | G9: 12371550 | H9: 1819382.6 | Q9: =SUM(E9:P9) -> 24120282
D10: Balanza 24 | E10: =E8-E9 -> 19863220 | F10: =F8-F9 -> 11469938 | G10: =G8-G9 -> -9877772.7 | H10: =H8-H9 -> 50321864 | I10: =I8-I9 -> 0 | J10: =J8-J9 -> 0 | K10: =K8-K9 -> 0 | L10: =L8-L9 -> 0 | ... Q10: =Q8-Q9 -> 71777249

Sheet Hoja2
B2: Seguridad social | E2: Retención en la fuente
B3: Enero | C3: 326365300 | E3: Enero | F3: 132004000
B4: Febrero | C4: 366144100 | E4: Febrero | F4: 114838000
B5: Marzo | C5: 336362300 | E5: Marzo | F5: 122963000
B6: Abril | C6: 356100200 | E6: Abril | F6: 121740150
B7: Total | C7: =AVERAGE(C3:C6) -> 346242975 | E7: Total | F7: =AVERAGE(F3:F6) -> 1.2288629e+08

Sheet Análisis
B2: Semana | C2: Fecha Inicial | D2: Fecha Final | E2: Descripción | F2: Valor
B3: 1 | C3: 45689 | D3: 45697 | E3: Proveedores | F3: 4927863.5
B4: 2 | C4: 45698 | D4: 45701 | E4: SS-Movistar | F4: 366472412
B5: 2 | C5: 45702 | D5: 45702 | E5: Cesantías-Anticipo NZD ACT | F5: 497926761
B6: 4 | C6: 45705 | D6: 45711 | E6: RTE FTE-TC Endrington-Proveedores | F6: 151400713
B7: SUBTOTAL | F7: =SUM(F3:F6) -> 1.0207277e+09
B8: 4 x MIL | F8: =(F7*4)/1000 -> 4082911
B9: TOTAL | F9: =SUM(F7:F8) -> 1.0248107e+09
E11: Bancos | F11: =#REF! -> #REF!
E12: Action # 5678 | F12: =#REF! -> #REF!
E13: Monetizaciones | F13: ='MONETIZACIONES PEND'!$R$23 -> 148257053 | J13: Facturado | K13: ='MONETIZACIONES PEND'!Q23 -> 1.9379392e+08 | L13: Monetizado | M13: =F13 -> 148257053 | N13: =F13-K13 -> -45536863
E14: Endrington | F14: =#REF! -> #REF!
E15: Payroll Safeguard | F15: =#REF! -> #REF! | H15: 13791.26 | I15: 4406.16 | J15: Facturado | K15: =H15*I15 -> 60766498 | L15: Monetizado | M15: =$H$15*$I$16 -> #REF! | N15: =K16-K15 -> #REF!
E16: Gran Total | F16: =SUM(F11:F15) -> #REF! | I16: ='MONETIZACIONES PEND'!#REF! -> #REF! | K16: =$H$15*$I$16 -> #REF!
E18: Deficit | F18: =F16-F9 -> #REF! | J18: Total | K18: =K13+K15 -> 2.5456041e+08 | M18: =M13+M15 -> #REF! | N18: =N13+N15 -> #REF!
N19: =N18/K18 -> #REF!

Sheet Hoja1
B2: Nazdar | C2: 13336.33 | D2: 1
B3: Flexco | C3: 6784.5 | D3: 2 | K3: 288.62 | L3: =K3/K5 -> 0.013950321 | M3: =G7*L3 -> 177.21916
B4: MKD | C4: 2103.98 | D4: 3 | K4: 20400.51 | L4: =K4/K5 -> 0.98604968 | M4: =G7*L4 -> 12526.371
B5: Remotefirst | C5: 106335.63 | K5: =SUM(K3:K4) -> 20689.13
B6: Remotefisrt | C6: 33144.18
B7: Neo | C7: 20628.13 | D7: 4 | F7: ='MONETIZACIONES PEND'!K239+'MONETIZACIONES PEND'!K240 -> 7924.54 | G7: =C7-F7 -> 12703.59
B8: Oncehub | C8: 2866.23 | D8: 5
B9: Total | C9: =SUM(C2:C8) -> 185198.98
H11: Mayor valor
B12: Forward 1 | C12: 133605.5 | E12: 4294.81 | G12: =C5+C6 -> 139479.81 | H12: =G12-C12 -> 5874.31
B13: Forward 2 | C13: 49487.77 | E13: 4239.77 | G13: =C2+C3+C4+C7+C8 -> 45719.17 | H13: =G13-C13 -> -3768.6
F38: Pendiente | G38: 33144.18
F40: Saldo | G40: 3768.6
F41: Saldo | G41: 27269.87
F42: Negocie | G42: 2105.71
G43: =SUM(G40:G42) -> 33144.18 | I43: =G43*4278.77 -> 1.4181632e+08
G45: =G38-G43 -> 0

Sheet Proyectado Moneti 
B2: ID | C2: Client | D2: Invoice | E2: Incoming resources | F2: Maximum Date for Monetization | G2: Días | H2: Progress | J2: Invoiced | L2: Received | M2: Banking taxes | N2: TRM Invoice Cops | O2: TRM Bank (Average) Cops | P2: Difference in exchange rates | Q2: invoicing in COPS | R2: negotiated COPS | S2: difference | T2: KPI | U2: Color KPI
B3: 1 | C3: Remofirst-10AK | D3: 4820 | E3: 45443 | F3: 45503 | G3: =F3-E3 -> 60 | H3: =IFERROR(IF(TODAY()>=E3,(TODAY()-E3)/G3,0),0) -> 11.3 | I3: 1 | J3: 9692.05 | K3: =J3/$J$23 -> 0.088543303 | L3: =J3-M3 -> 9688.0656 | M3: =K3*$K$23 -> 3.9844486 | N3: 3864.23 | O3: 3882.9 | P3: =O3-N3 -> 18.67 | Q3: =J3*N3 -> 37452310 | R3: =L3*O3 -> 37617790 | S3: =R3-Q3 -> 165479.36 | T3: =IF(O3<= N3,"No Monetizar","Monetizar") -> Monetizar | W3: Remofirst-10AK Factura # 4820
B4: 2 | C4: Remofirst-Ferrous | D4: 4821 | E4: 45443 | F4: 45503 | G4: =F4-E4 -> 60 | H4: =IFERROR(IF(TODAY()>=E4,(TODAY()-E4)/G4,0),0) -> 11.3 | I4: 1 | J4: 8127.7 | K4: =J4/$J$23 -> 0.074251929 | L4: =J4-M4 -> 8124.3587 | M4: =K4*$K$23 -> 3.3413368 | N4: 3864.23 | O4: 3882.9 | P4: =O4-N4 -> 18.67 | Q4: =J4*N4 -> 31407302 | R4: =L4*O4 -> 31546072 | S4: =R4-Q4 -> 138770.08 | T4: =IF(O4<= N4,"No Monetizar","Monetizar") -> Monetizar | W4: Remofirst-Ferrous Factura # 4821
B5: 3 | C5: Remofirst Bluleadz | D5: 4822 | E5: 45443 | F5: 45503 | G5: =F5-E5 -> 60 | H5: =IFERROR(IF(TODAY()>=E5,(TODAY()-E5)/G5,0),0) -> 11.3 | I5: 1 | J5: 5392.67 | K5: =J5/$J$23 -> 0.049265616 | L5: =J5-M5 -> 5390.453 | M5: =K5*$K$23 -> 2.2169527 | N5: 3864.23 | O5: 3882.9 | P5: =O5-N5 -> 18.67 | Q5: =J5*N5 -> 20838517 | R5: =L5*O5 -> 20930590 | S5: =R5-Q5 -> 92072.943 | T5: =IF(O5<= N5,"No Monetizar","Monetizar") -> Monetizar | W5: Remofirst Bluleadz Factura # 4822
B6: 4 | C6: Remofirst TC1 Corporation SAC | D6: 4823 | E6: 45443 | F6: 45503 | G6: =F6-E6 -> 60 | H6: =IFERROR(IF(TODAY()>=E6,(TODAY()-E6)/G6,0),0) -> 11.3 | I6: 1 | J6: 6167.93 | K6: =J6/$J$23 -> 0.05634813 | L6: =J6-M6 -> 6165.3943 | M6: =K6*$K$23 -> 2.5356659 | N6: 3864.23 | O6: 3882.9 | P6: =O6-N6 -> 18.67 | Q6: =J6*N6 -> 23834300 | R6: =L6*O6 -> 23939610 | S6: =R6-Q6 -> 105309.52 | T6: =IF(O6<= N6,"No Monetizar","Monetizar") -> Monetizar | W6: Remofirst TC1 Corporation SAC Factura # 4823
B7: 5 | C7: Remofirst BGB Comunications | D7: 4824 | E7: 45443 | F7: 45503 | G7: =F7-E7 -> 60 | H7: =IFERROR(IF(TODAY()>=E7,(TODAY()-E7)/G7,0),0) -> 11.3 | I7: 1 | J7: 2914.59 | K7: =J7/$J$23 -> 0.026626712 | L7: =J7-M7 -> 2913.3918 | M7: =K7*$K$23 -> 1.198202 | N7: 3864.23 | O7: 3882.9 | P7: =O7-N7 -> 18.67 | Q7: =J7*N7 -> 11262646 | R7: =L7*O7 -> 11312409 | S7: =R7-Q7 -> 49762.897 | T7: =IF(O7<= N7,"No Monetizar","Monetizar") -> Monetizar | W7: Remofirst BGB Comunications Factura # 4824
B8: 6 | C8: Remofirst Hypatos | D8: 4835 | E8: 45443 | F8: 45503 | G8: =F8-E8 -> 60 | H8: =IFERROR(IF(TODAY()>=E8,(TODAY()-E8)/G8,0),0) -> 11.3 | I8: 1 | J8: 3873.2 | K8: =J8/$J$23 -> 0.03538425 | L8: =J8-M8 -> 3871.6077 | M8: =K8*$K$23 -> 1.5922913 | N8: 3864.23 | O8: 3882.9 | P8: =O8-N8 -> 18.67 | Q8: =J8*N8 -> 14966936 | R8: =L8*O8 -> 15033066 | S8: =R8-Q8 -> 66129.936 | T8: =IF(O8<= N8,"No Monetizar","Monetizar") -> Monetizar | W8: Remofirst Hypatos Factura # 4835
B9: 7 | C9: Remofirst R&R Windows | D9: 4825 | E9: 45443 | F9: 45503 | G9: =F9-E9 -> 60 | H9: =IFERROR(IF(TODAY()>=E9,(TODAY()-E9)/G9,0),0) -> 11.3 | I9: 1 | J9: 7033.16 | K9: =J9/$J$23 -> 0.06425258 | L9: =J9-M9 -> 7030.2686 | M9: =K9*$K$23 -> 2.8913661 | N9: 3864.23 | O9: 3882.9 | P9: =O9-N9 -> 18.67 | Q9: =J9*N9 -> 27177748 | R9: =L9*O9 -> 27297830 | S9: =R9-Q9 -> 120082.21 | T9: =IF(O9<= N9,"No Monetizar","Monetizar") -> Monetizar | W9: Remofirst R&R Windows Factura # 4825
B10: 8 | C10: Remofirst Velo3D | D10: 4826 | E10: 45443 | F10: 45503 | G10: =F10-E10 -> 60 | H10: =IFERROR(IF(TODAY()>=E10,(TODAY()-E10)/G10,0),0) -> 11.3 | I10: 1 | J10: 3625.59 | K10: =J10/$J$23 -> 0.033122169 | L10: =J10-M10 -> 3624.0995 | M10: =K10*$K$23 -> 1.4904976 | N10: 3864.23 | O10: 3882.9 | P10: =O10-N10 -> 18.67 | Q10: =J10*N10 -> 14010114 | R10: =L10*O10 -> 14072016 | S10: =R10-Q10 -> 61902.312 | T10: =IF(O10<= N10,"No Monetizar","Monetizar") -> Monetizar | W10: Remofirst Velo3D Factura # 4826
B11: 9 | C11: Remofirst Starlight Software Solutions | D11: 4827 | E11: 45443 | F11: 45503 | G11: =F11-E11 -> 60 | H11: =IFERROR(IF(TODAY()>=E11,(TODAY()-E11)/G11,0),0) -> 11.3 | I11: 1 | J11: 5792.08 | K11: =J11/$J$23 -> 0.052914491 | L11: =J11-M11 -> 5789.6988 | M11: =K11*$K$23 -> 2.3811521 | N11: 3864.23 | O11: 3882.9 | P11: =O11-N11 -> 18.67 | Q11: =J11*N11 -> 22381929 | R11: =L11*O11 -> 22480822 | S11: =R11-Q11 -> 98892.358 | T11: =IF(O11<= N11,"No Monetizar","Monetizar") -> Monetizar | W11: Remofirst Starlight Software Solutions Factura # 4827
B12: 10 | C12: Remofirst One firefly | D12: 4828 | E12: 45443 | F12: 45503 | G12: =F12-E12 -> 60 | H12: =IFERROR(IF(TODAY()>=E12,(TODAY()-E12)/G12,0),0) -> 11.3 | I12: 1 | J12: 2779.95 | K12: =J12/$J$23 -> 0.025396686 | L12: =J12-M12 -> 2778.8071 | M12: =K12*$K$23 -> 1.1428509 | N12: 3864.23 | O12: 3882.9 | P12: =O12-N12 -> 18.67 | Q12: =J12*N12 -> 10742366 | R12: =L12*O12 -> 10789830 | S12: =R12-Q12 -> 47464.091 | T12: =IF(O12<= N12,"No Monetizar","Monetizar") -> Monetizar | W12: Remofirst One firefly Factura # 4828
B13: 11 | C13: Remofirst Search Wizards | D13: 4829 | E13: 45443 | F13: 45503 | G13: =F13-E13 -> 60 | H13: =IFERROR(IF(TODAY()>=E13,(TODAY()-E13)/G13,0),0) -> 11.3 | I13: 1 | J13: 1838.65 | K13: =J13/$J$23 -> 0.016797287 | L13: =J13-M13 -> 1837.8941 | M13: =K13*$K$23 -> 0.75587791 | N13: 3864.23 | O13: 3882.9 | P13: =O13-N13 -> 18.67 | Q13: =J13*N13 -> 7104966.5 | R13: =L13*O13 -> 7136359.1 | S13: =R13-Q13 -> 31392.597 | T13: =IF(O13<= N13,"No Monetizar","Monetizar") -> Monetizar | W13: Remofirst Search Wizards Factura # 4829
B14: 12 | C14: Remofirst Search Insighful | D14: 4830 | E14: 45443 | F14: 45503 | G14: =F14-E14 -> 60 | H14: =IFERROR(IF(TODAY()>=E14,(TODAY()-E14)/G14,0),0) -> 11.3 | I14: 1 | J14: 19928.19 | K14: =J14/$J$23 -> 0.18205723 | L14: =J14-M14 -> 19919.997 | M14: =K14*$K$23 -> 8.1925753 | N14: 3864.23 | O14: 3882.9 | P14: =O14-N14 -> 18.67 | Q14: =J14*N14 -> 77007110 | R14: =L14*O14 -> 77347358 | S14: =R14-Q14 -> 340248.36 | T14: =IF(O14<= N14,"No Monetizar","Monetizar") -> Monetizar | W14: Remofirst Search Insighful Factura # 4830
... B16: 14 | C16: Remofirst Coop Edgar | D16: 4832 | E16: 45443 | F16: 45503 | G16: =F16-E16 -> 60 | H16: =IFERROR(IF(TODAY()>=E16,(TODAY()-E16)/G16,0),0) -> 11.3 | I16: 1 | J16: 4054.74 | K16: =J16/$J$23 -> 0.037042738 | L16: =J16-M16 -> 4053.0731 | M16: =K16*$K$23 -> 1.6669232 | N16: 3864.23 | O16: 3882.9 | P16: =O16-N16 -> 18.67 | Q16: =J16*N16 -> 15668448 | R16: =L16*O16 -> 15737677 | S16: =R16-Q16 -> 69229.5 | T16: =IF(O16<= N16,"No Monetizar","Monetizar") -> Monetizar | W16: Remofirst Coop Edgar Factura # 4832
B17: 15 | C17: Remofirst Search AMG Global Distribution | D17: 4833 | E17: 45443 | F17: 45503 | G17: =F17-E17 -> 60 | H17: =IFERROR(IF(TODAY()>=E17,(TODAY()-E17)/G17,0),0) -> 11.3 | I17: 1 | J17: =16965.69 -> 16965.69 | K17: =J17/$J$23 -> 0.15499283 | L17: =J17-M17 -> 16958.715 | M17: =K17*$K$23 -> 6.9746772 | N17: 3864.23 | O17: 3882.9 | P17: =O17-N17 -> 18.67 | Q17: =J17*N17 -> 65559328 | R17: =L17*O17 -> 65848996 | S17: =R17-Q17 -> 289667.46 | T17: =IF(O17<= N17,"No Monetizar","Monetizar") -> Monetizar | W17: Remofirst Search AMG Global Distribution Factura # 4833
B18: 16 | C18: Remofirst Search Carbon better | D18: 4834 | E18: 45443 | F18: 45503 | G18: =F18-E18 -> 60 | H18: =IFERROR(IF(TODAY()>=E18,(TODAY()-E18)/G18,0),0) -> 11.3 | I18: 1 | J18: =1712.33 -> 1712.33 | K18: =J18/$J$23 -> 0.01564327 | L18: =J18-M18 -> 1711.6261 | M18: =K18*$K$23 -> 0.70394715 | N18: 3864.23 | O18: 3882.9 | P18: =O18-N18 -> 18.67 | Q18: =J18*N18 -> 6616837 | R18: =L18*O18 -> 6646072.8 | S18: =R18-Q18 -> 29235.845 | T18: =IF(O18<= N18,"No Monetizar","Monetizar") -> Monetizar | W18: Remofirst Search Carbon better Factura # 4834
B19: 17 | C19: Remofirst CPaT Global LLC | D19: 4879 | E19: 45443 | F19: 45503 | G19: =F19-E19 -> 60 | H19: =IFERROR(IF(TODAY()>=E19,(TODAY()-E19)/G19,0),0) -> 11.3 | J19: 4772 | K19: =J19/$J$23 -> 0.043595384 | L19: =J19-M19 -> 4770.0382 | M19: =K19*$K$23 -> 1.9617923 | N19: 3864.23 | O19: 3882.9 | P19: =O19-N19 -> 18.67 | Q19: =J19*N19 -> 18440106 | R19: =L19*O19 -> 18521581 | S19: =R19-Q19 -> 81475.797 | T19: =IF(O19<= N19,"No Monetizar","Monetizar") -> Monetizar | W19: Remofirst CPaT Global LLC Factura # 4879
B20: 18 | C20: Remofirst CPaT Global LLC | D20: 4880 | E20: 45443 | F20: 45503 | G20: =F20-E20 -> 60 | H20: =IFERROR(IF(TODAY()>=E20,(TODAY()-E20)/G20,0),0) -> 11.3 | J20: 3016.51 | K20: =J20/$J$23 -> 0.027557819 | L20: =J20-M20 -> 3015.2699 | M20: =K20*$K$23 -> 1.2401019 | N20: 3864.23 | O20: 3882.9 | P20: =O20-N20 -> 18.67 | Q20: =J20*N20 -> 11656488 | R20: =L20*O20 -> 11707991 | S20: =R20-Q20 -> 51503.05 | T20: =IF(O20<= N20,"No Monetizar","Monetizar") -> Monetizar | W20: Remofirst CPaT Global LLC Factura # 4880
B21: TOTAL | J21: =SUM(J3:J20) -> 109461.13 | L21: =SUM(L3:L20) -> 109416.13 | M21: =SUM(M3:M20) -> 45 | Q21: =SUM(Q3:Q20) -> 4.2298298e+08 | R21: =SUM(R3:R20) -> 4.2485189e+08 | S21: =SUM(S3:S20) -> 1868908.8 | T21: =S21/Q21 -> 0.0044184019
H23: Remotefirst | J23: =SUM(J3:J20) -> 109461.13 | K23: 45
J26: Diferencia Cambio
J28: Diferencia en cambio ( Ingreso) | M28: =#REF!+#REF!+#REF! -> #REF!
J29: Diferencia en cambio ( Gasto) | M29: =S21+'MONETIZACIONES PEND'!S23 -> -43667954
J30: Balanza | M30: =SUM(M28:M29) -> #REF!
