Workbook
Name Marca: #REF!
Name Marca: #REF!
Name Marca1: #REF!
Name Marca1: #REF!
Name Marcas: #REF!
Name Marcas: #REF!
Name Valor: #REF!
Name Valor: #REF!
Name Value: #REF!
Name Value: #REF!
Name values: #REF!

Sheet DICIEMBRE
E1: 42400
D4: BANCOS | E4: =SUBTOTAL(9,E5:E5) -> 1.0260921e+09
D5: Bancos | E5: 1.0260921e+09
D6: FACTURACIÓN PENDIENTE POR MONETIZAR | E6: =SUBTOTAL(9,E7:E7) -> 3.9592753e+09
D7: Monetización - facturación y Offycycle Diciembre | E7: =171505293.6+294581581.61+43363251.75+75955982+3373869149.59 -> 3.9592753e+09
E8: =SUBTOTAL(9,E4:E7) -> 4.9853673e+09
C11: CUENTAS X PAGAR MES | E11: DICIEMBRE | F11: Fecha de Elaboración: | I11: 45992
C12: Factura | D12: PROVEEDOR | E12: VALOR | F12: Fecha vencimiento | G12: Estado | I12: KPI | J12: Objeto
D13: PAGOS ANTICIPADOS | E13: =SUBTOTAL(9,E14) -> 25041817
A14: =G14 -> Cancelado | B14: =IF(#REF!<=-1,1,IF(#REF!<=5,2,IF(#REF!<=15,3,IF(H14<=60,4)))) -> #REF! | C14: 1 registro | D14: Nómina Sergio Jimenez Belimo | E14: 25041817 | F14: 46020 | G14: Cancelado | H14: =IF(OR(G14="Sin pagar",G14="Pagar"),NETWORKDAYS($I$11,F14,'Festivos Colombia'!$A$3:$A$22),0) -> 0 | I14: =H14 -> 0
D15: SEGURIDAD SOCIAL | E15: =SUBTOTAL(9,E16:E16) -> 545064300
A16: =G16 -> Cancelado | B16: =IF(#REF!<=-1,1,IF(#REF!<=5,2,IF(#REF!<=15,3,IF(H16<=60,4)))) -> #REF! | D16: Pago seguridad social Global | E16: 545064300 | F16: 46003 | G16: Cancelado | H16: =IF(OR(G16="Sin pagar",G16="Pagar"),NETWORKDAYS($I$11,F16,'Festivos Colombia'!$A$3:$A$22),0) -> 0 | I16: =H16 -> 0
D17: AFC´S | E17: =SUBTOTAL(9,E18:E19) -> 80309295
A18: =G18 -> Cancelado | B18: =IF(#REF!<=-1,1,IF(#REF!<=5,2,IF(#REF!<=15,3,IF(H18<=60,4)))) -> #REF! | C18: 1 | D18: AFC y aportes voluntarios - Cheque | E18: =19400000+7900000 -> 27300000 | F18: 46017 | G18: Cancelado | H18: =IF(OR(G18="Sin pagar",G18="Pagar"),NETWORKDAYS($I$11,F18,'Festivos Colombia'!$A$3:$A$22),0) -> 0 | I18: =H18 -> 0
A19: =G19 -> Cancelado | B19: =IF(#REF!<=-1,1,IF(#REF!<=5,2,IF(#REF!<=15,3,IF(H19<=60,4)))) -> #REF! | C19: 1 | D19: AFC y aportes voluntarios -SOI y Aportes en Linea | E19: 53009295 | F19: 46017 | G19: Cancelado | H19: =IF(OR(G19="Sin pagar",G19="Pagar"),NETWORKDAYS($I$11,F19,'Festivos Colombia'!$A$3:$A$22),0) -> 0 | I19: =H19 -> 0
D20: IMPUESTOS | E20: =SUBTOTAL(9,E21:E21) -> 311877000 | H20: =IF(OR(G20="Sin pagar",G20="Pagar"),NETWORKDAYS($I$11,F20,'Festivos Colombia'!$A$3:$A$22),0) -> 0 | I20: =H20 -> 0
A21: =G21 -> Cancelado | B21: =IF(#REF!<=-1,1,IF(#REF!<=5,2,IF(#REF!<=15,3,IF(H21<=60,4)))) -> #REF! | D21: Retención en la fuente | E21: 311877000 | F21: 46003 | G21: Cancelado | H21: =IF(OR(G21="Sin pagar",G21="Pagar"),NETWORKDAYS($I$11,F21,'Festivos Colombia'!$A$3:$A$22),0) -> 0 | I21: =H21 -> 0
D22: PLANES COMPLEMENTARIOS Y PREPAGADAS | E22: =SUBTOTAL(9,E23:E25) -> 11402659 | H22: =IF(OR(G22="Sin pagar",G22="Pagar"),NETWORKDAYS($I$11,F22,'Festivos Colombia'!$A$3:$A$22),0) -> 0
A23: =G23 -> Cancelado | B23: =IF(#REF!<=-1,1,IF(#REF!<=5,2,IF(#REF!<=15,3,IF(H23<=60,4)))) -> #REF! | C23: 2091201744 | D23: Póliza suramericana # 091000808150 SALUD FAMILIAR | E23: 10359668 | F23: 46017 | G23: Cancelado | H23: =IF(OR(G23="Sin pagar",G23="Pagar"),NETWORKDAYS($I$11,F23,'Festivos Colombia'!$A$3:$A$22),0) -> 0 | I23: =H23 -> 0
A24: =G24 -> Cancelado | B24: =IF(#REF!<=-1,1,IF(#REF!<=5,2,IF(#REF!<=15,3,IF(H24<=60,4)))) -> #REF! | C24: 20911202787 | D24: Póliza suramericana # 091000808150 SALUD FAMILIAR | E24: 565363 | F24: 46017 | G24: Cancelado | H24: =IF(OR(G24="Sin pagar",G24="Pagar"),NETWORKDAYS($I$11,F24,'Festivos Colombia'!$A$3:$A$22),0) -> 0 | I24: =H24 -> 0
A25: =G25 -> Cancelado | B25: =IF(#REF!<=-1,1,IF(#REF!<=5,2,IF(#REF!<=15,3,IF(H25<=60,4)))) -> #REF! | C25: 20833316862 | D25: Póliza suramericana # 0904418894 SALUD FAMILIAR | E25: 477628 | F25: 46017 | G25: Cancelado | H25: =IF(OR(G25="Sin pagar",G25="Pagar"),NETWORKDAYS($I$11,F25,'Festivos Colombia'!$A$3:$A$22),0) -> 0 | I25: =H25 -> 0
D26: PÓLIZAS Y SEGUROS | E26: =SUBTOTAL(9,E27:E44) -> 36113797 | H26: =IF(OR(G26="Sin pagar",G26="Pagar"),NETWORKDAYS($I$11,F26,'Festivos Colombia'!$A$3:$A$22),0) -> 0
A27: =G27 -> Cancelado | B27: =IF(#REF!<=-1,1,IF(#REF!<=5,2,IF(#REF!<=15,3,IF(H27<=60,4)))) -> #REF! | C27: 1239806816 | D27: Plan grupo 10108069057 | E27: 12733350 | F27: 45995 | G27: Cancelado | H27: =IF(OR(G27="Sin pagar",G27="Pagar"),NETWORKDAYS($I$11,F27,'Festivos Colombia'!$A$3:$A$22),0) -> 0 | I27: =H27 -> 0
A28: =G28 -> Cancelado | B28: =IF(#REF!<=-1,1,IF(#REF!<=5,2,IF(#REF!<=15,3,IF(H28<=60,4)))) -> #REF! | C28: 1239781227 | D28: Plan grupo 103226992 - Aana Aguirre - GRAINGER SERVICES INTERNATIONA | E28: 193253 | F28: 45995 | G28: Cancelado | H28: =IF(OR(G28="Sin pagar",G28="Pagar"),NETWORKDAYS($I$11,F28,'Festivos Colombia'!$A$3:$A$22),0) -> 0 | I28: =H28 -> 0
A29: =G29 -> Cancelado | B29: =IF(#REF!<=-1,1,IF(#REF!<=5,2,IF(#REF!<=15,3,IF(H29<=60,4)))) -> #REF! | C29: 1239772460 | D29: Plan dental 103229130 Luna Rodriguez - LANO SOFTWARE GMBH | E29: 298337 | F29: 45995 | G29: Cancelado | H29: =IF(OR(G29="Sin pagar",G29="Pagar"),NETWORKDAYS($I$11,F29,'Festivos Colombia'!$A$3:$A$22),0) -> 0 | I29: =H29 -> 0
A30: =G30 -> Cancelado | B30: =IF(#REF!<=-1,1,IF(#REF!<=5,2,IF(#REF!<=15,3,IF(H30<=60,4)))) -> #REF! | C30: 1239773169 | D30: Plan dental 10325327 Ivonne Torres | E30: 295313 | F30: 45995 | G30: Cancelado | H30: =IF(OR(G30="Sin pagar",G30="Pagar"),NETWORKDAYS($I$11,F30,'Festivos Colombia'!$A$3:$A$22),0) -> 0 | I30: =H30 -> 0
A31: =G31 -> Cancelado | B31: =IF(#REF!<=-1,1,IF(#REF!<=5,2,IF(#REF!<=15,3,IF(H31<=60,4)))) -> #REF! | C31: 1239749107 | D31: Plan grupo 10108170475 - Sandra Barba - ALLEGIS GROUP INC | E31: 1642200 | F31: 45995 | G31: Cancelado | H31: =IF(OR(G31="Sin pagar",G31="Pagar"),NETWORKDAYS($I$11,F31,'Festivos Colombia'!$A$3:$A$22),0) -> 0 | I31: =H31 -> 0
A32: =G32 -> Cancelado | B32: =IF(#REF!<=-1,1,IF(#REF!<=5,2,IF(#REF!<=15,3,IF(H32<=60,4)))) -> #REF! | C32: 1239720449 | D32: Plan grupo 103225452 - Freddy Gomez - TITAN METER BIDCO CORPORATION | E32: 318465 | F32: 45995 | G32: Cancelado | H32: =IF(OR(G32="Sin pagar",G32="Pagar"),NETWORKDAYS($I$11,F32,'Festivos Colombia'!$A$3:$A$22),0) -> 0 | I32: =H32 -> 0
A33: =G33 -> Cancelado | B33: =IF(#REF!<=-1,1,IF(#REF!<=5,2,IF(#REF!<=15,3,IF(H33<=60,4)))) -> #REF! | C33: 1239803861 | D33: Plan grupo-103229134 - María Amaya Gomez - LANO SOFTWARE | E33: 68040 | F33: 45995 | G33: Cancelado | H33: =IF(OR(G33="Sin pagar",G33="Pagar"),NETWORKDAYS($I$11,F33,'Festivos Colombia'!$A$3:$A$22),0) -> 0 | I33: =H33 -> 0
A34: =G34 -> Cancelado | B34: =IF(#REF!<=-1,1,IF(#REF!<=5,2,IF(#REF!<=15,3,IF(H34<=60,4)))) -> #REF! | C34: 1239543181 | D34: Plan grupo 10108174837 - Freddy Gomez - TITAN METER BIDCO CORPORATION | E34: 1860600 | F34: 46000 | G34: Cancelado | H34: =IF(OR(G34="Sin pagar",G34="Pagar"),NETWORKDAYS($I$11,F34,'Festivos Colombia'!$A$3:$A$22),0) -> 0 | I34: =H34 -> 0
A35: =G35 -> Cancelado | B35: =IF(#REF!<=-1,1,IF(#REF!<=5,2,IF(#REF!<=15,3,IF(H35<=60,4)))) -> #REF! | C35: 1239817137 | D35: Plan grupo-103229134 - María Gabriela Acosta - LANO SOFTWARE | E35: 68040 | F35: 45995 | G35: Cancelado | H35: =IF(OR(G35="Sin pagar",G35="Pagar"),NETWORKDAYS($I$11,F35,'Festivos Colombia'!$A$3:$A$22),0) -> 0 | I35: =H35 -> 0
A36: =G36 -> Cancelado | B36: =IF(#REF!<=-1,1,IF(#REF!<=5,2,IF(#REF!<=15,3,IF(H36<=60,4)))) -> #REF! | C36: 12310058809 | D36: Plan grupo 10108069057 | E36: 13580700 | F36: 46028 | G36: Cancelado | H36: =IF(OR(G36="Sin pagar",G36="Pagar"),NETWORKDAYS($I$11,F36,'Festivos Colombia'!$A$3:$A$22),0) -> 0 | I36: =H36 -> 0
A37: =G37 -> Cancelado | B37: =IF(#REF!<=-1,1,IF(#REF!<=5,2,IF(#REF!<=15,3,IF(H37<=60,4)))) -> #REF! | C37: 1239964849 | D37: Plan grupo 103226992 - Aana Aguirre - GRAINGER SERVICES INTERNATIONA | E37: 205538 | F37: 46028 | G37: Cancelado | H37: =IF(OR(G37="Sin pagar",G37="Pagar"),NETWORKDAYS($I$11,F37,'Festivos Colombia'!$A$3:$A$22),0) -> 0 | I37: =H37 -> 0
A38: =G38 -> Cancelado | B38: =IF(#REF!<=-1,1,IF(#REF!<=5,2,IF(#REF!<=15,3,IF(H38<=60,4)))) -> #REF! | C38: 1239905171 | D38: Plan dental 103229130 Luna Rodriguez - LANO SOFTWARE GMBH | E38: 316953 | F38: 46028 | G38: Cancelado | H38: =IF(OR(G38="Sin pagar",G38="Pagar"),NETWORKDAYS($I$11,F38,'Festivos Colombia'!$A$3:$A$22),0) -> 0 | I38: =H38 -> 0
... A44: =G44 -> Cancelado | B44: =IF(#REF!<=-1,1,IF(#REF!<=5,2,IF(#REF!<=15,3,IF(H44<=60,4)))) -> #REF! | C44: 12310060492 | D44: Plan grupo-103229134 - María Gabriela Acosta - LANO SOFTWARE | E44: 71820 | F44: 46028 | G44: Cancelado | H44: =IF(OR(G44="Sin pagar",G44="Pagar"),NETWORKDAYS($I$11,F44,'Festivos Colombia'!$A$3:$A$22),0) -> 0 | I44: =H44 -> 0
D45: REEMBOLSO GASTOS VIAJE | E45: =SUBTOTAL(9,E46:E91) -> 1.3923323e+08
D46: Reembolso Cristhian Javier Gutierrez Torres-Sophos-CC020 | E46: 754854 | F46: 45995 | G46: Cancelado
D47: Reembolso Fabian Augusto Porto Dulcey cc020 - Sophos | E47: 224349.45 | F47: 45995 | G47: Cancelado
D48: Reembolso Howard Antonio Donado Padilla cc073- Zenio | E48: 380000 | F48: 45995 | G48: Cancelado
D49: Reembolso Edith johana pineda zapata cc020 - sophos | E49: 5720201.4 | F49: 45995 | G49: Cancelado
D50: Reembolso Marylin Restrepo z cc020 - sophos | E50: 2830000 | F50: 45995 | G50: Cancelado
D51: Reembolso Pablo Andres Ossa Ocampo cc073- Zenio | E51: 316925 | F51: 45995 | G51: Cancelado
D52: Reembolso de santa anna campdera alberto enrique - cc029 - leistritz advanced technologies corp | E52: 16350000 | F52: 45995 | G52: Cancelado
D53: Reembolso hoyos arrioja carlos alberto - cc029 - leistritz advanced technologies corp | E53: 6750000 | F53: 45995 | G53: Cancelado
D54: Reembolso Camila Marin Melo cc020 - sophos | E54: 44600 | F54: 46003 | G54: Cancelado
D55: Reembolso Maria Claudia Bohorquez Quintero cc020 - Sophos | E55: 35409 | F55: 46003 | G55: Cancelado
D56: Reembolso Fabian Augusto Porto Dulcey cc020 - Sophos | E56: 2324827.1 | F56: 46003 | G56: Cancelado
D57: Reembolso Howard Antonio Donado Padilla cc073- Zenio | E57: 642376 | F57: 46003 | G57: Cancelado
... D73: Reembolso Mario Fernando Benitez Zabala cc020 - sophos | E73: 1806000 | F73: 46020 | G73: Cancelado
E74: 10683224 | F74: 46020 | G74: Cancelado
D75: Reembolso Milagros Sanchez cc020 - sophos | E75: 17928625 | F75: 46020 | G75: Cancelado
D76: Reembolso Sandra viviana barba lizarralde - cco65 - allegis group inc | E76: 3021994 | F76: 46020 | G76: Cancelado
D77: Reembolso Sandra Juliana Mariño Lozano-cc073 - Zennio | E77: 192200 | F77: 46020 | G77: Cancelado
D78: Reembolso Alina Restrepo Jaramillo-cc035 - Georgia Institute | E78: 717001.1 | F78: 46020 | G78: Cancelado
D79: Reembolso Angélica María Benitez Yusti cc070- BMC Medical | E79: =5385563.02+770561 -> 6156124 | F79: 46020 | G79: Cancelado
D80: Reembolso Christian Henao - CC079 - GILL INSTRUMENTS | E80: 413889.2 | F80: 46020 | G80: Cancelado
D81: Reembolso Diana Ximena Rodriguez Patiño-HSI | E81: 223551.4 | F81: 46020 | G81: Cancelado
D82: Reembolso genesis marchena gómez - cc081 - go - global outsourcing inc | E82: 946310 | F82: 46020 | G82: Cancelado
D83: Reembolso anaya latorre juan felipe - cc005 - basis global technologies, inc. | E83: 745110 | F83: 46020 | G83: Cancelado
D84: Reembolso Sandra Juliana Mariño Lozano-cc073 - Zennio | E84: 413438 | F84: 46020 | G84: Cancelado
D85: Reembolso Cristian Javier Gutierrez Torres-cc020 - Sophos | E85: 467154 | F85: 46024 | G85: Cancelado
D86: Reembolso Jorge Daniel Ramos DUran cc040 - Environmental Dynamics INTL | E86: 1000226 | F86: 46024 | G86: Cancelado
D87: Reembolso Edwin fernando alonso castelblanco cc020 - sophos | E87: 255113.01 | F87: 46024 | G87: Cancelado
D88: Reembolso Howard Antonio Donado Padilla cc073- Zenio | E88: 468000 | F88: 46024 | G88: Cancelado
D89: Reembolso Ivonne Torres-cc012 - lifenet health | E89: 1546811 | F89: 46024 | G89: Cancelado
D90: Reembolso Edith johana pineda zapata cc020 - sophos | E90: 1783405 | F90: 46024 | G90: Cancelado
D91: Reembolso Mario Fernando Benitez Zabala cc020 - sophos | E91: 166330 | F91: 46024 | G91: Cancelado
D92: TIQUETES AÉREOS , HOTELES | E92: =SUBTOTAL(9,E93:E96) -> 6833580
D93: Tiquete Andy Muñoz Cartagena-Bogota y Vsa | E93: 840740 | F93: 46002 | G93: Cancelado | H93: =IF(OR(G93="Sin pagar",G93="Pagar"),NETWORKDAYS($I$11,F93,'Festivos Colombia'!$A$3:$A$22),0) -> 0 | I93: =H93 -> 0
D94: Tiquete Sandra Barba | E94: 1462100 | F94: 46003 | G94: Cancelado | H94: =IF(OR(G94="Sin pagar",G94="Pagar"),NETWORKDAYS($I$11,F94,'Festivos Colombia'!$A$3:$A$22),0) -> 0 | I94: =H94 -> 0
D95: Tiquete Andy Muñoz Cartagena-Bogota y Vsa-Equipaje Cartagena | E95: 125000 | F95: 46008 | G95: Cancelado | H95: =IF(OR(G95="Sin pagar",G95="Pagar"),NETWORKDAYS($I$11,F95,'Festivos Colombia'!$A$3:$A$22),0) -> 0 | I95: =H95 -> 0
D96: Tiquete Andy Muñoz Cartagena-ciudades estados unidos Vsa-Equipaje Cartagena | E96: 4405740 | F96: 46028 | G96: Cancelado | H96: =IF(OR(G96="Sin pagar",G96="Pagar"),NETWORKDAYS($I$11,F96,'Festivos Colombia'!$A$3:$A$22),0) -> 0 | I96: =H96 -> 0
D97: ASESORÍAS | E97: =SUBTOTAL(9,E98:E99) -> 17766798
A98: =G98 -> Cancelado | B98: =IF(#REF!<=-1,1,IF(#REF!<=5,2,IF(#REF!<=15,3,IF(H98<=60,4)))) -> #REF! | C98: 6443 | D98: Global CS Colombia SAS -Solutions & payroll-Servicio Noviembre 2025 | E98: 17406804 | F98: 46003 | G98: Cancelado | H98: =IF(OR(G98="Sin pagar",G98="Pagar"),NETWORKDAYS($I$11,F98,'Festivos Colombia'!$A$3:$A$22),0) -> 0 | I98: =H98 -> 0
A99: =G99 -> Cancelado | B99: =IF(#REF!<=-1,1,IF(#REF!<=5,2,IF(#REF!<=15,3,IF(H99<=60,4)))) -> #REF! | C99: 5-124 | D99: Global CS Colombia SAS -Solutions & payroll- Reembolso Gastos Noviembre | E99: 359994 | F99: 46003 | G99: Cancelado | H99: =IF(OR(G99="Sin pagar",G99="Pagar"),NETWORKDAYS($I$11,F99,'Festivos Colombia'!$A$3:$A$22),0) -> 0 | I99: =H99 -> 0
D100: COSTOS FINANCIEROS | E100: =SUBTOTAL(9,E101) -> 13453784
A101: =G101 -> Cancelado | B101: =IF(#REF!<=-1,1,IF(#REF!<=5,2,IF(#REF!<=15,3,IF(H101<=60,4)))) -> #REF! | D101: Costos financieros (Cuenta GLOBAL CS) | E101: =12688157.41+765626.18 -> 13453784 | F101: 46022 | G101: Cancelado | H101: =IF(OR(G101="Sin pagar",G101="Pagar"),NETWORKDAYS($I$11,F101,'Festivos Colombia'!$A$3:$A$22),0) -> 0 | I101: =H101 -> 0
D102: CREDITOS Y LIBRANZAS | E102: =SUBTOTAL(9,E103) -> 0
A103: =G103 -> Cancelado | B103: =IF(#REF!<=-1,1,IF(#REF!<=5,2,IF(#REF!<=15,3,IF(H103<=60,4)))) -> #REF! | F103: 46022 | G103: Cancelado | H103: =IF(OR(G103="Sin pagar",G103="Pagar"),NETWORKDAYS($I$11,F103,'Festivos Colombia'!$A$3:$A$22),0) -> 0 | I103: =H103 -> 0
D104: ESTUDIOS DE SEGURIDAD Y EXAMENES OCUPACIONALES-PÓLIZAS SALUD | E104: =SUBTOTAL(9,E105:E113) -> 1940706
A105: =G105 -> Cancelado | B105: =IF(#REF!<=-1,1,IF(#REF!<=5,2,IF(#REF!<=15,3,IF(H105<=60,4)))) -> #REF! | C105: 16001348099148 | D105: Allianz Póliza No: 23730847- Jerson Porras | E105: =467206 -> 467206 | F105: 46017 | G105: Cancelado | H105: =IF(OR(G105="Sin pagar",G105="Pagar"),NETWORKDAYS($I$11,F105,'Festivos Colombia'!$A$3:$A$22),0) -> 0 | I105: =H105 -> 0
A106: =G106 -> Cancelado | B106: =IF(#REF!<=-1,1,IF(#REF!<=5,2,IF(#REF!<=15,3,IF(H106<=60,4)))) -> #REF! | C106: 6786 | D106: EMASOC | E106: =519000 -> 519000 | F106: 45995 | G106: Cancelado | H106: =IF(OR(G106="Sin pagar",G106="Pagar"),NETWORKDAYS($I$11,F106,'Festivos Colombia'!$A$3:$A$22),0) -> 0 | I106: =H106 -> 0
A107: =G107 -> Cancelado | B107: =IF(#REF!<=-1,1,IF(#REF!<=5,2,IF(#REF!<=15,3,IF(H107<=60,4)))) -> #REF! | C107: 6796 | D107: EMASOC | E107: =410000 -> 410000 | F107: 46010 | G107: Cancelado | H107: =IF(OR(G107="Sin pagar",G107="Pagar"),NETWORKDAYS($I$11,F107,'Festivos Colombia'!$A$3:$A$22),0) -> 0 | I107: =H107 -> 0
A108: =G108 -> Cancelado | B108: =IF(#REF!<=-1,1,IF(#REF!<=5,2,IF(#REF!<=15,3,IF(H108<=60,4)))) -> #REF! | C108: 6820 | D108: EMASOC | E108: =337000 -> 337000 | F108: 46013 | G108: Cancelado | H108: =IF(OR(G108="Sin pagar",G108="Pagar"),NETWORKDAYS($I$11,F108,'Festivos Colombia'!$A$3:$A$22),0) -> 0 | I108: =H108 -> 0
A109: =G109 -> Cancelado | B109: =IF(#REF!<=-1,1,IF(#REF!<=5,2,IF(#REF!<=15,3,IF(H109<=60,4)))) -> #REF! | C109: 6830 | D109: EMASOC | E109: 207500 | F109: 46013 | G109: Cancelado | H109: =IF(OR(G109="Sin pagar",G109="Pagar"),NETWORKDAYS($I$11,F109,'Festivos Colombia'!$A$3:$A$22),0) -> 0 | I109: =H109 -> 0
A110: =G110 -> Sin Pagar | B110: =IF(#REF!<=-1,1,IF(#REF!<=5,2,IF(#REF!<=15,3,IF(H110<=60,4)))) -> #REF! | C110: 6838 | D110: EMASOC | E110: =205000*0 -> 0 | F110: 46027 | G110: Sin Pagar | H110: =IF(OR(G110="Sin pagar",G110="Pagar"),NETWORKDAYS($I$11,F110,'Festivos Colombia'!$A$3:$A$22),0) -> 25 | I110: =H110 -> 25
A111: =G111 -> Sin Pagar | B111: =IF(#REF!<=-1,1,IF(#REF!<=5,2,IF(#REF!<=15,3,IF(H111<=60,4)))) -> #REF! | C111: 6845 | D111: EMASOC | E111: =1432500*0 -> 0 | F111: 46033 | G111: Sin Pagar | H111: =IF(OR(G111="Sin pagar",G111="Pagar"),NETWORKDAYS($I$11,F111,'Festivos Colombia'!$A$3:$A$22),0) -> 29 | I111: =H111 -> 29
A112: =G112 -> Sin Pagar | B112: =IF(#REF!<=-1,1,IF(#REF!<=5,2,IF(#REF!<=15,3,IF(H112<=60,4)))) -> #REF! | C112: 6856 | D112: EMASOC | E112: =406500*0 -> 0 | F112: 46039 | G112: Sin Pagar | H112: =IF(OR(G112="Sin pagar",G112="Pagar"),NETWORKDAYS($I$11,F112,'Festivos Colombia'!$A$3:$A$22),0) -> 33 | I112: =H112 -> 33
A113: =G113 -> Sin Pagar | B113: =IF(#REF!<=-1,1,IF(#REF!<=5,2,IF(#REF!<=15,3,IF(H113<=60,4)))) -> #REF! | C113: 6860 | D113: EMASOC | E113: =311500*0 -> 0 | F113: 46039 | G113: Sin Pagar | H113: =IF(OR(G113="Sin pagar",G113="Pagar"),NETWORKDAYS($I$11,F113,'Festivos Colombia'!$A$3:$A$22),0) -> 33 | I113: =H113 -> 33
D114: NÓMINAS Y ABONO A TARJETAS PEOPLE PASS | E114: =SUBTOTAL(9,E115:E123) -> 1767857970
A115: =G115 -> Cancelado | B115: =IF(#REF!<=-1,1,IF(#REF!<=5,2,IF(#REF!<=15,3,IF(H115<=60,4)))) -> #REF! | D115: Monetización Sena Septiembre | E115: 6405750 | F115: 45995 | G115: Cancelado | H115: =IF(OR(G115="Sin pagar",G115="Pagar"),NETWORKDAYS($I$11,F115,'Festivos Colombia'!$A$3:$A$22),0) -> 0 | I115: =H115 -> 0
A116: =G116 -> Cancelado | B116: =IF(#REF!<=-1,1,IF(#REF!<=5,2,IF(#REF!<=15,3,IF(H116<=60,4)))) -> #REF! | D116: Prima OE | E116: 321157325 | F116: 46008 | G116: Cancelado | H116: =IF(OR(G116="Sin pagar",G116="Pagar"),NETWORKDAYS($I$11,F116,'Festivos Colombia'!$A$3:$A$22),0) -> 0 | I116: =H116 -> 0
A117: =G117 -> Cancelado | B117: =IF(#REF!<=-1,1,IF(#REF!<=5,2,IF(#REF!<=15,3,IF(H117<=60,4)))) -> #REF! | C117: 4 Registros | D117: Prima OE-Pago adicional por personal nuevo ingreso el 15 diciembre | E117: 3263682 | F117: 46010 | G117: Cancelado | H117: =IF(OR(G117="Sin pagar",G117="Pagar"),NETWORKDAYS($I$11,F117,'Festivos Colombia'!$A$3:$A$22),0) -> 0 | I117: =H117 -> 0
A118: =G118 -> Cancelado | B118: =IF(#REF!<=-1,1,IF(#REF!<=5,2,IF(#REF!<=15,3,IF(H118<=60,4)))) -> #REF! | C118: 87 Registros | D118: Nomina OE | E118: =1379413315-E14 -> 1354371498 | F118: 46020 | G118: Cancelado | H118: =IF(OR(G118="Sin pagar",G118="Pagar"),NETWORKDAYS($I$11,F118,'Festivos Colombia'!$A$3:$A$22),0) -> 0 | I118: =H118 -> 0
A119: =G119 -> Cancelado | B119: =IF(#REF!<=-1,1,IF(#REF!<=5,2,IF(#REF!<=15,3,IF(H119<=60,4)))) -> #REF! | D119: Libranza compensar | E119: 2209861 | F119: 46017 | G119: Cancelado | H119: =IF(OR(G119="Sin pagar",G119="Pagar"),NETWORKDAYS($I$11,F119,'Festivos Colombia'!$A$3:$A$22),0) -> 0 | I119: =H119 -> 0
A120: =G120 -> Cancelado | B120: =IF(#REF!<=-1,1,IF(#REF!<=5,2,IF(#REF!<=15,3,IF(H120<=60,4)))) -> #REF! | C120: FPP434067 | D120: People Pass-Market | E120: 815232 | F120: 46017 | G120: Cancelado | H120: =IF(OR(G120="Sin pagar",G120="Pagar"),NETWORKDAYS($I$11,F120,'Festivos Colombia'!$A$3:$A$22),0) -> 0 | I120: =H120 -> 0
A121: =G121 -> Cancelado | B121: =IF(#REF!<=-1,1,IF(#REF!<=5,2,IF(#REF!<=15,3,IF(H121<=60,4)))) -> #REF! | C121: 1 registro | D121: Pago institucional Protección Sergio Jimenez Belimo | E121: 75603248 | F121: 46021 | G121: Cancelado | H121: =IF(OR(G121="Sin pagar",G121="Pagar"),NETWORKDAYS($I$11,F121,'Festivos Colombia'!$A$3:$A$22),0) -> 0 | I121: =H121 -> 0
A122: =G122 -> Cancelado | B122: =IF(#REF!<=-1,1,IF(#REF!<=5,2,IF(#REF!<=15,3,IF(H122<=60,4)))) -> #REF! | C122: 1 registro | D122: Pago Ajuste prima extralegal Jerson Porras | E122: 4031374 | F122: 46024 | G122: Cancelado | H122: =IF(OR(G122="Sin pagar",G122="Pagar"),NETWORKDAYS($I$11,F122,'Festivos Colombia'!$A$3:$A$22),0) -> 0 | I122: =H122 -> 0
A123: =G123 -> Sin Pagar | B123: =IF(#REF!<=-1,1,IF(#REF!<=5,2,IF(#REF!<=15,3,IF(H123<=60,4)))) -> #REF! | C123: FPP434067 | D123: People Pass-Market | E123: =((1600000*1.19)-E120)*0 -> 0 | F123: 46032 | G123: Sin Pagar | H123: =IF(OR(G123="Sin pagar",G123="Pagar"),NETWORKDAYS($I$11,F123,'Festivos Colombia'!$A$3:$A$22),0) -> 29 | I123: =H123 -> 29 | J123: Saldo pendiente de pagar
D124: LIQUIDACIONES | E124: =SUBTOTAL(9,E125:E125) -> 151161703
...

Sheet ENERO
E1: 42400
D4: BANCOS | E4: =SUBTOTAL(9,E5:E5) -> 1.8610213e+09
D5: Bancos | E5: =DICIEMBRE!E137 -> 1.8610213e+09
D6: FACTURACIÓN PENDIENTE POR MONETIZAR | E6: =SUBTOTAL(9,E7:E7) -> 2.5253478e+09
D7: Monetización - facturación y Offycycle enero | E7: =45000000+2477791585.72+2556216 -> 2.5253478e+09
E8: =SUBTOTAL(9,E4:E7) -> 4.3863691e+09
C11: CUENTAS X PAGAR MES | E11: ENERO | F11: Fecha de Elaboración: | I11: 46023
C12: Factura | D12: PROVEEDOR | E12: VALOR | F12: Fecha vencimiento | G12: Estado | I12: KPI | J12: Objeto
D13: PAGOS ANTICIPADOS | E13: =SUBTOTAL(9,E14) -> 26559341
A14: =G14 -> Cancelado | B14: =IF(#REF!<=-1,1,IF(#REF!<=5,2,IF(#REF!<=15,3,IF(H14<=60,4)))) -> #REF! | C14: 1 registro | D14: Nómina Sergio Jimenez Belimo | E14: 26559341 | F14: 46050 | G14: Cancelado | H14: =IF(OR(G14="Sin pagar",G14="Pagar"),NETWORKDAYS($I$11,F14,'Festivos Colombia'!$A$3:$A$22),0) -> 0 | I14: =H14 -> 0
D15: SEGURIDAD SOCIAL | E15: =SUBTOTAL(9,E16:E16) -> 564617800
A16: =G16 -> Cancelado | B16: =IF(#REF!<=-1,1,IF(#REF!<=5,2,IF(#REF!<=15,3,IF(H16<=60,4)))) -> #REF! | D16: Pago seguridad social Global | E16: 564617800 | F16: 46031 | G16: Cancelado | H16: =IF(OR(G16="Sin pagar",G16="Pagar"),NETWORKDAYS($I$11,F16,'Festivos Colombia'!$A$3:$A$22),0) -> 0 | I16: =H16 -> 0
D17: AFC´S | E17: =SUBTOTAL(9,E18:E20) -> 64815500
A18: =G18 -> Cancelado | B18: =IF(#REF!<=-1,1,IF(#REF!<=5,2,IF(#REF!<=15,3,IF(H18<=60,4)))) -> #REF! | C18: 1 | D18: AFC y aportes voluntarios - Cheque | E18: 21300000 | F18: 46050 | G18: Cancelado | H18: =IF(OR(G18="Sin pagar",G18="Pagar"),NETWORKDAYS($I$11,F18,'Festivos Colombia'!$A$3:$A$22),0) -> 0 | I18: =H18 -> 0
A19: =G19 -> Cancelado | B19: =IF(#REF!<=-1,1,IF(#REF!<=5,2,IF(#REF!<=15,3,IF(H19<=60,4)))) -> #REF! | C19: 1 | D19: AFC y aportes voluntarios -SOI y Aportes en Linea | E19: 39715500 | F19: 46050 | G19: Cancelado | H19: =IF(OR(G19="Sin pagar",G19="Pagar"),NETWORKDAYS($I$11,F19,'Festivos Colombia'!$A$3:$A$22),0) -> 0 | I19: =H19 -> 0
A20: =G20 -> Cancelado | B20: =IF(#REF!<=-1,1,IF(#REF!<=5,2,IF(#REF!<=15,3,IF(H20<=60,4)))) -> #REF! | C20: 1 | D20: AFC y aportes voluntarios Aportes en Linea adicional Skandia | E20: 3800000 | F20: 46057 | G20: Cancelado | H20: =IF(OR(G20="Sin pagar",G20="Pagar"),NETWORKDAYS($I$11,F20,'Festivos Colombia'!$A$3:$A$22),0) -> 0 | I20: =H20 -> 0
D21: IMPUESTOS | E21: =SUBTOTAL(9,E22:E24) -> 416605000 | H21: =IF(OR(G21="Sin pagar",G21="Pagar"),NETWORKDAYS($I$11,F21,'Festivos Colombia'!$A$3:$A$22),0) -> 0 | I21: =H21 -> 0
A22: =G22 -> Cancelado | B22: =IF(#REF!<=-1,1,IF(#REF!<=5,2,IF(#REF!<=15,3,IF(H22<=60,4)))) -> #REF! | D22: Retención en la fuente | E22: 411959000 | F22: 46037 | G22: Cancelado | H22: =IF(OR(G22="Sin pagar",G22="Pagar"),NETWORKDAYS($I$11,F22,'Festivos Colombia'!$A$3:$A$22),0) -> 0 | I22: =H22 -> 0
A23: =G23 -> Cancelado | B23: =IF(#REF!<=-1,1,IF(#REF!<=5,2,IF(#REF!<=15,3,IF(H23<=60,4)))) -> #REF! | D23: IVA tecer cuatrimestre | E23: 4352000 | F23: 46037 | G23: Cancelado | H23: =IF(OR(G23="Sin pagar",G23="Pagar"),NETWORKDAYS($I$11,F23,'Festivos Colombia'!$A$3:$A$22),0) -> 0 | I23: =H23 -> 0
A24: =G24 -> Cancelado | B24: =IF(#REF!<=-1,1,IF(#REF!<=5,2,IF(#REF!<=15,3,IF(H24<=60,4)))) -> #REF! | D24: Retención de ICA 6to bimestre 2025 | E24: 294000 | F24: 46036 | G24: Cancelado | H24: =IF(OR(G24="Sin pagar",G24="Pagar"),NETWORKDAYS($I$11,F24,'Festivos Colombia'!$A$3:$A$22),0) -> 0 | I24: =H24 -> 0
D25: PLANES COMPLEMENTARIOS Y PREPAGADAS | E25: =SUBTOTAL(9,E26:E28) -> 6780762 | H25: =IF(OR(G25="Sin pagar",G25="Pagar"),NETWORKDAYS($I$11,F25,'Festivos Colombia'!$A$3:$A$22),0) -> 0
A26: =G26 -> Cancelado | B26: =IF(#REF!<=-1,1,IF(#REF!<=5,2,IF(#REF!<=15,3,IF(H26<=60,4)))) -> #REF! | C26: 20911207746 | D26: Póliza suramericana # 091000808150 SALUD FAMILIAR | E26: 4265060 | F26: 46053 | G26: Cancelado | H26: =IF(OR(G26="Sin pagar",G26="Pagar"),NETWORKDAYS($I$11,F26,'Festivos Colombia'!$A$3:$A$22),0) -> 0 | I26: =H26 -> 0
A27: =G27 -> Cancelado | B27: =IF(#REF!<=-1,1,IF(#REF!<=5,2,IF(#REF!<=15,3,IF(H27<=60,4)))) -> #REF! | C27: 20833359623 | D27: Póliza suramericana # 0904418894 SALUD FAMILIAR | E27: 437176 | F27: 46058 | G27: Cancelado | H27: =IF(OR(G27="Sin pagar",G27="Pagar"),NETWORKDAYS($I$11,F27,'Festivos Colombia'!$A$3:$A$22),0) -> 0 | I27: =H27 -> 0
A28: =G28 -> Cancelado | B28: =IF(#REF!<=-1,1,IF(#REF!<=5,2,IF(#REF!<=15,3,IF(H28<=60,4)))) -> #REF! | C28: 20911209250 | D28: Póliza suramericana # 091000808150 SALUD FAMILIAR | E28: 2078526 | F28: 46052 | G28: Cancelado | H28: =IF(OR(G28="Sin pagar",G28="Pagar"),NETWORKDAYS($I$11,F28,'Festivos Colombia'!$A$3:$A$22),0) -> 0 | I28: =H28 -> 0
D29: PÓLIZAS Y SEGUROS | E29: =SUBTOTAL(9,E30:E38) -> 0 | H29: =IF(OR(G29="Sin pagar",G29="Pagar"),NETWORKDAYS($I$11,F29,'Festivos Colombia'!$A$3:$A$22),0) -> 0
A30: =G30 -> Cancelado | B30: =IF(#REF!<=-1,1,IF(#REF!<=5,2,IF(#REF!<=15,3,IF(H30<=60,4)))) -> #REF! | C30: 12310058809 | D30: Plan grupo 10108069057 | E30: =13580700*0 -> 0 | F30: 46028 | G30: Cancelado | H30: =IF(OR(G30="Sin pagar",G30="Pagar"),NETWORKDAYS($I$11,F30,'Festivos Colombia'!$A$3:$A$22),0) -> 0 | I30: =H30 -> 0
A31: =G31 -> Cancelado | B31: =IF(#REF!<=-1,1,IF(#REF!<=5,2,IF(#REF!<=15,3,IF(H31<=60,4)))) -> #REF! | C31: 1239964849 | D31: Plan grupo 103226992 - Aana Aguirre - GRAINGER SERVICES INTERNATIONA | E31: =205538*0 -> 0 | F31: 46028 | G31: Cancelado | H31: =IF(OR(G31="Sin pagar",G31="Pagar"),NETWORKDAYS($I$11,F31,'Festivos Colombia'!$A$3:$A$22),0) -> 0 | I31: =H31 -> 0
A32: =G32 -> Cancelado | B32: =IF(#REF!<=-1,1,IF(#REF!<=5,2,IF(#REF!<=15,3,IF(H32<=60,4)))) -> #REF! | C32: 1239905171 | D32: Plan dental 103229130 Luna Rodriguez - LANO SOFTWARE GMBH | E32: =316953*0 -> 0 | F32: 46028 | G32: Cancelado | H32: =IF(OR(G32="Sin pagar",G32="Pagar"),NETWORKDAYS($I$11,F32,'Festivos Colombia'!$A$3:$A$22),0) -> 0 | I32: =H32 -> 0
A33: =G33 -> Cancelado | B33: =IF(#REF!<=-1,1,IF(#REF!<=5,2,IF(#REF!<=15,3,IF(H33<=60,4)))) -> #REF! | C33: 1239956382 | D33: Plan dental 10325327 Ivonne Torres | E33: =314213*0 -> 0 | F33: 46028 | G33: Cancelado | H33: =IF(OR(G33="Sin pagar",G33="Pagar"),NETWORKDAYS($I$11,F33,'Festivos Colombia'!$A$3:$A$22),0) -> 0 | I33: =H33 -> 0
A34: =G34 -> Cancelado | B34: =IF(#REF!<=-1,1,IF(#REF!<=5,2,IF(#REF!<=15,3,IF(H34<=60,4)))) -> #REF! | C34: 1231040566 | D34: Plan grupo 10108170475 - Sandra Barba - ALLEGIS GROUP INC | E34: =1751400*0 -> 0 | F34: 46028 | G34: Cancelado | H34: =IF(OR(G34="Sin pagar",G34="Pagar"),NETWORKDAYS($I$11,F34,'Festivos Colombia'!$A$3:$A$22),0) -> 0 | I34: =H34 -> 0
A35: =G35 -> Cancelado | B35: =IF(#REF!<=-1,1,IF(#REF!<=5,2,IF(#REF!<=15,3,IF(H35<=60,4)))) -> #REF! | C35: 1239902938 | D35: Plan grupo 103225452 - Freddy Gomez - TITAN METER BIDCO CORPORATION | E35: =339255*0 -> 0 | F35: 46028 | G35: Cancelado | H35: =IF(OR(G35="Sin pagar",G35="Pagar"),NETWORKDAYS($I$11,F35,'Festivos Colombia'!$A$3:$A$22),0) -> 0 | I35: =H35 -> 0
A36: =G36 -> Cancelado | B36: =IF(#REF!<=-1,1,IF(#REF!<=5,2,IF(#REF!<=15,3,IF(H36<=60,4)))) -> #REF! | C36: 1239987772 | D36: Plan grupo-103229134 - María Amaya Gomez - LANO SOFTWARE | E36: =71820*0 -> 0 | F36: 46028 | G36: Cancelado | H36: =IF(OR(G36="Sin pagar",G36="Pagar"),NETWORKDAYS($I$11,F36,'Festivos Colombia'!$A$3:$A$22),0) -> 0 | I36: =H36 -> 0
A37: =G37 -> Cancelado | B37: =IF(#REF!<=-1,1,IF(#REF!<=5,2,IF(#REF!<=15,3,IF(H37<=60,4)))) -> #REF! | C37: 1239909226 | D37: Plan grupo 10108174837 - Freddy Gomez - TITAN METER BIDCO CORPORATION | E37: =1984500*0 -> 0 | F37: 46028 | G37: Cancelado | H37: =IF(OR(G37="Sin pagar",G37="Pagar"),NETWORKDAYS($I$11,F37,'Festivos Colombia'!$A$3:$A$22),0) -> 0 | I37: =H37 -> 0
A38: =G38 -> Cancelado | B38: =IF(#REF!<=-1,1,IF(#REF!<=5,2,IF(#REF!<=15,3,IF(H38<=60,4)))) -> #REF! | C38: 12310060492 | D38: Plan grupo-103229134 - María Gabriela Acosta - LANO SOFTWARE | E38: =71820*0 -> 0 | F38: 46028 | G38: Cancelado | H38: =IF(OR(G38="Sin pagar",G38="Pagar"),NETWORKDAYS($I$11,F38,'Festivos Colombia'!$A$3:$A$22),0) -> 0 | I38: =H38 -> 0
D39: REEMBOLSO GASTOS VIAJE | E39: =SUBTOTAL(9,E40:E72) -> 69701217
D40: Reembolso Cristian Javier Gutierrez Torres-cc020 - Sophos | E40: =467154*0 -> 0 | F40: 46024 | G40: Cancelado | H40: =IF(OR(G40="Sin pagar",G40="Pagar"),NETWORKDAYS($I$11,F40,'Festivos Colombia'!$A$3:$A$22),0) -> 0 | I40: =H40 -> 0
D41: Reembolso Jorge Daniel Ramos DUran cc040 - Environmental Dynamics INTL | E41: =1000226*0 -> 0 | F41: 46024 | G41: Cancelado | H41: =IF(OR(G41="Sin pagar",G41="Pagar"),NETWORKDAYS($I$11,F41,'Festivos Colombia'!$A$3:$A$22),0) -> 0 | I41: =H41 -> 0
D42: Reembolso Edwin fernando alonso castelblanco cc020 - sophos | E42: =255113.01*0 -> 0 | F42: 46024 | G42: Cancelado | H42: =IF(OR(G42="Sin pagar",G42="Pagar"),NETWORKDAYS($I$11,F42,'Festivos Colombia'!$A$3:$A$22),0) -> 0 | I42: =H42 -> 0
D43: Reembolso Howard Antonio Donado Padilla cc073- Zenio | E43: =468000*0 -> 0 | F43: 46024 | G43: Cancelado | H43: =IF(OR(G43="Sin pagar",G43="Pagar"),NETWORKDAYS($I$11,F43,'Festivos Colombia'!$A$3:$A$22),0) -> 0 | I43: =H43 -> 0
D44: Reembolso Ivonne Torres-cc012 - lifenet health | E44: =1546810.95*0 -> 0 | F44: 46024 | G44: Cancelado | H44: =IF(OR(G44="Sin pagar",G44="Pagar"),NETWORKDAYS($I$11,F44,'Festivos Colombia'!$A$3:$A$22),0) -> 0 | I44: =H44 -> 0
D45: Reembolso Edith johana pineda zapata cc020 - sophos | E45: =1783405*0 -> 0 | F45: 46024 | G45: Cancelado | H45: =IF(OR(G45="Sin pagar",G45="Pagar"),NETWORKDAYS($I$11,F45,'Festivos Colombia'!$A$3:$A$22),0) -> 0 | I45: =H45 -> 0
D46: Reembolso Mario Fernando Benitez Zabala cc020 - sophos | E46: =166330*0 -> 0 | F46: 46024 | G46: Cancelado | H46: =IF(OR(G46="Sin pagar",G46="Pagar"),NETWORKDAYS($I$11,F46,'Festivos Colombia'!$A$3:$A$22),0) -> 0 | I46: =H46 -> 0
D47: Reembolso Cristiam Silva cc020 - sophos | E47: 457800 | F47: 46035 | G47: Cancelado | H47: =IF(OR(G47="Sin pagar",G47="Pagar"),NETWORKDAYS($I$11,F47,'Festivos Colombia'!$A$3:$A$22),0) -> 0 | I47: =H47 -> 0
D48: Reembolso Jhon Grazon cc020 - sophos | E48: 3095450 | F48: 46035 | G48: Cancelado | H48: =IF(OR(G48="Sin pagar",G48="Pagar"),NETWORKDAYS($I$11,F48,'Festivos Colombia'!$A$3:$A$22),0) -> 0 | I48: =H48 -> 0
D49: Reembolso Juan Pablo Giraldo Rios CC037 - EDRINGTON AMERICAS | E49: 8034380 | F49: 46035 | G49: Cancelado | H49: =IF(OR(G49="Sin pagar",G49="Pagar"),NETWORKDAYS($I$11,F49,'Festivos Colombia'!$A$3:$A$22),0) -> 0 | I49: =H49 -> 0
D50: Reembolso Jorge Crismatt cc060 - Best Formulation | E50: 1605910 | F50: 46041 | G50: Cancelado | H50: =IF(OR(G50="Sin pagar",G50="Pagar"),NETWORKDAYS($I$11,F50,'Festivos Colombia'!$A$3:$A$22),0) -> 0 | I50: =H50 -> 0
D51: Reembolso Mario Benitez cc020 - sophos | E51: 128200 | F51: 46041 | G51: Cancelado | H51: =IF(OR(G51="Sin pagar",G51="Pagar"),NETWORKDAYS($I$11,F51,'Festivos Colombia'!$A$3:$A$22),0) -> 0 | I51: =H51 -> 0
D52: Reembolso Paula Andrea Alba cc020 - sophos | E52: 1227258 | F52: 46041 | G52: Cancelado | H52: =IF(OR(G52="Sin pagar",G52="Pagar"),NETWORKDAYS($I$11,F52,'Festivos Colombia'!$A$3:$A$22),0) -> 0 | I52: =H52 -> 0
D53: Reembolso Cristiam Silva cc020 - sophos | E53: 218138 | F53: 46048 | G53: Cancelado | H53: =IF(OR(G53="Sin pagar",G53="Pagar"),NETWORKDAYS($I$11,F53,'Festivos Colombia'!$A$3:$A$22),0) -> 0 | I53: =H53 -> 0
D54: Reembolso Maria Claudia Bohorquez cc020 - sophos | E54: 159048 | F54: 46048 | G54: Cancelado | H54: =IF(OR(G54="Sin pagar",G54="Pagar"),NETWORKDAYS($I$11,F54,'Festivos Colombia'!$A$3:$A$22),0) -> 0 | I54: =H54 -> 0
D55: Reembolso Jhon Garzon cc020 - sophos | E55: 702200 | F55: 46048 | G55: Cancelado | H55: =IF(OR(G55="Sin pagar",G55="Pagar"),NETWORKDAYS($I$11,F55,'Festivos Colombia'!$A$3:$A$22),0) -> 0 | I55: =H55 -> 0
D56: Reembolso Jorge Crismatt cc060 - Best Formulation | E56: 4081067 | F56: 46048 | G56: Cancelado | H56: =IF(OR(G56="Sin pagar",G56="Pagar"),NETWORKDAYS($I$11,F56,'Festivos Colombia'!$A$3:$A$22),0) -> 0 | I56: =H56 -> 0
D57: Reembolso Mairilyn Restrepo cc020 - sophos | E57: 1656286 | F57: 46048 | G57: Cancelado | H57: =IF(OR(G57="Sin pagar",G57="Pagar"),NETWORKDAYS($I$11,F57,'Festivos Colombia'!$A$3:$A$22),0) -> 0 | I57: =H57 -> 0
D58: Reembolso Jandres Arbelaez CC037 - EDRINGTON AMERICAS | E58: 1098209 | F58: 46048 | G58: Cancelado | H58: =IF(OR(G58="Sin pagar",G58="Pagar"),NETWORKDAYS($I$11,F58,'Festivos Colombia'!$A$3:$A$22),0) -> 0 | I58: =H58 -> 0
... D66: Reembolso Giraldo Rios Juan Pablo CC037 - EDRINGTON AMERICAS | E66: 3690775 | F66: 46050 | G66: Cancelado | H66: =IF(OR(G66="Sin pagar",G66="Pagar"),NETWORKDAYS($I$11,F66,'Festivos Colombia'!$A$3:$A$22),0) -> 0 | I66: =H66 -> 0
D67: Reembolso Edwin fernando alonso castelblanco cc020 - sophos | E67: 1794290 | F67: 46051 | G67: Cancelado
D68: Reembolso Stephanie Perez cc020 - sophos | E68: 3309679 | F68: 46051 | G68: Cancelado
D69: Reembolso Mairilyn Restrepo cc020 - sophos | E69: 190111 | F69: 46051 | G69: Cancelado
D70: Reembolso Mario Benitez cc020 - sophos | E70: 166330 | F70: 46051 | G70: Cancelado
D71: Reembolso Milagro del Vallle Sanchez cc020 - sophos | E71: 2067282 | F71: 46051 | G71: Cancelado
D72: Reembolso Andy Muñoz CC021 - HITACHI GLOBAL AIR POWER Pago Cotización D GROUPE SAS | E72: 3800750 | F72: 46051 | G72: Cancelado
D73: TIQUETES AÉREOS , HOTELES | E73: =SUBTOTAL(9,E74:E79) -> 13084610
D74: Tiquete Andy Muñoz Cartagena-ciudades estados unidos Vsa-Equipaje Cartagena | E74: =4405740*0 -> 0 | F74: 46028 | G74: Cancelado | H74: =IF(OR(G74="Sin pagar",G74="Pagar"),NETWORKDAYS($I$11,F74,'Festivos Colombia'!$A$3:$A$22),0) -> 0 | I74: =H74 -> 0
D75: Tiquete Sandra Barba Bog - Ciudad de México - Bog | E75: 2961580 | F75: 46030 | G75: Cancelado | H75: =IF(OR(G75="Sin pagar",G75="Pagar"),NETWORKDAYS($I$11,F75,'Festivos Colombia'!$A$3:$A$22),0) -> 0 | I75: =H75 -> 0
D76: Tiquete Sandra Barba Viaje a Brasil | E76: 4685820 | F76: 46036 | G76: Cancelado
D77: Tiquete Sandra Barba Viaje a Monterrey | E77: 884000 | F77: 46037 | G77: Cancelado
D78: Tiquete Catalina Duque Bogotá-Cartagena y Vsa | E78: 1268210 | F78: 46044 | G78: Cancelado
D79: Tiquete Sandra Barba Bog - SFO - Bog | E79: 3285000 | F79: 46057 | G79: Cancelado
D80: ASESORÍAS | E80: =SUBTOTAL(9,E81:E82) -> 19282040
A81: =G81 -> Cancelado | B81: =IF(#REF!<=-1,1,IF(#REF!<=5,2,IF(#REF!<=15,3,IF(H81<=60,4)))) -> #REF! | C81: 6554 | D81: Global CS Colombia SAS -Solutions & payroll-Servicio Diciembre 2025 | E81: 18922046 | F81: 46031 | G81: Cancelado | H81: =IF(OR(G81="Sin pagar",G81="Pagar"),NETWORKDAYS($I$11,F81,'Festivos Colombia'!$A$3:$A$22),0) -> 0 | I81: =H81 -> 0
A82: =G82 -> Cancelado | B82: =IF(#REF!<=-1,1,IF(#REF!<=5,2,IF(#REF!<=15,3,IF(H82<=60,4)))) -> #REF! | C82: 5-163 | D82: Global CS Colombia SAS -Solutions & payroll- Reembolso Gastos Diciembre | E82: 359994 | F82: 46031 | G82: Cancelado | H82: =IF(OR(G82="Sin pagar",G82="Pagar"),NETWORKDAYS($I$11,F82,'Festivos Colombia'!$A$3:$A$22),0) -> 0 | I82: =H82 -> 0
D83: COSTOS FINANCIEROS | E83: =SUBTOTAL(9,E84) -> 13087371
A84: =G84 -> Cancelado | B84: =IF(#REF!<=-1,1,IF(#REF!<=5,2,IF(#REF!<=15,3,IF(H84<=60,4)))) -> #REF! | D84: Costos financieros (Cuenta GLOBAL CS) | E84: 13087371 | F84: 46053 | G84: Cancelado | H84: =IF(OR(G84="Sin pagar",G84="Pagar"),NETWORKDAYS($I$11,F84,'Festivos Colombia'!$A$3:$A$22),0) -> 0 | I84: =H84 -> 0
D85: CREDITOS Y LIBRANZAS | E85: =SUBTOTAL(9,E86) -> 2209861
A86: =G86 -> Cancelado | B86: =IF(#REF!<=-1,1,IF(#REF!<=5,2,IF(#REF!<=15,3,IF(H86<=60,4)))) -> #REF! | D86: Libranza compensar | E86: 2209861 | F86: 46050 | G86: Cancelado | H86: =IF(OR(G86="Sin pagar",G86="Pagar"),NETWORKDAYS($I$11,F86,'Festivos Colombia'!$A$3:$A$22),0) -> 0 | I86: =H86 -> 0
D87: ESTUDIOS DE SEGURIDAD Y EXAMENES OCUPACIONALES-PÓLIZAS SALUD | E87: =SUBTOTAL(9,E88:E93) -> 2822706
A88: =G88 -> Cancelado | B88: =IF(#REF!<=-1,1,IF(#REF!<=5,2,IF(#REF!<=15,3,IF(H88<=60,4)))) -> #REF! | C88: 6838 | D88: EMASOC | E88: =205000 -> 205000 | F88: 46031 | G88: Cancelado | H88: =IF(OR(G88="Sin pagar",G88="Pagar"),NETWORKDAYS($I$11,F88,'Festivos Colombia'!$A$3:$A$22),0) -> 0 | I88: =H88 -> 0
A89: =G89 -> Cancelado | B89: =IF(#REF!<=-1,1,IF(#REF!<=5,2,IF(#REF!<=15,3,IF(H89<=60,4)))) -> #REF! | C89: 6845 | D89: EMASOC | E89: =1432500 -> 1432500 | F89: 46031 | G89: Cancelado | H89: =IF(OR(G89="Sin pagar",G89="Pagar"),NETWORKDAYS($I$11,F89,'Festivos Colombia'!$A$3:$A$22),0) -> 0 | I89: =H89 -> 0
A90: =G90 -> Cancelado | B90: =IF(#REF!<=-1,1,IF(#REF!<=5,2,IF(#REF!<=15,3,IF(H90<=60,4)))) -> #REF! | C90: 6856 | D90: EMASOC | E90: =406500 -> 406500 | F90: 46038 | G90: Cancelado | H90: =IF(OR(G90="Sin pagar",G90="Pagar"),NETWORKDAYS($I$11,F90,'Festivos Colombia'!$A$3:$A$22),0) -> 0 | I90: =H90 -> 0
A91: =G91 -> Cancelado | B91: =IF(#REF!<=-1,1,IF(#REF!<=5,2,IF(#REF!<=15,3,IF(H91<=60,4)))) -> #REF! | C91: 6860 | D91: EMASOC | E91: =311500 -> 311500 | F91: 46038 | G91: Cancelado | H91: =IF(OR(G91="Sin pagar",G91="Pagar"),NETWORKDAYS($I$11,F91,'Festivos Colombia'!$A$3:$A$22),0) -> 0 | I91: =H91 -> 0
A92: =G92 -> Cancelado | B92: =IF(#REF!<=-1,1,IF(#REF!<=5,2,IF(#REF!<=15,3,IF(H92<=60,4)))) -> #REF! | C92: 16001350783712 | D92: Allianz Póliza No: 23730847- Jerson Porras | E92: =467206 -> 467206 | F92: 46052 | G92: Cancelado | H92: =IF(OR(G92="Sin pagar",G92="Pagar"),NETWORKDAYS($I$11,F92,'Festivos Colombia'!$A$3:$A$22),0) -> 0 | I92: =H92 -> 0
A93: =G93 -> Sin Pagar | B93: =IF(#REF!<=-1,1,IF(#REF!<=5,2,IF(#REF!<=15,3,IF(H93<=60,4)))) -> #REF! | C93: 6872 | D93: EMASOC | E93: =178500*0 -> 0 | F93: 46066 | G93: Sin Pagar | H93: =IF(OR(G93="Sin pagar",G93="Pagar"),NETWORKDAYS($I$11,F93,'Festivos Colombia'!$A$3:$A$22),0) -> 30 | I93: =H93 -> 30
D94: NÓMINAS Y ABONO A TARJETAS PEOPLE PASS | E94: =SUBTOTAL(9,E95:E99) -> 1480382960
A95: =G95 -> Cancelado | B95: =IF(#REF!<=-1,1,IF(#REF!<=5,2,IF(#REF!<=15,3,IF(H95<=60,4)))) -> #REF! | D95: Monetización Sena Diciembre | E95: 6405750 | F95: 46029 | G95: Cancelado | H95: =IF(OR(G95="Sin pagar",G95="Pagar"),NETWORKDAYS($I$11,F95,'Festivos Colombia'!$A$3:$A$22),0) -> 0 | I95: =H95 -> 0
A96: =G96 -> Cancelado | B96: =IF(#REF!<=-1,1,IF(#REF!<=5,2,IF(#REF!<=15,3,IF(H96<=60,4)))) -> #REF! | C96: FPP439858 | D96: People Pass-Market-Diciembre | E96: 815232 | F96: 46038 | G96: Cancelado | H96: =IF(OR(G96="Sin pagar",G96="Pagar"),NETWORKDAYS($I$11,F96,'Festivos Colombia'!$A$3:$A$22),0) -> 0 | I96: =H96 -> 0 | J96: Saldo pendiente de pagar
A97: =G97 -> Cancelado | B97: =IF(#REF!<=-1,1,IF(#REF!<=5,2,IF(#REF!<=15,3,IF(H97<=60,4)))) -> #REF! | C97: 87 Registros | D97: Nomina OE | E97: 1463652441 | F97: 46050 | G97: Cancelado | H97: =IF(OR(G97="Sin pagar",G97="Pagar"),NETWORKDAYS($I$11,F97,'Festivos Colombia'!$A$3:$A$22),0) -> 0 | I97: =H97 -> 0
A98: =G98 -> Cancelado | B98: =IF(#REF!<=-1,1,IF(#REF!<=5,2,IF(#REF!<=15,3,IF(H98<=60,4)))) -> #REF! | C98: FPP443638 | D98: People Pass-Market Enero | E98: 1630464 | F98: 46050 | G98: Cancelado | H98: =IF(OR(G98="Sin pagar",G98="Pagar"),NETWORKDAYS($I$11,F98,'Festivos Colombia'!$A$3:$A$22),0) -> 0 | I98: =H98 -> 0
A99: =G99 -> Cancelado | B99: =IF(#REF!<=-1,1,IF(#REF!<=5,2,IF(#REF!<=15,3,IF(H99<=60,4)))) -> #REF! | D99: Monetización Sena Enero | E99: 7879073 | F99: 46052 | G99: Cancelado | H99: =IF(OR(G99="Sin pagar",G99="Pagar"),NETWORKDAYS($I$11,F99,'Festivos Colombia'!$A$3:$A$22),0) -> 0 | I99: =H99 -> 0
D100: LIQUIDACIONES | E100: =SUBTOTAL(9,E101:E105) -> 45716452
A101: =G101 -> Cancelado | B101: =IF(#REF!<=-1,1,IF(#REF!<=5,2,IF(#REF!<=15,3,IF(H101<=60,4)))) -> #REF! | C101: 1 registro | D101: Liquidación Howard Antonio Donado Padilla cc073- Zennio | E101: 8291057 | F101: 46036 | G101: Cancelado | H101: =IF(OR(G101="Sin pagar",G101="Pagar"),NETWORKDAYS($I$11,F101,'Festivos Colombia'!$A$3:$A$22),0) -> 0 | I101: =H101 -> 0
A102: =G102 -> Cancelado | B102: =IF(#REF!<=-1,1,IF(#REF!<=5,2,IF(#REF!<=15,3,IF(H102<=60,4)))) -> #REF! | C102: 1 registro | D102: Liquidación Pablo Andres Ossa Ocampo cc073- Zennio | E102: 6044770 | F102: 46036 | G102: Cancelado | H102: =IF(OR(G102="Sin pagar",G102="Pagar"),NETWORKDAYS($I$11,F102,'Festivos Colombia'!$A$3:$A$22),0) -> 0 | I102: =H102 -> 0
A103: =G103 -> Cancelado | B103: =IF(#REF!<=-1,1,IF(#REF!<=5,2,IF(#REF!<=15,3,IF(H103<=60,4)))) -> #REF! | C103: 1 registro | D103: Liquidación Sandra Juliana Mariño Lozano-cc073 - Zennio | E103: 13610885 | F103: 46038 | G103: Cancelado | H103: =IF(OR(G103="Sin pagar",G103="Pagar"),NETWORKDAYS($I$11,F103,'Festivos Colombia'!$A$3:$A$22),0) -> 0 | I103: =H103 -> 0
A104: =G104 -> Cancelado | B104: =IF(#REF!<=-1,1,IF(#REF!<=5,2,IF(#REF!<=15,3,IF(H104<=60,4)))) -> #REF! | C104: 1 registro | D104: Liquidación Andrea del Pilar Alvarado - Oportunity International | E104: 17769740 | F104: 46052 | G104: Cancelado | H104: =IF(OR(G104="Sin pagar",G104="Pagar"),NETWORKDAYS($I$11,F104,'Festivos Colombia'!$A$3:$A$22),0) -> 0 | I104: =H104 -> 0
A105: =G105 -> Sin Pagar | B105: =IF(#REF!<=-1,1,IF(#REF!<=5,2,IF(#REF!<=15,3,IF(H105<=60,4)))) -> #REF! | C105: 1 registro | D105: Liquidaciones previstas | E105: =200401562*0 -> 0 | F105: 46059 | G105: Sin Pagar | H105: =IF(OR(G105="Sin pagar",G105="Pagar"),NETWORKDAYS($I$11,F105,'Festivos Colombia'!$A$3:$A$22),0) -> 25 | I105: =H105 -> 25
D106: IMPREVISTO | E106: =SUBTOTAL(9,E107:E107) -> 0
A107: =G107 -> Cancelado | B107: =IF(#REF!<=-1,1,IF(#REF!<=5,2,IF(#REF!<=15,3,IF(H107<=60,4)))) -> #REF! | D107: Imprevisto | E107: 0 | F107: 46053 | G107: Cancelado | H107: =IF(OR(G107="Sin pagar",G107="Pagar"),NETWORKDAYS($I$11,F107,'Festivos Colombia'!$A$3:$A$22),0) -> 0 | I107: =H107 -> 0
D108: TOTAL EGRESOS | E108: =SUBTOTAL(9,E13:E107) -> 2.7256656e+09
D109: 4 x mil transacciones | E109: =(E108*4)/1000 -> 10902662
D110: TOTAL A PAGAR | E110: =E108+E109 -> 2.7365683e+09 | G110: Sin Pagar
D114: SALDO | E114: =E8-E108 -> 1.6607035e+09
...

Sheet FEBRERO
E1: 42400
D4: BANCOS | E4: =SUBTOTAL(9,E5:E5) -> 1.6607035e+09
D5: Bancos | E5: =ENERO!$E$114 -> 1.6607035e+09
D6: FACTURACIÓN PENDIENTE POR MONETIZAR | E6: =SUBTOTAL(9,E7:E7) -> 2.8571378e+09
D7: Monetización - facturación y Offycycle Febrero | E7: =22812718.88+65000000+244115339.06+2385335023+116957872+22916818 -> 2.8571378e+09
E8: =SUBTOTAL(9,E4:E7) -> 4.5178413e+09
C11: CUENTAS X PAGAR MES | E11: FEBRERO | F11: Fecha de Elaboración: | I11: 46054
C12: Factura | D12: PROVEEDOR | E12: VALOR | F12: Fecha vencimiento | G12: Estado | I12: KPI | J12: Objeto
D13: PAGOS ANTICIPADOS | E13: =SUBTOTAL(9,E14) -> 25815079
A14: =G14 -> Cancelado | B14: =IF(#REF!<=-1,1,IF(#REF!<=5,2,IF(#REF!<=15,3,IF(H14<=60,4)))) -> #REF! | C14: 1 registro | D14: Nómina Sergio Jimenez Belimo | E14: 25815079 | F14: 46079 | G14: Cancelado | H14: =IF(OR(G14="Sin pagar",G14="Pagar"),NETWORKDAYS($I$11,F14,'Festivos Colombia'!$A$3:$A$22),0) -> 0 | I14: =H14 -> 0
D15: SEGURIDAD SOCIAL | E15: =SUBTOTAL(9,E16:E16) -> 553473400
A16: =G16 -> Cancelado | B16: =IF(#REF!<=-1,1,IF(#REF!<=5,2,IF(#REF!<=15,3,IF(H16<=60,4)))) -> #REF! | D16: Pago seguridad social Global | E16: 553473400 | F16: 46065 | G16: Cancelado | H16: =IF(OR(G16="Sin pagar",G16="Pagar"),NETWORKDAYS($I$11,F16,'Festivos Colombia'!$A$3:$A$22),0) -> 0 | I16: =H16 -> 0
D17: AFC´S | E17: =SUBTOTAL(9,E18:E19) -> 69505500
A18: =G18 -> Cancelado | B18: =IF(#REF!<=-1,1,IF(#REF!<=5,2,IF(#REF!<=15,3,IF(H18<=60,4)))) -> #REF! | C18: 1 | D18: AFC y aportes voluntarios - Cheque | E18: 19300000 | F18: 46080 | G18: Cancelado | H18: =IF(OR(G18="Sin pagar",G18="Pagar"),NETWORKDAYS($I$11,F18,'Festivos Colombia'!$A$3:$A$22),0) -> 0 | I18: =H18 -> 0
A19: =G19 -> Cancelado | B19: =IF(#REF!<=-1,1,IF(#REF!<=5,2,IF(#REF!<=15,3,IF(H19<=60,4)))) -> #REF! | C19: 1 | D19: AFC y aportes voluntarios -SOI y Aportes en Linea | E19: 50205500 | F19: 46077 | G19: Cancelado | H19: =IF(OR(G19="Sin pagar",G19="Pagar"),NETWORKDAYS($I$11,F19,'Festivos Colombia'!$A$3:$A$22),0) -> 0 | I19: =H19 -> 0
D20: IMPUESTOS | E20: =SUBTOTAL(9,E21:E22) -> 261448000 | H20: =IF(OR(G20="Sin pagar",G20="Pagar"),NETWORKDAYS($I$11,F20,'Festivos Colombia'!$A$3:$A$22),0) -> 0 | I20: =H20 -> 0
A21: =G21 -> Cancelado | B21: =IF(#REF!<=-1,1,IF(#REF!<=5,2,IF(#REF!<=15,3,IF(H21<=60,4)))) -> #REF! | D21: Retención en la fuente | E21: 258734000 | F21: 46065 | G21: Cancelado | H21: =IF(OR(G21="Sin pagar",G21="Pagar"),NETWORKDAYS($I$11,F21,'Festivos Colombia'!$A$3:$A$22),0) -> 0 | I21: =H21 -> 0
A22: =G22 -> Cancelado | B22: =IF(#REF!<=-1,1,IF(#REF!<=5,2,IF(#REF!<=15,3,IF(H22<=60,4)))) -> #REF! | D22: ICA anual | E22: 2714000 | F22: 46077 | G22: Cancelado | H22: =IF(OR(G22="Sin pagar",G22="Pagar"),NETWORKDAYS($I$11,F22,'Festivos Colombia'!$A$3:$A$22),0) -> 0 | I22: =H22 -> 0
D23: PLANES COMPLEMENTARIOS Y PREPAGADAS | E23: =SUBTOTAL(9,E24:E29) -> 14951682 | H23: =IF(OR(G23="Sin pagar",G23="Pagar"),NETWORKDAYS($I$11,F23,'Festivos Colombia'!$A$3:$A$22),0) -> 0
A24: =G24 -> Cancelado | B24: =IF(#REF!<=-1,1,IF(#REF!<=5,2,IF(#REF!<=15,3,IF(H24<=60,4)))) -> #REF! | C24: 20911209571 | D24: Póliza suramericana # 091000808150 SALUD FAMILIAR | E24: 576588 | F24: 46078 | G24: Cancelado | H24: =IF(OR(G24="Sin pagar",G24="Pagar"),NETWORKDAYS($I$11,F24,'Festivos Colombia'!$A$3:$A$22),0) -> 0 | I24: =H24 -> 0
A25: =G25 -> Cancelado | B25: =IF(#REF!<=-1,1,IF(#REF!<=5,2,IF(#REF!<=15,3,IF(H25<=60,4)))) -> #REF! | C25: 20911209572 | D25: Póliza suramericana # 091000808150 SALUD FAMILIAR | E25: 165038 | F25: 46078 | G25: Cancelado | H25: =IF(OR(G25="Sin pagar",G25="Pagar"),NETWORKDAYS($I$11,F25,'Festivos Colombia'!$A$3:$A$22),0) -> 0 | I25: =H25 -> 0
A26: =G26 -> Cancelado | B26: =IF(#REF!<=-1,1,IF(#REF!<=5,2,IF(#REF!<=15,3,IF(H26<=60,4)))) -> #REF! | C26: 20911209573 | D26: Póliza suramericana # 091000808150 SALUD FAMILIAR | E26: 169028 | F26: 46078 | G26: Cancelado | H26: =IF(OR(G26="Sin pagar",G26="Pagar"),NETWORKDAYS($I$11,F26,'Festivos Colombia'!$A$3:$A$22),0) -> 0 | I26: =H26 -> 0
A27: =G27 -> Cancelado | B27: =IF(#REF!<=-1,1,IF(#REF!<=5,2,IF(#REF!<=15,3,IF(H27<=60,4)))) -> #REF! | C27: 20911214073 | D27: Póliza suramericana # 091000808150 SALUD FAMILIAR | E27: 2196266 | F27: 46084 | G27: Cancelado | H27: =IF(OR(G27="Sin pagar",G27="Pagar"),NETWORKDAYS($I$11,F27,'Festivos Colombia'!$A$3:$A$22),0) -> 0 | I27: =H27 -> 0
A28: =G28 -> Cancelado | B28: =IF(#REF!<=-1,1,IF(#REF!<=5,2,IF(#REF!<=15,3,IF(H28<=60,4)))) -> #REF! | C28: 209833411130 | D28: Póliza suramericana # 0904418894 SALUD FAMILIAR | E28: 437176 | F28: 46084 | G28: Cancelado | H28: =IF(OR(G28="Sin pagar",G28="Pagar"),NETWORKDAYS($I$11,F28,'Festivos Colombia'!$A$3:$A$22),0) -> 0 | I28: =H28 -> 0
A29: =G29 -> Cancelado | B29: =IF(#REF!<=-1,1,IF(#REF!<=5,2,IF(#REF!<=15,3,IF(H29<=60,4)))) -> #REF! | C29: 20911213105 | D29: Póliza suramericana # 091000808150 SALUD FAMILIAR | E29: 11407586 | F29: 46084 | G29: Cancelado | H29: =IF(OR(G29="Sin pagar",G29="Pagar"),NETWORKDAYS($I$11,F29,'Festivos Colombia'!$A$3:$A$22),0) -> 0 | I29: =H29 -> 0
D30: PÓLIZAS Y SEGUROS | E30: =SUBTOTAL(9,E31:E40) -> 20743199 | H30: =IF(OR(G30="Sin pagar",G30="Pagar"),NETWORKDAYS($I$11,F30,'Festivos Colombia'!$A$3:$A$22),0) -> 0
A31: =G31 -> Cancelado | B31: =IF(#REF!<=-1,1,IF(#REF!<=5,2,IF(#REF!<=15,3,IF(H31<=60,4)))) -> #REF! | C31: 10175650 | D31: Plan grupo 10108069057 | E31: =13580700 -> 13580700 | F31: 46058 | G31: Cancelado | H31: =IF(OR(G31="Sin pagar",G31="Pagar"),NETWORKDAYS($I$11,F31,'Festivos Colombia'!$A$3:$A$22),0) -> 0 | I31: =H31 -> 0
A32: =G32 -> Cancelado | B32: =IF(#REF!<=-1,1,IF(#REF!<=5,2,IF(#REF!<=15,3,IF(H32<=60,4)))) -> #REF! | C32: 10226780 | D32: Plan grupo 103226992 - Aana Aguirre - GRAINGER SERVICES INTERNATIONA | E32: =205538 -> 205538 | F32: 46058 | G32: Cancelado | H32: =IF(OR(G32="Sin pagar",G32="Pagar"),NETWORKDAYS($I$11,F32,'Festivos Colombia'!$A$3:$A$22),0) -> 0 | I32: =H32 -> 0
A33: =G33 -> Cancelado | B33: =IF(#REF!<=-1,1,IF(#REF!<=5,2,IF(#REF!<=15,3,IF(H33<=60,4)))) -> #REF! | C33: 10090637 | D33: Plan dental 103229130 Luna Rodriguez - LANO SOFTWARE GMBH | E33: =316953 -> 316953 | F33: 46058 | G33: Cancelado | H33: =IF(OR(G33="Sin pagar",G33="Pagar"),NETWORKDAYS($I$11,F33,'Festivos Colombia'!$A$3:$A$22),0) -> 0 | I33: =H33 -> 0
A34: =G34 -> Cancelado | B34: =IF(#REF!<=-1,1,IF(#REF!<=5,2,IF(#REF!<=15,3,IF(H34<=60,4)))) -> #REF! | C34: 10238635 | D34: Plan dental 10325327 Ivonne Torres | E34: =314213 -> 314213 | F34: 46058 | G34: Cancelado | H34: =IF(OR(G34="Sin pagar",G34="Pagar"),NETWORKDAYS($I$11,F34,'Festivos Colombia'!$A$3:$A$22),0) -> 0 | I34: =H34 -> 0
A35: =G35 -> Cancelado | B35: =IF(#REF!<=-1,1,IF(#REF!<=5,2,IF(#REF!<=15,3,IF(H35<=60,4)))) -> #REF! | C35: 10225583 | D35: Plan grupo 10108170475 - Sandra Barba - ALLEGIS GROUP INC | E35: =1751400 -> 1751400 | F35: 46058 | G35: Cancelado | H35: =IF(OR(G35="Sin pagar",G35="Pagar"),NETWORKDAYS($I$11,F35,'Festivos Colombia'!$A$3:$A$22),0) -> 0 | I35: =H35 -> 0
A36: =G36 -> Cancelado | B36: =IF(#REF!<=-1,1,IF(#REF!<=5,2,IF(#REF!<=15,3,IF(H36<=60,4)))) -> #REF! | C36: 10230226 | D36: Plan grupo 103225452 - Freddy Gomez - TITAN METER BIDCO CORPORATION | E36: =339255 -> 339255 | F36: 46059 | G36: Cancelado | H36: =IF(OR(G36="Sin pagar",G36="Pagar"),NETWORKDAYS($I$11,F36,'Festivos Colombia'!$A$3:$A$22),0) -> 0 | I36: =H36 -> 0
A37: =G37 -> Cancelado | B37: =IF(#REF!<=-1,1,IF(#REF!<=5,2,IF(#REF!<=15,3,IF(H37<=60,4)))) -> #REF! | C37: 10173108 | D37: Plan grupo-103229134 - María Amaya Gomez - LANO SOFTWARE | E37: =71820 -> 71820 | F37: 46058 | G37: Cancelado | H37: =IF(OR(G37="Sin pagar",G37="Pagar"),NETWORKDAYS($I$11,F37,'Festivos Colombia'!$A$3:$A$22),0) -> 0 | I37: =H37 -> 0
A38: =G38 -> Cancelado | B38: =IF(#REF!<=-1,1,IF(#REF!<=5,2,IF(#REF!<=15,3,IF(H38<=60,4)))) -> #REF! | C38: 10094969 | D38: Plan grupo 10108174837 - Freddy Gomez - TITAN METER BIDCO CORPORATION | E38: =1984500 -> 1984500 | F38: 46058 | G38: Cancelado | H38: =IF(OR(G38="Sin pagar",G38="Pagar"),NETWORKDAYS($I$11,F38,'Festivos Colombia'!$A$3:$A$22),0) -> 0 | I38: =H38 -> 0
A39: =G39 -> Cancelado | B39: =IF(#REF!<=-1,1,IF(#REF!<=5,2,IF(#REF!<=15,3,IF(H39<=60,4)))) -> #REF! | C39: 10245676 | D39: Plan grupo-103229134 - María Gabriela Acosta - LANO SOFTWARE | E39: =71820 -> 71820 | F39: 46058 | G39: Cancelado | H39: =IF(OR(G39="Sin pagar",G39="Pagar"),NETWORKDAYS($I$11,F39,'Festivos Colombia'!$A$3:$A$22),0) -> 0 | I39: =H39 -> 0
A40: =G40 -> Cancelado | B40: =IF(#REF!<=-1,1,IF(#REF!<=5,2,IF(#REF!<=15,3,IF(H40<=60,4)))) -> #REF! | C40: 10245676 | D40: Póliza Sanitas Carlos Urrego | E40: 2107000 | F40: 46069 | G40: Cancelado | H40: =IF(OR(G40="Sin pagar",G40="Pagar"),NETWORKDAYS($I$11,F40,'Festivos Colombia'!$A$3:$A$22),0) -> 0 | I40: =H40 -> 0
D41: REEMBOLSO GASTOS VIAJE | E41: =SUBTOTAL(9,E42:E91) -> 1.2685418e+08
D42: Reembolso Maria Claudia Bohorquez cc020 - sophos | E42: 226425 | F42: 46059 | G42: Cancelado | H42: =IF(OR(G42="Sin pagar",G42="Pagar"),NETWORKDAYS($I$11,F42,'Festivos Colombia'!$A$3:$A$22),0) -> 0 | I42: =H42 -> 0
D43: Reembolso Fabian Augusto Porto Dulcey cc020 - Sophos | E43: 4250341 | F43: 46059 | G43: Cancelado | H43: =IF(OR(G43="Sin pagar",G43="Pagar"),NETWORKDAYS($I$11,F43,'Festivos Colombia'!$A$3:$A$22),0) -> 0 | I43: =H43 -> 0
D44: Reembolso Ivonne Torres-cc012 - lifenet health | E44: 298700 | F44: 46059 | G44: Cancelado | H44: =IF(OR(G44="Sin pagar",G44="Pagar"),NETWORKDAYS($I$11,F44,'Festivos Colombia'!$A$3:$A$22),0) -> 0 | I44: =H44 -> 0
D45: Reembolso Jhon Jairo Garzon Beleño cc020 - Sophos | E45: 3151900 | F45: 46059 | G45: Cancelado | H45: =IF(OR(G45="Sin pagar",G45="Pagar"),NETWORKDAYS($I$11,F45,'Festivos Colombia'!$A$3:$A$22),0) -> 0 | I45: =H45 -> 0
D46: Reembolso Laura Marilyn Restrepo cc020 - sophos | E46: 964348 | F46: 46059 | G46: Cancelado | H46: =IF(OR(G46="Sin pagar",G46="Pagar"),NETWORKDAYS($I$11,F46,'Festivos Colombia'!$A$3:$A$22),0) -> 0 | I46: =H46 -> 0
D47: Reembolso Cristiam Silva cc020 - sophos | E47: 408515 | F47: 46066 | G47: Cancelado | H47: =IF(OR(G47="Sin pagar",G47="Pagar"),NETWORKDAYS($I$11,F47,'Festivos Colombia'!$A$3:$A$22),0) -> 0 | I47: =H47 -> 0
D48: Reembolso Maria Claudia Bohorquez cc020 - sophos | E48: 45670 | F48: 46066 | G48: Cancelado | H48: =IF(OR(G48="Sin pagar",G48="Pagar"),NETWORKDAYS($I$11,F48,'Festivos Colombia'!$A$3:$A$22),0) -> 0 | I48: =H48 -> 0
D49: Reembolso Cristian Javier Gutierrez Torres-cc020 - Sophos | E49: 3377654.7 | F49: 46066 | G49: Cancelado | H49: =IF(OR(G49="Sin pagar",G49="Pagar"),NETWORKDAYS($I$11,F49,'Festivos Colombia'!$A$3:$A$22),0) -> 0 | I49: =H49 -> 0
D50: Reembolso Jorge Daniel Ramos DUran cc040 - Environmental Dynamics INTL | E50: 784847 | F50: 46066 | G50: Cancelado | H50: =IF(OR(G50="Sin pagar",G50="Pagar"),NETWORKDAYS($I$11,F50,'Festivos Colombia'!$A$3:$A$22),0) -> 0 | I50: =H50 -> 0
D51: Reembolso Edwin fernando alonso castelblanco cc020 - sophos | E51: 213686 | F51: 46066 | G51: Cancelado | H51: =IF(OR(G51="Sin pagar",G51="Pagar"),NETWORKDAYS($I$11,F51,'Festivos Colombia'!$A$3:$A$22),0) -> 0 | I51: =H51 -> 0
D52: Reembolso Fabian Augusto Porto Dulcey cc020 - Sophos | E52: 3416820 | F52: 46066 | G52: Cancelado | H52: =IF(OR(G52="Sin pagar",G52="Pagar"),NETWORKDAYS($I$11,F52,'Festivos Colombia'!$A$3:$A$22),0) -> 0 | I52: =H52 -> 0
D53: Reembolso Jorge Eduardo Crismatt Dungand cc060 - Best Formulation | E53: 59207.62 | F53: 46066 | G53: Cancelado | H53: =IF(OR(G53="Sin pagar",G53="Pagar"),NETWORKDAYS($I$11,F53,'Festivos Colombia'!$A$3:$A$22),0) -> 0 | I53: =H53 -> 0
... D91: Reembolso Manuel Francisco Torres Prieto CC057 - PROJECT MANAGEMENT INSTITUTE | E91: 934685.62 | F91: 46086 | G91: Cancelado | H91: =IF(OR(G91="Sin pagar",G91="Pagar"),NETWORKDAYS($I$11,F91,'Festivos Colombia'!$A$3:$A$22),0) -> 0 | I91: =H91 -> 0
D92: TIQUETES AÉREOS , HOTELES | E92: =SUBTOTAL(9,E93:E94) -> 3447106
D93: Tiquete Sandra Barba Bog - SFO - Bog | E93: =3285000*0 -> 0 | F93: 46057 | G93: Cancelado
D94: Tiquete Andy Muñoz Cartagena- Lima y VSA | E94: 3447106 | F94: 46070 | G94: Cancelado | H94: =IF(OR(G94="Sin pagar",G94="Pagar"),NETWORKDAYS($I$11,F94,'Festivos Colombia'!$A$3:$A$22),0) -> 0 | I94: =H94 -> 0
D95: ASESORÍAS | E95: =SUBTOTAL(9,E96:E99) -> 20139514
A96: =G96 -> Cancelado | B96: =IF(#REF!<=-1,1,IF(#REF!<=5,2,IF(#REF!<=15,3,IF(H96<=60,4)))) -> #REF! | C96: 6605 | D96: Global CS Colombia SAS -Solutions & payroll-Servicio Enero 2026 | E96: 19779520 | F96: 46064 | G96: Cancelado | H96: =IF(OR(G96="Sin pagar",G96="Pagar"),NETWORKDAYS($I$11,F96,'Festivos Colombia'!$A$3:$A$22),0) -> 0 | I96: =H96 -> 0
A97: =G97 -> Cancelado | B97: =IF(#REF!<=-1,1,IF(#REF!<=5,2,IF(#REF!<=15,3,IF(H97<=60,4)))) -> #REF! | C97: 5-163 | D97: Global CS Colombia SAS -Solutions & payroll- Reembolso Gastos Enero | E97: 359994 | F97: 46064 | G97: Cancelado | H97: =IF(OR(G97="Sin pagar",G97="Pagar"),NETWORKDAYS($I$11,F97,'Festivos Colombia'!$A$3:$A$22),0) -> 0 | I97: =H97 -> 0
A98: =G98 -> Sin Pagar | B98: =IF(#REF!<=-1,1,IF(#REF!<=5,2,IF(#REF!<=15,3,IF(H98<=60,4)))) -> #REF! | C98: 6696 | D98: Global CS Colombia SAS -Solutions & payroll-Servicio Febrero 2026 | E98: =18538188.72*0 -> 0 | F98: 46087 | G98: Sin Pagar | H98: =IF(OR(G98="Sin pagar",G98="Pagar"),NETWORKDAYS($I$11,F98,'Festivos Colombia'!$A$3:$A$22),0) -> 25 | I98: =H98 -> 25
A99: =G99 -> Sin Pagar | B99: =IF(#REF!<=-1,1,IF(#REF!<=5,2,IF(#REF!<=15,3,IF(H99<=60,4)))) -> #REF! | C99: 5-235 | D99: Global CS Colombia SAS -Solutions & payroll- Reembolso Gastos Febrero | E99: =383162*0 -> 0 | F99: 46087 | G99: Sin Pagar | H99: =IF(OR(G99="Sin pagar",G99="Pagar"),NETWORKDAYS($I$11,F99,'Festivos Colombia'!$A$3:$A$22),0) -> 25 | I99: =H99 -> 25
D100: COSTOS FINANCIEROS | E100: =SUBTOTAL(9,E101) -> 14020236
A101: =G101 -> Cancelado | B101: =IF(#REF!<=-1,1,IF(#REF!<=5,2,IF(#REF!<=15,3,IF(H101<=60,4)))) -> #REF! | D101: Costos financieros (Cuenta GLOBAL CS) | E101: =13927764.83+92470.928 -> 14020236 | F101: 46081 | G101: Cancelado | H101: =IF(OR(G101="Sin pagar",G101="Pagar"),NETWORKDAYS($I$11,F101,'Festivos Colombia'!$A$3:$A$22),0) -> 0 | I101: =H101 -> 0
D102: CREDITOS Y LIBRANZAS | E102: =SUBTOTAL(9,E103) -> 2209861
A103: =G103 -> Cancelado | B103: =IF(#REF!<=-1,1,IF(#REF!<=5,2,IF(#REF!<=15,3,IF(H103<=60,4)))) -> #REF! | D103: Libranza compensar | E103: 2209861 | F103: 46080 | G103: Cancelado | H103: =IF(OR(G103="Sin pagar",G103="Pagar"),NETWORKDAYS($I$11,F103,'Festivos Colombia'!$A$3:$A$22),0) -> 0 | I103: =H103 -> 0
D104: ESTUDIOS DE SEGURIDAD Y EXAMENES OCUPACIONALES-PÓLIZAS SALUD | E104: =SUBTOTAL(9,E105:E110) -> 748206
A105: =G105 -> Cancelado | B105: =IF(#REF!<=-1,1,IF(#REF!<=5,2,IF(#REF!<=15,3,IF(H105<=60,4)))) -> #REF! | C105: 6872 | D105: EMASOC | E105: =178500 -> 178500 | F105: 46073 | G105: Cancelado | H105: =IF(OR(G105="Sin pagar",G105="Pagar"),NETWORKDAYS($I$11,F105,'Festivos Colombia'!$A$3:$A$22),0) -> 0 | I105: =H105 -> 0
A106: =G106 -> Cancelado | B106: =IF(#REF!<=-1,1,IF(#REF!<=5,2,IF(#REF!<=15,3,IF(H106<=60,4)))) -> #REF! | C106: 16001350783712 | D106: Allianz Póliza No: 23730847- Jerson Porras | E106: =467206 -> 467206 | F106: 46078 | G106: Cancelado | H106: =IF(OR(G106="Sin pagar",G106="Pagar"),NETWORKDAYS($I$11,F106,'Festivos Colombia'!$A$3:$A$22),0) -> 0 | I106: =H106 -> 0
A107: =G107 -> Cancelado | B107: =IF(#REF!<=-1,1,IF(#REF!<=5,2,IF(#REF!<=15,3,IF(H107<=60,4)))) -> #REF! | C107: 6918 | D107: EMASOC | E107: =102500 -> 102500 | F107: 46073 | G107: Cancelado | H107: =IF(OR(G107="Sin pagar",G107="Pagar"),NETWORKDAYS($I$11,F107,'Festivos Colombia'!$A$3:$A$22),0) -> 0 | I107: =H107 -> 0
A108: =G108 -> Sin Pagar | B108: =IF(#REF!<=-1,1,IF(#REF!<=5,2,IF(#REF!<=15,3,IF(H108<=60,4)))) -> #REF! | C108: 6938 | D108: EMASOC | E108: =117000*0 -> 0 | F108: 46100 | G108: Sin Pagar | H108: =IF(OR(G108="Sin pagar",G108="Pagar"),NETWORKDAYS($I$11,F108,'Festivos Colombia'!$A$3:$A$22),0) -> 34 | I108: =H108 -> 34
A109: =G109 -> Sin Pagar | B109: =IF(#REF!<=-1,1,IF(#REF!<=5,2,IF(#REF!<=15,3,IF(H109<=60,4)))) -> #REF! | C109: 6941 | D109: EMASOC | E109: =117500*0 -> 0 | F109: 46105 | G109: Sin Pagar | H109: =IF(OR(G109="Sin pagar",G109="Pagar"),NETWORKDAYS($I$11,F109,'Festivos Colombia'!$A$3:$A$22),0) -> 36 | I109: =H109 -> 36
A110: =G110 -> Sin Pagar | B110: =IF(#REF!<=-1,1,IF(#REF!<=5,2,IF(#REF!<=15,3,IF(H110<=60,4)))) -> #REF! | C110: 6951 | D110: EMASOC | E110: =117500*0 -> 0 | F110: 46108 | G110: Sin Pagar | H110: =IF(OR(G110="Sin pagar",G110="Pagar"),NETWORKDAYS($I$11,F110,'Festivos Colombia'!$A$3:$A$22),0) -> 39 | I110: =H110 -> 39
D111: NÓMINAS Y ABONO A TARJETAS PEOPLE PASS | E111: =SUBTOTAL(9,E112:E116) -> 2043817442
A112: =G112 -> Cancelado | B112: =IF(#REF!<=-1,1,IF(#REF!<=5,2,IF(#REF!<=15,3,IF(H112<=60,4)))) -> #REF! | D112: Monetización Sena Enero | E112: =7879073*0 -> 0 | F112: 46054 | G112: Cancelado | H112: =IF(OR(G112="Sin pagar",G112="Pagar"),NETWORKDAYS($I$11,F112,'Festivos Colombia'!$A$3:$A$22),0) -> 0 | I112: =H112 -> 0
A113: =G113 -> Cancelado | B113: =IF(#REF!<=-1,1,IF(#REF!<=5,2,IF(#REF!<=15,3,IF(H113<=60,4)))) -> #REF! | D113: Cesantías | E113: 504461843 | F113: 46065 | G113: Cancelado | H113: =IF(OR(G113="Sin pagar",G113="Pagar"),NETWORKDAYS($I$11,F113,'Festivos Colombia'!$A$3:$A$22),0) -> 0 | I113: =H113 -> 0
A114: =G114 -> Cancelado | B114: =IF(#REF!<=-1,1,IF(#REF!<=5,2,IF(#REF!<=15,3,IF(H114<=60,4)))) -> #REF! | C114: 87 Registros | D114: Nomina OE | E114: 1536328015 | F114: 46079 | G114: Cancelado | H114: =IF(OR(G114="Sin pagar",G114="Pagar"),NETWORKDAYS($I$11,F114,'Festivos Colombia'!$A$3:$A$22),0) -> 0 | I114: =H114 -> 0
A115: =G115 -> Cancelado | B115: =IF(#REF!<=-1,1,IF(#REF!<=5,2,IF(#REF!<=15,3,IF(H115<=60,4)))) -> #REF! | C115: FP454293 | D115: People Pass-Market Enero | E115: 1630464 | F115: 46079 | G115: Cancelado | H115: =IF(OR(G115="Sin pagar",G115="Pagar"),NETWORKDAYS($I$11,F115,'Festivos Colombia'!$A$3:$A$22),0) -> 0 | I115: =H115 -> 0
A116: =G116 -> Cancelado | B116: =IF(#REF!<=-1,1,IF(#REF!<=5,2,IF(#REF!<=15,3,IF(H116<=60,4)))) -> #REF! | C116: S/N | D116: Reintregro Libranza marzo Juan Anaya | E116: 1397120 | F116: 46084 | G116: Cancelado | H116: =IF(OR(G116="Sin pagar",G116="Pagar"),NETWORKDAYS($I$11,F116,'Festivos Colombia'!$A$3:$A$22),0) -> 0 | I116: =H116 -> 0
A117: =G117 -> Cancelado | B117: =IF(#REF!<=-1,1,IF(#REF!<=5,2,IF(#REF!<=15,3,IF(H117<=60,4)))) -> #REF! | D117: Monetización Sena Febrero | E117: =7879073 -> 7879073 | F117: 46054 | G117: Cancelado | H117: =IF(OR(G117="Sin pagar",G117="Pagar"),NETWORKDAYS($I$11,F117,'Festivos Colombia'!$A$3:$A$22),0) -> 0 | I117: =H117 -> 0
D118: LIQUIDACIONES | E118: =SUBTOTAL(9,E119:E119) -> 13827883
A119: =G119 -> Cancelado | B119: =IF(#REF!<=-1,1,IF(#REF!<=5,2,IF(#REF!<=15,3,IF(H119<=60,4)))) -> #REF! | C119: 1 registro | D119: Liquidaciones Sebastian Terreros Perdomo | E119: 13827883 | F119: 46065 | G119: Cancelado | H119: =IF(OR(G119="Sin pagar",G119="Pagar"),NETWORKDAYS($I$11,F119,'Festivos Colombia'!$A$3:$A$22),0) -> 0 | I119: =H119 -> 0
D120: IMPREVISTO | E120: =SUBTOTAL(9,E121:E122) -> 35288787
A121: =G121 -> Cancelado | B121: =IF(#REF!<=-1,1,IF(#REF!<=5,2,IF(#REF!<=15,3,IF(H121<=60,4)))) -> #REF! | D121: Comisiones anticipadas María Paula Amaya Gómez-Grainger Services international INC | E121: 12364783 | F121: 46062 | G121: Cancelado | H121: =IF(OR(G121="Sin pagar",G121="Pagar"),NETWORKDAYS($I$11,F121,'Festivos Colombia'!$A$3:$A$22),0) -> 0 | I121: =H121 -> 0
A122: =G122 -> Cancelado | B122: =IF(#REF!<=-1,1,IF(#REF!<=5,2,IF(#REF!<=15,3,IF(H122<=60,4)))) -> #REF! | D122: Comisiones anticipadas Ana María Aguirre Alvarado-Grainger Services international INC | E122: 22924004 | F122: 46062 | G122: Cancelado | H122: =IF(OR(G122="Sin pagar",G122="Pagar"),NETWORKDAYS($I$11,F122,'Festivos Colombia'!$A$3:$A$22),0) -> 0 | I122: =H122 -> 0
D123: TOTAL EGRESOS | E123: =SUBTOTAL(9,E13:E122) -> 3.2141691e+09
D124: 4 x mil transacciones | E124: =(E123*4)/1000 -> 12856677
D125: TOTAL A PAGAR | E125: =E123+E124 -> 3.2270258e+09 | G125: Sin Pagar
D129: SALDO | E129: =E8-E123 -> 1.3036721e+09
D130: % | E130: =IF($E$8=0,0,E129/$E$8) -> 0.28856085
D133: Cristhian Guapacha-Root Capital -Tarjeta 1 | E133: Carestream
D137: 46054 | E137: 46061 | F137: =SUMIFS($E$12:$E$132,$F$12:$F$132,">="&D137,$F$12:$F$132,"<="&E137,$G$12:$G$132,$E$156) -> 0
D138: 46062 | E138: 46064 | F138: =SUMIFS($E$12:$E$132,$F$12:$F$132,">="&D138,$F$12:$F$132,"<="&E138,$G$12:$G$132,$E$156) -> 0 | G138: Pago suramericana
D139: 46065 | E139: 46065 | F139: =SUMIFS($E$12:$E$132,$F$12:$F$132,">="&D139,$F$12:$F$132,"<="&E139,$G$12:$G$132,$E$156) -> 0 | G139: Seguridad social, Rte fte
D140: 46066 | E140: 46066 | F140: =SUMIFS($E$12:$E$132,$F$12:$F$132,">="&D140,$F$12:$F$132,"<="&E140,$G$12:$G$132,$E$156) -> 0 | G140: Cesantías, nómina anticipadas reembolsos y tiquetes previstos
D141: 46067 | E141: 46068 | F141: =SUMIFS($E$12:$E$132,$F$12:$F$132,">="&D141,$F$12:$F$132,"<="&E141,$G$12:$G$132,$E$156) -> 0
D142: 46069 | E142: 46075 | F142: =SUMIFS($E$12:$E$132,$F$12:$F$132,">="&D142,$F$12:$F$132,"<="&E142,$G$12:$G$132,$E$156) -> 0 | G142: Reembolsos y tiquetes
D143: 46076 | E143: 46081 | F143: =SUMIFS($E$12:$E$132,$F$12:$F$132,">="&D143,$F$12:$F$132,"<="&E143,$G$12:$G$132,$E$156) -> 0 | G143: Nóminas , Reembolsos, libranzas, ICA anual
D144: 46082 | E144: 46089 | F144: =SUMIFS($E$12:$E$132,$F$12:$F$132,">="&D144,$F$12:$F$132,"<="&E144,$G$12:$G$132,$E$156) -> 0
D145: TOTAL EGRESOS | F145: =SUM(F137:F144) -> 0
D148: Gastos del 23 al 28 febrero | F148: =SUM(F137:F144) -> 0
D149: 4 x mil transacciones | F149: =(F148*4)/1000 -> 0
D150: Total | F150: =SUM(F148:F149) -> 0
D152: 46086 | F152: 1.3036721e+09
...

Sheet MARZO
E1: 42400
D4: BANCOS | E4: =SUBTOTAL(9,E5:E5) -> 1.3036721e+09
D5: Bancos | E5: =FEBRERO!E129 -> 1.3036721e+09
D6: FACTURACIÓN PENDIENTE POR MONETIZAR | E6: =SUBTOTAL(9,E7:E7) -> 2.8172875e+09
D7: Monetización - facturación y Offycycle Marzo | E7: =2672864.02+7831260.8+47157848.5+71157372.72+2651028558.59+5475747+56288376-24324546.76 -> 2.8172875e+09
E8: =SUBTOTAL(9,E4:E7) -> 4.1209596e+09
C11: CUENTAS X PAGAR MES | E11: MARZO | F11: Fecha de Elaboración: | I11: 46082
C12: Factura | D12: PROVEEDOR | E12: VALOR | F12: Fecha vencimiento | G12: Estado | I12: KPI | J12: Objeto
D13: PAGOS ANTICIPADOS | E13: =SUBTOTAL(9,E14) -> 29793135
A14: =G14 -> Cancelado | B14: =IF(#REF!<=-1,1,IF(#REF!<=5,2,IF(#REF!<=15,3,IF(H14<=60,4)))) -> #REF! | C14: 1 registro | D14: Nómina Sergio Jimenez Belimo | E14: 29793135 | F14: 46108 | G14: Cancelado | H14: =IF(OR(G14="Sin pagar",G14="Pagar"),NETWORKDAYS($I$11,F14,'Festivos Colombia'!$A$3:$A$22),0) -> 0 | I14: =H14 -> 0
D15: SEGURIDAD SOCIAL | E15: =SUBTOTAL(9,E16:E16) -> 623291500
A16: =G16 -> Cancelado | B16: =IF(#REF!<=-1,1,IF(#REF!<=5,2,IF(#REF!<=15,3,IF(H16<=60,4)))) -> #REF! | D16: Pago seguridad social Global | E16: 623291500 | F16: 46091 | G16: Cancelado | H16: =IF(OR(G16="Sin pagar",G16="Pagar"),NETWORKDAYS($I$11,F16,'Festivos Colombia'!$A$3:$A$22),0) -> 0 | I16: =H16 -> 0
D17: AFC´S | E17: =SUBTOTAL(9,E18:E19) -> 67234163
A18: =G18 -> Cancelado | B18: =IF(#REF!<=-1,1,IF(#REF!<=5,2,IF(#REF!<=15,3,IF(H18<=60,4)))) -> #REF! | C18: 1 | D18: AFC y aportes voluntarios - Cheque | E18: 21300000 | F18: 46108 | G18: Cancelado | H18: =IF(OR(G18="Sin pagar",G18="Pagar"),NETWORKDAYS($I$11,F18,'Festivos Colombia'!$A$3:$A$22),0) -> 0 | I18: =H18 -> 0
A19: =G19 -> Cancelado | B19: =IF(#REF!<=-1,1,IF(#REF!<=5,2,IF(#REF!<=15,3,IF(H19<=60,4)))) -> #REF! | C19: 1 | D19: AFC y aportes voluntarios -SOI y Aportes en Linea | E19: 45934163 | F19: 46111 | G19: Cancelado | H19: =IF(OR(G19="Sin pagar",G19="Pagar"),NETWORKDAYS($I$11,F19,'Festivos Colombia'!$A$3:$A$22),0) -> 0 | I19: =H19 -> 0
D20: IMPUESTOS | E20: =SUBTOTAL(9,E21:E22) -> 332839000 | H20: =IF(OR(G20="Sin pagar",G20="Pagar"),NETWORKDAYS($I$11,F20,'Festivos Colombia'!$A$3:$A$22),0) -> 0 | I20: =H20 -> 0
A21: =G21 -> Cancelado | B21: =IF(#REF!<=-1,1,IF(#REF!<=5,2,IF(#REF!<=15,3,IF(H21<=60,4)))) -> #REF! | D21: Retención en la fuente | E21: 332523000 | F21: 46093 | G21: Cancelado | H21: =IF(OR(G21="Sin pagar",G21="Pagar"),NETWORKDAYS($I$11,F21,'Festivos Colombia'!$A$3:$A$22),0) -> 0 | I21: =H21 -> 0
A22: =G22 -> Cancelado | B22: =IF(#REF!<=-1,1,IF(#REF!<=5,2,IF(#REF!<=15,3,IF(H22<=60,4)))) -> #REF! | D22: Reteica 1er bimestre 2026 | E22: 316000 | F22: 46100 | G22: Cancelado | H22: =IF(OR(G22="Sin pagar",G22="Pagar"),NETWORKDAYS($I$11,F22,'Festivos Colombia'!$A$3:$A$22),0) -> 0 | I22: =H22 -> 0
D23: PLANES COMPLEMENTARIOS Y PREPAGADAS | E23: =SUBTOTAL(9,E24:E29) -> 15400832 | H23: =IF(OR(G23="Sin pagar",G23="Pagar"),NETWORKDAYS($I$11,F23,'Festivos Colombia'!$A$3:$A$22),0) -> 0
A24: =G24 -> Cancelado | B24: =IF(#REF!<=-1,1,IF(#REF!<=5,2,IF(#REF!<=15,3,IF(H24<=60,4)))) -> #REF! | C24: 20911217888 | D24: Póliza suramericana # 091000808150 SALUD FAMILIAR | E24: 14963656 | F24: 46111 | G24: Cancelado | H24: =IF(OR(G24="Sin pagar",G24="Pagar"),NETWORKDAYS($I$11,F24,'Festivos Colombia'!$A$3:$A$22),0) -> 0 | I24: =H24 -> 0
A25: =G25 -> Cancelado | B25: =IF(#REF!<=-1,1,IF(#REF!<=5,2,IF(#REF!<=15,3,IF(H25<=60,4)))) -> #REF! | C25: 20833457861 | D25: Póliza suramericana # 0904418894 SALUD FAMILIAR | E25: 437176 | F25: 46111 | G25: Cancelado | H25: =IF(OR(G25="Sin pagar",G25="Pagar"),NETWORKDAYS($I$11,F25,'Festivos Colombia'!$A$3:$A$22),0) -> 0 | I25: =H25 -> 0
A26: =G26 -> Sin Pagar | B26: =IF(#REF!<=-1,1,IF(#REF!<=5,2,IF(#REF!<=15,3,IF(H26<=60,4)))) -> #REF! | C26: 20911209572 | D26: Póliza suramericana # 091000808150 SALUD FAMILIAR | E26: =576588*0 -> 0 | F26: 46122 | G26: Sin Pagar | H26: =IF(OR(G26="Sin pagar",G26="Pagar"),NETWORKDAYS($I$11,F26,'Festivos Colombia'!$A$3:$A$22),0) -> 27 | I26: =H26 -> 27 | J26: Sin radicar
A27: =G27 -> Sin Pagar | B27: =IF(#REF!<=-1,1,IF(#REF!<=5,2,IF(#REF!<=15,3,IF(H27<=60,4)))) -> #REF! | C27: 20911209573 | D27: Póliza suramericana # 091000808150 SALUD FAMILIAR | E27: =576588*0 -> 0 | F27: 46122 | G27: Sin Pagar | H27: =IF(OR(G27="Sin pagar",G27="Pagar"),NETWORKDAYS($I$11,F27,'Festivos Colombia'!$A$3:$A$22),0) -> 27 | I27: =H27 -> 27 | J27: Sin radicar
A28: =G28 -> Sin Pagar | B28: =IF(#REF!<=-1,1,IF(#REF!<=5,2,IF(#REF!<=15,3,IF(H28<=60,4)))) -> #REF! | C28: 20911214073 | D28: Póliza suramericana # 091000808150 SALUD FAMILIAR | E28: =576588*0 -> 0 | F28: 46122 | G28: Sin Pagar | H28: =IF(OR(G28="Sin pagar",G28="Pagar"),NETWORKDAYS($I$11,F28,'Festivos Colombia'!$A$3:$A$22),0) -> 27 | I28: =H28 -> 27 | J28: Sin radicar
A29: =G29 -> Sin Pagar | B29: =IF(#REF!<=-1,1,IF(#REF!<=5,2,IF(#REF!<=15,3,IF(H29<=60,4)))) -> #REF! | C29: 20911213105 | D29: Póliza suramericana # 091000808150 SALUD FAMILIAR | E29: =576588*0 -> 0 | F29: 46122 | G29: Sin Pagar | H29: =IF(OR(G29="Sin pagar",G29="Pagar"),NETWORKDAYS($I$11,F29,'Festivos Colombia'!$A$3:$A$22),0) -> 27 | I29: =H29 -> 27 | J29: Sin radicar
D30: PÓLIZAS Y SEGUROS | E30: =SUBTOTAL(9,E34:E36) -> 18535234 | H30: =IF(OR(G30="Sin pagar",G30="Pagar"),NETWORKDAYS($I$11,F30,'Festivos Colombia'!$A$3:$A$22),0) -> 0
A31: =G31 -> Cancelado | B31: =IF(#REF!<=-1,1,IF(#REF!<=5,2,IF(#REF!<=15,3,IF(H31<=60,4)))) -> #REF! | C31: 10304561 | D31: Plan grupo 10108170475 - Sandra Barba - ALLEGIS GROUP INC | E31: =1751400 -> 1751400 | F31: 46091 | G31: Cancelado | H31: =IF(OR(G31="Sin pagar",G31="Pagar"),NETWORKDAYS($I$11,F31,'Festivos Colombia'!$A$3:$A$22),0) -> 0 | I31: =H31 -> 0
A32: =G32 -> Cancelado | B32: =IF(#REF!<=-1,1,IF(#REF!<=5,2,IF(#REF!<=15,3,IF(H32<=60,4)))) -> #REF! | C32: 12310455687 | D32: Plan Dental 103232083 | E32: 1080034 | F32: 46097 | G32: Cancelado | H32: =IF(OR(G32="Sin pagar",G32="Pagar"),NETWORKDAYS($I$11,F32,'Festivos Colombia'!$A$3:$A$22),0) -> 0 | I32: =H32 -> 0
A33: =G33 -> Cancelado | B33: =IF(#REF!<=-1,1,IF(#REF!<=5,2,IF(#REF!<=15,3,IF(H33<=60,4)))) -> #REF! | C33: 12310455690 | D33: Plan salud 10108211747 | E33: 15703800 | F33: 46097 | G33: Cancelado | H33: =IF(OR(G33="Sin pagar",G33="Pagar"),NETWORKDAYS($I$11,F33,'Festivos Colombia'!$A$3:$A$22),0) -> 0 | I33: =H33 -> 0
A34: =G34 -> Cancelado | B34: =IF(#REF!<=-1,1,IF(#REF!<=5,2,IF(#REF!<=15,3,IF(H34<=60,4)))) -> #REF! | C34: 12310603651 | D34: Plan grupo 10108170475 - Sandra Barba - ALLEGIS GROUP INC | E34: =1751400 -> 1751400 | F34: 46119 | G34: Cancelado | H34: =IF(OR(G34="Sin pagar",G34="Pagar"),NETWORKDAYS($I$11,F34,'Festivos Colombia'!$A$3:$A$22),0) -> 0 | I34: =H34 -> 0
A35: =G35 -> Cancelado | B35: =IF(#REF!<=-1,1,IF(#REF!<=5,2,IF(#REF!<=15,3,IF(H35<=60,4)))) -> #REF! | C35: 12310458522 | D35: Plan Dental 103232083 | E35: 1080034 | F35: 46123 | G35: Cancelado | H35: =IF(OR(G35="Sin pagar",G35="Pagar"),NETWORKDAYS($I$11,F35,'Festivos Colombia'!$A$3:$A$22),0) -> 0 | I35: =H35 -> 0
A36: =G36 -> Cancelado | B36: =IF(#REF!<=-1,1,IF(#REF!<=5,2,IF(#REF!<=15,3,IF(H36<=60,4)))) -> #REF! | C36: 12310459539 | D36: Plan salud 10108211747 | E36: 15703800 | F36: 46123 | G36: Cancelado | H36: =IF(OR(G36="Sin pagar",G36="Pagar"),NETWORKDAYS($I$11,F36,'Festivos Colombia'!$A$3:$A$22),0) -> 0 | I36: =H36 -> 0
D37: REEMBOLSO GASTOS VIAJE | E37: =SUBTOTAL(9,E38:E84) -> 1.8858256e+08
D38: Reembolso Camila Marin Melo cc020 - sophos | E38: 197477 | F38: 46093 | G38: Cancelado | H38: =IF(OR(G38="Sin pagar",G38="Pagar"),NETWORKDAYS($I$11,F38,'Festivos Colombia'!$A$3:$A$22),0) -> 0 | I38: =H38 -> 0
D39: Reembolso Cristiam Silva cc020 - sophos | E39: 368769 | F39: 46093 | G39: Cancelado | H39: =IF(OR(G39="Sin pagar",G39="Pagar"),NETWORKDAYS($I$11,F39,'Festivos Colombia'!$A$3:$A$22),0) -> 0 | I39: =H39 -> 0
D40: Reembolso Cristian Javier Gutierrez Torres-cc020 - Sophos | E40: 2459151 | F40: 46093 | G40: Cancelado | H40: =IF(OR(G40="Sin pagar",G40="Pagar"),NETWORKDAYS($I$11,F40,'Festivos Colombia'!$A$3:$A$22),0) -> 0 | I40: =H40 -> 0
D41: Reembolso Daniel Alberto Ramos Duran cc040 - Environmental Dynamics INTL | E41: 575750 | F41: 46093 | G41: Cancelado | H41: =IF(OR(G41="Sin pagar",G41="Pagar"),NETWORKDAYS($I$11,F41,'Festivos Colombia'!$A$3:$A$22),0) -> 0 | I41: =H41 -> 0
D42: Reembolso Ivonne Torres-cc012 - lifenet health | E42: 7661306.2 | F42: 46093 | G42: Cancelado | H42: =IF(OR(G42="Sin pagar",G42="Pagar"),NETWORKDAYS($I$11,F42,'Festivos Colombia'!$A$3:$A$22),0) -> 0 | I42: =H42 -> 0
D43: Reembolso Jhon Jairo Garzon Beleño cc020 - Sophos | E43: 6469600 | F43: 46093 | G43: Cancelado | H43: =IF(OR(G43="Sin pagar",G43="Pagar"),NETWORKDAYS($I$11,F43,'Festivos Colombia'!$A$3:$A$22),0) -> 0 | I43: =H43 -> 0
D44: Reembolso Lina Marcela Gomez Nuñez cc083 - Acaps | E44: 54300 | F44: 46093 | G44: Cancelado | H44: =IF(OR(G44="Sin pagar",G44="Pagar"),NETWORKDAYS($I$11,F44,'Festivos Colombia'!$A$3:$A$22),0) -> 0 | I44: =H44 -> 0
D45: Reembolso Milagro del Vallle Sanchez cc020 - sophos | E45: 5093686 | F45: 46093 | G45: Cancelado | H45: =IF(OR(G45="Sin pagar",G45="Pagar"),NETWORKDAYS($I$11,F45,'Festivos Colombia'!$A$3:$A$22),0) -> 0 | I45: =H45 -> 0
D46: Reembolso Monica Martinez Martinez-cc012 - lifenet health | E46: 3766043.7 | F46: 46093 | G46: Cancelado | H46: =IF(OR(G46="Sin pagar",G46="Pagar"),NETWORKDAYS($I$11,F46,'Festivos Colombia'!$A$3:$A$22),0) -> 0 | I46: =H46 -> 0
D47: Reembolso Paula Andrea Alba Grajales CC077 - LANO SOFTWARE GMBH | E47: 657859 | F47: 46093 | G47: Cancelado | H47: =IF(OR(G47="Sin pagar",G47="Pagar"),NETWORKDAYS($I$11,F47,'Festivos Colombia'!$A$3:$A$22),0) -> 0 | I47: =H47 -> 0
D48: Reembolso Sandra Viviana Barba cc065 - Allegis Group Inc | E48: 9757903 | F48: 46093 | G48: Cancelado | H48: =IF(OR(G48="Sin pagar",G48="Pagar"),NETWORKDAYS($I$11,F48,'Festivos Colombia'!$A$3:$A$22),0) -> 0 | I48: =H48 -> 0
D49: Reembolso Andy Muñoz CC021 - HITACHI GLOBAL AIR POWER | E49: 5375008 | F49: 46093 | G49: Cancelado | H49: =IF(OR(G49="Sin pagar",G49="Pagar"),NETWORKDAYS($I$11,F49,'Festivos Colombia'!$A$3:$A$22),0) -> 0 | I49: =H49 -> 0
... D84: Reembolso Paula Andrea Alba Grajales CC077 - LANO SOFTWARE GMBH | E84: 4756267 | F84: 46113 | G84: Cancelado | H84: =IF(OR(G84="Sin pagar",G84="Pagar"),NETWORKDAYS($I$11,F84,'Festivos Colombia'!$A$3:$A$22),0) -> 0 | I84: =H84 -> 0
D85: TIQUETES AÉREOS , HOTELES | E85: =SUBTOTAL(9,E86:E90) -> 15249050
D86: Tiquete Catalina Duque Bog - Medellin y Bog - Barranquilla | E86: 1923690 | F86: 46090 | G86: Cancelado | H86: =IF(OR(G86="Sin pagar",G86="Pagar"),NETWORKDAYS($I$11,F86,'Festivos Colombia'!$A$3:$A$22),0) -> 0 | I86: =H86 -> 0
D87: Tiquete Sandra Barba Bog - Ctg y Bog - Smr | E87: 1552394 | F87: 46094 | G87: Cancelado | H87: =IF(OR(G87="Sin pagar",G87="Pagar"),NETWORKDAYS($I$11,F87,'Festivos Colombia'!$A$3:$A$22),0) -> 0 | I87: =H87 -> 0
D88: Tiquete Sandra Bogota -San francisco -Orlando- Bogota | E88: 5419440 | F88: 46098 | G88: Cancelado | H88: =IF(OR(G88="Sin pagar",G88="Pagar"),NETWORKDAYS($I$11,F88,'Festivos Colombia'!$A$3:$A$22),0) -> 0 | I88: =H88 -> 0
D89: Tiquete Andy Muñoz Cartagena-Medellin-Bogota y vsa | E89: 1396916 | F89: 46098 | G89: Cancelado | H89: =IF(OR(G89="Sin pagar",G89="Pagar"),NETWORKDAYS($I$11,F89,'Festivos Colombia'!$A$3:$A$22),0) -> 0 | I89: =H89 -> 0
D90: Tiquete Andy Muñoz Viaje a Chile | E90: 4956610 | F90: 46118 | G90: Cancelado | H90: =IF(OR(G90="Sin pagar",G90="Pagar"),NETWORKDAYS($I$11,F90,'Festivos Colombia'!$A$3:$A$22),0) -> 0 | I90: =H90 -> 0
D91: ASESORÍAS | E91: =SUBTOTAL(9,E92:E93) -> 18921351
A92: =G92 -> Cancelado | B92: =IF(#REF!<=-1,1,IF(#REF!<=5,2,IF(#REF!<=15,3,IF(H92<=60,4)))) -> #REF! | C92: 6696 | D92: Global CS Colombia SAS -Solutions & payroll-Servicio Febrero 2026 | E92: =18538188.72 -> 18538189 | F92: 46091 | G92: Cancelado | H92: =IF(OR(G92="Sin pagar",G92="Pagar"),NETWORKDAYS($I$11,F92,'Festivos Colombia'!$A$3:$A$22),0) -> 0 | I92: =H92 -> 0
A93: =G93 -> Cancelado | B93: =IF(#REF!<=-1,1,IF(#REF!<=5,2,IF(#REF!<=15,3,IF(H93<=60,4)))) -> #REF! | C93: 5-235 | D93: Global CS Colombia SAS -Solutions & payroll- Reembolso Gastos Febrero | E93: =383162 -> 383162 | F93: 46087 | G93: Cancelado | H93: =IF(OR(G93="Sin pagar",G93="Pagar"),NETWORKDAYS($I$11,F93,'Festivos Colombia'!$A$3:$A$22),0) -> 0 | I93: =H93 -> 0
D94: COSTOS FINANCIEROS | E94: =SUBTOTAL(9,E95) -> 12804844
A95: =G95 -> Cancelado | B95: =IF(#REF!<=-1,1,IF(#REF!<=5,2,IF(#REF!<=15,3,IF(H95<=60,4)))) -> #REF! | D95: Costos financieros (Cuenta GLOBAL CS) | E95: 12804844 | F95: 46112 | G95: Cancelado | H95: =IF(OR(G95="Sin pagar",G95="Pagar"),NETWORKDAYS($I$11,F95,'Festivos Colombia'!$A$3:$A$22),0) -> 0 | I95: =H95 -> 0
D96: CREDITOS Y LIBRANZAS | E96: =SUBTOTAL(9,E97) -> 2209861
A97: =G97 -> Cancelado | B97: =IF(#REF!<=-1,1,IF(#REF!<=5,2,IF(#REF!<=15,3,IF(H97<=60,4)))) -> #REF! | D97: Libranza compensar | E97: 2209861 | F97: 46111 | G97: Cancelado | H97: =IF(OR(G97="Sin pagar",G97="Pagar"),NETWORKDAYS($I$11,F97,'Festivos Colombia'!$A$3:$A$22),0) -> 0 | I97: =H97 -> 0
D98: ESTUDIOS DE SEGURIDAD Y EXAMENES OCUPACIONALES-PÓLIZAS SALUD | E98: =SUBTOTAL(9,E99:E104) -> 819206
A99: =G99 -> Cancelado | B99: =IF(#REF!<=-1,1,IF(#REF!<=5,2,IF(#REF!<=15,3,IF(H99<=60,4)))) -> #REF! | C99: 6938 | D99: EMASOC | E99: =117000 -> 117000 | F99: 46101 | G99: Cancelado | H99: =IF(OR(G99="Sin pagar",G99="Pagar"),NETWORKDAYS($I$11,F99,'Festivos Colombia'!$A$3:$A$22),0) -> 0 | I99: =H99 -> 0
A100: =G100 -> Cancelado | B100: =IF(#REF!<=-1,1,IF(#REF!<=5,2,IF(#REF!<=15,3,IF(H100<=60,4)))) -> #REF! | C100: 6941 | D100: EMASOC | E100: =117500 -> 117500 | F100: 46111 | G100: Cancelado | H100: =IF(OR(G100="Sin pagar",G100="Pagar"),NETWORKDAYS($I$11,F100,'Festivos Colombia'!$A$3:$A$22),0) -> 0 | I100: =H100 -> 0
A101: =G101 -> Cancelado | B101: =IF(#REF!<=-1,1,IF(#REF!<=5,2,IF(#REF!<=15,3,IF(H101<=60,4)))) -> #REF! | C101: 6951 | D101: EMASOC | E101: =117500 -> 117500 | F101: 46111 | G101: Cancelado | H101: =IF(OR(G101="Sin pagar",G101="Pagar"),NETWORKDAYS($I$11,F101,'Festivos Colombia'!$A$3:$A$22),0) -> 0 | I101: =H101 -> 0
A102: =G102 -> Sin Pagar | B102: =IF(#REF!<=-1,1,IF(#REF!<=5,2,IF(#REF!<=15,3,IF(H102<=60,4)))) -> #REF! | C102: 6993 | D102: EMASOC | E102: =235000*0 -> 0 | F102: 46136 | G102: Sin Pagar | H102: =IF(OR(G102="Sin pagar",G102="Pagar"),NETWORKDAYS($I$11,F102,'Festivos Colombia'!$A$3:$A$22),0) -> 37 | I102: =H102 -> 37
A103: =G103 -> Sin Pagar | B103: =IF(#REF!<=-1,1,IF(#REF!<=5,2,IF(#REF!<=15,3,IF(H103<=60,4)))) -> #REF! | C103: 7003 | D103: EMASOC | E103: =547500*0 -> 0 | F103: 46139 | G103: Sin Pagar | H103: =IF(OR(G103="Sin pagar",G103="Pagar"),NETWORKDAYS($I$11,F103,'Festivos Colombia'!$A$3:$A$22),0) -> 38 | I103: =H103 -> 38
A104: =G104 -> Cancelado | B104: =IF(#REF!<=-1,1,IF(#REF!<=5,2,IF(#REF!<=15,3,IF(H104<=60,4)))) -> #REF! | C104: 354315586 | D104: Allianz Póliza No: 23730847- Jerson Porras | E104: =467206 -> 467206 | F104: 46111 | G104: Cancelado | H104: =IF(OR(G104="Sin pagar",G104="Pagar"),NETWORKDAYS($I$11,F104,'Festivos Colombia'!$A$3:$A$22),0) -> 0 | I104: =H104 -> 0 | J104: Sin radicar
D105: NÓMINAS Y ABONO A TARJETAS PEOPLE PASS | E105: =SUBTOTAL(9,E106:E109) -> 1565377850
A106: =G106 -> Cancelado | B106: =IF(#REF!<=-1,1,IF(#REF!<=5,2,IF(#REF!<=15,3,IF(H106<=60,4)))) -> #REF! | D106: Monetización Sena Febrero | E106: =7879073 -> 7879073 | F106: 46087 | G106: Cancelado | H106: =IF(OR(G106="Sin pagar",G106="Pagar"),NETWORKDAYS($I$11,F106,'Festivos Colombia'!$A$3:$A$22),0) -> 0 | I106: =H106 -> 0
A107: =G107 -> Cancelado | B107: =IF(#REF!<=-1,1,IF(#REF!<=5,2,IF(#REF!<=15,3,IF(H107<=60,4)))) -> #REF! | C107: 87 Registros | D107: Nomina OE | E107: 1547989240 | F107: 46108 | G107: Cancelado | H107: =IF(OR(G107="Sin pagar",G107="Pagar"),NETWORKDAYS($I$11,F107,'Festivos Colombia'!$A$3:$A$22),0) -> 0 | I107: =H107 -> 0
A108: =G108 -> Cancelado | B108: =IF(#REF!<=-1,1,IF(#REF!<=5,2,IF(#REF!<=15,3,IF(H108<=60,4)))) -> #REF! | C108: FPP464570 | D108: People Pass-Market | E108: 1630464 | F108: 46108 | G108: Cancelado | H108: =IF(OR(G108="Sin pagar",G108="Pagar"),NETWORKDAYS($I$11,F108,'Festivos Colombia'!$A$3:$A$22),0) -> 0 | I108: =H108 -> 0
A109: =G109 -> Cancelado | B109: =IF(#REF!<=-1,1,IF(#REF!<=5,2,IF(#REF!<=15,3,IF(H109<=60,4)))) -> #REF! | D109: Monetización Sena Marzo | E109: =7879073 -> 7879073 | F109: 46113 | G109: Cancelado | H109: =IF(OR(G109="Sin pagar",G109="Pagar"),NETWORKDAYS($I$11,F109,'Festivos Colombia'!$A$3:$A$22),0) -> 0 | I109: =H109 -> 0
D110: LIQUIDACIONES | E110: =SUBTOTAL(9,E111:E111) -> 0
A111: =G111 -> Cancelado | B111: =IF(#REF!<=-1,1,IF(#REF!<=5,2,IF(#REF!<=15,3,IF(H111<=60,4)))) -> #REF! | C111: 1 registro | D111: Liquidaciones previstas | E111: 0 | F111: 46111 | G111: Cancelado | H111: =IF(OR(G111="Sin pagar",G111="Pagar"),NETWORKDAYS($I$11,F111,'Festivos Colombia'!$A$3:$A$22),0) -> 0 | I111: =H111 -> 0
D112: IMPREVISTO | E112: =SUBTOTAL(9,E113:E114) -> 4505836
A113: =G113 -> Cancelado | B113: =IF(#REF!<=-1,1,IF(#REF!<=5,2,IF(#REF!<=15,3,IF(H113<=60,4)))) -> #REF! | C113: 5070 | D113: El laboratorio de café - Andy Muñoz | E113: 1876336 | F113: 46094 | G113: Cancelado | H113: =IF(OR(G113="Sin pagar",G113="Pagar"),NETWORKDAYS($I$11,F113,'Festivos Colombia'!$A$3:$A$22),0) -> 0 | I113: =H113 -> 0
A114: =G114 -> Cancelado | B114: =IF(#REF!<=-1,1,IF(#REF!<=5,2,IF(#REF!<=15,3,IF(H114<=60,4)))) -> #REF! | D114: Renovación registro mercantil - Global | E114: 2629500 | F114: 46111 | G114: Cancelado | H114: =IF(OR(G114="Sin pagar",G114="Pagar"),NETWORKDAYS($I$11,F114,'Festivos Colombia'!$A$3:$A$22),0) -> 0 | I114: =H114 -> 0
D115: TOTAL EGRESOS | E115: =SUBTOTAL(9,E13:E114) -> 2.9140997e+09
D116: 4 x mil transacciones | E116: =(E115*4)/1000 -> 11656399
D117: TOTAL A PAGAR | E117: =E115+E116 -> 2.9257561e+09 | G117: Sin Pagar
D121: SALDO | E121: =E8-E115 -> 1.2068599e+09
D122: % | E122: =IF($E$8=0,0,E121/$E$8) -> 0.29285896
D125: Cristhian Guapacha-Root Capital -Tarjeta 1 | E125: Carestream
D128: 46082 | E128: 46089 | F128: =SUMIFS($E$12:$E$124,$F$12:$F$124,">="&D128,$F$12:$F$124,"<="&E128,$G$12:$G$124,$E$147) -> 0 | G128: Sanitas y reembolsos
D129: 46090 | E129: 46092 | F129: =SUMIFS($E$12:$E$124,$F$12:$F$124,">="&D129,$F$12:$F$124,"<="&E129,$G$12:$G$124,$E$147) -> 0
D130: 46093 | E130: 46093 | F130: =SUMIFS($E$12:$E$124,$F$12:$F$124,">="&D130,$F$12:$F$124,"<="&E130,$G$12:$G$124,$E$147) -> 0
D131: 46094 | E131: 46096 | F131: =SUMIFS($E$12:$E$124,$F$12:$F$124,">="&D131,$F$12:$F$124,"<="&E131,$G$12:$G$124,$E$147) -> 0
D132: 46097 | E132: 46104 | F132: =SUMIFS($E$12:$E$124,$F$12:$F$124,">="&D132,$F$12:$F$124,"<="&E132,$G$12:$G$124,$E$147) -> 0 | G132: Reembolsos y tiquetes
D133: 46105 | E133: 46110 | F133: =SUMIFS($E$12:$E$124,$F$12:$F$124,">="&D133,$F$12:$F$124,"<="&E133,$G$12:$G$124,$E$147) -> 0 | G133: Nóminas , Reembolsos, libranzas, ICA anual
D134: 46111 | E134: 46112 | F134: =SUMIFS($E$12:$E$124,$F$12:$F$124,">="&D134,$F$12:$F$124,"<="&E134,$G$12:$G$124,$E$147) -> 0 | G134: Nóminas , Reembolsos, libranzas, ICA anual
D135: 46113 | E135: 46124 | F135: =SUMIFS($E$12:$E$124,$F$12:$F$124,">="&D135,$F$12:$F$124,"<="&E135,$G$12:$G$124,$E$147) -> 0
D136: TOTAL EGRESOS | F136: =SUM(F128:F135) -> 0
D139: Gastos del 24 al 31 Marzo | F139: =SUM(F128:F135) -> 0
D140: 4 x mil | F140: =(F139*4)/1000 -> 0
D141: Total | F141: =SUM(F139:F140) -> 0
D143: 46119 | F143: 1.2068599e+09
E144: Superavit o Deficit | F144: =F143-F141 -> 1.2068599e+09
E147: Sin Pagar | F147: =SUMIFS($E$12:$E$115,$F$12:$F$115,">="&D128,$F$12:$F$115,"<="&E135,$G$12:$G$115,$E$147) -> 0
E148: Cancelado | F148: =SUMIFS($E$12:$E$115,$F$12:$F$115,">="&D128,$F$12:$F$115,"<="&E135,$G$12:$G$115,$E$148) -> 2.9140997e+09
E149: Total | F149: =SUM(F147:F148) -> 2.9140997e+09
E150: Comprobación | F150: =E115-F149 -> 0

Sheet ABRIL
E1: 42400
D4: BANCOS | E4: =SUBTOTAL(9,E5:E5) -> 1.2068599e+09
D5: Bancos | E5: =MARZO!$E$121 -> 1.2068599e+09
D6: FACTURACIÓN PENDIENTE POR MONETIZAR | E6: =SUBTOTAL(9,E7:E7) -> 3.1908855e+09
D7: Monetización - facturación y Offycycle Abril | E7: =5553553.2+8903168.4+54058.69+279638141.4+2657714938.49+106046819.2+33451228+30169695.15+69353897 -> 3.1908855e+09
E8: =SUBTOTAL(9,E4:E7) -> 4.3977454e+09
C11: CUENTAS X PAGAR MES | E11: ABRIL | F11: Fecha de Elaboración: | I11: 46113
C12: Factura | D12: PROVEEDOR | E12: VALOR | F12: Fecha vencimiento | G12: Estado | I12: KPI | J12: Objeto
D13: PAGOS ANTICIPADOS | E13: =SUBTOTAL(9,E14) -> 25815079
A14: =G14 -> Cancelado | B14: =IF(#REF!<=-1,1,IF(#REF!<=5,2,IF(#REF!<=15,3,IF(H14<=60,4)))) -> #REF! | C14: 1 registro | D14: Nómina Sergio Jimenez Belimo | E14: 25815079 | F14: 46140 | G14: Cancelado | H14: =IF(OR(G14="Sin pagar",G14="Pagar"),NETWORKDAYS($I$11,F14,'Festivos Colombia'!$A$3:$A$22),0) -> 0 | I14: =H14 -> 0
D15: SEGURIDAD SOCIAL | E15: =SUBTOTAL(9,E16:E16) -> 648657500
A16: =G16 -> Cancelado | B16: =IF(#REF!<=-1,1,IF(#REF!<=5,2,IF(#REF!<=15,3,IF(H16<=60,4)))) -> #REF! | D16: Pago seguridad social Global | E16: 648657500 | F16: 46128 | G16: Cancelado | H16: =IF(OR(G16="Sin pagar",G16="Pagar"),NETWORKDAYS($I$11,F16,'Festivos Colombia'!$A$3:$A$22),0) -> 0 | I16: =H16 -> 0 | J16: 648217000 | K16: =+J16-E16 -> -440500
D17: AFC´S | E17: =SUBTOTAL(9,E18:E19) -> 77581011
A18: =G18 -> Cancelado | B18: =IF(#REF!<=-1,1,IF(#REF!<=5,2,IF(#REF!<=15,3,IF(H18<=60,4)))) -> #REF! | C18: 1 | D18: AFC y aportes voluntarios - Cheque | E18: 18566667 | F18: 46139 | G18: Cancelado | H18: =IF(OR(G18="Sin pagar",G18="Pagar"),NETWORKDAYS($I$11,F18,'Festivos Colombia'!$A$3:$A$22),0) -> 0 | I18: =H18 -> 0
A19: =G19 -> Cancelado | B19: =IF(#REF!<=-1,1,IF(#REF!<=5,2,IF(#REF!<=15,3,IF(H19<=60,4)))) -> #REF! | C19: 1 | D19: AFC y aportes voluntarios -SOI y Aportes en Linea | E19: 59014344 | F19: 46140 | G19: Cancelado | H19: =IF(OR(G19="Sin pagar",G19="Pagar"),NETWORKDAYS($I$11,F19,'Festivos Colombia'!$A$3:$A$22),0) -> 0 | I19: =H19 -> 0
D20: IMPUESTOS | E20: =SUBTOTAL(9,E21:E21) -> 340661000 | H20: =IF(OR(G20="Sin pagar",G20="Pagar"),NETWORKDAYS($I$11,F20,'Festivos Colombia'!$A$3:$A$22),0) -> 0 | I20: =H20 -> 0
A21: =G21 -> Cancelado | B21: =IF(#REF!<=-1,1,IF(#REF!<=5,2,IF(#REF!<=15,3,IF(H21<=60,4)))) -> #REF! | D21: Retención en la fuente | E21: 340661000 | F21: 46126 | G21: Cancelado | H21: =IF(OR(G21="Sin pagar",G21="Pagar"),NETWORKDAYS($I$11,F21,'Festivos Colombia'!$A$3:$A$22),0) -> 0 | I21: =H21 -> 0
D22: PLANES COMPLEMENTARIOS Y PREPAGADAS | E22: =SUBTOTAL(9,E23:E26) -> 17294698 | H22: =IF(OR(G22="Sin pagar",G22="Pagar"),NETWORKDAYS($I$11,F22,'Festivos Colombia'!$A$3:$A$22),0) -> 0
A23: =G23 -> Cancelado | B23: =IF(#REF!<=-1,1,IF(#REF!<=5,2,IF(#REF!<=15,3,IF(H23<=60,4)))) -> #REF! | C23: 20833471824 | D23: Póliza suramericana # 0904418894 SALUD FAMILIAR | E23: 15052 | F23: 46135 | G23: Cancelado | H23: =IF(OR(G23="Sin pagar",G23="Pagar"),NETWORKDAYS($I$11,F23,'Festivos Colombia'!$A$3:$A$22),0) -> 0 | I23: =H23 -> 0
A24: =G24 -> Cancelado | B24: =IF(#REF!<=-1,1,IF(#REF!<=5,2,IF(#REF!<=15,3,IF(H24<=60,4)))) -> #REF! | C24: 12310363886 | D24: Póliza suramericana # 091000808150 SALUD FAMILIAR | E24: 1864800 | F24: 46139 | G24: Cancelado | H24: =IF(OR(G24="Sin pagar",G24="Pagar"),NETWORKDAYS($I$11,F24,'Festivos Colombia'!$A$3:$A$22),0) -> 0 | I24: =H24 -> 0
A25: =G25 -> Cancelado | B25: =IF(#REF!<=-1,1,IF(#REF!<=5,2,IF(#REF!<=15,3,IF(H25<=60,4)))) -> #REF! | C25: 20911224616 | D25: Póliza suramericana # 091000808150 SALUD FAMILIAR | E25: 14963656 | F25: 46141 | G25: Cancelado | H25: =IF(OR(G25="Sin pagar",G25="Pagar"),NETWORKDAYS($I$11,F25,'Festivos Colombia'!$A$3:$A$22),0) -> 0 | I25: =H25 -> 0
A26: =G26 -> Cancelado | B26: =IF(#REF!<=-1,1,IF(#REF!<=5,2,IF(#REF!<=15,3,IF(H26<=60,4)))) -> #REF! | C26: 20833497839 | D26: Póliza suramericana # 0904418894 SALUD FAMILIAR | E26: 451190 | F26: 46141 | G26: Cancelado | H26: =IF(OR(G26="Sin pagar",G26="Pagar"),NETWORKDAYS($I$11,F26,'Festivos Colombia'!$A$3:$A$22),0) -> 0 | I26: =H26 -> 0
D27: PÓLIZAS Y SEGUROS | E27: =SUBTOTAL(9,E28:E30) -> 0 | H27: =IF(OR(G27="Sin pagar",G27="Pagar"),NETWORKDAYS($I$11,F27,'Festivos Colombia'!$A$3:$A$22),0) -> 0
A28: =G28 -> Cancelado | B28: =IF(#REF!<=-1,1,IF(#REF!<=5,2,IF(#REF!<=15,3,IF(H28<=60,4)))) -> #REF! | C28: 12310603651 | D28: Plan grupo 10108170475 - Sandra Barba - ALLEGIS GROUP INC | E28: =1751400*0 -> 0 | F28: 46119 | G28: Cancelado | H28: =IF(OR(G28="Sin pagar",G28="Pagar"),NETWORKDAYS($I$11,F28,'Festivos Colombia'!$A$3:$A$22),0) -> 0 | I28: =H28 -> 0
A29: =G29 -> Cancelado | B29: =IF(#REF!<=-1,1,IF(#REF!<=5,2,IF(#REF!<=15,3,IF(H29<=60,4)))) -> #REF! | C29: 12310458522 | D29: Plan Dental 103232083 | E29: =1080034*0 -> 0 | F29: 46119 | G29: Cancelado | H29: =IF(OR(G29="Sin pagar",G29="Pagar"),NETWORKDAYS($I$11,F29,'Festivos Colombia'!$A$3:$A$22),0) -> 0 | I29: =H29 -> 0
A30: =G30 -> Cancelado | B30: =IF(#REF!<=-1,1,IF(#REF!<=5,2,IF(#REF!<=15,3,IF(H30<=60,4)))) -> #REF! | C30: 12310459539 | D30: Plan salud 10108211747 | E30: =15703800*0 -> 0 | F30: 46119 | G30: Cancelado | H30: =IF(OR(G30="Sin pagar",G30="Pagar"),NETWORKDAYS($I$11,F30,'Festivos Colombia'!$A$3:$A$22),0) -> 0 | I30: =H30 -> 0
D31: REEMBOLSO GASTOS VIAJE | E31: =SUBTOTAL(9,E32:E83) -> 1.0005003e+08
D32: Reembolso Cristiam Silva cc020 - sophos | E32: =3861857*0 -> 0 | F32: 46113 | G32: Cancelado | H32: =IF(OR(G32="Sin pagar",G32="Pagar"),NETWORKDAYS($I$11,F32,'Festivos Colombia'!$A$3:$A$22),0) -> 0 | I32: =H32 -> 0
D33: Reembolso Carla Georgina Arcia - CC083 - ACAPS | E33: =531900*0 -> 0 | F33: 46113 | G33: Cancelado | H33: =IF(OR(G33="Sin pagar",G33="Pagar"),NETWORKDAYS($I$11,F33,'Festivos Colombia'!$A$3:$A$22),0) -> 0 | I33: =H33 -> 0
D34: Reembolso Maria Claudia Bohorquez cc020 - sophos | E34: =51272*0 -> 0 | F34: 46113 | G34: Cancelado | H34: =IF(OR(G34="Sin pagar",G34="Pagar"),NETWORKDAYS($I$11,F34,'Festivos Colombia'!$A$3:$A$22),0) -> 0 | I34: =H34 -> 0
D35: Reembolso Cristian Javier Gutierrez Torres-cc020 - Sophos | E35: =433968*0 -> 0 | F35: 46113 | G35: Cancelado | H35: =IF(OR(G35="Sin pagar",G35="Pagar"),NETWORKDAYS($I$11,F35,'Festivos Colombia'!$A$3:$A$22),0) -> 0 | I35: =H35 -> 0
D36: Reembolso Daniel Alberto Ramos Duran cc040 - Environmental Dynamics INTL | E36: =4848643*0 -> 0 | F36: 46113 | G36: Cancelado | H36: =IF(OR(G36="Sin pagar",G36="Pagar"),NETWORKDAYS($I$11,F36,'Festivos Colombia'!$A$3:$A$22),0) -> 0 | I36: =H36 -> 0
D37: Reembolso Ivonne Torres-cc012 - lifenet health | E37: =104600*0 -> 0 | F37: 46113 | G37: Cancelado | H37: =IF(OR(G37="Sin pagar",G37="Pagar"),NETWORKDAYS($I$11,F37,'Festivos Colombia'!$A$3:$A$22),0) -> 0 | I37: =H37 -> 0
D38: Reembolso Jhon Jairo Garzon Beleño cc020 - Sophos | E38: =4669650*0 -> 0 | F38: 46113 | G38: Cancelado | H38: =IF(OR(G38="Sin pagar",G38="Pagar"),NETWORKDAYS($I$11,F38,'Festivos Colombia'!$A$3:$A$22),0) -> 0 | I38: =H38 -> 0
D39: Reembolso Lina Marcela Gomez Nuñez cc083 - Acaps | E39: =906118*0 -> 0 | F39: 46113 | G39: Cancelado | H39: =IF(OR(G39="Sin pagar",G39="Pagar"),NETWORKDAYS($I$11,F39,'Festivos Colombia'!$A$3:$A$22),0) -> 0 | I39: =H39 -> 0
D40: Reembolso Milagro del Vallle Sanchez cc020 - sophos | E40: =4672644*0 -> 0 | F40: 46113 | G40: Cancelado | H40: =IF(OR(G40="Sin pagar",G40="Pagar"),NETWORKDAYS($I$11,F40,'Festivos Colombia'!$A$3:$A$22),0) -> 0 | I40: =H40 -> 0
D41: Reembolso Monica Martinez CC082 - CHRISTEL HOUSE INTERNATIONAL | E41: =5157482*0 -> 0 | F41: 46113 | G41: Cancelado | H41: =IF(OR(G41="Sin pagar",G41="Pagar"),NETWORKDAYS($I$11,F41,'Festivos Colombia'!$A$3:$A$22),0) -> 0 | I41: =H41 -> 0
D42: Reembolso Paula Andrea Alba Grajales CC077 - LANO SOFTWARE GMBH | E42: =4756267*0 -> 0 | F42: 46113 | G42: Cancelado | H42: =IF(OR(G42="Sin pagar",G42="Pagar"),NETWORKDAYS($I$11,F42,'Festivos Colombia'!$A$3:$A$22),0) -> 0 | I42: =H42 -> 0
D43: Reembolso Cristiam Silva cc020 - sophos | E43: 278017 | F43: 46122 | G43: Cancelado | H43: =IF(OR(G43="Sin pagar",G43="Pagar"),NETWORKDAYS($I$11,F43,'Festivos Colombia'!$A$3:$A$22),0) -> 0 | I43: =H43 -> 0
D44: Reembolso Daniel Alberto Ramos Duran cc040 - Environmental Dynamics INTL | E44: 8438461 | F44: 46122 | G44: Cancelado | H44: =IF(OR(G44="Sin pagar",G44="Pagar"),NETWORKDAYS($I$11,F44,'Festivos Colombia'!$A$3:$A$22),0) -> 0 | I44: =H44 -> 0
D45: Reembolso Genesis Coromoto Marchena Gómez - cc081 - go - global outsourcing inc | E45: 3448505 | F45: 46122 | G45: Cancelado | H45: =IF(OR(G45="Sin pagar",G45="Pagar"),NETWORKDAYS($I$11,F45,'Festivos Colombia'!$A$3:$A$22),0) -> 0 | I45: =H45 -> 0
D46: Reembolso Edith johana pineda zapata cc020 - sophos | E46: 11353280 | F46: 46122 | G46: Cancelado | H46: =IF(OR(G46="Sin pagar",G46="Pagar"),NETWORKDAYS($I$11,F46,'Festivos Colombia'!$A$3:$A$22),0) -> 0 | I46: =H46 -> 0
D47: Reembolso Mario Fernando Benitez Zabala cc020 - sophos | E47: 112480 | F47: 46122 | G47: Cancelado | H47: =IF(OR(G47="Sin pagar",G47="Pagar"),NETWORKDAYS($I$11,F47,'Festivos Colombia'!$A$3:$A$22),0) -> 0 | I47: =H47 -> 0
D48: Reembolso Paula Andrea Alba Grajales CC077 - LANO SOFTWARE GMBH | E48: 443901 | F48: 46122 | G48: Cancelado | H48: =IF(OR(G48="Sin pagar",G48="Pagar"),NETWORKDAYS($I$11,F48,'Festivos Colombia'!$A$3:$A$22),0) -> 0 | I48: =H48 -> 0
D49: Reembolso Sandra Viviana Barba cc065 - Allegis Group Inc | E49: 1061505 | F49: 46122 | G49: Cancelado | H49: =IF(OR(G49="Sin pagar",G49="Pagar"),NETWORKDAYS($I$11,F49,'Festivos Colombia'!$A$3:$A$22),0) -> 0 | I49: =H49 -> 0
D50: Reembolso Catalina Duque CC021 - HITACHI GLOBAL AIR POWER | E50: 9860073 | F50: 46122 | G50: Cancelado | H50: =IF(OR(G50="Sin pagar",G50="Pagar"),NETWORKDAYS($I$11,F50,'Festivos Colombia'!$A$3:$A$22),0) -> 0 | I50: =H50 -> 0
D51: Reembolso Manuel Francisco Torres Prieto CC057 - PROJECT MANAGEMENT INSTITUTE | E51: 1213734.8 | F51: 46122 | G51: Cancelado | H51: =IF(OR(G51="Sin pagar",G51="Pagar"),NETWORKDAYS($I$11,F51,'Festivos Colombia'!$A$3:$A$22),0) -> 0 | I51: =H51 -> 0
D52: Reembolso Andres Arbelaez CC037 - EDRINGTON AMERICAS | E52: 1934628 | F52: 46122 | G52: Cancelado | H52: =IF(OR(G52="Sin pagar",G52="Pagar"),NETWORKDAYS($I$11,F52,'Festivos Colombia'!$A$3:$A$22),0) -> 0 | I52: =H52 -> 0
D53: Reembolso Juan Giraldo Rios CC037 - EDRINGTON AMERICAS | E53: 1934628 | F53: 46122 | G53: Cancelado | H53: =IF(OR(G53="Sin pagar",G53="Pagar"),NETWORKDAYS($I$11,F53,'Festivos Colombia'!$A$3:$A$22),0) -> 0 | I53: =H53 -> 0
D54: Reembolso Daniel Alberto Ramos Duran cc040 - Environmental Dynamics INTL | E54: 33100 | F54: 46128 | G54: Cancelado | H54: =IF(OR(G54="Sin pagar",G54="Pagar"),NETWORKDAYS($I$11,F54,'Festivos Colombia'!$A$3:$A$22),0) -> 0 | I54: =H54 -> 0
... D83: Reembolso Mario Fernando Benitez Zabala cc020 - sophos | E83: 112480 | F83: 46142 | G83: Cancelado | H83: =IF(OR(G83="Sin pagar",G83="Pagar"),NETWORKDAYS($I$11,F83,'Festivos Colombia'!$A$3:$A$22),0) -> 0 | I83: =H83 -> 0
D84: TIQUETES AÉREOS , HOTELES | E84: =SUBTOTAL(9,E85:E87) -> 16446730
D85: Tiquete Catalina Duque Bog - Lima, guayaquil y Bog | E85: 5213840 | F85: 46128 | G85: Cancelado | H85: =IF(OR(G85="Sin pagar",G85="Pagar"),NETWORKDAYS($I$11,F85,'Festivos Colombia'!$A$3:$A$22),0) -> 0 | I85: =H85 -> 0
D86: Tiquete Andy Muñoz Bog - Lima, guayaquil y Bog | E86: 5739280 | F86: 46129 | G86: Cancelado | H86: =IF(OR(G86="Sin pagar",G86="Pagar"),NETWORKDAYS($I$11,F86,'Festivos Colombia'!$A$3:$A$22),0) -> 0 | I86: =H86 -> 0
D87: Tiquete Catalina Duque viaje a Mexico | E87: 5493610 | F87: 46147 | G87: Cancelado | H87: =IF(OR(G87="Sin pagar",G87="Pagar"),NETWORKDAYS($I$11,F87,'Festivos Colombia'!$A$3:$A$22),0) -> 0 | I87: =H87 -> 0
D88: ASESORÍAS | E88: =SUBTOTAL(9,E89:E90) -> 20244754
A89: =G89 -> Cancelado | B89: =IF(#REF!<=-1,1,IF(#REF!<=5,2,IF(#REF!<=15,3,IF(H89<=60,4)))) -> #REF! | C89: 6778 | D89: Global CS Colombia SAS -Solutions & payroll-Servicio Marzo 2026 | E89: 19853587 | F89: 46122 | G89: Cancelado | H89: =IF(OR(G89="Sin pagar",G89="Pagar"),NETWORKDAYS($I$11,F89,'Festivos Colombia'!$A$3:$A$22),0) -> 0 | I89: =H89 -> 0
A90: =G90 -> Cancelado | B90: =IF(#REF!<=-1,1,IF(#REF!<=5,2,IF(#REF!<=15,3,IF(H90<=60,4)))) -> #REF! | C90: 5-272 | D90: Global CS Colombia SAS -Solutions & payroll- Reembolso Gastos Marzo | E90: 391167 | F90: 46122 | G90: Cancelado | H90: =IF(OR(G90="Sin pagar",G90="Pagar"),NETWORKDAYS($I$11,F90,'Festivos Colombia'!$A$3:$A$22),0) -> 0 | I90: =H90 -> 0
D91: COSTOS FINANCIEROS | E91: =SUBTOTAL(9,E92) -> 13545478
A92: =G92 -> Cancelado | B92: =IF(#REF!<=-1,1,IF(#REF!<=5,2,IF(#REF!<=15,3,IF(H92<=60,4)))) -> #REF! | D92: Costos financieros (Cuenta GLOBAL CS) | E92: 13545478 | F92: 46142 | G92: Cancelado | H92: =IF(OR(G92="Sin pagar",G92="Pagar"),NETWORKDAYS($I$11,F92,'Festivos Colombia'!$A$3:$A$22),0) -> 0 | I92: =H92 -> 0
D93: CREDITOS Y LIBRANZAS | E93: =SUBTOTAL(9,E94) -> 2209861
A94: =G94 -> Cancelado | B94: =IF(#REF!<=-1,1,IF(#REF!<=5,2,IF(#REF!<=15,3,IF(H94<=60,4)))) -> #REF! | D94: Libranza compensar | E94: 2209861 | F94: 46142 | G94: Cancelado | H94: =IF(OR(G94="Sin pagar",G94="Pagar"),NETWORKDAYS($I$11,F94,'Festivos Colombia'!$A$3:$A$22),0) -> 0 | I94: =H94 -> 0
D95: ESTUDIOS DE SEGURIDAD Y EXAMENES OCUPACIONALES-PÓLIZAS SALUD | E95: =SUBTOTAL(9,E96:E102) -> 1014706
A96: =G96 -> Cancelado | B96: =IF(#REF!<=-1,1,IF(#REF!<=5,2,IF(#REF!<=15,3,IF(H96<=60,4)))) -> #REF! | C96: 6993 | D96: EMASOC | E96: =235000 -> 235000 | F96: 46135 | G96: Cancelado | H96: =IF(OR(G96="Sin pagar",G96="Pagar"),NETWORKDAYS($I$11,F96,'Festivos Colombia'!$A$3:$A$22),0) -> 0 | I96: =H96 -> 0
A97: =G97 -> Cancelado | B97: =IF(#REF!<=-1,1,IF(#REF!<=5,2,IF(#REF!<=15,3,IF(H97<=60,4)))) -> #REF! | C97: 7003 | D97: EMASOC | E97: 312500 | F97: 46141 | G97: Cancelado | H97: =IF(OR(G97="Sin pagar",G97="Pagar"),NETWORKDAYS($I$11,F97,'Festivos Colombia'!$A$3:$A$22),0) -> 0 | I97: =H97 -> 0
A98: =G98 -> Sin Pagar | B98: =IF(#REF!<=-1,1,IF(#REF!<=5,2,IF(#REF!<=15,3,IF(H98<=60,4)))) -> #REF! | C98: 7014 | D98: EMASOC | E98: =315500*0 -> 0 | F98: 46149 | G98: Sin Pagar | H98: =IF(OR(G98="Sin pagar",G98="Pagar"),NETWORKDAYS($I$11,F98,'Festivos Colombia'!$A$3:$A$22),0) -> 24 | I98: =H98 -> 24
A99: =G99 -> Sin Pagar | B99: =IF(#REF!<=-1,1,IF(#REF!<=5,2,IF(#REF!<=15,3,IF(H99<=60,4)))) -> #REF! | C99: 7033 | D99: EMASOC | E99: =107500*0 -> 0 | F99: 46159 | G99: Sin Pagar | H99: =IF(OR(G99="Sin pagar",G99="Pagar"),NETWORKDAYS($I$11,F99,'Festivos Colombia'!$A$3:$A$22),0) -> 30 | I99: =H99 -> 30
A100: =G100 -> Sin Pagar | B100: =IF(#REF!<=-1,1,IF(#REF!<=5,2,IF(#REF!<=15,3,IF(H100<=60,4)))) -> #REF! | C100: 7047 | D100: EMASOC | E100: =117500*0 -> 0 | F100: 46165 | G100: Sin Pagar | H100: =IF(OR(G100="Sin pagar",G100="Pagar"),NETWORKDAYS($I$11,F100,'Festivos Colombia'!$A$3:$A$22),0) -> 34 | I100: =H100 -> 34
A101: =G101 -> Sin Pagar | B101: =IF(#REF!<=-1,1,IF(#REF!<=5,2,IF(#REF!<=15,3,IF(H101<=60,4)))) -> #REF! | C101: 7052 | D101: EMASOC | E101: =117500*0 -> 0 | F101: 46170 | G101: Sin Pagar | H101: =IF(OR(G101="Sin pagar",G101="Pagar"),NETWORKDAYS($I$11,F101,'Festivos Colombia'!$A$3:$A$22),0) -> 38 | I101: =H101 -> 38
A102: =G102 -> Cancelado | B102: =IF(#REF!<=-1,1,IF(#REF!<=5,2,IF(#REF!<=15,3,IF(H102<=60,4)))) -> #REF! | C102: 356015978 | D102: Allianz Póliza No: 23730847- Jerson Porras | E102: =467206 -> 467206 | F102: 46142 | G102: Cancelado | H102: =IF(OR(G102="Sin pagar",G102="Pagar"),NETWORKDAYS($I$11,F102,'Festivos Colombia'!$A$3:$A$22),0) -> 0 | I102: =H102 -> 0
D103: NÓMINAS Y ABONO A TARJETAS PEOPLE PASS | E103: =SUBTOTAL(9,E104:E106) -> 1625960577
A104: =G104 -> Cancelado | B104: =IF(#REF!<=-1,1,IF(#REF!<=5,2,IF(#REF!<=15,3,IF(H104<=60,4)))) -> #REF! | D104: Monetización Sena Marzo | E104: =7879073*0 -> 0 | F104: 46113 | G104: Cancelado | H104: =IF(OR(G104="Sin pagar",G104="Pagar"),NETWORKDAYS($I$11,F104,'Festivos Colombia'!$A$3:$A$22),0) -> 0 | I104: =H104 -> 0
A105: =G105 -> Cancelado | B105: =IF(#REF!<=-1,1,IF(#REF!<=5,2,IF(#REF!<=15,3,IF(H105<=60,4)))) -> #REF! | C105: 87 Registros | D105: Nomina OE | E105: 1624330113 | F105: 46140 | G105: Cancelado | H105: =IF(OR(G105="Sin pagar",G105="Pagar"),NETWORKDAYS($I$11,F105,'Festivos Colombia'!$A$3:$A$22),0) -> 0 | I105: =H105 -> 0
A106: =G106 -> Cancelado | B106: =IF(#REF!<=-1,1,IF(#REF!<=5,2,IF(#REF!<=15,3,IF(H106<=60,4)))) -> #REF! | C106: FPP476539 | D106: People Pass-Market | E106: 1630464 | F106: 46140 | G106: Cancelado | H106: =IF(OR(G106="Sin pagar",G106="Pagar"),NETWORKDAYS($I$11,F106,'Festivos Colombia'!$A$3:$A$22),0) -> 0 | I106: =H106 -> 0
D107: LIQUIDACIONES | E107: =SUBTOTAL(9,E108:E109) -> 101480304
A108: =G108 -> Cancelado | B108: =IF(#REF!<=-1,1,IF(#REF!<=5,2,IF(#REF!<=15,3,IF(H108<=60,4)))) -> #REF! | C108: 1 registro | D108: Liquidación Jorge Crismatt Dungand-Best Formulations | E108: 90497092 | F108: 46122 | G108: Cancelado | H108: =IF(OR(G108="Sin pagar",G108="Pagar"),NETWORKDAYS($I$11,F108,'Festivos Colombia'!$A$3:$A$22),0) -> 0 | I108: =H108 -> 0
A109: =G109 -> Cancelado | B109: =IF(#REF!<=-1,1,IF(#REF!<=5,2,IF(#REF!<=15,3,IF(H109<=60,4)))) -> #REF! | C109: 1 registro | D109: Liquidación Sandra Viviana Barba Lizaralde-Allegis Group | E109: 10983212 | F109: 46141 | G109: Cancelado | H109: =IF(OR(G109="Sin pagar",G109="Pagar"),NETWORKDAYS($I$11,F109,'Festivos Colombia'!$A$3:$A$22),0) -> 0 | I109: =H109 -> 0
D110: IMPREVISTO | E110: =SUBTOTAL(9,E111:E117) -> 123007156
A111: =G111 -> Cancelado | B111: =IF(#REF!<=-1,1,IF(#REF!<=5,2,IF(#REF!<=15,3,IF(H111<=60,4)))) -> #REF! | D111: Gastos adicionales evento hotel - Catalina Duque (Hitachi) | E111: 222050 | F111: 46121 | G111: Cancelado | H111: =IF(OR(G111="Sin pagar",G111="Pagar"),NETWORKDAYS($I$11,F111,'Festivos Colombia'!$A$3:$A$22),0) -> 0 | I111: =H111 -> 0
A112: =G112 -> Cancelado | B112: =IF(#REF!<=-1,1,IF(#REF!<=5,2,IF(#REF!<=15,3,IF(H112<=60,4)))) -> #REF! | D112: Bonos anticipados Alberto de Santa Ana y Carlos Hoyos- Leistritz advanced Technologies Corp | E112: 115566758 | F112: 46122 | G112: Cancelado | H112: =IF(OR(G112="Sin pagar",G112="Pagar"),NETWORKDAYS($I$11,F112,'Festivos Colombia'!$A$3:$A$22),0) -> 0 | I112: =H112 -> 0
A113: =G113 -> Cancelado | B113: =IF(#REF!<=-1,1,IF(#REF!<=5,2,IF(#REF!<=15,3,IF(H113<=60,4)))) -> #REF! | C113: 10466184 | D113: Generacióncertificado camara y comercio | E113: 12100 | F113: 46133 | G113: Cancelado | H113: =IF(OR(G113="Sin pagar",G113="Pagar"),NETWORKDAYS($I$11,F113,'Festivos Colombia'!$A$3:$A$22),0) -> 0 | I113: =H113 -> 0
A114: =G114 -> Cancelado | B114: =IF(#REF!<=-1,1,IF(#REF!<=5,2,IF(#REF!<=15,3,IF(H114<=60,4)))) -> #REF! | D114: Pago a proveedor - Ivonne Torres Cotización La piña electrica (anticipo 50%) | E114: 3377500 | F114: 46133 | G114: Cancelado | H114: =IF(OR(G114="Sin pagar",G114="Pagar"),NETWORKDAYS($I$11,F114,'Festivos Colombia'!$A$3:$A$22),0) -> 0 | I114: =H114 -> 0
A115: =G115 -> Cancelado | B115: =IF(#REF!<=-1,1,IF(#REF!<=5,2,IF(#REF!<=15,3,IF(H115<=60,4)))) -> #REF! | D115: Pago vales sanitas - Ivonne Torres | E115: =(47400*1.19)*3 -> 169218 | F115: 46135 | G115: Cancelado | H115: =IF(OR(G115="Sin pagar",G115="Pagar"),NETWORKDAYS($I$11,F115,'Festivos Colombia'!$A$3:$A$22),0) -> 0 | I115: =H115 -> 0
A116: =G116 -> Cancelado | B116: =IF(#REF!<=-1,1,IF(#REF!<=5,2,IF(#REF!<=15,3,IF(H116<=60,4)))) -> #REF! | D116: Pago vales sanitas -Maria Gabriela Acosta | E116: =(47400*1.19)*5 -> 282030 | F116: 46135 | G116: Cancelado | H116: =IF(OR(G116="Sin pagar",G116="Pagar"),NETWORKDAYS($I$11,F116,'Festivos Colombia'!$A$3:$A$22),0) -> 0 | I116: =H116 -> 0
A117: =G117 -> Cancelado | B117: =IF(#REF!<=-1,1,IF(#REF!<=5,2,IF(#REF!<=15,3,IF(H117<=60,4)))) -> #REF! | D117: Pago a proveedor - Ivonne Torres Cotización La piña electrica (saldo 50%) | E117: =3377500 -> 3377500 | F117: 46146 | G117: Cancelado | H117: =IF(OR(G117="Sin pagar",G117="Pagar"),NETWORKDAYS($I$11,F117,'Festivos Colombia'!$A$3:$A$22),0) -> 0 | I117: =H117 -> 0
D118: TOTAL EGRESOS | E118: =SUBTOTAL(9,E13:E117) -> 3.1139689e+09
D119: 4 x mil transacciones | E119: =(E118*4)/1000 -> 12455876
D120: TOTAL A PAGAR | E120: =E118+E119 -> 3.1264248e+09 | G120: Sin Pagar
D124: SALDO | E124: =E8-E118 -> 1.2837765e+09
D125: % | E125: =IF($E$8=0,0,E124/$E$8) -> 0.29191698
D128: Cristhian Guapacha-Root Capital -Tarjeta 1 | E128: Carestream
D131: 46113 | E131: 46124 | F131: =SUMIFS($E$12:$E$127,$F$12:$F$127,">="&D131,$F$12:$F$127,"<="&E131,$G$12:$G$127,$E$149) -> 0 | G131: Reembolsos y tiquetes
D132: 46125 | E132: 46126 | F132: =SUMIFS($E$12:$E$127,$F$12:$F$127,">="&D132,$F$12:$F$127,"<="&E132,$G$12:$G$127,$E$149) -> 0
D133: 46127 | E133: 46127 | F133: =SUMIFS($E$12:$E$127,$F$12:$F$127,">="&D133,$F$12:$F$127,"<="&E133,$G$12:$G$127,$E$149) -> 0 | G133: RTE FTE y SS
D134: 46128 | E134: 46131 | F134: =SUMIFS($E$12:$E$127,$F$12:$F$127,">="&D134,$F$12:$F$127,"<="&E134,$G$12:$G$127,$E$149) -> 0 | G134: Reembolsos y tiquetes
D135: 46132 | E135: 46138 | F135: =SUMIFS($E$12:$E$127,$F$12:$F$127,">="&D135,$F$12:$F$127,"<="&E135,$G$12:$G$127,$E$149) -> 0 | G135: Reembolsos y tiquetes
D136: 46139 | E136: 46142 | F136: =SUMIFS($E$12:$E$127,$F$12:$F$127,">="&D136,$F$12:$F$127,"<="&E136,$G$12:$G$127,$E$149) -> 0 | G136: Nóminas , Reembolsos, libranzas, ICA anual
D137: 46143 | E137: 46148 | F137: =SUMIFS($E$12:$E$127,$F$12:$F$127,">="&D137,$F$12:$F$127,"<="&E137,$G$12:$G$127,$E$149) -> 0
D138: TOTAL EGRESOS | F138: =SUM(F131:F137) -> 0
D141: Gastos del 27 al 30 Marzo | F141: =SUM(F131:F137) -> 0
...

Sheet MAYO
E1: 42400
D4: BANCOS | E4: =SUBTOTAL(9,E5:E5) -> 1.2837765e+09
D5: Bancos | E5: =ABRIL!$F$146 -> 1.2837765e+09
D6: FACTURACIÓN PENDIENTE POR MONETIZAR | E6: =SUBTOTAL(9,E7:E7) -> 10328391
D7: Monetización - facturación y Offycycle mayo | E7: 10328391
E8: =SUBTOTAL(9,E4:E7) -> 1.2941049e+09
C11: CUENTAS X PAGAR MES | E11: MAYO | F11: Fecha de Elaboración: | I11: 46143
C12: Factura | D12: PROVEEDOR | E12: VALOR | F12: Fecha vencimiento | G12: Estado | I12: KPI | J12: Objeto
D13: PAGOS ANTICIPADOS | E13: =SUBTOTAL(9,E14) -> 25815079
A14: =G14 -> Sin Pagar | B14: =IF(#REF!<=-1,1,IF(#REF!<=5,2,IF(#REF!<=15,3,IF(H14<=60,4)))) -> #REF! | C14: 1 registro | D14: Nómina Sergio Jimenez Belimo | E14: 25815079 | F14: 46170 | G14: Sin Pagar | H14: =IF(OR(G14="Sin pagar",G14="Pagar"),NETWORKDAYS($I$11,F14,'Festivos Colombia'!$A$3:$A$22),0) -> 18 | I14: =H14 -> 18
D15: SEGURIDAD SOCIAL | E15: =SUBTOTAL(9,E16:E16) -> 652981100
A16: =G16 -> Cancelado | B16: =IF(#REF!<=-1,1,IF(#REF!<=5,2,IF(#REF!<=15,3,IF(H16<=60,4)))) -> #REF! | D16: Pago seguridad social Global | E16: 652981100 | F16: 46155 | G16: Cancelado | H16: =IF(OR(G16="Sin pagar",G16="Pagar"),NETWORKDAYS($I$11,F16,'Festivos Colombia'!$A$3:$A$22),0) -> 0 | I16: =H16 -> 0
D17: AFC´S | E17: =SUBTOTAL(9,E18:E20) -> 81747678
A18: =G18 -> Cancelado | B18: =IF(#REF!<=-1,1,IF(#REF!<=5,2,IF(#REF!<=15,3,IF(H18<=60,4)))) -> #REF! | C18: 1 | D18: AFC Bancolombia Carlos de real de Abril por devolución | E18: 4166667 | F18: 46154 | G18: Cancelado | H18: =IF(OR(G18="Sin pagar",G18="Pagar"),NETWORKDAYS($I$11,F18,'Festivos Colombia'!$A$3:$A$22),0) -> 0 | I18: =H18 -> 0
A19: =G19 -> Sin Pagar | B19: =IF(#REF!<=-1,1,IF(#REF!<=5,2,IF(#REF!<=15,3,IF(H19<=60,4)))) -> #REF! | C19: 1 | D19: AFC y aportes voluntarios - Cheque | E19: 18566667 | F19: 46171 | G19: Sin Pagar | H19: =IF(OR(G19="Sin pagar",G19="Pagar"),NETWORKDAYS($I$11,F19,'Festivos Colombia'!$A$3:$A$22),0) -> 19 | I19: =H19 -> 19
A20: =G20 -> Sin Pagar | B20: =IF(#REF!<=-1,1,IF(#REF!<=5,2,IF(#REF!<=15,3,IF(H20<=60,4)))) -> #REF! | C20: 1 | D20: AFC y aportes voluntarios -SOI y Aportes en Linea | E20: 59014344 | F20: 46171 | G20: Sin Pagar | H20: =IF(OR(G20="Sin pagar",G20="Pagar"),NETWORKDAYS($I$11,F20,'Festivos Colombia'!$A$3:$A$22),0) -> 19 | I20: =H20 -> 19
D21: IMPUESTOS | E21: =SUBTOTAL(9,E22:E24) -> 437515000 | H21: =IF(OR(G21="Sin pagar",G21="Pagar"),NETWORKDAYS($I$11,F21,'Festivos Colombia'!$A$3:$A$22),0) -> 0 | I21: =H21 -> 0
A22: =G22 -> Cancelado | B22: =IF(#REF!<=-1,1,IF(#REF!<=5,2,IF(#REF!<=15,3,IF(H22<=60,4)))) -> #REF! | D22: Retención en la fuente | E22: 400001000 | F22: 46156 | G22: Cancelado | H22: =IF(OR(G22="Sin pagar",G22="Pagar"),NETWORKDAYS($I$11,F22,'Festivos Colombia'!$A$3:$A$22),0) -> 0 | I22: =H22 -> 0 | J22: =E22+E23 -> 437109000
A23: =G23 -> Cancelado | B23: =IF(#REF!<=-1,1,IF(#REF!<=5,2,IF(#REF!<=15,3,IF(H23<=60,4)))) -> #REF! | D23: Renta año 2025 | E23: 37108000 | F23: 46156 | G23: Cancelado | H23: =IF(OR(G23="Sin pagar",G23="Pagar"),NETWORKDAYS($I$11,F23,'Festivos Colombia'!$A$3:$A$22),0) -> 0 | I23: =H23 -> 0
A24: =G24 -> Sin Pagar | B24: =IF(#REF!<=-1,1,IF(#REF!<=5,2,IF(#REF!<=15,3,IF(H24<=60,4)))) -> #REF! | D24: Retención de ICA | E24: 406000 | F24: 46164 | G24: Sin Pagar | H24: =IF(OR(G24="Sin pagar",G24="Pagar"),NETWORKDAYS($I$11,F24,'Festivos Colombia'!$A$3:$A$22),0) -> 14 | I24: =H24 -> 14
D25: PLANES COMPLEMENTARIOS Y PREPAGADAS | E25: =SUBTOTAL(9,E26:E28) -> 1712130 | H25: =IF(OR(G25="Sin pagar",G25="Pagar"),NETWORKDAYS($I$11,F25,'Festivos Colombia'!$A$3:$A$22),0) -> 0
A26: =G26 -> Cancelado | B26: =IF(#REF!<=-1,1,IF(#REF!<=5,2,IF(#REF!<=15,3,IF(H26<=60,4)))) -> #REF! | C26: 20911226831 | D26: Póliza suramericana # 091000808150 SALUD FAMILIAR | E26: 471136 | F26: 46159 | G26: Cancelado | H26: =IF(OR(G26="Sin pagar",G26="Pagar"),NETWORKDAYS($I$11,F26,'Festivos Colombia'!$A$3:$A$22),0) -> 0 | I26: =H26 -> 0
A27: =G27 -> Cancelado | B27: =IF(#REF!<=-1,1,IF(#REF!<=5,2,IF(#REF!<=15,3,IF(H27<=60,4)))) -> #REF! | C27: 20911226518 | D27: Póliza suramericana # 091000808150 SALUD FAMILIAR | E27: 828400 | F27: 46155 | G27: Cancelado | H27: =IF(OR(G27="Sin pagar",G27="Pagar"),NETWORKDAYS($I$11,F27,'Festivos Colombia'!$A$3:$A$22),0) -> 0 | I27: =H27 -> 0
A28: =G28 -> Cancelado | B28: =IF(#REF!<=-1,1,IF(#REF!<=5,2,IF(#REF!<=15,3,IF(H28<=60,4)))) -> #REF! | C28: 20911226519 | D28: Póliza suramericana # 091000808150 SALUD FAMILIAR | E28: 412594 | F28: 46155 | G28: Cancelado | H28: =IF(OR(G28="Sin pagar",G28="Pagar"),NETWORKDAYS($I$11,F28,'Festivos Colombia'!$A$3:$A$22),0) -> 0 | I28: =H28 -> 0
D29: PÓLIZAS Y SEGUROS | E29: =SUBTOTAL(9,E30:E31) -> 16795651 | H29: =IF(OR(G29="Sin pagar",G29="Pagar"),NETWORKDAYS($I$11,F29,'Festivos Colombia'!$A$3:$A$22),0) -> 0
A30: =G30 -> Cancelado | B30: =IF(#REF!<=-1,1,IF(#REF!<=5,2,IF(#REF!<=15,3,IF(H30<=60,4)))) -> #REF! | C30: 12310648205 | D30: Plan Dental 103232083 | E30: 1081351 | F30: 46154 | G30: Cancelado | H30: =IF(OR(G30="Sin pagar",G30="Pagar"),NETWORKDAYS($I$11,F30,'Festivos Colombia'!$A$3:$A$22),0) -> 0 | I30: =H30 -> 0
A31: =G31 -> Cancelado | B31: =IF(#REF!<=-1,1,IF(#REF!<=5,2,IF(#REF!<=15,3,IF(H31<=60,4)))) -> #REF! | C31: 12310649246 | D31: Plan salud 10108211747 | E31: 15714300 | F31: 46154 | G31: Cancelado | H31: =IF(OR(G31="Sin pagar",G31="Pagar"),NETWORKDAYS($I$11,F31,'Festivos Colombia'!$A$3:$A$22),0) -> 0 | I31: =H31 -> 0
D32: REEMBOLSO GASTOS VIAJE | E32: =SUBTOTAL(9,E33:E52) -> 1.3134604e+08
D33: Reembolso Camila Marin Melo cc020 - sophos | E33: 7658879 | F33: 46149 | G33: Cancelado | H33: =IF(OR(G33="Sin pagar",G33="Pagar"),NETWORKDAYS($I$11,F33,'Festivos Colombia'!$A$3:$A$22),0) -> 0 | I33: =H33 -> 0
D34: Reembolso Cristiam Silva cc020 - sophos | E34: 1337160 | F34: 46149 | G34: Cancelado | H34: =IF(OR(G34="Sin pagar",G34="Pagar"),NETWORKDAYS($I$11,F34,'Festivos Colombia'!$A$3:$A$22),0) -> 0 | I34: =H34 -> 0
D35: Reembolso Cristian Javier Gutierrez Torres-cc020 - Sophos | E35: 518478 | F35: 46149 | G35: Cancelado | H35: =IF(OR(G35="Sin pagar",G35="Pagar"),NETWORKDAYS($I$11,F35,'Festivos Colombia'!$A$3:$A$22),0) -> 0 | I35: =H35 -> 0
D36: Reembolso Daniel Alberto Ramos Duran cc040 - Environmental Dynamics INTL | E36: 5242497.6 | F36: 46149 | G36: Cancelado | H36: =IF(OR(G36="Sin pagar",G36="Pagar"),NETWORKDAYS($I$11,F36,'Festivos Colombia'!$A$3:$A$22),0) -> 0 | I36: =H36 -> 0
D37: Reembolso Genesis Coromoto Marchena Gómez - cc081 - go - global outsourcing inc | E37: 1944281 | F37: 46149 | G37: Cancelado | H37: =IF(OR(G37="Sin pagar",G37="Pagar"),NETWORKDAYS($I$11,F37,'Festivos Colombia'!$A$3:$A$22),0) -> 0 | I37: =H37 -> 0
D38: Reembolso Milagro del Vallle Sanchez cc020 - sophos | E38: 1270939 | F38: 46149 | G38: Cancelado | H38: =IF(OR(G38="Sin pagar",G38="Pagar"),NETWORKDAYS($I$11,F38,'Festivos Colombia'!$A$3:$A$22),0) -> 0 | I38: =H38 -> 0
D39: Reembolso Paula Andrea Alba Grajales CC077 - LANO SOFTWARE GMBH | E39: 9648516 | F39: 46149 | G39: Cancelado | H39: =IF(OR(G39="Sin pagar",G39="Pagar"),NETWORKDAYS($I$11,F39,'Festivos Colombia'!$A$3:$A$22),0) -> 0 | I39: =H39 -> 0
D40: Reembolso Monica Martinez Martinez-cc012 - lifenet health | E40: 9022977 | F40: 46149 | G40: Cancelado | H40: =IF(OR(G40="Sin pagar",G40="Pagar"),NETWORKDAYS($I$11,F40,'Festivos Colombia'!$A$3:$A$22),0) -> 0 | I40: =H40 -> 0
D41: Reembolso Camila Marin Melo cc020 - sophos | E41: 2214750 | F41: 46157 | G41: Cancelado | H41: =IF(OR(G41="Sin pagar",G41="Pagar"),NETWORKDAYS($I$11,F41,'Festivos Colombia'!$A$3:$A$22),0) -> 0 | I41: =H41 -> 0
D42: Reembolso Cristiam Silva cc020 - sophos | E42: 63900 | F42: 46157 | G42: Cancelado | H42: =IF(OR(G42="Sin pagar",G42="Pagar"),NETWORKDAYS($I$11,F42,'Festivos Colombia'!$A$3:$A$22),0) -> 0 | I42: =H42 -> 0
D43: Reembolso Maria Claudia Bohorquez cc020 - sophos | E43: 1679100 | F43: 46157 | G43: Cancelado | H43: =IF(OR(G43="Sin pagar",G43="Pagar"),NETWORKDAYS($I$11,F43,'Festivos Colombia'!$A$3:$A$22),0) -> 0 | I43: =H43 -> 0
D44: Reembolso Cristian Javier Gutierrez Torres-cc020 - Sophos | E44: 79400 | F44: 46157 | G44: Cancelado | H44: =IF(OR(G44="Sin pagar",G44="Pagar"),NETWORKDAYS($I$11,F44,'Festivos Colombia'!$A$3:$A$22),0) -> 0 | I44: =H44 -> 0
... D51: Reembolso Previsto | E51: 33000000 | F51: 46164 | G51: Sin Pagar | H51: =IF(OR(G51="Sin pagar",G51="Pagar"),NETWORKDAYS($I$11,F51,'Festivos Colombia'!$A$3:$A$22),0) -> 14 | I51: =H51 -> 14
D52: Reembolso Previsto | E52: =160000000/4 -> 40000000 | F52: 46171 | G52: Sin Pagar | H52: =IF(OR(G52="Sin pagar",G52="Pagar"),NETWORKDAYS($I$11,F52,'Festivos Colombia'!$A$3:$A$22),0) -> 19 | I52: =H52 -> 19
D53: TIQUETES AÉREOS , HOTELES | E53: =SUBTOTAL(9,E54:E55) -> 10491352
D54: Tiquete Andy Muñoz Cartagena-Lima y Vsa | E54: 2991352 | F54: 46156 | G54: Cancelado | H54: =IF(OR(G54="Sin pagar",G54="Pagar"),NETWORKDAYS($I$11,F54,'Festivos Colombia'!$A$3:$A$22),0) -> 0 | I54: =H54 -> 0
D55: Tiquete Previsto | E55: =30000000/4 -> 7500000 | F55: 46171 | G55: Sin Pagar | H55: =IF(OR(G55="Sin pagar",G55="Pagar"),NETWORKDAYS($I$11,F55,'Festivos Colombia'!$A$3:$A$22),0) -> 19 | I55: =H55 -> 19
D56: ASESORÍAS | E56: =SUBTOTAL(9,E57:E58) -> 20242736
A57: =G57 -> Cancelado | B57: =IF(#REF!<=-1,1,IF(#REF!<=5,2,IF(#REF!<=15,3,IF(H57<=60,4)))) -> #REF! | C57: 6857 | D57: Global CS Colombia SAS -Solutions & payroll-Servicio abril 2026 | E57: 19748433 | F57: 46150 | G57: Cancelado | H57: =IF(OR(G57="Sin pagar",G57="Pagar"),NETWORKDAYS($I$11,F57,'Festivos Colombia'!$A$3:$A$22),0) -> 0 | I57: =H57 -> 0
A58: =G58 -> Cancelado | B58: =IF(#REF!<=-1,1,IF(#REF!<=5,2,IF(#REF!<=15,3,IF(H58<=60,4)))) -> #REF! | C58: 5-313 | D58: Global CS Colombia SAS -Solutions & payroll- Reembolso Gastos abril | E58: 494303 | F58: 46150 | G58: Cancelado | H58: =IF(OR(G58="Sin pagar",G58="Pagar"),NETWORKDAYS($I$11,F58,'Festivos Colombia'!$A$3:$A$22),0) -> 0 | I58: =H58 -> 0
D59: COSTOS FINANCIEROS | E59: =SUBTOTAL(9,E60) -> 13545478
A60: =G60 -> Sin Pagar | B60: =IF(#REF!<=-1,1,IF(#REF!<=5,2,IF(#REF!<=15,3,IF(H60<=60,4)))) -> #REF! | D60: Costos financieros (Cuenta GLOBAL CS) | E60: 13545478 | F60: 46172 | G60: Sin Pagar | H60: =IF(OR(G60="Sin pagar",G60="Pagar"),NETWORKDAYS($I$11,F60,'Festivos Colombia'!$A$3:$A$22),0) -> 19 | I60: =H60 -> 19
D61: CREDITOS Y LIBRANZAS | E61: =SUBTOTAL(9,E62) -> 2209861
A62: =G62 -> Sin Pagar | B62: =IF(#REF!<=-1,1,IF(#REF!<=5,2,IF(#REF!<=15,3,IF(H62<=60,4)))) -> #REF! | D62: Libranza compensar | E62: 2209861 | F62: 46172 | G62: Sin Pagar | H62: =IF(OR(G62="Sin pagar",G62="Pagar"),NETWORKDAYS($I$11,F62,'Festivos Colombia'!$A$3:$A$22),0) -> 19 | I62: =H62 -> 19
D63: ESTUDIOS DE SEGURIDAD Y EXAMENES OCUPACIONALES-PÓLIZAS SALUD | E63: =SUBTOTAL(9,E64:E69) -> 1242707
A64: =G64 -> Cancelado | B64: =IF(#REF!<=-1,1,IF(#REF!<=5,2,IF(#REF!<=15,3,IF(H64<=60,4)))) -> #REF! | C64: 7014 | D64: EMASOC | E64: =315500 -> 315500 | F64: 46150 | G64: Cancelado | H64: =IF(OR(G64="Sin pagar",G64="Pagar"),NETWORKDAYS($I$11,F64,'Festivos Colombia'!$A$3:$A$22),0) -> 0 | I64: =H64 -> 0
A65: =G65 -> Cancelado | B65: =IF(#REF!<=-1,1,IF(#REF!<=5,2,IF(#REF!<=15,3,IF(H65<=60,4)))) -> #REF! | C65: 7033 | D65: EMASOC | E65: =107500 -> 107500 | F65: 46157 | G65: Cancelado | H65: =IF(OR(G65="Sin pagar",G65="Pagar"),NETWORKDAYS($I$11,F65,'Festivos Colombia'!$A$3:$A$22),0) -> 0 | I65: =H65 -> 0
A66: =G66 -> Sin Pagar | B66: =IF(#REF!<=-1,1,IF(#REF!<=5,2,IF(#REF!<=15,3,IF(H66<=60,4)))) -> #REF! | C66: 7047 | D66: EMASOC | E66: =117500 -> 117500 | F66: 46164 | G66: Sin Pagar | H66: =IF(OR(G66="Sin pagar",G66="Pagar"),NETWORKDAYS($I$11,F66,'Festivos Colombia'!$A$3:$A$22),0) -> 14 | I66: =H66 -> 14
A67: =G67 -> Sin Pagar | B67: =IF(#REF!<=-1,1,IF(#REF!<=5,2,IF(#REF!<=15,3,IF(H67<=60,4)))) -> #REF! | C67: 7052 | D67: EMASOC | E67: =117500 -> 117500 | F67: 46170 | G67: Sin Pagar | H67: =IF(OR(G67="Sin pagar",G67="Pagar"),NETWORKDAYS($I$11,F67,'Festivos Colombia'!$A$3:$A$22),0) -> 18 | I67: =H67 -> 18
A68: =G68 -> Sin Pagar | B68: =IF(#REF!<=-1,1,IF(#REF!<=5,2,IF(#REF!<=15,3,IF(H68<=60,4)))) -> #REF! | C68: 7058 | D68: EMASOC | E68: =117500 -> 117500 | F68: 46170 | G68: Sin Pagar | H68: =IF(OR(G68="Sin pagar",G68="Pagar"),NETWORKDAYS($I$11,F68,'Festivos Colombia'!$A$3:$A$22),0) -> 18 | I68: =H68 -> 18
A69: =G69 -> Sin Pagar | B69: =IF(#REF!<=-1,1,IF(#REF!<=5,2,IF(#REF!<=15,3,IF(H69<=60,4)))) -> #REF! | C69: 357765027 | D69: Allianz Póliza No: 23730847- Jerson Porras | E69: =467207 -> 467207 | F69: 46173 | G69: Sin Pagar | H69: =IF(OR(G69="Sin pagar",G69="Pagar"),NETWORKDAYS($I$11,F69,'Festivos Colombia'!$A$3:$A$22),0) -> 19 | I69: =H69 -> 19 | J69: Sin radicar
D70: NÓMINAS Y ABONO A TARJETAS PEOPLE PASS | E70: =SUBTOTAL(9,E71:E73) -> 1865856101
A71: =G71 -> Cancelado | B71: =IF(#REF!<=-1,1,IF(#REF!<=5,2,IF(#REF!<=15,3,IF(H71<=60,4)))) -> #REF! | D71: Monetización Sena Marzo | E71: 10505430 | F71: 46153 | G71: Cancelado | H71: =IF(OR(G71="Sin pagar",G71="Pagar"),NETWORKDAYS($I$11,F71,'Festivos Colombia'!$A$3:$A$22),0) -> 0 | I71: =H71 -> 0
A72: =G72 -> Sin Pagar | B72: =IF(#REF!<=-1,1,IF(#REF!<=5,2,IF(#REF!<=15,3,IF(H72<=60,4)))) -> #REF! | C72: 87 Registros | D72: Nomina OE | E72: 1853720207 | F72: 46170 | G72: Sin Pagar | H72: =IF(OR(G72="Sin pagar",G72="Pagar"),NETWORKDAYS($I$11,F72,'Festivos Colombia'!$A$3:$A$22),0) -> 18 | I72: =H72 -> 18
A73: =G73 -> Sin Pagar | B73: =IF(#REF!<=-1,1,IF(#REF!<=5,2,IF(#REF!<=15,3,IF(H73<=60,4)))) -> #REF! | C73: FPP476539 | D73: People Pass-Market | E73: 1630464 | F73: 46170 | G73: Sin Pagar | H73: =IF(OR(G73="Sin pagar",G73="Pagar"),NETWORKDAYS($I$11,F73,'Festivos Colombia'!$A$3:$A$22),0) -> 18 | I73: =H73 -> 18
D74: LIQUIDACIONES | E74: =SUBTOTAL(9,E75:E75) -> 8282537
A75: =G75 -> Sin Pagar | B75: =IF(#REF!<=-1,1,IF(#REF!<=5,2,IF(#REF!<=15,3,IF(H75<=60,4)))) -> #REF! | C75: 1 registro | D75: Liquidacion prevista | E75: 8282537 | F75: 46164 | G75: Sin Pagar | H75: =IF(OR(G75="Sin pagar",G75="Pagar"),NETWORKDAYS($I$11,F75,'Festivos Colombia'!$A$3:$A$22),0) -> 14 | I75: =H75 -> 14
D76: IMPREVISTO | E76: =SUBTOTAL(9,E77:E77) -> 12100
A77: =G77 -> Sin Pagar | B77: =IF(#REF!<=-1,1,IF(#REF!<=5,2,IF(#REF!<=15,3,IF(H77<=60,4)))) -> #REF! | C77: 10466184 | D77: Generacióncertificado camara y comercio | E77: 12100 | F77: 46162 | G77: Sin Pagar | H77: =IF(OR(G77="Sin pagar",G77="Pagar"),NETWORKDAYS($I$11,F77,'Festivos Colombia'!$A$3:$A$22),0) -> 12 | I77: =H77 -> 12
D78: TOTAL EGRESOS | E78: =SUBTOTAL(9,E13:E77) -> 3.2697955e+09
D79: 4 x mil transacciones | E79: =(E78*4)/1000 -> 13079182
D80: TOTAL A PAGAR | E80: =E78+E79 -> 3.2828747e+09 | G80: Sin Pagar
D84: SALDO | E84: =E8-E78 -> -1.9756907e+09
D85: % | E85: =IF($E$8=0,0,E84/$E$8) -> -1.5266851
D88: Cristhian Guapacha-Root Capital -Tarjeta 1 | E88: Carestream
D91: 46143 | E91: 46152 | F91: =SUMIFS($E$12:$E$87,$F$12:$F$87,">="&D91,$F$12:$F$87,"<="&E91,$G$12:$G$87,$E$109) -> 0 | G91: Reembolsos y tiquetes
D92: 46153 | E92: 46155 | F92: =SUMIFS($E$12:$E$87,$F$12:$F$87,">="&D92,$F$12:$F$87,"<="&E92,$G$12:$G$87,$E$109) -> 0 | G92: Colsanitas
D93: 46156 | E93: 46156 | F93: =SUMIFS($E$12:$E$87,$F$12:$F$87,">="&D93,$F$12:$F$87,"<="&E93,$G$12:$G$87,$E$109) -> 0 | G93: RTE FTE y SS
D94: 46157 | E94: 46160 | F94: =SUMIFS($E$12:$E$87,$F$12:$F$87,">="&D94,$F$12:$F$87,"<="&E94,$G$12:$G$87,$E$109) -> 0 | G94: Reembolsos y tiquetes
D95: 46161 | E95: 46166 | F95: =SUMIFS($E$12:$E$87,$F$12:$F$87,">="&D95,$F$12:$F$87,"<="&E95,$G$12:$G$87,$E$109) -> 41818137 | G95: Reembolsos y tiquetes
D96: 46167 | E96: 46169 | F96: =SUMIFS($E$12:$E$87,$F$12:$F$87,">="&D96,$F$12:$F$87,"<="&E96,$G$12:$G$87,$E$109) -> 0
D97: 46170 | E97: 46173 | F97: =SUMIFS($E$12:$E$87,$F$12:$F$87,">="&D97,$F$12:$F$87,"<="&E97,$G$12:$G$87,$E$109) -> 2.0227043e+09 | G97: Nóminas , Reembolsos, libranzas, ICA anual
D98: TOTAL EGRESOS | F98: =SUM(F91:F97) -> 2.0645224e+09
D101: Gastos 01 al 27 mayo | F101: =SUM(F91:F96) -> 41818137
D102: 4 x mil | F102: =(F101*4)/1000 -> 167272.55
D103: Total | F103: =SUM(F101:F102) -> 41985410
D105: 46161 | F105: 86968485
E106: Superavit o Deficit | F106: =F105-F103 -> 44983076
E109: Sin Pagar | F109: =SUMIFS($E$12:$E$78,$F$12:$F$78,">="&D91,$F$12:$F$78,"<="&$E$96,$G$12:$G$78,$E$109) -> 41818137
E110: Cancelado | F110: =SUMIFS($E$12:$E$78,$F$12:$F$78,">="&D91,$F$12:$F$78,"<="&#REF!,$G$12:$G$78,$E$110) -> 0
E111: Total | F111: =SUM(F109:F110) -> 41818137
E112: Comprobación | F112: =E78-F111 -> 3.2279774e+09

Sheet RESUMEN
B2: 46023
E3: Trm ref 7/1/26 | F3: 3730.26
B5: INGRESOS
E7: Valores COPS | F7: Valor USD
D8: Saldo Banco Santander 07/01/2026 | E8: =ENERO!F137 -> 1.6607852e+09 | F8: =E8/F3 -> 445219.69
B10: PAGOS
B12: Desde | C12: Hasta | D12: Descripción | E12: Valores COPS | F12: Valor USD
B13: 46027 | C13: 46034 | D13: Polizas de salud, Reembolsos y tiquetes | E13: 53914058 | F13: =E13/$F$3 -> 14453.164
B14: 46037 | C14: 46037 | D14: Seguridad social, Rte fte e IVA tercer cuatrimestre | E14: 9.8949618e+08 | F14: =E14/$F$3 -> 265261.99
B15: 46038 | C15: 46038 | D15: Retención ICA, liquidacion prevista, reembolso y tiquetes | E15: 252438422 | F15: =E15/$F$3 -> 67673.144
B16: 46041 | C16: 46047 | D16: Reembolsos | E16: 55000000 | F16: =E16/$F$3 -> 14744.281
B17: 46048 | C17: 46053 | D17: Nómina, Libranzas, AFC, Reembolsos,pagos terceros | E17: 1.8667865e+09 | F17: =E17/$F$3 -> 500444.07
B18: TOTAL EGRESOS DEL MES | E18: =SUM(E13:E17) -> 3.2176352e+09 | F18: =SUM(F13:F17) -> 862576.65
D20: Pagos del 01 al 25 de enero | E20: =SUM(E13:E16) -> 1.3508487e+09 | F20: =SUM(F13:F16) -> 362132.58
D21: Impuesto 4 x mil por transacciones | E21: =E20*4/1000 -> 5403394.6 | F21: =F20*4/1000 -> 1448.5303
D22: Gran total | E22: =SUM(E20:E21) -> 1.3562521e+09 | F22: =SUM(F20:F21) -> 363581.11
D24: Superavit o Deficit | E24: =E8-E22 -> 3.0453313e+08 | F24: =F8-F22 -> 81638.58

Sheet Prioridades de pago
C2: Ingreso
B3: 44612 | C3: Saldo Banco | D3: 37331755 | E3: 5.5935868e+08
C4: Dnero pendiente por llegar | D4: =E4*F4 -> #REF! | E4: =#REF! -> #REF! | F4: 4760 | H4: =F4*#REF! -> #REF!
C5: Total | D5: =SUM(D3:D4) -> #REF!
B8: Pagos Urgentes
B10: 44965 | C10: Correción retención en la fuente Diciembre | D10: =#REF!*0 -> #REF!
B11: 44966 | C11: Rte Fte | D11: =#REF!*0 -> #REF!
B12: 44970 | C12: Seguridad social | D12: =#REF!*0 -> #REF!
B13: 44966 | C13: IVA diciembre | D13: =#REF!*0 -> #REF!
B14: 44971 | C14: Cesantías | D14: =#REF!*0 -> #REF!
B15: 44978 | C15: ICA | D15: =#REF!*0 -> #REF!
B16: Total | D16: =SUM(D10:D15) -> #REF!
B18: Otros pagos y proveedores a realizar mes de febrero
B20: 44965 | C20: Póliza suramericana 090001175163 SALUD FAMILIAR | D20: =#REF!*0 -> #REF!
B21: 44968 | C21: Póliza suramericana 090001175195 SALUD FAMILIAR | D21: =#REF!*0 -> #REF!
B22: 44969 | C22: Emasoc Fra #4340 | D22: =#REF! -> #REF! | E22: Final mes
B23: 44977 | C23: Emasoc Fra #4368 | D23: =#REF! -> #REF! | E23: Final mes
B24: 44977 | C24: Anticipo nómina Ivonne Torres | D24: =#REF! -> #REF!
B25: 44977 | C25: AFC Ivonne Torres | D25: =#REF!*0 -> #REF! | E25: Ya se pago 01 de febrero
B26: Total | D26: =SUM(D20:D25) -> #REF!
B28: Total Pagos urgentes + otros pagos | D28: =D16+D26 -> #REF!
B29: 4 x mil | C29: 4 x mil | D29: =(D28*4)/1000 -> #REF!
B30: Gran total | D30: =SUM(D28:D29) -> #REF!
C32: Diferencia | D32: =D5-D30 -> #REF!
B35: Nota: No se tiene en cuenta los valores por reembolos, tiquetes
B36: Nóminas y AFC para pagar el 28 de febrero
D40: 5.5935868e+08
D42: 2133830
D43: 2633022
D44: 264022000
D45: =SUM(D42:D44) -> 268788852
D46: =(D45*4)/1000 -> 1075155.4
D47: =SUM(D45:D46) -> 2.6986401e+08
D49: =D40-D47 -> 2.8949467e+08
D50: 2.9056485e+08
D51: =+D50-D49 -> 1070177.4

Sheet Pagos realiDiferencia 2022
B2: INVOICES | L2: PAYMENTS | P2: BALANCE
B4: Number | C4: TRM Factura | D4: Client | E4: Description | F4: Invoice Amount USD | G4: Invoice Amount COPS | I4: Total Payment | J4: partial payments COPS | L4: Date | M4: traded value | N4: TRM | O4: traded value | P4: Difference
B5: FV-4-3521 | C5: 4922.7 | D5: GLOBAL PEO SERVICES LLC | E5: EO Third parties service Client: GLOBAL CS COLOMBIA -November | F5: 330717.95 | G5: =F5*C5 -> 1.6280253e+09 | I5: 0 | J5: =280218.95*C5 -> 1.3794338e+09 | L5: 44896 | M5: 280218.95 | N5: 4821 | O5: =N5*M5 -> 1.3509356e+09 | P5: =O5-J5 -> -28498267
I6: 0 | J6: =50499*C5 -> 2.4859143e+08 | L6: 44904 | M6: 50499 | N6: 4816.3485 | O6: =N6*M6 -> 2.4322078e+08 | P6: =O6-J6+19.92 -> -5370627
B7: FV-4-3522 | C7: 4922.7 | D7: GLOBAL PEO SERVICES LLC | E7: Employer of Record Service - November | F7: 5358 | G7: =F7*C7 -> 26375827 | I7: =F7*C7 -> 26375827 | J7: 0 | L7: 44896 | M7: 5358.57 | N7: 4821 | O7: =N7*M7 -> 25833666 | P7: =O7-I7 -> -542160.63
B8: FV-4-3523 | C8: 4922.7 | D8: GLOBAL PEO SERVICES LLC | E8: Banking Taxes - November (4x1000) | F8: 1579.96 | G8: =F8*C8 -> 7777669.1 | I8: =F8*C8 -> 7777669.1 | J8: 0 | L8: 44896 | M8: 1579.96 | N8: 4821 | O8: =N8*M8 -> 7616987.2 | P8: =O8-I8 -> -160681.93
B9: FV-4-3528 | C9: 4922.7 | D9: GLOBAL PEO SERVICES LLC | E9: EO Third parties service Client: GLOBAL CS COLOMBIA -November (Paola Romero) | F9: 1207.19 | G9: =F9*C9 -> 5942634.2 | I9: =C9*F9 -> 5942634.2 | J9: 0 | L9: 44896 | M9: 1207.19 | N9: 4821 | O9: =N9*M9 -> 5819863 | P9: =O9-I9 -> -122771.22
B10: FV-4-3579 | C10: 4737.19 | D10: GLOBAL PEO SERVICES LLC | E10: Employer of Record Service - December | F10: 4543.43 | G10: =F10*C10 -> 21523091 | I10: 21523091 | J10: 0 | L10: 44917 | M10: 4543.43 | N10: 4746.3 | O10: =N10*M10 -> 21564482 | P10: =O10-I10 -> 41390.647
B11: FV-4-3580 | C11: 4737.19 | D11: GLOBAL PEO SERVICES LLC | E11: EO Third parties service Client: GLOBAL CS COLOMBIA -December | F11: 467025.04 | G11: =F11*C11 -> 2.2123863e+09 | I11: 2.2123863e+09 | J11: 0 | L11: 44917 | M11: 467025.04 | N11: 4746.3 | O11: =N11*M11 -> 2.2166409e+09 | P11: =O11-I11 -> 4254598.1
B12: FV-4-3581 | C12: 4737.19 | D12: GLOBAL PEO SERVICES LLC | E12: Banking Taxes - December (4x1000) | F12: 2242.17 | G12: =F12*C12 -> 10621585 | I12: 10621585 | J12: 0 | L12: 44917 | M12: 2242.17 | N12: 4746.3 | O12: =N12*M12 -> 10642011 | P12: =O12-I12 -> 20426.169
B13: FV-4-3582 | C13: 4737.19 | D13: GLOBAL PEO SERVICES LLC | E13: PEO Third parties service Client: GLOBAL CS COLOMBIA -December (Paola Romero) | F13: 4021.16 | G13: =F13*C13 -> 19048999 | I13: 19048999 | J13: 0 | L13: 44914 | M13: 4021.16 | N13: 4767.22 | O13: =N13*M13 -> 19169754 | P13: =O13-I13 -> 120755.43
F14: =SUM(F5:F13) -> 816694.9 | G14: =SUM(G5:G13) -> 3.9317014e+09 | I14: =SUM(I5:I13) -> 2.3036762e+09 | J14: =SUM(J5:J13) -> 1.6280253e+09 | M14: =SUM(M5:M13) -> 816695.47 | O14: =SUM(O5:O13) -> 3.901444e+09 | P14: =SUM(P5:P13) -> -30257338

Sheet Festivos Colombia
A2: FESTIVOS COLOMBIA
A3: 46023
A4: 46034
A5: 46104
A6: 46110
A7: 46114
A8: 46115
A9: 46117
A10: 46143
A11: 46160
A12: 46181
A13: 46188
A14: 46202
... A22: 46381
