Workbook
Name Fact: #REF!
Name Fact: #REF!
Name Marca: '[1]Facturas Pagadas y Pendientes'!#REF!
Name Marca: '[1]Facturas Pagadas y Pendientes'!#REF!
Name Marca1: '[1]Facturas Pagadas y Pendientes'!#REF!
Name Marca1: '[1]Facturas Pagadas y Pendientes'!#REF!
Name Marcas: '[1]Facturas Pagadas y Pendientes'!#REF!
Name Marcas: '[1]Facturas Pagadas y Pendientes'!#REF!
Name Valor: '[1]Facturas Pagadas y Pendientes'!#REF!
Name Valor: '[1]Facturas Pagadas y Pendientes'!#REF!
Name Value: '[1]Facturas Pagadas y Pendientes'!#REF!
Name Value: '[1]Facturas Pagadas y Pendientes'!#REF!
Name values: '[1]Facturas Pagadas y Pendientes'!#REF!

Sheet Hoja1
B2: No. | C2: Tipo de Gasto | D2: Fecha | E2: Gastos | F2: Ingreso | G2: Saldo
B3: 1 | C3: Transferencia recibida $. 371.65 | D3: 44974 | E3: 0 | F3: 2697.47 | G3: =F3 -> 2697.47
B4: 2 | C4: Gastos Tramites legales SAT, IGSS | D4: 44974 | E4: -2697.47 | F4: 0 | G4: =G3+E4 -> 0
B5: 3 | C5: Compra de Computadora Macbook 14 | D5: 44988 | E5: -19999.99 | F5: 0 | G5: =G4+E5 -> -19999.99
B6: 4 | C6: Apertura de cuenta y Gastos Administrativos | D6: 44991 | F6: 1000 | G6: =F6+E6 -> 1000
B7: 5 | C7: Transferencia recibida $. 150.00 | D7: 45000 | F7: 1487.85 | G7: =G6+F7 -> 2487.85
B8: 6 | C8: Devolucion apertura de cuenta y movilizacion | D8: 45003 | E8: -1500 | G8: =G7+E8 -> 987.85
B9: 7 | C9: Transferencia recibida | D9: 45015 | F9: 35063.13 | G9: =G8+F9 -> 36050.98
B10: 8 | C10: Pago de salario mes de marzo 2023 | D10: 45016 | E10: -18236.9 | G10: =G9+E10 -> 17814.08
B11: 9 | C11: Anticipo honorarios febrero a marzo 2023 | D11: 45038 | E11: -2000 | G11: =G10+E11 -> 15814.08
C12: TOTAL | E12: =SUM(E3:E11) -> -44434.36 | F12: =SUM(F3:F11) -> 40248.45 | G12: =G11 -> 15814.08

Sheet RESUMEN
A1: RESUMEN INGRESOS Y GASTOS
A2: SOLUTIONS & PAYROLL, S. A.
A3: SUCURSAL GUATEMALA
A4: No | B4: DESCRIPCION | C4: INGRESOS | D4: GASTOS
A5: 1 | B5: TRANSFERENCIAS RECIBIDAS A LA CUENTA
A6: 1.1 | B6: SALDO INCIAL | C6: 20477.39
A7: 1.2 | B7: TRANSFERENCIAS RECIBIDAS ENERO 2024 | C7: 295632.14
A9: 2 | B9: GASTOS EFECTUADOS
A10: 2.1 | B10: EGRESOS MES ENERO 2024 | D10: 32633.16
B12: SUBTOTAL | C12: =SUM(C6:C8) -> 316109.53 | D12: =SUM(D6:D10) -> 32633.16
B13: SALDO SEGÚN LIBROS | D13: =C12-D12 -> 283476.37
B14: TOTAL FINAL | C14: =SUM(C12) -> 316109.53 | D14: =SUM(D12:D13) -> 316109.53

Sheet Caja USD
B1: LIBRO DE CAJA
B2: SOLUTIONS & PAYROLL, S. A.
B3: SUCURSAL GUATEMALA USD
C4: INGRESOS | G4: EGRESOS
B5: FECHA | C5: CONCEPTO | D5: TOTAL | F5: FECHA | G5: CONCEPTO | H5: TOTAL
B6: 45292 | C6: Saldo Inicial | D6: 100 | F6: 45321 | G6: Pago Póliza Salud | H6: 1039.74
B7: 45321 | C7: transf fondos pagos Póliza | D7: 1040
C8: TOTAL INGRESOS ENERO | D8: =SUM(D6:D7) -> 1140 | G8: TOTAL EGRESOS ENERO | H8: =SUM(H6:H7) -> 1039.74
G9: SALDO DE CAJA ENERO | H9: =(D8-H8) -> 100.26
B11: FECHA | C11: CONCEPTO | D11: TOTAL | F11: FECHA | G11: CONCEPTO | H11: TOTAL
B12: 45323 | C12: Saldo Inicial | D12: =H9 -> 100.26 | F12: 45323 | G12: Pago Reembolso Ronny Quan | H12: 821.65
B13: 45323 | C13: Transf fondos Pago Reembol | D13: 821.65 | F13: 45323 | G13: Pago Póliza Vida | H13: 519.87
B14: 45349 | C14: Transf fondos Pago Póliza Salud | D14: 499.74
C15: TOTAL INGRESOS FEBRERO | D15: =SUM(D12:D14) -> 1421.65 | G15: TOTAL EGRESOS FEBRERO | H15: =SUM(H12:H14) -> 1341.52
G16: SALDO DE CAJA MARZO | H16: =D15-H15 -> 80.13
B18: FECHA | C18: CONCEPTO | D18: TOTAL | F18: FECHA | G18: CONCEPTO | H18: TOTAL
B19: 45352 | C19: Saldo Inicial | D19: =H16 -> 80.13 | F19: 45358 | G19: Pago reembolso Ronny Quan USD | H19: 979.7
B20: 45323 | C20: Transf fondos Pago Reembol | D20: 1000
C21: TOTAL INGRESOS MARZO | D21: =SUM(D19:D20) -> 1080.13 | G21: TOTAL EGRESOS MARZO | H21: =SUM(H19:H20) -> 979.7
G22: SALDO DE CAJA MARZO | H22: =D21-H21 -> 100.43
B25: FECHA | C25: CONCEPTO | D25: TOTAL | F25: FECHA | G25: CONCEPTO | H25: TOTAL
B26: 45383 | C26: Saldo Inicial | D26: =H22 -> 100.43 | F26: 45384 | G26: Pago reembolso Ronny Quan USD | H26: 753.91
B27: 45383 | C27: Transf fondos Pago Reembol | D27: 2017.06 | F27: 45384 | G27: Pago reembolso Iván Estuardo Chávez Morales | H27: 1263.15
B28: 45405 | C28: Transf fondos Pago Póliza vida abril | D28: 420.79 | F28: 45405 | G28: Pago Póliza Vida | H28: 519.87
C30: TOTAL INGRESOS ABRIL | D30: =SUM(D26:D29) -> 2538.28 | G30: TOTAL EGRESOS ABRIL | H30: =SUM(H26:H29) -> 2536.93
G31: SALDO DE CAJA ABRIL | H31: =D30-H30 -> 1.35
B34: FECHA | C34: CONCEPTO | D34: TOTAL | F34: FECHA | G34: CONCEPTO | H34: TOTAL
B35: 45413 | C35: Saldo Inicial | D35: =H31 -> 1.35 | F35: 45440 | G35: Pago Póliza Vida | H35: 519.87
B36: 45440 | C36: Transf fondos Pago Póliza vida MAYO | D36: 571.07 | F36: 45441 | G36: Pago reembolso Ronny Quan USD | H36: 1434.21
B37: 45441 | C37: Transf fondos Pago reembolsos mayo | D37: 2600 | F37: 45441 | G37: Pago reembolso Iván Estuardo Chávez Morales | H37: 1088.35
C39: TOTAL INGRESOS MAYO | D39: =SUM(D35:D38) -> 3172.42 | G39: TOTAL EGRESOS MAYO | H39: =SUM(H35:H38) -> 3042.43
G40: SALDO DE CAJA MAYO | H40: =D39-H39 -> 129.99
B45: FECHA | C45: CONCEPTO | D45: TOTAL | F45: FECHA | G45: CONCEPTO | H45: TOTAL
B46: 45444 | C46: Saldo Inicial | D46: =$H$40 -> 129.99 | F46: 45450 | G46: Pago reembolso jerry García USD | H46: =1088.35 -> 1088.35
B47: 45447 | C47: Devolución de Dinero Ivan Estuardo Chavez | D47: 1088.35 | F47: 45457 | G47: Pago reembolso Ronny Quan USD | H47: =1065.86 -> 1065.86
B48: 45449 | C48: Transf pagos facturas enero a may S&P Col | D48: 5280.45 | F48: 45471 | G48: Póliza de vida Ivan Estuardo Chavez Morales | H48: =55.07*$J$46 -> 0
F49: 45471 | G49: Poliza de vida Rony Eduardo Quan Lam | H49: =259.47*$J$46 -> 0
C50: TOTAL INGRESOS JUNIO | D50: =SUM(D46:D49) -> 6498.79 | F50: 45471 | G50: Poliza de vida Jerry García Carillo | H50: =205.33*$J$46 -> 0
G52: TOTAL EGRESOS JUNIO | H52: =SUM(H46:H51) -> 2154.21
G53: SALDO DE CAJA JUNIO | H53: =D50-H52 -> 4344.58
B57: FECHA | C57: CONCEPTO | D57: TOTAL | F57: FECHA | G57: CONCEPTO | H57: TOTAL
B58: 1/07024 | C58: Saldo Inicial | D58: =H53 -> 4344.58 | F58: 45475 | G58: Póliza de vida Ivan Estuardo Chavez Morales-Junio | H58: =55.07 -> 55.07
F59: 45475 | G59: Poliza de vida Rony Eduardo Quan Lam-Junio | H59: =259.47 -> 259.47
F60: 45475 | G60: Poliza de vida Jerry García Carillo-Julio | H60: =205.33 -> 205.33
F61: 45496 | G61: Póliza de vida Ivan Estuardo Chavez Morales-Julio | H61: =55.07 -> 55.07
C62: TOTAL INGRESOS JULIO | D62: =SUM(D58:D61) -> 4344.58 | F62: 45496 | G62: Poliza de vida Rony Eduardo Quan Lam-Julio | H62: =259.47 -> 259.47
F63: 45496 | G63: Poliza de vida Jerry García Carillo-Julio | H63: =205.33 -> 205.33
F64: 45499 | G64: Pago reembolso jerry García USD | H64: =1544.59 -> 1544.59
F65: 45499 | G65: Pago reembolso Ronny Quan USD | H65: =912.34 -> 912.34
G69: TOTAL EGRESOS JULIO | H69: =SUM(H58:H68) -> 3496.67
G70: SALDO DE CAJA JULIO | H70: =D62-H69 -> 847.91
B72: FECHA | C72: CONCEPTO | D72: TOTAL | F72: FECHA | G72: CONCEPTO | H72: TOTAL
B73: 45505 | C73: Saldo Inicial | D73: =H70 -> 847.91 | F73: 45527 | G73: Póliza de vida Ivan Estuardo Chavez Morales-Agosto | H73: =55.07 -> 55.07
B74: 45532 | C74: Transf fondos Pago Reembol | D74: =2000 -> 2000 | F74: 45527 | G74: Poliza de vida Rony Eduardo Quan Lam-Agosto | H74: =259.47 -> 259.47
F75: 45527 | G75: Poliza de vida Jerry García Carillo-Agosto | H75: =205.33 -> 205.33
F76: 45532 | G76: Pago reembolso Ronny Quan USD | H76: =911.26 -> 911.26
C77: TOTAL INGRESOS AGOSTO | D77: =SUM(D73:D76) -> 2847.91
G84: TOTAL EGRESOS AGOSTO | H84: =SUM(H73:H83) -> 1431.13
G85: SALDO DE CAJA AGOSTO | H85: =D77-H84 -> 1416.78
B89: FECHA | C89: CONCEPTO | D89: TOTAL | F89: FECHA | G89: CONCEPTO | H89: TOTAL
B90: 45536 | C90: Saldo Inicial | D90: =H85 -> 1416.78 | F90: 45560 | G90: Póliza de vida Ivan Estuardo Chavez Morales-Septiembre | H90: =55.07 -> 55.07
B91: 45561 | C91: Transf fondos Pago Reembol | D91: =2000 -> 2000 | F91: 45560 | G91: Poliza de vida Rony Eduardo Quan Lam-Septiembre | H91: =259.47 -> 259.47
F92: 45560 | G92: Poliza de vida Jerry García Carillo-Septiembre | H92: =205.33 -> 205.33
F93: 45561 | G93: Pago reembolso Ronny Quan USD | H93: =852.06 -> 852.06
C94: TOTAL INGRESOS SEPTIEMBRE | D94: =SUM(D90:D93) -> 3416.78 | F94: 45562 | G94: Pago reembolso Jerry García USD | H94: =1713.19 -> 1713.19
G101: TOTAL EGRESOS SEPTIEMBRE | H101: =SUM(H90:H100) -> 3085.12
G102: SALDO DE CAJA SEPTIEMBRE | H102: =D94-H101 -> 331.66
B104: FECHA | C104: CONCEPTO | D104: TOTAL | F104: FECHA | G104: CONCEPTO | H104: TOTAL
B105: 45566 | C105: Saldo Inicial | D105: =H102 -> 331.66 | F105: 45582 | G105: Póliza de vida Ivan Estuardo Chavez Morales-Octubre | H105: =55.07 -> 55.07 | J105: 0
B106: 45582 | C106: Transf fondos Pago Reembol y Pólizas | D106: =2000 -> 2000 | F106: 45582 | G106: Poliza de vida Rony Eduardo Quan Lam-octubre | H106: =259.47 -> 259.47
F107: 45582 | G107: Poliza de vida Jerry García Carillo-Octubre | H107: =205.33 -> 205.33
F108: 45593 | G108: Pago reembolso Ronny Quan USD | H108: =695.72 -> 695.72
C109: TOTAL INGRESOS OCTUBRE | D109: =SUM(D105:D108) -> 2331.66 | F109: 45593 | G109: Pago reembolso Jerry García USD | H109: =769.01 -> 769.01
G116: TOTAL EGRESOS OCTUBRE | H116: =SUM(H105:H115) -> 1984.6
G117: SALDO DE CAJA OCTUBRE | H117: =D109-H116 -> 347.06
B120: FECHA | C120: CONCEPTO | D120: TOTAL | F120: FECHA | G120: CONCEPTO | H120: TOTAL
B121: 45597 | C121: Saldo Inicial | D121: =H117 -> 347.06 | F121: 45617 | G121: Póliza de vida Ivan Estuardo Chavez Morales-noviembre | H121: =55.07 -> 55.07
B122: 45617 | C122: Transf fondos Pago Reembol y Pólizas | D122: =4000 -> 4000 | F122: 45617 | G122: Poliza de vida Rony Eduardo Quan Lam-noviembre | H122: =259.47 -> 259.47
F123: 45617 | G123: Poliza de vida Jerry Garcia-noviembre | H123: =205.33 -> 205.33 | J123: 1
F124: 45624 | G124: Pago reembolso Ronny Quan USD | H124: =1020.64 -> 1020.64
C125: TOTAL INGRESOS NOVIEMBRE | D125: =SUM(D121:D124) -> 4347.06
G132: TOTAL EGRESOS NOVIEMBRE | H132: =SUM(H121:H131) -> 1540.51
G133: SALDO DE CAJA NOVIEMBRE | H133: =D125-H132 -> 2806.55
B135: FECHA | C135: CONCEPTO | D135: TOTAL | F135: FECHA | G135: CONCEPTO | H135: TOTAL
B136: 45627 | C136: Saldo Inicial | D136: =H133 -> 2806.55 | F136: 45644 | G136: Póliza de vida Ivan Estuardo Chavez Morales | H136: 55.07
F137: 45644 | G137: Poliza de vida Rony Eduardo Quan Lam | H137: 259.47
F138: 45644 | G138: Poliza de vida Jerry García Carillo | H138: 205.33
C140: TOTAL INGRESOS DICIEMBRE | D140: =SUM(D136:D139) -> 2806.55
G147: TOTAL EGRESOS DICIEMBRE | H147: =SUM(H136:H146) -> 519.87
G148: SALDO DE CAJA DICIEMBRE | H148: =D140-H147 -> 2286.68
B150: FECHA | C150: CONCEPTO | D150: TOTAL | F150: FECHA | G150: CONCEPTO | H150: TOTAL
B151: 45658 | C151: Saldo Inicial | D151: =H148 -> 2286.68 | F151: 45686 | G151: Póliza de vida Ivan Estuardo Chavez Morales-USD-Póliza Vida | H151: 55.07
B152: 45686 | C152: Transf fondos Pago Reembol y Pólizas | D152: 4000 | F152: 45686 | G152: Poliza de vida Rony Eduardo Quan Lam-USD-Póliza Vida | H152: 259.47
F153: 45686 | G153: Poliza de vida Jerry García Carillo -USD-Póliza Vida | H153: 205.33
F154: 45686 | G154: Reembolso Ronny Quan | H154: 4190.95
C155: TOTAL INGRESOS ENERO | D155: =SUM(D151:D154) -> 6286.68 | F155: 45686 | G155: Reembolso Jerry García | H155: 572.81
G159: TOTAL EGRESOS ENERO | H159: =SUM(H151:H158) -> 5283.63
G160: SALDO DE CAJA ENERO | H160: =D155-H159 -> 1003.05
B164: FECHA | C164: CONCEPTO | D164: TOTAL | F164: FECHA | G164: CONCEPTO | H164: TOTAL
B165: 45689 | C165: Saldo Inicial | D165: =$H$160 -> 1003.05 | F165: 45714 | G165: Pago póliza Gastos médicos empleados Guatemala | H165: 519.87
...

Sheet Caja QTQ
B1: LIBRO DE CAJA
B2: SOLUTIONS & PAYROLL, S. A.
B3: SUCURSAL GUATEMALA USD
C4: INGRESOS | G4: EGRESOS
B5: FECHA | C5: CONCEPTO | D5: TOTAL | F5: FECHA | G5: CONCEPTO | H5: TOTAL
B6: 45292 | C6: SALDO INICIAL | D6: 20477.39 | F6: 45296 | G6: Emisión estados de cuenta | H6: 15
B7: 45303 | C7: Marta Xicay -GFC-202401 | D7: 18270.77 | F7: 45296 | G7: Emisión estados de cuenta | H7: 15
B8: 45322 | C8: Ivan Ch-Jerry G-Ronny Q-Energyzer 202401 | D8: 277361.37 | F8: 45296 | G8: Emisión estados de cuenta | H8: 15
F9: 45307 | G9: pago ISR asalariados 2023 | H9: 1892.89
F10: 45308 | G10: Pago planilla igss dic 2023 | H10: 3159.63
F11: 45320 | G11: Pago salario marta xicay en 2024 | H11: 17507.04
F12: 45321 | G12: Compra $. 1,039.74 traslado cta dolares | H12: 8236.8
F13: 45321 | G13: Pago seguro mes enero y febrero 2024 | H13: 1791.8
C16: TOTAL INGRESOS ENERO | D16: =SUM(D6:D15) -> 316109.53 | G16: TOTAL EGRESOS ENERO | H16: =SUM(H6:H15) -> 32633.16
G17: SALDO DE CAJA ENERO | H17: =(D16-H16) -> 283476.37
B19: FECHA | C19: CONCEPTO | D19: TOTAL | F19: FECHA | G19: CONCEPTO | H19: TOTAL
B20: 45323 | C20: Saldo Inicial | D20: =H17 -> 283476.37 | F20: 45323 | G20: Jerry Garcia Carrillo Enero 2024 | H20: 69020.57
B21: 45334 | C21: ACH City Bank Penny Test (SG) | D21: 25 | F21: 45323 | G21: Ronny Eduardo Quan Lam Enero 24 | H21: 80877.89
B22: 45335 | C22: Marta Xicay -GFC-202401 | D22: 22574.81 | F22: 45323 | G22: Ivan Eduardo Chavez Morales En 2024 | H22: 39790.21
F23: 45323 | G23: Reembolso Ronny Quan | H23: 5386.76
F24: 45323 | G24: Reembolso Ronny Quan | H24: 6507.47
F25: 45336 | G25: Declaraguate ISR Asalariados Enero 2024 | H25: 12314.65
F26: 45341 | G26: Pago planilla IGSS Mes enero 2024 | H26: 30448.42
F27: 45349 | G27: Traslado cuenta dolares pago PANAMERICAN LIFE | H27: 3952.94
F28: 45349 | G28: Pago Seguro salud Marzo 2024 | H28: 1792.2
F29: 45351 | G29: Pago Salario Marta Xicay Feb 2024 | H29: 17507.04
C30: TOTAL INGRESOS FEBRERO | D30: =SUM(D20:D29) -> 306076.18 | G30: TOTAL EGRESOS FEBRERO | H30: =SUM(H20:H29) -> 267598.15
G31: SALDO DE CAJA FEBRERO | H31: =D30-H30 -> 38478.03
B33: FECHA | C33: CONCEPTO | D33: TOTAL | F33: FECHA | G33: CONCEPTO | H33: TOTAL
B34: 45352 | C34: Saldo Inicial | D34: =H31 -> 38478.03 | F34: 45352 | G34: Jerry Garcia Carrillo Febrero 2024 | H34: 54332.57
B35: 45352 | C35: Ivan Ch-Jerry G-Ronny Q-Energyzer 202401 | D35: 225566.58 | F35: 45352 | G35: Ronny Eduardo Quan Lam Febrero 24 | H35: 66189.9
B36: 45362 | C36: Client:Global For Children-Marta Xicay 202402-Termination | D36: 17468.75 | F36: 45352 | G36: Ivan Eduardo Chavez Morales febrero 2024 | H36: 24970.21
B37: 45366 | C37: Client:Kairos-Ivan Chavez-Ruth Carolina Vasquez 202403 | D37: 7172.5 | F37: 45355 | G37: Reembolso Gtos Ivan chavez enero 2024 | H37: 4381.18
B38: 45371 | C38: Client:Energyzer-Ivan Chavez-Jerry García-Ronny Quan 202403 | D38: 288267.58 | F38: 45357 | G38: Servicios honorarios Juan Santiago enero | H38: 945
B39: 45377 | C39: Client: Czarnikow- Sthepanie Rodriguez Lopez 202403 | D39: 77876.16 | F39: 45358 | G39: Reembolso Ronny Quan Marzo | H39: 1868.42
F40: 45358 | G40: Traslado cuenta dolares pago Reembolso Ronny Quan | H40: 7910
F41: 45364 | G41: Declaraguate ISR Asalariados Febrero 2024 | H41: 9710.64
C42: TOTAL INGRESOS MARZO | D42: =SUM(D34:D41) -> 654829.6 | F42: 45366 | G42: Liquidación Marta Xicay | H42: =16550.42 -> 16550.42
F43: 45369 | G43: Cobro emisión estado cuenta | H43: 15
F44: 45369 | G44: Cobro emisión estado cuenta | H44: 15
F45: 45370 | G45: ISR Contribuyentes no residentes | H45: 2086.88
F46: 45372 | G46: Compra celular personal Energyzer | H46: =22996 -> 22996
F47: 45372 | G47: Póliza 567000000001073 | Ivan Estuardo Chavez Morales | H47: =888.15 -> 888.15
F48: 45372 | G48: Póliza 567000000001074 | Rony Eduardo Quan Lam | H48: =903.72 -> 903.72
F49: 45378 | G49: Jerry Garcia Carrillo Marzo 2024 | H49: 64225.96
F50: 45378 | G50: Ronny Eduardo Quan Lam Marzo 24 | H50: 104766.97
F51: 45378 | G51: Ivan Eduardo Chavez Morales Marzo 2024 | H51: 24970.21
F52: 45378 | G52: Edlin Ivette Ramos Poitan | H52: 9364.49
F53: 45378 | G53: Ruth Carolina Vasquez Avelar | H53: 5732.9
G54: TOTAL EGRESOS MARZO | H54: =SUM(H34:H53) -> 422823.62
G55: SALDO DE CAJA MARZO | H55: =D42-H54 -> 232005.98
B57: FECHA | C57: CONCEPTO | D57: TOTAL | F57: FECHA | G57: CONCEPTO | H57: TOTAL
B58: 45383 | C58: Saldo Inicial | D58: =H55 -> 232005.98 | F58: 45383 | G58: Stephanie Rodriguez Lopez Marzo 2024 | H58: =66373.88 -> 66373.88
B59: 45383 | C59: Client: Opportunity-Edlin Ivette Poitan 202403 | D59: 11926.09 | F59: 45384 | G59: Transferencia de fondos para pago reembolsos Ronny Quan e Ivan Chavez mes marzo | H59: 15934.78
B60: 45393 | C60: Client:KairosRuth Carolina Vasquez 202404 | D60: 7182.2 | F60: 45392 | G60: Pago planilla IGSS Mes febrero 2024 y mora | H60: 30680.39
B61: 45397 | C61: Client: Opportunity-Edlin Ivette Poitan 202404 | D61: 13290.7 | F61: 45392 | G61: Pago Servicios profesionales Juan-Servicios prestados- Feb Marzo | H61: 1783
B62: 45405 | C62: Client: Czarnikow- Sthepanie Rodriguez Lopez 202403 | D62: 46356.3 | F62: 45393 | G62: Pago arnoldo Gestión de representación legal 2024­-2027 | H62: 1700
B63: 45405 | C63: Client:Energyzer-Ivan Chavez-Jerry García-Ronny Quan 202404 | D63: 371170.87 | F63: 45394 | G63: Declaraguate ISR Asalariados Marzo 2024 | H63: 17191.61
F64: 45394 | G64: ISR en concepto de la factura 4700 | H64: 1178.23
F65: 45397 | G65: Pago saldo factura Juan y envios | H65: =90+125 -> 215
C66: TOTAL INGRESOS ABRIL | D66: =SUM(D58:D65) -> 681932.14 | F66: 45397 | G66: Pago planilla IGSS Mes marzo 2024 | H66: 45016.17
F67: 45405 | G67: Polizas salud Abril Ivan Estuardo Chavez-Ronny Quan | H67: 1791.87
F68: 45405 | G68: Pago prima inicial Póliza Salud Guatemala QTZ Abril-Jerry García | H68: 914.3
F69: 45405 | G69: Traslado cuenta dolares pago Póliza vida abril | H69: 3320
F70: 45406 | G70: Declaraguate Impuesto de Solidaridad (ISO)Ene-Marzo | H70: 558.38
F71: 45408 | G71: Jerry Garcia Carrillo Abril 2024 | H71: 79101.47
F72: 45408 | G72: Ronny Eduardo Quan Lam Abril 24 | H72: 105311.95
F73: 45408 | G73: Ivan Eduardo Chavez Morales Abril 2024 | H73: 24970.21
F74: 45408 | G74: Edlin Ivette Ramos Poitan Abril 2024 | H74: 10382.76
F75: 45408 | G75: Ruth Carolina Vasquez Avelar Abril 2024 | H75: 5732.9
F76: 45408 | G76: Stephanie Rodriguez Lopez abril 2024 | H76: 28242.02
F77: 45411 | G77: Pago reembolso Ivan Estuardo Chavez Energizer | H77: 3707
F78: 45411 | G78: Pago reembolso Jerry García Energizer | H78: 56936.08
F79: 45411 | G79: Pago reembolso Ronny Eduardo Quan Energizer | H79: 12012.85
G82: TOTAL EGRESOS ABRIL | H82: =SUM(H58:H81) -> 513054.85
G83: SALDO DE CAJA ABRIL | H83: =D66-H82 -> 168877.29
B85: FECHA | C85: CONCEPTO | D85: TOTAL | F85: FECHA | G85: CONCEPTO | H85: TOTAL
B86: 45413 | C86: Saldo Inicial | D86: =H83 -> 168877.29 | F86: 45420 | G86: Pago Servicios profesionales Juan-Servicios prestados- Abril | H86: 840
B87: 45425 | C87: Client:KairosRuth Carolina Vasquez y Opportunity-Edlin Ivette Poitan 202405 | D87: 20483.74 | F87: 45426 | G87: Pago planilla IGSS Mes Abril | H87: 48442.26
B88: 45428 | C88: Client:Energyzer-Ivan Chavez-Jerry García-Ronny Quan 202405 | D88: 269107.6 | F88: 45426 | G88: Declaraguate ISR Asalariados Abril 2024 | H88: 15808.3
B89: 45440 | C89: Client: Czarnikow- Sthepanie Rodriguez Lopez 202405 | D89: 41146.97 | F89: 45426 | G89: ISR en concepto de la factura 4776 | H89: 1771.69
F90: 45428 | G90: Pago Servicios profesionales Arnoldo perez-Servicios prestados-Enero a abril | H90: =1200*4 -> 4800
F91: 45440 | G91: Jerry Garcia Carrillo Mayo 2024 | H91: 54108.45
F92: 45440 | G92: Ronny Eduardo Quan Lam Mayo 24 | H92: 84606.11
F93: 45440 | G93: Ivan Eduardo Chavez Morales Mayo 2024 | H93: 24970.21
C94: TOTAL INGRESOS MAYO | D94: =SUM(D86:D93) -> 499615.6 | F94: 45440 | G94: Edlin Ivette Ramos Poitan Mayo 2024 | H94: 10382.76
F95: 45440 | G95: Ruth Carolina Vasquez Avelar Abril 2024 | H95: 5732.9
F96: 45440 | G96: Stephanie Rodriguez Lopez mayo 2024 | H96: =28242.02 -> 28242.02
F97: 45440 | G97: Polizas GM Mayo Ivan Estuardo Chavez-Ronny Quan | H97: =1791.87 -> 1791.87
F98: 45440 | G98: Traslado cuenta dolares pago Póliza vida Mayo | H98: 4500
F99: 45441 | G99: Polizas GM Mayo Jerry Garcia | H99: 1828.6
F100: 45441 | G100: Traslado cuenta dolares pago reembolsos mayo | H100: 20488 | I100: 7.88
F101: 45441 | G101: Pago reembolso Ivan Estuardo Chavez Energizer | H101: 2376.61
F102: 45441 | G102: Pago reembolso Jerry García Energizer | H102: 3960.32
F103: 45441 | G103: Pago reembolso Ronny Eduardo Quan Energizer | H103: 7782.15
G110: TOTAL EGRESOS MAYO | H110: =SUM(H86:H109) -> 322432.25
G111: SALDO DE CAJA MAYO | H111: =D94-H110 -> 177183.35
B114: FECHA | C114: CONCEPTO | D114: TOTAL | F114: FECHA | G114: CONCEPTO | H114: TOTAL
B115: 45444 | C115: Saldo Inicial | D115: =H111 -> 177183.35 | F115: 45449 | G115: Transf a USD reembolsos junio | H115: 41609.94
B116: 45455 | C116: Client:Kairos Ruth Carolina Vasquez y Opportunity-Edlin Ivette Poitan 202406 | D116: 9387.8072 | F116: 45450 | G116: Pago Servicios profesionales Juan-Servicios prestados- Mayo | H116: =840 -> 840 | J116: 0
...

Sheet Flujo Caja Noviembre 2025
D1: 42400
D4: Fecha de Elaboración: | E4: 45962
C6: Tasa de cambio: | D6: 7.46
D7: NOVIEMBRE
D8: VALOR QTQ | E8: VALOR USD
C9: BANCOS | D9: =SUBTOTAL(9,D10:D11) -> 461596.24 | E9: =SUBTOTAL(9,E10:E11) -> 61876.171
C10: Bancos QTQ | D10: ='Caja QTQ'!$J$822+31241.13 -> 447415.67 | E10: =D10/$D$6 -> 59975.291
C11: Bancos USD | D11: =E11*D6 -> 14180.565 | E11: ='Caja USD'!$H$260 -> 1900.88
C12: CLIENTES | D12: =SUBTOTAL(9,D13:D29) -> 1519234.7 | E12: =SUBTOTAL(9,E13:E29) -> 199963.21
B13: Pagado | C13: Client: NotableGrowth, Inc-Remotefist | D13: ='Diferencia en cambio'!I187 -> 50408.41 | E13: =D13/'Diferencia en cambio'!$L$187 -> 6633.77 | G13: 232387.56 | J13: =G13/$D$6 -> 31151.147
B14: Pagado | C14: Client: Bilingual Bridges, Inc-Remotefist | D14: ='Diferencia en cambio'!I188 -> 12594.789 | E14: =D14/'Diferencia en cambio'!$L$188 -> 1657.48 | G14: 59616.41 | J14: =G14/$D$6 -> 7991.4759
B15: Pagado | C15: Client: :Iberia Foods LLC -Remotefist | D15: ='Diferencia en cambio'!I189 -> 28246.938 | E15: =D15/'Diferencia en cambio'!$L$189 -> 3717.31
B16: Pagado | C16: Client: Vinmar International,-Liza Marlene Torres valdes 202508-Remofirst | D16: ='Diferencia en cambio'!I190 -> 20247.953 | E16: =D16/'Diferencia en cambio'!$L$190 -> 2664.64
B17: Pagado | C17: Client: Czarnikow- Sthepanie Rodriguez Lopez-Remotefist | D17: ='Diferencia en cambio'!I191 -> 18416.425 | E17: =D17/'Diferencia en cambio'!L191 -> 2423.61
B18: Pagado | C18: Client: Soul Innovations-Remotefist | D18: ='Diferencia en cambio'!I192 -> 102473.05 | E18: =D18/'Diferencia en cambio'!$L$192 -> 13485.5
B19: Pagado | C19: Client:Energyzer-Safeguard | D19: ='Diferencia en cambio'!I193 -> 425268.22 | E19: =$D$19/'Diferencia en cambio'!$L$193 -> 55740.43
B20: Pagado | C20: Client:Kairos- Safeguard | D20: ='Diferencia en cambio'!$I$194 -> 23739.41 | E20: =D20/'Diferencia en cambio'!$L$194 -> 3174.48
B21: Pagado | C21: Client: Opportunity-Safeguard | D21: ='Diferencia en cambio'!I195 -> 42797.111 | E21: =D21/'Diferencia en cambio'!$L$195 -> 5609.47
B22: Pagado | C22: Client: Panthera, Inc-Safeguard | D22: ='Diferencia en cambio'!I196 -> 33691.756 | E22: =D22/'Diferencia en cambio'!$L$196 -> 4416.02
B23: Pagado | C23: Client: :Careercircle, LLC-Safeguard | D23: ='Diferencia en cambio'!I197 -> 69708.449 | E23: =D23/'Diferencia en cambio'!$L$197 -> 9219.28
B24: Pagado | C24: Client: :Highspring, LLC-Safeguard | D24: ='Diferencia en cambio'!I198 -> 17297.159 | E24: =D24/'Diferencia en cambio'!$L$198 -> 2267.16
B25: Pagado | C25: Client: :Archewll, LLC-Safeguard | D25: ='Diferencia en cambio'!I199 -> 143579.24 | E25: =D25/'Diferencia en cambio'!$L$199 -> 18989.05
B26: Pagado | C26: Client:Global Expansion | D26: ='Diferencia en cambio'!I186 -> 121412.13 | E26: =D26/'Diferencia en cambio'!L186 -> 15938.35
B27: Pagado | C27: Client: Safeguard expenses | D27: ='Diferencia en cambio'!I185 -> 38638.95 | E27: =D27/'Diferencia en cambio'!L185 -> 5150
B28: Pagado | C28: Client: Safeguard Nomina directa | D28: ='Diferencia en cambio'!I200 -> 311098.25 | E28: =D28/'Diferencia en cambio'!L200 -> 40885.18
B29: Pagado | C29: Client: Safeguard Nomina directa-Valor duplicado | D29: 59616.45 | E29: =D29/D6 -> 7991.4812
C30: TOTAL INGRESOS | D30: =SUBTOTAL(9,D9:D29) -> 1980830.9 | E30: =SUBTOTAL(9,E9:E29) -> 261839.38
B33: CUENTAS X PAGAR MES | D33: NOVIEMBRE
B34: Factura | C34: PROVEEDOR | D34: VALOR QTQ | E34: VALOR USD | F34: Fecha vencimiento | G34: Estado | J34: KPI
C35: SEGURIDAD IGSS | D35: =SUBTOTAL(9,D36:D36) -> 119631.47 | E35: =SUBTOTAL(9,E36:E36) -> 16036.39
B36: 5794688 | C36: Pago planilla IGSS Octubre | D36: 119631.47 | E36: =D36/$D$6 -> 16036.39 | F36: 45975 | G36: Cancelado | H36: =IF(OR(G36="Sin pagar",G36="Pagar"),NETWORKDAYS($E$4,F36,'Festivos Guatemala'!$A$3:$A$15),0) -> 0 | I36: =NETWORKDAYS($E$4,F36,'Festivos Guatemala'!$A$3:$A$15) -> 10 | J36: =H36 -> 0
C37: IMPUESTOS | D37: =SUBTOTAL(9,D38:D40) -> 29911.35 | E37: =SUBTOTAL(9,E38:E40) -> 4009.5643 | J37: =H37 -> 0
B38: 49088379970 | C38: Declaraguate ISR Septiembre | D38: 25414.84 | E38: =D38/$D$6 -> 3406.815 | F38: 45975 | G38: Cancelado | H38: =IF(OR(G38="Sin pagar",G38="Pagar"),NETWORKDAYS($E$4,F38,'Festivos Guatemala'!$A$3:$A$15),0) -> 0 | I38: =NETWORKDAYS($E$4,F38,'Festivos Guatemala'!$A$3:$A$15) -> 10 | J38: =H38 -> 0
B39: 49088577105 | C39: Declaraguate ISR no residentes facturación Col Factura 601 Octubre (15%) | D39: 3462.99 | E39: =D39/$D$6 -> 464.20777 | F39: 45975 | G39: Cancelado | H39: =IF(OR(G39="Sin pagar",G39="Pagar"),NETWORKDAYS($E$4,F39,'Festivos Guatemala'!$A$3:$A$15),0) -> 0 | I39: =NETWORKDAYS($E$4,F39,'Festivos Guatemala'!$A$3:$A$15) -> 10 | J39: =H39 -> 0
B40: 4904205174 | C40: Declaraguate ISR No Residentes / Grupo CGR Lawyer | D40: 1033.52 | E40: =D40/$D$6 -> 138.54155 | F40: 45975 | G40: Cancelado | H40: =IF(OR(G40="Sin pagar",G40="Pagar"),NETWORKDAYS($E$4,F40,'Festivos Guatemala'!$A$3:$A$15),0) -> 0 | I40: =NETWORKDAYS($E$4,F40,'Festivos Guatemala'!$A$3:$A$15) -> 10 | J40: =H40 -> 0
C41: SERVICIOS PROFESIONALES -REPRESENTACIÓN LEGAL -GASTOS DE OFICINA | D41: =SUBTOTAL(9,D42:D46) -> 17617.89 | E41: =SUBTOTAL(9,E42:E46) -> 2361.6475 | J41: =H41 -> 0
B42: E320000000007 | C42: Servicio de representación, diligencia de alta TSS y ministerio Grupo CGR Lawyer | D42: =$E$42*$D$6 -> 10071 | E42: 1350 | F42: 45968 | G42: Cancelado | H42: =IF(OR(G42="Sin pagar",G42="Pagar"),NETWORKDAYS($E$4,F42,'Festivos Guatemala'!$A$3:$A$15),0) -> 0 | I42: =NETWORKDAYS($E$4,F42,'Festivos Guatemala'!$A$3:$A$15) -> 5 | J42: =H42 -> 0
B43: 752578 | C43: Inbers contadores Servicios contables con entrega de información financiera correspondiente al periodo de octubre 2025 | D43: =4673.2 -> 4673.2 | E43: =D43/$D$6 -> 626.43432 | F43: 45982 | G43: Cancelado | H43: =IF(OR(G43="Sin pagar",G43="Pagar"),NETWORKDAYS($E$4,F43,'Festivos Guatemala'!$A$3:$A$15),0) -> 0 | I43: =NETWORKDAYS($E$4,F43,'Festivos Guatemala'!$A$3:$A$15) -> 15 | J43: =H43 -> 0
B44: 2888256700 | C44: Servicios prestados por representación entidad Global Guatemala Nov. 2025 | D44: 1368.42 | E44: =D44/$D$6 -> 183.43432 | F44: 45982 | G44: Cancelado | H44: =IF(OR(G44="Sin pagar",G44="Pagar"),NETWORKDAYS($E$4,F44,'Festivos Guatemala'!$A$3:$A$15),0) -> 0 | I44: =NETWORKDAYS($E$4,F44,'Festivos Guatemala'!$A$3:$A$15) -> 15 | J44: =H44 -> 0
B45: 1089948594 | C45: Servicios prestados de representación mes de Octubre de 2025 | D45: 926.32 | E45: =D45/$D$6 -> 124.17158 | F45: 45982 | G45: Cancelado | H45: =IF(OR(G45="Sin pagar",G45="Pagar"),NETWORKDAYS($E$4,F45,'Festivos Guatemala'!$A$3:$A$15),0) -> 0 | I45: =NETWORKDAYS($E$4,F45,'Festivos Guatemala'!$A$3:$A$15) -> 15 | J45: =H45 -> 0
B46: 363809461 | C46: Gastos mes de Octubre S&P de 2025 | D46: 578.95 | E46: =D46/$D$6 -> 77.607239 | F46: 45982 | G46: Cancelado | H46: =IF(OR(G46="Sin pagar",G46="Pagar"),NETWORKDAYS($E$4,F46,'Festivos Guatemala'!$A$3:$A$15),0) -> 0 | I46: =NETWORKDAYS($E$4,F46,'Festivos Guatemala'!$A$3:$A$15) -> 15 | J46: =H46 -> 0
C47: PÓLIZAS Y SEGUROS | D47: =SUBTOTAL(9,D48:D55) -> 10192.01 | E47: =SUBTOTAL(9,E48:E55) -> 1366.2212 | F47: ,
B48: Ok | C48: Póliza de vida Ivan Estuardo Chavez Morales-USD-Póliza Vida | D48: =E48*$D$6 -> 410.8222 | E48: 55.07 | F48: 45982 | G48: Cancelado | H48: =IF(OR(G48="Sin pagar",G48="Pagar"),NETWORKDAYS($E$4,F48,'Festivos Guatemala'!$A$3:$A$15),0) -> 0 | I48: =NETWORKDAYS($E$4,F48,'Festivos Guatemala'!$A$3:$A$15) -> 15 | J48: =H48 -> 0
B49: OK | C49: Poliza de vida Rony Eduardo Quan Lam-USD-Póliza Vida | D49: =E49*$D$6 -> 1935.6462 | E49: 259.47 | F49: 45982 | G49: Cancelado | H49: =IF(OR(G49="Sin pagar",G49="Pagar"),NETWORKDAYS($E$4,F49,'Festivos Guatemala'!$A$3:$A$15),0) -> 0 | I49: =NETWORKDAYS($E$4,F49,'Festivos Guatemala'!$A$3:$A$15) -> 15 | J49: =H49 -> 0
B50: OK | C50: Poliza de vida Jerry García Carillo -USD-Póliza Vida | D50: =E50*$D$6 -> 1531.7618 | E50: 205.33 | F50: 45982 | G50: Cancelado | H50: =IF(OR(G50="Sin pagar",G50="Pagar"),NETWORKDAYS($E$4,F50,'Festivos Guatemala'!$A$3:$A$15),0) -> 0 | I50: =NETWORKDAYS($E$4,F50,'Festivos Guatemala'!$A$3:$A$15) -> 15 | J50: =H50 -> 0
B51: OK | C51: Póliza de salud Hector Augusto Castillo Luna-QTQ-GM-Inclusión | D51: 722.42 | E51: =D51/$D$6 -> 96.839142 | F51: 45982 | G51: Cancelado | H51: =IF(OR(G51="Sin pagar",G51="Pagar"),NETWORKDAYS($E$4,F51,'Festivos Guatemala'!$A$3:$A$15),0) -> 0 | I51: =NETWORKDAYS($E$4,F51,'Festivos Guatemala'!$A$3:$A$15) -> 15 | J51: =H51 -> 0
B52: OK | C52: Póliza de salud Miriam Lucia Morfin González-QTQ-GM | D52: 861.81 | E52: =D52/$D$6 -> 115.52413 | F52: 45982 | G52: Cancelado | H52: =IF(OR(G52="Sin pagar",G52="Pagar"),NETWORKDAYS($E$4,F52,'Festivos Guatemala'!$A$3:$A$15),0) -> 0 | I52: =NETWORKDAYS($E$4,F52,'Festivos Guatemala'!$A$3:$A$15) -> 15 | J52: =H52 -> 0
B53: OK | C53: Póliza de salud Ivan Estuardo Chavez Morales-QTQ-GM | D53: 1704.44 | E53: =D53/$D$6 -> 228.47721 | F53: 45982 | G53: Cancelado | H53: =IF(OR(G53="Sin pagar",G53="Pagar"),NETWORKDAYS($E$4,F53,'Festivos Guatemala'!$A$3:$A$15),0) -> 0 | I53: =NETWORKDAYS($E$4,F53,'Festivos Guatemala'!$A$3:$A$15) -> 15 | J53: =H53 -> 0
B54: OK | C54: Poliza de salud Rony Eduardo Quan Lam-QTQ-GM | D54: 1023.02 | E54: =D54/$D$6 -> 137.13405 | F54: 45982 | G54: Cancelado | H54: =IF(OR(G54="Sin pagar",G54="Pagar"),NETWORKDAYS($E$4,F54,'Festivos Guatemala'!$A$3:$A$15),0) -> 0 | I54: =NETWORKDAYS($E$4,F54,'Festivos Guatemala'!$A$3:$A$15) -> 15 | J54: =H54 -> 0
B55: OK | C55: Poliza de salud Jerry García Carillo -QTQ-GM-Claudia Marisol Mayorga Ayala | D55: 2002.09 | E55: =D55/$D$6 -> 268.37668 | F55: 45982 | G55: Cancelado | H55: =IF(OR(G55="Sin pagar",G55="Pagar"),NETWORKDAYS($E$4,F55,'Festivos Guatemala'!$A$3:$A$15),0) -> 0 | I55: =NETWORKDAYS($E$4,F55,'Festivos Guatemala'!$A$3:$A$15) -> 15 | J55: =H55 -> 0
C56: COBROS ENTRE SUCURSALES | D56: =SUBTOTAL(9,D57:D57) -> 0 | E56: =SUBTOTAL(9,E57:E57) -> 0
B57: 0 | D57: =E57*7.8 -> 0 | E57: 0 | F57: 45991 | G57: Cancelado | H57: =IF(OR(G57="Sin pagar",G57="Pagar"),NETWORKDAYS($E$4,F57,'Festivos Guatemala'!$A$3:$A$15),0) -> 0 | I57: =NETWORKDAYS($E$4,F57,'Festivos Guatemala'!$A$3:$A$15) -> 20 | J57: =H57 -> 0
C58: TIQUETES AÉREOS , HOTELES | D58: =SUBTOTAL(9,D59:D59) -> 0 | E58: =SUBTOTAL(9,E59:E59) -> 0
F59: 45991 | G59: Cancelado | H59: =IF(OR(G59="Sin pagar",G59="Pagar"),NETWORKDAYS($E$4,F59,'Festivos Guatemala'!$A$3:$A$15),0) -> 0 | I59: =NETWORKDAYS($E$4,F59,'Festivos Guatemala'!$A$3:$A$15) -> 20 | J59: =H59 -> 0
C60: COSTOS FINANCIEROS | D60: =SUBTOTAL(9,D61:D62) -> 298.4 | E60: =SUBTOTAL(9,E61:E62) -> 40
C61: Gastos financieros por envio de recursos pago factura CGR Lawyer dominicana | D61: =E61*$D$6 -> 298.4 | E61: 40 | F61: 45968 | G61: Cancelado | H61: =IF(OR(G61="Sin pagar",G61="Pagar"),NETWORKDAYS($E$4,F61,'Festivos Guatemala'!$A$3:$A$15),0) -> 0 | I61: =NETWORKDAYS($E$4,F61,'Festivos Guatemala'!$A$3:$A$15) -> 5 | J61: =H61 -> 0
C62: Cobro emisión estado cuenta | D62: =E62*D6 -> 0 | E62: =40*0 -> 0 | F62: 45991 | G62: Cancelado | H62: =IF(OR(G62="Sin pagar",G62="Pagar"),NETWORKDAYS($E$4,F62,'Festivos Guatemala'!$A$3:$A$15),0) -> 0 | I62: =NETWORKDAYS($E$4,F62,'Festivos Guatemala'!$A$3:$A$15) -> 20 | J62: =H62 -> 0
C63: NÓMINAS | D63: =SUBTOTAL(9,D64:D85) -> 1005209.7 | E63: =SUBTOTAL(9,E64:E85) -> 134746.6
B64: America Ctral | C64: Hector Augusto Castillo Luna-Iberia-CC013 | D64: 29589.9 | E64: =D64/$D$6 -> 3966.4745 | F64: 45988 | G64: Cancelado | H64: =IF(OR(G64="Sin pagar",G64="Pagar"),NETWORKDAYS($E$4,F64,'Festivos Guatemala'!$A$3:$A$15),0) -> 0 | I64: =NETWORKDAYS($E$4,F64,'Festivos Guatemala'!$A$3:$A$15) -> 19 | J64: =H64 -> 0
B65: America Ctral | C65: Victor Jose Moscoso Portillo -Global Expansion-CC015 | D65: 76403.6 | E65: =D65/$D$6 -> 10241.769 | F65: 45988 | G65: Cancelado | H65: =IF(OR(G65="Sin pagar",G65="Pagar"),NETWORKDAYS($E$4,F65,'Festivos Guatemala'!$A$3:$A$15),0) -> 0 | I65: =NETWORKDAYS($E$4,F65,'Festivos Guatemala'!$A$3:$A$15) -> 19 | J65: =H65 -> 0
B66: America Ctral | C66: Stephanie Rodriguez Lopez-RF-Czarnikow-CC002 | D66: 56575.92 | E66: =D66/$D$6 -> 7583.9035 | F66: 45988 | G66: Cancelado | H66: =IF(OR(G66="Sin pagar",G66="Pagar"),NETWORKDAYS($E$4,F66,'Festivos Guatemala'!$A$3:$A$15),0) -> 0 | I66: =NETWORKDAYS($E$4,F66,'Festivos Guatemala'!$A$3:$A$15) -> 19 | J66: =H66 -> 0
B67: America Ctral | C67: Carlos Alejandro Montiel Lorenzana-Archell -CC014 | D67: 24838.23 | E67: =D67/$D$6 -> 3329.5214 | F67: 45988 | G67: Cancelado | H67: =IF(OR(G67="Sin pagar",G67="Pagar"),NETWORKDAYS($E$4,F67,'Festivos Guatemala'!$A$3:$A$15),0) -> 0 | I67: =NETWORKDAYS($E$4,F67,'Festivos Guatemala'!$A$3:$A$15) -> 19 | J67: =H67 -> 0
B68: G&T Cont | C68: Liza Marlene Torres Valdes -Vinmar international -CC016 | D68: 19172.23 | E68: =D68/$D$6 -> 2570.004 | F68: 45988 | G68: Cancelado | H68: =IF(OR(G68="Sin pagar",G68="Pagar"),NETWORKDAYS($E$4,F68,'Festivos Guatemala'!$A$3:$A$15),0) -> 0 | I68: =NETWORKDAYS($E$4,F68,'Festivos Guatemala'!$A$3:$A$15) -> 19 | J68: =H68 -> 0
B69: G&T Cont | C69: Douglas Miguel Villa Fuerte Leiva -Archell -CC014 | D69: 12965.13 | E69: =D69/$D$6 -> 1737.9531 | F69: 45988 | G69: Cancelado | H69: =IF(OR(G69="Sin pagar",G69="Pagar"),NETWORKDAYS($E$4,F69,'Festivos Guatemala'!$A$3:$A$15),0) -> 0 | I69: =NETWORKDAYS($E$4,F69,'Festivos Guatemala'!$A$3:$A$15) -> 19 | J69: =H69 -> 0
B70: G&T Cont | C70: Michael scott Edgar -Basis Global Technologies -CC011 | D70: 57055.09 | E70: =D70/$D$6 -> 7648.1354 | F70: 45988 | G70: Cancelado | H70: =IF(OR(G70="Sin pagar",G70="Pagar"),NETWORKDAYS($E$4,F70,'Festivos Guatemala'!$A$3:$A$15),0) -> 0 | I70: =NETWORKDAYS($E$4,F70,'Festivos Guatemala'!$A$3:$A$15) -> 19 | J70: =H70 -> 0
B71: G&T Cont | C71: Javier Ricardo Martinez Cruz-Suol Innovations Ltd (RF) | D71: 73689.47 | E71: =D71/$D$6 -> 9877.945 | F71: 45988 | G71: Cancelado | H71: =IF(OR(G71="Sin pagar",G71="Pagar"),NETWORKDAYS($E$4,F71,'Festivos Guatemala'!$A$3:$A$15),0) -> 0 | I71: =NETWORKDAYS($E$4,F71,'Festivos Guatemala'!$A$3:$A$15) -> 19 | J71: =H71 -> 0
B72: Rural | C72: Joshua Esteban Lopez Fernandez -Highspring-CC017 | D72: 14130.71 | E72: =D72/$D$6 -> 1894.1971 | F72: 45988 | G72: Cancelado | H72: =IF(OR(G72="Sin pagar",G72="Pagar"),NETWORKDAYS($E$4,F72,'Festivos Guatemala'!$A$3:$A$15),0) -> 0 | I72: =NETWORKDAYS($E$4,F72,'Festivos Guatemala'!$A$3:$A$15) -> 19 | J72: =H72 -> 0
B73: International | C73: María Fernanda Robles Solis -Oportunity-CC006 | D73: 14162.36 | E73: =D73/$D$6 -> 1898.4397 | F73: 45988 | G73: Cancelado | H73: =IF(OR(G73="Sin pagar",G73="Pagar"),NETWORKDAYS($E$4,F73,'Festivos Guatemala'!$A$3:$A$15),0) -> 0 | I73: =NETWORKDAYS($E$4,F73,'Festivos Guatemala'!$A$3:$A$15) -> 19 | J73: =H73 -> 0
B74: Bibank | C74: Jerry García-Energyzer-CC004 | D74: 133147 | E74: =D74/$D$6 -> 17848.123 | F74: 45988 | G74: Cancelado | H74: =IF(OR(G74="Sin pagar",G74="Pagar"),NETWORKDAYS($E$4,F74,'Festivos Guatemala'!$A$3:$A$15),0) -> 0 | I74: =NETWORKDAYS($E$4,F74,'Festivos Guatemala'!$A$3:$A$15) -> 19 | J74: =H74 -> 0
B75: Bibank | C75: Edlin Ivette Ramos Poitan-Opportunnity-CC006 | D75: 21769 | E75: =D75/$D$6 -> 2918.0965 | F75: 45988 | G75: Cancelado | H75: =IF(OR(G75="Sin pagar",G75="Pagar"),NETWORKDAYS($E$4,F75,'Festivos Guatemala'!$A$3:$A$15),0) -> 0 | I75: =NETWORKDAYS($E$4,F75,'Festivos Guatemala'!$A$3:$A$15) -> 19 | J75: =H75 -> 0
... B85: Bibank | C85: Miriam Lucia Morfin Gonzalez RF-Notable Growth INC-CC007 | D85: 68891.81 | E85: =D85/$D$6 -> 9234.8271 | F85: 45988 | G85: Cancelado | H85: =IF(OR(G85="Sin pagar",G85="Pagar"),NETWORKDAYS($E$4,F85,'Festivos Guatemala'!$A$3:$A$15),0) -> 0 | I85: =NETWORKDAYS($E$4,F85,'Festivos Guatemala'!$A$3:$A$15) -> 19 | J85: =H85 -> 0
C86: REEMBOLSOS GASTOS | D86: =SUBTOTAL(9,D87:D90) -> 5425.96 | E86: =SUBTOTAL(9,E87:E90) -> 727.34048
C87: Ronny Quan. Energyzer-CC003-USD | D87: =E87*D6 -> 0 | E87: 0 | F87: 45991 | G87: Cancelado | H87: =IF(OR(G87="Sin pagar",G87="Pagar"),NETWORKDAYS($E$4,F87,'Festivos Guatemala'!$A$3:$A$15),0) -> 0 | I87: =NETWORKDAYS($E$4,F87,'Festivos Guatemala'!$A$3:$A$15) -> 20 | J87: =H87 -> 0
C88: Ronny Quan. Energyzer-CC003-QTQ | D88: 4577.25 | E88: =D88/$D$6 -> 613.57239 | F88: 45988 | G88: Cancelado | H88: =IF(OR(G88="Sin pagar",G88="Pagar"),NETWORKDAYS($E$4,F88,'Festivos Guatemala'!$A$3:$A$15),0) -> 0 | I88: =NETWORKDAYS($E$4,F88,'Festivos Guatemala'!$A$3:$A$15) -> 19 | J88: =H88 -> 0
C89: Ivan Estuardo Chávez Morales-Energyzer-CC004-QTQ | D89: 107.5 | E89: =D89/$D$6 -> 14.410188 | F89: 45988 | G89: Cancelado | H89: =IF(OR(G89="Sin pagar",G89="Pagar"),NETWORKDAYS($E$4,F89,'Festivos Guatemala'!$A$3:$A$15),0) -> 0 | I89: =NETWORKDAYS($E$4,F89,'Festivos Guatemala'!$A$3:$A$15) -> 19 | J89: =H89 -> 0
C90: Michael scott Edgar -Basis Global Technologies -CC011-QTQ | D90: 741.21 | E90: =D90/$D$6 -> 99.357909 | F90: 45988 | G90: Cancelado | H90: =IF(OR(G90="Sin pagar",G90="Pagar"),NETWORKDAYS($E$4,F90,'Festivos Guatemala'!$A$3:$A$15),0) -> 0 | I90: =NETWORKDAYS($E$4,F90,'Festivos Guatemala'!$A$3:$A$15) -> 19 | J90: =H90 -> 0
C91: IMPREVISTO | D91: =SUBTOTAL(9,D92:D92) -> 0 | E91: =SUBTOTAL(9,E92:E92) -> 0
B92: S/N | C92: Transferencia de Prefondeo cuenta global Republica Dominicana | D92: =$E$92*$D$6 -> 0 | E92: 0 | F92: 45991 | G92: Cancelado | H92: =IF(OR(G92="Sin pagar",G92="Pagar"),NETWORKDAYS($E$4,F92,'Festivos Guatemala'!$A$3:$A$15),0) -> 0 | I92: =NETWORKDAYS($E$4,F92,'Festivos Guatemala'!$A$3:$A$15) -> 20 | J92: =H92 -> 0
C93: LIQUIDACIONES | D93: =SUBTOTAL(9,D94:D94) -> 0 | E93: =SUBTOTAL(9,E94:E94) -> 0
D94: 0 | E94: =D94/$D$6 -> 0 | F94: 45991 | G94: Cancelado | H94: =IF(OR(G94="Sin pagar",G94="Pagar"),NETWORKDAYS($E$4,F94,'Festivos Guatemala'!$A$3:$A$15),0) -> 0 | I94: =NETWORKDAYS($E$4,F94,'Festivos Guatemala'!$A$3:$A$15) -> 20 | J94: =H94 -> 0
C95: OTROS GASTOS DE OFICINA Y EMPLADOS | D95: =SUBTOTAL(9,D96:D96) -> 1500 | E95: =SUBTOTAL(9,E96:E96) -> 201.07239
B96: 3075098786 | C96: Factura Claro | D96: 1500 | E96: =D96/$D$6 -> 201.07239 | F96: 45987 | G96: Cancelado | H96: =IF(OR(G96="Sin pagar",G96="Pagar"),NETWORKDAYS($E$4,F96,'Festivos Guatemala'!$A$3:$A$15),0) -> 0 | I96: =NETWORKDAYS($E$4,F96,'Festivos Guatemala'!$A$3:$A$15) -> 18 | J96: =H96 -> 0
C97: NÓMINA SAFEGUARD | D97: =SUBTOTAL(9,D98:D106) -> 224523.03 | E97: =SUBTOTAL(9,E98:E106) -> 30096.921
B98: Bibank | C98: Jorge Benjamin Granados Anderson-USD-Pago adelanto de gastos | D98: =E98*D6 -> 37300 | E98: 5000 | F98: 45971 | G98: Cancelado | H98: =IF(OR(G98="Sin pagar",G98="Pagar"),NETWORKDAYS($E$4,F98,'Festivos Guatemala'!$A$3:$A$15),0) -> 0 | I98: =NETWORKDAYS($E$4,F98,'Festivos Guatemala'!$A$3:$A$15) -> 6 | J98: =H98 -> 0
B99: Bibank | C99: Rudy Renato Chic Arriaza | D99: 10855.64 | E99: =D99/$D$6 -> 1455.1796 | F99: 45988 | G99: Cancelado | H99: =IF(OR(G99="Sin pagar",G99="Pagar"),NETWORKDAYS($E$4,F99,'Festivos Guatemala'!$A$3:$A$15),0) -> 0 | I99: =NETWORKDAYS($E$4,F99,'Festivos Guatemala'!$A$3:$A$15) -> 19 | J99: =H99 -> 0
B100: Bibank | C100: Jorge Benjamin Granados Anderson | D100: 37726.23 | E100: =D100/$D$6 -> 5057.1354 | F100: 45988 | G100: Cancelado | H100: =IF(OR(G100="Sin pagar",G100="Pagar"),NETWORKDAYS($E$4,F100,'Festivos Guatemala'!$A$3:$A$15),0) -> 0 | I100: =NETWORKDAYS($E$4,F100,'Festivos Guatemala'!$A$3:$A$15) -> 19 | J100: =H100 -> 0
B101: Bibank | C101: Carlos Raymundo Morales Santos | D101: 16287.9 | E101: =D101/$D$6 -> 2183.3646 | F101: 45988 | G101: Cancelado | H101: =IF(OR(G101="Sin pagar",G101="Pagar"),NETWORKDAYS($E$4,F101,'Festivos Guatemala'!$A$3:$A$15),0) -> 0 | I101: =NETWORKDAYS($E$4,F101,'Festivos Guatemala'!$A$3:$A$15) -> 19 | J101: =H101 -> 0
B102: Bibank | C102: Ana Isabel Pinillos Melville | D102: 15653.9 | E102: =D102/$D$6 -> 2098.378 | F102: 45988 | G102: Cancelado | H102: =IF(OR(G102="Sin pagar",G102="Pagar"),NETWORKDAYS($E$4,F102,'Festivos Guatemala'!$A$3:$A$15),0) -> 0 | I102: =NETWORKDAYS($E$4,F102,'Festivos Guatemala'!$A$3:$A$15) -> 19 | J102: =H102 -> 0
B103: Bibank | C103: Odalis Alejandra Reyes Pirir | D103: 22644.97 | E103: =D103/$D$6 -> 3035.5188 | F103: 45988 | G103: Cancelado | H103: =IF(OR(G103="Sin pagar",G103="Pagar"),NETWORKDAYS($E$4,F103,'Festivos Guatemala'!$A$3:$A$15),0) -> 0 | I103: =NETWORKDAYS($E$4,F103,'Festivos Guatemala'!$A$3:$A$15) -> 19 | J103: =H103 -> 0
B104: Bibank | C104: Domenica Georgina Samayoa Ramirez | D104: 9032.61 | E104: =D104/$D$6 -> 1210.8056 | F104: 45988 | G104: Cancelado | H104: =IF(OR(G104="Sin pagar",G104="Pagar"),NETWORKDAYS($E$4,F104,'Festivos Guatemala'!$A$3:$A$15),0) -> 0 | I104: =NETWORKDAYS($E$4,F104,'Festivos Guatemala'!$A$3:$A$15) -> 19 | J104: =H104 -> 0
B105: Bibank | C105: Jessica Patricia Vasquez Gonzalez | D105: 47799.56 | E105: =D105/$D$6 -> 6407.4477 | F105: 45988 | G105: Cancelado | H105: =IF(OR(G105="Sin pagar",G105="Pagar"),NETWORKDAYS($E$4,F105,'Festivos Guatemala'!$A$3:$A$15),0) -> 0 | I105: =NETWORKDAYS($E$4,F105,'Festivos Guatemala'!$A$3:$A$15) -> 19 | J105: =H105 -> 0
B106: Rural | C106: David Enrique Herman Juarez | D106: 27222.22 | E106: =D106/$D$6 -> 3649.0912 | F106: 45988 | G106: Cancelado | H106: =IF(OR(G106="Sin pagar",G106="Pagar"),NETWORKDAYS($E$4,F106,'Festivos Guatemala'!$A$3:$A$15),0) -> 0 | I106: =NETWORKDAYS($E$4,F106,'Festivos Guatemala'!$A$3:$A$15) -> 19 | J106: =H106 -> 0
C107: SEGURIDAD IGSS | D107: =SUBTOTAL(9,D108:D108) -> 25913.38 | E107: =SUBTOTAL(9,E108:E108) -> 3473.6434
B108: 5794755 | C108: Pago planilla IGSS Octubre-SG | D108: 25913.38 | E108: =D108/$D$6 -> 3473.6434 | F108: 45975 | G108: Cancelado | H108: =IF(OR(G108="Sin pagar",G108="Pagar"),NETWORKDAYS($E$4,F108,'Festivos Guatemala'!$A$3:$A$15),0) -> 0 | I108: =NETWORKDAYS($E$4,F108,'Festivos Guatemala'!$A$3:$A$15) -> 10 | J108: =H108 -> 0
C109: IMPUESTOS | D109: =SUBTOTAL(9,D110:D110) -> 2749.27 | E109: =SUBTOTAL(9,E110:E110) -> 368.53485 | J109: =H109 -> 0
B110: 49115192689 | C110: Declaraguate ISR rentas de trabajo Octubre | D110: 2749.27 | E110: =D110/$D$6 -> 368.53485 | F110: 45975 | G110: Cancelado | H110: =IF(OR(G110="Sin pagar",G110="Pagar"),NETWORKDAYS($E$4,F110,'Festivos Guatemala'!$A$3:$A$15),0) -> 0 | I110: =NETWORKDAYS($E$4,F110,'Festivos Guatemala'!$A$3:$A$15) -> 10 | J110: =H110 -> 0
C111: REEMBOLSOS GASTOS | D111: =SUBTOTAL(9,D112:D113) -> 68711.228 | E111: =SUBTOTAL(9,E112:E113) -> 9210.6204
C112: Jorge Benjamin Granados Anderson-USD | D112: =E112*$D$6 -> 43253.378 | E112: 5798.04 | F112: 45989 | G112: Cancelado | H112: =IF(OR(G112="Sin pagar",G112="Pagar"),NETWORKDAYS($E$4,F112,'Festivos Guatemala'!$A$3:$A$15),0) -> 0 | I112: =NETWORKDAYS($E$4,F112,'Festivos Guatemala'!$A$3:$A$15) -> 20 | J112: =H112 -> 0
C113: Jorge Benjamin Granados Anderson -QTQ | D113: 25457.85 | E113: =D113/$D$6 -> 3412.5804 | F113: 45988 | G113: Cancelado | H113: =IF(OR(G113="Sin pagar",G113="Pagar"),NETWORKDAYS($E$4,F113,'Festivos Guatemala'!$A$3:$A$15),0) -> 0 | I113: =NETWORKDAYS($E$4,F113,'Festivos Guatemala'!$A$3:$A$15) -> 19 | J113: =H113 -> 0
C114: PÓLIZAS Y SEGUROS | D114: =SUBTOTAL(9,D115:D117) -> 5627.52 | E114: =SUBTOTAL(9,E115:E117) -> 754.35925 | F114: ,
...

Sheet Flujo Caja Diciembre 2025
D1: 42400
D4: Fecha de Elaboración: | E4: 45992
C6: Tasa de cambio: | D6: 7.46
D7: DICIEMBRE
D8: VALOR QTQ | E8: VALOR USD
C9: BANCOS | D9: =SUBTOTAL(9,D10:D12) -> 503122.91 | E9: =SUBTOTAL(9,E10:E12) -> 67442.75
C10: Bancos QTQ | D10: ='Caja QTQ'!$D$826+7012.4 -> 433717.46 | E10: =D10/$D$6 -> 58139.07
C11: Bancos USD | D11: =E11*D6 -> 36420.69 | E11: ='Caja USD'!$D$290 -> 4882.13
C12: Devolución de dinero Roony Quan por pago doble reembolso | D12: =E12*D6 -> 32984.763 | E12: 4421.55
C13: CLIENTES | D13: =SUBTOTAL(9,D14:D31) -> 1100545.3 | E13: =SUBTOTAL(9,E14:E31) -> 144950.03
B14: Pagado | C14: Client: NotableGrowth, Inc-Remotefist | D14: ='Diferencia en cambio'!I201 -> 50276.328 | E14: =D14/'Diferencia en cambio'!L201 -> 6633.77
B15: Pagado | C15: Client: Bilingual Bridges, Inc-Remotefist | D15: ='Diferencia en cambio'!I202 -> 12562.242 | E15: =D15/'Diferencia en cambio'!L202 -> 1657.54
B16: Pagado | C16: Client: :Iberia Foods LLC -Remotefist | D16: ='Diferencia en cambio'!I203 -> 28172.924 | E16: =D16/'Diferencia en cambio'!L203 -> 3717.31
B17: Pagado | C17: Client: Vinmar International,-Liza Marlene Torres valdes 202508-Remofirst | D17: ='Diferencia en cambio'!I204 -> 20194.899 | E17: =D17/'Diferencia en cambio'!L204 -> 2664.64
B18: Pagado | C18: Client: Czarnikow- Sthepanie Rodriguez Lopez-Remotefist | D18: ='Diferencia en cambio'!I205 -> 42031.831 | E18: =D18/'Diferencia en cambio'!L205 -> 5545.94
B19: Pagado | C19: Client: Soul Innovations-Remotefist | D19: ='Diferencia en cambio'!I206 -> 95878.326 | E19: =D19/'Diferencia en cambio'!L206 -> 12650.78
B20: Sin Pagar | C20: Client:Energyzer-Safeguard | D20: =E20*$D$6 -> 0 | E20: ='Diferencia en cambio'!F207*0 -> 0
B21: Pagado | C21: Client:Kairos- Safeguard | D21: ='Diferencia en cambio'!I208 -> 11102.886 | E21: =D21/'Diferencia en cambio'!L208 -> 1465.01
B22: Pagado | C22: Client: Opportunity-Safeguard | D22: ='Diferencia en cambio'!I209 -> 27323.372 | E22: =D22/'Diferencia en cambio'!L209 -> 3605.28
D23: 2059 | E23: =D23/D6 -> 276.00536
B25: Pagado | C25: Client: Panthera, Inc-Safeguard | D25: ='Diferencia en cambio'!I210 -> 18300.69 | E25: =D25/'Diferencia en cambio'!L210 -> 2414.75
B26: Pagado | C26: Client: :Careercircle, LLC-Safeguard | D26: ='Diferencia en cambio'!I211 -> 45390.562 | E26: =D26/'Diferencia en cambio'!L211 -> 5989.22
B27: Pagado | C27: Client: :Highspring, LLC-Safeguard | D27: ='Diferencia en cambio'!I212 -> 107775.17 | E27: =D27/'Diferencia en cambio'!L212 -> 14220.78
B28: Pagado | C28: Client: :Archewll, LLC-Safeguard | D28: ='Diferencia en cambio'!I213 -> 12749.512 | E28: =D28/'Diferencia en cambio'!L213 -> 1682.28
B29: Pagado | C29: Client:Global Expansion | D29: ='Diferencia en cambio'!I215 -> 121412.05 | E29: =$D$29/'Diferencia en cambio'!$L$215 -> 15938.34
B30: Pagado | C30: Client: Safeguard Nomina directa-Aguinaldo | D30: ='Diferencia en cambio'!I214 -> 117321.19 | E30: =$D$30/'Diferencia en cambio'!$L$214 -> 15564.84
B31: Pagado | C31: Client: Safeguard Nomina directa | D31: ='Diferencia en cambio'!I216 -> 387994.35 | E31: =$D$31/'Diferencia en cambio'!$L$216 -> 50923.54
C32: TOTAL INGRESOS | D32: =SUBTOTAL(9,D9:D31) -> 1603668.2 | E32: =SUBTOTAL(9,E9:E31) -> 212392.78
B35: CUENTAS X PAGAR MES | D35: DICIEMBRE
B36: Factura | C36: PROVEEDOR | D36: VALOR QTQ | E36: VALOR USD | F36: Fecha vencimiento | G36: Estado | J36: KPI
C37: SEGURIDAD IGSS | D37: =SUBTOTAL(9,D38:D38) -> 106546.18 | E37: =SUBTOTAL(9,E38:E38) -> 14282.33
B38: 5794688 | C38: Pago planilla IGSS Noviembre | D38: 106546.18 | E38: =D38/$D$6 -> 14282.33 | F38: 46006 | G38: Cancelado | H38: =IF(OR(G38="Sin pagar",G38="Pagar"),NETWORKDAYS($E$4,F38,'Festivos Guatemala'!$A$3:$A$15),0) -> 0 | I38: =NETWORKDAYS($E$4,F38,'Festivos Guatemala'!$A$3:$A$15) -> 11 | J38: =H38 -> 0
C39: IMPUESTOS | D39: =SUBTOTAL(9,D40:D42) -> 31765.83 | E39: =SUBTOTAL(9,E40:E42) -> 4258.1542 | J39: =H39 -> 0
B40: 49380053011 | C40: Declaraguate ISR Septiembre | D40: 28513.4 | E40: =D40/$D$6 -> 3822.1716 | F40: 46003 | G40: Cancelado | H40: =IF(OR(G40="Sin pagar",G40="Pagar"),NETWORKDAYS($E$4,F40,'Festivos Guatemala'!$A$3:$A$15),0) -> 0 | I40: =NETWORKDAYS($E$4,F40,'Festivos Guatemala'!$A$3:$A$15) -> 10 | J40: =H40 -> 0
B41: 49375016788 | C41: Declaraguate ISR no residentes facturación Col Factura Noviembre (15%) | D41: 1703 | E41: =D41/$D$6 -> 228.28418 | F41: 46003 | G41: Cancelado | H41: =IF(OR(G41="Sin pagar",G41="Pagar"),NETWORKDAYS($E$4,F41,'Festivos Guatemala'!$A$3:$A$15),0) -> 0 | I41: =NETWORKDAYS($E$4,F41,'Festivos Guatemala'!$A$3:$A$15) -> 10 | J41: =H41 -> 0
B42: 49375134303 | C42: Declaraguate ISR No Residentes / Grupo CGR Lawyer | D42: 1549.43 | E42: =D42/$D$6 -> 207.69839 | F42: 46003 | G42: Cancelado | H42: =IF(OR(G42="Sin pagar",G42="Pagar"),NETWORKDAYS($E$4,F42,'Festivos Guatemala'!$A$3:$A$15),0) -> 0 | I42: =NETWORKDAYS($E$4,F42,'Festivos Guatemala'!$A$3:$A$15) -> 10 | J42: =H42 -> 0
C43: SERVICIOS PROFESIONALES -REPRESENTACIÓN LEGAL -GASTOS DE OFICINA | D43: =SUBTOTAL(9,D44:D48) -> 31485.94 | E43: =SUBTOTAL(9,E44:E48) -> 3470.6354 | J43: =H43 -> 0
B44: E320000000008 | C44: Servicio de representación, diligencia de alta TSS y ministerio Grupo CGR Lawyer | D44: =$E$44*$D$6 -> 12309 | E44: 1650 | F44: 45995 | G44: Cancelado | H44: =IF(OR(G44="Sin pagar",G44="Pagar"),NETWORKDAYS($E$4,F44,'Festivos Guatemala'!$A$3:$A$15),0) -> 0 | I44: =NETWORKDAYS($E$4,F44,'Festivos Guatemala'!$A$3:$A$15) -> 4 | J44: =H44 -> 0
B45: 12557 | C45: Inbers contadores Servicios contables con entrega de información financiera correspondiente al periodo de Noviembre 2025 | D45: =4673.2-100 -> 4573.2 | E45: =D45/$D$6 -> 613.02949 | F45: 46010 | G45: Cancelado | H45: =IF(OR(G45="Sin pagar",G45="Pagar"),NETWORKDAYS($E$4,F45,'Festivos Guatemala'!$A$3:$A$15),0) -> 0 | I45: =NETWORKDAYS($E$4,F45,'Festivos Guatemala'!$A$3:$A$15) -> 15 | J45: =H45 -> 0
B46: 2888256700 | C46: Servicios prestados por representación entidad Global Guatemala Diciembre 2025 | D46: 1368.42 | E46: =D46/$D$6 -> 183.43432 | F46: 46010 | G46: Cancelado | H46: =IF(OR(G46="Sin pagar",G46="Pagar"),NETWORKDAYS($E$4,F46,'Festivos Guatemala'!$A$3:$A$15),0) -> 0 | I46: =NETWORKDAYS($E$4,F46,'Festivos Guatemala'!$A$3:$A$15) -> 15 | J46: =H46 -> 0
B47: 1774800791 | C47: Servicios prestados de representación mes de noviembre de 2025 | D47: 926.32 | E47: =D47/$D$6 -> 124.17158 | F47: 46010 | G47: Cancelado | H47: =IF(OR(G47="Sin pagar",G47="Pagar"),NETWORKDAYS($E$4,F47,'Festivos Guatemala'!$A$3:$A$15),0) -> 0 | I47: =NETWORKDAYS($E$4,F47,'Festivos Guatemala'!$A$3:$A$15) -> 15 | J47: =H47 -> 0
B48: E320000000009 | C48: Servicio de representación, diligencia de alta TSS y ministerio Grupo CGR Lawyer-Enero | D48: =$E$44*$D$6 -> 12309 | E48: 900 | F48: 46028 | G48: Cancelado | H48: =IF(OR(G48="Sin pagar",G48="Pagar"),NETWORKDAYS($E$4,F48,'Festivos Guatemala'!$A$3:$A$15),0) -> 0 | I48: =NETWORKDAYS($E$4,F48,'Festivos Guatemala'!$A$3:$A$15) -> 24 | J48: =H48 -> 0
C49: PÓLIZAS Y SEGUROS | D49: =SUBTOTAL(9,D50:D57) -> 10192.01 | E49: =SUBTOTAL(9,E50:E57) -> 1366.2212
B50: Ok | C50: Póliza de vida Ivan Estuardo Chavez Morales-USD-Póliza Vida | D50: =E50*$D$6 -> 410.8222 | E50: 55.07 | F50: 46014 | G50: Cancelado | H50: =IF(OR(G50="Sin pagar",G50="Pagar"),NETWORKDAYS($E$4,F50,'Festivos Guatemala'!$A$3:$A$15),0) -> 0 | I50: =NETWORKDAYS($E$4,F50,'Festivos Guatemala'!$A$3:$A$15) -> 17 | J50: =H50 -> 0
B51: OK | C51: Poliza de vida Rony Eduardo Quan Lam-USD-Póliza Vida | D51: =E51*$D$6 -> 1935.6462 | E51: 259.47 | F51: 46014 | G51: Cancelado | H51: =IF(OR(G51="Sin pagar",G51="Pagar"),NETWORKDAYS($E$4,F51,'Festivos Guatemala'!$A$3:$A$15),0) -> 0 | I51: =NETWORKDAYS($E$4,F51,'Festivos Guatemala'!$A$3:$A$15) -> 17 | J51: =H51 -> 0
B52: OK | C52: Poliza de vida Jerry García Carillo -USD-Póliza Vida | D52: =E52*$D$6 -> 1531.7618 | E52: 205.33 | F52: 46014 | G52: Cancelado | H52: =IF(OR(G52="Sin pagar",G52="Pagar"),NETWORKDAYS($E$4,F52,'Festivos Guatemala'!$A$3:$A$15),0) -> 0 | I52: =NETWORKDAYS($E$4,F52,'Festivos Guatemala'!$A$3:$A$15) -> 17 | J52: =H52 -> 0
B53: OK | C53: Póliza de salud Hector Augusto Castillo Luna-QTQ-GM-Inclusión | D53: 722.42 | E53: =D53/$D$6 -> 96.839142 | F53: 46014 | G53: Cancelado | H53: =IF(OR(G53="Sin pagar",G53="Pagar"),NETWORKDAYS($E$4,F53,'Festivos Guatemala'!$A$3:$A$15),0) -> 0 | I53: =NETWORKDAYS($E$4,F53,'Festivos Guatemala'!$A$3:$A$15) -> 17 | J53: =H53 -> 0
B54: OK | C54: Póliza de salud Miriam Lucia Morfin González-QTQ-GM | D54: 861.81 | E54: =D54/$D$6 -> 115.52413 | F54: 46014 | G54: Cancelado | H54: =IF(OR(G54="Sin pagar",G54="Pagar"),NETWORKDAYS($E$4,F54,'Festivos Guatemala'!$A$3:$A$15),0) -> 0 | I54: =NETWORKDAYS($E$4,F54,'Festivos Guatemala'!$A$3:$A$15) -> 17 | J54: =H54 -> 0
B55: OK | C55: Póliza de salud Ivan Estuardo Chavez Morales-QTQ-GM | D55: 1704.44 | E55: =D55/$D$6 -> 228.47721 | F55: 46014 | G55: Cancelado | H55: =IF(OR(G55="Sin pagar",G55="Pagar"),NETWORKDAYS($E$4,F55,'Festivos Guatemala'!$A$3:$A$15),0) -> 0 | I55: =NETWORKDAYS($E$4,F55,'Festivos Guatemala'!$A$3:$A$15) -> 17 | J55: =H55 -> 0
B56: OK | C56: Poliza de salud Rony Eduardo Quan Lam-QTQ-GM | D56: 1023.02 | E56: =D56/$D$6 -> 137.13405 | F56: 46014 | G56: Cancelado | H56: =IF(OR(G56="Sin pagar",G56="Pagar"),NETWORKDAYS($E$4,F56,'Festivos Guatemala'!$A$3:$A$15),0) -> 0 | I56: =NETWORKDAYS($E$4,F56,'Festivos Guatemala'!$A$3:$A$15) -> 17 | J56: =H56 -> 0
B57: OK | C57: Poliza de salud Jerry García Carillo -QTQ-GM-Claudia Marisol Mayorga Ayala | D57: 2002.09 | E57: =D57/$D$6 -> 268.37668 | F57: 46014 | G57: Cancelado | H57: =IF(OR(G57="Sin pagar",G57="Pagar"),NETWORKDAYS($E$4,F57,'Festivos Guatemala'!$A$3:$A$15),0) -> 0 | I57: =NETWORKDAYS($E$4,F57,'Festivos Guatemala'!$A$3:$A$15) -> 17 | J57: =H57 -> 0
C58: COBROS ENTRE SUCURSALES | D58: =SUBTOTAL(9,D59:D59) -> 0 | E58: =SUBTOTAL(9,E59:E59) -> 0
B59: 0 | D59: =E59*7.8 -> 0 | E59: 0 | F59: 46022 | G59: Cancelado | H59: =IF(OR(G59="Sin pagar",G59="Pagar"),NETWORKDAYS($E$4,F59,'Festivos Guatemala'!$A$3:$A$15),0) -> 0 | I59: =NETWORKDAYS($E$4,F59,'Festivos Guatemala'!$A$3:$A$15) -> 20 | J59: =H59 -> 0
C60: TIQUETES AÉREOS , HOTELES | D60: =SUBTOTAL(9,D61:D61) -> 0 | E60: =SUBTOTAL(9,E61:E61) -> 0
F61: 46022 | G61: Cancelado | H61: =IF(OR(G61="Sin pagar",G61="Pagar"),NETWORKDAYS($E$4,F61,'Festivos Guatemala'!$A$3:$A$15),0) -> 0 | I61: =NETWORKDAYS($E$4,F61,'Festivos Guatemala'!$A$3:$A$15) -> 20 | J61: =H61 -> 0
C62: COSTOS FINANCIEROS | D62: =SUBTOTAL(9,D63:D65) -> 596.8 | E62: =SUBTOTAL(9,E63:E65) -> 80
C63: Gastos financieros por envio de recursos pago factura CGR Lawyer dominicana | D63: =E63*$D$6 -> 298.4 | E63: 40 | F63: 45995 | G63: Cancelado | H63: =IF(OR(G63="Sin pagar",G63="Pagar"),NETWORKDAYS($E$4,F63,'Festivos Guatemala'!$A$3:$A$15),0) -> 0 | I63: =NETWORKDAYS($E$4,F63,'Festivos Guatemala'!$A$3:$A$15) -> 4 | J63: =H63 -> 0
C64: Cobro emisión estado cuenta | D64: =E64*D6 -> 0 | E64: =40*0 -> 0 | F64: 46022 | G64: Cancelado | H64: =IF(OR(G64="Sin pagar",G64="Pagar"),NETWORKDAYS($E$4,F64,'Festivos Guatemala'!$A$3:$A$15),0) -> 0 | I64: =NETWORKDAYS($E$4,F64,'Festivos Guatemala'!$A$3:$A$15) -> 20 | J64: =H64 -> 0
C65: Gastos financieros por envio de recursos pago factura CGR Lawyer dominicana | D65: =E65*$D$6 -> 298.4 | E65: 40 | F65: 46028 | G65: Cancelado | H65: =IF(OR(G65="Sin pagar",G65="Pagar"),NETWORKDAYS($E$4,F65,'Festivos Guatemala'!$A$3:$A$15),0) -> 0 | I65: =NETWORKDAYS($E$4,F65,'Festivos Guatemala'!$A$3:$A$15) -> 24 | J65: =H65 -> 0
C66: NÓMINAS | D66: =SUBTOTAL(9,D67:D88) -> 598115.01 | E66: =SUBTOTAL(9,E67:E88) -> 80176.275
B67: America Ctral | C67: Victor Jose Moscoso Portillo -Global Expansion-CC015 | D67: 49577.78 | E67: =D67/$D$6 -> 6645.815 | F67: 46008 | G67: Cancelado | H67: =IF(OR(G67="Sin pagar",G67="Pagar"),NETWORKDAYS($E$4,F67,'Festivos Guatemala'!$A$3:$A$15),0) -> 0 | I67: =NETWORKDAYS($E$4,F67,'Festivos Guatemala'!$A$3:$A$15) -> 13 | J67: =H67 -> 0
B68: Bibank | C68: Cynthia Arlene fuentes elias -Global Expansion -CC015 | D68: 32589.92 | E68: =D68/$D$6 -> 4368.622 | F68: 46008 | G68: Cancelado | H68: =IF(OR(G68="Sin pagar",G68="Pagar"),NETWORKDAYS($E$4,F68,'Festivos Guatemala'!$A$3:$A$15),0) -> 0 | I68: =NETWORKDAYS($E$4,F68,'Festivos Guatemala'!$A$3:$A$15) -> 13 | J68: =H68 -> 0
B69: America Ctral | C69: Hector Augusto Castillo Luna-Iberia-CC013 | D69: 18701.01 | E69: =D69/$D$6 -> 2506.8378 | F69: 46017 | G69: Cancelado | H69: =IF(OR(G69="Sin pagar",G69="Pagar"),NETWORKDAYS($E$4,F69,'Festivos Guatemala'!$A$3:$A$15),0) -> 0 | I69: =NETWORKDAYS($E$4,F69,'Festivos Guatemala'!$A$3:$A$15) -> 18 | J69: =H69 -> 0 | M69: Pago el 26 Dic
B70: America Ctral | C70: Stephanie Rodriguez Lopez-RF-Czarnikow-CC002 | D70: 29033.11 | E70: =D70/$D$6 -> 3891.8378 | F70: 46017 | G70: Cancelado | H70: =IF(OR(G70="Sin pagar",G70="Pagar"),NETWORKDAYS($E$4,F70,'Festivos Guatemala'!$A$3:$A$15),0) -> 0 | I70: =NETWORKDAYS($E$4,F70,'Festivos Guatemala'!$A$3:$A$15) -> 18 | J70: =H70 -> 0 | M70: Pago el 26 Dic
B71: America Ctral | C71: Carlos Alejandro Montiel Lorenzana-Archell -CC014 | D71: 25531.03 | E71: =D71/$D$6 -> 3422.3901 | F71: 46017 | G71: Cancelado | H71: =IF(OR(G71="Sin pagar",G71="Pagar"),NETWORKDAYS($E$4,F71,'Festivos Guatemala'!$A$3:$A$15),0) -> 0 | I71: =NETWORKDAYS($E$4,F71,'Festivos Guatemala'!$A$3:$A$15) -> 18 | J71: =H71 -> 0 | M71: Pago con cheque
B72: G&T Cont | C72: Liza Marlene Torres Valdes -Vinmar international -CC016 | D72: 13622.51 | E72: =D72/$D$6 -> 1826.0737 | F72: 46017 | G72: Cancelado | H72: =IF(OR(G72="Sin pagar",G72="Pagar"),NETWORKDAYS($E$4,F72,'Festivos Guatemala'!$A$3:$A$15),0) -> 0 | I72: =NETWORKDAYS($E$4,F72,'Festivos Guatemala'!$A$3:$A$15) -> 18 | J72: =H72 -> 0 | M72: Pago el 26 Dic
B73: G&T Cont | C73: Douglas Miguel Villa Fuerte Leiva -Archell -CC014 | D73: 10127.07 | E73: =D73/$D$6 -> 1357.5161 | F73: 46017 | G73: Cancelado | H73: =IF(OR(G73="Sin pagar",G73="Pagar"),NETWORKDAYS($E$4,F73,'Festivos Guatemala'!$A$3:$A$15),0) -> 0 | I73: =NETWORKDAYS($E$4,F73,'Festivos Guatemala'!$A$3:$A$15) -> 18 | J73: =H73 -> 0 | M73: Pago el 26 Dic
B74: G&T Cont | C74: Javier Ricardo Martinez Cruz-Suol Innovations Ltd (RF) | D74: 67218.36 | E74: =D74/$D$6 -> 9010.504 | F74: 46017 | G74: Cancelado | H74: =IF(OR(G74="Sin pagar",G74="Pagar"),NETWORKDAYS($E$4,F74,'Festivos Guatemala'!$A$3:$A$15),0) -> 0 | I74: =NETWORKDAYS($E$4,F74,'Festivos Guatemala'!$A$3:$A$15) -> 18 | J74: =H74 -> 0 | M74: Pago el 26 Dic
B75: G&T Cont | C75: Michael scott Edgar -Basis Global Technologies -CC011 | D75: 34601.33 | E75: =D75/$D$6 -> 4638.248 | F75: 46017 | G75: Cancelado | H75: =IF(OR(G75="Sin pagar",G75="Pagar"),NETWORKDAYS($E$4,F75,'Festivos Guatemala'!$A$3:$A$15),0) -> 0 | I75: =NETWORKDAYS($E$4,F75,'Festivos Guatemala'!$A$3:$A$15) -> 18 | J75: =H75 -> 0 | M75: Pago el 26 Dic
B76: Rural | C76: Joshua Esteban Lopez Fernandez -Highspring-CC017 | D76: 9930.71 | E76: =D76/$D$6 -> 1331.1944 | F76: 46017 | G76: Cancelado | H76: =IF(OR(G76="Sin pagar",G76="Pagar"),NETWORKDAYS($E$4,F76,'Festivos Guatemala'!$A$3:$A$15),0) -> 0 | I76: =NETWORKDAYS($E$4,F76,'Festivos Guatemala'!$A$3:$A$15) -> 18 | J76: =H76 -> 0 | M76: Pago el 26 Dic
B77: International | C77: María Fernanda Robles Solis -Oportunity-CC006 | D77: 9662.36 | E77: =D77/$D$6 -> 1295.2225 | F77: 46017 | G77: Cancelado | H77: =IF(OR(G77="Sin pagar",G77="Pagar"),NETWORKDAYS($E$4,F77,'Festivos Guatemala'!$A$3:$A$15),0) -> 0 | I77: =NETWORKDAYS($E$4,F77,'Festivos Guatemala'!$A$3:$A$15) -> 18 | J77: =H77 -> 0 | M77: Pago el 26 Dic
B78: Bibank | C78: Edlin Ivette Ramos Poitan-Opportunnity-CC006 | D78: 11877 | E78: =D78/$D$6 -> 1592.0912 | F78: 46017 | G78: Cancelado | H78: =IF(OR(G78="Sin pagar",G78="Pagar"),NETWORKDAYS($E$4,F78,'Festivos Guatemala'!$A$3:$A$15),0) -> 0 | I78: =NETWORKDAYS($E$4,F78,'Festivos Guatemala'!$A$3:$A$15) -> 18 | J78: =H78 -> 0 | M78: Programado 26 Dic
B79: Bibank | C79: Barbara Isabela Escobar Anleu -Panthera-CC008 | D79: 14151 | E79: =D79/$D$6 -> 1896.9169 | F79: 46017 | G79: Cancelado | H79: =IF(OR(G79="Sin pagar",G79="Pagar"),NETWORKDAYS($E$4,F79,'Festivos Guatemala'!$A$3:$A$15),0) -> 0 | I79: =NETWORKDAYS($E$4,F79,'Festivos Guatemala'!$A$3:$A$15) -> 18 | J79: =H79 -> 0 | M79: Programado 26 Dic
B80: Bibank | C80: Wendy Maricela Marroquin Hernandez-Archewll-CC014 | D80: 24923 | E80: =D80/$D$6 -> 3340.8847 | F80: 46017 | G80: Cancelado | H80: =IF(OR(G80="Sin pagar",G80="Pagar"),NETWORKDAYS($E$4,F80,'Festivos Guatemala'!$A$3:$A$15),0) -> 0 | I80: =NETWORKDAYS($E$4,F80,'Festivos Guatemala'!$A$3:$A$15) -> 18 | J80: =H80 -> 0 | M80: Programado 26 Dic
... B88: Bibank | C88: Ronny Eduardo Quan Lam-Energyzer-CC004 | D88: 67852.6 | E88: =D88/$D$6 -> 9095.5228 | F88: 46021 | G88: Cancelado | H88: =IF(OR(G88="Sin pagar",G88="Pagar"),NETWORKDAYS($E$4,F88,'Festivos Guatemala'!$A$3:$A$15),0) -> 0 | I88: =NETWORKDAYS($E$4,F88,'Festivos Guatemala'!$A$3:$A$15) -> 20 | J88: =H88 -> 0 | M88: Pago liquidación
C89: REEMBOLSOS GASTOS | D89: =SUBTOTAL(9,D90:D93) -> 0 | E89: =SUBTOTAL(9,E90:E93) -> 0
C90: Ronny Quan. Energyzer-CC003-USD | D90: 0 | E90: 0 | F90: 46021 | G90: Cancelado | H90: =IF(OR(G90="Sin pagar",G90="Pagar"),NETWORKDAYS($E$4,F90,'Festivos Guatemala'!$A$3:$A$15),0) -> 0 | I90: =NETWORKDAYS($E$4,F90,'Festivos Guatemala'!$A$3:$A$15) -> 20 | J90: =H90 -> 0
C91: Ronny Quan. Energyzer-CC003-QTQ | D91: 0 | E91: =D91/$D$6 -> 0 | F91: 46021 | G91: Cancelado | H91: =IF(OR(G91="Sin pagar",G91="Pagar"),NETWORKDAYS($E$4,F91,'Festivos Guatemala'!$A$3:$A$15),0) -> 0 | I91: =NETWORKDAYS($E$4,F91,'Festivos Guatemala'!$A$3:$A$15) -> 20 | J91: =H91 -> 0
C92: Ivan Estuardo Chávez Morales-Energyzer-CC004-QTQ | D92: 0 | E92: =D92/$D$6 -> 0 | F92: 46021 | G92: Cancelado | H92: =IF(OR(G92="Sin pagar",G92="Pagar"),NETWORKDAYS($E$4,F92,'Festivos Guatemala'!$A$3:$A$15),0) -> 0 | I92: =NETWORKDAYS($E$4,F92,'Festivos Guatemala'!$A$3:$A$15) -> 20 | J92: =H92 -> 0
C93: Michael scott Edgar -Basis Global Technologies -CC011-QTQ | D93: 0 | E93: =D93/$D$6 -> 0 | F93: 46021 | G93: Cancelado | H93: =IF(OR(G93="Sin pagar",G93="Pagar"),NETWORKDAYS($E$4,F93,'Festivos Guatemala'!$A$3:$A$15),0) -> 0 | I93: =NETWORKDAYS($E$4,F93,'Festivos Guatemala'!$A$3:$A$15) -> 20 | J93: =H93 -> 0
C94: IMPREVISTO | D94: =SUBTOTAL(9,D95:D95) -> 0 | E94: =SUBTOTAL(9,E95:E95) -> 0
B95: S/N | C95: Transferencia de Prefondeo cuenta global Republica Dominicana | D95: =$E$95*$D$6 -> 0 | E95: 0 | F95: 46022 | G95: Cancelado | H95: =IF(OR(G95="Sin pagar",G95="Pagar"),NETWORKDAYS($E$4,F95,'Festivos Guatemala'!$A$3:$A$15),0) -> 0 | I95: =NETWORKDAYS($E$4,F95,'Festivos Guatemala'!$A$3:$A$15) -> 20 | J95: =H95 -> 0
C96: LIQUIDACIONES | D96: =SUBTOTAL(9,D97:D97) -> 0 | E96: =SUBTOTAL(9,E97:E97) -> 0
D97: 0 | E97: =D97/$D$6 -> 0 | F97: 46022 | G97: Cancelado | H97: =IF(OR(G97="Sin pagar",G97="Pagar"),NETWORKDAYS($E$4,F97,'Festivos Guatemala'!$A$3:$A$15),0) -> 0 | I97: =NETWORKDAYS($E$4,F97,'Festivos Guatemala'!$A$3:$A$15) -> 20 | J97: =H97 -> 0
C98: OTROS GASTOS DE OFICINA Y EMPLADOS | D98: =SUBTOTAL(9,D99:D99) -> 1500 | E98: =SUBTOTAL(9,E99:E99) -> 201.07239
B99: S/N | C99: Factura Claro | D99: 1500 | E99: =D99/$D$6 -> 201.07239 | F99: 46010 | G99: Cancelado | H99: =IF(OR(G99="Sin pagar",G99="Pagar"),NETWORKDAYS($E$4,F99,'Festivos Guatemala'!$A$3:$A$15),0) -> 0 | I99: =NETWORKDAYS($E$4,F99,'Festivos Guatemala'!$A$3:$A$15) -> 15 | J99: =H99 -> 0
C100: AGUINALDOS SAFEGUARD | D100: =SUBTOTAL(9,D101:D109) -> 176893.54 | E100: =SUBTOTAL(9,E101:E109) -> 23712.271
B101: Bibank | C101: Rudy Renato Chic Arriaza | D101: 11081.8 | E101: =D101/$D$6 -> 1485.496 | F101: 46006 | G101: Cancelado | H101: =IF(OR(G101="Sin pagar",G101="Pagar"),NETWORKDAYS($E$4,F101,'Festivos Guatemala'!$A$3:$A$15),0) -> 0 | I101: =NETWORKDAYS($E$4,F101,'Festivos Guatemala'!$A$3:$A$15) -> 11 | J101: =H101 -> 0
B102: Bibank | C102: Jorge Benjamin Granados Anderson | D102: 34571.02 | E102: =D102/$D$6 -> 4634.185 | F102: 46006 | G102: Cancelado | H102: =IF(OR(G102="Sin pagar",G102="Pagar"),NETWORKDAYS($E$4,F102,'Festivos Guatemala'!$A$3:$A$15),0) -> 0 | I102: =NETWORKDAYS($E$4,F102,'Festivos Guatemala'!$A$3:$A$15) -> 11 | J102: =H102 -> 0
B103: Bibank | C103: Carlos Raymundo Morales Santos | D103: 4269.25 | E103: =D103/$D$6 -> 572.28552 | F103: 46006 | G103: Cancelado | H103: =IF(OR(G103="Sin pagar",G103="Pagar"),NETWORKDAYS($E$4,F103,'Festivos Guatemala'!$A$3:$A$15),0) -> 0 | I103: =NETWORKDAYS($E$4,F103,'Festivos Guatemala'!$A$3:$A$15) -> 11 | J103: =H103 -> 0
B104: Bibank | C104: Ana Isabel Pinillos Melville | D104: 16296.43 | E104: =D104/$D$6 -> 2184.508 | F104: 46006 | G104: Cancelado | H104: =IF(OR(G104="Sin pagar",G104="Pagar"),NETWORKDAYS($E$4,F104,'Festivos Guatemala'!$A$3:$A$15),0) -> 0 | I104: =NETWORKDAYS($E$4,F104,'Festivos Guatemala'!$A$3:$A$15) -> 11 | J104: =H104 -> 0
B105: Bibank | C105: Odalis Alejandra Reyes Pirir | D105: 36025.33 | E105: =D105/$D$6 -> 4829.1327 | F105: 46006 | G105: Cancelado | H105: =IF(OR(G105="Sin pagar",G105="Pagar"),NETWORKDAYS($E$4,F105,'Festivos Guatemala'!$A$3:$A$15),0) -> 0 | I105: =NETWORKDAYS($E$4,F105,'Festivos Guatemala'!$A$3:$A$15) -> 11 | J105: =H105 -> 0
B106: Bibank | C106: Domenica Georgina Samayoa Ramirez | D106: 17206.72 | E106: =D106/$D$6 -> 2306.5308 | F106: 46006 | G106: Cancelado | H106: =IF(OR(G106="Sin pagar",G106="Pagar"),NETWORKDAYS($E$4,F106,'Festivos Guatemala'!$A$3:$A$15),0) -> 0 | I106: =NETWORKDAYS($E$4,F106,'Festivos Guatemala'!$A$3:$A$15) -> 11 | J106: =H106 -> 0
B107: Bibank | C107: Jessica Patricia Vasquez Gonzalez | D107: 48042.88 | E107: =D107/$D$6 -> 6440.0643 | F107: 46006 | G107: Cancelado | H107: =IF(OR(G107="Sin pagar",G107="Pagar"),NETWORKDAYS($E$4,F107,'Festivos Guatemala'!$A$3:$A$15),0) -> 0 | I107: =NETWORKDAYS($E$4,F107,'Festivos Guatemala'!$A$3:$A$15) -> 11 | J107: =H107 -> 0
B108: Rural | C108: David Enrique Herman Juarez | D108: 3906.98 | E108: =D108/$D$6 -> 523.72386 | F108: 46006 | G108: Cancelado | H108: =IF(OR(G108="Sin pagar",G108="Pagar"),NETWORKDAYS($E$4,F108,'Festivos Guatemala'!$A$3:$A$15),0) -> 0 | I108: =NETWORKDAYS($E$4,F108,'Festivos Guatemala'!$A$3:$A$15) -> 11 | J108: =H108 -> 0
B109: Bibank | C109: Jorge Benjamin Granados Anderson- Aguinaldo ajuste | D109: 5493.13 | E109: =D109/$D$6 -> 736.3445 | F109: 46014 | G109: Cancelado | H109: =IF(OR(G109="Sin pagar",G109="Pagar"),NETWORKDAYS($E$4,F109,'Festivos Guatemala'!$A$3:$A$15),0) -> 0 | I109: =NETWORKDAYS($E$4,F109,'Festivos Guatemala'!$A$3:$A$15) -> 17 | J109: =H109 -> 0
C110: NÓMINA SAFEGUARD | D110: =SUBTOTAL(9,D111:D118) -> 185904.44 | E110: =SUBTOTAL(9,E111:E118) -> 24920.166
B111: Bibank | C111: Rudy Renato Chic Arriaza | D111: 10855.64 | E111: =D111/$D$6 -> 1455.1796 | F111: 46017 | G111: Cancelado | H111: =IF(OR(G111="Sin pagar",G111="Pagar"),NETWORKDAYS($E$4,F111,'Festivos Guatemala'!$A$3:$A$15),0) -> 0 | I111: =NETWORKDAYS($E$4,F111,'Festivos Guatemala'!$A$3:$A$15) -> 18 | J111: =H111 -> 0
B112: Bibank | C112: Jorge Benjamin Granados Anderson | D112: 37726.22 | E112: =D112/$D$6 -> 5057.134 | F112: 46017 | G112: Cancelado | H112: =IF(OR(G112="Sin pagar",G112="Pagar"),NETWORKDAYS($E$4,F112,'Festivos Guatemala'!$A$3:$A$15),0) -> 0 | I112: =NETWORKDAYS($E$4,F112,'Festivos Guatemala'!$A$3:$A$15) -> 18 | J112: =H112 -> 0
B113: Bibank | C113: Carlos Raymundo Morales Santos | D113: 16287.9 | E113: =D113/$D$6 -> 2183.3646 | F113: 46017 | G113: Cancelado | H113: =IF(OR(G113="Sin pagar",G113="Pagar"),NETWORKDAYS($E$4,F113,'Festivos Guatemala'!$A$3:$A$15),0) -> 0 | I113: =NETWORKDAYS($E$4,F113,'Festivos Guatemala'!$A$3:$A$15) -> 18 | J113: =H113 -> 0
...

Sheet RECURSOS
B1: INGRESO
B2: MES | C2: CLIENTE | D2: FACTURA | E2: FEE
B3: Enero | C3: Energyzer | D3: 4258350666 | E3: 1708.86
B4: Enero | C4: Global for children | D4: 1904100714 | E4: 125.43
B5: Febrero | C5: =+C4 -> Global for children | D5: 2820099227 | E5: 120.09
B6: Febrero | C6: =+C5 -> Global for children | D6: 4150543673 | E6: 155.11
B7: Febrero | C7: =+C3 -> Energyzer | D7: 2018594064 | E7: 1389.79
B8: Marzo | C8: =+C7 -> Energyzer | D8: 614157553 | E8: 1778.35
B9: Marzo | C9: Opportunity | D9: 1264599604 | E9: 75.06
B10: Marzo | C10: Kairos | D10: 112609088 | E10: 45.18
B11: Total ingresos operacionales | E11: =SUM(E3:E10) -> 5397.87
B13: COSTOS
B14: MES | C14: PROVEEDOR | D14: FACTURA | E14: VALOR
B15: Enero | C15: S&P | D15: 4640 | E15: 917.15
B16: Enero | C16: JUAN Y ARNOLDO | E16: 256 | F16: 2000
B17: Febrero | C17: =+C15 -> S&P | D17: 4641 | E17: 832.5
B18: Febrero | C18: =+C16 -> JUAN Y ARNOLDO | E18: =+E16 -> 256 | F18: 2000
B19: Marzo | C19: =+C17 -> S&P | D19: PENDIENTE | E19: 949.295 | H19: 120 | I19: =E18-H19 -> 136
B20: Marzo | C20: =+C18 -> JUAN Y ARNOLDO | D20: PENDIENTE | E20: =+E18 -> 256 | F20: =+F18 -> 2000
B21: Marzo | C21: Representación legal | D21: PENDIENTE | E21: 217 | F21: 1700 | H21: =E21*7.91 -> 1716.47
B22: Total egresos operacionales | E22: =SUM(E15:E21) -> 3683.945
B24: Saldo | E24: =+E11-E22 -> 1713.925 | F24: =+E24*7.81 -> 13385.754

Sheet Flujo caja Abril
D1: 42400
D4: Fecha de Elaboración: | E4: 45385
C6: Tasa de cambio: | D6: 7.55
D7: ABRIL
D8: VALOR QTQ | E8: VALOR USD
C9: BANCOS | D9: =SUBTOTAL(9,D10:D11) -> 174210.98 | E9: =SUBTOTAL(9,E10:E11) -> 23074.302
C10: Bancos QTQ | D10: 173452.73 | E10: =D10/$D$6 -> 22973.872
C11: Bancos USD | D11: 758.2465 | E11: =D11/$D$6 -> 100.43
C12: CLIENTES | D12: =SUBTOTAL(9,D13:D16) -> 429182.71 | E12: =SUBTOTAL(9,E13:E16) -> 56845.393
C13: Client: Czarnikow- Sthepanie Rodriguez Lopez-TC 7.55 | D13: 46149.77 | E13: =D13/$D$6 -> 6112.5523
C14: Client:Energyzer-Ivan Chavez-Jerry García-Ronny Quan-TC 7.55 | D14: 362565.53 | E14: =D14/$D$6 -> 48021.924
C15: Client:Kairos-Ivan Chavez-Ruth Carolina Vasquez-TC 7.55 | D15: 7191.534 | E15: =D15/$D$6 -> 952.52106
C16: Client: Opportunity-Edlin Ivette Poitan-TC 7.55 | D16: 13275.885 | E16: =D16/$D$6 -> 1758.3954
C17: TOTAL INGRESOS | D17: =SUBTOTAL(9,D9:D16) -> 603393.69 | E17: =SUBTOTAL(9,E9:E16) -> 79919.694
B20: CUENTAS X PAGAR MES | D20: ABRIL
B21: Factura | C21: PROVEEDOR | D21: VALOR QTQ | E21: VALOR USD | F21: Fecha vencimiento | G21: Estado | J21: KPI
C22: SEGURIDAD IGSS | D22: =SUBTOTAL(9,D23:D24) -> 77479.56 | E22: =SUBTOTAL(9,E23:E24) -> 8065.8066
B23: 176206200 | C23: Pago planilla IGSS Febrero | D23: ='Caja QTQ'!H60+'Caja QTQ'!H61 -> 32463.39 | E23: =30448.42/$D$6 -> 4032.9033 | F23: 45392 | G23: Cancelado | H23: =IF(OR(G23="Sin pagar",G23="Pagar"),NETWORKDAYS($E$4,F23,'Festivos Guatemala'!$A$3:$A$15),0) -> 0 | I23: =NETWORKDAYS($E$4,F23,'Festivos Guatemala'!$A$3:$A$15) -> 6 | J23: =H23 -> 0
B24: 176206200 | C24: Pago planilla IGSS Marzo | D24: 45016.17 | E24: =30448.42/$D$6 -> 4032.9033 | F24: 45397 | G24: Cancelado | H24: =IF(OR(G24="Sin pagar",G24="Pagar"),NETWORKDAYS($E$4,F24,'Festivos Guatemala'!$A$3:$A$15),0) -> 0 | I24: =NETWORKDAYS($E$4,F24,'Festivos Guatemala'!$A$3:$A$15) -> 9 | J24: =H24 -> 0
C25: IMPUESTOS | D25: =SUBTOTAL(9,D26:D28) -> 18928.22 | E25: =SUBTOTAL(9,E26:E28) -> 2507.049 | J25: =H25 -> 0
C26: Declaraguate ISR Marzo | D26: 17191.61 | E26: =D26/$D$6 -> 2277.0344 | F26: 45394 | G26: Cancelado | H26: =IF(OR(G26="Sin pagar",G26="Pagar"),NETWORKDAYS($E$4,F26,'Festivos Guatemala'!$A$3:$A$15),0) -> 0 | I26: =NETWORKDAYS($E$4,F26,'Festivos Guatemala'!$A$3:$A$15) -> 8 | J26: =H26 -> 0
C27: ISR en concepto de la factura 4700 | D27: 1178.23 | E27: =D27/$D$6 -> 156.05695 | F27: 45394 | G27: Cancelado | H27: =IF(OR(G27="Sin pagar",G27="Pagar"),NETWORKDAYS($E$4,F27,'Festivos Guatemala'!$A$3:$A$15),0) -> 0 | I27: =NETWORKDAYS($E$4,F27,'Festivos Guatemala'!$A$3:$A$15) -> 8 | J27: =H27 -> 0
C28: Impuesto de Solidaridad (ISO) | D28: 558.38 | E28: =D28/$D$6 -> 73.957616 | F28: 45406 | G28: Cancelado | H28: =IF(OR(G28="Sin pagar",G28="Pagar"),NETWORKDAYS($E$4,F28,'Festivos Guatemala'!$A$3:$A$15),0) -> 0 | I28: =NETWORKDAYS($E$4,F28,'Festivos Guatemala'!$A$3:$A$15) -> 16 | J28: =H28 -> 0
C29: SERVICIOS PROFESIONALES -REPRESENTACIÓN LEGAL | D29: =SUBTOTAL(9,D30:D36) -> 3380 | E29: =SUBTOTAL(9,E30:E36) -> 447.68212 | J29: =H29 -> 0
C30: Servicios profesionales Juan-Servicios prestados- mes Febrero | D30: 840 | E30: =D30/$D$6 -> 111.25828 | F30: 45393 | G30: Cancelado | H30: =IF(OR(G30="Sin pagar",G30="Pagar"),NETWORKDAYS($E$4,F30,'Festivos Guatemala'!$A$3:$A$15),0) -> 0 | I30: =NETWORKDAYS($E$4,F30,'Festivos Guatemala'!$A$3:$A$15) -> 7 | J30: =H30 -> 0
C31: Servicios profesionales Juan-Servicios prestados-Marzo | D31: 840 | E31: =D31/$D$6 -> 111.25828 | F31: 45393 | G31: Cancelado | H31: =IF(OR(G31="Sin pagar",G31="Pagar"),NETWORKDAYS($E$4,F31,'Festivos Guatemala'!$A$3:$A$15),0) -> 0 | I31: =NETWORKDAYS($E$4,F31,'Festivos Guatemala'!$A$3:$A$15) -> 7 | J31: =H31 -> 0
B32: S/N | C32: 81% Gestión de representación legal 2024­-2027 | D32: 1700 | E32: =D32/$D$6 -> 225.16556 | F32: 45393 | G32: Cancelado | H32: =IF(OR(G32="Sin pagar",G32="Pagar"),NETWORKDAYS($E$4,F32,'Festivos Guatemala'!$A$3:$A$15),0) -> 0 | I32: =NETWORKDAYS($E$4,F32,'Festivos Guatemala'!$A$3:$A$15) -> 7 | J32: =H32 -> 0
B33: S/N | C33: Servicios profesionales Arnoldo prestados en Enero | D33: =1200*0 -> 0 | E33: =D33/$D$6 -> 0 | F33: 45412 | G33: Sin Pagar | H33: =IF(OR(G33="Sin pagar",G33="Pagar"),NETWORKDAYS($E$4,F33,'Festivos Guatemala'!$A$3:$A$15),0) -> 20 | I33: =NETWORKDAYS($E$4,F33,'Festivos Guatemala'!$A$3:$A$15) -> 20 | J33: =H33 -> 20
B34: S/N | C34: Servicios profesionales Arnoldo prestados en Febrero | D34: =1200*0 -> 0 | E34: =D34/$D$6 -> 0 | F34: 45412 | G34: Sin Pagar | H34: =IF(OR(G34="Sin pagar",G34="Pagar"),NETWORKDAYS($E$4,F34,'Festivos Guatemala'!$A$3:$A$15),0) -> 20 | I34: =NETWORKDAYS($E$4,F34,'Festivos Guatemala'!$A$3:$A$15) -> 20 | J34: =H34 -> 20
B35: S/N | C35: Servicios profesionales Arnoldo prestados en Marzo | D35: =1200*0 -> 0 | E35: =D35/$D$6 -> 0 | F35: 45412 | G35: Sin Pagar | H35: =IF(OR(G35="Sin pagar",G35="Pagar"),NETWORKDAYS($E$4,F35,'Festivos Guatemala'!$A$3:$A$15),0) -> 20 | I35: =NETWORKDAYS($E$4,F35,'Festivos Guatemala'!$A$3:$A$15) -> 20 | J35: =H35 -> 20
B36: S/N | C36: Servicio cambios de socio | D36: =11200*0 -> 0 | E36: =D36/$D$6 -> 0 | F36: 45416 | G36: Sin Pagar | H36: =IF(OR(G36="Sin pagar",G36="Pagar"),NETWORKDAYS($E$4,F36,'Festivos Guatemala'!$A$3:$A$15),0) -> 23 | I36: =NETWORKDAYS($E$4,F36,'Festivos Guatemala'!$A$3:$A$15) -> 23 | J36: =H36 -> 23
C37: PÓLIZAS Y SEGUROS | D37: =SUBTOTAL(9,D38:D43) -> 6631.1885 | E37: =SUBTOTAL(9,E38:E43) -> 878.30311
C38: Póliza de vida Ivan Estuardo Chavez Morales-USD-Póliza Vida | D38: =E38*$D$6 -> 1958.9985 | E38: 259.47 | F38: 45405 | G38: Cancelado | H38: =IF(OR(G38="Sin pagar",G38="Pagar"),NETWORKDAYS($E$4,F38,'Festivos Guatemala'!$A$3:$A$15),0) -> 0 | I38: =NETWORKDAYS($E$4,F38,'Festivos Guatemala'!$A$3:$A$15) -> 15 | J38: =H38 -> 0
C39: Poliza de vida Rony Eduardo Quan Lam-USD-Póliza Vida | D39: =E39*$D$6 -> 415.7785 | E39: 55.07 | F39: 45405 | G39: Cancelado | H39: =IF(OR(G39="Sin pagar",G39="Pagar"),NETWORKDAYS($E$4,F39,'Festivos Guatemala'!$A$3:$A$15),0) -> 0 | I39: =NETWORKDAYS($E$4,F39,'Festivos Guatemala'!$A$3:$A$15) -> 15 | J39: =H39 -> 0
C40: Poliza de vida Jerry García Carillo -USD-Póliza Vida | D40: =E40*$D$6 -> 1550.2415 | E40: 205.33 | F40: 45405 | G40: Cancelado | H40: =IF(OR(G40="Sin pagar",G40="Pagar"),NETWORKDAYS($E$4,F40,'Festivos Guatemala'!$A$3:$A$15),0) -> 0 | I40: =NETWORKDAYS($E$4,F40,'Festivos Guatemala'!$A$3:$A$15) -> 15 | J40: =H40 -> 0
C41: Póliza de vida Ivan Estuardo Chavez Morales-QTZ-GM | D41: 888.15 | E41: =D41/$D$6 -> 117.63576 | F41: 45405 | G41: Cancelado | H41: =IF(OR(G41="Sin pagar",G41="Pagar"),NETWORKDAYS($E$4,F41,'Festivos Guatemala'!$A$3:$A$15),0) -> 0 | I41: =NETWORKDAYS($E$4,F41,'Festivos Guatemala'!$A$3:$A$15) -> 15 | J41: =H41 -> 0
C42: Poliza de vida Rony Eduardo Quan Lam-QTQ-GM | D42: 903.72 | E42: =D42/$D$6 -> 119.69801 | F42: 45405 | G42: Cancelado | H42: =IF(OR(G42="Sin pagar",G42="Pagar"),NETWORKDAYS($E$4,F42,'Festivos Guatemala'!$A$3:$A$15),0) -> 0 | I42: =NETWORKDAYS($E$4,F42,'Festivos Guatemala'!$A$3:$A$15) -> 15 | J42: =H42 -> 0
C43: Poliza de vida Jerry García Carillo -QTQ-GM | D43: 914.3 | E43: =D43/$D$6 -> 121.09934 | F43: 45405 | G43: Cancelado | H43: =IF(OR(G43="Sin pagar",G43="Pagar"),NETWORKDAYS($E$4,F43,'Festivos Guatemala'!$A$3:$A$15),0) -> 0 | I43: =NETWORKDAYS($E$4,F43,'Festivos Guatemala'!$A$3:$A$15) -> 15 | J43: =H43 -> 0
C44: COBROS ENTRE SUCURSALES | D44: =SUBTOTAL(9,D45:D49) -> 0 | E44: =SUBTOTAL(9,E45:E49) -> 0
B45: 4640 | C45: Cobro S&P a sucursal Guatemala -Enero | D45: =E45*$D$6 -> 0 | E45: =917.15*0 -> 0 | F45: 45411 | G45: Sin Pagar | H45: =IF(OR(G45="Sin pagar",G45="Pagar"),NETWORKDAYS($E$4,F45,'Festivos Guatemala'!$A$3:$A$15),0) -> 19 | I45: =NETWORKDAYS($E$4,F45,'Festivos Guatemala'!$A$3:$A$15) -> 19 | J45: =H45 -> 19
B46: 4641 | C46: Cobro S&P a sucursal Guatemala -febrero | D46: =E46*$D$6 -> 0 | E46: =832.5*0 -> 0 | F46: 45411 | G46: Sin Pagar | H46: =IF(OR(G46="Sin pagar",G46="Pagar"),NETWORKDAYS($E$4,F46,'Festivos Guatemala'!$A$3:$A$15),0) -> 19 | I46: =NETWORKDAYS($E$4,F46,'Festivos Guatemala'!$A$3:$A$15) -> 19 | J46: =H46 -> 19
B47: 4700 | C47: Cobro S&P a sucursal Guatemala -Marzo | D47: =E47*$D$6 -> 0 | E47: =1009.3*0 -> 0 | F47: 45433 | G47: Sin Pagar | H47: =IF(OR(G47="Sin pagar",G47="Pagar"),NETWORKDAYS($E$4,F47,'Festivos Guatemala'!$A$3:$A$15),0) -> 35 | I47: =NETWORKDAYS($E$4,F47,'Festivos Guatemala'!$A$3:$A$15) -> 35 | J47: =H47 -> 35
B48: 4707 | C48: Cobro S&P a sucursal Guatemala -Marzo | D48: =E48*$D$6 -> 0 | E48: =1000*0 -> 0 | F48: 45438 | G48: Sin Pagar | H48: =IF(OR(G48="Sin pagar",G48="Pagar"),NETWORKDAYS($E$4,F48,'Festivos Guatemala'!$A$3:$A$15),0) -> 38 | I48: =NETWORKDAYS($E$4,F48,'Festivos Guatemala'!$A$3:$A$15) -> 38 | J48: =H48 -> 38
B49: 4776 | C49: Cobro S&P a sucursal Guatemala -Abril | D49: =E49*$D$6 -> 0 | E49: =1521.5*0 -> 0 | F49: 45435 | G49: Sin Pagar | H49: =IF(OR(G49="Sin pagar",G49="Pagar"),NETWORKDAYS($E$4,F49,'Festivos Guatemala'!$A$3:$A$15),0) -> 37 | I49: =NETWORKDAYS($E$4,F49,'Festivos Guatemala'!$A$3:$A$15) -> 37 | J49: =H49 -> 37
C50: TIQUETES AÉREOS , HOTELES | D50: =SUBTOTAL(9,D51:D52) -> 0 | E50: =SUBTOTAL(9,E51:E52) -> 0
C51: Tiquetes Ricardo y Eduard Visita Sucursal Guatemala | D51: =(((4000000/3901.51)*$D$6)+7000)*0 -> 0 | E51: =D51/D6 -> 0 | F51: 45412 | G51: Cancelado | H51: =IF(OR(G51="Sin pagar",G51="Pagar"),NETWORKDAYS($E$4,F51,'Festivos Guatemala'!$A$3:$A$15),0) -> 0 | I51: =NETWORKDAYS($E$4,F51,'Festivos Guatemala'!$A$3:$A$15) -> 20 | J51: =H51 -> 0
C52: Hoteles Ricardo y Eduard Visita Sucursal Guatemala | D52: =(((4000000/3901.51)*$D$6)+7000)*0 -> 0 | E52: =D52/D6 -> 0 | F52: 45412 | G52: Cancelado | H52: =IF(OR(G52="Sin pagar",G52="Pagar"),NETWORKDAYS($E$4,F52,'Festivos Guatemala'!$A$3:$A$15),0) -> 0 | I52: =NETWORKDAYS($E$4,F52,'Festivos Guatemala'!$A$3:$A$15) -> 20 | J52: =H52 -> 0
C53: COSTOS FINANCIEROS | D53: =SUBTOTAL(9,D54:D54) -> 0 | E53: =SUBTOTAL(9,E54:E54) -> 0
C54: Cobro emisión estado cuenta | D54: =(15*2*4)*0 -> 0 | E54: =D54/$D$6 -> 0 | F54: 45412 | G54: Sin Pagar | H54: =IF(OR(G54="Sin pagar",G54="Pagar"),NETWORKDAYS($E$4,F54,'Festivos Guatemala'!$A$3:$A$15),0) -> 20 | I54: =NETWORKDAYS($E$4,F54,'Festivos Guatemala'!$A$3:$A$15) -> 20 | J54: =H54 -> 20
C55: NÓMINAS | D55: =SUBTOTAL(9,D56:D61) -> 253741.31 | E55: =SUBTOTAL(9,E60:E61) -> 2134.5245
C56: Stephanie Rodriguez Lopez-RF-Czarnikow-CC002 | D56: 28242.02 | E56: =D56/$D$6 -> 3740.6649 | F56: 45411 | G56: Cancelado | H56: =IF(OR(G56="Sin pagar",G56="Pagar"),NETWORKDAYS($E$4,F56,'Festivos Guatemala'!$A$3:$A$15),0) -> 0 | I56: =NETWORKDAYS($E$4,F56,'Festivos Guatemala'!$A$3:$A$15) -> 19 | J56: =H56 -> 0
C57: Ivan Estuardo Chávez Morales-Energyzer-CC003 | D57: 24970.21 | E57: =D57/$D$6 -> 3307.3126 | F57: 45411 | G57: Cancelado | H57: =IF(OR(G57="Sin pagar",G57="Pagar"),NETWORKDAYS($E$4,F57,'Festivos Guatemala'!$A$3:$A$15),0) -> 0 | I57: =NETWORKDAYS($E$4,F57,'Festivos Guatemala'!$A$3:$A$15) -> 19 | J57: =H57 -> 0
C58: Jerry García-Energyzer-CC003 | D58: 79101.47 | E58: =D58/$D$6 -> 10477.016 | F58: 45411 | G58: Cancelado | H58: =IF(OR(G58="Sin pagar",G58="Pagar"),NETWORKDAYS($E$4,F58,'Festivos Guatemala'!$A$3:$A$15),0) -> 0 | I58: =NETWORKDAYS($E$4,F58,'Festivos Guatemala'!$A$3:$A$15) -> 19 | J58: =H58 -> 0
C59: Ronny Eduardo Quan Lam-Energyzer-CC003 | D59: 105311.95 | E59: =D59/$D$6 -> 13948.603 | F59: 45411 | G59: Cancelado | H59: =IF(OR(G59="Sin pagar",G59="Pagar"),NETWORKDAYS($E$4,F59,'Festivos Guatemala'!$A$3:$A$15),0) -> 0 | I59: =NETWORKDAYS($E$4,F59,'Festivos Guatemala'!$A$3:$A$15) -> 19 | J59: =H59 -> 0
C60: Edlin Ivette Ramos Poitan-Opportunnity | D60: 10382.76 | E60: =D60/$D$6 -> 1375.2 | F60: 45411 | G60: Cancelado | H60: =IF(OR(G60="Sin pagar",G60="Pagar"),NETWORKDAYS($E$4,F60,'Festivos Guatemala'!$A$3:$A$15),0) -> 0 | I60: =NETWORKDAYS($E$4,F60,'Festivos Guatemala'!$A$3:$A$15) -> 19 | J60: =H60 -> 0
C61: Ruth Carolina Vasquez Avelar de Rabanal-Kairos | D61: 5732.9 | E61: =D61/$D$6 -> 759.3245 | F61: 45411 | G61: Cancelado | H61: =IF(OR(G61="Sin pagar",G61="Pagar"),NETWORKDAYS($E$4,F61,'Festivos Guatemala'!$A$3:$A$15),0) -> 0 | I61: =NETWORKDAYS($E$4,F61,'Festivos Guatemala'!$A$3:$A$15) -> 19 | J61: =H61 -> 0
C62: REEMBOLSOS GASTOS | D62: =SUBTOTAL(9,D63:D65) -> 72655.93 | E62: =SUBTOTAL(9,E63:E65) -> 9623.302
C63: Ronny Quan. Energyzer-CC003 | D63: 12012.85 | E63: =D63/$D$6 -> 1591.106 | F63: 45411 | G63: Cancelado | H63: =IF(OR(G63="Sin pagar",G63="Pagar"),NETWORKDAYS($E$4,F63,'Festivos Guatemala'!$A$3:$A$15),0) -> 0 | I63: =NETWORKDAYS($E$4,F63,'Festivos Guatemala'!$A$3:$A$15) -> 19 | J63: =H63 -> 0
C64: Iván Estuardo Chávez Morales-Energyzer-CC003 | D64: 3707 | E64: =D64/$D$6 -> 490.99338 | F64: 45412 | G64: Cancelado | J64: =H64 -> 0
C65: Jerry García-Energyzer-CC003 | D65: 56936.08 | E65: =D65/$D$6 -> 7541.2026 | F65: 45412 | G65: Cancelado | J65: =H65 -> 0
C66: CELULARES | D66: =SUBTOTAL(9,D67:D67) -> 1497 | E66: =SUBTOTAL(9,E67:E67) -> 198.27815
C67: Mensualidad celulares empleados | D67: =499*3 -> 1497 | E67: =D67/$D$6 -> 198.27815 | F67: 45397 | G67: Cancelado | H67: =IF(OR(G67="Sin pagar",G67="Pagar"),NETWORKDAYS($E$4,F67,'Festivos Guatemala'!$A$3:$A$15),0) -> 0 | I67: =NETWORKDAYS($E$4,F67,'Festivos Guatemala'!$A$3:$A$15) -> 9 | J67: =H67 -> 0
C68: IMPREVISTO | D68: =SUBTOTAL(9,D69:D70) -> 408 | E68: =SUBTOTAL(9,E69:E70) -> 54.039735
C69: Gastos de movilización y trámites varios Juan mes Marzo | D69: 193 | E69: =D69/$D$6 -> 25.562914 | F69: 45393 | G69: Cancelado | H69: =IF(OR(G69="Sin pagar",G69="Pagar"),NETWORKDAYS($E$4,F69,'Festivos Guatemala'!$A$3:$A$15),0) -> 0 | I69: =NETWORKDAYS($E$4,F69,'Festivos Guatemala'!$A$3:$A$15) -> 7 | J69: =H69 -> 0
C70: Envío documentos Juan | D70: 215 | E70: =D70/$D$6 -> 28.476821 | F70: 45397 | G70: Cancelado | H70: =IF(OR(G70="Sin pagar",G70="Pagar"),NETWORKDAYS($E$4,F70,'Festivos Guatemala'!$A$3:$A$15),0) -> 0 | I70: =NETWORKDAYS($E$4,F70,'Festivos Guatemala'!$A$3:$A$15) -> 9 | J70: =H70 -> 0
C71: TOTAL EGRESOS | D71: =SUBTOTAL(9,D22:D69) -> 434506.21 | E71: =SUBTOTAL(9,E22:E69) -> 55354.104
C73: SALDO | D73: =D17-D71 -> 168887.48 | E73: =E17-E71 -> 24565.59
C74: % | D74: =IF($D$17=0,0,D73/$D$17) -> 0.279896 | E74: =IF($E$17=0,0,E73/$E$17) -> 0.30737843
C78: Fecha Inicial | D78: Fecha Final | E78: Valor VALOR QTQ | F78: Valor VALOR USD
C79: 45383 | D79: 45389 | E79: =SUMIFS($D$21:$D$71,$F$21:$F$71,">="&C79,$F$21:$F$71,"<="&D79,$G$21:$G$71,$D$94) -> 0 | F79: =SUMIFS($E$21:$E$71,$F$21:$F$71,">="&C79,$F$21:$F$71,"<="&D79,$G$21:$G$71,$D$94) -> 0
C80: 45390 | D80: 45396 | E80: =SUMIFS($D$21:$D$71,$F$21:$F$71,">="&C80,$F$21:$F$71,"<="&D80,$G$21:$G$71,$D$94) -> 0 | F80: =SUMIFS($E$21:$E$71,$F$21:$F$71,">="&C80,$F$21:$F$71,"<="&D80,$G$21:$G$71,$D$94) -> 0
C81: 45397 | D81: 45403 | E81: =SUMIFS($D$21:$D$71,$F$21:$F$71,">="&C81,$F$21:$F$71,"<="&D81,$G$21:$G$71,$D$94) -> 0 | F81: =SUMIFS($E$21:$E$71,$F$21:$F$71,">="&C81,$F$21:$F$71,"<="&D81,$G$21:$G$71,$D$94) -> 0
C82: 45404 | D82: 45410 | E82: =SUMIFS($D$21:$D$71,$F$21:$F$71,">="&C82,$F$21:$F$71,"<="&D82,$G$21:$G$71,$D$94) -> 0 | F82: =SUMIFS($E$21:$E$71,$F$21:$F$71,">="&C82,$F$21:$F$71,"<="&D82,$G$21:$G$71,$D$94) -> 0
C83: 45411 | D83: 45412 | E83: =SUMIFS($D$21:$D$71,$F$21:$F$71,">="&C83,$F$21:$F$71,"<="&D83,$G$21:$G$71,$D$94) -> 0 | F83: =SUMIFS($E$21:$E$71,$F$21:$F$71,">="&C83,$F$21:$F$71,"<="&D83,$G$21:$G$71,$D$94) -> 0
C84: 45413 | D84: 45443 | E84: =SUMIFS($D$21:$D$71,$F$21:$F$71,">="&C84,$F$21:$F$71,"<="&D84,$G$21:$G$71,$D$94) -> 0 | F84: =SUMIFS($E$21:$E$71,$F$21:$F$71,">="&C84,$F$21:$F$71,"<="&D84,$G$21:$G$71,$D$94) -> 0
C85: TOTAL EGRESOS | E85: =SUM(E79:E84) -> 0 | F85: =SUM(F79:F84) -> 0
C88: Bancos | E88: =$D$9 -> 174210.98 | F88: =$E$9 -> 23074.302
C89: Gastos y costos Periodo 15 al 21 abril Planilla y declaraguate | E89: =SUM(E79:E81) -> 0 | F89: =SUM(F79:F81) -> 0
C90: Saldo | E90: =E88-E89 -> 174210.98 | F90: =F88-F89 -> 23074.302
D93: Cancelado | E93: =SUMIFS($D$21:$D$71,$F$21:$F$71,">="&C79,$F$21:$F$71,"<="&D84,$G$21:$G$71,$D$93) -> 434721.21 | F93: =SUMIFS($E$21:$E$71,$F$21:$F$71,">="&C79,$F$21:$F$71,"<="&D84,$G$21:$G$71,$D$93) -> 55382.581
D94: Sin Pagar | E94: =SUMIFS($D$21:$D$71,$F$21:$F$71,">="&C79,$F$21:$F$71,"<="&D84,$G$21:$G$71,$D$94) -> 0 | F94: =SUMIFS($E$21:$E$71,$F$21:$F$71,">="&C79,$F$21:$F$71,"<="&D84,$G$21:$G$71,$D$94) -> 0
D95: Total Egresos | E95: =SUM(E93:E94) -> 434721.21 | F95: =SUM(F93:F94) -> 55382.581
D96: Validación | E96: =E95-D71 -> 215 | F96: =F95-E71 -> 28.476821

Sheet Flujo caja Mayo
D1: 42400
D4: Fecha de Elaboración: | E4: 45413
C6: Tasa de cambio: | D6: 7.88
D7: ABRIL
D8: VALOR QTQ | E8: VALOR USD
C9: BANCOS | D9: =SUBTOTAL(9,D10:D11) -> 148167.93 | E9: =SUBTOTAL(9,E10:E11) -> 18803.037
C10: Bancos QTQ | D10: ='Caja QTQ'!$H$83-20720 -> 148157.29 | E10: =D10/$D$6 -> 18801.687
C11: Bancos USD | D11: ='Caja USD'!$H$31*'Flujo caja Mayo'!$D$6 -> 10.638 | E11: =D11/$D$6 -> 1.35
C12: CLIENTES | D12: =SUBTOTAL(9,D13:D16) -> 330738.31 | E12: =SUBTOTAL(9,E13:E16) -> 41971.867
C13: Client: Czarnikow- Sthepanie Rodriguez Lopez-TC 7.55 | D13: 41146.97 | E13: =D13/$D$6 -> 5221.6967
C14: Client:Energyzer-Ivan Chavez-Jerry García-Ronny Quan-TC 7.55 | D14: ='Diferencia en cambio'!$I$17 -> 269107.6 | E14: =D14/$D$6 -> 34150.711
C15: Client:Kairos-Ivan Chavez-Ruth Carolina Vasquez-TC 7.55 | D15: ='Diferencia en cambio'!I18 -> 7197.2643 | E15: =D15/$D$6 -> 913.35841
C16: Client: Opportunity-Edlin Ivette Poitan-TC 7.55 | D16: ='Diferencia en cambio'!$I$19 -> 13286.476 | E16: =D16/$D$6 -> 1686.101
C17: TOTAL INGRESOS | D17: =SUBTOTAL(9,D9:D16) -> 478906.24 | E17: =SUBTOTAL(9,E9:E16) -> 60774.903
B20: CUENTAS X PAGAR MES | D20: ABRIL
B21: Factura | C21: PROVEEDOR | D21: VALOR QTQ | E21: VALOR USD | F21: Fecha vencimiento | G21: Estado | J21: KPI
C22: SEGURIDAD IGSS | D22: =SUBTOTAL(9,D23:D23) -> 48442.26 | E22: =SUBTOTAL(9,E23:E23) -> 3864.0127
B23: 176206200 | C23: Pago planilla IGSS Abril | D23: 48442.26 | E23: =30448.42/$D$6 -> 3864.0127 | F23: 45426 | G23: Cancelado | H23: =IF(OR(G23="Sin pagar",G23="Pagar"),NETWORKDAYS($E$4,F23,'Festivos Guatemala'!$A$3:$A$15),0) -> 0 | I23: =NETWORKDAYS($E$4,F23,'Festivos Guatemala'!$A$3:$A$15) -> 10 | J23: =H23 -> 0
C24: IMPUESTOS | D24: =SUBTOTAL(9,D25:D27) -> 17579.69 | E24: =SUBTOTAL(9,E25:E27) -> 2230.9251 | J24: =H24 -> 0
B25: 42629341546 | C25: Declaraguate ISR Abril | D25: 15808 | E25: =D25/$D$6 -> 2006.0914 | F25: 45426 | G25: Cancelado | H25: =IF(OR(G25="Sin pagar",G25="Pagar"),NETWORKDAYS($E$4,F25,'Festivos Guatemala'!$A$3:$A$15),0) -> 0 | I25: =NETWORKDAYS($E$4,F25,'Festivos Guatemala'!$A$3:$A$15) -> 10 | J25: =H25 -> 0
B26: 426295952621 | C26: Declaraguate ISR Abril | D26: 1771.69 | E26: =D26/$D$6 -> 224.83376 | F26: 45426 | G26: Cancelado | H26: =IF(OR(G26="Sin pagar",G26="Pagar"),NETWORKDAYS($E$4,F26,'Festivos Guatemala'!$A$3:$A$15),0) -> 0 | I26: =NETWORKDAYS($E$4,F26,'Festivos Guatemala'!$A$3:$A$15) -> 10 | J26: =H26 -> 0
B27: 42780261927 | C27: Declaraguate IVA mes de abril | D27: 0 | E27: =D27/$D$6 -> 0 | F27: 45443 | G27: Cancelado | H27: =IF(OR(G27="Sin pagar",G27="Pagar"),NETWORKDAYS($E$4,F27,'Festivos Guatemala'!$A$3:$A$15),0) -> 0 | I27: =NETWORKDAYS($E$4,F27,'Festivos Guatemala'!$A$3:$A$15) -> 23 | J27: =H27 -> 0
C28: SERVICIOS PROFESIONALES -REPRESENTACIÓN LEGAL | D28: =SUBTOTAL(9,D29:D34) -> 5640 | E28: =SUBTOTAL(9,E29:E34) -> 715.73604 | J28: =H28 -> 0
C29: Servicios profesionales Juan-Servicios prestados-Abril | D29: 840 | E29: =D29/$D$6 -> 106.59898 | F29: 45420 | G29: Cancelado | H29: =IF(OR(G29="Sin pagar",G29="Pagar"),NETWORKDAYS($E$4,F29,'Festivos Guatemala'!$A$3:$A$15),0) -> 0 | I29: =NETWORKDAYS($E$4,F29,'Festivos Guatemala'!$A$3:$A$15) -> 6 | J29: =H29 -> 0
B30: 790 | C30: Servicios profesionales Arnoldo prestados en Enero | D30: =1200 -> 1200 | E30: =D30/$D$6 -> 152.28426 | F30: 45428 | G30: Cancelado | H30: =IF(OR(G30="Sin pagar",G30="Pagar"),NETWORKDAYS($E$4,F30,'Festivos Guatemala'!$A$3:$A$15),0) -> 0 | I30: =NETWORKDAYS($E$4,F30,'Festivos Guatemala'!$A$3:$A$15) -> 12 | J30: =H30 -> 0
B31: 780 | C31: Servicios profesionales Arnoldo prestados en Febrero | D31: =1200 -> 1200 | E31: =D31/$D$6 -> 152.28426 | F31: 45428 | G31: Cancelado | H31: =IF(OR(G31="Sin pagar",G31="Pagar"),NETWORKDAYS($E$4,F31,'Festivos Guatemala'!$A$3:$A$15),0) -> 0 | I31: =NETWORKDAYS($E$4,F31,'Festivos Guatemala'!$A$3:$A$15) -> 12 | J31: =H31 -> 0
B32: 830 | C32: Servicios profesionales Arnoldo prestados en Marzo | D32: =1200 -> 1200 | E32: =D32/$D$6 -> 152.28426 | F32: 45428 | G32: Cancelado | H32: =IF(OR(G32="Sin pagar",G32="Pagar"),NETWORKDAYS($E$4,F32,'Festivos Guatemala'!$A$3:$A$15),0) -> 0 | I32: =NETWORKDAYS($E$4,F32,'Festivos Guatemala'!$A$3:$A$15) -> 12 | J32: =H32 -> 0
B33: 921 | C33: Servicios profesionales Arnoldo prestados en Abril | D33: =1200 -> 1200 | E33: =D33/$D$6 -> 152.28426 | F33: 45467 | G33: Cancelado | H33: =IF(OR(G33="Sin pagar",G33="Pagar"),NETWORKDAYS($E$4,F33,'Festivos Guatemala'!$A$3:$A$15),0) -> 0 | I33: =NETWORKDAYS($E$4,F33,'Festivos Guatemala'!$A$3:$A$15) -> 39 | J33: =H33 -> 0
B34: 922 | C34: Servicios profesionales Arnoldo prestados en Mayo | D34: =1200*0 -> 0 | E34: =D34/$D$6 -> 0 | F34: 45473 | G34: Cancelado | H34: =IF(OR(G34="Sin pagar",G34="Pagar"),NETWORKDAYS($E$4,F34,'Festivos Guatemala'!$A$3:$A$15),0) -> 0 | I34: =NETWORKDAYS($E$4,F34,'Festivos Guatemala'!$A$3:$A$15) -> 43 | J34: =H34 -> 0
C35: PÓLIZAS Y SEGUROS | D35: =SUBTOTAL(9,D36:D41) -> 7717.0456 | E35: =SUBTOTAL(9,E36:E41) -> 979.32051
B36: Valores previstos | C36: Póliza de vida Ivan Estuardo Chavez Morales-USD-Póliza Vida | D36: =E36*$D$6 -> 2044.6236 | E36: 259.47 | F36: 45440 | G36: Cancelado | H36: =IF(OR(G36="Sin pagar",G36="Pagar"),NETWORKDAYS($E$4,F36,'Festivos Guatemala'!$A$3:$A$15),0) -> 0 | I36: =NETWORKDAYS($E$4,F36,'Festivos Guatemala'!$A$3:$A$15) -> 20 | J36: =H36 -> 0
C37: Poliza de vida Rony Eduardo Quan Lam-USD-Póliza Vida | D37: =E37*$D$6 -> 433.9516 | E37: 55.07 | F37: 45440 | G37: Cancelado | H37: =IF(OR(G37="Sin pagar",G37="Pagar"),NETWORKDAYS($E$4,F37,'Festivos Guatemala'!$A$3:$A$15),0) -> 0 | I37: =NETWORKDAYS($E$4,F37,'Festivos Guatemala'!$A$3:$A$15) -> 20 | J37: =H37 -> 0
C38: Poliza de vida Jerry García Carillo -USD-Póliza Vida | D38: =E38*$D$6 -> 1618.0004 | E38: 205.33 | F38: 45440 | G38: Cancelado | H38: =IF(OR(G38="Sin pagar",G38="Pagar"),NETWORKDAYS($E$4,F38,'Festivos Guatemala'!$A$3:$A$15),0) -> 0 | I38: =NETWORKDAYS($E$4,F38,'Festivos Guatemala'!$A$3:$A$15) -> 20 | J38: =H38 -> 0
C39: Póliza de vida Ivan Estuardo Chavez Morales-QTQ-GM | D39: 888.15 | E39: =D39/$D$6 -> 112.70939 | F39: 45440 | G39: Cancelado | H39: =IF(OR(G39="Sin pagar",G39="Pagar"),NETWORKDAYS($E$4,F39,'Festivos Guatemala'!$A$3:$A$15),0) -> 0 | I39: =NETWORKDAYS($E$4,F39,'Festivos Guatemala'!$A$3:$A$15) -> 20 | J39: =H39 -> 0
C40: Poliza de vida Rony Eduardo Quan Lam-QTQ-GM | D40: 903.72 | E40: =D40/$D$6 -> 114.68528 | F40: 45440 | G40: Cancelado | H40: =IF(OR(G40="Sin pagar",G40="Pagar"),NETWORKDAYS($E$4,F40,'Festivos Guatemala'!$A$3:$A$15),0) -> 0 | I40: =NETWORKDAYS($E$4,F40,'Festivos Guatemala'!$A$3:$A$15) -> 20 | J40: =H40 -> 0
C41: Poliza de vida Jerry García Carillo -QTQ-GM-Claudia Marisol Mayorga Ayala | D41: 1828.6 | E41: =D41/$D$6 -> 232.05584 | F41: 45441 | G41: Cancelado | H41: =IF(OR(G41="Sin pagar",G41="Pagar"),NETWORKDAYS($E$4,F41,'Festivos Guatemala'!$A$3:$A$15),0) -> 0 | I41: =NETWORKDAYS($E$4,F41,'Festivos Guatemala'!$A$3:$A$15) -> 21 | J41: =H41 -> 0
C42: COBROS ENTRE SUCURSALES | D42: =SUBTOTAL(9,D43:D48) -> 0 | E42: =SUBTOTAL(9,E43:E48) -> 0
B43: 4640 | C43: Cobro S&P a sucursal Guatemala -Enero | D43: =E43*$D$6 -> 0 | E43: =917.15*0 -> 0 | F43: 45443 | G43: Cancelado | H43: =IF(OR(G43="Sin pagar",G43="Pagar"),NETWORKDAYS($E$4,F43,'Festivos Guatemala'!$A$3:$A$15),0) -> 0 | I43: =NETWORKDAYS($E$4,F43,'Festivos Guatemala'!$A$3:$A$15) -> 23 | J43: =H43 -> 0
B44: 4641 | C44: Cobro S&P a sucursal Guatemala -febrero | D44: =E44*$D$6 -> 0 | E44: =832.5*0 -> 0 | F44: 45443 | G44: Cancelado | H44: =IF(OR(G44="Sin pagar",G44="Pagar"),NETWORKDAYS($E$4,F44,'Festivos Guatemala'!$A$3:$A$15),0) -> 0 | I44: =NETWORKDAYS($E$4,F44,'Festivos Guatemala'!$A$3:$A$15) -> 23 | J44: =H44 -> 0
B45: 4700 | C45: Cobro S&P a sucursal Guatemala -Marzo | D45: =E45*$D$6 -> 0 | E45: =1009.3*0 -> 0 | F45: 45443 | G45: Cancelado | H45: =IF(OR(G45="Sin pagar",G45="Pagar"),NETWORKDAYS($E$4,F45,'Festivos Guatemala'!$A$3:$A$15),0) -> 0 | I45: =NETWORKDAYS($E$4,F45,'Festivos Guatemala'!$A$3:$A$15) -> 23 | J45: =H45 -> 0
B46: 4707 | C46: Cobro S&P a sucursal Guatemala -Marzo | D46: =E46*$D$6 -> 0 | E46: =1000*0 -> 0 | F46: 45443 | G46: Cancelado | H46: =IF(OR(G46="Sin pagar",G46="Pagar"),NETWORKDAYS($E$4,F46,'Festivos Guatemala'!$A$3:$A$15),0) -> 0 | I46: =NETWORKDAYS($E$4,F46,'Festivos Guatemala'!$A$3:$A$15) -> 23 | J46: =H46 -> 0
B47: 4776 | C47: Cobro S&P a sucursal Guatemala -Abril | D47: =E47*$D$6 -> 0 | E47: =1521.5*0 -> 0 | F47: 45473 | G47: Cancelado | H47: =IF(OR(G47="Sin pagar",G47="Pagar"),NETWORKDAYS($E$4,F47,'Festivos Guatemala'!$A$3:$A$15),0) -> 0 | I47: =NETWORKDAYS($E$4,F47,'Festivos Guatemala'!$A$3:$A$15) -> 43 | J47: =H47 -> 0
B48: 4838 | C48: Cobro S&P a sucursal Guatemala -Mayo | D48: =E48*$D$6 -> 0 | E48: =1153.36*0 -> 0 | F48: 45473 | G48: Cancelado | H48: =IF(OR(G48="Sin pagar",G48="Pagar"),NETWORKDAYS($E$4,F48,'Festivos Guatemala'!$A$3:$A$15),0) -> 0 | I48: =NETWORKDAYS($E$4,F48,'Festivos Guatemala'!$A$3:$A$15) -> 43 | J48: =H48 -> 0
C49: TIQUETES AÉREOS , HOTELES | D49: =SUBTOTAL(9,D50:D51) -> 0 | E49: =SUBTOTAL(9,E50:E51) -> 0
C50: Tiquetes Ricardo y Eduard Visita Sucursal Guatemala | D50: =(((4000000/3901.51)*$D$6))*0 -> 0 | E50: =D50/D6 -> 0 | F50: 45473 | G50: Cancelado | H50: =IF(OR(G50="Sin pagar",G50="Pagar"),NETWORKDAYS($E$4,F50,'Festivos Guatemala'!$A$3:$A$15),0) -> 0 | I50: =NETWORKDAYS($E$4,F50,'Festivos Guatemala'!$A$3:$A$15) -> 43 | J50: =H50 -> 0
C51: Hoteles Ricardo y Eduard Visita Sucursal Guatemala | D51: =(((4000000/3901.51)*$D$6))*0 -> 0 | E51: =D51/D6 -> 0 | F51: 45473 | G51: Cancelado | H51: =IF(OR(G51="Sin pagar",G51="Pagar"),NETWORKDAYS($E$4,F51,'Festivos Guatemala'!$A$3:$A$15),0) -> 0 | I51: =NETWORKDAYS($E$4,F51,'Festivos Guatemala'!$A$3:$A$15) -> 43 | J51: =H51 -> 0
C52: COSTOS FINANCIEROS | D52: =SUBTOTAL(9,D53:D53) -> 0 | E52: =SUBTOTAL(9,E53:E53) -> 0
C53: Cobro emisión estado cuenta | D53: =(15*2*4)*0 -> 0 | E53: =D53/$D$6 -> 0 | F53: 45442 | G53: Sin Pagar | H53: =IF(OR(G53="Sin pagar",G53="Pagar"),NETWORKDAYS($E$4,F53,'Festivos Guatemala'!$A$3:$A$15),0) -> 22 | I53: =NETWORKDAYS($E$4,F53,'Festivos Guatemala'!$A$3:$A$15) -> 22 | J53: =H53 -> 22
C54: NÓMINAS | D54: =SUBTOTAL(9,D55:D60) -> 208042.45 | E54: =SUBTOTAL(9,E55:E60) -> 26401.326
C55: Stephanie Rodriguez Lopez-RF-Czarnikow-CC002 | D55: 28242.02 | E55: =D55/$D$6 -> 3584.0127 | F55: 45440 | G55: Cancelado | H55: =IF(OR(G55="Sin pagar",G55="Pagar"),NETWORKDAYS($E$4,F55,'Festivos Guatemala'!$A$3:$A$15),0) -> 0 | I55: =NETWORKDAYS($E$4,F55,'Festivos Guatemala'!$A$3:$A$15) -> 20 | J55: =H55 -> 0
C56: Ivan Estuardo Chávez Morales-Energyzer-CC003 | D56: 24970.21 | E56: =D56/$D$6 -> 3168.8084 | F56: 45440 | G56: Cancelado | H56: =IF(OR(G56="Sin pagar",G56="Pagar"),NETWORKDAYS($E$4,F56,'Festivos Guatemala'!$A$3:$A$15),0) -> 0 | I56: =NETWORKDAYS($E$4,F56,'Festivos Guatemala'!$A$3:$A$15) -> 20 | J56: =H56 -> 0
C57: Jerry García-Energyzer-CC003 | D57: 54108.45 | E57: =D57/$D$6 -> 6866.5546 | F57: 45440 | G57: Cancelado | H57: =IF(OR(G57="Sin pagar",G57="Pagar"),NETWORKDAYS($E$4,F57,'Festivos Guatemala'!$A$3:$A$15),0) -> 0 | I57: =NETWORKDAYS($E$4,F57,'Festivos Guatemala'!$A$3:$A$15) -> 20 | J57: =H57 -> 0
C58: Ronny Eduardo Quan Lam-Energyzer-CC003 | D58: 84606.11 | E58: =D58/$D$6 -> 10736.816 | F58: 45440 | G58: Cancelado | H58: =IF(OR(G58="Sin pagar",G58="Pagar"),NETWORKDAYS($E$4,F58,'Festivos Guatemala'!$A$3:$A$15),0) -> 0 | I58: =NETWORKDAYS($E$4,F58,'Festivos Guatemala'!$A$3:$A$15) -> 20 | J58: =H58 -> 0
C59: Edlin Ivette Ramos Poitan-Opportunnity | D59: 10382.76 | E59: =D59/$D$6 -> 1317.6091 | F59: 45440 | G59: Cancelado | H59: =IF(OR(G59="Sin pagar",G59="Pagar"),NETWORKDAYS($E$4,F59,'Festivos Guatemala'!$A$3:$A$15),0) -> 0 | I59: =NETWORKDAYS($E$4,F59,'Festivos Guatemala'!$A$3:$A$15) -> 20 | J59: =H59 -> 0
C60: Ruth Carolina Vasquez Avelar de Rabanal-Kairos | D60: 5732.9 | E60: =D60/$D$6 -> 727.52538 | F60: 45440 | G60: Cancelado | H60: =IF(OR(G60="Sin pagar",G60="Pagar"),NETWORKDAYS($E$4,F60,'Festivos Guatemala'!$A$3:$A$15),0) -> 0 | I60: =NETWORKDAYS($E$4,F60,'Festivos Guatemala'!$A$3:$A$15) -> 20 | J60: =H60 -> 0
C61: REEMBOLSOS GASTOS | D61: =SUBTOTAL(9,D62:D66) -> 14301.086 | E61: =SUBTOTAL(9,E62:E66) -> 3225.9714
C62: Ronny Quan. Energyzer-CC003-USD | D62: =E62/$D$6 -> 182.00635 | E62: =1434.21 -> 1434.21 | F62: 45441 | G62: Cancelado | H62: =IF(OR(G62="Sin pagar",G62="Pagar"),NETWORKDAYS($E$4,F62,'Festivos Guatemala'!$A$3:$A$15),0) -> 0 | I62: =NETWORKDAYS($E$4,F62,'Festivos Guatemala'!$A$3:$A$15) -> 21 | J62: =H62 -> 0
C63: Jerry García-Energyzer-CC003-USD | D63: =E63/$D$6 -> 0 | E63: =1088.35*0 -> 0 | F63: 45448 | G63: Sin Pagar | H63: =IF(OR(G63="Sin pagar",G63="Pagar"),NETWORKDAYS($E$4,F63,'Festivos Guatemala'!$A$3:$A$15),0) -> 26 | I63: =NETWORKDAYS($E$4,F63,'Festivos Guatemala'!$A$3:$A$15) -> 26 | J63: =H63 -> 26
C64: Ronny Quan. Energyzer-CC003-QTQ | D64: 2376.61 | E64: =D64/$D$6 -> 301.60025 | F64: 45441 | G64: Cancelado | H64: =IF(OR(G64="Sin pagar",G64="Pagar"),NETWORKDAYS($E$4,F64,'Festivos Guatemala'!$A$3:$A$15),0) -> 0 | I64: =NETWORKDAYS($E$4,F64,'Festivos Guatemala'!$A$3:$A$15) -> 21 | J64: =H64 -> 0
C65: Jerry García-Energyzer-CC003-QTQ | D65: 3960.32 | E65: =D65/$D$6 -> 502.57868 | F65: 45441 | G65: Cancelado | H65: =IF(OR(G65="Sin pagar",G65="Pagar"),NETWORKDAYS($E$4,F65,'Festivos Guatemala'!$A$3:$A$15),0) -> 0 | I65: =NETWORKDAYS($E$4,F65,'Festivos Guatemala'!$A$3:$A$15) -> 21 | J65: =H65 -> 0
C66: Iván Estuardo Chávez Morales-Energyzer-CC003-QTQ | D66: 7782.15 | E66: =D66/$D$6 -> 987.58249 | F66: 45441 | G66: Cancelado | H66: =IF(OR(G66="Sin pagar",G66="Pagar"),NETWORKDAYS($E$4,F66,'Festivos Guatemala'!$A$3:$A$15),0) -> 0 | I66: =NETWORKDAYS($E$4,F66,'Festivos Guatemala'!$A$3:$A$15) -> 21 | J66: =H66 -> 0
C67: CELULARES | D67: =SUBTOTAL(9,D68:D68) -> 0 | E67: =SUBTOTAL(9,E68:E68) -> 0
C68: Mensualidad celulares empleados | D68: =499*3*0 -> 0 | E68: =D68/$D$6 -> 0 | F68: 45473 | G68: Sin Pagar | H68: =IF(OR(G68="Sin pagar",G68="Pagar"),NETWORKDAYS($E$4,F68,'Festivos Guatemala'!$A$3:$A$15),0) -> 43 | I68: =NETWORKDAYS($E$4,F68,'Festivos Guatemala'!$A$3:$A$15) -> 43 | J68: =H68 -> 43
C69: IMPREVISTO | D69: =SUBTOTAL(9,D70:D71) -> 0 | E69: =SUBTOTAL(9,E70:E71) -> 0
C70: Gastos de movilización y trámites varios Juan | D70: 0 | E70: =D70/$D$6 -> 0 | F70: 45443 | G70: Cancelado | H70: =IF(OR(G70="Sin pagar",G70="Pagar"),NETWORKDAYS($E$4,F70,'Festivos Guatemala'!$A$3:$A$15),0) -> 0 | I70: =NETWORKDAYS($E$4,F70,'Festivos Guatemala'!$A$3:$A$15) -> 23 | J70: =H70 -> 0
C71: Envío documentos Juan | D71: 0 | E71: =D71/$D$6 -> 0 | F71: 45443 | G71: Cancelado | H71: =IF(OR(G71="Sin pagar",G71="Pagar"),NETWORKDAYS($E$4,F71,'Festivos Guatemala'!$A$3:$A$15),0) -> 0 | I71: =NETWORKDAYS($E$4,F71,'Festivos Guatemala'!$A$3:$A$15) -> 23 | J71: =H71 -> 0
C72: TOTAL EGRESOS | D72: =SUBTOTAL(9,D22:D71) -> 301722.53 | E72: =SUBTOTAL(9,E22:E71) -> 37417.292
C74: SALDO | D74: =D17-D72 -> 177183.71 | E74: =E17-E72 -> 23357.611
C75: % | D75: =IF($D$17=0,0,D74/$D$17) -> 0.36997577 | E75: =IF($E$17=0,0,E74/$E$17) -> 0.38432988
C79: Fecha Inicial | D79: Fecha Final | E79: Valor VALOR QTQ | F79: Valor VALOR USD
C80: 45413 | D80: 45417 | E80: =SUMIFS($D$21:$D$72,$F$21:$F$72,">="&C80,$F$21:$F$72,"<="&D80,$G$21:$G$72,$D$91) -> 0 | F80: =SUMIFS($E$21:$E$72,$F$21:$F$72,">="&C80,$F$21:$F$72,"<="&D80,$G$21:$G$72,$D$91) -> 0
C81: 45418 | D81: 45425 | E81: =SUMIFS($D$21:$D$72,$F$21:$F$72,">="&C81,$F$21:$F$72,"<="&D81,$G$21:$G$72,$D$91) -> 0 | F81: =SUMIFS($E$21:$E$72,$F$21:$F$72,">="&C81,$F$21:$F$72,"<="&D81,$G$21:$G$72,$D$91) -> 0
C82: 45426 | D82: 45431 | E82: =SUMIFS($D$21:$D$72,$F$21:$F$72,">="&C82,$F$21:$F$72,"<="&D82,$G$21:$G$72,$D$91) -> 0 | F82: =SUMIFS($E$21:$E$72,$F$21:$F$72,">="&C82,$F$21:$F$72,"<="&D82,$G$21:$G$72,$D$91) -> 0
C83: 45432 | D83: 45438 | E83: =SUMIFS($D$21:$D$72,$F$21:$F$72,">="&C83,$F$21:$F$72,"<="&D83,$G$21:$G$72,$D$91) -> 0 | F83: =SUMIFS($E$21:$E$72,$F$21:$F$72,">="&C83,$F$21:$F$72,"<="&D83,$G$21:$G$72,$D$91) -> 0
C84: 45439 | D84: 45443 | E84: =SUMIFS($D$21:$D$72,$F$21:$F$72,">="&C84,$F$21:$F$72,"<="&D84,$G$21:$G$72,$D$91) -> 0 | F84: =SUMIFS($E$21:$E$72,$F$21:$F$72,">="&C84,$F$21:$F$72,"<="&D84,$G$21:$G$72,$D$91) -> 0
C85: TOTAL EGRESOS | E85: =SUM(E80:E84) -> 0 | F85: =SUM(F80:F84) -> 0
D90: Cancelado | E90: =SUMIFS($D$21:$D$76,$F$21:$F$76,">="&C80,$F$21:$F$76,"<="&D84,$G$21:$G$76,$D$90)+1200 -> 301722.53 | F90: =SUMIFS($E$21:$E$76,$F$21:$F$76,">="&C80,$F$21:$F$76,"<="&D84,$G$21:$G$76,$D$90) -> 37265.008
D91: Sin Pagar | E91: =SUMIFS($D$21:$D$76,$F$21:$F$76,">="&C80,$F$21:$F$76,"<="&D84,$G$21:$G$76,$D$91) -> 0 | F91: =SUMIFS($E$21:$E$76,$F$21:$F$76,">="&C80,$F$21:$F$76,"<="&D84,$G$21:$G$76,$D$91) -> 0
D92: Total Egresos | E92: =SUM(E90:E91) -> 301722.53 | F92: =SUM(F90:F91) -> 37265.008
D93: Validación | E93: =E92-D72 -> 0 | F93: =F92-E72 -> -152.28426
E98: 177183.35
E99: =D74-E98 -> 0.35605482 | F99: =E99/D6 -> 0.045184622

Sheet Flujo caja Junio 
D1: 42400
D4: Fecha de Elaboración: | E4: 45447
C6: Tasa de cambio: | D6: 7.55
D7: ABRIL
D8: VALOR QTQ | E8: VALOR USD
C9: BANCOS | D9: =SUBTOTAL(9,D10:D12) -> 229471.41 | E9: =SUBTOTAL(9,E10:E12) -> 30393.564
C10: Bancos QTQ | D10: ='Caja QTQ'!$H$111+43089.5890499999 -> 220272.94 | E10: =D10/$D$6 -> 29175.224
C11: Bancos USD | D11: ='Caja USD'!H40*$D$6 -> 981.4245 | E11: =D11/$D$6 -> 129.99
C12: Devolución de Dinero Ivan Estuardo Chavez | D12: ='Caja USD'!$D$47*D6 -> 8217.0425 | E12: =D12/$D$6 -> 1088.35
C13: CLIENTES | D13: =SUBTOTAL(9,D14:D18) -> 450741.79 | E13: =SUBTOTAL(9,E14:E18) -> 59675.833
C14: Client: Czarnikow- Sthepanie Rodriguez Lopez-TC 7.55 | D14: 41200.42 | E14: =D14/7.55 -> 5457.0093
C15: Client:Energyzer-Ivan Chavez-Jerry García-Ronny Quan-TC 7.55 | D15: 341220.02 | E15: =D15/7.55 -> 45194.705
C16: Client:Kairos-Ivan Chavez-Ruth Carolina Vasquez-TC 7.55 | D16: 9387.8072 | E16: =D16/7.55 -> 1243.4182
C17: Client: Opportunity-Edlin Ivette Poitan-TC 7.55 | D17: 15861.723 | E17: =D17/7.55 -> 2100.8905
C18: Client: NotableGrowth, Inc-TC 7.55 | D18: 43071.81 | E18: 5679.81
C19: TOTAL INGRESOS | D19: =SUBTOTAL(9,D9:D18) -> 680213.19 | E19: =SUBTOTAL(9,E9:E18) -> 90069.397
B22: CUENTAS X PAGAR MES | D22: ABRIL
B23: Factura | C23: PROVEEDOR | D23: VALOR QTQ | E23: VALOR USD | F23: Fecha vencimiento | G23: Estado | J23: KPI
C24: SEGURIDAD IGSS | D24: =SUBTOTAL(9,D25:D25) -> 39252.51 | E24: =SUBTOTAL(9,E25:E25) -> 4032.9033
B25: 176206200 | C25: Pago planilla IGSS Mayo | D25: 39252.51 | E25: =30448.42/$D$6 -> 4032.9033 | F25: 45456 | G25: Cancelado | H25: =IF(OR(G25="Sin pagar",G25="Pagar"),NETWORKDAYS($E$4,F25,'Festivos Guatemala'!$A$3:$A$15),0) -> 0 | I25: =NETWORKDAYS($E$4,F25,'Festivos Guatemala'!$A$3:$A$15) -> 8 | J25: =H25 -> 0
C26: IMPUESTOS | D26: =SUBTOTAL(9,D27:D29) -> 13238.19 | E26: =SUBTOTAL(9,E27:E29) -> 1753.4026 | J26: =H26 -> 0
B27: 42629341546 | C27: Declaraguate ISR Mayo | D27: 11895.04 | E27: =D27/$D$6 -> 1575.502 | F27: 45457 | G27: Cancelado | H27: =IF(OR(G27="Sin pagar",G27="Pagar"),NETWORKDAYS($E$4,F27,'Festivos Guatemala'!$A$3:$A$15),0) -> 0 | I27: =NETWORKDAYS($E$4,F27,'Festivos Guatemala'!$A$3:$A$15) -> 9 | J27: =H27 -> 0
B28: 426295952621 | C28: Declaraguate ISR Mayo facturación Col | D28: 1343.15 | E28: =D28/$D$6 -> 177.90066 | F28: 45457 | G28: Cancelado | H28: =IF(OR(G28="Sin pagar",G28="Pagar"),NETWORKDAYS($E$4,F28,'Festivos Guatemala'!$A$3:$A$15),0) -> 0 | I28: =NETWORKDAYS($E$4,F28,'Festivos Guatemala'!$A$3:$A$15) -> 9 | J28: =H28 -> 0
B29: 42780261927 | C29: Declaraguate IVA mes de abril | D29: 0 | E29: =D29/$D$6 -> 0 | F29: 45473 | G29: Cancelado | H29: =IF(OR(G29="Sin pagar",G29="Pagar"),NETWORKDAYS($E$4,F29,'Festivos Guatemala'!$A$3:$A$15),0) -> 0 | I29: =NETWORKDAYS($E$4,F29,'Festivos Guatemala'!$A$3:$A$15) -> 19 | J29: =H29 -> 0
C30: SERVICIOS PROFESIONALES -REPRESENTACIÓN LEGAL | D30: =SUBTOTAL(9,D31:D32) -> 840 | E30: =SUBTOTAL(9,E31:E32) -> 111.25828 | J30: =H30 -> 0
C31: Servicios profesionales Juan-Servicios prestados-Mayo | D31: 840 | E31: =D31/$D$6 -> 111.25828 | F31: 45450 | G31: Cancelado | H31: =IF(OR(G31="Sin pagar",G31="Pagar"),NETWORKDAYS($E$4,F31,'Festivos Guatemala'!$A$3:$A$15),0) -> 0 | I31: =NETWORKDAYS($E$4,F31,'Festivos Guatemala'!$A$3:$A$15) -> 4 | J31: =H31 -> 0
B32: 922 | C32: Servicios profesionales Arnoldo prestados en Mayo | D32: =1200*0 -> 0 | E32: =D32/$D$6 -> 0 | F32: 45464 | G32: Cancelado | H32: =IF(OR(G32="Sin pagar",G32="Pagar"),NETWORKDAYS($E$4,F32,'Festivos Guatemala'!$A$3:$A$15),0) -> 0 | I32: =NETWORKDAYS($E$4,F32,'Festivos Guatemala'!$A$3:$A$15) -> 14 | J32: =H32 -> 0
C33: PÓLIZAS Y SEGUROS | D33: =SUBTOTAL(9,D34:D39) -> 7545.4885 | E33: =SUBTOTAL(9,E34:E39) -> 999.40245
C34: Póliza de vida Ivan Estuardo Chavez Morales-USD-Póliza Vida | D34: =E34*$D$6 -> 415.7785 | E34: =55.07 -> 55.07 | F34: 45471 | G34: Cancelado | H34: =IF(OR(G34="Sin pagar",G34="Pagar"),NETWORKDAYS($E$4,F34,'Festivos Guatemala'!$A$3:$A$15),0) -> 0 | I34: =NETWORKDAYS($E$4,F34,'Festivos Guatemala'!$A$3:$A$15) -> 19 | J34: =H34 -> 0
C35: Poliza de vida Rony Eduardo Quan Lam-USD-Póliza Vida | D35: =E35*$D$6 -> 1958.9985 | E35: =259.47 -> 259.47 | F35: 45471 | G35: Cancelado | H35: =IF(OR(G35="Sin pagar",G35="Pagar"),NETWORKDAYS($E$4,F35,'Festivos Guatemala'!$A$3:$A$15),0) -> 0 | I35: =NETWORKDAYS($E$4,F35,'Festivos Guatemala'!$A$3:$A$15) -> 19 | J35: =H35 -> 0
C36: Poliza de vida Jerry García Carillo -USD-Póliza Vida | D36: =E36*$D$6 -> 1550.2415 | E36: =205.33 -> 205.33 | F36: 45471 | G36: Cancelado | H36: =IF(OR(G36="Sin pagar",G36="Pagar"),NETWORKDAYS($E$4,F36,'Festivos Guatemala'!$A$3:$A$15),0) -> 0 | I36: =NETWORKDAYS($E$4,F36,'Festivos Guatemala'!$A$3:$A$15) -> 19 | J36: =H36 -> 0
C37: Póliza de vida Ivan Estuardo Chavez Morales-QTQ-GM | D37: =888.15 -> 888.15 | E37: =D37/$D$6 -> 117.63576 | F37: 45471 | G37: Cancelado | H37: =IF(OR(G37="Sin pagar",G37="Pagar"),NETWORKDAYS($E$4,F37,'Festivos Guatemala'!$A$3:$A$15),0) -> 0 | I37: =NETWORKDAYS($E$4,F37,'Festivos Guatemala'!$A$3:$A$15) -> 19 | J37: =H37 -> 0
C38: Poliza de vida Rony Eduardo Quan Lam-QTQ-GM | D38: =903.72 -> 903.72 | E38: =D38/$D$6 -> 119.69801 | F38: 45471 | G38: Cancelado | H38: =IF(OR(G38="Sin pagar",G38="Pagar"),NETWORKDAYS($E$4,F38,'Festivos Guatemala'!$A$3:$A$15),0) -> 0 | I38: =NETWORKDAYS($E$4,F38,'Festivos Guatemala'!$A$3:$A$15) -> 19 | J38: =H38 -> 0
C39: Poliza de vida Jerry García Carillo -QTQ-GM-Claudia Marisol Mayorga Ayala | D39: =1828.6 -> 1828.6 | E39: =D39/$D$6 -> 242.19868 | F39: 45471 | G39: Cancelado | H39: =IF(OR(G39="Sin pagar",G39="Pagar"),NETWORKDAYS($E$4,F39,'Festivos Guatemala'!$A$3:$A$15),0) -> 0 | I39: =NETWORKDAYS($E$4,F39,'Festivos Guatemala'!$A$3:$A$15) -> 19 | J39: =H39 -> 0
C40: COBROS ENTRE SUCURSALES | D40: =SUBTOTAL(9,D41:D47) -> 48575.265 | E40: =SUBTOTAL(9,E41:E47) -> 6433.81 | M40: =SUM(M41:M47) -> 42965403 | N40: =11000*4145.1 -> 45596100
B41: 4640 | C41: Cobro S&P a sucursal Guatemala -Enero | D41: =E41*$D$6 -> 6924.4825 | E41: =917.15 -> 917.15 | F41: 45449 | G41: Cancelado | H41: =IF(OR(G41="Sin pagar",G41="Pagar"),NETWORKDAYS($E$4,F41,'Festivos Guatemala'!$A$3:$A$15),0) -> 0 | I41: =NETWORKDAYS($E$4,F41,'Festivos Guatemala'!$A$3:$A$15) -> 3 | J41: =H41 -> 0 | M41: =E41*3933.56 -> 3607664.6
B42: 4641 | C42: Cobro S&P a sucursal Guatemala -febrero | D42: =E42*$D$6 -> 6285.375 | E42: =832.5 -> 832.5 | F42: 45449 | G42: Cancelado | H42: =IF(OR(G42="Sin pagar",G42="Pagar"),NETWORKDAYS($E$4,F42,'Festivos Guatemala'!$A$3:$A$15),0) -> 0 | I42: =NETWORKDAYS($E$4,F42,'Festivos Guatemala'!$A$3:$A$15) -> 3 | J42: =H42 -> 0 | M42: =E42*3933.56 -> 3274688.7
B43: 4700 | C43: Cobro S&P a sucursal Guatemala -Marzo | D43: =E43*$D$6 -> 7620.215 | E43: =1009.3 -> 1009.3 | F43: 45449 | G43: Cancelado | H43: =IF(OR(G43="Sin pagar",G43="Pagar"),NETWORKDAYS($E$4,F43,'Festivos Guatemala'!$A$3:$A$15),0) -> 0 | I43: =NETWORKDAYS($E$4,F43,'Festivos Guatemala'!$A$3:$A$15) -> 3 | J43: =H43 -> 0 | M43: =E43*3888.02 -> 3924178.6
B44: 4707 | C44: Cobro S&P a sucursal Guatemala -Marzo | D44: =E44*$D$6 -> 7550 | E44: =1000 -> 1000 | F44: 45449 | G44: Cancelado | H44: =IF(OR(G44="Sin pagar",G44="Pagar"),NETWORKDAYS($E$4,F44,'Festivos Guatemala'!$A$3:$A$15),0) -> 0 | I44: =NETWORKDAYS($E$4,F44,'Festivos Guatemala'!$A$3:$A$15) -> 3 | J44: =H44 -> 0 | M44: =E44*3865.97 -> 3865970
B45: 4776 | C45: Cobro S&P a sucursal Guatemala -Abril | D45: =E45*$D$6 -> 11487.325 | E45: =1521.5 -> 1521.5 | F45: 45449 | G45: Cancelado | H45: =IF(OR(G45="Sin pagar",G45="Pagar"),NETWORKDAYS($E$4,F45,'Festivos Guatemala'!$A$3:$A$15),0) -> 0 | I45: =NETWORKDAYS($E$4,F45,'Festivos Guatemala'!$A$3:$A$15) -> 3 | J45: =H45 -> 0 | M45: =E45*3924.82 -> 5971613.6
B46: 4838 | C46: Cobro S&P a sucursal Guatemala -Mayo | D46: =E46*$D$6 -> 8707.868 | E46: =1153.36 -> 1153.36 | F46: 45456 | G46: Cancelado | H46: =IF(OR(G46="Sin pagar",G46="Pagar"),NETWORKDAYS($E$4,F46,'Festivos Guatemala'!$A$3:$A$15),0) -> 0 | I46: =NETWORKDAYS($E$4,F46,'Festivos Guatemala'!$A$3:$A$15) -> 8 | J46: =H46 -> 0 | M46: =E46*3902.63 -> 4501137.3
B47: 4944 | C47: Cobro S&P a sucursal Guatemala -Junio-Previsto | D47: =E47*$D$6 -> 0 | E47: =1507.5*0 -> 0 | F47: 45503 | G47: Cancelado | H47: =IF(OR(G47="Sin pagar",G47="Pagar"),NETWORKDAYS($E$4,F47,'Festivos Guatemala'!$A$3:$A$15),0) -> 0 | I47: =NETWORKDAYS($E$4,F47,'Festivos Guatemala'!$A$3:$A$15) -> 41 | J47: =H47 -> 0 | M47: =(11000-6433.81)*3902.63 -> 17820150
C48: TIQUETES AÉREOS , HOTELES | D48: =SUBTOTAL(9,D49:D50) -> 0 | E48: =SUBTOTAL(9,E49:E50) -> 0
C49: Tiquetes Ricardo y Eduard Visita Sucursal Guatemala | D49: =(((4000000/3901.51)*$D$6))*0 -> 0 | E49: =D49/D6 -> 0 | F49: 45473 | G49: Cancelado | H49: =IF(OR(G49="Sin pagar",G49="Pagar"),NETWORKDAYS($E$4,F49,'Festivos Guatemala'!$A$3:$A$15),0) -> 0 | I49: =NETWORKDAYS($E$4,F49,'Festivos Guatemala'!$A$3:$A$15) -> 19 | J49: =H49 -> 0
C50: Hoteles Ricardo y Eduard Visita Sucursal Guatemala | D50: =(((4000000/3901.51)*$D$6))*0 -> 0 | E50: =D50/D6 -> 0 | F50: 45473 | G50: Cancelado | H50: =IF(OR(G50="Sin pagar",G50="Pagar"),NETWORKDAYS($E$4,F50,'Festivos Guatemala'!$A$3:$A$15),0) -> 0 | I50: =NETWORKDAYS($E$4,F50,'Festivos Guatemala'!$A$3:$A$15) -> 19 | J50: =H50 -> 0
C51: COSTOS FINANCIEROS | D51: =SUBTOTAL(9,D52:D54) -> 604 | E51: =SUBTOTAL(9,E52:E54) -> 80
C52: Envío de divisas a Bancolombioa panama pago facturas S&P Col-Primer Envío | D52: =E52*$D$6 -> 302 | E52: 40 | F52: 45449 | G52: Cancelado | H52: =IF(OR(G52="Sin pagar",G52="Pagar"),NETWORKDAYS($E$4,F52,'Festivos Guatemala'!$A$3:$A$15),0) -> 0 | I52: =NETWORKDAYS($E$4,F52,'Festivos Guatemala'!$A$3:$A$15) -> 3 | J52: =H52 -> 0
C53: Envío de divisas a Bancolombioa panama pago facturas S&P Col-Segundo Envío | D53: =E53*$D$6 -> 302 | E53: 40 | F53: 45456 | G53: Cancelado | H53: =IF(OR(G53="Sin pagar",G53="Pagar"),NETWORKDAYS($E$4,F53,'Festivos Guatemala'!$A$3:$A$15),0) -> 0 | I53: =NETWORKDAYS($E$4,F53,'Festivos Guatemala'!$A$3:$A$15) -> 8 | J53: =H53 -> 0
C54: Cobro emisión estado cuenta | D54: =(15*2*4)*0 -> 0 | E54: =D54/$D$6 -> 0 | F54: 45473 | G54: Cancelado | H54: =IF(OR(G54="Sin pagar",G54="Pagar"),NETWORKDAYS($E$4,F54,'Festivos Guatemala'!$A$3:$A$15),0) -> 0 | I54: =NETWORKDAYS($E$4,F54,'Festivos Guatemala'!$A$3:$A$15) -> 19 | J54: =H54 -> 0
C55: NÓMINAS | D55: =SUBTOTAL(9,D56:D62) -> 340958.92 | E55: =SUBTOTAL(9,E56:E62) -> 45160.122
C56: Stephanie Rodriguez Lopez-RF-Czarnikow-CC002 | D56: =38497.02 -> 38497.02 | E56: =D56/$D$6 -> 5098.943 | F56: 45471 | G56: Cancelado | H56: =IF(OR(G56="Sin pagar",G56="Pagar"),NETWORKDAYS($E$4,F56,'Festivos Guatemala'!$A$3:$A$15),0) -> 0 | I56: =NETWORKDAYS($E$4,F56,'Festivos Guatemala'!$A$3:$A$15) -> 19 | J56: =H56 -> 0
C57: Miriam Lucia Morfin Gonzalez RF-Czarnikow-CC002 | D57: 32199.32 | E57: =D57/$D$6 -> 4264.8106 | F57: 45471 | G57: Cancelado | H57: =IF(OR(G57="Sin pagar",G57="Pagar"),NETWORKDAYS($E$4,F57,'Festivos Guatemala'!$A$3:$A$15),0) -> 0 | I57: =NETWORKDAYS($E$4,F57,'Festivos Guatemala'!$A$3:$A$15) -> 19 | J57: =H57 -> 0
C58: Ivan Estuardo Chávez Morales-Energyzer-CC003 | D58: 38748.71 | E58: =D58/$D$6 -> 5132.2795 | F58: 45471 | G58: Cancelado | H58: =IF(OR(G58="Sin pagar",G58="Pagar"),NETWORKDAYS($E$4,F58,'Festivos Guatemala'!$A$3:$A$15),0) -> 0 | I58: =NETWORKDAYS($E$4,F58,'Festivos Guatemala'!$A$3:$A$15) -> 19 | J58: =H58 -> 0
C59: Jerry García-Energyzer-CC003 | D59: 96255.75 | E59: =D59/$D$6 -> 12749.106 | F59: 45471 | G59: Cancelado | H59: =IF(OR(G59="Sin pagar",G59="Pagar"),NETWORKDAYS($E$4,F59,'Festivos Guatemala'!$A$3:$A$15),0) -> 0 | I59: =NETWORKDAYS($E$4,F59,'Festivos Guatemala'!$A$3:$A$15) -> 19 | J59: =H59 -> 0
C60: Ronny Eduardo Quan Lam-Energyzer-CC003 | D60: 114725.07 | E60: =D60/$D$6 -> 15195.374 | F60: 45471 | G60: Cancelado | H60: =IF(OR(G60="Sin pagar",G60="Pagar"),NETWORKDAYS($E$4,F60,'Festivos Guatemala'!$A$3:$A$15),0) -> 0 | I60: =NETWORKDAYS($E$4,F60,'Festivos Guatemala'!$A$3:$A$15) -> 19 | J60: =H60 -> 0
C61: Edlin Ivette Ramos Poitan-Opportunnity | D61: 12847.82 | E61: =D61/$D$6 -> 1701.698 | F61: 45471 | G61: Cancelado | H61: =IF(OR(G61="Sin pagar",G61="Pagar"),NETWORKDAYS($E$4,F61,'Festivos Guatemala'!$A$3:$A$15),0) -> 0 | I61: =NETWORKDAYS($E$4,F61,'Festivos Guatemala'!$A$3:$A$15) -> 19 | J61: =H61 -> 0
C62: Ruth Carolina Vasquez Avelar de Rabanal-Kairos | D62: 7685.23 | E62: =D62/$D$6 -> 1017.9113 | F62: 45471 | G62: Cancelado | H62: =IF(OR(G62="Sin pagar",G62="Pagar"),NETWORKDAYS($E$4,F62,'Festivos Guatemala'!$A$3:$A$15),0) -> 0 | I62: =NETWORKDAYS($E$4,F62,'Festivos Guatemala'!$A$3:$A$15) -> 19 | J62: =H62 -> 0
C63: REEMBOLSOS GASTOS | D63: =SUBTOTAL(9,D64:D67) -> 29930.244 | E63: =SUBTOTAL(9,E64:E67) -> 3948.7417
C64: Jerry García-Energyzer-CC003-USD | D64: =E64*$D$6 -> 9038.7468 | E64: =1088.35*1.1 -> 1197.185 | F64: 45450 | G64: Cancelado | H64: =IF(OR(G64="Sin pagar",G64="Pagar"),NETWORKDAYS($E$4,F64,'Festivos Guatemala'!$A$3:$A$15),0) -> 0 | I64: =NETWORKDAYS($E$4,F64,'Festivos Guatemala'!$A$3:$A$15) -> 4 | J64: =H64 -> 0
C65: Ronny Quan. Energyzer-CC003-USD | D65: =E65*7.66 -> 8164.4876 | E65: 1065.86 | F65: 45457 | G65: Cancelado | H65: =IF(OR(G65="Sin pagar",G65="Pagar"),NETWORKDAYS($E$4,F65,'Festivos Guatemala'!$A$3:$A$15),0) -> 0 | I65: =NETWORKDAYS($E$4,F65,'Festivos Guatemala'!$A$3:$A$15) -> 9 | J65: =H65 -> 0
C66: Ronny Quan. Energyzer-CC003-QTQ | D66: 1740.27 | E66: =D66/$D$6 -> 230.49934 | F66: 45457 | G66: Cancelado | H66: =IF(OR(G66="Sin pagar",G66="Pagar"),NETWORKDAYS($E$4,F66,'Festivos Guatemala'!$A$3:$A$15),0) -> 0 | I66: =NETWORKDAYS($E$4,F66,'Festivos Guatemala'!$A$3:$A$15) -> 9 | J66: =H66 -> 0
C67: Jerry García-Energyzer-CC003-QTQ | D67: 10986.74 | E67: =D67/$D$6 -> 1455.1974 | F67: 45457 | G67: Cancelado | H67: =IF(OR(G67="Sin pagar",G67="Pagar"),NETWORKDAYS($E$4,F67,'Festivos Guatemala'!$A$3:$A$15),0) -> 0 | I67: =NETWORKDAYS($E$4,F67,'Festivos Guatemala'!$A$3:$A$15) -> 9 | J67: =H67 -> 0
C68: CELULARES | D68: =SUBTOTAL(9,D69:D69) -> 0 | E68: =SUBTOTAL(9,E69:E69) -> 0
C69: Mensualidad celulares empleados | D69: =499*3*2*0 -> 0 | E69: =D69/$D$6 -> 0 | F69: 45473 | G69: Cancelado | H69: =IF(OR(G69="Sin pagar",G69="Pagar"),NETWORKDAYS($E$4,F69,'Festivos Guatemala'!$A$3:$A$15),0) -> 0 | I69: =NETWORKDAYS($E$4,F69,'Festivos Guatemala'!$A$3:$A$15) -> 19 | J69: =H69 -> 0
C70: IMPREVISTO | D70: =SUBTOTAL(9,D71:D72) -> 0 | E70: =SUBTOTAL(9,E71:E72) -> 0
C71: Gastos de movilización y trámites varios Juan | D71: 0 | E71: =D71/$D$6 -> 0 | F71: 45473 | G71: Cancelado | H71: =IF(OR(G71="Sin pagar",G71="Pagar"),NETWORKDAYS($E$4,F71,'Festivos Guatemala'!$A$3:$A$15),0) -> 0 | I71: =NETWORKDAYS($E$4,F71,'Festivos Guatemala'!$A$3:$A$15) -> 19 | J71: =H71 -> 0
C72: Envío documentos Juan | D72: 0 | E72: =D72/$D$6 -> 0 | F72: 45473 | G72: Cancelado | H72: =IF(OR(G72="Sin pagar",G72="Pagar"),NETWORKDAYS($E$4,F72,'Festivos Guatemala'!$A$3:$A$15),0) -> 0 | I72: =NETWORKDAYS($E$4,F72,'Festivos Guatemala'!$A$3:$A$15) -> 19 | J72: =H72 -> 0
C73: TOTAL EGRESOS | D73: =SUBTOTAL(9,D24:D72) -> 480944.62 | E73: =SUBTOTAL(9,E24:E72) -> 62519.64
C75: SALDO | D75: =D19-D73 -> 199268.57 | E75: =E19-E73 -> 27549.757
C76: % | D76: =IF($D$19=0,0,D75/$D$19) -> 0.29295017 | E76: =IF($E$19=0,0,E75/$E$19) -> 0.30587256
C80: Fecha Inicial | D80: Fecha Final | E80: Valor VALOR QTQ | F80: Valor VALOR USD
C81: 45446 | D81: 45452 | E81: =SUMIFS($D$23:$D$73,$F$23:$F$73,">="&C81,$F$23:$F$73,"<="&D81,$G$23:$G$73,$D$94) -> 0 | F81: =SUMIFS($E$23:$E$73,$F$23:$F$73,">="&C81,$F$23:$F$73,"<="&D81,$G$23:$G$73,$D$94) -> 0
C82: 45453 | D82: 45459 | E82: =SUMIFS($D$23:$D$73,$F$23:$F$73,">="&C82,$F$23:$F$73,"<="&D82,$G$23:$G$73,$D$94) -> 0 | F82: =SUMIFS($E$23:$E$73,$F$23:$F$73,">="&C82,$F$23:$F$73,"<="&D82,$G$23:$G$73,$D$94) -> 0
C83: 45460 | D83: 45466 | E83: =SUMIFS($D$23:$D$73,$F$23:$F$73,">="&C83,$F$23:$F$73,"<="&D83,$G$23:$G$73,$D$94) -> 0 | F83: =SUMIFS($E$23:$E$73,$F$23:$F$73,">="&C83,$F$23:$F$73,"<="&D83,$G$23:$G$73,$D$94) -> 0
C84: 45467 | D84: 45473 | E84: =SUMIFS($D$23:$D$73,$F$23:$F$73,">="&C84,$F$23:$F$73,"<="&D84,$G$23:$G$73,$D$94) -> 0 | F84: =SUMIFS($E$23:$E$73,$F$23:$F$73,">="&C84,$F$23:$F$73,"<="&D84,$G$23:$G$73,$D$94) -> 0
C85: TOTAL EGRESOS | E85: =SUM(E81:E84) -> 0 | F85: =SUM(F81:F84) -> 0
D86: Pagado | E86: =D73-E85 -> 480944.62
C88: Bancos 26/06/2024 | E88: =384656.62+(4344.58*7.55) -> 417458.2 | F88: =E88/7.55 -> 55292.477
C89: Gastos y costos Periodo 24 al 30 de Junio | E89: =E84 -> 0 | F89: =F84 -> 0
C90: Saldo | E90: =E88-E89 -> 417458.2 | F90: =F88-F89 -> 55292.477
D93: Cancelado | E93: =SUMIFS($D$23:$D$77,$F$23:$F$77,">="&C81,$F$23:$F$77,"<="&D84,$G$23:$G$77,$D$93) -> 480944.62 | F93: =SUMIFS($E$23:$E$77,$F$23:$F$77,">="&C81,$F$23:$F$77,"<="&D84,$G$23:$G$77,$D$93) -> 62519.64
D94: Sin Pagar | E94: =SUMIFS($D$23:$D$77,$F$23:$F$77,">="&C81,$F$23:$F$77,"<="&D84,$G$23:$G$77,$D$94) -> 0 | F94: =SUMIFS($E$23:$E$77,$F$23:$F$77,">="&C81,$F$23:$F$77,"<="&D84,$G$23:$G$77,$D$94) -> 0
D95: Total Egresos | E95: =SUM(E93:E94) -> 480944.62 | F95: =SUM(F93:F94) -> 62519.64
D96: Validación | E96: =E95-D73 -> 0 | F96: =F95-E73 -> 0
D98: Saldo FC | E98: =$D$75 -> 199268.57
D99: Saldo Libro | E99: =('Caja QTQ'!$D$142+'Caja USD'!H53*'Flujo caja Junio '!$D$6) -> 199268.57
D100: Diferencia | E100: =E98-E99 -> 0.0015 | F100: =E100/7.88 -> 0.00019035532

Sheet Flujo caja Julio
D1: 42400
D4: Fecha de Elaboración: | E4: 45475
C6: Tasa de cambio: | D6: 7.55
D7: JULIO
D8: VALOR QTQ | E8: VALOR USD
C9: BANCOS | D9: =SUBTOTAL(9,D10:D11) -> 170811.57 | E9: =SUBTOTAL(9,E10:E11) -> 26393.188
C10: Bancos QTQ | D10: ='Caja QTQ'!$D$142 -> 166466.99 | E10: =D10/$D$6 -> 22048.608
C11: Bancos USD | D11: ='Caja USD'!$H$53 -> 4344.58 | E11: ='Caja USD'!D58 -> 4344.58
C12: CLIENTES | D12: =SUBTOTAL(9,D13:D17) -> 389916.26 | E12: =SUBTOTAL(9,E13:E17) -> 51644.538
C13: Client: Czarnikow- Sthepanie Rodriguez Lopez-TC 7.55 | D13: ='Diferencia en cambio'!$I$25 -> 41329.252 | E13: =D13/$D$6 -> 5474.0732
C14: Client:Energyzer-Ivan Chavez-Jerry García-Ronny Quan-TC 7.55 | D14: ='Diferencia en cambio'!$I$26 -> 284899.12 | E14: =D14/$D$6 -> 37734.983
C15: Client:Kairos-Ivan Chavez-Ruth Carolina Vasquez-TC 7.55 | D15: ='Diferencia en cambio'!$I$27 -> 7197.2643 | E15: =D15/$D$6 -> 953.28004
C16: Client: Opportunity-Edlin Ivette Poitan-TC 7.55 | D16: ='Diferencia en cambio'!$I$28 -> 13286.476 | E16: =D16/$D$6 -> 1759.7981
C17: Client: NotableGrowth, Inc-TC 7.55 | D17: ='Diferencia en cambio'!$I$29 -> 43204.148 | E17: =D17/$D$6 -> 5722.4037
C18: TOTAL INGRESOS | D18: =SUBTOTAL(9,D9:D17) -> 560727.83 | E18: =SUBTOTAL(9,E9:E17) -> 78037.726
B21: CUENTAS X PAGAR MES | D21: ABRIL
B22: Factura | C22: PROVEEDOR | D22: VALOR QTQ | E22: VALOR USD | F22: Fecha vencimiento | G22: Estado | J22: KPI
C23: SEGURIDAD IGSS | D23: =SUBTOTAL(9,D24:D24) -> 43669.12 | E23: =SUBTOTAL(9,E24:E24) -> 4032.9033
B24: 176206200 | C24: Pago planilla IGSS Junio | D24: =43669.12 -> 43669.12 | E24: =30448.42/$D$6 -> 4032.9033 | F24: 45483 | G24: Cancelado | H24: =IF(OR(G24="Sin pagar",G24="Pagar"),NETWORKDAYS($E$4,F24,'Festivos Guatemala'!$A$3:$A$15),0) -> 0 | I24: =NETWORKDAYS($E$4,F24,'Festivos Guatemala'!$A$3:$A$15) -> 7 | J24: =H24 -> 0
C25: IMPUESTOS | D25: =SUBTOTAL(9,D26:D30) -> 15152.01 | E25: =SUBTOTAL(9,E26:E30) -> 2006.8887 | J25: =H25 -> 0
B26: 42629341546 | C26: Declaraguate ISR Junio | D26: 12837.81 | E26: =D26/$D$6 -> 1700.3722 | F26: 45488 | G26: Cancelado | H26: =IF(OR(G26="Sin pagar",G26="Pagar"),NETWORKDAYS($E$4,F26,'Festivos Guatemala'!$A$3:$A$15),0) -> 0 | I26: =NETWORKDAYS($E$4,F26,'Festivos Guatemala'!$A$3:$A$15) -> 10 | J26: =H26 -> 0
B27: 426295952621 | C27: Declaraguate ISR Julio facturación Col | D27: 1755.82 | E27: =D27/$D$6 -> 232.55894 | F27: 45488 | G27: Cancelado | H27: =IF(OR(G27="Sin pagar",G27="Pagar"),NETWORKDAYS($E$4,F27,'Festivos Guatemala'!$A$3:$A$15),0) -> 0 | I27: =NETWORKDAYS($E$4,F27,'Festivos Guatemala'!$A$3:$A$15) -> 10 | J27: =H27 -> 0
B28: 43589111783 | C28: Declaraguate IVA mes de Junio | D28: 0 | E28: =D28/$D$6 -> 0 | F28: 45504 | G28: Cancelado | H28: =IF(OR(G28="Sin pagar",G28="Pagar"),NETWORKDAYS($E$4,F28,'Festivos Guatemala'!$A$3:$A$15),0) -> 0 | I28: =NETWORKDAYS($E$4,F28,'Festivos Guatemala'!$A$3:$A$15) -> 22 | J28: =H28 -> 0
B29: 43631922735 | C29: Declaraguate Pago ISO | D29: 558.38 | E29: =D29/$D$6 -> 73.957616 | F29: 45504 | G29: Cancelado | H29: =IF(OR(G29="Sin pagar",G29="Pagar"),NETWORKDAYS($E$4,F29,'Festivos Guatemala'!$A$3:$A$15),0) -> 0 | I29: =NETWORKDAYS($E$4,F29,'Festivos Guatemala'!$A$3:$A$15) -> 22 | J29: =H29 -> 0
B30: 43640140958 | C30: Declaraguate declaración de ISR 2do trimestre 2024 | D30: 0 | E30: =D30/$D$6 -> 0 | F30: 45504 | G30: Cancelado | H30: =IF(OR(G30="Sin pagar",G30="Pagar"),NETWORKDAYS($E$4,F30,'Festivos Guatemala'!$A$3:$A$15),0) -> 0 | I30: =NETWORKDAYS($E$4,F30,'Festivos Guatemala'!$A$3:$A$15) -> 22 | J30: =H30 -> 0
C31: SERVICIOS PROFESIONALES -REPRESENTACIÓN LEGAL | D31: =SUBTOTAL(9,D32:D33) -> 2040 | E31: =SUBTOTAL(9,E32:E33) -> 270.19868 | J31: =H31 -> 0
C32: Servicios profesionales Juan-Servicios prestados-Junio | D32: 840 | E32: =D32/$D$6 -> 111.25828 | F32: 45483 | G32: Cancelado | H32: =IF(OR(G32="Sin pagar",G32="Pagar"),NETWORKDAYS($E$4,F32,'Festivos Guatemala'!$A$3:$A$15),0) -> 0 | I32: =NETWORKDAYS($E$4,F32,'Festivos Guatemala'!$A$3:$A$15) -> 7 | J32: =H32 -> 0
B33: 922 | C33: Servicios profesionales Arnoldo prestados en Mayo | D33: =1200 -> 1200 | E33: =D33/$D$6 -> 158.9404 | F33: 45485 | G33: Cancelado | H33: =IF(OR(G33="Sin pagar",G33="Pagar"),NETWORKDAYS($E$4,F33,'Festivos Guatemala'!$A$3:$A$15),0) -> 0 | I33: =NETWORKDAYS($E$4,F33,'Festivos Guatemala'!$A$3:$A$15) -> 9 | J33: =H33 -> 0
C34: PÓLIZAS Y SEGUROS | D34: =SUBTOTAL(9,D35:D43) -> 11165.959 | E34: =SUBTOTAL(9,E35:E43) -> 1478.9349
C35: Poliza de vida Jerry García Carillo -QTQ-GM-Claudia Marisol Mayorga Ayala | D35: 1828.6 | E35: =D35/$D$6 -> 242.19868 | F35: 45475 | G35: Cancelado | H35: =IF(OR(G35="Sin pagar",G35="Pagar"),NETWORKDAYS($E$4,F35,'Festivos Guatemala'!$A$3:$A$15),0) -> 0 | I35: =NETWORKDAYS($E$4,F35,'Festivos Guatemala'!$A$3:$A$15) -> 1 | J35: =H35 -> 0
C36: Póliza de vida Ivan Estuardo Chavez Morales-QTQ-GM | D36: 888.15 | E36: =D36/$D$6 -> 117.63576 | F36: 45475 | G36: Cancelado | H36: =IF(OR(G36="Sin pagar",G36="Pagar"),NETWORKDAYS($E$4,F36,'Festivos Guatemala'!$A$3:$A$15),0) -> 0 | I36: =NETWORKDAYS($E$4,F36,'Festivos Guatemala'!$A$3:$A$15) -> 1 | J36: =H36 -> 0
C37: Poliza de vida Rony Eduardo Quan Lam-QTQ-GM | D37: 903.72 | E37: =D37/$D$6 -> 119.69801 | F37: 45475 | G37: Cancelado | H37: =IF(OR(G37="Sin pagar",G37="Pagar"),NETWORKDAYS($E$4,F37,'Festivos Guatemala'!$A$3:$A$15),0) -> 0 | I37: =NETWORKDAYS($E$4,F37,'Festivos Guatemala'!$A$3:$A$15) -> 1 | J37: =H37 -> 0
C38: Póliza de vida Ivan Estuardo Chavez Morales-USD-Póliza Vida | D38: =E38*$D$6 -> 415.7785 | E38: 55.07 | F38: 45496 | G38: Cancelado | H38: =IF(OR(G38="Sin pagar",G38="Pagar"),NETWORKDAYS($E$4,F38,'Festivos Guatemala'!$A$3:$A$15),0) -> 0 | I38: =NETWORKDAYS($E$4,F38,'Festivos Guatemala'!$A$3:$A$15) -> 16 | J38: =H38 -> 0
C39: Poliza de vida Rony Eduardo Quan Lam-USD-Póliza Vida | D39: =E39*$D$6 -> 1958.9985 | E39: 259.47 | F39: 45496 | G39: Cancelado | H39: =IF(OR(G39="Sin pagar",G39="Pagar"),NETWORKDAYS($E$4,F39,'Festivos Guatemala'!$A$3:$A$15),0) -> 0 | I39: =NETWORKDAYS($E$4,F39,'Festivos Guatemala'!$A$3:$A$15) -> 16 | J39: =H39 -> 0
C40: Poliza de vida Jerry García Carillo -USD-Póliza Vida | D40: =E40*$D$6 -> 1550.2415 | E40: 205.33 | F40: 45496 | G40: Cancelado | H40: =IF(OR(G40="Sin pagar",G40="Pagar"),NETWORKDAYS($E$4,F40,'Festivos Guatemala'!$A$3:$A$15),0) -> 0 | I40: =NETWORKDAYS($E$4,F40,'Festivos Guatemala'!$A$3:$A$15) -> 16 | J40: =H40 -> 0
C41: Póliza de vida Ivan Estuardo Chavez Morales-QTQ-GM | D41: 888.15 | E41: =D41/$D$6 -> 117.63576 | F41: 45496 | G41: Cancelado | H41: =IF(OR(G41="Sin pagar",G41="Pagar"),NETWORKDAYS($E$4,F41,'Festivos Guatemala'!$A$3:$A$15),0) -> 0 | I41: =NETWORKDAYS($E$4,F41,'Festivos Guatemala'!$A$3:$A$15) -> 16 | J41: =H41 -> 0
C42: Poliza de vida Rony Eduardo Quan Lam-QTQ-GM | D42: 903.72 | E42: =D42/$D$6 -> 119.69801 | F42: 45496 | G42: Cancelado | H42: =IF(OR(G42="Sin pagar",G42="Pagar"),NETWORKDAYS($E$4,F42,'Festivos Guatemala'!$A$3:$A$15),0) -> 0 | I42: =NETWORKDAYS($E$4,F42,'Festivos Guatemala'!$A$3:$A$15) -> 16 | J42: =H42 -> 0
C43: Poliza de vida Jerry García Carillo -QTQ-GM-Claudia Marisol Mayorga Ayala | D43: 1828.6 | E43: =D43/$D$6 -> 242.19868 | F43: 45496 | G43: Cancelado | H43: =IF(OR(G43="Sin pagar",G43="Pagar"),NETWORKDAYS($E$4,F43,'Festivos Guatemala'!$A$3:$A$15),0) -> 0 | I43: =NETWORKDAYS($E$4,F43,'Festivos Guatemala'!$A$3:$A$15) -> 16 | J43: =H43 -> 0
C44: COBROS ENTRE SUCURSALES | D44: =SUBTOTAL(9,D45:D46) -> 0 | E44: =SUBTOTAL(9,E45:E46) -> 0 | M44: =SUM(M45:M45) -> 17820150 | N44: =11000*4145.1 -> 45596100
B45: 4944 | C45: Cobro S&P a sucursal Guatemala -Junio | D45: =E45*$D$6 -> 0 | E45: =((1507.5)*0) -> 0 | F45: 45499 | G45: Cancelado | H45: =IF(OR(G45="Sin pagar",G45="Pagar"),NETWORKDAYS($E$4,F45,'Festivos Guatemala'!$A$3:$A$15),0) -> 0 | I45: =NETWORKDAYS($E$4,F45,'Festivos Guatemala'!$A$3:$A$15) -> 19 | J45: =H45 -> 0 | M45: =(11000-6433.81)*3902.63 -> 17820150
B46: 5027 | C46: Cobro S&P a sucursal Guatemala -Julio | D46: =E46*$D$6 -> 0 | E46: =1281.5*0 -> 0 | F46: 45499 | G46: Cancelado | H46: =IF(OR(G46="Sin pagar",G46="Pagar"),NETWORKDAYS($E$4,F46,'Festivos Guatemala'!$A$3:$A$15),0) -> 0 | I46: =NETWORKDAYS($E$4,F46,'Festivos Guatemala'!$A$3:$A$15) -> 19 | J46: =H46 -> 0 | M46: =(11000-6433.81)*3902.63 -> 17820150
C47: TIQUETES AÉREOS , HOTELES | D47: =SUBTOTAL(9,D48:D49) -> 0 | E47: =SUBTOTAL(9,E48:E49) -> 0
C48: Tiquetes Ricardo y Eduard Visita Sucursal Guatemala | D48: =(((4000000/4150)*$D$6))*0 -> 0 | E48: =D48/D6 -> 0 | F48: 45499 | G48: Cancelado | H48: =IF(OR(G48="Sin pagar",G48="Pagar"),NETWORKDAYS($E$4,F48,'Festivos Guatemala'!$A$3:$A$15),0) -> 0 | I48: =NETWORKDAYS($E$4,F48,'Festivos Guatemala'!$A$3:$A$15) -> 19 | J48: =H48 -> 0
C49: Hoteles Ricardo y Eduard Visita Sucursal Guatemala | D49: =(((4000000/4150)*$D$6))*0 -> 0 | E49: =D49/D6 -> 0 | F49: 45499 | G49: Cancelado | H49: =IF(OR(G49="Sin pagar",G49="Pagar"),NETWORKDAYS($E$4,F49,'Festivos Guatemala'!$A$3:$A$15),0) -> 0 | I49: =NETWORKDAYS($E$4,F49,'Festivos Guatemala'!$A$3:$A$15) -> 19 | J49: =H49 -> 0
C50: COSTOS FINANCIEROS | D50: =SUBTOTAL(9,D51:D51) -> 0 | E50: =SUBTOTAL(9,E51:E51) -> 0
C51: Cobro emisión estado cuenta | D51: 0 | E51: =D51/$D$6 -> 0 | F51: 45503 | G51: Cancelado | H51: =IF(OR(G51="Sin pagar",G51="Pagar"),NETWORKDAYS($E$4,F51,'Festivos Guatemala'!$A$3:$A$15),0) -> 0 | I51: =NETWORKDAYS($E$4,F51,'Festivos Guatemala'!$A$3:$A$15) -> 21 | J51: =H51 -> 0
C52: NÓMINAS | D52: =SUBTOTAL(9,D53:D60) -> 270409.53 | E52: =SUBTOTAL(9,E53:E60) -> 35815.832
C53: Stephanie Rodriguez Lopez-RF-Czarnikow-CC002 | D53: 13922 | E53: =D53/$D$6 -> 1843.9735 | F53: 45475 | G53: Cancelado | H53: =IF(OR(G53="Sin pagar",G53="Pagar"),NETWORKDAYS($E$4,F53,'Festivos Guatemala'!$A$3:$A$15),0) -> 0 | I53: =NETWORKDAYS($E$4,F53,'Festivos Guatemala'!$A$3:$A$15) -> 1 | J53: =H53 -> 0
C54: Miriam Lucia Morfin Gonzalez RF-Czarnikow-CC002 | D54: 29515.65 | E54: =D54/$D$6 -> 3909.3576 | F54: 45499 | G54: Cancelado | H54: =IF(OR(G54="Sin pagar",G54="Pagar"),NETWORKDAYS($E$4,F54,'Festivos Guatemala'!$A$3:$A$15),0) -> 0 | I54: =NETWORKDAYS($E$4,F54,'Festivos Guatemala'!$A$3:$A$15) -> 19 | J54: =H54 -> 0
C55: Ivan Estuardo Chávez Morales-Energyzer-CC003 | D55: 24970.21 | E55: =D55/$D$6 -> 3307.3126 | F55: 45499 | G55: Cancelado | H55: =IF(OR(G55="Sin pagar",G55="Pagar"),NETWORKDAYS($E$4,F55,'Festivos Guatemala'!$A$3:$A$15),0) -> 0 | I55: =NETWORKDAYS($E$4,F55,'Festivos Guatemala'!$A$3:$A$15) -> 19 | J55: =H55 -> 0
C56: Jerry García-Energyzer-CC003 | D56: 84891.41 | E56: =D56/$D$6 -> 11243.895 | F56: 45499 | G56: Cancelado | H56: =IF(OR(G56="Sin pagar",G56="Pagar"),NETWORKDAYS($E$4,F56,'Festivos Guatemala'!$A$3:$A$15),0) -> 0 | I56: =NETWORKDAYS($E$4,F56,'Festivos Guatemala'!$A$3:$A$15) -> 19 | J56: =H56 -> 0
C57: Ronny Eduardo Quan Lam-Energyzer-CC003 | D57: 72752.58 | E57: =D57/$D$6 -> 9636.1033 | F57: 45499 | G57: Cancelado | H57: =IF(OR(G57="Sin pagar",G57="Pagar"),NETWORKDAYS($E$4,F57,'Festivos Guatemala'!$A$3:$A$15),0) -> 0 | I57: =NETWORKDAYS($E$4,F57,'Festivos Guatemala'!$A$3:$A$15) -> 19 | J57: =H57 -> 0
C58: Edlin Ivette Ramos Poitan-Opportunnity | D58: 10382.76 | E58: =D58/$D$6 -> 1375.2 | F58: 45499 | G58: Cancelado | H58: =IF(OR(G58="Sin pagar",G58="Pagar"),NETWORKDAYS($E$4,F58,'Festivos Guatemala'!$A$3:$A$15),0) -> 0 | I58: =NETWORKDAYS($E$4,F58,'Festivos Guatemala'!$A$3:$A$15) -> 19 | J58: =H58 -> 0
C59: Ruth Carolina Vasquez Avelar de Rabanal-Kairos | D59: 5732.9 | E59: =D59/$D$6 -> 759.3245 | F59: 45499 | G59: Cancelado | H59: =IF(OR(G59="Sin pagar",G59="Pagar"),NETWORKDAYS($E$4,F59,'Festivos Guatemala'!$A$3:$A$15),0) -> 0 | I59: =NETWORKDAYS($E$4,F59,'Festivos Guatemala'!$A$3:$A$15) -> 19 | J59: =H59 -> 0
C60: Stephanie Rodriguez Lopez-RF-Czarnikow-CC002 | D60: 28242.02 | E60: =D60/$D$6 -> 3740.6649 | F60: 45499 | G60: Cancelado | H60: =IF(OR(G60="Sin pagar",G60="Pagar"),NETWORKDAYS($E$4,F60,'Festivos Guatemala'!$A$3:$A$15),0) -> 0 | I60: =NETWORKDAYS($E$4,F60,'Festivos Guatemala'!$A$3:$A$15) -> 19 | J60: =H60 -> 0
C61: REEMBOLSOS GASTOS | D61: =SUBTOTAL(9,D62:D66) -> 27968.851 | E61: =SUBTOTAL(9,E62:E66) -> 3704.4836
C62: Jerry García-Energyzer-CC003-USD | D62: =E62*$D$6 -> 11661.654 | E62: 1544.59 | F62: 45503 | G62: Cancelado | H62: =IF(OR(G62="Sin pagar",G62="Pagar"),NETWORKDAYS($E$4,F62,'Festivos Guatemala'!$A$3:$A$15),0) -> 0 | I62: =NETWORKDAYS($E$4,F62,'Festivos Guatemala'!$A$3:$A$15) -> 21 | J62: =H62 -> 0
C63: Ronny Quan. Energyzer-CC003-USD | D63: =E63*$D$6 -> 6888.167 | E63: 912.34 | F63: 45499 | G63: Cancelado | H63: =IF(OR(G63="Sin pagar",G63="Pagar"),NETWORKDAYS($E$4,F63,'Festivos Guatemala'!$A$3:$A$15),0) -> 0 | I63: =NETWORKDAYS($E$4,F63,'Festivos Guatemala'!$A$3:$A$15) -> 19 | J63: =H63 -> 0
C64: Ronny Quan. Energyzer-CC003-QTQ | D64: 4796.53 | E64: =D64/$D$6 -> 635.30199 | F64: 45503 | G64: Cancelado | H64: =IF(OR(G64="Sin pagar",G64="Pagar"),NETWORKDAYS($E$4,F64,'Festivos Guatemala'!$A$3:$A$15),0) -> 0 | I64: =NETWORKDAYS($E$4,F64,'Festivos Guatemala'!$A$3:$A$15) -> 21 | J64: =H64 -> 0
C65: Jerry García-Energyzer-CC003-QTQ | D65: 4622.5 | E65: =D65/$D$6 -> 612.25166 | F65: 45503 | G65: Cancelado | H65: =IF(OR(G65="Sin pagar",G65="Pagar"),NETWORKDAYS($E$4,F65,'Festivos Guatemala'!$A$3:$A$15),0) -> 0 | I65: =NETWORKDAYS($E$4,F65,'Festivos Guatemala'!$A$3:$A$15) -> 21 | J65: =H65 -> 0
C66: Mensualidad celulares empleados | D66: =499*3*3*0 -> 0 | E66: =D66/$D$6 -> 0 | F66: 45503 | G66: Cancelado | H66: =IF(OR(G66="Sin pagar",G66="Pagar"),NETWORKDAYS($E$4,F66,'Festivos Guatemala'!$A$3:$A$15),0) -> 0 | I66: =NETWORKDAYS($E$4,F66,'Festivos Guatemala'!$A$3:$A$15) -> 21 | J66: =H66 -> 0
C67: IMPREVISTO | D67: =SUBTOTAL(9,D68:D69) -> 223.15 | E67: =SUBTOTAL(9,E68:E69) -> 29.556291
C68: Reembolso Gastos a Juan audicencia IGSS | D68: 223.15 | E68: =D68/$D$6 -> 29.556291 | F68: 45488 | G68: Cancelado | H68: =IF(OR(G68="Sin pagar",G68="Pagar"),NETWORKDAYS($E$4,F68,'Festivos Guatemala'!$A$3:$A$15),0) -> 0 | I68: =NETWORKDAYS($E$4,F68,'Festivos Guatemala'!$A$3:$A$15) -> 10 | J68: =H68 -> 0
C69: Envío documentos Juan | D69: 0 | E69: =D69/$D$6 -> 0 | F69: 45503 | G69: Cancelado | H69: =IF(OR(G69="Sin pagar",G69="Pagar"),NETWORKDAYS($E$4,F69,'Festivos Guatemala'!$A$3:$A$15),0) -> 0 | I69: =NETWORKDAYS($E$4,F69,'Festivos Guatemala'!$A$3:$A$15) -> 21 | J69: =H69 -> 0
C70: TOTAL EGRESOS | D70: =SUBTOTAL(9,D23:D69) -> 370628.62 | E70: =SUBTOTAL(9,E23:E69) -> 47338.797
C72: SALDO | D72: =D18-D70 -> 190099.21 | E72: =E18-E70 -> 30698.929
C73: % | D73: =IF($D$18=0,0,D72/$D$18) -> 0.33902225 | E73: =IF($E$18=0,0,E72/$E$18) -> 0.39338574
C75: Fecha Inicial | D75: Fecha Final | E75: Valor VALOR QTQ | F75: Valor VALOR USD
C76: 45474 | D76: 45480 | E76: =SUMIFS($D$23:$D$73,$F$23:$F$73,">="&C76,$F$23:$F$73,"<="&D76,$G$23:$G$73,$D$84) -> 0 | F76: =SUMIFS($E$23:$E$73,$F$23:$F$73,">="&C76,$F$23:$F$73,"<="&D76,$G$23:$G$73,$D$84) -> 0
C77: 45481 | D77: 45487 | E77: =SUMIFS($D$23:$D$73,$F$23:$F$73,">="&C77,$F$23:$F$73,"<="&D77,$G$23:$G$73,$D$84) -> 0 | F77: =SUMIFS($E$23:$E$73,$F$23:$F$73,">="&C77,$F$23:$F$73,"<="&D77,$G$23:$G$73,$D$84) -> 0
C78: 45488 | D78: 45494 | E78: =SUMIFS($D$23:$D$73,$F$23:$F$73,">="&C78,$F$23:$F$73,"<="&D78,$G$23:$G$73,$D$84) -> 0 | F78: =SUMIFS($E$23:$E$73,$F$23:$F$73,">="&C78,$F$23:$F$73,"<="&D78,$G$23:$G$73,$D$84) -> 0
C79: 45495 | D79: 45501 | E79: =SUMIFS($D$23:$D$73,$F$23:$F$73,">="&C79,$F$23:$F$73,"<="&D79,$G$23:$G$73,$D$84) -> 0 | F79: =SUMIFS($E$23:$E$73,$F$23:$F$73,">="&C79,$F$23:$F$73,"<="&D79,$G$23:$G$73,$D$84) -> 0
C80: 45502 | D80: 45504 | E80: =SUMIFS($D$23:$D$73,$F$23:$F$73,">="&C80,$F$23:$F$73,"<="&D80,$G$23:$G$73,$D$84) -> 0 | F80: =SUMIFS($E$23:$E$73,$F$23:$F$73,">="&C80,$F$23:$F$73,"<="&D80,$G$23:$G$73,$D$84) -> 0
C81: TOTAL EGRESOS | E81: =SUM(E76:E80) -> 0 | F81: =SUM(F76:F80) -> 0
D83: Cancelado | E83: =SUMIFS($D$23:$D$77,$F$23:$F$77,">="&C76,$F$23:$F$77,"<="&D80,$G$23:$G$77,$D$83) -> 370628.62 | F83: =SUMIFS($E$23:$E$77,$F$23:$F$77,">="&C76,$F$23:$F$77,"<="&D80,$G$23:$G$77,$D$83) -> 47338.797
D84: Sin Pagar | E84: =SUMIFS($D$23:$D$77,$F$23:$F$77,">="&C77,$F$23:$F$77,"<="&D80,$G$23:$G$77,$D$84) -> 0 | F84: =SUMIFS($E$23:$E$77,$F$23:$F$77,">="&C77,$F$23:$F$77,"<="&D80,$G$23:$G$77,$D$84) -> 0
D85: Total Egresos | E85: =SUM(E83:E84) -> 370628.62 | F85: =SUM(F83:F84) -> 47338.797
D86: Validación | E86: =E85-D70 -> 0 | F86: =F85-E70 -> 0
D88: Flujo Caja | E88: =D72 -> 190099.21
D89: Saldo Libro | E89: ='Caja QTQ'!H167+('Caja USD'!H70*7.6) -> 190098.57
D90: Diferencia | E90: =E88-E89 -> 0.644 | F90: =E90/7.88 -> 0.081725888

Sheet Flujo caja Agosto
D1: 42400
D4: Fecha de Elaboración: | E4: 45506
C6: Tasa de cambio: | D6: 7.58
D7: AGOSTO
D8: VALOR QTQ | E8: VALOR USD
C9: BANCOS | D9: =SUBTOTAL(9,D10:D12) -> 215137.73 | E9: =SUBTOTAL(9,E10:E12) -> 28382.286
C10: Bancos QTQ | D10: ='Caja QTQ'!$H$167 -> 183654.45 | E10: =D10/$D$6 -> 24228.82
C11: Bancos USD | D11: =E11*D6 -> 6427.1578 | E11: 847.91
C12: Ajuste a ingreso | D12: 25056.12 | E12: =D12/D6 -> 3305.5567
C13: CLIENTES | D13: =SUBTOTAL(9,D14:D20) -> 350253.08 | E13: =SUBTOTAL(9,E14:E20) -> 45885.614
C14: Client: Czarnikow- Sthepanie Rodriguez Lopez | D14: ='Diferencia en cambio'!$I$30 -> 41118.301 | E14: =D14/'Diferencia en cambio'!$L$30 -> 5412.3008
C15: Client:Energyzer-Ivan Chavez-Jerry García-Ronny Quan | D15: ='Diferencia en cambio'!$I$31 -> 220045.98 | E15: =D15/'Diferencia en cambio'!$L$31 -> 28731.467
C16: Client:Kairos-Ivan Chavez-Ruth Carolina Vasquez | D16: ='Diferencia en cambio'!$I$32 -> 7266.2065 | E16: =D16/'Diferencia en cambio'!$L$32 -> 948.75066
C17: Client: Opportunity-Edlin Ivette Poitan | D17: ='Caja QTQ'!$D$172 -> 13203.01 | E17: =D17/'Diferencia en cambio'!$L$33 -> 1751.4367
C18: Client: NotableGrowth, Inc | D18: ='Diferencia en cambio'!$I$34 -> 42983.472 | E18: =D18/'Diferencia en cambio'!$L$34 -> 5657.8087
C19: Client: Panthera, Inc | D19: ='Diferencia en cambio'!$I$35 -> 6832.27 | E19: =D19/'Diferencia en cambio'!$L$35 -> 908.7473
C20: Client: Bilingual Bridges, Inc | D20: ='Diferencia en cambio'!$I$36 -> 18803.838 | E20: =D20/'Diferencia en cambio'!$L$36 -> 2475.1029
C21: TOTAL INGRESOS | D21: =SUBTOTAL(9,D9:D18) -> 539754.7 | E21: =SUBTOTAL(9,E9:E18) -> 70884.05
B24: CUENTAS X PAGAR MES | D24: AGOSTO
B25: Factura | C25: PROVEEDOR | D25: VALOR QTQ | E25: VALOR USD | F25: Fecha vencimiento | G25: Estado | J25: KPI
C26: SEGURIDAD IGSS | D26: =SUBTOTAL(9,D27:D27) -> 48735.99 | E26: =SUBTOTAL(9,E27:E27) -> 4016.942
B27: 176206200 | C27: Pago planilla IGSS Julio | D27: 48735.99 | E27: =30448.42/$D$6 -> 4016.942 | F27: 45513 | G27: Cancelado | H27: =IF(OR(G27="Sin pagar",G27="Pagar"),NETWORKDAYS($E$4,F27,'Festivos Guatemala'!$A$3:$A$15),0) -> 0 | I27: =NETWORKDAYS($E$4,F27,'Festivos Guatemala'!$A$3:$A$15) -> 6 | J27: =H27 -> 0
C28: IMPUESTOS | D28: =SUBTOTAL(9,D29:D31) -> 16396.43 | E28: =SUBTOTAL(9,E29:E31) -> 2163.1174 | J28: =H28 -> 0
B29: 43809986140 | C29: Declaraguate ISR Julio | D29: 14909.47 | E29: =D29/$D$6 -> 1966.9485 | F29: 45518 | G29: Cancelado | H29: =IF(OR(G29="Sin pagar",G29="Pagar"),NETWORKDAYS($E$4,F29,'Festivos Guatemala'!$A$3:$A$15),0) -> 0 | I29: =NETWORKDAYS($E$4,F29,'Festivos Guatemala'!$A$3:$A$15) -> 9 | J29: =H29 -> 0
B30: 43802212905 | C30: Declaraguate ISR Agosto facturación Col Factura 5027 | D30: 1486.96 | E30: =D30/$D$6 -> 196.16887 | F30: 45517 | G30: Cancelado | H30: =IF(OR(G30="Sin pagar",G30="Pagar"),NETWORKDAYS($E$4,F30,'Festivos Guatemala'!$A$3:$A$15),0) -> 0 | I30: =NETWORKDAYS($E$4,F30,'Festivos Guatemala'!$A$3:$A$15) -> 8 | J30: =H30 -> 0
B31: 43589111783 | C31: Declaraguate IVA mes de Julio | D31: 0 | E31: =D31/$D$6 -> 0 | F31: 45535 | G31: Cancelado | H31: =IF(OR(G31="Sin pagar",G31="Pagar"),NETWORKDAYS($E$4,F31,'Festivos Guatemala'!$A$3:$A$15),0) -> 0 | I31: =NETWORKDAYS($E$4,F31,'Festivos Guatemala'!$A$3:$A$15) -> 21 | J31: =H31 -> 0
C32: SERVICIOS PROFESIONALES -REPRESENTACIÓN LEGAL | D32: =SUBTOTAL(9,D33:D37) -> 1682.11 | E32: =SUBTOTAL(9,E33:E37) -> 221.91425 | J32: =H32 -> 0
C33: Servicios profesionales Juan-Servicios prestados-Julio | D33: 840 | E33: =D33/$D$6 -> 110.81794 | F33: 45513 | G33: Cancelado | H33: =IF(OR(G33="Sin pagar",G33="Pagar"),NETWORKDAYS($E$4,F33,'Festivos Guatemala'!$A$3:$A$15),0) -> 0 | I33: =NETWORKDAYS($E$4,F33,'Festivos Guatemala'!$A$3:$A$15) -> 6 | J33: =H33 -> 0
C34: Servicios prestados por audiencias IGSS el día 11 y 31 de julio | D34: 842.11 | E34: =D34/$D$6 -> 111.09631 | F34: 45513 | G34: Cancelado | H34: =IF(OR(G34="Sin pagar",G34="Pagar"),NETWORKDAYS($E$4,F34,'Festivos Guatemala'!$A$3:$A$15),0) -> 0 | I34: =NETWORKDAYS($E$4,F34,'Festivos Guatemala'!$A$3:$A$15) -> 6 | J34: =H34 -> 0
B35: 954 | C35: Servicios profesionales Arnoldo prestados en Junio | D35: =1250*0 -> 0 | E35: =D35/$D$6 -> 0 | F35: 45534 | G35: Cancelado | H35: =IF(OR(G35="Sin pagar",G35="Pagar"),NETWORKDAYS($E$4,F35,'Festivos Guatemala'!$A$3:$A$15),0) -> 0 | I35: =NETWORKDAYS($E$4,F35,'Festivos Guatemala'!$A$3:$A$15) -> 21 | J35: =H35 -> 0 | M35: Sin radicar
B36: 1083 | C36: Servicios profesionales Arnoldo prestados en Julio | D36: =1200*0 -> 0 | E36: =D36/$D$6 -> 0 | F36: 45534 | G36: Cancelado | H36: =IF(OR(G36="Sin pagar",G36="Pagar"),NETWORKDAYS($E$4,F36,'Festivos Guatemala'!$A$3:$A$15),0) -> 0 | I36: =NETWORKDAYS($E$4,F36,'Festivos Guatemala'!$A$3:$A$15) -> 21 | J36: =H36 -> 0 | M36: Sin radicar
B37: 1086 | C37: Servicios profesionales Arnoldo prestados en Agosto | D37: =1200*0 -> 0 | E37: =D37/$D$6 -> 0 | F37: 45534 | G37: Cancelado | H37: =IF(OR(G37="Sin pagar",G37="Pagar"),NETWORKDAYS($E$4,F37,'Festivos Guatemala'!$A$3:$A$15),0) -> 0 | I37: =NETWORKDAYS($E$4,F37,'Festivos Guatemala'!$A$3:$A$15) -> 21 | J37: =H37 -> 0 | M37: Sin radicar
C38: PÓLIZAS Y SEGUROS | D38: =SUBTOTAL(9,D39:D44) -> 7561.0846 | E38: =SUBTOTAL(9,E39:E44) -> 997.50456
C39: Póliza de vida Ivan Estuardo Chavez Morales-USD-Póliza Vida | D39: =E39*$D$6 -> 417.4306 | E39: 55.07 | F39: 45527 | G39: Cancelado | H39: =IF(OR(G39="Sin pagar",G39="Pagar"),NETWORKDAYS($E$4,F39,'Festivos Guatemala'!$A$3:$A$15),0) -> 0 | I39: =NETWORKDAYS($E$4,F39,'Festivos Guatemala'!$A$3:$A$15) -> 16 | J39: =H39 -> 0
C40: Poliza de vida Rony Eduardo Quan Lam-USD-Póliza Vida | D40: =E40*$D$6 -> 1966.7826 | E40: 259.47 | F40: 45527 | G40: Cancelado | H40: =IF(OR(G40="Sin pagar",G40="Pagar"),NETWORKDAYS($E$4,F40,'Festivos Guatemala'!$A$3:$A$15),0) -> 0 | I40: =NETWORKDAYS($E$4,F40,'Festivos Guatemala'!$A$3:$A$15) -> 16 | J40: =H40 -> 0
C41: Poliza de vida Jerry García Carillo -USD-Póliza Vida | D41: =E41*$D$6 -> 1556.4014 | E41: 205.33 | F41: 45527 | G41: Cancelado | H41: =IF(OR(G41="Sin pagar",G41="Pagar"),NETWORKDAYS($E$4,F41,'Festivos Guatemala'!$A$3:$A$15),0) -> 0 | I41: =NETWORKDAYS($E$4,F41,'Festivos Guatemala'!$A$3:$A$15) -> 16 | J41: =H41 -> 0
C42: Póliza de vida Ivan Estuardo Chavez Morales-QTQ-GM | D42: 888.15 | E42: =D42/$D$6 -> 117.17018 | F42: 45527 | G42: Cancelado | H42: =IF(OR(G42="Sin pagar",G42="Pagar"),NETWORKDAYS($E$4,F42,'Festivos Guatemala'!$A$3:$A$15),0) -> 0 | I42: =NETWORKDAYS($E$4,F42,'Festivos Guatemala'!$A$3:$A$15) -> 16 | J42: =H42 -> 0
C43: Poliza de vida Rony Eduardo Quan Lam-QTQ-GM | D43: 903.72 | E43: =D43/$D$6 -> 119.22427 | F43: 45527 | G43: Cancelado | H43: =IF(OR(G43="Sin pagar",G43="Pagar"),NETWORKDAYS($E$4,F43,'Festivos Guatemala'!$A$3:$A$15),0) -> 0 | I43: =NETWORKDAYS($E$4,F43,'Festivos Guatemala'!$A$3:$A$15) -> 16 | J43: =H43 -> 0
C44: Poliza de vida Jerry García Carillo -QTQ-GM-Claudia Marisol Mayorga Ayala | D44: 1828.6 | E44: =D44/$D$6 -> 241.24011 | F44: 45527 | G44: Cancelado | H44: =IF(OR(G44="Sin pagar",G44="Pagar"),NETWORKDAYS($E$4,F44,'Festivos Guatemala'!$A$3:$A$15),0) -> 0 | I44: =NETWORKDAYS($E$4,F44,'Festivos Guatemala'!$A$3:$A$15) -> 16 | J44: =H44 -> 0
C45: COBROS ENTRE SUCURSALES | D45: =SUBTOTAL(9,D46:D48) -> 32054.51 | E45: =SUBTOTAL(9,E46:E48) -> 4073 | M45: =SUM(M46:M46) -> 17820150 | N45: =11000*4145.1 -> 45596100
B46: 4944 | C46: Cobro S&P a sucursal Guatemala -Junio | D46: =E46*7.87 -> 11864.025 | E46: =((1507.5)) -> 1507.5 | F46: 45533 | G46: Cancelado | H46: =IF(OR(G46="Sin pagar",G46="Pagar"),NETWORKDAYS($E$4,F46,'Festivos Guatemala'!$A$3:$A$15),0) -> 0 | I46: =NETWORKDAYS($E$4,F46,'Festivos Guatemala'!$A$3:$A$15) -> 20 | J46: =H46 -> 0 | M46: =(11000-6433.81)*3902.63 -> 17820150
B47: 5027 | C47: Cobro S&P a sucursal Guatemala -Julio | D47: =E47*7.87 -> 10085.405 | E47: =1281.5 -> 1281.5 | F47: 45533 | G47: Cancelado | H47: =IF(OR(G47="Sin pagar",G47="Pagar"),NETWORKDAYS($E$4,F47,'Festivos Guatemala'!$A$3:$A$15),0) -> 0 | I47: =NETWORKDAYS($E$4,F47,'Festivos Guatemala'!$A$3:$A$15) -> 20 | J47: =H47 -> 0 | M47: =(11000-6433.81)*3902.63 -> 17820150
B48: 5125 | C48: Cobro S&P a sucursal Guatemala -Agosto | D48: =E48*7.87 -> 10105.08 | E48: 1284 | F48: 45533 | G48: Cancelado | H48: =IF(OR(G48="Sin pagar",G48="Pagar"),NETWORKDAYS($E$4,F48,'Festivos Guatemala'!$A$3:$A$15),0) -> 0 | I48: =NETWORKDAYS($E$4,F48,'Festivos Guatemala'!$A$3:$A$15) -> 20 | J48: =H48 -> 0 | M48: =(11000-6433.81)*3902.63 -> 17820150
C49: TIQUETES AÉREOS , HOTELES | D49: =SUBTOTAL(9,D50:D51) -> 0 | E49: =SUBTOTAL(9,E50:E51) -> 0
C50: Tiquetes Ricardo y Eduard Visita Sucursal Guatemala | D50: =(((4000000/4150)*$D$6))*0 -> 0 | E50: =D50/D6 -> 0 | F50: 45534 | G50: Cancelado | H50: =IF(OR(G50="Sin pagar",G50="Pagar"),NETWORKDAYS($E$4,F50,'Festivos Guatemala'!$A$3:$A$15),0) -> 0 | I50: =NETWORKDAYS($E$4,F50,'Festivos Guatemala'!$A$3:$A$15) -> 21 | J50: =H50 -> 0
C51: Hoteles Ricardo y Eduard Visita Sucursal Guatemala | D51: =(((4000000/4150)*$D$6))*0 -> 0 | E51: =D51/D6 -> 0 | F51: 45534 | G51: Cancelado | H51: =IF(OR(G51="Sin pagar",G51="Pagar"),NETWORKDAYS($E$4,F51,'Festivos Guatemala'!$A$3:$A$15),0) -> 0 | I51: =NETWORKDAYS($E$4,F51,'Festivos Guatemala'!$A$3:$A$15) -> 21 | J51: =H51 -> 0
C52: COSTOS FINANCIEROS | D52: =SUBTOTAL(9,D53:D54) -> 359.8 | E52: =SUBTOTAL(9,E53:E54) -> 45.936675
C53: Gasto envio de divisas a Panamá | D53: 314.8 | E53: =D53/7.87 -> 40 | F53: 45533 | G53: Cancelado | H53: =IF(OR(G53="Sin pagar",G53="Pagar"),NETWORKDAYS($E$4,F53,'Festivos Guatemala'!$A$3:$A$15),0) -> 0 | I53: =NETWORKDAYS($E$4,F53,'Festivos Guatemala'!$A$3:$A$15) -> 20 | J53: =H53 -> 0
C54: Cobro emisión estado cuenta | D54: =15*3 -> 45 | E54: =D54/$D$6 -> 5.9366755 | F54: 45527 | G54: Cancelado | H54: =IF(OR(G54="Sin pagar",G54="Pagar"),NETWORKDAYS($E$4,F54,'Festivos Guatemala'!$A$3:$A$15),0) -> 0 | I54: =NETWORKDAYS($E$4,F54,'Festivos Guatemala'!$A$3:$A$15) -> 16 | J54: =H54 -> 0
C55: NÓMINAS | D55: =SUBTOTAL(9,D56:D66) -> 236248.57 | E55: =SUBTOTAL(9,E56:E66) -> 31167.358
C56: Stephanie Rodriguez Lopez-RF-Czarnikow-CC002 | D56: 28242.02 | E56: =D56/$D$6 -> 3725.8602 | F56: 45532 | G56: Cancelado | H56: =IF(OR(G56="Sin pagar",G56="Pagar"),NETWORKDAYS($E$4,F56,'Festivos Guatemala'!$A$3:$A$15),0) -> 0 | I56: =NETWORKDAYS($E$4,F56,'Festivos Guatemala'!$A$3:$A$15) -> 19 | J56: =H56 -> 0
C57: Ivan Estuardo Chávez Morales-Energyzer-CC004 | D57: 24970.21 | E57: =D57/$D$6 -> 3294.223 | F57: 45532 | G57: Cancelado | H57: =IF(OR(G57="Sin pagar",G57="Pagar"),NETWORKDAYS($E$4,F57,'Festivos Guatemala'!$A$3:$A$15),0) -> 0 | I57: =NETWORKDAYS($E$4,F57,'Festivos Guatemala'!$A$3:$A$15) -> 19 | J57: =H57 -> 0
C58: Jerry García-Energyzer-CC004 | D58: 53704.34 | E58: =D58/$D$6 -> 7085.0053 | F58: 45532 | G58: Cancelado | H58: =IF(OR(G58="Sin pagar",G58="Pagar"),NETWORKDAYS($E$4,F58,'Festivos Guatemala'!$A$3:$A$15),0) -> 0 | I58: =NETWORKDAYS($E$4,F58,'Festivos Guatemala'!$A$3:$A$15) -> 19 | J58: =H58 -> 0
C59: Ronny Eduardo Quan Lam-Energyzer-CC004 | D59: 66369.9 | E59: =D59/$D$6 -> 8755.9235 | F59: 45532 | G59: Cancelado | H59: =IF(OR(G59="Sin pagar",G59="Pagar"),NETWORKDAYS($E$4,F59,'Festivos Guatemala'!$A$3:$A$15),0) -> 0 | I59: =NETWORKDAYS($E$4,F59,'Festivos Guatemala'!$A$3:$A$15) -> 19 | J59: =H59 -> 0
C60: Ruth Carolina Vasquez Avelar de Rabanal-Kairos-CC005 | D60: 5732.9 | E60: =D60/$D$6 -> 756.31926 | F60: 45532 | G60: Cancelado | H60: =IF(OR(G60="Sin pagar",G60="Pagar"),NETWORKDAYS($E$4,F60,'Festivos Guatemala'!$A$3:$A$15),0) -> 0 | I60: =NETWORKDAYS($E$4,F60,'Festivos Guatemala'!$A$3:$A$15) -> 19 | J60: =H60 -> 0
C61: Edlin Ivette Ramos Poitan-Opportunnity-CC006 | D61: 10382.76 | E61: =D61/$D$6 -> 1369.7573 | F61: 45532 | G61: Cancelado | H61: =IF(OR(G61="Sin pagar",G61="Pagar"),NETWORKDAYS($E$4,F61,'Festivos Guatemala'!$A$3:$A$15),0) -> 0 | I61: =NETWORKDAYS($E$4,F61,'Festivos Guatemala'!$A$3:$A$15) -> 19 | J61: =H61 -> 0
C62: Miriam Lucia Morfin Gonzalez RF-Notable Growth INC-CC007 | D62: 29515.65 | E62: =D62/$D$6 -> 3893.8852 | F62: 45532 | G62: Cancelado | H62: =IF(OR(G62="Sin pagar",G62="Pagar"),NETWORKDAYS($E$4,F62,'Festivos Guatemala'!$A$3:$A$15),0) -> 0 | I62: =NETWORKDAYS($E$4,F62,'Festivos Guatemala'!$A$3:$A$15) -> 19 | J62: =H62 -> 0
C63: Barbara Isabela Escobar Anleu -Panthera-CC008 | D63: 5501.16 | E63: =D63/$D$6 -> 725.7467 | F63: 45532 | G63: Cancelado | H63: =IF(OR(G63="Sin pagar",G63="Pagar"),NETWORKDAYS($E$4,F63,'Festivos Guatemala'!$A$3:$A$15),0) -> 0 | I63: =NETWORKDAYS($E$4,F63,'Festivos Guatemala'!$A$3:$A$15) -> 19 | J63: =H63 -> 0
C64: Osman Alejandro López Acuta -Bilingual Bridges -CC009 | D64: 3943.21 | E64: =D64/$D$6 -> 520.2124 | F64: 45532 | G64: Cancelado | H64: =IF(OR(G64="Sin pagar",G64="Pagar"),NETWORKDAYS($E$4,F64,'Festivos Guatemala'!$A$3:$A$15),0) -> 0 | I64: =NETWORKDAYS($E$4,F64,'Festivos Guatemala'!$A$3:$A$15) -> 19 | J64: =H64 -> 0
C65: Sara María Arias Arrivillaga -Bilingual Bridges -CC009 | D65: 3943.21 | E65: =D65/$D$6 -> 520.2124 | F65: 45532 | G65: Cancelado | H65: =IF(OR(G65="Sin pagar",G65="Pagar"),NETWORKDAYS($E$4,F65,'Festivos Guatemala'!$A$3:$A$15),0) -> 0 | I65: =NETWORKDAYS($E$4,F65,'Festivos Guatemala'!$A$3:$A$15) -> 19 | J65: =H65 -> 0
C66: Natali Gabriela Ziller Santos -Bilingual Bridges -CC009 | D66: 3943.21 | E66: =D66/$D$6 -> 520.2124 | F66: 45532 | G66: Cancelado | H66: =IF(OR(G66="Sin pagar",G66="Pagar"),NETWORKDAYS($E$4,F66,'Festivos Guatemala'!$A$3:$A$15),0) -> 0 | I66: =NETWORKDAYS($E$4,F66,'Festivos Guatemala'!$A$3:$A$15) -> 19 | J66: =H66 -> 0
C67: REEMBOLSOS GASTOS | D67: =SUBTOTAL(9,D68:D72) -> 18655.381 | E67: =SUBTOTAL(9,E68:E72) -> 2461.132
C68: Jerry García-Energyzer-CC003-USD | D68: =E68*$D$6 -> 0 | E68: 0 | F68: 45532 | G68: Cancelado | H68: =IF(OR(G68="Sin pagar",G68="Pagar"),NETWORKDAYS($E$4,F68,'Festivos Guatemala'!$A$3:$A$15),0) -> 0 | I68: =NETWORKDAYS($E$4,F68,'Festivos Guatemala'!$A$3:$A$15) -> 19 | J68: =H68 -> 0
C69: Ronny Quan. Energyzer-CC003-USD | D69: =E69*$D$6 -> 6907.3508 | E69: 911.26 | F69: 45532 | G69: Cancelado | H69: =IF(OR(G69="Sin pagar",G69="Pagar"),NETWORKDAYS($E$4,F69,'Festivos Guatemala'!$A$3:$A$15),0) -> 0 | I69: =NETWORKDAYS($E$4,F69,'Festivos Guatemala'!$A$3:$A$15) -> 19 | J69: =H69 -> 0
C70: Ronny Quan. Energyzer-CC003-QTQ | D70: 6724.03 | E70: =D70/$D$6 -> 887.0752 | F70: 45532 | G70: Cancelado | H70: =IF(OR(G70="Sin pagar",G70="Pagar"),NETWORKDAYS($E$4,F70,'Festivos Guatemala'!$A$3:$A$15),0) -> 0 | I70: =NETWORKDAYS($E$4,F70,'Festivos Guatemala'!$A$3:$A$15) -> 19 | J70: =H70 -> 0
C71: Jerry García-Energyzer-CC003-QTQ | D71: 5024 | E71: =D71/$D$6 -> 662.79683 | F71: 45532 | G71: Cancelado | H71: =IF(OR(G71="Sin pagar",G71="Pagar"),NETWORKDAYS($E$4,F71,'Festivos Guatemala'!$A$3:$A$15),0) -> 0 | I71: =NETWORKDAYS($E$4,F71,'Festivos Guatemala'!$A$3:$A$15) -> 19 | J71: =H71 -> 0
C72: Mensualidad celulares empleados | D72: =(499*3*8)*0 -> 0 | E72: =D72/$D$6 -> 0 | F72: 45534 | G72: Cancelado | H72: =IF(OR(G72="Sin pagar",G72="Pagar"),NETWORKDAYS($E$4,F72,'Festivos Guatemala'!$A$3:$A$15),0) -> 0 | I72: =NETWORKDAYS($E$4,F72,'Festivos Guatemala'!$A$3:$A$15) -> 21 | J72: =H72 -> 0
C73: IMPREVISTO | D73: =SUBTOTAL(9,D74:D75) -> 0 | E73: =SUBTOTAL(9,E74:E75) -> 0
C74: Reembolso Gastos a Juan audicencia IGSS | D74: 0 | E74: =D74/$D$6 -> 0 | F74: 45535 | G74: Cancelado | H74: =IF(OR(G74="Sin pagar",G74="Pagar"),NETWORKDAYS($E$4,F74,'Festivos Guatemala'!$A$3:$A$15),0) -> 0 | I74: =NETWORKDAYS($E$4,F74,'Festivos Guatemala'!$A$3:$A$15) -> 21 | J74: =H74 -> 0
C75: Envío documentos Juan | D75: 0 | E75: =D75/$D$6 -> 0 | F75: 45535 | G75: Cancelado | H75: =IF(OR(G75="Sin pagar",G75="Pagar"),NETWORKDAYS($E$4,F75,'Festivos Guatemala'!$A$3:$A$15),0) -> 0 | I75: =NETWORKDAYS($E$4,F75,'Festivos Guatemala'!$A$3:$A$15) -> 21 | J75: =H75 -> 0
C76: TOTAL EGRESOS | D76: =SUBTOTAL(9,D26:D75) -> 361693.88 | E76: =SUBTOTAL(9,E26:E75) -> 45146.904
C78: SALDO | D78: =D21-D76 -> 178060.83 | E78: =E21-E76 -> 25737.146
C79: % | D79: =IF($D$21=0,0,D78/$D$21) -> 0.32989213 | E79: =IF($E$21=0,0,E78/$E$21) -> 0.36308797
C81: Fecha Inicial | D81: Fecha Final | E81: Valor VALOR QTQ | F81: Valor VALOR USD
C82: 45505 | D82: 45508 | E82: =SUMIFS($D$26:$D$79,$F$26:$F$79,">="&C82,$F$26:$F$79,"<="&D82,$G$26:$G$79,$D$95) -> 0 | F82: =SUMIFS($E$26:$E$79,$F$26:$F$79,">="&C82,$F$26:$F$79,"<="&D82,$G$26:$G$79,$D$95) -> 0
C83: 45509 | D83: 45515 | E83: =SUMIFS($D$26:$D$79,$F$26:$F$79,">="&C83,$F$26:$F$79,"<="&D83,$G$26:$G$79,$D$95) -> 0 | F83: =SUMIFS($E$26:$E$79,$F$26:$F$79,">="&C83,$F$26:$F$79,"<="&D83,$G$26:$G$79,$D$95) -> 0
C84: 45516 | D84: 45522 | E84: =SUMIFS($D$26:$D$79,$F$26:$F$79,">="&C84,$F$26:$F$79,"<="&D84,$G$26:$G$79,$D$95) -> 0 | F84: =SUMIFS($E$26:$E$79,$F$26:$F$79,">="&C84,$F$26:$F$79,"<="&D84,$G$26:$G$79,$D$95) -> 0 | G84: Impuestos
C85: 45523 | D85: 45529 | E85: =SUMIFS($D$26:$D$79,$F$26:$F$79,">="&C85,$F$26:$F$79,"<="&D85,$G$26:$G$79,$D$95) -> 0 | F85: =SUMIFS($E$26:$E$79,$F$26:$F$79,">="&C85,$F$26:$F$79,"<="&D85,$G$26:$G$79,$D$95) -> 0 | G85: Viaje, Pólizas, pago fac casa Matriz y pago servicios arnoldo
C86: 45530 | D86: 45535 | E86: =SUMIFS($D$26:$D$79,$F$26:$F$79,">="&C86,$F$26:$F$79,"<="&D86,$G$26:$G$79,$D$95) -> 0 | F86: =SUMIFS($E$26:$E$79,$F$26:$F$79,">="&C86,$F$26:$F$79,"<="&D86,$G$26:$G$79,$D$95) -> 0 | G86: Nómina y reembolso
C87: TOTAL EGRESOS | E87: =SUM(E82:E86) -> 0 | F87: =SUM(F82:F86) -> 0
C90: Bancos | D90: Bancos | E90: ='Caja QTQ'!$H$202+('Caja USD'!$H$85*$D$6) -> 178060.82 | F90: ='Caja USD'!H85+('Caja QTQ'!H202/'Flujo caja Agosto'!$D$6) -> 23490.874
D91: Pagos 19 al 31 agosto | E91: =SUM(E85:E86) -> 0 | F91: =SUM(F82:F86) -> 0
D92: Saldo | E92: =E90-E91 -> 178060.82 | F92: =F90-F91 -> 23490.874
D94: Cancelado | E94: =SUMIFS($D$26:$D$83,$F$26:$F$83,">="&C82,$F$26:$F$83,"<="&D86,$G$26:$G$83,$D$94) -> 361693.88 | F94: =SUMIFS($E$26:$E$83,$F$26:$F$83,">="&C82,$F$26:$F$83,"<="&D86,$G$26:$G$83,$D$94) -> 45146.904
D95: Sin Pagar | E95: =SUMIFS($D$26:$D$83,$F$26:$F$83,">="&C82,$F$26:$F$83,"<="&D86,$G$26:$G$83,$D$95) -> 0 | F95: =SUMIFS($E$26:$E$83,$F$26:$F$83,">="&C82,$F$26:$F$83,"<="&D86,$G$26:$G$83,$D$95) -> 0
D96: Total Egresos | E96: =SUM(E94:E95) -> 361693.88 | F96: =SUM(F94:F95) -> 45146.904
D97: Validación | E97: =E96-D76 -> 0 | F97: =F96-E76 -> 0
D99: Flujo Caja | E99: =D78 -> 178060.83
D100: Saldo Libro | E100: ='Caja QTQ'!H167+('Caja USD'!H70*7.6) -> 190098.57
D101: Diferencia | E101: =E99-E100 -> -12037.741 | F101: =E101/7.88 -> -1527.6321
D104: Flujo Caja | E104: =D78 -> 178060.83
D105: Saldo Libro | E105: ='Caja QTQ'!$H$202+('Caja USD'!H85*$D$6) -> 178060.82
D106: Diferencia QTZ | E106: =E105-E104 -> -0.0024195875
D107: Diferencia QTZ | E107: =E106/D6 -> -0.00031920679

Sheet Flujo caja Septiembre
D1: 42400
D4: Fecha de Elaboración: | E4: 45537
C6: Tasa de cambio: | D6: 7.55
D7: SEPTIEMBRE
D8: VALOR QTQ | E8: VALOR USD
C9: BANCOS | D9: =SUBTOTAL(9,D10:D12) -> 203374.26 | E9: =SUBTOTAL(9,E10:E12) -> 26936.989
C10: Bancos QTQ | D10: ='Caja QTQ'!$H$202 -> 167321.63 | E10: =D10/$D$6 -> 22161.806
C11: Bancos USD | D11: =E11*D6 -> 10696.689 | E11: ='Caja USD'!$H$85 -> 1416.78
C12: Diferencia en cambio | D12: 25355.943 | E12: =D12/D6 -> 3358.4031
C13: CLIENTES | D13: =SUBTOTAL(9,D14:D20) -> 357885.06 | E13: =SUBTOTAL(9,E14:E20) -> 47024.5
C14: Client: Czarnikow- Sthepanie Rodriguez Lopez | D14: ='Diferencia en cambio'!$I$37 -> 41117.357 | E14: =$D$14/'Diferencia en cambio'!$L$37 -> 5412.16
C15: Client:Energyzer-Ivan Chavez-Jerry García-Ronny Quan | D15: ='Diferencia en cambio'!$I$38 -> 226530.03 | E15: =D15/'Diferencia en cambio'!$L$38 -> 29732.93
C16: Client:Kairos-Ivan Chavez-Ruth Carolina Vasquez | D16: ='Diferencia en cambio'!$I$39 -> 7228.3614 | E16: =D16/'Diferencia en cambio'!$L$39 -> 948.75
C17: Client: Opportunity-Edlin Ivette Poitan | D17: ='Diferencia en cambio'!$I$40 -> 13543.911 | E17: =D17/'Diferencia en cambio'!$L$40 -> 1777.69
C18: Client: NotableGrowth, Inc | D18: ='Diferencia en cambio'!$I$41 -> 43829.26 | E18: =$D$18/'Diferencia en cambio'!$L$41 -> 5769.12
C19: Client: Panthera, Inc | D19: ='Caja QTQ'!$D$209 -> 6832.27 | E19: =D19/'Diferencia en cambio'!L42 -> 908.75
C20: Client: Bilingual Bridges, Inc | D20: ='Diferencia en cambio'!$I$43 -> 18803.873 | E20: =$D$20/'Diferencia en cambio'!$L$43 -> 2475.1
C21: TOTAL INGRESOS | D21: =SUBTOTAL(9,D9:D18) -> 535623.18 | E21: =SUBTOTAL(9,E9:E18) -> 70577.639
B24: CUENTAS X PAGAR MES | D24: AGOSTO
B25: Factura | C25: PROVEEDOR | D25: VALOR QTQ | E25: VALOR USD | F25: Fecha vencimiento | G25: Estado | J25: KPI
C26: SEGURIDAD IGSS | D26: =SUBTOTAL(9,D27:D27) -> 44275.81 | E26: =SUBTOTAL(9,E27:E27) -> 5864.3457
B27: 176206200 | C27: Pago planilla IGSS Agosto | D27: 44275.81 | E27: =D27/D6 -> 5864.3457 | F27: 45548 | G27: Cancelado | H27: =IF(OR(G27="Sin pagar",G27="Pagar"),NETWORKDAYS($E$4,F27,'Festivos Guatemala'!$A$3:$A$15),0) -> 0 | I27: =NETWORKDAYS($E$4,F27,'Festivos Guatemala'!$A$3:$A$15) -> 10 | J27: =H27 -> 0
C28: IMPUESTOS | D28: =SUBTOTAL(9,D29:D31) -> 13381.64 | E28: =SUBTOTAL(9,E29:E31) -> 1772.4026 | J28: =H28 -> 0
B29: 44130358346 | C29: Declaraguate ISR Agosto | D29: 11892.63 | E29: =D29/$D$6 -> 1575.1828 | F29: 45548 | G29: Cancelado | H29: =IF(OR(G29="Sin pagar",G29="Pagar"),NETWORKDAYS($E$4,F29,'Festivos Guatemala'!$A$3:$A$15),0) -> 0 | I29: =NETWORKDAYS($E$4,F29,'Festivos Guatemala'!$A$3:$A$15) -> 10 | J29: =H29 -> 0
B30: 44127378325 | C30: Declaraguate ISR no residentes facturación Col Factura 5125 Agosto | D30: 1489.01 | E30: =D30/$D$6 -> 197.21987 | F30: 45548 | G30: Cancelado | H30: =IF(OR(G30="Sin pagar",G30="Pagar"),NETWORKDAYS($E$4,F30,'Festivos Guatemala'!$A$3:$A$15),0) -> 0 | I30: =NETWORKDAYS($E$4,F30,'Festivos Guatemala'!$A$3:$A$15) -> 10 | J30: =H30 -> 0
B31: 43589111783 | C31: Declaraguate IVA mes de Agosto | D31: 0 | E31: =D31/$D$6 -> 0 | F31: 45565 | G31: Cancelado | H31: =IF(OR(G31="Sin pagar",G31="Pagar"),NETWORKDAYS($E$4,F31,'Festivos Guatemala'!$A$3:$A$15),0) -> 0 | I31: =NETWORKDAYS($E$4,F31,'Festivos Guatemala'!$A$3:$A$15) -> 21 | J31: =H31 -> 0
C32: SERVICIOS PROFESIONALES -REPRESENTACIÓN LEGAL | D32: =SUBTOTAL(9,D33:D37) -> 840 | E32: =SUBTOTAL(9,E33:E37) -> 111.25828 | J32: =H32 -> 0
C33: Servicios profesionales Juan-Servicios prestados-Agosto | D33: 840 | E33: =D33/$D$6 -> 111.25828 | F33: 45541 | G33: Cancelado | H33: =IF(OR(G33="Sin pagar",G33="Pagar"),NETWORKDAYS($E$4,F33,'Festivos Guatemala'!$A$3:$A$15),0) -> 0 | I33: =NETWORKDAYS($E$4,F33,'Festivos Guatemala'!$A$3:$A$15) -> 5 | J33: =H33 -> 0
B34: 954 | C34: Servicios profesionales Arnoldo prestados en Junio | D34: =1250*0 -> 0 | E34: =D34/$D$6 -> 0 | F34: 45565 | G34: Cancelado | H34: =IF(OR(G34="Sin pagar",G34="Pagar"),NETWORKDAYS($E$4,F34,'Festivos Guatemala'!$A$3:$A$15),0) -> 0 | I34: =NETWORKDAYS($E$4,F34,'Festivos Guatemala'!$A$3:$A$15) -> 21 | J34: =H34 -> 0 | M34: Sin radicar
B35: 1083 | C35: Servicios profesionales Arnoldo prestados en Julio | D35: =1200*0 -> 0 | E35: =D35/$D$6 -> 0 | F35: 45565 | G35: Cancelado | H35: =IF(OR(G35="Sin pagar",G35="Pagar"),NETWORKDAYS($E$4,F35,'Festivos Guatemala'!$A$3:$A$15),0) -> 0 | I35: =NETWORKDAYS($E$4,F35,'Festivos Guatemala'!$A$3:$A$15) -> 21 | J35: =H35 -> 0 | M35: Sin radicar
B36: 1086 | C36: Servicios profesionales Arnoldo prestados en Agosto | D36: =1200*0 -> 0 | E36: =D36/$D$6 -> 0 | F36: 45565 | G36: Cancelado | H36: =IF(OR(G36="Sin pagar",G36="Pagar"),NETWORKDAYS($E$4,F36,'Festivos Guatemala'!$A$3:$A$15),0) -> 0 | I36: =NETWORKDAYS($E$4,F36,'Festivos Guatemala'!$A$3:$A$15) -> 21 | J36: =H36 -> 0 | M36: Sin radicar
B37: 1091 | C37: Servicios profesionales Arnoldo prestados en Septiembre | D37: =1200*0 -> 0 | E37: =D37/$D$6 -> 0 | F37: 45565 | G37: Cancelado | H37: =IF(OR(G37="Sin pagar",G37="Pagar"),NETWORKDAYS($E$4,F37,'Festivos Guatemala'!$A$3:$A$15),0) -> 0 | I37: =NETWORKDAYS($E$4,F37,'Festivos Guatemala'!$A$3:$A$15) -> 21 | J37: =H37 -> 0 | M37: Sin radicar
C38: PÓLIZAS Y SEGUROS | D38: =SUBTOTAL(9,D39:D45) -> 8389.0485 | E38: =SUBTOTAL(9,E39:E45) -> 1111.1323
C39: Póliza de vida Ivan Estuardo Chavez Morales-USD-Póliza Vida | D39: =E39*$D$6 -> 415.7785 | E39: 55.07 | F39: 45558 | G39: Cancelado | H39: =IF(OR(G39="Sin pagar",G39="Pagar"),NETWORKDAYS($E$4,F39,'Festivos Guatemala'!$A$3:$A$15),0) -> 0 | I39: =NETWORKDAYS($E$4,F39,'Festivos Guatemala'!$A$3:$A$15) -> 16 | J39: =H39 -> 0
C40: Poliza de vida Rony Eduardo Quan Lam-USD-Póliza Vida | D40: =E40*$D$6 -> 1958.9985 | E40: 259.47 | F40: 45558 | G40: Cancelado | H40: =IF(OR(G40="Sin pagar",G40="Pagar"),NETWORKDAYS($E$4,F40,'Festivos Guatemala'!$A$3:$A$15),0) -> 0 | I40: =NETWORKDAYS($E$4,F40,'Festivos Guatemala'!$A$3:$A$15) -> 16 | J40: =H40 -> 0
C41: Poliza de vida Jerry García Carillo -USD-Póliza Vida | D41: =E41*$D$6 -> 1550.2415 | E41: 205.33 | F41: 45558 | G41: Cancelado | H41: =IF(OR(G41="Sin pagar",G41="Pagar"),NETWORKDAYS($E$4,F41,'Festivos Guatemala'!$A$3:$A$15),0) -> 0 | I41: =NETWORKDAYS($E$4,F41,'Festivos Guatemala'!$A$3:$A$15) -> 16 | J41: =H41 -> 0
C42: Póliza de vida Miriam Lucian Morfin González-QTQ-GM ( Incluisíon) | D42: 843.56 | E42: =D42/$D$6 -> 111.7298 | F42: 45545 | G42: Cancelado | H42: =IF(OR(G42="Sin pagar",G42="Pagar"),NETWORKDAYS($E$4,F42,'Festivos Guatemala'!$A$3:$A$15),0) -> 0 | I42: =NETWORKDAYS($E$4,F42,'Festivos Guatemala'!$A$3:$A$15) -> 7 | J42: =H42 -> 0
C43: Póliza de vida Ivan Estuardo Chavez Morales-QTQ-GM | D43: 888.15 | E43: =D43/$D$6 -> 117.63576 | F43: 45558 | G43: Cancelado | H43: =IF(OR(G43="Sin pagar",G43="Pagar"),NETWORKDAYS($E$4,F43,'Festivos Guatemala'!$A$3:$A$15),0) -> 0 | I43: =NETWORKDAYS($E$4,F43,'Festivos Guatemala'!$A$3:$A$15) -> 16 | J43: =H43 -> 0
C44: Poliza de vida Rony Eduardo Quan Lam-QTQ-GM | D44: 903.72 | E44: =D44/$D$6 -> 119.69801 | F44: 45558 | G44: Cancelado | H44: =IF(OR(G44="Sin pagar",G44="Pagar"),NETWORKDAYS($E$4,F44,'Festivos Guatemala'!$A$3:$A$15),0) -> 0 | I44: =NETWORKDAYS($E$4,F44,'Festivos Guatemala'!$A$3:$A$15) -> 16 | J44: =H44 -> 0
C45: Poliza de vida Jerry García Carillo -QTQ-GM-Claudia Marisol Mayorga Ayala | D45: 1828.6 | E45: =D45/$D$6 -> 242.19868 | F45: 45558 | G45: Cancelado | H45: =IF(OR(G45="Sin pagar",G45="Pagar"),NETWORKDAYS($E$4,F45,'Festivos Guatemala'!$A$3:$A$15),0) -> 0 | I45: =NETWORKDAYS($E$4,F45,'Festivos Guatemala'!$A$3:$A$15) -> 16 | J45: =H45 -> 0
C46: COBROS ENTRE SUCURSALES | D46: =SUBTOTAL(9,D47:D47) -> 0 | E46: =SUBTOTAL(9,E47:E47) -> 0 | M46: =SUM(#REF!) -> #REF! | N46: =11000*4145.1 -> 45596100
B47: 5229 | C47: Cobro S&P a sucursal Guatemala -Septiembre | D47: =E47*D6 -> 0 | E47: =1313.37*0 -> 0 | F47: 45565 | G47: Cancelado | H47: =IF(OR(G47="Sin pagar",G47="Pagar"),NETWORKDAYS($E$4,F47,'Festivos Guatemala'!$A$3:$A$15),0) -> 0 | I47: =NETWORKDAYS($E$4,F47,'Festivos Guatemala'!$A$3:$A$15) -> 21 | J47: =H47 -> 0 | M47: =(11000-6433.81)*3902.63 -> 17820150
C48: TIQUETES AÉREOS , HOTELES | D48: =SUBTOTAL(9,D49:D50) -> 0 | E48: =SUBTOTAL(9,E49:E50) -> 0
C49: Tiquetes Ricardo y Eduard Visita Sucursal Guatemala | D49: =(((4000000/4150)*$D$6))*0 -> 0 | E49: =D49/D6 -> 0 | F49: 45551 | G49: Cancelado | H49: =IF(OR(G49="Sin pagar",G49="Pagar"),NETWORKDAYS($E$4,F49,'Festivos Guatemala'!$A$3:$A$15),0) -> 0 | I49: =NETWORKDAYS($E$4,F49,'Festivos Guatemala'!$A$3:$A$15) -> 11 | J49: =H49 -> 0
C50: Hoteles Ricardo y Eduard Visita Sucursal Guatemala | D50: =(((4000000/4150)*$D$6))*0 -> 0 | E50: =D50/D6 -> 0 | F50: 45551 | G50: Cancelado | H50: =IF(OR(G50="Sin pagar",G50="Pagar"),NETWORKDAYS($E$4,F50,'Festivos Guatemala'!$A$3:$A$15),0) -> 0 | I50: =NETWORKDAYS($E$4,F50,'Festivos Guatemala'!$A$3:$A$15) -> 11 | J50: =H50 -> 0
C51: COSTOS FINANCIEROS | D51: =SUBTOTAL(9,D52:D54) -> 477.85 | E51: =SUBTOTAL(9,E52:E54) -> 60.960265
C52: Gasto envio de divisas a España | D52: =E52*7.87 -> 118.05 | E52: 15 | F52: 45541 | G52: Cancelado | H52: =IF(OR(G52="Sin pagar",G52="Pagar"),NETWORKDAYS($E$4,F52,'Festivos Guatemala'!$A$3:$A$15),0) -> 0 | I52: =NETWORKDAYS($E$4,F52,'Festivos Guatemala'!$A$3:$A$15) -> 5 | J52: =H52 -> 0
C53: Gasto envio de divisas a Panamá | D53: 314.8 | E53: =D53/7.87 -> 40 | F53: 45565 | G53: Cancelado | H53: =IF(OR(G53="Sin pagar",G53="Pagar"),NETWORKDAYS($E$4,F53,'Festivos Guatemala'!$A$3:$A$15),0) -> 0 | I53: =NETWORKDAYS($E$4,F53,'Festivos Guatemala'!$A$3:$A$15) -> 21 | J53: =H53 -> 0
C54: Cobro emisión estado cuenta | D54: =15*3 -> 45 | E54: =D54/$D$6 -> 5.9602649 | F54: 45565 | G54: Cancelado | H54: =IF(OR(G54="Sin pagar",G54="Pagar"),NETWORKDAYS($E$4,F54,'Festivos Guatemala'!$A$3:$A$15),0) -> 0 | I54: =NETWORKDAYS($E$4,F54,'Festivos Guatemala'!$A$3:$A$15) -> 21 | J54: =H54 -> 0
C55: NÓMINAS | D55: =SUBTOTAL(9,D56:D66) -> 236428.61 | E55: =SUBTOTAL(9,E56:E66) -> 31315.048
C56: Stephanie Rodriguez Lopez-RF-Czarnikow-CC002 | D56: 28242.02 | E56: =D56/$D$6 -> 3740.6649 | F56: 45562 | G56: Cancelado | H56: =IF(OR(G56="Sin pagar",G56="Pagar"),NETWORKDAYS($E$4,F56,'Festivos Guatemala'!$A$3:$A$15),0) -> 0 | I56: =NETWORKDAYS($E$4,F56,'Festivos Guatemala'!$A$3:$A$15) -> 20 | J56: =H56 -> 0
C57: Ivan Estuardo Chávez Morales-Energyzer-CC004 | D57: 24970.21 | E57: =D57/$D$6 -> 3307.3126 | F57: 45562 | G57: Cancelado | H57: =IF(OR(G57="Sin pagar",G57="Pagar"),NETWORKDAYS($E$4,F57,'Festivos Guatemala'!$A$3:$A$15),0) -> 0 | I57: =NETWORKDAYS($E$4,F57,'Festivos Guatemala'!$A$3:$A$15) -> 20 | J57: =H57 -> 0
C58: Jerry García-Energyzer-CC004 | D58: 53704.34 | E58: =D58/$D$6 -> 7113.1576 | F58: 45562 | G58: Cancelado | H58: =IF(OR(G58="Sin pagar",G58="Pagar"),NETWORKDAYS($E$4,F58,'Festivos Guatemala'!$A$3:$A$15),0) -> 0 | I58: =NETWORKDAYS($E$4,F58,'Festivos Guatemala'!$A$3:$A$15) -> 20 | J58: =H58 -> 0
C59: Ronny Eduardo Quan Lam-Energyzer-CC004 | D59: 66369.9 | E59: =D59/$D$6 -> 8790.7152 | F59: 45562 | G59: Cancelado | H59: =IF(OR(G59="Sin pagar",G59="Pagar"),NETWORKDAYS($E$4,F59,'Festivos Guatemala'!$A$3:$A$15),0) -> 0 | I59: =NETWORKDAYS($E$4,F59,'Festivos Guatemala'!$A$3:$A$15) -> 20 | J59: =H59 -> 0
C60: Ruth Carolina Vasquez Avelar de Rabanal-Kairos-CC005 | D60: 5732.9 | E60: =D60/$D$6 -> 759.3245 | F60: 45562 | G60: Cancelado | H60: =IF(OR(G60="Sin pagar",G60="Pagar"),NETWORKDAYS($E$4,F60,'Festivos Guatemala'!$A$3:$A$15),0) -> 0 | I60: =NETWORKDAYS($E$4,F60,'Festivos Guatemala'!$A$3:$A$15) -> 20 | J60: =H60 -> 0
C61: Edlin Ivette Ramos Poitan-Opportunnity-CC006 | D61: 10562.8 | E61: =D61/$D$6 -> 1399.0464 | F61: 45562 | G61: Cancelado | H61: =IF(OR(G61="Sin pagar",G61="Pagar"),NETWORKDAYS($E$4,F61,'Festivos Guatemala'!$A$3:$A$15),0) -> 0 | I61: =NETWORKDAYS($E$4,F61,'Festivos Guatemala'!$A$3:$A$15) -> 20 | J61: =H61 -> 0
C62: Miriam Lucia Morfin Gonzalez RF-Notable Growth INC-CC007 | D62: 29515.65 | E62: =D62/$D$6 -> 3909.3576 | F62: 45562 | G62: Cancelado | H62: =IF(OR(G62="Sin pagar",G62="Pagar"),NETWORKDAYS($E$4,F62,'Festivos Guatemala'!$A$3:$A$15),0) -> 0 | I62: =NETWORKDAYS($E$4,F62,'Festivos Guatemala'!$A$3:$A$15) -> 20 | J62: =H62 -> 0
C63: Barbara Isabela Escobar Anleu -Panthera-CC008 | D63: 5501.16 | E63: =D63/$D$6 -> 728.63046 | F63: 45562 | G63: Cancelado | H63: =IF(OR(G63="Sin pagar",G63="Pagar"),NETWORKDAYS($E$4,F63,'Festivos Guatemala'!$A$3:$A$15),0) -> 0 | I63: =NETWORKDAYS($E$4,F63,'Festivos Guatemala'!$A$3:$A$15) -> 20 | J63: =H63 -> 0
C64: Osman Alejandro López Acuta -Bilingual Bridges -CC009 | D64: 3943.21 | E64: =D64/$D$6 -> 522.27947 | F64: 45562 | G64: Cancelado | H64: =IF(OR(G64="Sin pagar",G64="Pagar"),NETWORKDAYS($E$4,F64,'Festivos Guatemala'!$A$3:$A$15),0) -> 0 | I64: =NETWORKDAYS($E$4,F64,'Festivos Guatemala'!$A$3:$A$15) -> 20 | J64: =H64 -> 0
C65: Sara María Arias Arrivillaga -Bilingual Bridges -CC009 | D65: 3943.21 | E65: =D65/$D$6 -> 522.27947 | F65: 45562 | G65: Cancelado | H65: =IF(OR(G65="Sin pagar",G65="Pagar"),NETWORKDAYS($E$4,F65,'Festivos Guatemala'!$A$3:$A$15),0) -> 0 | I65: =NETWORKDAYS($E$4,F65,'Festivos Guatemala'!$A$3:$A$15) -> 20 | J65: =H65 -> 0
C66: Natali Gabriela Ziller Santos -Bilingual Bridges -CC009 | D66: 3943.21 | E66: =D66/$D$6 -> 522.27947 | F66: 45562 | G66: Cancelado | H66: =IF(OR(G66="Sin pagar",G66="Pagar"),NETWORKDAYS($E$4,F66,'Festivos Guatemala'!$A$3:$A$15),0) -> 0 | I66: =NETWORKDAYS($E$4,F66,'Festivos Guatemala'!$A$3:$A$15) -> 20 | J66: =H66 -> 0
C67: REEMBOLSOS GASTOS | D67: =SUBTOTAL(9,D68:D72) -> 25527.728 | E67: =SUBTOTAL(9,E68:E72) -> 3381.156
C68: Ronny Quan. Energyzer-CC003-USD | D68: =E68*$D$6 -> 6433.053 | E68: 852.06 | F68: 45561 | G68: Cancelado | H68: =IF(OR(G68="Sin pagar",G68="Pagar"),NETWORKDAYS($E$4,F68,'Festivos Guatemala'!$A$3:$A$15),0) -> 0 | I68: =NETWORKDAYS($E$4,F68,'Festivos Guatemala'!$A$3:$A$15) -> 19 | J68: =H68 -> 0
C69: Jerry García-Energyzer-CC003-USD | D69: =E69*D6 -> 12934.585 | E69: 1713.19 | F69: 45561 | G69: Cancelado | H69: =IF(OR(G69="Sin pagar",G69="Pagar"),NETWORKDAYS($E$4,F69,'Festivos Guatemala'!$A$3:$A$15),0) -> 0 | I69: =NETWORKDAYS($E$4,F69,'Festivos Guatemala'!$A$3:$A$15) -> 19 | J69: =H69 -> 0
C70: Ronny Quan. Energyzer-CC003-QTQ | D70: 6160.09 | E70: =D70/$D$6 -> 815.90596 | F70: 45561 | G70: Cancelado | H70: =IF(OR(G70="Sin pagar",G70="Pagar"),NETWORKDAYS($E$4,F70,'Festivos Guatemala'!$A$3:$A$15),0) -> 0 | I70: =NETWORKDAYS($E$4,F70,'Festivos Guatemala'!$A$3:$A$15) -> 19 | J70: =H70 -> 0
C71: Jerry García-Energyzer-CC003-QTQ | D71: 0 | E71: =D71/$D$6 -> 0 | F71: 45565 | G71: Cancelado | H71: =IF(OR(G71="Sin pagar",G71="Pagar"),NETWORKDAYS($E$4,F71,'Festivos Guatemala'!$A$3:$A$15),0) -> 0 | I71: =NETWORKDAYS($E$4,F71,'Festivos Guatemala'!$A$3:$A$15) -> 21 | J71: =H71 -> 0
C72: Mensualidad celulares empleados | D72: =(499*3*8)*0 -> 0 | E72: =D72/$D$6 -> 0 | F72: 45534 | G72: Cancelado | H72: =IF(OR(G72="Sin pagar",G72="Pagar"),NETWORKDAYS($E$4,F72,'Festivos Guatemala'!$A$3:$A$15),0) -> 0 | I72: =NETWORKDAYS($E$4,F72,'Festivos Guatemala'!$A$3:$A$15) -> -2 | J72: =H72 -> 0
C73: IMPREVISTO | D73: =SUBTOTAL(9,D74:D75) -> 1888.8 | E73: =SUBTOTAL(9,E74:E75) -> 240
C74: Compra Sim Card Claro-Se paga por agencia-Juan 03/09/24 | D74: 0 | E74: =D74/$D$6 -> 0 | F74: 45565 | G74: Cancelado | H74: =IF(OR(G74="Sin pagar",G74="Pagar"),NETWORKDAYS($E$4,F74,'Festivos Guatemala'!$A$3:$A$15),0) -> 0 | I74: =NETWORKDAYS($E$4,F74,'Festivos Guatemala'!$A$3:$A$15) -> 21 | J74: =H74 -> 0
C75: The wisser Seeker -Assessment Auxiliar de Cartera y Facturación-TWS-24-00113 | D75: =E75*7.87 -> 1888.8 | E75: 240 | F75: 45541 | G75: Cancelado | H75: =IF(OR(G75="Sin pagar",G75="Pagar"),NETWORKDAYS($E$4,F75,'Festivos Guatemala'!$A$3:$A$15),0) -> 0 | I75: =NETWORKDAYS($E$4,F75,'Festivos Guatemala'!$A$3:$A$15) -> 5 | J75: =H75 -> 0
C76: TOTAL EGRESOS | D76: =SUBTOTAL(9,D26:D75) -> 331209.49 | E76: =SUBTOTAL(9,E26:E75) -> 43856.303
C78: SALDO | D78: =D21-D76 -> 204413.7 | E78: =E21-E76 -> 26721.336
C79: % | D79: =IF($D$21=0,0,D78/$D$21) -> 0.38163713 | E79: =IF($E$21=0,0,E78/$E$21) -> 0.37860909
C81: Fecha Inicial | D81: Fecha Final | E81: Valor VALOR QTQ | F81: Valor VALOR USD
C82: 45537 | D82: 45543 | E82: =SUMIFS($D$26:$D$79,$F$26:$F$79,">="&C82,$F$26:$F$79,"<="&D82,$G$26:$G$79,$D$94) -> 0 | F82: =SUMIFS($E$26:$E$79,$F$26:$F$79,">="&C82,$F$26:$F$79,"<="&D82,$G$26:$G$79,$D$94) -> 0 | G82: The wisser Seeker
C83: 45544 | D83: 45550 | E83: =SUMIFS($D$26:$D$79,$F$26:$F$79,">="&C83,$F$26:$F$79,"<="&D83,$G$26:$G$79,$D$94) -> 0 | F83: =SUMIFS($E$26:$E$79,$F$26:$F$79,">="&C83,$F$26:$F$79,"<="&D83,$G$26:$G$79,$D$94) -> 0 | G83: Impuestos
C84: 45551 | D84: 45557 | E84: =SUMIFS($D$26:$D$79,$F$26:$F$79,">="&C84,$F$26:$F$79,"<="&D84,$G$26:$G$79,$D$94) -> 0 | F84: =SUMIFS($E$26:$E$79,$F$26:$F$79,">="&C84,$F$26:$F$79,"<="&D84,$G$26:$G$79,$D$94) -> 0 | G84: Viaje, Pólizas, pago fac casa Matriz y pago servicios arnoldo
C85: 45558 | D85: 45565 | E85: =SUMIFS($D$26:$D$79,$F$26:$F$79,">="&C85,$F$26:$F$79,"<="&D85,$G$26:$G$79,$D$94) -> 0 | F85: =SUMIFS($E$26:$E$79,$F$26:$F$79,">="&C85,$F$26:$F$79,"<="&D85,$G$26:$G$79,$D$94) -> 0 | G85: Nóminas , reembolsos, envio divisas
C86: TOTAL EGRESOS | E86: =SUM(E82:E85) -> 0 | F86: =SUM(F82:F85) -> 0
D89: Bancos | E89: ='Caja QTQ'!$H$229+('Caja USD'!$H$102*$D$6) -> 204413.7 | F89: ='Caja USD'!H102+('Caja QTQ'!H229/'Flujo caja Septiembre'!$D$6) -> 27074.662
D90: Pagos 02 al 22 sept | E90: =SUM(E82:E84) -> 0 | F90: =SUM(F82:F84) -> 0
D91: Saldo | E91: =E89-E90 -> 204413.7 | F91: =F89-F90 -> 27074.662
D93: Cancelado | E93: =SUMIFS($D$26:$D$88,$F$26:$F$88,">="&C82,$F$26:$F$88,"<="&D85,$G$26:$G$88,$D$93) -> 331209.49 | F93: =SUMIFS($E$26:$E$88,$F$26:$F$88,">="&C82,$F$26:$F$88,"<="&D85,$G$26:$G$88,$D$93) -> 43856.303
D94: Sin Pagar | E94: =SUMIFS($D$26:$D$88,$F$26:$F$88,">="&C82,$F$26:$F$88,"<="&D85,$G$26:$G$88,$D$94) -> 0 | F94: =SUMIFS($E$26:$E$88,$F$26:$F$88,">="&C82,$F$26:$F$88,"<="&D85,$G$26:$G$88,$D$94) -> 0
D95: Total Egresos | E95: =SUM(E93:E94) -> 331209.49 | F95: =SUM(F93:F94) -> 43856.303
D96: Validación | E96: =E95-D76 -> 0 | F96: =F95-E76 -> 0
D98: Flujo Caja | E98: =D78 -> 204413.7
D99: Saldo Libro | E99: ='Caja QTQ'!H167+('Caja USD'!H70*7.6) -> 190098.57
D100: Diferencia | E100: =E98-E99 -> 14315.127 | F100: =E100/7.88 -> 1816.6405
D103: Flujo Caja | E103: =$D$78 -> 204413.7
D104: Saldo Libro | E104: ='Caja QTQ'!$H$229+('Caja USD'!$H$102*$D$6) -> 204413.7
D105: Diferencia QTZ | E105: =E104-E103 -> 0
E106: =E105/$D$6 -> 0

Sheet Flujo caja Octubre
D1: 42400
D4: Fecha de Elaboración: | E4: 45566
C6: Tasa de cambio: | D6: 7.58
D7: AGOSTO
D8: VALOR QTQ | E8: VALOR USD
C9: BANCOS | D9: =SUBTOTAL(9,D10:D12) -> 229653.34 | E9: =SUBTOTAL(9,E10:E12) -> 30297.274
C10: Bancos QTQ | D10: ='Caja QTQ'!$H$229 -> 201909.66 | E10: =D10/$D$6 -> 26637.159
C11: Bancos USD | D11: =E11*D6 -> 2513.9828 | E11: ='Caja USD'!$H$102 -> 331.66
C12: Ingreso | D12: 25229.69 | E12: =D12/$D$6 -> 3328.4551
C13: CLIENTES | D13: =SUBTOTAL(9,D14:D20) -> 386111.86 | E13: =SUBTOTAL(9,E14:E20) -> 50575.576
C14: Client: Czarnikow- Sthepanie Rodriguez Lopez-Remotefist | D14: ='Diferencia en cambio'!$I$44 -> 41118.426 | E14: =$D$14/'Diferencia en cambio'!$L$44 -> 5412.3008
C15: Client:Energyzer-Ivan Chavez-Jerry García-Ronny Quan-Safeguard | D15: ='Diferencia en cambio'!$I$45 -> 254916.3 | E15: =$D$15/'Diferencia en cambio'!$L$45 -> 33283.886
C16: Client:Kairos-Ivan Chavez-Ruth Carolina Vasquez-Safeguard | D16: ='Diferencia en cambio'!$I$46 -> 7162.6735 | E16: =$D$16/'Diferencia en cambio'!$L$46 -> 948.75119
C17: Client: Opportunity-Edlin Ivette Poitan-Safeguard | D17: ='Diferencia en cambio'!$I$47 -> 13420.826 | E17: =$D$17/'Diferencia en cambio'!$L$47 -> 1777.6916
C18: Client: NotableGrowth, Inc-Remotefist | D18: ='Diferencia en cambio'!$I$48 -> 43829.079 | E18: =$D$18/'Diferencia en cambio'!$L$48 -> 5769.0963
C19: Client: Panthera, Inc-Safeguard | D19: ='Diferencia en cambio'!$I$49 -> 6860.6609 | E19: =$D$19/'Diferencia en cambio'!$L$49 -> 908.7473
C20: Client: Bilingual Bridges, Inc-Remotefist | D20: ='Diferencia en cambio'!$I$50 -> 18803.895 | E20: =$D$20/'Diferencia en cambio'!$L$50 -> 2475.1029
C21: TOTAL INGRESOS | D21: =SUBTOTAL(9,D9:D18) -> 590100.64 | E21: =SUBTOTAL(9,E9:E18) -> 77489
B24: CUENTAS X PAGAR MES | D24: AGOSTO
B25: Factura | C25: PROVEEDOR | D25: VALOR QTQ | E25: VALOR USD | F25: Fecha vencimiento | G25: Estado | J25: KPI
C26: SEGURIDAD IGSS | D26: =SUBTOTAL(9,D27:D27) -> 44275.81 | E26: =SUBTOTAL(9,E27:E27) -> 5841.1359
B27: 176206200 | C27: Pago planilla IGSS Septiembre | D27: 44275.81 | E27: =D27/D6 -> 5841.1359 | F27: 45568 | G27: Cancelado | H27: =IF(OR(G27="Sin pagar",G27="Pagar"),NETWORKDAYS($E$4,F27,'Festivos Guatemala'!$A$3:$A$15),0) -> 0 | I27: =NETWORKDAYS($E$4,F27,'Festivos Guatemala'!$A$3:$A$15) -> 3 | J27: =H27 -> 0
C28: IMPUESTOS | D28: =SUBTOTAL(9,D29:D32) -> 17360.19 | E28: =SUBTOTAL(9,E29:E32) -> 2290.2625 | J28: =H28 -> 0
B29: 44466513563 | C29: Declaraguate ISR Septiembre | D29: 11902.13 | E29: =D29/$D$6 -> 1570.2018 | F29: 45577 | G29: Cancelado | H29: =IF(OR(G29="Sin pagar",G29="Pagar"),NETWORKDAYS($E$4,F29,'Festivos Guatemala'!$A$3:$A$15),0) -> 0 | I29: =NETWORKDAYS($E$4,F29,'Festivos Guatemala'!$A$3:$A$15) -> 9 | J29: =H29 -> 0
B30: 44466657649 | C30: Declaraguate ISR no residentes facturación Col Factura 5229 Septiembre | D30: 1522.3 | E30: =D30/$D$6 -> 200.83113 | F30: 45579 | G30: Cancelado | H30: =IF(OR(G30="Sin pagar",G30="Pagar"),NETWORKDAYS($E$4,F30,'Festivos Guatemala'!$A$3:$A$15),0) -> 0 | I30: =NETWORKDAYS($E$4,F30,'Festivos Guatemala'!$A$3:$A$15) -> 10 | J30: =H30 -> 0
B31: 44417935357 | C31: Declaraguate ISO del 3re. Trimestre 2024. | D31: 558.38 | E31: =D31/$D$6 -> 73.664908 | F31: 45579 | G31: Cancelado | H31: =IF(OR(G31="Sin pagar",G31="Pagar"),NETWORKDAYS($E$4,F31,'Festivos Guatemala'!$A$3:$A$15),0) -> 0 | I31: =NETWORKDAYS($E$4,F31,'Festivos Guatemala'!$A$3:$A$15) -> 10 | J31: =H31 -> 0
B32: 44656748347 | C32: ISR Utilidades trimestral | D32: 3377.38 | E32: =D32/$D$6 -> 445.56464 | F32: 45595 | G32: Cancelado | H32: =IF(OR(G32="Sin pagar",G32="Pagar"),NETWORKDAYS($E$4,F32,'Festivos Guatemala'!$A$3:$A$15),0) -> 0 | I32: =NETWORKDAYS($E$4,F32,'Festivos Guatemala'!$A$3:$A$15) -> 22 | J32: =H32 -> 0
C33: SERVICIOS PROFESIONALES -REPRESENTACIÓN LEGAL | D33: =SUBTOTAL(9,D34:D38) -> 3418.5 | E33: =SUBTOTAL(9,E34:E38) -> 450.98945 | J33: =H33 -> 0
C34: Servicios profesionales Juan-Servicios prestados-Septiembre y movilización transportes Bac y expresa | D34: =880+88.5 -> 968.5 | E34: =D34/$D$6 -> 127.77045 | F34: 45569 | G34: Cancelado | H34: =IF(OR(G34="Sin pagar",G34="Pagar"),NETWORKDAYS($E$4,F34,'Festivos Guatemala'!$A$3:$A$15),0) -> 0 | I34: =NETWORKDAYS($E$4,F34,'Festivos Guatemala'!$A$3:$A$15) -> 4 | J34: =H34 -> 0
B35: 954 | C35: Servicios profesionales Arnoldo prestados en Junio | D35: =1250 -> 1250 | E35: =D35/$D$6 -> 164.90765 | F35: 45569 | G35: Cancelado | H35: =IF(OR(G35="Sin pagar",G35="Pagar"),NETWORKDAYS($E$4,F35,'Festivos Guatemala'!$A$3:$A$15),0) -> 0 | I35: =NETWORKDAYS($E$4,F35,'Festivos Guatemala'!$A$3:$A$15) -> 4 | J35: =H35 -> 0
B36: 1083 | C36: Servicios profesionales Arnoldo prestados en Julio | D36: =1200 -> 1200 | E36: =D36/$D$6 -> 158.31135 | F36: 45569 | G36: Cancelado | H36: =IF(OR(G36="Sin pagar",G36="Pagar"),NETWORKDAYS($E$4,F36,'Festivos Guatemala'!$A$3:$A$15),0) -> 0 | I36: =NETWORKDAYS($E$4,F36,'Festivos Guatemala'!$A$3:$A$15) -> 4 | J36: =H36 -> 0
B37: 1086 | C37: Servicios profesionales Arnoldo prestados en Agosto | D37: =1200*0 -> 0 | E37: =D37/$D$6*0 -> 0 | F37: 45616 | G37: Cancelado | H37: =IF(OR(G37="Sin pagar",G37="Pagar"),NETWORKDAYS($E$4,F37,'Festivos Guatemala'!$A$3:$A$15),0) -> 0 | I37: =NETWORKDAYS($E$4,F37,'Festivos Guatemala'!$A$3:$A$15) -> 37 | J37: =H37 -> 0
B38: 1091 | C38: Servicios profesionales Arnoldo prestados en Septiembre | D38: =1200*0 -> 0 | E38: =D38/$D$6 -> 0 | F38: 45595 | G38: Cancelado | H38: =IF(OR(G38="Sin pagar",G38="Pagar"),NETWORKDAYS($E$4,F38,'Festivos Guatemala'!$A$3:$A$15),0) -> 0 | I38: =NETWORKDAYS($E$4,F38,'Festivos Guatemala'!$A$3:$A$15) -> 22 | J38: =H38 -> 0
C39: PÓLIZAS Y SEGUROS | D39: =SUBTOTAL(9,D40:D46) -> 8404.6446 | E39: =SUBTOTAL(9,E40:E46) -> 1108.7922
C40: Póliza de vida Ivan Estuardo Chavez Morales-USD-Póliza Vida | D40: =E40*$D$6 -> 417.4306 | E40: 55.07 | F40: 45582 | G40: Cancelado | H40: =IF(OR(G40="Sin pagar",G40="Pagar"),NETWORKDAYS($E$4,F40,'Festivos Guatemala'!$A$3:$A$15),0) -> 0 | I40: =NETWORKDAYS($E$4,F40,'Festivos Guatemala'!$A$3:$A$15) -> 13 | J40: =H40 -> 0
C41: Poliza de vida Rony Eduardo Quan Lam-USD-Póliza Vida | D41: =E41*$D$6 -> 1966.7826 | E41: 259.47 | F41: 45582 | G41: Cancelado | H41: =IF(OR(G41="Sin pagar",G41="Pagar"),NETWORKDAYS($E$4,F41,'Festivos Guatemala'!$A$3:$A$15),0) -> 0 | I41: =NETWORKDAYS($E$4,F41,'Festivos Guatemala'!$A$3:$A$15) -> 13 | J41: =H41 -> 0
C42: Poliza de vida Jerry García Carillo -USD-Póliza Vida | D42: =E42*$D$6 -> 1556.4014 | E42: 205.33 | F42: 45582 | G42: Cancelado | H42: =IF(OR(G42="Sin pagar",G42="Pagar"),NETWORKDAYS($E$4,F42,'Festivos Guatemala'!$A$3:$A$15),0) -> 0 | I42: =NETWORKDAYS($E$4,F42,'Festivos Guatemala'!$A$3:$A$15) -> 13 | J42: =H42 -> 0
C43: Póliza de vida Miriam Lucian Morfin González-QTQ-GM | D43: 843.56 | E43: =D43/$D$6 -> 111.2876 | F43: 45582 | G43: Cancelado | H43: =IF(OR(G43="Sin pagar",G43="Pagar"),NETWORKDAYS($E$4,F43,'Festivos Guatemala'!$A$3:$A$15),0) -> 0 | I43: =NETWORKDAYS($E$4,F43,'Festivos Guatemala'!$A$3:$A$15) -> 13 | J43: =H43 -> 0
C44: Póliza de vida Ivan Estuardo Chavez Morales-QTQ-GM | D44: 888.15 | E44: =D44/$D$6 -> 117.17018 | F44: 45582 | G44: Cancelado | H44: =IF(OR(G44="Sin pagar",G44="Pagar"),NETWORKDAYS($E$4,F44,'Festivos Guatemala'!$A$3:$A$15),0) -> 0 | I44: =NETWORKDAYS($E$4,F44,'Festivos Guatemala'!$A$3:$A$15) -> 13 | J44: =H44 -> 0
C45: Poliza de vida Rony Eduardo Quan Lam-QTQ-GM | D45: 903.72 | E45: =D45/$D$6 -> 119.22427 | F45: 45582 | G45: Cancelado | H45: =IF(OR(G45="Sin pagar",G45="Pagar"),NETWORKDAYS($E$4,F45,'Festivos Guatemala'!$A$3:$A$15),0) -> 0 | I45: =NETWORKDAYS($E$4,F45,'Festivos Guatemala'!$A$3:$A$15) -> 13 | J45: =H45 -> 0
C46: Poliza de vida Jerry García Carillo -QTQ-GM-Claudia Marisol Mayorga Ayala | D46: 1828.6 | E46: =D46/$D$6 -> 241.24011 | F46: 45582 | G46: Cancelado | H46: =IF(OR(G46="Sin pagar",G46="Pagar"),NETWORKDAYS($E$4,F46,'Festivos Guatemala'!$A$3:$A$15),0) -> 0 | I46: =NETWORKDAYS($E$4,F46,'Festivos Guatemala'!$A$3:$A$15) -> 13 | J46: =H46 -> 0
C47: COBROS ENTRE SUCURSALES | D47: =SUBTOTAL(9,D48:D49) -> 37210.934 | E47: =SUBTOTAL(9,E48:E49) -> 4728.2
B48: 5229 | C48: Cobro S&P a sucursal Guatemala -Septiembre TRM 4.285,61 | D48: =E48*7.87 -> 10336.222 | E48: =1313.37 -> 1313.37 | F48: 45595 | G48: Cancelado | H48: =IF(OR(G48="Sin pagar",G48="Pagar"),NETWORKDAYS($E$4,F48,'Festivos Guatemala'!$A$3:$A$15),0) -> 0 | I48: =NETWORKDAYS($E$4,F48,'Festivos Guatemala'!$A$3:$A$15) -> 22 | J48: =H48 -> 0
B49: 5333 | C49: Cobro S&P a sucursal Guatemala -Octubre TRM 4.233,17 | D49: =E49*7.87 -> 26874.712 | E49: 3414.83 | F49: 45595 | G49: Cancelado | H49: =IF(OR(G49="Sin pagar",G49="Pagar"),NETWORKDAYS($E$4,F49,'Festivos Guatemala'!$A$3:$A$15),0) -> 0 | I49: =NETWORKDAYS($E$4,F49,'Festivos Guatemala'!$A$3:$A$15) -> 22 | J49: =H49 -> 0
C50: TIQUETES AÉREOS , HOTELES | D50: =SUBTOTAL(9,D51:D52) -> 0 | E50: =SUBTOTAL(9,E51:E52) -> 0
C51: Tiquetes Ricardo y Eduard Visita Sucursal Guatemala | D51: =(((4000000/4150)*$D$6))*0 -> 0 | E51: =D51/D6 -> 0 | F51: 45596 | G51: Cancelado | H51: =IF(OR(G51="Sin pagar",G51="Pagar"),NETWORKDAYS($E$4,F51,'Festivos Guatemala'!$A$3:$A$15),0) -> 0 | I51: =NETWORKDAYS($E$4,F51,'Festivos Guatemala'!$A$3:$A$15) -> 23 | J51: =H51 -> 0
C52: Hoteles Ricardo y Eduard Visita Sucursal Guatemala | D52: =(((4000000/4150)*$D$6))*0 -> 0 | E52: =D52/D6 -> 0 | F52: 45596 | G52: Cancelado | H52: =IF(OR(G52="Sin pagar",G52="Pagar"),NETWORKDAYS($E$4,F52,'Festivos Guatemala'!$A$3:$A$15),0) -> 0 | I52: =NETWORKDAYS($E$4,F52,'Festivos Guatemala'!$A$3:$A$15) -> 23 | J52: =H52 -> 0
C53: COSTOS FINANCIEROS | D53: =SUBTOTAL(9,D54:D55) -> 359.8 | E53: =SUBTOTAL(9,E54:E55) -> 45.936675
C54: Gasto envio de divisas a Colombia | D54: 314.8 | E54: =D54/7.87 -> 40 | F54: 45595 | G54: Cancelado | H54: =IF(OR(G54="Sin pagar",G54="Pagar"),NETWORKDAYS($E$4,F54,'Festivos Guatemala'!$A$3:$A$15),0) -> 0 | I54: =NETWORKDAYS($E$4,F54,'Festivos Guatemala'!$A$3:$A$15) -> 22 | J54: =H54 -> 0
C55: Cobro emisión estado cuenta | D55: =15*3 -> 45 | E55: =D55/$D$6 -> 5.9366755 | F55: 45595 | G55: Cancelado | H55: =IF(OR(G55="Sin pagar",G55="Pagar"),NETWORKDAYS($E$4,F55,'Festivos Guatemala'!$A$3:$A$15),0) -> 0 | I55: =NETWORKDAYS($E$4,F55,'Festivos Guatemala'!$A$3:$A$15) -> 22 | J55: =H55 -> 0
C56: NÓMINAS | D56: =SUBTOTAL(9,D57:D67) -> 259716.77 | E56: =SUBTOTAL(9,E57:E67) -> 34263.426
C57: Stephanie Rodriguez Lopez-RF-Czarnikow-CC002 | D57: 28242.02 | E57: =D57/$D$6 -> 3725.8602 | F57: 45593 | G57: Cancelado | H57: =IF(OR(G57="Sin pagar",G57="Pagar"),NETWORKDAYS($E$4,F57,'Festivos Guatemala'!$A$3:$A$15),0) -> 0 | I57: =NETWORKDAYS($E$4,F57,'Festivos Guatemala'!$A$3:$A$15) -> 20 | J57: =H57 -> 0
C58: Ivan Estuardo Chávez Morales-Energyzer-CC004 | D58: 24970.21 | E58: =D58/$D$6 -> 3294.223 | F58: 45593 | G58: Cancelado | H58: =IF(OR(G58="Sin pagar",G58="Pagar"),NETWORKDAYS($E$4,F58,'Festivos Guatemala'!$A$3:$A$15),0) -> 0 | I58: =NETWORKDAYS($E$4,F58,'Festivos Guatemala'!$A$3:$A$15) -> 20 | J58: =H58 -> 0
C59: Jerry García-Energyzer-CC004 | D59: 69782.54 | E59: =D59/$D$6 -> 9206.1398 | F59: 45593 | G59: Cancelado | H59: =IF(OR(G59="Sin pagar",G59="Pagar"),NETWORKDAYS($E$4,F59,'Festivos Guatemala'!$A$3:$A$15),0) -> 0 | I59: =NETWORKDAYS($E$4,F59,'Festivos Guatemala'!$A$3:$A$15) -> 20 | J59: =H59 -> 0
C60: Ronny Eduardo Quan Lam-Energyzer-CC004 | D60: 73579.86 | E60: =D60/$D$6 -> 9707.1055 | F60: 45593 | G60: Cancelado | H60: =IF(OR(G60="Sin pagar",G60="Pagar"),NETWORKDAYS($E$4,F60,'Festivos Guatemala'!$A$3:$A$15),0) -> 0 | I60: =NETWORKDAYS($E$4,F60,'Festivos Guatemala'!$A$3:$A$15) -> 20 | J60: =H60 -> 0
C61: Ruth Carolina Vasquez Avelar de Rabanal-Kairos-CC005 | D61: 5732.9 | E61: =D61/$D$6 -> 756.31926 | F61: 45593 | G61: Cancelado | H61: =IF(OR(G61="Sin pagar",G61="Pagar"),NETWORKDAYS($E$4,F61,'Festivos Guatemala'!$A$3:$A$15),0) -> 0 | I61: =NETWORKDAYS($E$4,F61,'Festivos Guatemala'!$A$3:$A$15) -> 20 | J61: =H61 -> 0
C62: Edlin Ivette Ramos Poitan-Opportunnity-CC006 | D62: 10562.8 | E62: =D62/$D$6 -> 1393.5092 | F62: 45593 | G62: Cancelado | H62: =IF(OR(G62="Sin pagar",G62="Pagar"),NETWORKDAYS($E$4,F62,'Festivos Guatemala'!$A$3:$A$15),0) -> 0 | I62: =NETWORKDAYS($E$4,F62,'Festivos Guatemala'!$A$3:$A$15) -> 20 | J62: =H62 -> 0
C63: Miriam Lucia Morfin Gonzalez RF-Notable Growth INC-CC007 | D63: 29515.65 | E63: =D63/$D$6 -> 3893.8852 | F63: 45593 | G63: Cancelado | H63: =IF(OR(G63="Sin pagar",G63="Pagar"),NETWORKDAYS($E$4,F63,'Festivos Guatemala'!$A$3:$A$15),0) -> 0 | I63: =NETWORKDAYS($E$4,F63,'Festivos Guatemala'!$A$3:$A$15) -> 20 | J63: =H63 -> 0
C64: Barbara Isabela Escobar Anleu -Panthera-CC008 | D64: 5501.16 | E64: =D64/$D$6 -> 725.7467 | F64: 45593 | G64: Cancelado | H64: =IF(OR(G64="Sin pagar",G64="Pagar"),NETWORKDAYS($E$4,F64,'Festivos Guatemala'!$A$3:$A$15),0) -> 0 | I64: =NETWORKDAYS($E$4,F64,'Festivos Guatemala'!$A$3:$A$15) -> 20 | J64: =H64 -> 0
C65: Osman Alejandro López Acuta -Bilingual Bridges -CC009 | D65: 3943.21 | E65: =D65/$D$6 -> 520.2124 | F65: 45593 | G65: Cancelado | H65: =IF(OR(G65="Sin pagar",G65="Pagar"),NETWORKDAYS($E$4,F65,'Festivos Guatemala'!$A$3:$A$15),0) -> 0 | I65: =NETWORKDAYS($E$4,F65,'Festivos Guatemala'!$A$3:$A$15) -> 20 | J65: =H65 -> 0
C66: Sara María Arias Arrivillaga -Bilingual Bridges -CC009 | D66: 3943.21 | E66: =D66/$D$6 -> 520.2124 | F66: 45593 | G66: Cancelado | H66: =IF(OR(G66="Sin pagar",G66="Pagar"),NETWORKDAYS($E$4,F66,'Festivos Guatemala'!$A$3:$A$15),0) -> 0 | I66: =NETWORKDAYS($E$4,F66,'Festivos Guatemala'!$A$3:$A$15) -> 20 | J66: =H66 -> 0
C67: Natali Gabriela Ziller Santos -Bilingual Bridges -CC009 | D67: 3943.21 | E67: =D67/$D$6 -> 520.2124 | F67: 45593 | G67: Cancelado | H67: =IF(OR(G67="Sin pagar",G67="Pagar"),NETWORKDAYS($E$4,F67,'Festivos Guatemala'!$A$3:$A$15),0) -> 0 | I67: =NETWORKDAYS($E$4,F67,'Festivos Guatemala'!$A$3:$A$15) -> 20 | J67: =H67 -> 0
C68: REEMBOLSOS GASTOS | D68: =SUBTOTAL(9,D69:D73) -> 21596.113 | E68: =SUBTOTAL(9,E69:E73) -> 2849.0915
C69: Ronny Quan. Energyzer-CC003-USD | D69: =E69*$D$6 -> 5273.5576 | E69: 695.72 | F69: 45593 | G69: Cancelado | H69: =IF(OR(G69="Sin pagar",G69="Pagar"),NETWORKDAYS($E$4,F69,'Festivos Guatemala'!$A$3:$A$15),0) -> 0 | I69: =NETWORKDAYS($E$4,F69,'Festivos Guatemala'!$A$3:$A$15) -> 20 | J69: =H69 -> 0
C70: Jerry García-Energyzer-CC003-USD | D70: =E70*D6 -> 5829.0958 | E70: 769.01 | F70: 45593 | G70: Cancelado | H70: =IF(OR(G70="Sin pagar",G70="Pagar"),NETWORKDAYS($E$4,F70,'Festivos Guatemala'!$A$3:$A$15),0) -> 0 | I70: =NETWORKDAYS($E$4,F70,'Festivos Guatemala'!$A$3:$A$15) -> 20 | J70: =H70 -> 0
C71: Ronny Quan. Energyzer-CC003-QTQ | D71: 4194.64 | E71: =D71/$D$6 -> 553.38259 | F71: 45593 | G71: Cancelado | H71: =IF(OR(G71="Sin pagar",G71="Pagar"),NETWORKDAYS($E$4,F71,'Festivos Guatemala'!$A$3:$A$15),0) -> 0 | I71: =NETWORKDAYS($E$4,F71,'Festivos Guatemala'!$A$3:$A$15) -> 20 | J71: =H71 -> 0
C72: Jerry García-Energyzer-CC003-QTQ | D72: 4448 | E72: =D72/$D$6 -> 586.80739 | F72: 45593 | G72: Cancelado | H72: =IF(OR(G72="Sin pagar",G72="Pagar"),NETWORKDAYS($E$4,F72,'Festivos Guatemala'!$A$3:$A$15),0) -> 0 | I72: =NETWORKDAYS($E$4,F72,'Festivos Guatemala'!$A$3:$A$15) -> 20 | J72: =H72 -> 0
B73: 1093748010 | C73: Factura Claro- Incluido valor factura Nro 3075098786 Q350,82 | D73: 1850.82 | E73: =D73/$D$6 -> 244.1715 | F73: 45569 | G73: Cancelado | H73: =IF(OR(G73="Sin pagar",G73="Pagar"),NETWORKDAYS($E$4,F73,'Festivos Guatemala'!$A$3:$A$15),0) -> 0 | I73: =NETWORKDAYS($E$4,F73,'Festivos Guatemala'!$A$3:$A$15) -> 4 | J73: =H73 -> 0
C74: IMPREVISTO | D74: =SUBTOTAL(9,D75:D75) -> 0 | E74: =SUBTOTAL(9,E75:E75) -> 0
F75: 45595 | G75: Cancelado | H75: =IF(OR(G75="Sin pagar",G75="Pagar"),NETWORKDAYS($E$4,F75,'Festivos Guatemala'!$A$3:$A$15),0) -> 0 | I75: =NETWORKDAYS($E$4,F75,'Festivos Guatemala'!$A$3:$A$15) -> 22 | J75: =H75 -> 0
C76: TOTAL EGRESOS | D76: =SUBTOTAL(9,D26:D75) -> 392342.76 | E76: =SUBTOTAL(9,E26:E75) -> 51577.834
C78: SALDO | D78: =D21-D76 -> 197757.88 | E78: =E21-E76 -> 25911.166
C79: % | D79: =IF($D$21=0,0,D78/$D$21) -> 0.33512568 | E79: =IF($E$21=0,0,E78/$E$21) -> 0.33438508
C81: Fecha Inicial | D81: Fecha Final | E81: Valor VALOR QTQ | F81: Valor VALOR USD
C82: 45566 | D82: 45571 | E82: =SUMIFS($D$26:$D$79,$F$26:$F$79,">="&C82,$F$26:$F$79,"<="&D82,$G$26:$G$79,$D$95) -> 0 | F82: =SUMIFS($E$26:$E$79,$F$26:$F$79,">="&C82,$F$26:$F$79,"<="&D82,$G$26:$G$79,$D$95) -> 0 | G82: Pago factura claro, Servicios arnoldo y Juan
C83: 45572 | D83: 45578 | E83: =SUMIFS($D$26:$D$79,$F$26:$F$79,">="&C83,$F$26:$F$79,"<="&D83,$G$26:$G$79,$D$95) -> 0 | F83: =SUMIFS($E$26:$E$79,$F$26:$F$79,">="&C83,$F$26:$F$79,"<="&D83,$G$26:$G$79,$D$95) -> 0 | G83: Impuestos
C84: 45579 | D84: 45585 | E84: =SUMIFS($D$26:$D$79,$F$26:$F$79,">="&C84,$F$26:$F$79,"<="&D84,$G$26:$G$79,$D$95) -> 0 | F84: =SUMIFS($E$26:$E$79,$F$26:$F$79,">="&C84,$F$26:$F$79,"<="&D84,$G$26:$G$79,$D$95) -> 0 | G84: Viaje, Pólizas,
C85: 45586 | D85: 45592 | E85: =SUMIFS($D$26:$D$79,$F$26:$F$79,">="&C85,$F$26:$F$79,"<="&D85,$G$26:$G$79,$D$95) -> 0 | F85: =SUMIFS($E$26:$E$79,$F$26:$F$79,">="&C85,$F$26:$F$79,"<="&D85,$G$26:$G$79,$D$95) -> 0 | G85: Pólizas, pago fac casa Matriz
C86: 45593 | D86: 45596 | E86: =SUMIFS($D$26:$D$79,$F$26:$F$79,">="&C86,$F$26:$F$79,"<="&D86,$G$26:$G$79,$D$95) -> 0 | F86: =SUMIFS($E$26:$E$79,$F$26:$F$79,">="&C86,$F$26:$F$79,"<="&D86,$G$26:$G$79,$D$95) -> 0 | G86: Nóminas , envio divisas, reembolsos
C87: TOTAL EGRESOS | E87: =SUM(E82:E86) -> 0 | F87: =SUM(F82:F86) -> 0
D90: Bancos | E90: ='Caja QTQ'!$H$266+('Caja USD'!$H$117*$D$6) -> 197657.23 | F90: =('Caja QTQ'!$H$266/$D$6)+'Caja USD'!$H$117 -> 26076.152
D91: Pagos 01 al 27 Oct | E91: =SUM(E82:E85) -> 0 | F91: =SUM(F82:F85) -> 0
D92: Saldo | E92: =E90-E91 -> 197657.23 | F92: =F90-F91 -> 26076.152
D94: Cancelado | E94: =SUMIFS($D$26:$D$89,$F$26:$F$89,">="&C82,$F$26:$F$89,"<="&D86,$G$26:$G$89,$D$94) -> 392342.76 | F94: =SUMIFS($E$26:$E$89,$F$26:$F$89,">="&C82,$F$26:$F$89,"<="&D86,$G$26:$G$89,$D$94) -> 51577.834
D95: Sin Pagar | E95: =SUMIFS($D$26:$D$89,$F$26:$F$89,">="&C82,$F$26:$F$89,"<="&D86,$G$26:$G$89,$D$95) -> 0 | F95: =SUMIFS($E$26:$E$89,$F$26:$F$89,">="&C82,$F$26:$F$89,"<="&D86,$G$26:$G$89,$D$95) -> 0
D96: Total Egresos | E96: =SUM(E94:E95) -> 392342.76 | F96: =SUM(F94:F95) -> 51577.834
D97: Validación | E97: =E96-D76 -> 0 | F97: =F96-E76 -> 0
D99: Flujo Caja | E99: =D78 -> 197757.88
D100: Saldo Libro | E100: ='Caja QTQ'!H167+('Caja USD'!H70*7.6) -> 190098.57
D101: Diferencia | E101: =E99-E100 -> 7659.309 | F101: =E101/7.88 -> 971.99352
D103: Flujo Caja | E103: =D78 -> 197757.88
D104: Saldo Libro | E104: ='Caja QTQ'!$H$266+('Caja USD'!$H$117*7.87) -> 197757.88
D105: Diferencia QTZ | E105: =E104-E103 -> 0.0032437627

Sheet Flujo caja Noviembre 
D1: 42400
D4: Fecha de Elaboración: | E4: 45597
C6: Tasa de cambio: | D6: 7.6
D7: NOVIEMBRE
D8: VALOR QTQ | E8: VALOR USD
C9: BANCOS | D9: =SUBTOTAL(9,D10:D11) -> 224503.05 | E9: =SUBTOTAL(9,E10:E11) -> 29539.876
C10: Bancos QTQ | D10: ='Caja QTQ'!$H$266+26838.88 -> 221865.4 | E10: =D10/$D$6 -> 29192.816
C11: Bancos USD | D11: =E11*D6 -> 2637.656 | E11: ='Caja USD'!$H$117 -> 347.06
C12: CLIENTES | D12: =SUBTOTAL(9,D13:D19) -> 555107.61 | E12: =SUBTOTAL(9,E13:E19) -> 72430.99
B13: Pagado | C13: Client: Czarnikow- Sthepanie Rodriguez Lopez-Remotefist | D13: ='Diferencia en cambio'!$I$51 -> 41067.208 | E13: =D13/'Diferencia en cambio'!L51 -> 5405.3
B14: Pagado | C14: Client:Energyzer-Ivan Chavez-Jerry García-Ronny Quan-Safeguard | D14: ='Diferencia en cambio'!$I$52 -> 408290.82 | E14: =D14/'Diferencia en cambio'!L52 -> 53167.38
B15: Pagado | C15: Client:Kairos-Ivan Chavez-Ruth Carolina Vasquez-Safeguard | D15: ='Diferencia en cambio'!$I$53 -> 11942.846 | E15: =D15/'Diferencia en cambio'!L53 -> 1555.19
B16: Pagado | C16: Client: Opportunity-Edlin Ivette Poitan-Safeguard | D16: ='Diferencia en cambio'!$I$54 -> 22300.597 | E16: =D16/'Diferencia en cambio'!L54 -> 2903.97
B17: Pagado | C17: Client: NotableGrowth, Inc-Remotefist | D17: ='Diferencia en cambio'!$I$55 -> 43769.668 | E17: =D17/'Diferencia en cambio'!L55 -> 5761
B18: Pagado | C18: Client: Panthera, Inc-Safeguard | D18: ='Diferencia en cambio'!$I$56 -> 8952.8145 | E18: =D18/'Diferencia en cambio'!L56 -> 1165.83
B19: Pagado | C19: Client: Bilingual Bridges, Inc-Remotefist | D19: ='Diferencia en cambio'!$I$57 -> 18783.653 | E19: =D19/'Diferencia en cambio'!L57 -> 2472.32
C20: TOTAL INGRESOS | D20: =SUBTOTAL(9,D9:D17) -> 751874.2 | E20: =SUBTOTAL(9,E9:E17) -> 98332.716
B23: CUENTAS X PAGAR MES | D23: DICIEMBRE
B24: Factura | C24: PROVEEDOR | D24: VALOR QTQ | E24: VALOR USD | F24: Fecha vencimiento | G24: Estado | J24: KPI
C25: SEGURIDAD IGSS | D25: =SUBTOTAL(9,D26:D26) -> 48910.95 | E25: =SUBTOTAL(9,E26:E26) -> 6435.6513
B26: 176206200 | C26: Pago planilla IGSS Octubre | D26: 48910.95 | E26: =D26/D6 -> 6435.6513 | F26: 45608 | G26: Cancelado | H26: =IF(OR(G26="Sin pagar",G26="Pagar"),NETWORKDAYS($E$4,F26,'Festivos Guatemala'!$A$3:$A$15),0) -> 0 | I26: =NETWORKDAYS($E$4,F26,'Festivos Guatemala'!$A$3:$A$15) -> 8 | J26: =H26 -> 0
C27: IMPUESTOS | D27: =SUBTOTAL(9,D28:D29) -> 17774.44 | E27: =SUBTOTAL(9,E28:E29) -> 2338.7421 | J27: =H27 -> 0
B28: 44806420761 | C28: Declaraguate ISR Octubre | D28: 13821.14 | E28: =D28/$D$6 -> 1818.5711 | F28: 45609 | G28: Cancelado | H28: =IF(OR(G28="Sin pagar",G28="Pagar"),NETWORKDAYS($E$4,F28,'Festivos Guatemala'!$A$3:$A$15),0) -> 0 | I28: =NETWORKDAYS($E$4,F28,'Festivos Guatemala'!$A$3:$A$15) -> 9 | J28: =H28 -> 0
B29: 44807605272 | C29: Declaraguate ISR no residentes facturación Col Factura 5333 Octubre | D29: 3953.3 | E29: =D29/$D$6 -> 520.17105 | F29: 45609 | G29: Cancelado | H29: =IF(OR(G29="Sin pagar",G29="Pagar"),NETWORKDAYS($E$4,F29,'Festivos Guatemala'!$A$3:$A$15),0) -> 0 | I29: =NETWORKDAYS($E$4,F29,'Festivos Guatemala'!$A$3:$A$15) -> 9 | J29: =H29 -> 0
C30: SERVICIOS PROFESIONALES -REPRESENTACIÓN LEGAL | D30: =SUBTOTAL(9,D31:D36) -> 5829 | E30: =SUBTOTAL(9,E31:E36) -> 766.97368 | J30: =H30 -> 0
C31: Servicios profesionales Juan-Servicios prestados Octubre y movilización transportes Bac | D31: =880+100 -> 980 | E31: =D31/$D$6 -> 128.94737 | F31: 45610 | G31: Cancelado | H31: =IF(OR(G31="Sin pagar",G31="Pagar"),NETWORKDAYS($E$4,F31,'Festivos Guatemala'!$A$3:$A$15),0) -> 0 | I31: =NETWORKDAYS($E$4,F31,'Festivos Guatemala'!$A$3:$A$15) -> 10 | J31: =H31 -> 0
C32: Servicios movilización transportes Bac -Octubre | D32: 50 | E32: =D32/$D$6 -> 6.5789474 | F32: 45610 | G32: Cancelado | H32: =IF(OR(G32="Sin pagar",G32="Pagar"),NETWORKDAYS($E$4,F32,'Festivos Guatemala'!$A$3:$A$15),0) -> 0 | I32: =NETWORKDAYS($E$4,F32,'Festivos Guatemala'!$A$3:$A$15) -> 10 | J32: =H32 -> 0
B33: A060468B-1758219238 | C33: Inbers contadores Servicios contables con entrega de información financiera correspondiente al periodo de octubre 2024 | D33: 2299 | E33: =D33/$D$6 -> 302.5 | F33: 45611 | G33: Cancelado | H33: =IF(OR(G33="Sin pagar",G33="Pagar"),NETWORKDAYS($E$4,F33,'Festivos Guatemala'!$A$3:$A$15),0) -> 0 | I33: =NETWORKDAYS($E$4,F33,'Festivos Guatemala'!$A$3:$A$15) -> 11 | J33: =H33 -> 0
B34: S/N | C34: Anticipo del 50% Victor Hugo Moscozo- Abogado tramites notariales sucursales | D34: =2500 -> 2500 | E34: =D34/$D$6 -> 328.94737 | F34: 45614 | G34: Cancelado | H34: =IF(OR(G34="Sin pagar",G34="Pagar"),NETWORKDAYS($E$4,F34,'Festivos Guatemala'!$A$3:$A$15),0) -> 0 | I34: =NETWORKDAYS($E$4,F34,'Festivos Guatemala'!$A$3:$A$15) -> 12 | J34: =H34 -> 0
B35: 1086 | C35: Servicios profesionales Arnoldo prestados en Agosto | D35: =1200*0 -> 0 | E35: =D35/$D$6 -> 0 | F35: 45641 | G35: Sin Pagar | H35: =IF(OR(G35="Sin pagar",G35="Pagar"),NETWORKDAYS($E$4,F35,'Festivos Guatemala'!$A$3:$A$15),0) -> 31 | I35: =NETWORKDAYS($E$4,F35,'Festivos Guatemala'!$A$3:$A$15) -> 31 | J35: =H35 -> 31
B36: 1091 | C36: Servicios profesionales Arnoldo prestados en Septiembre | D36: =1200*0 -> 0 | E36: =D36/$D$6 -> 0 | F36: 45641 | G36: Sin Pagar | H36: =IF(OR(G36="Sin pagar",G36="Pagar"),NETWORKDAYS($E$4,F36,'Festivos Guatemala'!$A$3:$A$15),0) -> 31 | I36: =NETWORKDAYS($E$4,F36,'Festivos Guatemala'!$A$3:$A$15) -> 31 | J36: =H36 -> 31
C37: PÓLIZAS Y SEGUROS | D37: =SUBTOTAL(9,D38:D44) -> 8415.042 | E37: =SUBTOTAL(9,E38:E44) -> 1107.2424
C38: Póliza de vida Ivan Estuardo Chavez Morales-USD-Póliza Vida | D38: =E38*$D$6 -> 418.532 | E38: 55.07 | F38: 45617 | G38: Cancelado | H38: =IF(OR(G38="Sin pagar",G38="Pagar"),NETWORKDAYS($E$4,F38,'Festivos Guatemala'!$A$3:$A$15),0) -> 0 | I38: =NETWORKDAYS($E$4,F38,'Festivos Guatemala'!$A$3:$A$15) -> 15 | J38: =H38 -> 0
C39: Poliza de vida Rony Eduardo Quan Lam-USD-Póliza Vida | D39: =E39*$D$6 -> 1971.972 | E39: 259.47 | F39: 45617 | G39: Cancelado | H39: =IF(OR(G39="Sin pagar",G39="Pagar"),NETWORKDAYS($E$4,F39,'Festivos Guatemala'!$A$3:$A$15),0) -> 0 | I39: =NETWORKDAYS($E$4,F39,'Festivos Guatemala'!$A$3:$A$15) -> 15 | J39: =H39 -> 0
C40: Poliza de vida Jerry García Carillo -USD-Póliza Vida | D40: =E40*$D$6 -> 1560.508 | E40: 205.33 | F40: 45617 | G40: Cancelado | H40: =IF(OR(G40="Sin pagar",G40="Pagar"),NETWORKDAYS($E$4,F40,'Festivos Guatemala'!$A$3:$A$15),0) -> 0 | I40: =NETWORKDAYS($E$4,F40,'Festivos Guatemala'!$A$3:$A$15) -> 15 | J40: =H40 -> 0
C41: Póliza de vida Miriam Lucian Morfin González-QTQ-GM | D41: 843.56 | E41: =D41/$D$6 -> 110.99474 | F41: 45617 | G41: Cancelado | H41: =IF(OR(G41="Sin pagar",G41="Pagar"),NETWORKDAYS($E$4,F41,'Festivos Guatemala'!$A$3:$A$15),0) -> 0 | I41: =NETWORKDAYS($E$4,F41,'Festivos Guatemala'!$A$3:$A$15) -> 15 | J41: =H41 -> 0
C42: Póliza de vida Ivan Estuardo Chavez Morales-QTQ-GM | D42: 888.15 | E42: =D42/$D$6 -> 116.86184 | F42: 45617 | G42: Cancelado | H42: =IF(OR(G42="Sin pagar",G42="Pagar"),NETWORKDAYS($E$4,F42,'Festivos Guatemala'!$A$3:$A$15),0) -> 0 | I42: =NETWORKDAYS($E$4,F42,'Festivos Guatemala'!$A$3:$A$15) -> 15 | J42: =H42 -> 0
C43: Poliza de vida Rony Eduardo Quan Lam-QTQ-GM | D43: 903.72 | E43: =D43/$D$6 -> 118.91053 | F43: 45617 | G43: Cancelado | H43: =IF(OR(G43="Sin pagar",G43="Pagar"),NETWORKDAYS($E$4,F43,'Festivos Guatemala'!$A$3:$A$15),0) -> 0 | I43: =NETWORKDAYS($E$4,F43,'Festivos Guatemala'!$A$3:$A$15) -> 15 | J43: =H43 -> 0
C44: Poliza de vida Jerry García Carillo -QTQ-GM-Claudia Marisol Mayorga Ayala | D44: 1828.6 | E44: =D44/$D$6 -> 240.60526 | F44: 45617 | G44: Cancelado | H44: =IF(OR(G44="Sin pagar",G44="Pagar"),NETWORKDAYS($E$4,F44,'Festivos Guatemala'!$A$3:$A$15),0) -> 0 | I44: =NETWORKDAYS($E$4,F44,'Festivos Guatemala'!$A$3:$A$15) -> 15 | J44: =H44 -> 0
C45: COBROS ENTRE SUCURSALES | D45: =SUBTOTAL(9,D46:D46) -> 0 | E45: =SUBTOTAL(9,E46:E46) -> 0
