Workbook

Sheet BBVA SOLES
D2: BCP SOLES
A4: FECHA | D4: DESCRIPCIÓN | E4: INGRESO | F4: SALIDA | G4: SALDO
A5: 45901
A6: 45926 | D6: Transferencia de fondos por apertura de cuenta | E6: 1500 | G6: =G5+E6-F6 -> 1500
A7: 45927 | D7: Bastanteo poderes y escrituras | F7: 45 | G7: =G6+E7-F7 -> 1455
A8: 45930 | D8: Comisión de mantenimiento | F8: 15 | G8: =G7+E8-F8 -> 1440
A9: 45930 | D9: Saldo | G9: =G8+E9-F9 -> 1440
A10: 45566 | D10: Inicio mes | G10: =G9+E10-F10 -> 1440
A11: 45596 | D11: Comisión de mantenimiento | F11: 15 | G11: =G10+E11-F11 -> 1425
A12: 45596 | D12: Saldo | G12: =G11+E12-F12 -> 1425
A13: 45597 | D13: Inicio mes | G13: =G12+E13-F13 -> 1425
A14: 45973 | D14: Transferencia a la cuenta BBVA de S&P para pagos CTS Safeguard interbank | E14: 23650 | G14: =G13+E14-F14 -> 25075
A15: 45973 | D15: Transferencia a la cuenta BBVA de S&P para pagos CTS Safeguard interbank | E15: 23650 | G15: =G14+E15-F15 -> 48725
A16: 45973 | D16: Pago CTS Interbank Safeguard | F16: 37652.9 | G16: =G15+E16-F16 -> 11072.1
A17: 45973 | D17: Impuesto ITF | F17: 1.85 | G17: =G16+E17-F17 -> 11070.25
A18: 45973 | D18: Comisión CTS | F18: 6 | G18: =G17+E18-F18 -> 11064.25
A19: 45973 | D19: Transferencia de la cuenta de Avanza para pago AFP Habitat Safeguard | E19: 9530.3 | G19: =G18+E19-F19 -> 20594.55
A20: 45973 | D20: Impuesto ITF | F20: 0.45 | G20: =G19+E20-F20 -> 20594.1
A21: 45973 | D21: Pago AFP Habitat Safeguard | F21: 9530.3 | G21: =G20+E21-F21 -> 11063.8
A22: 45973 | D22: Impuesto ITF | F22: 0.45 | G22: =G21+E22-F22 -> 11063.35
A23: 45974 | D23: Transferencia a la cuenta BBVA de S&P para pagos CTS Safeguard y S&P | E23: 13318.7 | G23: =G22+E23-F23 -> 24382.05
A24: 45974 | D24: Pago CTS Olga Paredes Interbank y Melissa Guadalupe Caja piura-Safeguard-Noviembre | F24: 21063.69 | G24: =G23+E24-F24 -> 3318.36
A25: 45974 | D25: Impuesto ITF | F25: 1.05 | G25: =G24+E25-F25 -> 3317.31
A26: 45974 | D26: Comisión CTS | F26: 2 | G26: =G25+E26-F26 -> 3315.31
A27: 45975 | D27: Devolución CTS Fiorella Chavez Noviembre -Safeguard | E27: 1591.01 | G27: =G26+E27-F27 -> 4906.32
A28: 45975 | D28: Impuesto ITF | F28: 0.05 | G28: =G27+E28-F28 -> 4906.27
A29: 45975 | D29: Pago CTS Andrés Felipe Uribe BBVA S&P | F29: 1533.34 | G29: =G28+E29-F29 -> 3372.93
A30: 45975 | D30: Impuesto ITF | F30: =0.05+0.05 -> 0.1 | G30: =G29+E30-F30 -> 3372.83
A31: 45975 | D31: Impuesto ITF | F31: 0.05 | G31: =G30+E31-F31 -> 3372.78
A32: 45975 | D32: Pago CTS Fiorella Chavez Noviembre -Safeguard | F32: 1591.01 | G32: =G31+E32-F32 -> 1781.77
A33: 45975 | D33: Comisión CTS | F33: 1 | G33: =G32+E33-F33 -> 1780.77
A34: 45987 | D34: Pago CTS Andrés Felipe Uribe BBVA S&P-Ajuste | F34: 170.36 | G34: =G33+E34-F34 -> 1610.41
A35: 45988 | D35: Pago CTS Christiam Valle BBVA Noviembre- USD S&P-Ajuste | F35: 1046.08 | G35: =G34+E35-F35 -> 564.33
A36: 45989 | D36: Comisión de mantenimiento | F36: 15 | G36: =G35+E36-F36 -> 549.33
A37: 45991 | G37: =G36+E37-F37 -> 549.33
A38: 45992 | G38: =G37+E38-F38 -> 549.33
A39: 45995 | D39: Transferencia de fondos a cuenta BBVA para pago Planilla de declaración y pago de aportes previsional SG | E39: 30000 | G39: =G38+E39-F39 -> 30549.33
A40: 45996 | D40: Pago AFP Habitat Safeguard | F40: 6615.13 | G40: =G39+E40-F40 -> 23934.2
A41: 45996 | D41: Pago AFP Integra Safeguard | F41: 6050.25 | G41: =G40+E41-F41 -> 17883.95
A42: 45996 | D42: Pago AFP Prima Safeguard | F42: 11925.06 | G42: =G41+E42-F42 -> 5958.89
A43: 45996 | D43: Pago AFP Prima Safeguard | F43: 2897.95 | G43: =G42+E43-F43 -> 3060.94
A44: 45996 | D44: Impuesto ITF | F44: 1.05 | G44: =G43+E44-F44 -> 3059.89
A45: 46007 | D45: Transferencia de la cuenta BBVA a la cuenta BCP para pago IGV SG | F45: 3000 | G45: =G44+E45-F45 -> 59.89
A46: 46007 | D46: Comisión por transferencia de dinero SG | F46: 5.8 | G46: =G45+E46-F46 -> 54.09
A47: 46022 | D47: Comisión de mantenimiento | F47: 15 | G47: =G46+E47-F47 -> 39.09
A48: 46022 | G48: =G47+E48-F48 -> 39.09
A49: 46023 | G49: =G48+E49-F49 -> 39.09
A50: 46029 | D50: Transferencia de fondos a cuenta BBVA para pago Planilla de declaración y pago de aportes previsional SG | E50: 30000 | G50: =G49+E50-F50 -> 30039.09
A51: 46029 | D51: Pago AFP Habitat Safeguard | F51: ='FLUJO CAJA ENERO 2026'!D74 -> 5812.55 | G51: =G50+E51-F51 -> 24226.54
A52: 46029 | D52: Pago AFP Integra Safeguard | F52: ='FLUJO CAJA ENERO 2026'!D75 -> 7998.34 | G52: =G51+E52-F52 -> 16228.2
A53: 46029 | D53: Pago AFP Prima Safeguard | F53: ='FLUJO CAJA ENERO 2026'!D76 -> 12425.95 | G53: =G52+E53-F53 -> 3802.25
A54: 46029 | D54: Pago AFP Prima Safeguard | F54: ='FLUJO CAJA ENERO 2026'!D77 -> 2253.43 | G54: =G53+E54-F54 -> 1548.82
A55: 46029 | D55: Impuesto ITF | F55: 1.3 | G55: =G54+E55-F55 -> 1547.52
A56: 46045 | D56: Transferencia de fondos a cuenta BBVA para pago gratificación reintegro Sergio Gustin-SG | E56: 5450 | G56: =G55+E56-F56 -> 6997.52
A57: 46045 | D57: Pago gratificación reintegro Sergio Gustin-SG | F57: 5444.17 | G57: =G56+E57-F57 -> 1553.35
A58: 46045 | D58: Comisión | F58: 4.3 | G58: =G57+E58-F58 -> 1549.05
A59: 46045 | D59: Impuesto ITF | F59: 0.25 | G59: =G58+E59-F59 -> 1548.8
A60: 46049 | D60: Pago gratificación reintegro Sergio Gustin-SG -Devolución | E60: 5444.17 | G60: =G59+E60-F60 -> 6992.97
A61: 46049 | D61: Impuesto ITF-Devolución | E61: 0.25 | G61: =G60+E61-F61 -> 6993.22
A62: 46049 | D62: Comisión Devolucion | E62: 4.3 | G62: =G61+E62-F62 -> 6997.52
A63: 46049 | D63: Impuesto ITF | F63: 4.8 | G63: =G62+E63-F63 -> 6992.72
A64: 46050 | D64: Pago gratificación reintegro Sergio Gustin-SG | F64: 5444.17 | G64: =G63+E64-F64 -> 1548.55
A65: 46050 | D65: Comisión | F65: 1 | G65: =G64+E65-F65 -> 1547.55
A66: 46050 | D66: Impuesto ITF | F66: 0.25 | G66: =G65+E66-F66 -> 1547.3
A67: 46053 | D67: Comisión de mantenimiento | F67: 15 | G67: =G66+E67-F67 -> 1532.3
A68: 46053 | G68: =G67+E68-F68 -> 1532.3
A69: 46054 | G69: =G68+E69-F69 -> 1532.3
A70: 46059 | D70: Transferencia de fondos a cuenta BBVA para pago Planilla de declaración y pago de aportes previsional SG | E70: 29564 | G70: =G69+E70-F70 -> 31096.3
A71: 46059 | D71: Pago AFP Habitat Safeguard | F71: ='FLUJO CAJA FEBRERO 2026'!D80 -> 5915.75 | G71: =G70+E71-F71 -> 25180.55
A72: 46059 | D72: Pago AFP Integra Safeguard | F72: ='FLUJO CAJA FEBRERO 2026'!D81 -> 7966.13 | G72: =G71+E72-F72 -> 17214.42
A73: 46059 | D73: Pago AFP Prima Safeguard | F73: ='FLUJO CAJA FEBRERO 2026'!D82 -> 13251.99 | G73: =G72+E73-F73 -> 3962.43
A74: 46059 | D74: Pago AFP Prima Safeguard | F74: ='FLUJO CAJA FEBRERO 2026'!D83 -> 2429.8 | G74: =G73+E74-F74 -> 1532.63
A75: 46059 | D75: Impuesto ITF | F75: 1.35 | G75: =G74+E75-F75 -> 1531.28
A76: 46080 | D76: Comisión de mantenimiento | F76: =5.4+9.6 -> 15 | G76: =G75+E76-F76 -> 1516.28
A77: 46081 | G77: =G76+E77-F77 -> 1516.28
A78: 46082 | G78: =G77+E78-F78 -> 1516.28
A79: 46084 | D79: Transferencia fondos a la cuenta BBVA para EPS Rimac | E79: 9000 | G79: =G78+E79-F79 -> 10516.28
A80: 46085 | D80: Rimac EPS Galy Madelein Torres Rivermate | F80: 8878.5 | G80: =G79+E80-F80 -> 1637.78
A81: 46087 | D81: Transferencia de fondos a cuenta BBVA para pago Planilla de declaración y pago de aportes previsional SG | E81: 38600 | G81: =G80+E81-F81 -> 40237.78
A82: 46087 | D82: Pago AFP Habitat Safeguard | F82: 11479.95 | G82: =G81+E82-F82 -> 28757.83
A83: 46087 | D83: Pago AFP Integra Safeguard | F83: 9115.1 | G83: =G82+E83-F83 -> 19642.73
A84: 46087 | D84: Pago AFP Prima Safeguard | F84: 15036.33 | G84: =G83+E84-F84 -> 4606.4
A85: 46087 | D85: Pago AFP Prima Safeguard | F85: 2874.77 | G85: =G84+E85-F85 -> 1731.63
A86: 46087 | D86: Impuesto ITF | F86: 2.25 | G86: =G85+E86-F86 -> 1729.38
A87: 46112 | D87: Comisión de mantenimiento | F87: =5.4+9.6 -> 15 | G87: =G86+E87-F87 -> 1714.38
A88: 46112 | G88: =G87+E88-F88 -> 1714.38
A89: 46113 | G89: =G88+E89-F89 -> 1714.38
A90: 46120 | D90: Transferencia de fondos a cuenta BBVA para pago Planilla de declaración y pago de aportes previsional SG | E90: 38000 | G90: =G89+E90-F90 -> 39714.38
A91: 46121 | D91: Pago AFP Habitat Safeguard | F91: ='FLUJO CAJA ABRIL 2026 '!D73 -> 7612.45 | G91: =G90+E91-F91 -> 32101.93
A92: 46121 | D92: Pago AFP Integra Safeguard | F92: ='FLUJO CAJA ABRIL 2026 '!D74 -> 9435.94 | G92: =G91+E92-F92 -> 22665.99
A93: 46121 | D93: Pago AFP Prima Safeguard | F93: ='FLUJO CAJA ABRIL 2026 '!D75 -> 14526.21 | G93: =G92+E93-F93 -> 8139.78
A94: 46121 | D94: Pago AFP Prima Safeguard | F94: ='FLUJO CAJA ABRIL 2026 '!D76 -> 5572.97 | G94: =G93+E94-F94 -> 2566.81
F95: 1.75 | G95: =G94+E95-F95 -> 2565.06
G96: =G95+E96-F96 -> 2565.06
G97: =G96+E97-F97 -> 2565.06
G98: =G97+E98-F98 -> 2565.06
G99: =G98+E99-F99 -> 2565.06
G100: =G99+E100-F100 -> 2565.06

Sheet BBVA USD
D2: BCP USD
A4: FECHA | D4: DESCRIPCIÓN | E4: INGRESO | F4: SALIDA | G4: SALDO
A5: 45901 | G5: 0
A6: 45925 | D6: Transferencia de fondos para apertura de cuenta | E6: 500 | G6: =G5+E6-F6 -> 500
A7: 45930 | D7: Comisión de mantenimiento | F7: 5.4 | G7: =G6+E7-F7 -> 494.6
A8: 45930 | G8: =G7+E8-F8 -> 494.6
A9: 45931 | G9: =G8+E9-F9 -> 494.6
A10: 45961 | D10: Comisión de mantenimiento | F10: 5.4 | G10: =G9+E10-F10 -> 489.2
A11: 45961 | G11: =G10+E11-F11 -> 489.2
A12: 45962 | G12: =G11+E12-F12 -> 489.2
A13: 45610 | D13: Transferencia de fondos de la cuenta BBVA para pago CTS Christiam Valle BBVA Noviembre- USD S&P | E13: 1602.78 | G13: =G12+E13-F13 -> 2091.98
A14: 45610 | D14: Pago CTS Christiam Valle BBVA Noviembre- USD S&P | F14: 1602.78 | G14: =G13+E14-F14 -> 489.2
A15: 45610 | D15: Impuesto ITF | F15: 0.05 | G15: =G14+E15-F15 -> 489.15
A16: 45622 | D16: Comisión de mantenimiento | F16: 5.4 | G16: =G15+E16-F16 -> 483.75
A17: 45991 | G17: =G16+E17-F17 -> 483.75
A18: 45992 | G18: =G17+E18-F18 -> 483.75
A19: 46007 | D19: Transferencia de la cuenta BBVA de USD a la cuenta BCP USD para pago IGV SG | F19: 450 | G19: =G18+E19-F19 -> 33.75
A20: 46007 | D20: Comisión por transferencia de dinero SG | F20: 2.01 | G20: =G19+E20-F20 -> 31.74
A21: 46022 | D21: Comisión de mantenimiento | F21: 5.4 | G21: =G20+E21-F21 -> 26.34
A22: 46022 | G22: =G21+E22-F22 -> 26.34
A23: 46023 | D23: Comisión de mantenimiento | F23: 5.4 | G23: =G22+E23-F23 -> 20.94
A24: 46053 | G24: =G23+E24-F24 -> 20.94
A25: 46080 | D25: Comisión de mantenimiento | F25: 5.4 | G25: =G24+E25-F25 -> 15.54
A26: 46081 | G26: =G25+E26-F26 -> 15.54
A27: 46112 | D27: Comisión de mantenimiento | F27: 5.4 | G27: =G26+E27-F27 -> 10.14
A28: 46112 | G28: =G27+E28-F28 -> 10.14
G29: =G28+E29-F29 -> 10.14
G30: =G29+E30-F30 -> 10.14
G31: =G30+E31-F31 -> 10.14
G32: =G31+E32-F32 -> 10.14
G33: =G32+E33-F33 -> 10.14
G34: =G33+E34-F34 -> 10.14
G35: =G34+E35-F35 -> 10.14
G36: =G35+E36-F36 -> 10.14
G37: =G36+E37-F37 -> 10.14
G38: =G37+E38-F38 -> 10.14
G39: =G38+E39-F39 -> 10.14
G40: =G39+E40-F40 -> 10.14
... G50: =G49+E50-F50 -> 10.14

Sheet BCP SOLES BCP
D2: BCP SOLES
A4: FECHA | D4: DESCRIPCIÓN | E4: INGRESO | F4: SALIDA | G4: SALDO
A5: 45536
A6: 45558 | D6: Transferencia de fondos por apertura de cuenta | E6: 500 | G6: =G5+E6-F6 -> 500
A7: 45548 | D7: Gestion pago del token | F7: 25 | G7: =G6+E7-F7 -> 475
A8: 45562 | D8: Envio estado de cuenta | F8: 5.5 | G8: =G7+E8-F8 -> 469.5
A9: 45562 | D9: Costo por uso de pagina bancaria | F9: 35 | G9: =G8+E9-F9 -> 434.5
A10: 45562 | D10: Cierre | G10: =G9+E10-F10 -> 434.5
A11: 45565 | D11: Saldo | G11: =G10+E11-F11 -> 434.5
A12: 45566 | D12: Inicio mes | G12: =G11+E12-F12 -> 434.5
A13: 45575 | D13: Mantenimiento TD | F13: 10 | G13: =G12+E13-F13 -> 424.5
A14: 45596 | D14: Envio estado de cuenta | F14: 5.5 | G14: =G13+E14-F14 -> 419
A15: 45596 | D15: Costo por uso de pagina bancaria | F15: 35 | G15: =G14+E15-F15 -> 384
A16: 45596 | D16: Saldo | G16: =G15+E16-F16 -> 384
A17: 45597 | D17: Inicio mes | G17: =G16+E17-F17 -> 384
A18: 45611 | D18: Mantenimiento TD | F18: 10 | G18: =G17+E18-F18 -> 374
A19: 45623 | D19: Transferencia de fondos desde la cuenta de USD a Soles para pago pólizas | E19: 300 | G19: =G18+E19-F19 -> 674
A20: 45623 | D20: Pago póliza vida seguro RUC 20613146360 | F20: 629.51 | G20: =G19+E20-F20 -> 44.49
A21: 45624 | D21: Transferencia de fondos de la cuenta de USD a Soles para pago de nómina | E21: 6600 | G21: =G20+E21-F21 -> 6644.49
A22: 45624 | D22: Pago Nómina Noviembre Gonzalo Gabriel Armas-Remofisrt | F22: 6536.4 | G22: =G21+E22-F22 -> 108.09
A23: 45624 | D23: Comisión interbancaria por transferencia pago nómina | F23: 4.8 | G23: =G22+E23-F23 -> 103.29
A24: 45624 | D24: Impuesto ITF | F24: 0.3 | G24: =G23+E24-F24 -> 102.99
A25: 45626 | D25: Envio estado de cuenta | F25: 5.5 | G25: =G24+E25-F25 -> 97.49
A26: 45626 | D26: Costo por uso de pagina bancaria | F26: 35 | G26: =G25+E26-F26 -> 62.49
A27: 45626 | D27: Saldo | G27: =G26+E27-F27 -> 62.49
A28: 45627 | D28: Inicio mes | G28: =G27+E28-F28 -> 62.49
A29: 45637 | D29: Transferencia de fondos de la cuenta de USD a Soles para pago de seguridad social de noviembre | E29: 3000 | G29: =G28+E29-F29 -> 3062.49
A30: 45637 | D30: Transferencia de fondos de la cuenta de USD a Soles para gastos empleado Noviembre | E30: 1239.32 | G30: =G29+E30-F30 -> 4301.81
A31: 45637 | D31: Transferencia de fondos de la cuenta de USD a Soles para gastos empleado Noviembre | E31: 3323.19 | G31: =G30+E31-F31 -> 7625
A32: 45638 | D32: Pago de seguridad social noviembre | F32: 914.43 | G32: =G31+E32-F32 -> 6710.57
A33: 45638 | D33: Pago Gratificaciones y Bonificación de Perú Gonzalo Gabriel Armas-Remofisrt | F33: 3270 | G33: =G32+E33-F33 -> 3440.57
A34: 45638 | D34: Comisión Gratificaciones y Bonificación de Perú Gonzalo Gabriel Armas-Remofisrt | F34: 4.3 | G34: =G33+E34-F34 -> 3436.27
A35: 45642 | D35: Transferencia de fondos de la cuenta de USD a Soles para Salarios, Seguridad social e impuestos de Diciembre | E35: 22167.95 | G35: =G34+E35-F35 -> 25604.22
A36: 45642 | D36: Transferencia de fondos de la cuenta de USD a Soles para Salarios, Seguridad social e impuestos de Diciembre | E36: 113.76 | G36: =G35+E36-F36 -> 25717.98
A37: 45642 | D37: Devolución de dinero Gratificaciones y Bonificación de Perú Gonzalo Gabriel Armas-Remofisrt | E37: 3270 | G37: =G36+E37-F37 -> 28987.98
A38: 45642 | D38: Impuesto ITF | F38: 0.15 | G38: =G37+E38-F38 -> 28987.83
A39: 45642 | D39: Mantenimiento Adic Neg | F39: 10 | G39: =G38+E39-F39 -> 28977.83
A40: 45643 | D40: Pago EESSALUD Seguridad regular trabajador Gonzalo Gabrile Armas-Remotefirst | F40: 702 | G40: =G39+E40-F40 -> 28275.83
A41: 45646 | D41: Pago Gratificaciones y Bonificación de Perú Gonzalo Gabriel Armas-Remofisrt | F41: 3270 | G41: =G40+E41-F41 -> 25005.83
A42: 45646 | D42: Comisión Gratificaciones y Bonificación de Perú Gonzalo Gabriel Armas-Remofisrt | F42: 4.8 | G42: =G41+E42-F42 -> 25001.03
A43: 45646 | D43: Impuesto ITF | F43: 0.15 | G43: =G42+E43-F43 -> 25000.88
A44: 45653 | D44: Pago Nómina Diciembre Gonzalo Gabriel Armas-Remofisrt | F44: 15995.74 | G44: =G43+E44-F44 -> 9005.14
A45: 45653 | D45: Comisión Gratificaciones y Bonificación de Perú Gonzalo Gabriel Armas-Remofisrt | F45: =4.8+0.65 -> 5.45 | G45: =G44+E45-F45 -> 8999.69
A46: 45653 | D46: Impuesto ITF | F46: 0.15 | G46: =G45+E46-F46 -> 8999.54
A47: 45657 | D47: Envio estado de cuenta | F47: 5.5 | G47: =G46+E47-F47 -> 8994.04
A48: 45657 | D48: Costo por uso de pagina bancaria | F48: 35 | G48: =G47+E48-F48 -> 8959.04
A49: 45657 | D49: Saldo | G49: =G48+E49-F49 -> 8959.04
A50: 45658 | D50: Inicio mes | G50: =G49+E50-F50 -> 8959.04
A51: 45665 | D51: Pago de seguridad social Diciembre | F51: 2004.26 | G51: =G50+E51-F51 -> 6954.78
A52: 45665 | D52: Impuesto ITF | F52: 0.1 | G52: =G51+E52-F52 -> 6954.68
A53: 45672 | D53: Mantenimiento Adic Neg | F53: 10 | G53: =G52+E53-F53 -> 6944.68
A54: 45673 | D54: Pago de renta Diciembre | F54: =777 -> 777 | G54: =G53+E54-F54 -> 6167.68
A55: 45673 | D55: Pago EESSALUD Seguridad regular trabajador Gonzalo Gabriel Armas-Remotefirst | F55: 1620 | G55: =G54+E55-F55 -> 4547.68
A56: 45685 | D56: Transferencia de fondos de la cuenta de USD a Soles para Salarios, reembolsos , Seguridad social e impuestos de Enero | E56: 27103.24 | G56: =G55+E56-F56 -> 31650.92
A57: 45685 | D57: Pago Nómina Enero Gonzalo Gabriel Armas-Remofisrt | F57: 19265.74 | G57: =G56+E57-F57 -> 12385.18
A58: 45685 | D58: Comisión Gratificaciones y Bonificación de Perú Gonzalo Gabriel Armas-Remofisrt | F58: =4.8 -> 4.8 | G58: =G57+E58-F58 -> 12380.38
A59: 45685 | D59: Pago reembolso Gonzalo Gabriel Armas-Remofisrt | F59: 2051.68 | G59: =G58+E59-F59 -> 10328.7
A60: 45685 | D60: Comisión Gratificaciones y Bonificación de Perú Gonzalo Gabriel Armas-Remofisrt | F60: =4.8 -> 4.8 | G60: =G59+E60-F60 -> 10323.9
A61: 45685 | D61: Impuesto ITF | F61: 1.05 | G61: =G60+E61-F61 -> 10322.85
A62: 45688 | D62: Pago Examenes médicos de ingreso señor Braidy Vera -Administración de servicio en salud ocupacional S.A.C | F62: 302 | G62: =G61+E62-F62 -> 10020.85
A63: 45688 | D63: Pago recibo Nro.1528202171 seguro complementario de trabajo de riesgo pensiones | F63: 121.54 | G63: =G62+E63-F63 -> 9899.31
A64: 45688 | D64: Pago recibos nro.158202179 -15202008 seguro complementario de trabajo de riesgo salud | F64: 236 | G64: =G63+E64-F64 -> 9663.31
A65: 45688 | D65: Envio estado de cuenta | F65: 5.5 | G65: =G64+E65-F65 -> 9657.81
A66: 45688 | D66: Costo por uso de pagina bancaria | F66: 35 | G66: =G65+E66-F66 -> 9622.81
A67: 45688 | D67: Saldo | G67: =G66+E67-F67 -> 9622.81
A68: 45689 | D68: Inicio mes | G68: =G67+E68-F68 -> 9622.81
A69: 45695 | D69: PLAME Essalud y Renta de Quinta Categoría (Retención) | F69: 4828 | G69: =G68+E69-F69 -> 4794.81
A70: 45702 | D70: Pago de seguridad social Enero | F70: 2389.55 | G70: =G69+E70-F70 -> 2405.26
A71: 45702 | D71: Impuesto ITF | F71: 0.1 | G71: =G70+E71-F71 -> 2405.16
A72: 45705 | D72: Pago de renta Enero | F72: 485 | G72: =G71+E72-F72 -> 1920.16
A73: 45705 | D73: Mantenimiento Adic Neg | F73: 10 | G73: =G72+E73-F73 -> 1910.16
A74: 45706 | D74: Pago recibo Nro.158638301 seguro complementario de trabajo de riesgo salud-HectorAndrés Zevallos Vásquez | F74: 29.81 | G74: =G73+E74-F74 -> 1880.35
A75: 45713 | D75: Transferencia de fondos de la cuenta de USD a Soles para Salarios, reembolsos , Seguridad social e impuestos de Febrero Remofirst | E75: 34389.85 | G75: =G74+E75-F75 -> 36270.2
A76: 45713 | D76: Pago anticipo de empleado Gonzalo Gabriel Armas-Remofisrt | F76: 4797 | G76: =G75+E76-F76 -> 31473.2
A77: 45713 | D77: Comisión Gratificaciones y Bonificación de Perú Gonzalo Gabriel Armas-Remofisrt | F77: =4.8 -> 4.8 | G77: =G76+E77-F77 -> 31468.4
A78: 45713 | D78: Impuesto ITF | F78: 0.2 | G78: =G77+E78-F78 -> 31468.2
A79: 45715 | D79: Seguro de vida Ley S - Paricela Castillo Carol Milagros | F79: 118 | G79: =G78+E79-F79 -> 31350.2
A80: 45715 | D80: Seguro complementario de trabajo de riesgos de salud | F80: 118 | G80: =G79+E80-F80 -> 31232.2
A81: 45715 | D81: Seguro complementario de trabajo de riesgos Pensio | F81: 121.54 | G81: =G80+E81-F81 -> 31110.66
A82: 45715 | D82: Impuesto ITF | F82: 0.2 | G82: =G81+E82-F82 -> 31110.46
A83: 45716 | D83: Pago Nómina Febrero Gonzalo Gabriel Armas-Remofisrt | F83: 13204.76 | G83: =G82+E83-F83 -> 17905.7
A84: 45716 | D84: Comisión Gratificaciones y Bonificación de Perú Gonzalo Gabriel Armas-Remofisrt | F84: =4.8 -> 4.8 | G84: =G83+E84-F84 -> 17900.9
A85: 45716 | D85: Pago Nómina Febrero Héctor Andrés Zevallos Vasquez-Europortage | F85: 3868.8117 | G85: =G84+E85-F85 -> 14032.088
A86: 45716 | D86: Comisión Gratificaciones y Bonificación de Perú Héctor Andrés Zevallos Vasquez-Remofirst | F86: =4.8 -> 4.8 | G86: =G85+E86-F86 -> 14027.288
A87: 45716 | D87: Impuesto ITF | F87: 0.6 | G87: =G86+E87-F87 -> 14026.688
A88: 45716 | D88: Transferencia de fondos de la cuenta de USD a Soles para Salarios, reembolsos , Seguridad social e impuestos de Febrero-Europortage | E88: 31230.34 | G88: =G87+E88-F88 -> 45257.028
A89: 45716 | D89: Pago Nómina Febrero Braydi Yusset Vera Neira | F89: 20011.433 | G89: =G88+E89-F89 -> 25245.595
A90: 45716 | D90: Envio estado de cuenta | F90: 5.5 | G90: =G89+E90-F90 -> 25240.095
A91: 45716 | D91: Costo por uso de pagina bancaria | F91: 35 | G91: =G90+E91-F91 -> 25205.095
A92: 45716 | D92: Impuesto ITF | F92: 1 | G92: =G91+E92-F92 -> 25204.095
A93: 45716 | D93: Saldo | G93: =G92+E93-F93 -> 25204.095
A94: 45717 | D94: Inicio mes | G94: =G93+E94-F94 -> 25204.095
A95: 45723 | D95: Planilla de declaración y pago de aportes previsional-Gonzálo de armas | F95: =1800+164.78 -> 1964.78 | G95: =G94+E95-F95 -> 23239.315
A96: 45723 | D96: Planilla de declaración y pago de aportes previsional-Braydi Yusset Vera Neyra | F96: =1860+164.78+288.3 -> 2313.08 | G96: =G95+E96-F96 -> 20926.235
A97: 45723 | D97: Planilla de declaración y pago de aportes previsional Hector Andrés Zevallos Vásquez | F97: =640+87.68 -> 727.68 | G97: =G96+E97-F97 -> 20198.555
A98: 45724 | D98: Impuesto ITF | F98: 0.15 | G98: =G97+E98-F98 -> 20198.405 | H98: =F98/3.68 -> 0.04076087
A99: 45724 | D99: Pago examen médico ocupacional de ingreso Christian Portugal Europortage | F99: 302 | G99: =G98+E99-F99 -> 19896.405
A100: 45724 | D100: Pago seguro complementario de trabajo riesgo salud-Obreros alto riesgo- Recibo Nro 159141649 | F100: 116.95 | G100: =G99+E100-F100 -> 19779.455
A101: 45724 | D101: Pago seguro complementario de trabajo riesgo salud-trabajadores de alto riesgo- Recibo Nro 159141650 | F101: 113.54 | G101: =G100+E101-F101 -> 19665.915
A102: 45724 | D102: Pago seguro complementario de vida ley Christian Portugal Europortage | F102: 29.81 | G102: =G101+E102-F102 -> 19636.105
...

Sheet BCP USD BCP
D2: BCP USD
A4: FECHA | D4: DESCRIPCIÓN | E4: INGRESO | F4: SALIDA | G4: SALDO
A5: 45566 | G5: 0
A6: 45575 | D6: Mantenimiento TD | F6: 15.84 | G6: =G5+E6-F6 -> -15.84
A7: 45596 | D7: Envio estado de cuenta | F7: 2 | G7: =G6+E7-F7 -> -17.84
A8: 45596 | G8: =G7+E8-F8 -> -17.84
A9: 45597 | G9: =G8+E9-F9 -> -17.84
A10: 45607 | D10: Devolución Mantenimiento TD | E10: 15.84 | G10: =G9+E10-F10 -> -2
A11: 45608 | D11: Envío de recursos desde casa matriz S&P col a Sucursal Perú para fondeo cuenta y pago Proveedor | E11: 2595 | G11: =G10+E11-F11 -> 2593
A12: 45608 | D12: Impuesto ITF | F12: 0.1 | G12: =G11+E12-F12 -> 2592.9
A13: 45610 | D13: Pago de facturas Nro. 4734 servicio de octubre y 4853 servicios de noviembre- Estudio Fuentes | F13: 1338.8 | G13: =G12+E13-F13 -> 1254.1
A14: 45610 | D14: Impuesto ITF | F14: 0.05 | G14: =G13+E14-F14 -> 1254.05
A15: 45614 | D15: Portes autosobre | F15: 1.32 | G15: =G14+E15-F15 -> 1252.73
A16: 45621 | D16: Pago servicios mes de noviembre Remotefisrt SIL | E16: 3833.74 | G16: =G15+E16-F16 -> 5086.47
A17: 45621 | D17: Impuesto ITF | F17: 0.15 | G17: =G16+E17-F17 -> 5086.32
A18: 45623 | D18: Transferencia de fondos desde la cuenta de USD a Soles para pago pólizas | F18: 81.06 | G18: =G17+E18-F18 -> 5005.26
A19: 45624 | D19: Transferencia de fondos de la cuenta de USD a Soles para pago nómina Gonzalo Gabriel Armas-Remotefisrt | F19: 1778.98 | G19: =G18+E19-F19 -> 3226.28
A20: 45626 | D20: Envio estado de cuenta | F20: 2 | G20: =G19+E20-F20 -> 3224.28
A21: 45626 | D21: Intereses deudores | F21: 0.15 | G21: =G20+E21-F21 -> 3224.13
A22: 45626 | D22: Mantenimiento TD | F22: 13 | G22: =G21+E22-F22 -> 3211.13
A23: 45626 | G23: =G22+E23-F23 -> 3211.13
A24: 45627 | G24: =G23+E24-F24 -> 3211.13
A25: 45628 | D25: Portes autosobre | F25: 1.32 | G25: =G24+E25-F25 -> 3209.81
A26: 45628 | D26: Porte extracto Numer | F26: 1.32 | G26: =G25+E26-F26 -> 3208.49
A27: 45637 | D27: Transferencia de fondos de la cuenta de USD a Soles para Seguridad social de noviembre | F27: 815.44 | G27: =G26+E27-F27 -> 2393.05
A28: 45637 | D28: Transferencia de fondos de la cuenta de USD a Soles para pagos | F28: 336.77 | G28: =G27+E28-F28 -> 2056.28
A29: 45637 | D29: Transferencia de fondos de la cuenta de USD a Soles para pagos | F29: 902.55 | G29: =G28+E29-F29 -> 1153.73
A30: 45639 | D30: Pago servicios mes de diciembre Remotefisrt SIL | E30: 6017.36 | G30: =G29+E30-F30 -> 7171.09
A31: 45639 | D31: Impuesto ITF | F31: 0.3 | G31: =G30+E31-F31 -> 7170.79
A32: 45639 | D32: Transferencia de fondos de la cuenta de USD a Soles para Salarios, Seguridad social e impuestos de Diciembre | F32: 5986.48 | G32: =G31+E32-F32 -> 1184.31
A33: 45639 | D33: Transferencia de fondos de la cuenta de USD a Soles para Salarios, Seguridad social e impuestos de Diciembre | F33: 30.88 | G33: =G32+E33-F33 -> 1153.43
A34: 45642 | D34: Portes autosobre | F34: 1.32 | G34: =G33+E34-F34 -> 1152.11
A35: 45645 | D35: Pago de facturas Nro.5107 servicio de Diciembre- Estudio Fuentes | F35: 938.1 | G35: =G34+E35-F35 -> 214.01
A36: 45657 | D36: Envio estado de cuenta | F36: 2 | G36: =G35+E36-F36 -> 212.01
A37: 45657 | D37: Mantenimiento TD | F37: 13 | G37: =G36+E37-F37 -> 199.01
A38: 45657 | G38: =G37+E38-F38 -> 199.01
A39: 45658 | G39: =G38+E39-F39 -> 199.01
A40: 45663 | D40: Devolución Mantenimiento TD | E40: 13 | G40: =G39+E40-F40 -> 212.01
A41: 45678 | D41: Pago servicios mes de enero Remotefisrt SIL | E41: 8565.91 | G41: =G40+E41-F41 -> 8777.92
A42: 45678 | D42: Impuesto ITF | F42: 0.4 | G42: =G41+E42-F42 -> 8777.52
A43: 45685 | D43: Pago de facturas Nro.5260 servicio de Enero- Estudio Fuentes | F43: 454.3 | G43: =G42+E43-F43 -> 8323.22
A44: 45685 | D44: Transferencia de fondos de la cuenta de USD a Soles para Salarios, Seguridad social e impuestos de Enero | F44: 7323.22 | G44: =G43+E44-F44 -> 1000
A45: 45685 | D45: Impuesto ITF | F45: 1.32 | G45: =G44+E45-F45 -> 998.68
A46: 45688 | D46: Envio estado de cuenta | F46: 2 | G46: =G45+E46-F46 -> 996.68
A47: 45688 | D47: Mantenimiento TD | F47: 13 | G47: =G46+E47-F47 -> 983.68
A48: 45688 | G48: =G47+E48-F48 -> 983.68
A49: 45689 | G49: =G48+E49-F49 -> 983.68
A50: 45709 | D50: Pago servicios mes de Febrero Remotefisrt SIL- Factura 7 | E50: 8181.44 | G50: =G49+E50-F50 -> 9165.12
A51: 45709 | D51: Impuesto ITF | F51: 0.4 | G51: =G50+E51-F51 -> 9164.72
A52: 45712 | D52: Pago servicios mes de Febrero Remotefisrt SIL-Factura 8 | E52: 1370.8 | G52: =G51+E52-F52 -> 10535.52
A53: 45712 | D53: Portes autosobre | F53: 1.32 | G53: =G52+E53-F53 -> 10534.2
A54: 45712 | D54: Impuesto ITF | F54: 0.05 | G54: =G53+E54-F54 -> 10534.15 | H54: ***** Saldo final llegada de recursos****
A55: 45713 | D55: Transferencia de fondos de la cuenta de USD a Soles para Salarios, Seguridad social e impuestos de Febrero | F55: 9434.8 | G55: =G54+E55-F55 -> 1099.35
A56: 45713 | D56: Pago de facturas Nro.5440 servicio de Febrero- Estudio Fuentes | F56: 348.1 | G56: =G55+E56-F56 -> 751.25
A57: 45716 | D57: Pago servicios mes de Febrero Remotefisrt SIL-Factura 6 | E57: 7173.86 | G57: =G56+E57-F57 -> 7925.11
A58: 45716 | D58: Pago servicios mes de Febrero Remotefisrt SIL-Factura 9 | E58: 1616.02 | G58: =G57+E58-F58 -> 9541.13
A59: 45716 | D59: Impuesto ITF | F59: 0.4 | G59: =G58+E59-F59 -> 9540.73
A60: 45716 | D60: Transferencia de fondos de la cuenta de USD a Soles para Salarios, reembolsos , Seguridad social e impuestos de Febrero-Europortage | F60: =(E57+E58)-250 -> 8539.88 | G60: =G59+E60-F60 -> 1000.85
A61: 45716 | D61: Mantenimiento TD | F61: 13 | G61: =G60+E61-F61 -> 987.85
A62: 45716 | D62: Envio estado de cuenta | F62: 2 | G62: =G61+E62-F62 -> 985.85
A63: 45716 | G63: =G62+E63-F63 -> 985.85
A64: 45717 | G64: =G63+E64-F64 -> 985.85
A65: 45719 | D65: Pago servicios mes de Febrero Remotefisrt SIL-Factura 9 | E65: 2246.37 | G65: =G64+E65-F65 -> 3232.22
A66: 45719 | D66: Portes autosobre | F66: 1.32 | G66: =G65+E66-F66 -> 3230.9
A67: 45719 | D67: Impuesto ITF | F67: 0.1 | G67: =G66+E67-F67 -> 3230.8
A68: 45726 | D68: Portes autosobre | F68: 1.32 | G68: =G67+E68-F68 -> 3229.48
A69: 45741 | D69: Pago servicios mes de Marzo Remotefisrt SIL-Factura 11- Abono | E69: 12729.47 | G69: =G68+E69-F69 -> 15958.95
A70: 45741 | D70: Impuesto ITF | F70: 0.6 | G70: =G69+E70-F70 -> 15958.35
A71: 45742 | D71: Pago servicios mes de Marzo Eurportage SIL-Factura 12 | E71: 9668.49 | G71: =G70+E71-F71 -> 25626.84
A72: 45742 | D72: Pago servicios mes de Marzo Remotefisrt SIL-Factura 13- Off cycle y saldo final factura 11 -USD 70,80 | E72: 2571.6 | G72: =G71+E72-F72 -> 28198.44
A73: 45742 | D73: Impuesto ITF | F73: 0.55 | G73: =G72+E73-F73 -> 28197.89
A74: 45743 | D74: Pago de facturas Nro.5628 servicio de Marzo- Estudio Fuentes | F74: 348.1 | G74: =G73+E74-F74 -> 27849.79
A75: 45744 | D75: Pago servicios mes de Marzo Eurportage SIL-14 | E75: 3578.05 | G75: =G74+E75-F75 -> 31427.84
A76: 45744 | D76: Impuesto ITF | F76: 0.15 | G76: =G75+E76-F76 -> 31427.69
A77: 45744 | D77: Transferencia de fondos de la cuenta de USD a Soles para Salarios, Seguridad social e impuestos de Marzo | F77: 7036.42 | G77: =G76+E77-F77 -> 24391.27
A78: 45744 | D78: Transferencia de fondos de la cuenta de USD a Soles para Salarios, Seguridad social e impuestos de Marzo | F78: 18463.58 | G78: =G77+E78-F78 -> 5927.69
A79: 45747 | D79: Portes autosobre | F79: 1.32 | G79: =G78+E79-F79 -> 5926.37
A80: 45747 | D80: Envio estado de cuenta | F80: 2 | G80: =G79+E80-F80 -> 5924.37
A81: 45747 | D81: Mantenimiento TD | F81: 13 | G81: =G80+E81-F81 -> 5911.37
A82: 45747 | G82: =G81+E82-F82 -> 5911.37
A83: 45748 | G83: =G82+E83-F83 -> 5911.37
A84: 45769 | D84: Pago servicios mes de abril Remotefisrt SIL Factura 15-17 | E84: 5589.3 | G84: =G83+E84-F84 -> 11500.67
A85: 45769 | D85: Impuesto ITF | F85: 0.25 | G85: =G84+E85-F85 -> 11500.42
A86: 45769 | D86: Tralasdo de fondos de la cuenta de soles a USD | E86: 1685.39 | G86: =G85+E86-F86 -> 13185.81
A87: 45769 | D87: Transferencia de fondos de la cuenta de USD a Soles para liquidación de Gonzalo de Armas y Hector Zevallos y retorno de fondos | F87: 2182.4 | G87: =G86+E87-F87 -> 11003.41
A88: 45769 | D88: Transferencia de fondos de la cuenta de USD a Soles para liquidación de Gonzalo de Armas y Hector Zevallos | F88: 5713.69 | G88: =G87+E88-F88 -> 5289.72
A89: 45769 | D89: Transferencia de fondos de la cuenta de USD a Soles para liquidación de Gonzalo de Armas y Hector Zevallos | F89: 150.89 | G89: =G88+E89-F89 -> 5138.83
A90: 45775 | D90: Pago servicios mes de Abril Europortage SIL-16-18 | E90: 14249.81 | G90: =G89+E90-F90 -> 19388.64
A91: 45775 | D91: Impuesto ITF | F91: 0.7 | G91: =G90+E91-F91 -> 19387.94
A92: 45775 | D92: Transferencia de fondos de la cuenta de USD a Soles para pago de nóminas y reembolsos, impuestos y SS Europortage | F92: 16387.94 | G92: =G91+E92-F92 -> 3000
A93: 45775 | D93: Portes autosobre | F93: 1.32 | G93: =G92+E93-F93 -> 2998.68
A94: 45776 | D94: Pago de factura Nro.5752 servicio de Abril- Estudio Fuentes | F94: 348.1 | G94: =G93+E94-F94 -> 2650.58
A95: 45777 | D95: Envio estado de cuenta | F95: 2 | G95: =G94+E95-F95 -> 2648.58
A96: 45777 | D96: Mantenimiento TD | F96: 13 | G96: =G95+E96-F96 -> 2635.58
A97: 45777 | G97: =G96+E97-F97 -> 2635.58
A98: 45778 | G98: =G97+E98-F98 -> 2635.58
A99: 45782 | D99: Portes autosobre | F99: 1.32 | G99: =G98+E99-F99 -> 2634.26
A100: 45799 | D100: Pago servicios mes de Mayo Europortage SIL-19 | E100: 22201.83 | G100: =G99+E100-F100 -> 24836.09 | H100: 22331.83 | I100: =H100-E100 -> 130 | J100: =I100/H100 -> 0.0058212874
A101: 45799 | D101: Impuesto ITF | F101: 1.1 | G101: =G100+E101-F101 -> 24834.99
A102: 45803 | D102: Portes autosobre | F102: 1.32 | G102: =G101+E102-F102 -> 24833.67
...

Sheet GASTOS SUCURSAL PERÚ
B2: Fecha | C2: Descripción | D2: Valor
B3: 45560 | C3: 50% Anticipo constitución | D3: 500
B4: 45560 | C4: IGV | D4: 90
B5: 45560 | C5: Apertura cuenta | D5: 150
B6: 45560 | C6: Comisión Bancaria | D6: 25
B7: 45566 | C7: 50% Saldo final constitución | D7: 500
B8: 45566 | C8: IGV | D8: 90
B9: 45566 | C9: Comisión Bancaria | D9: 25
B10: 45608 | C10: factura estudio fuentes 4734 Oct | D10: 348.1
B11: 45608 | C11: factura estudio fuentes 4853 Nov | D11: 1020.7
B12: 45608 | C12: Dinero Caja | D12: =2620-D10-D11 -> 1251.2
B13: 45623 | C13: Pago póliza vida seguro | D13: =629.51/'Diferencia Cambio S&P'!$S$26 -> #DIV/0!
B14: 45624 | C14: Pago Nómina Noviembre Gonzalo Gabriel Armas | D14: =6536.4/'Diferencia Cambio S&P'!$S$26 -> #DIV/0!
B15: 45638 | C15: Seguridad social noviembre | D15: =914.43/'Diferencia Cambio S&P'!$S$26 -> #DIV/0!
B16: 45638 | C16: Pago Gratificaciones y Bonificación de Perú Diciembre Gonzalo Gabriel Armas | D16: =3270/'Diferencia Cambio S&P'!$S$26 -> #DIV/0!
B17: 45642 | C17: Aporte Esauld | D17: =702/'Diferencia Cambio S&P'!$S$26 -> #DIV/0!
B18: 45646 | C18: factura estudio fuentes 5107 Dic | D18: 938.1
B19: 45646 | C19: Gastos Financieros soles | D19: =('BCP SOLES BCP'!$F$7+'BCP SOLES BCP'!$F$8+'BCP SOLES BCP'!$F$9+'BCP SOLES BCP'!$F$13+'BCP SOLES BCP'!$F$14+'BCP SOLES BCP'!$F$15+'BCP SOLES BCP'!$F$18+'BCP SOLES BCP'!$F$23+'BCP SOLES BCP'!$F$24+'BCP SOLES BCP'!$F$25+'BCP SOLES BCP'!$F$26+'BCP SOLES BCP'!$F$34+'BCP SOLES BCP'!$F$38)/'Diferencia Cambio S&P'!$S$26 -> #DIV/0!
B20: 45646 | C20: Gastos Financieros USD | D20: ='BCP USD BCP'!$F$6+'BCP USD BCP'!$F$7+'BCP USD BCP'!$F$12+'BCP USD BCP'!$F$14+'BCP USD BCP'!$F$15+'BCP USD BCP'!$F$17+'BCP USD BCP'!$F$20+'BCP USD BCP'!$F$21+'BCP USD BCP'!$F$22+'BCP USD BCP'!$F$25+'BCP USD BCP'!$F$26+'BCP USD BCP'!$F$31 -> 37.55
B21: 45653 | C21: Pago Nómina Noviembre Gonzalo Gabriel Armas | D21: ='BCP SOLES BCP'!F44/'Diferencia Cambio S&P'!$S$26 -> #DIV/0!
B22: 45653 | C22: Gastos Financieros USD | D22: =('BCP SOLES BCP'!$F$45+'BCP SOLES BCP'!$F$46)/'Diferencia Cambio S&P'!$S$26 -> #DIV/0!
B23: TOTAL | D23: =SUM(D3:D22) -> #DIV/0!

Sheet FLUJO CAJA MARZO
D1: 42400
D4: Fecha de Elaboración: | E4: 45719
C6: Tasa de cambio: | D6: 3.68 | J6: 12800.27
D7: MARZO | J7: 12729.47
D8: VALOR S/ Sol | E8: VALOR USD | J8: =J6-J7 -> 70.8
C9: BANCOS | D9: =SUBTOTAL(9,D10:D11) -> 38615.269 | E9: =SUBTOTAL(9,E10:E11) -> 10493.28
C10: Bancos S/ Soles | D10: ='BCP SOLES BCP'!$G$93+1521.83 -> 26725.925 | E10: =D10/$D$6 -> 7262.4796
C11: Bancos USD | D11: =E11*$D$6 -> 11889.344 | E11: ='BCP USD BCP'!$G$67 -> 3230.8
C12: CLIENTES | D12: =SUBTOTAL(9,D13:D15) -> 89149.454 | E12: =SUBTOTAL(9,E13:E15) -> 25084.56 | F12: Factura inicial | G12: Notas crédito | J12: Valor final real
B13: Pagado | C13: Client: Remorfist-Factura Nro 11-Abono | D13: =E13*3.54 -> 45312.956 | E13: =12729.47+70.8 -> 12800.27 | F13: =14132.55 -> 14132.55 | G13: =32.29+1300 -> 1332.29 | J13: =F13-G13 -> 12800.26
B14: Pagado | C14: Client: Eurportage-Factura Nro 12 | D14: =E14*3.54 -> 34633.555 | E14: 9783.49
B15: Pagado | C15: Client: Remorfist-Factura Nro 13-Offcycle | D15: =E15*3.68 -> 9202.944 | E15: 2500.8 | F15: 2571.6 | G15: =E15-F15 -> -70.8
C16: TOTAL INGRESOS | D16: =SUBTOTAL(9,D9:D14) -> 118561.78 | E16: =SUBTOTAL(9,E9:E14) -> 33077.04
B19: CUENTAS X PAGAR MES | D19: MARZO | F19: Fecha de Elaboración: | J19: 45717
B20: Factura | C20: PROVEEDOR | D20: VALOR S/Sol | E20: VALOR USD | F20: Fecha vencimiento | G20: Estado | J20: KPI
C21: SEGURIDAD IGSS | D21: =SUBTOTAL(9,D22:D24) -> 5005.54 | E21: =SUBTOTAL(9,E22:E24) -> 1360.2011
C22: Planilla de declaración y pago de aportes previsional-Gonzálo de armas | D22: 1964.78 | E22: =D22/$D$6 -> 533.90761 | F22: 45723 | G22: Cancelado | H22: =IF(OR(G22="Sin pagar",G22="Pagar"),_xlfn.SINGLE(NETWORKDAYS($J$19,F22,FestivosPerú!$A$2:$A$15)),0) -> 0 | I22: =NETWORKDAYS($J$19,F22,FestivosPerú!$A$2:$A$15) -> 5 | J22: =H22 -> 0
C23: Planilla de declaración y pago de aportes previsional-Braydi Yusset Vera Neyra | D23: 2313.08 | E23: =D23/$D$6 -> 628.55435 | F23: 45723 | G23: Cancelado | H23: =IF(OR(G23="Sin pagar",G23="Pagar"),_xlfn.SINGLE(NETWORKDAYS($J$19,F23,FestivosPerú!$A$2:$A$15)),0) -> 0 | I23: =NETWORKDAYS($J$19,F23,FestivosPerú!$A$2:$A$15) -> 5 | J23: =H23 -> 0
C24: Planilla de declaración y pago de aportes previsional Hector Andrés Zevallos Váquez | D24: 727.68 | E24: =D24/$D$6 -> 197.73913 | F24: 45723 | G24: Cancelado | H24: =IF(OR(G24="Sin pagar",G24="Pagar"),_xlfn.SINGLE(NETWORKDAYS($J$19,F24,FestivosPerú!$A$2:$A$15)),0) -> 0 | I24: =NETWORKDAYS($J$19,F24,FestivosPerú!$A$2:$A$15) -> 5 | J24: =H24 -> 0
C25: IMPUESTOS | D25: =SUBTOTAL(9,D26:D27) -> 12189 | E25: =SUBTOTAL(9,E26:E27) -> 3312.2283 | J25: =H25 -> 0
C26: PLAME Essalud y Renta de Quinta Categoría (Retención) | D26: 11110 | E26: =D26/$D$6 -> 3019.0217 | F26: 45728 | G26: Cancelado | H26: =IF(OR(G26="Sin pagar",G26="Pagar"),_xlfn.SINGLE(NETWORKDAYS($J$19,F26,FestivosPerú!$A$2:$A$15)),0) -> 0 | I26: =NETWORKDAYS($J$19,F26,FestivosPerú!$A$2:$A$15) -> 8 | J26: =H26 -> 0
C27: Pago de renta IGV | D27: 1079 | E27: =D27/$D$6 -> 293.20652 | F27: 45733 | G27: Cancelado | H27: =IF(OR(G27="Sin pagar",G27="Pagar"),_xlfn.SINGLE(NETWORKDAYS($J$19,F27,FestivosPerú!$A$2:$A$15)),0) -> 0 | I27: =NETWORKDAYS($J$19,F27,FestivosPerú!$A$2:$A$15) -> 11 | J27: =H27 -> 0
C28: SERVICIOS OUTSORCING CONTABLE | D28: =SUBTOTAL(9,D29:D29) -> 1281.008 | E28: =SUBTOTAL(9,E29:E29) -> 348.1 | J28: =H28 -> 0
B29: 5628 | C29: Estudio fuentes servicios marzo | D29: =$E$29*$D$6 -> 1281.008 | E29: 348.1 | F29: 45743 | G29: Cancelado | H29: =IF(OR(G29="Sin pagar",G29="Pagar"),_xlfn.SINGLE(NETWORKDAYS($J$19,F29,FestivosPerú!$A$2:$A$15)),0) -> 0 | I29: =NETWORKDAYS($J$19,F29,FestivosPerú!$A$2:$A$15) -> 19 | J29: =H29 -> 0
C30: PÓLIZAS DE VIDA Y SEGUROS MÉDICO | D30: =SUBTOTAL(9,D31:D31) -> 1254 | E30: =SUBTOTAL(9,E31:E31) -> 340.76087
C31: Póliza de salud Braidy Vera- pago 12 meses -1er mes | D31: 1254 | E31: =D31/D6 -> 340.76087 | F31: 45727 | G31: Sin Pagar | H31: =IF(OR(G31="Sin pagar",G31="Pagar"),_xlfn.SINGLE(NETWORKDAYS($J$19,F31,FestivosPerú!$A$2:$A$15)),0) -> 7 | I31: =NETWORKDAYS($J$19,F31,FestivosPerú!$A$2:$A$15) -> 7 | J31: =H31 -> 7
C32: COSTOS FINANCIEROS | D32: =SUBTOTAL(9,D33:D33) -> 116.16261 | E32: =SUBTOTAL(9,E33:E33) -> 31.565926
C33: COSTOS FINANCIEROS | D33: =('BCP SOLES BCP'!$F$98+'BCP SOLES BCP'!$F$105+'BCP SOLES BCP'!$F$108+'BCP SOLES BCP'!$F$113+'BCP SOLES BCP'!$F$115+'BCP SOLES BCP'!$F$117+'BCP SOLES BCP'!$F$119+'BCP SOLES BCP'!$F$122+'BCP SOLES BCP'!$F$124+'BCP SOLES BCP'!$F$126+'BCP SOLES BCP'!$F$127)+(('BCP USD BCP'!$F$66+'BCP USD BCP'!$F$67+'BCP USD BCP'!$F$68+'BCP USD BCP'!$F$70+'BCP USD BCP'!$F$73+'BCP USD BCP'!$F$76+'BCP USD BCP'!$F$79+'BCP USD BCP'!$F$80+'BCP USD BCP'!$F$81)/$D$6) -> 116.16261 | E33: =D33/D6 -> 31.565926 | F33: 45747 | G33: Cancelado | H33: =IF(OR(G33="Sin pagar",G33="Pagar"),_xlfn.SINGLE(NETWORKDAYS($J$19,F33,FestivosPerú!$A$2:$A$15)),0) -> 0 | I33: =NETWORKDAYS($J$19,F33,FestivosPerú!$A$2:$A$15) -> 21 | J33: =H33 -> 0
C34: NÓMINAS | D34: =SUBTOTAL(9,D35:D38) -> 47268.854 | E34: =SUBTOTAL(9,E35:E38) -> 12844.797
C35: Gonzalo Gabriel Armas-Remofisrt | D35: 13204.759 | E35: =D35/$D$6 -> 3588.2498 | F35: 45744 | G35: Cancelado | H35: =IF(OR(G35="Sin pagar",G35="Pagar"),_xlfn.SINGLE(NETWORKDAYS($J$19,F35,FestivosPerú!$A$2:$A$15)),0) -> 0 | I35: =NETWORKDAYS($J$19,F35,FestivosPerú!$A$2:$A$15) -> 20 | J35: =H35 -> 0
C36: Héctor Andrés Zevallos Vasquez-Remotefirst | D36: 12481.715 | E36: =D36/$D$6 -> 3391.7704 | F36: 45744 | G36: Cancelado | H36: =IF(OR(G36="Sin pagar",G36="Pagar"),_xlfn.SINGLE(NETWORKDAYS($J$19,F36,FestivosPerú!$A$2:$A$15)),0) -> 0 | I36: =NETWORKDAYS($J$19,F36,FestivosPerú!$A$2:$A$15) -> 20 | J36: =H36 -> 0
C37: Braydi Yusset Vera Neira-Europortage | D37: 13725.33 | E37: =D37/$D$6 -> 3729.7092 | F37: 45744 | G37: Cancelado | H37: =IF(OR(G37="Sin pagar",G37="Pagar"),_xlfn.SINGLE(NETWORKDAYS($J$19,F37,FestivosPerú!$A$2:$A$15)),0) -> 0 | I37: =NETWORKDAYS($J$19,F37,FestivosPerú!$A$2:$A$15) -> 20 | J37: =H37 -> 0
C38: Cristhian Portugal Segovia -Europortage | D38: 7857.05 | E38: =D38/$D$6 -> 2135.0679 | F38: 45744 | G38: Cancelado | H38: =IF(OR(G38="Sin pagar",G38="Pagar"),_xlfn.SINGLE(NETWORKDAYS($J$19,F38,FestivosPerú!$A$2:$A$15)),0) -> 0 | I38: =NETWORKDAYS($J$19,F38,FestivosPerú!$A$2:$A$15) -> 20 | J38: =H38 -> 0
C39: REEMBOLSO | D39: =SUBTOTAL(9,D40:D42) -> 17893.41 | E39: =SUBTOTAL(9,E40:E42) -> 4862.3397
C40: Reembolso Braydi Yusset Vera Neira-Europortage | D40: 7044.25 | E40: =D40/$D$6 -> 1914.1984 | F40: 45744 | G40: Cancelado | H40: =IF(OR(G40="Sin pagar",G40="Pagar"),_xlfn.SINGLE(NETWORKDAYS($J$19,F40,FestivosPerú!$A$2:$A$15)),0) -> 0 | I40: =NETWORKDAYS($J$19,F40,FestivosPerú!$A$2:$A$15) -> 20 | J40: =H40 -> 0
C41: Reembolso Gonzalo Gabriel Armas-Remofisrt | D41: 10437.22 | E41: =D41/$D$6 -> 2836.2011 | F41: 45744 | G41: Cancelado | H41: =IF(OR(G41="Sin pagar",G41="Pagar"),_xlfn.SINGLE(NETWORKDAYS($J$19,F41,FestivosPerú!$A$2:$A$15)),0) -> 0 | I41: =NETWORKDAYS($J$19,F41,FestivosPerú!$A$2:$A$15) -> 20 | J41: =H41 -> 0
C42: Reembolso Héctor Andrés Zevallos Vasquez-Remotefirst | D42: 411.94 | E42: =D42/$D$6 -> 111.94022 | F42: 45744 | G42: Cancelado | H42: =IF(OR(G42="Sin pagar",G42="Pagar"),_xlfn.SINGLE(NETWORKDAYS($J$19,F42,FestivosPerú!$A$2:$A$15)),0) -> 0 | I42: =NETWORKDAYS($J$19,F42,FestivosPerú!$A$2:$A$15) -> 20 | J42: =H42 -> 0
C43: IMPREVISTO | D43: =SUBTOTAL(9,D44:D47) -> 587.3 | E43: =SUBTOTAL(9,E44:E47) -> 128.73913
B44: F001 - 0013697 | C44: Pago examen médico ocupacional de ingreso Christian Portugal Europortage | D44: 327 | E44: =D44/$D$6 -> 88.858696 | F44: 45724 | G44: Cancelado | H44: =IF(OR(G44="Sin pagar",G44="Pagar"),_xlfn.SINGLE(NETWORKDAYS($J$19,F44,FestivosPerú!$A$2:$A$15)),0) -> 0 | I44: =NETWORKDAYS($J$19,F44,FestivosPerú!$A$2:$A$15) -> 5 | J44: =H44 -> 0
C45: Pago seguro complementario de trabajo riesgo salud-Obreros alto riesgo- Recibo Nro 159141649 | D45: 116.95 | E45: =D45/$D$6 -> 31.779891 | F45: 45724 | G45: Cancelado | H45: =IF(OR(G45="Sin pagar",G45="Pagar"),_xlfn.SINGLE(NETWORKDAYS($J$19,F45,FestivosPerú!$A$2:$A$15)),0) -> 0 | I45: =NETWORKDAYS($J$19,F45,FestivosPerú!$A$2:$A$15) -> 5 | J45: =H45 -> 0
C46: Pago seguro complementario de trabajo riesgo salud-trabajadores de alto riesgo- Recibo Nro 159141650 | D46: 113.54 | E46: 0 | F46: 45724 | G46: Cancelado | H46: =IF(OR(G46="Sin pagar",G46="Pagar"),_xlfn.SINGLE(NETWORKDAYS($J$19,F46,FestivosPerú!$A$2:$A$15)),0) -> 0 | I46: =NETWORKDAYS($J$19,F46,FestivosPerú!$A$2:$A$15) -> 5 | J46: =H46 -> 0
C47: Pago seguro complementario de vida ley Christian Portugal Europortage | D47: 29.81 | E47: =D47/$D$6 -> 8.1005435 | F47: 45724 | G47: Cancelado | H47: =IF(OR(G47="Sin pagar",G47="Pagar"),_xlfn.SINGLE(NETWORKDAYS($J$19,F47,FestivosPerú!$A$2:$A$15)),0) -> 0 | I47: =NETWORKDAYS($J$19,F47,FestivosPerú!$A$2:$A$15) -> 5 | J47: =H47 -> 0
C48: TOTAL EGRESOS | D48: =SUBTOTAL(9,D21:D47) -> 85595.275 | E48: =SUBTOTAL(9,E21:E47) -> 23228.732
C50: SALDO | D50: =D16-D48 -> 32966.505 | E50: =E16-E48 -> 9848.3073
C51: % | D51: =IF($D$16=0,0,D50/$D$16) -> 0.27805339 | E51: =IF($E$16=0,0,E50/$E$16) -> 0.29773848
C55: Fecha Inicial | D55: Fecha Final | E55: Valor VALOR ₡ CRC | F55: Valor VALOR USD
C56: 45717 | D56: 45725 | E56: =SUMIFS($D$20:$D$53,$F$20:$F$53,">="&C56,$F$20:$F$53,"<="&D56,$G$20:$G$53,$D$69) -> 0 | F56: =SUMIFS($E$20:$E$53,$F$20:$F$53,">="&C56,$F$20:$F$53,"<="&D56,$G$20:$G$53,$D$69) -> 0
C57: 45726 | D57: 45732 | E57: =SUMIFS($D$20:$D$53,$F$20:$F$53,">="&C57,$F$20:$F$53,"<="&D57,$G$20:$G$53,$D$69) -> 1254 | F57: =SUMIFS($E$20:$E$53,$F$20:$F$53,">="&C57,$F$20:$F$53,"<="&D57,$G$20:$G$53,$D$69) -> 340.76087
C58: 45733 | D58: 45739 | E58: =SUMIFS($D$20:$D$53,$F$20:$F$53,">="&C58,$F$20:$F$53,"<="&D58,$G$20:$G$53,$D$69) -> 0 | F58: =SUMIFS($E$20:$E$53,$F$20:$F$53,">="&C58,$F$20:$F$53,"<="&D58,$G$20:$G$53,$D$69) -> 0
C59: 45740 | D59: 45747 | E59: =SUMIFS($D$20:$D$53,$F$20:$F$53,">="&C59,$F$20:$F$53,"<="&D59,$G$20:$G$53,$D$69) -> 0 | F59: =SUMIFS($E$20:$E$53,$F$20:$F$53,">="&C59,$F$20:$F$53,"<="&D59,$G$20:$G$53,$D$69) -> 0
C60: TOTAL EGRESOS | E60: =SUM(E56:E59) -> 1254 | F60: =SUM(F56:F59) -> 340.76087
C64: Gastos y costos Periodo 01 al 23 de Marzo | E64: =SUM(E56:E58) -> 1254 | F64: =SUM(F56:F58) -> 340.76087
C65: Saldo | E65: =E63-E64 -> -1254 | F65: =F63-F64 -> -340.76087
D68: Cancelado | E68: =SUMIFS($D$20:$D$53,$F$20:$F$53,">="&C56,$F$20:$F$53,"<="&$D$59,$G$20:$G$53,$D$68) -> 84341.275 | F68: =SUMIFS($E$20:$E$53,$F$20:$F$53,">="&C56,$F$20:$F$53,"<="&D59,$G$20:$G$53,$D$68) -> 22887.971
D69: Sin Pagar | E69: =SUMIFS($D$20:$D$53,$F$20:$F$53,">="&C56,$F$20:$F$53,"<="&$D$59,$G$20:$G$53,$D$69) -> 1254 | F69: =SUMIFS($E$20:$E$53,$F$20:$F$53,">="&C56,$F$20:$F$53,"<="&D59,$G$20:$G$53,$D$69) -> 340.76087
D70: Total Egresos | E70: =SUM(E68:E69) -> 85595.275 | F70: =SUM(F68:F69) -> 23228.732
D71: Validación | E71: =(D48-E70)*0 -> 0 | F71: =F70-E48 -> 0
D74: Flujo Caja | E74: =D50 -> 32966.505
D75: Libro Bancos | E75: ='BCP SOLES BCP'!G128 -> 32966.501
D76: Diferencia Soles | E76: =E75-E74 -> -0.0037913044
D77: Diferencia USD | E77: =E76/$D$6 -> -0.0010302458

Sheet FLUJO CAJA ABRIL
D1: 42400
D4: Fecha de Elaboración: | E4: 45748
C6: Tasa de cambio: | D6: 3.68
D7: ABRIL
D8: VALOR S/ Sol | E8: VALOR USD
C9: BANCOS | D9: =SUBTOTAL(9,D10:D11) -> 54720.342 | E9: =SUBTOTAL(9,E10:E11) -> 14869.658
C10: Bancos S/ Soles | D10: ='BCP SOLES BCP'!$G$128 -> 32966.501 | E10: =D10/$D$6 -> 8958.2883
C11: Bancos USD | D11: =E11*$D$6 -> 21753.842 | E11: ='BCP USD BCP'!$G$82 -> 5911.37
C12: CLIENTES | D12: =SUBTOTAL(9,D13:D15) -> 72838.86 | E12: =SUBTOTAL(9,E13:E15) -> 19869.11
B13: Pagado | C13: Client: Remorfist-Factura Nro 15 | D13: 20189.153 | E13: =D13/3.63 -> 5561.75
B14: Pagado | C14: Client: Remorfist-Factura Nro 17 | D14: 100.0065 | E14: =D14/3.63 -> 27.55
B15: Pagado | C15: Client: Eurportage-Factura Nro 16-18 | D15: =$E$15*$D$6 -> 52549.701 | E15: 14279.81
C16: TOTAL INGRESOS | D16: =SUBTOTAL(9,D9:D15) -> 127559.2 | E16: =SUBTOTAL(9,E9:E15) -> 34738.768
B19: CUENTAS X PAGAR MES | D19: ABRIL | F19: Fecha de Elaboración: | J19: 45748
B20: Factura | C20: PROVEEDOR | D20: VALOR S/Sol | E20: VALOR USD | F20: Fecha vencimiento | G20: Estado | J20: KPI
C21: SEGURIDAD IGSS | D21: =SUBTOTAL(9,D22:D24) -> 7339.8 | E21: =SUBTOTAL(9,E22:E24) -> 1994.5109
C22: Planilla de declaración y pago de aportes previsional-Gonzálo de armas | D22: 1964.78 | E22: =D22/$D$6 -> 533.90761 | F22: 45755 | G22: Cancelado | H22: =IF(OR(G22="Sin pagar",G22="Pagar"),_xlfn.SINGLE(NETWORKDAYS($J$19,F22,FestivosPerú!$A$2:$A$15)),0) -> 0 | I22: =NETWORKDAYS($J$19,F22,FestivosPerú!$A$2:$A$15) -> 6 | J22: =H22 -> 0
C23: Planilla de declaración y pago de aportes previsional-Braydi Yusset Vera Neyra | D23: 2339.18 | E23: =D23/$D$6 -> 635.64674 | F23: 45755 | G23: Cancelado | H23: =IF(OR(G23="Sin pagar",G23="Pagar"),_xlfn.SINGLE(NETWORKDAYS($J$19,F23,FestivosPerú!$A$2:$A$15)),0) -> 0 | I23: =NETWORKDAYS($J$19,F23,FestivosPerú!$A$2:$A$15) -> 6 | J23: =H23 -> 0
C24: Planilla de declaración y pago de aportes previsional Hector Andrés Zevallos Váquez | D24: 3035.84 | E24: =D24/$D$6 -> 824.95652 | F24: 45755 | G24: Cancelado | H24: =IF(OR(G24="Sin pagar",G24="Pagar"),_xlfn.SINGLE(NETWORKDAYS($J$19,F24,FestivosPerú!$A$2:$A$15)),0) -> 0 | I24: =NETWORKDAYS($J$19,F24,FestivosPerú!$A$2:$A$15) -> 6 | J24: =H24 -> 0
C25: IMPUESTOS | D25: =SUBTOTAL(9,D26:D27) -> 14903 | E25: =SUBTOTAL(9,E26:E27) -> 4049.7283 | J25: =H25 -> 0
C26: PLAME Essalud y Renta de Quinta Categoría (Retención) | D26: 13330 | E26: =D26/$D$6 -> 3622.2826 | F26: 45761 | G26: Cancelado | H26: =IF(OR(G26="Sin pagar",G26="Pagar"),_xlfn.SINGLE(NETWORKDAYS($J$19,F26,FestivosPerú!$A$2:$A$15)),0) -> 0 | I26: =NETWORKDAYS($J$19,F26,FestivosPerú!$A$2:$A$15) -> 10 | J26: =H26 -> 0
C27: Pago de renta IGV | D27: 1573 | E27: =D27/$D$6 -> 427.44565 | F27: 45762 | G27: Cancelado | H27: =IF(OR(G27="Sin pagar",G27="Pagar"),_xlfn.SINGLE(NETWORKDAYS($J$19,F27,FestivosPerú!$A$2:$A$15)),0) -> 0 | I27: =NETWORKDAYS($J$19,F27,FestivosPerú!$A$2:$A$15) -> 11 | J27: =H27 -> 0 | M27: Estudio Fuentes
C28: SERVICIOS OUTSORCING CONTABLE | D28: =SUBTOTAL(9,D29:D29) -> 1281.008 | E28: =SUBTOTAL(9,E29:E29) -> 348.1 | J28: =H28 -> 0
B29: 5752 | C29: Estudio fuentes servicios Abril | D29: =$E$29*$D$6 -> 1281.008 | E29: 348.1 | F29: 45776 | G29: Cancelado | H29: =IF(OR(G29="Sin pagar",G29="Pagar"),_xlfn.SINGLE(NETWORKDAYS($J$19,F29,FestivosPerú!$A$2:$A$15)),0) -> 0 | I29: =NETWORKDAYS($J$19,F29,FestivosPerú!$A$2:$A$15) -> 20 | J29: =H29 -> 0
C30: PÓLIZAS DE VIDA Y SEGUROS MÉDICO | D30: =SUBTOTAL(9,D31:D34) -> 1832.17 | E30: =SUBTOTAL(9,E31:E34) -> 497.87228
B31: 159827721 | C31: Seguros de vida complementario ley, SCTS y SCTP Héctor Andréz Zevallos | D31: 227.08 | E31: =D31/$D$6 -> 61.706522 | F31: 45749 | G31: Cancelado | H31: =IF(OR(G31="Sin pagar",G31="Pagar"),_xlfn.SINGLE(NETWORKDAYS($J$19,F31,FestivosPerú!$A$2:$A$15)),0) -> 0 | I31: =NETWORKDAYS($J$19,F31,FestivosPerú!$A$2:$A$15) -> 2 | J31: =H31 -> 0
B32: 159827700 | C32: Seguros de vida complementario ley, SCTS y SCTP Braidy Yuseet vera Neyra | D32: 233.89 | E32: =D32/$D$6 -> 63.557065 | F32: 45749 | G32: Cancelado | H32: =IF(OR(G32="Sin pagar",G32="Pagar"),_xlfn.SINGLE(NETWORKDAYS($J$19,F32,FestivosPerú!$A$2:$A$15)),0) -> 0 | I32: =NETWORKDAYS($J$19,F32,FestivosPerú!$A$2:$A$15) -> 2 | J32: =H32 -> 0
B33: 159827866 | C33: Seguros de vida complementario ley, SCTS y SCTP Christian Portugal Segovia | D33: 118 | E33: =D33/$D$6 -> 32.065217 | F33: 45749 | G33: Cancelado | H33: =IF(OR(G33="Sin pagar",G33="Pagar"),_xlfn.SINGLE(NETWORKDAYS($J$19,F33,FestivosPerú!$A$2:$A$15)),0) -> 0 | I33: =NETWORKDAYS($J$19,F33,FestivosPerú!$A$2:$A$15) -> 2 | J33: =H33 -> 0
C34: Póliza de salud Braidy Vera- Couta 6 meses fraccionada | D34: 1253.2 | E34: =D34/D6 -> 340.54348 | F34: 45776 | G34: Cancelado | H34: =IF(OR(G34="Sin pagar",G34="Pagar"),_xlfn.SINGLE(NETWORKDAYS($J$19,F34,FestivosPerú!$A$2:$A$15)),0) -> 0 | I34: =NETWORKDAYS($J$19,F34,FestivosPerú!$A$2:$A$15) -> 20 | J34: =H34 -> 0
C35: COSTOS FINANCIEROS | D35: =SUBTOTAL(9,D36:D36) -> 478.0212 | E35: =SUBTOTAL(9,E36:E36) -> 129.89707
C36: COSTOS FINANCIEROS | D36: 478.0212 | E36: =$D$36/$D$6 -> 129.89707 | F36: 45777 | G36: Cancelado | H36: =IF(OR(G36="Sin pagar",G36="Pagar"),_xlfn.SINGLE(NETWORKDAYS($J$19,F36,FestivosPerú!$A$2:$A$15)),0) -> 0 | I36: =NETWORKDAYS($J$19,F36,FestivosPerú!$A$2:$A$15) -> 21 | J36: =H36 -> 0
C37: NÓMINAS | D37: =SUBTOTAL(9,D38:D41) -> 56729.82 | E37: =SUBTOTAL(9,E38:E41) -> 15415.712
C38: Gonzalo Gabriel Armas-Remofisrt ( Liquidación) | D38: 24477.58 | E38: =D38/$D$6 -> 6651.5163 | F38: 45769 | G38: Cancelado | H38: =IF(OR(G38="Sin pagar",G38="Pagar"),_xlfn.SINGLE(NETWORKDAYS($J$19,F38,FestivosPerú!$A$2:$A$15)),0) -> 0 | I38: =NETWORKDAYS($J$19,F38,FestivosPerú!$A$2:$A$15) -> 15 | J38: =H38 -> 0
C39: Héctor Andrés Zevallos Vasquez-Remotefirst ( Liquidación) | D39: 8135.5 | E39: =D39/$D$6 -> 2210.7337 | F39: 45770 | G39: Cancelado | H39: =IF(OR(G39="Sin pagar",G39="Pagar"),_xlfn.SINGLE(NETWORKDAYS($J$19,F39,FestivosPerú!$A$2:$A$15)),0) -> 0 | I39: =NETWORKDAYS($J$19,F39,FestivosPerú!$A$2:$A$15) -> 16 | J39: =H39 -> 0
C40: Braydi Yusset Vera Neira-Europortage | D40: 13725.33 | E40: =D40/$D$6 -> 3729.7092 | F40: 45775 | G40: Cancelado | H40: =IF(OR(G40="Sin pagar",G40="Pagar"),_xlfn.SINGLE(NETWORKDAYS($J$19,F40,FestivosPerú!$A$2:$A$15)),0) -> 0 | I40: =NETWORKDAYS($J$19,F40,FestivosPerú!$A$2:$A$15) -> 19 | J40: =H40 -> 0
C41: Cristhian Portugal Segovia -Europortage | D41: 10391.41 | E41: =D41/$D$6 -> 2823.7527 | F41: 45776 | G41: Cancelado | H41: =IF(OR(G41="Sin pagar",G41="Pagar"),_xlfn.SINGLE(NETWORKDAYS($J$19,F41,FestivosPerú!$A$2:$A$15)),0) -> 0 | I41: =NETWORKDAYS($J$19,F41,FestivosPerú!$A$2:$A$15) -> 20 | J41: =H41 -> 0
C42: REEMBOLSO | D42: =SUBTOTAL(9,D43:D44) -> 4341.36 | E42: =SUBTOTAL(9,E43:E44) -> 1179.7174
C43: Reembolso Braydi Yusset Vera Neira-Europortage | D43: 3642.99 | E43: =D43/$D$6 -> 989.94293 | F43: 45775 | G43: Cancelado | H43: =IF(OR(G43="Sin pagar",G43="Pagar"),_xlfn.SINGLE(NETWORKDAYS($J$19,F43,FestivosPerú!$A$2:$A$15)),0) -> 0 | I43: =NETWORKDAYS($J$19,F43,FestivosPerú!$A$2:$A$15) -> 19 | J43: =H43 -> 0
C44: Reembolso Cristhian Portugal Segovia -Europortage | D44: 698.37 | E44: =D44/$D$6 -> 189.77446 | F44: 45776 | G44: Cancelado | H44: =IF(OR(G44="Sin pagar",G44="Pagar"),_xlfn.SINGLE(NETWORKDAYS($J$19,F44,FestivosPerú!$A$2:$A$15)),0) -> 0 | I44: =NETWORKDAYS($J$19,F44,FestivosPerú!$A$2:$A$15) -> 20 | J44: =H44 -> 0
C45: IMPREVISTO | D45: =SUBTOTAL(9,D46:D46) -> 301.97 | E45: =SUBTOTAL(9,E46:E46) -> 82.057065
C46: Examen médico Davis Cesar oporto Figueroa | D46: 301.97 | E46: =D46/$D$6 -> 82.057065 | F46: 45761 | G46: Cancelado | H46: =IF(OR(G46="Sin pagar",G46="Pagar"),_xlfn.SINGLE(NETWORKDAYS($J$19,F46,FestivosPerú!$A$2:$A$15)),0) -> 0 | I46: =NETWORKDAYS($J$19,F46,FestivosPerú!$A$2:$A$15) -> 10 | J46: =H46 -> 0
C47: TOTAL EGRESOS | D47: =SUBTOTAL(9,D21:D46) -> 87207.149 | E47: =SUBTOTAL(9,E21:E46) -> 23697.595
C49: SALDO | D49: =D16-D47 -> 40352.053 | E49: =E16-E47 -> 11041.173
C50: % | D50: =IF($D$16=0,0,D49/$D$16) -> 0.31633981 | E50: =IF($E$16=0,0,E49/$E$16) -> 0.31783434
C55: Fecha Inicial | D55: Fecha Final | E55: Valor VALOR ₡ CRC | F55: Valor VALOR USD
C56: 45748 | D56: 45753 | E56: =SUMIFS($D$20:$D$53,$F$20:$F$53,">="&C56,$F$20:$F$53,"<="&D56,$G$20:$G$53,$D$70) -> 0 | F56: =SUMIFS($E$20:$E$53,$F$20:$F$53,">="&C56,$F$20:$F$53,"<="&D56,$G$20:$G$53,$D$70) -> 0
C57: 45761 | D57: 45767 | E57: =SUMIFS($D$20:$D$53,$F$20:$F$53,">="&C57,$F$20:$F$53,"<="&D57,$G$20:$G$53,$D$70) -> 0 | F57: =SUMIFS($E$20:$E$53,$F$20:$F$53,">="&C57,$F$20:$F$53,"<="&D57,$G$20:$G$53,$D$70) -> 0 | G57: Pago renta IGV e imprevisto
C58: 45768 | D58: 45774 | E58: =SUMIFS($D$20:$D$53,$F$20:$F$53,">="&C58,$F$20:$F$53,"<="&D58,$G$20:$G$53,$D$70) -> 0 | F58: =SUMIFS($E$20:$E$53,$F$20:$F$53,">="&C58,$F$20:$F$53,"<="&D58,$G$20:$G$53,$D$70) -> 0 | G58: Imprevisto
C59: 45775 | D59: 45777 | E59: =SUMIFS($D$20:$D$53,$F$20:$F$53,">="&C59,$F$20:$F$53,"<="&D59,$G$20:$G$53,$D$70) -> 0 | F59: =SUMIFS($E$20:$E$53,$F$20:$F$53,">="&C59,$F$20:$F$53,"<="&D59,$G$20:$G$53,$D$70) -> 0 | G59: Nóminas , reembolso, servicio Estudio fuente
C60: TOTAL EGRESOS | E60: =SUM(E56:E59) -> 0 | F60: =SUM(F56:F59) -> 0
C65: Bancos | E65: ='BCP SOLES BCP'!$G$207+('BCP USD BCP'!$G$213*'FLUJO CAJA ABRIL'!$D$6) -> 175939.74 | F65: ='BCP USD BCP'!$G$104+('BCP SOLES BCP'!$G$160/'FLUJO CAJA ABRIL'!$D$6) -> 13013.864
C66: Gastos y costos Periodo 28 al 30 de abril | E66: =SUM(E59) -> 0 | F66: =SUM(F59) -> 0
C67: Saldo | E67: =E65-E66 -> 175939.74 | F67: =F65-F66 -> 13013.864
D69: Cancelado | E69: =SUMIFS($D$20:$D$52,$F$20:$F$52,">="&C56,$F$20:$F$52,"<="&$D$59,$G$20:$G$52,$D$69) -> 87207.149 | F69: =SUMIFS($E$20:$E$52,$F$20:$F$52,">="&C56,$F$20:$F$52,"<="&D59,$G$20:$G$52,$D$69) -> 23697.595
D70: Sin Pagar | E70: =SUMIFS($D$20:$D$52,$F$20:$F$52,">="&C56,$F$20:$F$52,"<="&$D$59,$G$20:$G$52,$D$70) -> 0 | F70: =SUMIFS($E$20:$E$52,$F$20:$F$52,">="&C56,$F$20:$F$52,"<="&D59,$G$20:$G$52,$D$70) -> 0
D72: Total Egresos | E72: =SUM(E69:E71) -> 87207.149 | F72: =SUM(F69:F71) -> 23697.595
D73: Validación | E73: =(D47-E72) -> 0 | F73: =F72-E47 -> 0
D78: Flujo Caja | E78: =D49 -> 40352.053
D79: Libro Bancos | E79: ='BCP SOLES BCP'!$G$168+('BCP USD BCP'!G99*$D$6) -> 40352.058
D80: Diferencia Soles | E80: =E79-E78 -> 0.0043996667
D81: Diferencia USD | E81: =E80/$D$6 -> 0.0011955616

Sheet FLUJO CAJA MAYO
D1: 42400
D4: Fecha de Elaboración: | E4: 45778
C6: Tasa de cambio: | D6: 3.66
D7: MAYO
D8: VALOR S/ Sol | E8: VALOR USD
C9: BANCOS | D9: =SUBTOTAL(9,D10:D11) -> 40299.372 | E9: =SUBTOTAL(9,E10:E11) -> 11010.757
C10: Bancos S/ Soles | D10: ='BCP SOLES BCP'!$G$168 -> 30657.981 | E10: =D10/$D$6 -> 8376.4975
C11: Bancos USD | D11: =E11*$D$6 -> 9641.3916 | E11: ='BCP USD BCP'!$G$99 -> 2634.26
C12: CLIENTES | D12: =SUBTOTAL(9,D13:D13) -> #REF! | E12: =SUBTOTAL(9,E13:E13) -> #REF!
B13: Pagado | C13: Client: Eurportage-Factura Nro 19 | D13: =$E$13*'Diferencia Cambio S&P'!#REF! -> #REF! | E13: ='Diferencia Cambio S&P'!#REF! -> #REF!
C14: TOTAL INGRESOS | D14: =SUBTOTAL(9,D9:D13) -> #REF! | E14: =SUBTOTAL(9,E9:E13) -> #REF!
B17: CUENTAS X PAGAR MES | D17: ABRIL | F17: Fecha de Elaboración: | J17: 45778
B18: Factura | C18: PROVEEDOR | D18: VALOR S/Sol | E18: VALOR USD | F18: Fecha vencimiento | G18: Estado | J18: KPI
C19: SEGURIDAD IGSS | D19: =SUBTOTAL(9,D20:D22) -> 5518.22 | E19: =SUBTOTAL(9,E20:E22) -> 1507.7104
C20: Planilla de declaración y pago de aportes previsional-Gonzálo de armas | D20: 1199.54 | E20: =D20/$D$6 -> 327.74317 | F20: 45785 | G20: Cancelado | H20: =IF(OR(G20="Sin pagar",G20="Pagar"),_xlfn.SINGLE(NETWORKDAYS($J$17,F20,FestivosPerú!$A$2:$A$15)),0) -> 0 | I20: =NETWORKDAYS($J$17,F20,FestivosPerú!$A$2:$A$15) -> 5 | J20: =H20 -> 0
C21: Planilla de declaración y pago de aportes previsional-Braydi Yusset Vera Neyra | D21: 2161.35 | E21: =D21/$D$6 -> 590.53279 | F21: 45785 | G21: Cancelado | H21: =IF(OR(G21="Sin pagar",G21="Pagar"),_xlfn.SINGLE(NETWORKDAYS($J$17,F21,FestivosPerú!$A$2:$A$15)),0) -> 0 | I21: =NETWORKDAYS($J$17,F21,FestivosPerú!$A$2:$A$15) -> 5 | J21: =H21 -> 0
C22: Planilla de declaración y pago de aportes previsional Hector Andrés Zevallos Váquez | D22: 2157.33 | E22: =D22/$D$6 -> 589.43443 | F22: 45785 | G22: Cancelado | H22: =IF(OR(G22="Sin pagar",G22="Pagar"),_xlfn.SINGLE(NETWORKDAYS($J$17,F22,FestivosPerú!$A$2:$A$15)),0) -> 0 | I22: =NETWORKDAYS($J$17,F22,FestivosPerú!$A$2:$A$15) -> 5 | J22: =H22 -> 0
C23: IMPUESTOS | D23: =SUBTOTAL(9,D24:D25) -> 13769 | E23: =SUBTOTAL(9,E24:E25) -> 3762.0219 | J23: =H23 -> 0
C24: PLAME Essalud y Renta de Quinta Categoría (Retención) | D24: 12653 | E24: =D24/$D$6 -> 3457.1038 | F24: 45790 | G24: Cancelado | H24: =IF(OR(G24="Sin pagar",G24="Pagar"),_xlfn.SINGLE(NETWORKDAYS($J$17,F24,FestivosPerú!$A$2:$A$15)),0) -> 0 | I24: =NETWORKDAYS($J$17,F24,FestivosPerú!$A$2:$A$15) -> 8 | J24: =H24 -> 0
C25: Pago de renta IGV Abril | D25: 1116 | E25: =D25/$D$6 -> 304.91803 | F25: 45793 | G25: Cancelado | H25: =IF(OR(G25="Sin pagar",G25="Pagar"),_xlfn.SINGLE(NETWORKDAYS($J$17,F25,FestivosPerú!$A$2:$A$15)),0) -> 0 | I25: =NETWORKDAYS($J$17,F25,FestivosPerú!$A$2:$A$15) -> 11 | J25: =H25 -> 0 | M25: Outsorcing contable
C26: SERVICIOS OUTSORCING CONTABLE | D26: =SUBTOTAL(9,D27:D31) -> 3617.054 | E26: =SUBTOTAL(9,E27:E31) -> 988.26612 | J26: =H26 -> 0
B27: 5984 | C27: Estudio fuentes servicios mayo | D27: =E27*$D$6 -> 1317.234 | E27: 359.9 | F27: 45806 | G27: Cancelado | H27: =IF(OR(G27="Sin pagar",G27="Pagar"),_xlfn.SINGLE(NETWORKDAYS($J$17,F27,FestivosPerú!$A$2:$A$15)),0) -> 0 | I27: =NETWORKDAYS($J$17,F27,FestivosPerú!$A$2:$A$15) -> 20 | J27: =H27 -> 0
B28: 6035 | C28: Estudio fuentes servicios mayo | D28: =E28*$D$6 -> 647.82 | E28: 177 | F28: 45806 | G28: Cancelado | H28: =IF(OR(G28="Sin pagar",G28="Pagar"),_xlfn.SINGLE(NETWORKDAYS($J$17,F28,FestivosPerú!$A$2:$A$15)),0) -> 0 | I28: =NETWORKDAYS($J$17,F28,FestivosPerú!$A$2:$A$15) -> 20 | J28: =H28 -> 0
B29: 5984 | C29: Estudio fuentes servicio cambio gerente general | D29: =(E29*$D$6)*0 -> 0 | E29: =472*0 -> 0 | F29: 45814 | G29: Sin Pagar | H29: =IF(OR(G29="Sin pagar",G29="Pagar"),_xlfn.SINGLE(NETWORKDAYS($J$17,F29,FestivosPerú!$A$2:$A$15)),0) -> 26 | I29: =NETWORKDAYS($J$17,F29,FestivosPerú!$A$2:$A$15) -> 26 | J29: =H29 -> 26
B30: E001-584 | C30: Outsourcing contable servicio abril Avanza | D30: =700*1.18 -> 826 | E30: =$D$30/$D$6 -> 225.68306 | F30: 45806 | G30: Cancelado | H30: =IF(OR(G30="Sin pagar",G30="Pagar"),_xlfn.SINGLE(NETWORKDAYS($J$17,F30,FestivosPerú!$A$2:$A$15)),0) -> 0 | I30: =NETWORKDAYS($J$17,F30,FestivosPerú!$A$2:$A$15) -> 20 | J30: =H30 -> 0
B31: E001-602 | C31: Outsourcing contable servicio abril Avanza | D31: =700*1.18 -> 826 | E31: =$D$30/$D$6 -> 225.68306 | F31: 45811 | G31: Cancelado | H31: =IF(OR(G31="Sin pagar",G31="Pagar"),_xlfn.SINGLE(NETWORKDAYS($J$17,F31,FestivosPerú!$A$2:$A$15)),0) -> 0 | I31: =NETWORKDAYS($J$17,F31,FestivosPerú!$A$2:$A$15) -> 23 | J31: =H31 -> 0
C32: PÓLIZAS DE VIDA Y SEGUROS MÉDICO | D32: =SUBTOTAL(9,D33:D41) -> 3244.52 | E32: =SUBTOTAL(9,E33:E41) -> 886.48087
B33: F052-01723822 | C33: Seguros de vida recibo 160793407 | D33: 118 | E33: =D33/$D$6 -> 32.240437 | F33: 45786 | G33: Cancelado | H33: =IF(OR(G33="Sin pagar",G33="Pagar"),_xlfn.SINGLE(NETWORKDAYS($J$17,F33,FestivosPerú!$A$2:$A$15)),0) -> 0 | I33: =NETWORKDAYS($J$17,F33,FestivosPerú!$A$2:$A$15) -> 6 | J33: =H33 -> 0
B34: F052-01723823 | C34: SCTR Pensiones recibo 160793127 | D34: 354.04 | E34: =D34/$D$6 -> 96.73224 | F34: 45786 | G34: Cancelado | H34: =IF(OR(G34="Sin pagar",G34="Pagar"),_xlfn.SINGLE(NETWORKDAYS($J$17,F34,FestivosPerú!$A$2:$A$15)),0) -> 0 | I34: =NETWORKDAYS($J$17,F34,FestivosPerú!$A$2:$A$15) -> 6 | J34: =H34 -> 0
B35: F052-01534951 | C35: SCTR Salud recibo 160793128 | D35: 343.73 | E35: =D35/$D$6 -> 93.915301 | F35: 45786 | G35: Cancelado | H35: =IF(OR(G35="Sin pagar",G35="Pagar"),_xlfn.SINGLE(NETWORKDAYS($J$17,F35,FestivosPerú!$A$2:$A$15)),0) -> 0 | I35: =NETWORKDAYS($J$17,F35,FestivosPerú!$A$2:$A$15) -> 6 | J35: =H35 -> 0
C36: Póliza de salud Davis Oporto-Primera cuota | D36: 1613 | E36: =D36/D6 -> 440.71038 | F36: 45806 | G36: Cancelado | H36: =IF(OR(G36="Sin pagar",G36="Pagar"),_xlfn.SINGLE(NETWORKDAYS($J$17,F36,FestivosPerú!$A$2:$A$15)),0) -> 0 | I36: =NETWORKDAYS($J$17,F36,FestivosPerú!$A$2:$A$15) -> 20 | J36: =H36 -> 0
C37: Póliza de salud Braidy Vera- Cuota 6 meses fraccionada | D37: =1253.2*0 -> 0 | E37: =$D$37/$D$6 -> 0 | F37: 45808 | G37: Cancelado | H37: =IF(OR(G37="Sin pagar",G37="Pagar"),_xlfn.SINGLE(NETWORKDAYS($J$17,F37,FestivosPerú!$A$2:$A$15)),0) -> 0 | I37: =NETWORKDAYS($J$17,F37,FestivosPerú!$A$2:$A$15) -> 21 | J37: =H37 -> 0
B38: S/N | C38: Seguros de vida Ley recibo 161448077 | D38: =118 -> 118 | E38: =D38/$D$6 -> 32.240437 | F38: 45811 | G38: Cancelado | H38: =IF(OR(G38="Sin pagar",G38="Pagar"),_xlfn.SINGLE(NETWORKDAYS($J$17,F38,FestivosPerú!$A$2:$A$15)),0) -> 0 | I38: =NETWORKDAYS($J$17,F38,FestivosPerú!$A$2:$A$15) -> 23 | J38: =H38 -> 0
B39: S/N | C39: SCTR Pensiones recibo 161447562 | D39: =354.03 -> 354.03 | E39: =D39/$D$6 -> 96.729508 | F39: 45811 | G39: Cancelado | H39: =IF(OR(G39="Sin pagar",G39="Pagar"),_xlfn.SINGLE(NETWORKDAYS($J$17,F39,FestivosPerú!$A$2:$A$15)),0) -> 0 | I39: =NETWORKDAYS($J$17,F39,FestivosPerú!$A$2:$A$15) -> 23 | J39: =H39 -> 0
B40: S/N | C40: SCTR Salud recibo 161447573 | D40: =343.72 -> 343.72 | E40: =D40/$D$6 -> 93.912568 | F40: 45811 | G40: Cancelado | H40: =IF(OR(G40="Sin pagar",G40="Pagar"),_xlfn.SINGLE(NETWORKDAYS($J$17,F40,FestivosPerú!$A$2:$A$15)),0) -> 0 | I40: =NETWORKDAYS($J$17,F40,FestivosPerú!$A$2:$A$15) -> 23 | J40: =H40 -> 0
B41: S/N | C41: Póliza de salud Braidy Vera-Mes de abril y mayo | D41: =2508*0 -> 0 | E41: =$D$41/$D$6 -> 0 | F41: 45811 | G41: Sin Pagar | H41: =IF(OR(G41="Sin pagar",G41="Pagar"),_xlfn.SINGLE(NETWORKDAYS($J$17,F41,FestivosPerú!$A$2:$A$15)),0) -> 23 | I41: =NETWORKDAYS($J$17,F41,FestivosPerú!$A$2:$A$15) -> 23 | J41: =H41 -> 23
C42: COSTOS FINANCIEROS | D42: =SUBTOTAL(9,D43:D43) -> 3740.87 | E42: =SUBTOTAL(9,E43:E43) -> 1022.0956
C43: COSTOS FINANCIEROS | D43: =('BCP SOLES BCP'!$F$173+'BCP SOLES BCP'!$F$179+'BCP SOLES BCP'!$F$181+'BCP SOLES BCP'!$F$185+'BCP SOLES BCP'!$F$188+'BCP SOLES BCP'!$F$190+'BCP SOLES BCP'!$F$192+'BCP SOLES BCP'!$F$194+'BCP SOLES BCP'!$F$199+'BCP SOLES BCP'!$F$200+'BCP SOLES BCP'!$F$201)+(('BCP USD BCP'!F99+'BCP USD BCP'!F101+'BCP USD BCP'!F102+'BCP USD BCP'!F106+'BCP USD BCP'!F107*$D$6))+3517.81 -> 3740.87 | E43: =$D$43/$D$6 -> 1022.0956 | F43: 45808 | G43: Cancelado | H43: =IF(OR(G43="Sin pagar",G43="Pagar"),_xlfn.SINGLE(NETWORKDAYS($J$17,F43,FestivosPerú!$A$2:$A$15)),0) -> 0 | I43: =NETWORKDAYS($J$17,F43,FestivosPerú!$A$2:$A$15) -> 21 | J43: =H43 -> 0
C44: NÓMINAS | D44: =SUBTOTAL(9,D45:D47) -> 35146.754 | E44: =SUBTOTAL(9,E45:E47) -> 9602.9382
C45: Braydi Yusset Vera Neira-Europortage | D45: 13447.124 | E45: =D45/$D$6 -> 3674.0775 | F45: 45805 | G45: Cancelado | H45: =IF(OR(G45="Sin pagar",G45="Pagar"),_xlfn.SINGLE(NETWORKDAYS($J$17,F45,FestivosPerú!$A$2:$A$15)),0) -> 0 | I45: =NETWORKDAYS($J$17,F45,FestivosPerú!$A$2:$A$15) -> 19 | J45: =H45 -> 0
C46: Cristhian Portugal Segovia -Europortage | D46: 10842.7 | E46: =D46/$D$6 -> 2962.4863 | F46: 45805 | G46: Cancelado | H46: =IF(OR(G46="Sin pagar",G46="Pagar"),_xlfn.SINGLE(NETWORKDAYS($J$17,F46,FestivosPerú!$A$2:$A$15)),0) -> 0 | I46: =NETWORKDAYS($J$17,F46,FestivosPerú!$A$2:$A$15) -> 19 | J46: =H46 -> 0
C47: Davis Cesar oporto figueroa -Europortage | D47: 10856.93 | E47: =D47/$D$6 -> 2966.3743 | F47: 45805 | G47: Cancelado | H47: =IF(OR(G47="Sin pagar",G47="Pagar"),_xlfn.SINGLE(NETWORKDAYS($J$17,F47,FestivosPerú!$A$2:$A$15)),0) -> 0 | I47: =NETWORKDAYS($J$17,F47,FestivosPerú!$A$2:$A$15) -> 19 | J47: =H47 -> 0
C48: REEMBOLSO | D48: =SUBTOTAL(9,D49:D50) -> 11893.83 | E48: =SUBTOTAL(9,E49:E50) -> 3249.6803
C49: Reembolso Braydi Yusset Vera Neira-Europortage | D49: 1400.27 | E49: =D49/$D$6 -> 382.58743 | F49: 45805 | G49: Cancelado | H49: =IF(OR(G49="Sin pagar",G49="Pagar"),_xlfn.SINGLE(NETWORKDAYS($J$17,F49,FestivosPerú!$A$2:$A$15)),0) -> 0 | I49: =NETWORKDAYS($J$17,F49,FestivosPerú!$A$2:$A$15) -> 19 | J49: =H49 -> 0
C50: Reembolso Cristhian Portugal Segovia -Europortage | D50: 10493.56 | E50: =D50/$D$6 -> 2867.0929 | F50: 45806 | G50: Cancelado | H50: =IF(OR(G50="Sin pagar",G50="Pagar"),_xlfn.SINGLE(NETWORKDAYS($J$17,F50,FestivosPerú!$A$2:$A$15)),0) -> 0 | I50: =NETWORKDAYS($J$17,F50,FestivosPerú!$A$2:$A$15) -> 20 | J50: =H50 -> 0
C51: IMPREVISTO | D51: =SUBTOTAL(9,D52:D55) -> 4877 | E51: =SUBTOTAL(9,E52:E55) -> 1332.5137
C52: Deposito CTS -Braydi Yusset Vera Neira | D52: 4700 | E52: =D52/$D$6 -> 1284.153 | F52: 45793 | G52: Cancelado | H52: =IF(OR(G52="Sin pagar",G52="Pagar"),_xlfn.SINGLE(NETWORKDAYS($J$17,F52,FestivosPerú!$A$2:$A$15)),0) -> 0 | I52: =NETWORKDAYS($J$17,F52,FestivosPerú!$A$2:$A$15) -> 11 | J52: =H52 -> 0
B53: E001-585 | C53: Tramites pago CTS Braydi Yusset Vera Neira | D53: 177 | E53: =D53/$D$6 -> 48.360656 | F53: 45796 | G53: Cancelado | H53: =IF(OR(G53="Sin pagar",G53="Pagar"),_xlfn.SINGLE(NETWORKDAYS($J$17,F53,FestivosPerú!$A$2:$A$15)),0) -> 0 | I53: =NETWORKDAYS($J$17,F53,FestivosPerú!$A$2:$A$15) -> 12 | J53: =H53 -> 0
C54: Deposito CTS -Christian Portugal Segovia | D54: =2000*0 -> 0 | E54: =D54/$D$6 -> 0 | F54: 45814 | G54: Sin Pagar | H54: =IF(OR(G54="Sin pagar",G54="Pagar"),_xlfn.SINGLE(NETWORKDAYS($J$17,F54,FestivosPerú!$A$2:$A$15)),0) -> 26 | I54: =NETWORKDAYS($J$17,F54,FestivosPerú!$A$2:$A$15) -> 26 | J54: =H54 -> 26
B55: S/N | C55: Tramites Christian Portugal Segovia | D55: =(125*1.19)*0 -> 0 | E55: =D55/$D$6 -> 0 | F55: 45814 | G55: Sin Pagar | H55: =IF(OR(G55="Sin pagar",G55="Pagar"),_xlfn.SINGLE(NETWORKDAYS($J$17,F55,FestivosPerú!$A$2:$A$15)),0) -> 26 | I55: =NETWORKDAYS($J$17,F55,FestivosPerú!$A$2:$A$15) -> 26 | J55: =H55 -> 26
C56: TOTAL EGRESOS | D56: =SUBTOTAL(9,D19:D55) -> 81807.248 | E56: =SUBTOTAL(9,E19:E55) -> 22351.707
C57: SALDO | D57: =D14-D56 -> #REF! | E57: =E14-E56 -> #REF!
C58: % | D58: =IF($D$14=0,0,D56/$D$14) -> #REF! | E58: =IF($E$14=0,0,E56/$E$14) -> #REF!
C63: 45778 | D63: 45781 | E63: =SUMIFS($D$18:$D$60,$F$18:$F$60,">="&C63,$F$18:$F$60,"<="&D63,$G$18:$G$60,$D$80) -> 0 | F63: =SUMIFS($E$18:$E$60,$F$18:$F$60,">="&C63,$F$18:$F$60,"<="&D63,$G$18:$G$60,$D$80) -> 0
C64: 45782 | D64: 45788 | E64: =SUMIFS($D$18:$D$60,$F$18:$F$60,">="&C64,$F$18:$F$60,"<="&D64,$G$18:$G$60,$D$80) -> 0 | F64: =SUMIFS($E$18:$E$60,$F$18:$F$60,">="&C64,$F$18:$F$60,"<="&D64,$G$18:$G$60,$D$80) -> 0 | G64: Pago renta IGV e imprevisto
C65: 45789 | D65: 45795 | E65: =SUMIFS($D$18:$D$60,$F$18:$F$60,">="&C65,$F$18:$F$60,"<="&D65,$G$18:$G$60,$D$80) -> 0 | F65: =SUMIFS($E$18:$E$60,$F$18:$F$60,">="&C65,$F$18:$F$60,"<="&D65,$G$18:$G$60,$D$80) -> 0 | G65: Pago CTC -Pago Renta IGV
C66: 45796 | D66: 45802 | E66: =SUMIFS($D$18:$D$60,$F$18:$F$60,">="&C66,$F$18:$F$60,"<="&D66,$G$18:$G$60,$D$80) -> 0 | F66: =SUMIFS($E$18:$E$60,$F$18:$F$60,">="&C66,$F$18:$F$60,"<="&D66,$G$18:$G$60,$D$80) -> 0 | G66: Nóminas , reembolso, servicio Estudio fuente
C67: 45803 | D67: 45808 | E67: =SUMIFS($D$18:$D$60,$F$18:$F$60,">="&C67,$F$18:$F$60,"<="&D67,$G$18:$G$60,$D$80) -> 0 | F67: =SUMIFS($E$18:$E$60,$F$18:$F$60,">="&C67,$F$18:$F$60,"<="&D67,$G$18:$G$60,$D$80) -> 0
C68: 45809 | D68: 45814 | E68: =SUMIFS($D$18:$D$60,$F$18:$F$60,">="&C68,$F$18:$F$60,"<="&D68,$G$18:$G$60,$D$80) -> 0 | F68: =SUMIFS($E$18:$E$60,$F$18:$F$60,">="&C68,$F$18:$F$60,"<="&D68,$G$18:$G$60,$D$80) -> 0
C69: TOTAL EGRESOS | E69: =SUM(E63:E68) -> 0 | F69: =SUM(F63:F68) -> 0
C74: Bancos | E74: ='BCP SOLES BCP'!$G$300+('BCP USD BCP'!$G$299*$D$6) -> 67029.554 | F74: ='BCP USD BCP'!$G$299+('BCP SOLES BCP'!$G$300/$D$6) -> 18314.086
C75: Gastos y costos Periodo 01 al 25 Mayo | E75: =SUM(E63:E66) -> 0 | F75: =SUM(F63:F66) -> 0
C76: Saldo | E76: =E74-E75 -> 67029.554 | F76: =F74-F75 -> 18314.086
D79: Cancelado | E79: =SUMIFS($D$20:$D$60,$F$20:$F$60,">="&C63,$F$20:$F$60,"<="&$D$68,$G$20:$G$60,$D$79) -> 81807.248 | F79: =SUMIFS($E$20:$E$60,$F$20:$F$60,">="&C63,$F$20:$F$60,"<="&D68,$G$20:$G$60,$D$79) -> 22351.707
D80: Sin Pagar | E80: =SUMIFS($D$18:$D$59,$F$18:$F$59,">="&C63,$F$18:$F$59,"<="&$D$67,$G$18:$G$59,$D$80) -> 0 | F80: =SUMIFS($E$18:$E$59,$F$18:$F$59,">="&C63,$F$18:$F$59,"<="&D67,$G$18:$G$59,$D$80) -> 0
D81: Total Egresos | E81: =SUM(E79:E80) -> 81807.248 | F81: =SUM(F79:F80) -> 22351.707
D83: Validación | E83: =(D56-E81) -> 0 | F83: =F81-E56 -> 0
D86: Flujo Caja | E86: =D57 -> #REF!
D87: Libro Bancos | E87: ='BCP SOLES BCP'!$G$207+('BCP USD BCP'!$G$108*'FLUJO CAJA MAYO'!$D$6) -> 39768.583
D88: Diferencia Soles | E88: =E87-E86 -> #REF!
D89: Diferencia USD | E89: =E88/$D$6 -> #REF!

Sheet FLUJO CAJA JUNIO
D1: 42400
D4: Fecha de Elaboración: | E4: 45809
C6: Tasa de cambio: | D6: 3.62
D7: JUNIO
D8: VALOR S/ Sol | E8: VALOR USD
C9: BANCOS | D9: =SUBTOTAL(9,D10:D11) -> 37709.259 | E9: =SUBTOTAL(9,E10:E11) -> 10416.922
C10: Bancos S/ Soles | D10: ='BCP SOLES BCP'!$G$207-3014.44+508.02+505.02 -> 32467.137 | E10: =D10/$D$6 -> 8968.8224
C11: Bancos USD | D11: =E11*$D$6 -> 5242.122 | E11: ='BCP USD BCP'!$G$108 -> 1448.1
C12: CLIENTES | D12: =SUBTOTAL(9,D13:D13) -> 99548.157 | E12: =SUBTOTAL(9,E13:E13) -> 28304.85
B13: Pagado | C13: Client: Europortage-Factura Nro EB01-20 | D13: =$E$13*'Diferencia Cambio S&P'!$K$22 -> 99548.157 | E13: ='Diferencia Cambio S&P'!$J$22 -> 28304.85
C14: TOTAL INGRESOS | D14: =SUBTOTAL(9,D9:D13) -> 137257.42 | E14: =SUBTOTAL(9,E9:E13) -> 38721.772
B17: CUENTAS X PAGAR MES | D17: ABRIL | F17: Fecha de Elaboración: | J17: 45809
B18: Factura | C18: PROVEEDOR | D18: VALOR S/Sol | E18: VALOR USD | F18: Fecha vencimiento | G18: Estado | J18: KPI
C19: SEGURIDAD IGSS | D19: =SUBTOTAL(9,D20:D21) -> 5688.08 | E19: =SUBTOTAL(9,E20:E21) -> 1571.2928
C20: Planilla de declaración y pago de aportes previsional-Braydi Yusset Vera Neyra y Davis Cesar Oporto Figueroa | D20: =3274.57+623.23 -> 3897.8 | E20: =D20/$D$6 -> 1076.7403 | F20: 45817 | G20: Cancelado | H20: =IF(OR(G20="Sin pagar",G20="Pagar"),_xlfn.SINGLE(NETWORKDAYS($J$17,F20,FestivosPerú!$A$2:$A$15)),0) -> 0 | I20: =NETWORKDAYS($J$17,F20,FestivosPerú!$A$2:$A$15) -> 6 | J20: =H20 -> 0
C21: Planilla de declaración y pago de aportes previsional Christian Portugal Segovia | D21: 1790.28 | E21: =D21/$D$6 -> 494.55249 | F21: 45817 | G21: Cancelado | H21: =IF(OR(G21="Sin pagar",G21="Pagar"),_xlfn.SINGLE(NETWORKDAYS($J$17,F21,FestivosPerú!$A$2:$A$15)),0) -> 0 | I21: =NETWORKDAYS($J$17,F21,FestivosPerú!$A$2:$A$15) -> 6 | J21: =H21 -> 0
C22: IMPUESTOS | D22: =SUBTOTAL(9,D23:D24) -> 11084 | E22: =SUBTOTAL(9,E23:E24) -> 3061.8785 | J22: =H22 -> 0
C23: Plame Essalud y Renta de Quinta Categoría (Retención) | D23: 9857 | E23: =D23/$D$6 -> 2722.9282 | F23: 45820 | G23: Cancelado | H23: =IF(OR(G23="Sin pagar",G23="Pagar"),_xlfn.SINGLE(NETWORKDAYS($J$17,F23,FestivosPerú!$A$2:$A$15)),0) -> 0 | I23: =NETWORKDAYS($J$17,F23,FestivosPerú!$A$2:$A$15) -> 9 | J23: =H23 -> 0
C24: Pago de renta IGV Mayo | D24: 1227 | E24: =D24/$D$6 -> 338.95028 | F24: 45824 | G24: Cancelado | H24: =IF(OR(G24="Sin pagar",G24="Pagar"),_xlfn.SINGLE(NETWORKDAYS($J$17,F24,FestivosPerú!$A$2:$A$15)),0) -> 0 | I24: =NETWORKDAYS($J$17,F24,FestivosPerú!$A$2:$A$15) -> 11 | J24: =H24 -> 0 | M24: Outsorcing contable
C25: SERVICIOS OUTSORCING CONTABLE | D25: =SUBTOTAL(9,D26:D28) -> 3786.738 | E25: =SUBTOTAL(9,E26:E28) -> 1046.0602 | J25: =H25 -> 0
B26: F001 - 00006024 | C26: Estudio fuentes servicio cambio gerente general | D26: =(E26*$D$6) -> 1708.64 | E26: =472 -> 472 | F26: 45817 | G26: Cancelado | H26: =IF(OR(G26="Sin pagar",G26="Pagar"),_xlfn.SINGLE(NETWORKDAYS($J$17,F26,FestivosPerú!$A$2:$A$15)),0) -> 0 | I26: =NETWORKDAYS($J$17,F26,FestivosPerú!$A$2:$A$15) -> 6 | J26: =H26 -> 0
B27: F001 - 00006148 | C27: Servicio de apersonamiento CTS BBVA y Servicio dirección fiscal junio 2025 | D27: =E27*D6 -> 662.098 | E27: 182.9 | F27: 45834 | G27: Cancelado | H27: =IF(OR(G27="Sin pagar",G27="Pagar"),_xlfn.SINGLE(NETWORKDAYS($J$17,F27,FestivosPerú!$A$2:$A$15)),0) -> 0 | I27: =NETWORKDAYS($J$17,F27,FestivosPerú!$A$2:$A$15) -> 19 | J27: =H27 -> 0
B28: E001-584 | C28: Outsourcing contable servicio Junio Avanza | D28: 1416 | E28: =$D$28/$D$6 -> 391.16022 | F28: 45834 | G28: Cancelado | H28: =IF(OR(G28="Sin pagar",G28="Pagar"),_xlfn.SINGLE(NETWORKDAYS($J$17,F28,FestivosPerú!$A$2:$A$15)),0) -> 0 | I28: =NETWORKDAYS($J$17,F28,FestivosPerú!$A$2:$A$15) -> 19 | J28: =H28 -> 0
C29: PÓLIZAS DE VIDA Y SEGUROS MÉDICO | D29: =SUBTOTAL(9,D30:D34) -> 8339.75 | E29: =SUBTOTAL(9,E30:E34) -> 2996.616
B30: F052-01751987 | C30: Seguros de vida Ley recibo 161448077 | D30: =118 -> 118 | E30: =D30/$D$6 -> 32.596685 | F30: 45810 | G30: Cancelado | H30: =IF(OR(G30="Sin pagar",G30="Pagar"),_xlfn.SINGLE(NETWORKDAYS($J$17,F30,FestivosPerú!$A$2:$A$15)),0) -> 0 | I30: =NETWORKDAYS($J$17,F30,FestivosPerú!$A$2:$A$15) -> 1 | J30: =H30 -> 0
B31: F052-01751988 | C31: SCTR Pensiones recibo 161447562 | D31: =354.03 -> 354.03 | E31: =D31/$D$6 -> 97.798343 | F31: 45810 | G31: Cancelado | H31: =IF(OR(G31="Sin pagar",G31="Pagar"),_xlfn.SINGLE(NETWORKDAYS($J$17,F31,FestivosPerú!$A$2:$A$15)),0) -> 0 | I31: =NETWORKDAYS($J$17,F31,FestivosPerú!$A$2:$A$15) -> 1 | J31: =H31 -> 0
B32: F052-01558203 | C32: SCTR Salud recibo 161447573 | D32: =343.72 -> 343.72 | E32: =D32/$D$6 -> 94.950276 | F32: 45810 | G32: Cancelado | H32: =IF(OR(G32="Sin pagar",G32="Pagar"),_xlfn.SINGLE(NETWORKDAYS($J$17,F32,FestivosPerú!$A$2:$A$15)),0) -> 0 | I32: =NETWORKDAYS($J$17,F32,FestivosPerú!$A$2:$A$15) -> 1 | J32: =H32 -> 0
B33: S/N | C33: Póliza de salud Braidy Vera-Mes de abril y mayo | D33: =2508*2 -> 5016 | E33: =$D$33/$D$6 -> 1385.6354 | F33: 45813 | G33: Cancelado | H33: =IF(OR(G33="Sin pagar",G33="Pagar"),_xlfn.SINGLE(NETWORKDAYS($J$17,F33,FestivosPerú!$A$2:$A$15)),0) -> 0 | I33: =NETWORKDAYS($J$17,F33,FestivosPerú!$A$2:$A$15) -> 4 | J33: =H33 -> 0
B34: S/N | C34: Póliza de salud Braidy Vera-Mes de Junio-Doble débito | D34: 2508 | E34: =$D$33/$D$6 -> 1385.6354 | F34: 45821 | G34: Cancelado | H34: =IF(OR(G34="Sin pagar",G34="Pagar"),_xlfn.SINGLE(NETWORKDAYS($J$17,F34,FestivosPerú!$A$2:$A$15)),0) -> 0 | I34: =NETWORKDAYS($J$17,F34,FestivosPerú!$A$2:$A$15) -> 10 | J34: =H34 -> 0
C35: COSTOS FINANCIEROS | D35: =SUBTOTAL(9,D36:D36) -> 292.5242 | E35: =SUBTOTAL(9,E36:E36) -> 80.807789
C36: COSTOS FINANCIEROS | D36: =('BCP SOLES BCP'!$F$209+'BCP SOLES BCP'!$F$211+'BCP SOLES BCP'!$F$213+'BCP SOLES BCP'!$F$216+'BCP SOLES BCP'!$F$218+'BCP SOLES BCP'!$F$221+'BCP SOLES BCP'!$F$223+'BCP SOLES BCP'!$F$224+'BCP SOLES BCP'!$F$232+'BCP SOLES BCP'!$F$234+'BCP SOLES BCP'!$F$236+'BCP SOLES BCP'!$F$238+'BCP SOLES BCP'!$F$240+'BCP SOLES BCP'!$F$242+'BCP SOLES BCP'!$F$243+'BCP SOLES BCP'!$F$244+'BCP SOLES BCP'!$F$245)+('BCP USD BCP'!F114+'BCP USD BCP'!F118+'BCP USD BCP'!F119+'BCP USD BCP'!F120*$D$6) -> 292.5242 | E36: =$D$36/$D$6 -> 80.807789 | F36: 45838 | G36: Cancelado | H36: =IF(OR(G36="Sin pagar",G36="Pagar"),_xlfn.SINGLE(NETWORKDAYS($J$17,F36,FestivosPerú!$A$2:$A$15)),0) -> 0 | I36: =NETWORKDAYS($J$17,F36,FestivosPerú!$A$2:$A$15) -> 21 | J36: =H36 -> 0
C37: NÓMINAS | D37: =SUBTOTAL(9,D38:D40) -> 34849.09 | E37: =SUBTOTAL(9,E38:E40) -> 9626.8205
C38: Braydi Yusset Vera Neira-Europortage | D38: 13319.616 | E38: =D38/$D$6 -> 3679.452 | F38: 45834 | G38: Cancelado | H38: =IF(OR(G38="Sin pagar",G38="Pagar"),_xlfn.SINGLE(NETWORKDAYS($J$17,F38,FestivosPerú!$A$2:$A$15)),0) -> 0 | I38: =NETWORKDAYS($J$17,F38,FestivosPerú!$A$2:$A$15) -> 19 | J38: =H38 -> 0
C39: Cristhian Portugal Segovia -Europortage | D39: 10717.393 | E39: =D39/$D$6 -> 2960.6058 | F39: 45834 | G39: Cancelado | H39: =IF(OR(G39="Sin pagar",G39="Pagar"),_xlfn.SINGLE(NETWORKDAYS($J$17,F39,FestivosPerú!$A$2:$A$15)),0) -> 0 | I39: =NETWORKDAYS($J$17,F39,FestivosPerú!$A$2:$A$15) -> 19 | J39: =H39 -> 0
C40: Davis Cesar oporto figueroa -Europortage | D40: 10812.081 | E40: =D40/$D$6 -> 2986.7628 | F40: 45834 | G40: Cancelado | H40: =IF(OR(G40="Sin pagar",G40="Pagar"),_xlfn.SINGLE(NETWORKDAYS($J$17,F40,FestivosPerú!$A$2:$A$15)),0) -> 0 | I40: =NETWORKDAYS($J$17,F40,FestivosPerú!$A$2:$A$15) -> 19 | J40: =H40 -> 0
C41: REEMBOLSO | D41: =SUBTOTAL(9,D42:D44) -> 32819.93 | E41: =SUBTOTAL(9,E42:E44) -> 9066.279
C42: Reembolso Braydi Yusset Vera Neira-Europortage | D42: 14539.09 | E42: =D42/$D$6 -> 4016.3232 | F42: 45834 | G42: Cancelado | H42: =IF(OR(G42="Sin pagar",G42="Pagar"),_xlfn.SINGLE(NETWORKDAYS($J$17,F42,FestivosPerú!$A$2:$A$15)),0) -> 0 | I42: =NETWORKDAYS($J$17,F42,FestivosPerú!$A$2:$A$15) -> 19 | J42: =H42 -> 0
C43: Reembolso Cristhian Portugal Segovia -Europortage | D43: 9067.27 | E43: =D43/$D$6 -> 2504.7707 | F43: 45835 | G43: Cancelado | H43: =IF(OR(G43="Sin pagar",G43="Pagar"),_xlfn.SINGLE(NETWORKDAYS($J$17,F43,FestivosPerú!$A$2:$A$15)),0) -> 0 | I43: =NETWORKDAYS($J$17,F43,FestivosPerú!$A$2:$A$15) -> 20 | J43: =H43 -> 0
C44: Reembolso Davis Cesar oporto figueroa -Europortage | D44: 9213.57 | E44: =D44/$D$6 -> 2545.1851 | F44: 45835 | G44: Cancelado | H44: =IF(OR(G44="Sin pagar",G44="Pagar"),_xlfn.SINGLE(NETWORKDAYS($J$17,F44,FestivosPerú!$A$2:$A$15)),0) -> 0 | I44: =NETWORKDAYS($J$17,F44,FestivosPerú!$A$2:$A$15) -> 20 | J44: =H44 -> 0
C45: IMPREVISTO | D45: =SUBTOTAL(9,D46:D48) -> 3592.26 | E45: =SUBTOTAL(9,E46:E48) -> 987.73481
C46: Envio de dinero Joel David Dionisio Ore-Préstamo Ricardo Arambulo | D46: =E46*3.637 -> 3564.26 | E46: ='BCP USD BCP'!F112 -> 980 | F46: 45827 | G46: Cancelado | H46: =IF(OR(G46="Sin pagar",G46="Pagar"),_xlfn.SINGLE(NETWORKDAYS($J$17,F46,FestivosPerú!$A$2:$A$15)),0) -> 0 | I46: =NETWORKDAYS($J$17,F46,FestivosPerú!$A$2:$A$15) -> 14 | J46: =H46 -> 0
C47: Envio de dinero para completar los comisiones bancarias del Deposito CTS -Cristhan Portugal-BCP | D47: 28 | E47: =D47/$D$6 -> 7.7348066 | F47: 45833 | G47: Cancelado | H47: =IF(OR(G47="Sin pagar",G47="Pagar"),_xlfn.SINGLE(NETWORKDAYS($J$17,F47,FestivosPerú!$A$2:$A$15)),0) -> 0 | I47: =NETWORKDAYS($J$17,F47,FestivosPerú!$A$2:$A$15) -> 18 | J47: =H47 -> 0
C48: Deposito CTS -Cristhan Portugal-Intereses 1 al 10 Junio | D48: =150*0 -> 0 | E48: =D48/$D$6 -> 0 | F48: 45842 | G48: Sin Pagar | H48: =IF(OR(G48="Sin pagar",G48="Pagar"),_xlfn.SINGLE(NETWORKDAYS($J$17,F48,FestivosPerú!$A$2:$A$15)),0) -> 25 | I48: =NETWORKDAYS($J$17,F48,FestivosPerú!$A$2:$A$15) -> 25 | J48: =H48 -> 25
C49: TOTAL EGRESOS | D49: =SUBTOTAL(9,D19:D48) -> 100452.37 | E49: =SUBTOTAL(9,E19:E48) -> 28437.49
C51: SALDO | D51: =D14-D49 -> 36805.044 | E51: =E14-E49 -> 10284.283
C52: % | D52: =IF($D$14=0,0,D51/$D$14) -> 0.26814612 | E52: =IF($E$14=0,0,E51/$E$14) -> 0.26559432
C55: Fecha Inicial | D55: Fecha Final | E55: Valor Valor S/Soles | F55: Valor USD
C56: 45809 | D56: 45816 | E56: =SUMIFS($D$18:$D$53,$F$18:$F$53,">="&C56,$F$18:$F$53,"<="&D56,$G$18:$G$53,$D$71) -> 0 | F56: =SUMIFS($E$18:$E$53,$F$18:$F$53,">="&C56,$F$18:$F$53,"<="&D56,$G$18:$G$53,$D$71) -> 0
C57: 45817 | D57: 45823 | E57: =SUMIFS($D$18:$D$53,$F$18:$F$53,">="&C57,$F$18:$F$53,"<="&D57,$G$18:$G$53,$D$71) -> 0 | F57: =SUMIFS($E$18:$E$53,$F$18:$F$53,">="&C57,$F$18:$F$53,"<="&D57,$G$18:$G$53,$D$71) -> 0 | G57: Pago renta IGV , ISS, Estudio fuente
C58: 45824 | D58: 45830 | E58: =SUMIFS($D$18:$D$53,$F$18:$F$53,">="&C58,$F$18:$F$53,"<="&D58,$G$18:$G$53,$D$71) -> 0 | F58: =SUMIFS($E$18:$E$53,$F$18:$F$53,">="&C58,$F$18:$F$53,"<="&D58,$G$18:$G$53,$D$71) -> 0
C59: 45831 | D59: 45838 | E59: =SUMIFS($D$18:$D$53,$F$18:$F$53,">="&C59,$F$18:$F$53,"<="&D59,$G$18:$G$53,$D$71) -> 0 | F59: =SUMIFS($E$18:$E$53,$F$18:$F$53,">="&C59,$F$18:$F$53,"<="&D59,$G$18:$G$53,$D$71) -> 0 | G59: Nóminas , reembolso, servicio Estudio fuente
C60: TOTAL EGRESOS | E60: =SUM(E56:E59) -> 0 | F60: =SUM(F56:F59) -> 0
C65: Bancos | E65: ='BCP SOLES BCP'!$G$300+('BCP USD BCP'!$G$299*$D$6) -> 66765.74 | F65: ='BCP USD BCP'!$G$299+('BCP SOLES BCP'!$G$300/$D$6) -> 18443.575
C66: Gastos y costos Periodo 23 al 30 junio | E66: =SUM(E56:E59) -> 0 | F66: =SUM(F56:F59) -> 0
C67: Saldo | E67: =E65-E66 -> 66765.74 | F67: =F65-F66 -> 18443.575
D70: Cancelado | E70: =SUMIFS($D$20:$D$53,$F$20:$F$53,">="&$C$56,$F$20:$F$53,"<="&$D$59,$G$20:$G$53,$D$70) -> 100452.37 | F70: =SUMIFS($E$20:$E$53,$F$20:$F$53,">="&$C$56,$F$20:$F$53,"<="&$D$59,$G$20:$G$53,$D$70) -> 28437.49
D71: Sin Pagar | E71: =SUMIFS($D$18:$D$53,$F$18:$F$53,">="&C56,$F$18:$F$53,"<="&D59,$G$18:$G$53,$D$71) -> 0 | F71: =SUMIFS($E$18:$E$53,$F$18:$F$53,">="&$C$56,$F$18:$F$53,"<="&$D$59,$G$18:$G$53,$D$71) -> 0
D72: Total Egresos | E72: =SUM(E70:E71) -> 100452.37 | F72: =SUM(F70:F71) -> 28437.49
D74: Validación | E74: =(D49-E72) -> 0 | F74: =(F72-E49) -> 0
D77: Flujo Caja | E77: =D51 -> 36805.044
D78: Libro Bancos | E78: ='BCP SOLES BCP'!$G$246+('BCP USD BCP'!$G$121*D6) -> 36805.043
D79: Diferencia Soles | E79: =E78-E77 -> -0.00145
D80: Diferencia USD | E80: =E79/$D$6 -> -0.00040055249

Sheet FLUJO CAJA JULIO
D1: 42400
D4: Fecha de Elaboración: | E4: 45839
C6: Tasa de cambio: | D6: 3.5552
D7: JULIO
D8: VALOR S/ Sol | E8: VALOR USD
C9: BANCOS | D9: =SUBTOTAL(9,D10:D12) -> 40586.61 | E9: =SUBTOTAL(9,E10:E12) -> 11416.126
C10: Bancos S/ Soles | D10: ='BCP SOLES BCP'!$G$246-9955.17 -> 19668.951 | E10: =D10/$D$6 -> 5532.4457
C11: Bancos USD | D11: =E11*$D$6 -> 7052.3791 | E11: ='BCP USD BCP'!$G$121 -> 1983.68
C12: Préstamo S&P Colombia | D12: =E12*$D$6 -> 13865.28 | E12: 3900
C13: CLIENTES | D13: =SUBTOTAL(9,D14:D18) -> 140880.48 | E13: =SUBTOTAL(9,E14:E18) -> 40139.5
B14: Pagado | C14: Client: Europortage-Factura Nro EB01-21 | D14: =$E$14*'Diferencia Cambio S&P'!$K$23 -> 92937.955 | E14: ='BCP USD BCP'!E134 -> 26478.05
B15: Pagado | C15: Client: Yonyou xinfushe cloud technology co., limited-Factura Nro EB01-22 | D15: =$E$15*'Diferencia Cambio S&P'!$K$24 -> 18854.246 | E15: ='BCP USD BCP'!E132 -> 5371.58
B16: Pagado | C16: Client: Remotepass-Factura Nro EB01-23 | D16: =$E$16*'Diferencia Cambio S&P'!$K$25 -> 23734.55 | E16: ='BCP USD BCP'!E133 -> 6761.98
B17: Pagado | C17: Client: Safeguard-Factura Nro EB01-01 ( Cliente) | D17: =E17*3.504 -> 5353.7266 | E17: ='BCP USD BCP'!E129 -> 1527.89
B18: Sin Pagar | C18: Client: Safeguard-Factura Nro EB01-02 ( Cliente) | D18: =E18*3.44 -> 0 | E18: =1282.87*0 -> 0
C19: TOTAL INGRESOS | D19: =SUBTOTAL(9,D9:D18) -> 181467.09 | E19: =SUBTOTAL(9,E9:E18) -> 51555.626
B22: CUENTAS X PAGAR MES | D22: ABRIL | F22: Fecha de Elaboración: | J22: 45809
B23: Factura | C23: PROVEEDOR | D23: VALOR S/Sol | E23: VALOR USD | F23: Fecha vencimiento | G23: Estado | J23: KPI
C24: SEGURIDAD IGSS | D24: =SUBTOTAL(9,D25:D26) -> 5517.91 | E24: =SUBTOTAL(9,E25:E26) -> 1552.0674
B25: 2220819158 | C25: Planilla de declaración y pago de aportes previsional-Braydi Yusset Vera Neyra y Davis Cesar Oporto Figueroa | D25: 3727.63 | E25: =D25/$D$6 -> 1048.5008 | F25: 45842 | G25: Cancelado | H25: =IF(OR(G25="Sin pagar",G25="Pagar"),_xlfn.SINGLE(NETWORKDAYS($J$22,F25,FestivosPerú!$A$2:$A$15)),0) -> 0 | I25: =NETWORKDAYS($J$22,F25,FestivosPerú!$A$2:$A$15) -> 25 | J25: =H25 -> 0
B26: 2516822828 | C26: Planilla de declaración y pago de aportes previsional Christian Portugal Segovia | D26: 1790.28 | E26: =D26/$D$6 -> 503.56661 | F26: 45842 | G26: Cancelado | H26: =IF(OR(G26="Sin pagar",G26="Pagar"),_xlfn.SINGLE(NETWORKDAYS($J$22,F26,FestivosPerú!$A$2:$A$15)),0) -> 0 | I26: =NETWORKDAYS($J$22,F26,FestivosPerú!$A$2:$A$15) -> 25 | J26: =H26 -> 0
C27: IMPUESTOS | D27: =SUBTOTAL(9,D28:D29) -> 11486.35 | E27: =SUBTOTAL(9,E28:E29) -> 3230.859 | J27: =H27 -> 0
C28: Plame Essalud y Renta de Quinta Categoría (Retención) | D28: 9946 | E28: =D28/$D$6 -> 2797.5923 | F28: 45847 | G28: Cancelado | H28: =IF(OR(G28="Sin pagar",G28="Pagar"),_xlfn.SINGLE(NETWORKDAYS($J$22,F28,FestivosPerú!$A$2:$A$15)),0) -> 0 | I28: =NETWORKDAYS($J$22,F28,FestivosPerú!$A$2:$A$15) -> 28 | J28: =H28 -> 0
C29: Pago de renta IGV Junio | D29: 1540.35 | E29: =D29/$D$6 -> 433.26676 | F29: 45854 | G29: Cancelado | H29: =IF(OR(G29="Sin pagar",G29="Pagar"),_xlfn.SINGLE(NETWORKDAYS($J$22,F29,FestivosPerú!$A$2:$A$15)),0) -> 0 | I29: =NETWORKDAYS($J$22,F29,FestivosPerú!$A$2:$A$15) -> 33 | J29: =H29 -> 0 | M29: Outsorcing contable
C30: SERVICIOS OUTSORCING CONTABLE | D30: =SUBTOTAL(9,D31:D34) -> 3422 | E30: =SUBTOTAL(9,E31:E34) -> 647.22097 | J30: =H30 -> 0
B31: E001-637 | C31: Outsourcing contable servicio Julio a S&P- Avanza | D31: 1416 | E31: =$D$31/$D$6 -> 398.28983 | F31: 45867 | G31: Cancelado | H31: =IF(OR(G31="Sin pagar",G31="Pagar"),_xlfn.SINGLE(NETWORKDAYS($J$22,F31,FestivosPerú!$A$2:$A$15)),0) -> 0 | I31: =NETWORKDAYS($J$22,F31,FestivosPerú!$A$2:$A$15) -> 40 | J31: =H31 -> 0
B32: E001-641 | C32: Outsourcing contable servicio mayo a SG- Avanza | D32: 295 | E32: =$D$32/$D$6 -> 82.977048 | F32: 45867 | G32: Cancelado | H32: =IF(OR(G32="Sin pagar",G32="Pagar"),_xlfn.SINGLE(NETWORKDAYS($J$22,F32,FestivosPerú!$A$2:$A$15)),0) -> 0 | I32: =NETWORKDAYS($J$22,F32,FestivosPerú!$A$2:$A$15) -> 40 | J32: =H32 -> 0
B33: E001-642 | C33: Outsourcing contable servicio junio a SG- Avanza | D33: 295 | E33: =$D$32/$D$6 -> 82.977048 | F33: 45867 | G33: Cancelado | H33: =IF(OR(G33="Sin pagar",G33="Pagar"),_xlfn.SINGLE(NETWORKDAYS($J$22,F33,FestivosPerú!$A$2:$A$15)),0) -> 0 | I33: =NETWORKDAYS($J$22,F33,FestivosPerú!$A$2:$A$15) -> 40 | J33: =H33 -> 0
B34: E001-643 | C34: Outsourcing contable servicio julio a SG- Avanza | D34: 1416 | E34: =$D$32/$D$6 -> 82.977048 | F34: 45867 | G34: Cancelado | H34: =IF(OR(G34="Sin pagar",G34="Pagar"),_xlfn.SINGLE(NETWORKDAYS($J$22,F34,FestivosPerú!$A$2:$A$15)),0) -> 0 | I34: =NETWORKDAYS($J$22,F34,FestivosPerú!$A$2:$A$15) -> 40 | J34: =H34 -> 0
C35: PÓLIZAS DE VIDA Y SEGUROS MÉDICO | D35: =SUBTOTAL(9,D36:D45) -> 5216.7 | E35: =SUBTOTAL(9,E36:E45) -> 1467.3436
B36: F052-01751987 | C36: Seguros de vida Rimac -Davis oporto | D36: 1613 | E36: =D36/$D$6 -> 453.70162 | F36: 45840 | G36: Cancelado | H36: =IF(OR(G36="Sin pagar",G36="Pagar"),_xlfn.SINGLE(NETWORKDAYS($J$22,F36,FestivosPerú!$A$2:$A$15)),0) -> 0 | I36: =NETWORKDAYS($J$22,F36,FestivosPerú!$A$2:$A$15) -> 23 | J36: =H36 -> 0
B37: F052-01791304 | C37: Seguros de vida Ley recibo 162427159 | D37: =118 -> 118 | E37: =D37/$D$6 -> 33.190819 | F37: 45842 | G37: Cancelado | H37: =IF(OR(G37="Sin pagar",G37="Pagar"),_xlfn.SINGLE(NETWORKDAYS($J$22,F37,FestivosPerú!$A$2:$A$15)),0) -> 0 | I37: =NETWORKDAYS($J$22,F37,FestivosPerú!$A$2:$A$15) -> 25 | J37: =H37 -> 0
B38: F052-01791305 | C38: SCTR Pensiones recibo 162413259 | D38: =354.03 -> 354.03 | E38: =D38/$D$6 -> 99.580896 | F38: 45842 | G38: Cancelado | H38: =IF(OR(G38="Sin pagar",G38="Pagar"),_xlfn.SINGLE(NETWORKDAYS($J$22,F38,FestivosPerú!$A$2:$A$15)),0) -> 0 | I38: =NETWORKDAYS($J$22,F38,FestivosPerú!$A$2:$A$15) -> 25 | J38: =H38 -> 0
B39: F052-01590916 | C39: SCTR Salud recibo 162413267 | D39: =343.72 -> 343.72 | E39: =D39/$D$6 -> 96.680918 | F39: 45842 | G39: Cancelado | H39: =IF(OR(G39="Sin pagar",G39="Pagar"),_xlfn.SINGLE(NETWORKDAYS($J$22,F39,FestivosPerú!$A$2:$A$15)),0) -> 0 | I39: =NETWORKDAYS($J$22,F39,FestivosPerú!$A$2:$A$15) -> 25 | J39: =H39 -> 0
B40: F052-01791306 | C40: SCTR Salud recibo 162427441- Ingreso Yon you | D40: 179.6 | E40: =D40/$D$6 -> 50.517552 | F40: 45842 | G40: Cancelado | H40: =IF(OR(G40="Sin pagar",G40="Pagar"),_xlfn.SINGLE(NETWORKDAYS($J$22,F40,FestivosPerú!$A$2:$A$15)),0) -> 0 | I40: =NETWORKDAYS($J$22,F40,FestivosPerú!$A$2:$A$15) -> 25 | J40: =H40 -> 0
B41: S/N | C41: Seguros de vida Rimac -Davis oporto | D41: 1613 | E41: =D41/$D$6 -> 453.70162 | F41: 45871 | G41: Cancelado | H41: =IF(OR(G41="Sin pagar",G41="Pagar"),_xlfn.SINGLE(NETWORKDAYS($J$22,F41,FestivosPerú!$A$2:$A$15)),0) -> 0 | I41: =NETWORKDAYS($J$22,F41,FestivosPerú!$A$2:$A$15) -> 43 | J41: =H41 -> 0
B42: S/N | C42: SCTR Pensiones recibo 162413259 | D42: =354.03 -> 354.03 | E42: =D42/$D$6 -> 99.580896 | F42: 45873 | G42: Cancelado | H42: =IF(OR(G42="Sin pagar",G42="Pagar"),_xlfn.SINGLE(NETWORKDAYS($J$22,F42,FestivosPerú!$A$2:$A$15)),0) -> 0 | I42: =NETWORKDAYS($J$22,F42,FestivosPerú!$A$2:$A$15) -> 44 | J42: =H42 -> 0
B43: S/N | C43: SCTR Salud recibo 162413267 | D43: =343.72 -> 343.72 | E43: =D43/$D$6 -> 96.680918 | F43: 45873 | G43: Cancelado | H43: =IF(OR(G43="Sin pagar",G43="Pagar"),_xlfn.SINGLE(NETWORKDAYS($J$22,F43,FestivosPerú!$A$2:$A$15)),0) -> 0 | I43: =NETWORKDAYS($J$22,F43,FestivosPerú!$A$2:$A$15) -> 44 | J43: =H43 -> 0
B44: S/N | C44: Seguros de vida Ley recibo 162427159 | D44: =118 -> 118 | E44: =D44/$D$6 -> 33.190819 | F44: 45873 | G44: Cancelado | H44: =IF(OR(G44="Sin pagar",G44="Pagar"),_xlfn.SINGLE(NETWORKDAYS($J$22,F44,FestivosPerú!$A$2:$A$15)),0) -> 0 | I44: =NETWORKDAYS($J$22,F44,FestivosPerú!$A$2:$A$15) -> 44 | J44: =H44 -> 0
B45: S/N | C45: SCTR Salud recibo 162427441- Ingreso Yon you | D45: 179.6 | E45: =D45/$D$6 -> 50.517552 | F45: 45873 | G45: Cancelado | H45: =IF(OR(G45="Sin pagar",G45="Pagar"),_xlfn.SINGLE(NETWORKDAYS($J$22,F45,FestivosPerú!$A$2:$A$15)),0) -> 0 | I45: =NETWORKDAYS($J$22,F45,FestivosPerú!$A$2:$A$15) -> 44 | J45: =H45 -> 0
C46: COSTOS FINANCIEROS | D46: =SUBTOTAL(9,D47:D47) -> 385.0676 | E46: =SUBTOTAL(9,E47:E47) -> 108.31109
C47: COSTOS FINANCIEROS | D47: =('BCP SOLES BCP'!$F$249+'BCP SOLES BCP'!$F$251+'BCP SOLES BCP'!$F$257+'BCP SOLES BCP'!$F$261+'BCP SOLES BCP'!$F$265+'BCP SOLES BCP'!$F$266+'BCP SOLES BCP'!$F$268+'BCP SOLES BCP'!$F$269+'BCP SOLES BCP'!$F$270+'BCP SOLES BCP'!$F$272+'BCP SOLES BCP'!$F$274+'BCP SOLES BCP'!$F$277+'BCP SOLES BCP'!$F$279+'BCP SOLES BCP'!$F$281+'BCP SOLES BCP'!$F$282+'BCP SOLES BCP'!$F$285+'BCP SOLES BCP'!F292+'BCP SOLES BCP'!$F$294+'BCP SOLES BCP'!$F$296+'BCP SOLES BCP'!$F$301+'BCP SOLES BCP'!$F$302+'BCP SOLES BCP'!$F$307)+(('BCP USD BCP'!$F$126+'BCP USD BCP'!$F$130+'BCP USD BCP'!$F$131+'BCP USD BCP'!$F$135+'BCP USD BCP'!$F$139+'BCP USD BCP'!$F$141+'BCP USD BCP'!$F$142+'BCP USD BCP'!$F$143*$D$6)) -> 385.0676 | E47: =$D$47/$D$6 -> 108.31109 | F47: 45869 | G47: Cancelado | H47: =IF(OR(G47="Sin pagar",G47="Pagar"),_xlfn.SINGLE(NETWORKDAYS($J$22,F47,FestivosPerú!$A$2:$A$15)),0) -> 0 | I47: =NETWORKDAYS($J$22,F47,FestivosPerú!$A$2:$A$15) -> 42 | J47: =H47 -> 0
C48: NÓMINAS | D48: =SUBTOTAL(9,D49:D56) -> 76996.574 | E48: =SUBTOTAL(9,E49:E56) -> 25204.637
C49: Braydi Yusset Vera Neira-Europortage-Gratificación | D49: 16996.95 | E49: =D49/$D$6 -> 4780.8703 | F49: 45849 | G49: Cancelado | H49: =IF(OR(G49="Sin pagar",G49="Pagar"),_xlfn.SINGLE(NETWORKDAYS($J$22,F49,FestivosPerú!$A$2:$A$15)),0) -> 0 | I49: =NETWORKDAYS($J$22,F49,FestivosPerú!$A$2:$A$15) -> 30 | J49: =H49 -> 0
C50: Cristhian Portugal Segovia -Europortage-Gratificación | D50: 7630 | E50: =D50/$D$6 -> 2146.1521 | F50: 45852 | G50: Cancelado | H50: =IF(OR(G50="Sin pagar",G50="Pagar"),_xlfn.SINGLE(NETWORKDAYS($J$22,F50,FestivosPerú!$A$2:$A$15)),0) -> 0 | I50: =NETWORKDAYS($J$22,F50,FestivosPerú!$A$2:$A$15) -> 31 | J50: =H50 -> 0
C51: Davis Cesar oporto figueroa -Europortage-Gratificación | D51: 5086.67 | E51: =D51/$D$6 -> 1430.769 | F51: 45852 | G51: Cancelado | H51: =IF(OR(G51="Sin pagar",G51="Pagar"),_xlfn.SINGLE(NETWORKDAYS($J$22,F51,FestivosPerú!$A$2:$A$15)),0) -> 0 | I51: =NETWORKDAYS($J$22,F51,FestivosPerú!$A$2:$A$15) -> 31 | J51: =H51 -> 0
C52: Braydi Yusset Vera Neira-Europortage | D52: 13823.91 | E52: =D52/$D$6 -> 3888.3635 | F52: 45863 | G52: Cancelado | H52: =IF(OR(G52="Sin pagar",G52="Pagar"),_xlfn.SINGLE(NETWORKDAYS($J$22,F52,FestivosPerú!$A$2:$A$15)),0) -> 0 | I52: =NETWORKDAYS($J$22,F52,FestivosPerú!$A$2:$A$15) -> 39 | J52: =H52 -> 0
C53: Cristhian Portugal Segovia -Europortage | D53: 10903.284 | E53: =D53/$D$6 -> 3066.8553 | F53: 45863 | G53: Cancelado | H53: =IF(OR(G53="Sin pagar",G53="Pagar"),_xlfn.SINGLE(NETWORKDAYS($J$22,F53,FestivosPerú!$A$2:$A$15)),0) -> 0 | I53: =NETWORKDAYS($J$22,F53,FestivosPerú!$A$2:$A$15) -> 39 | J53: =H53 -> 0
C54: Davis Cesar oporto figueroa -Europortage | D54: 10983.892 | E54: =D54/$D$6 -> 3089.5287 | F54: 45863 | G54: Cancelado | H54: =IF(OR(G54="Sin pagar",G54="Pagar"),_xlfn.SINGLE(NETWORKDAYS($J$22,F54,FestivosPerú!$A$2:$A$15)),0) -> 0 | I54: =NETWORKDAYS($J$22,F54,FestivosPerú!$A$2:$A$15) -> 39 | J54: =H54 -> 0
C55: Luis Renato Sanchez Perez -Yon Yuo | D55: 10488.401 | E55: =D55/$D$6 -> 2950.1577 | F55: 45865 | G55: Cancelado | H55: =IF(OR(G55="Sin pagar",G55="Pagar"),_xlfn.SINGLE(NETWORKDAYS($J$22,F55,FestivosPerú!$A$2:$A$15)),0) -> 0 | I55: =NETWORKDAYS($J$22,F55,FestivosPerú!$A$2:$A$15) -> 39 | J55: =H55 -> 0
C56: Christiams Hebert Valle Gomez -Remotepass | D56: =E56/D6 -> 1083.4665 | E56: 3851.94 | F56: 45865 | G56: Cancelado | H56: =IF(OR(G56="Sin pagar",G56="Pagar"),_xlfn.SINGLE(NETWORKDAYS($J$22,F56,FestivosPerú!$A$2:$A$15)),0) -> 0 | I56: =NETWORKDAYS($J$22,F56,FestivosPerú!$A$2:$A$15) -> 39 | J56: =H56 -> 0
C57: REEMBOLSO | D57: =SUBTOTAL(9,D58:D61) -> 21311.67 | E57: =SUBTOTAL(9,E58:E61) -> 5994.5066
C58: Reembolso Braydi Yusset Vera Neira-Europortage | D58: 3280.08 | E58: =D58/$D$6 -> 922.61476 | F58: 45855 | G58: Cancelado | H58: =IF(OR(G58="Sin pagar",G58="Pagar"),_xlfn.SINGLE(NETWORKDAYS($J$22,F58,FestivosPerú!$A$2:$A$15)),0) -> 0 | I58: =NETWORKDAYS($J$22,F58,FestivosPerú!$A$2:$A$15) -> 34 | J58: =H58 -> 0
C59: Reembolso Braydi Yusset Vera Neira-Europortage | D59: 4594.33 | E59: =D59/$D$6 -> 1292.2845 | F59: 45866 | G59: Cancelado | H59: =IF(OR(G59="Sin pagar",G59="Pagar"),_xlfn.SINGLE(NETWORKDAYS($J$22,F59,FestivosPerú!$A$2:$A$15)),0) -> 0 | I59: =NETWORKDAYS($J$22,F59,FestivosPerú!$A$2:$A$15) -> 39 | J59: =H59 -> 0
C60: Reembolso Cristhian Portugal Segovia -Europortage | D60: 12323.06 | E60: =D60/$D$6 -> 3466.2072 | F60: 45866 | G60: Cancelado | H60: =IF(OR(G60="Sin pagar",G60="Pagar"),_xlfn.SINGLE(NETWORKDAYS($J$22,F60,FestivosPerú!$A$2:$A$15)),0) -> 0 | I60: =NETWORKDAYS($J$22,F60,FestivosPerú!$A$2:$A$15) -> 39 | J60: =H60 -> 0
C61: Reembolso Davis Cesar oporto figueroa -Europortage | D61: 1114.2 | E61: =D61/$D$6 -> 313.40009 | F61: 45866 | G61: Cancelado | H61: =IF(OR(G61="Sin pagar",G61="Pagar"),_xlfn.SINGLE(NETWORKDAYS($J$22,F61,FestivosPerú!$A$2:$A$15)),0) -> 0 | I61: =NETWORKDAYS($J$22,F61,FestivosPerú!$A$2:$A$15) -> 39 | J61: =H61 -> 0
C62: IMPREVISTO | D62: =SUBTOTAL(9,D63:D63) -> 0 | E62: =SUBTOTAL(9,E63:E63) -> 0
C63: Imprevisto | D63: 0 | E63: =D63/$D$6 -> 0 | F63: 45869 | G63: Cancelado | H63: =IF(OR(G63="Sin pagar",G63="Pagar"),_xlfn.SINGLE(NETWORKDAYS($J$22,F63,FestivosPerú!$A$2:$A$15)),0) -> 0 | I63: =NETWORKDAYS($J$22,F63,FestivosPerú!$A$2:$A$15) -> 42 | J63: =H63 -> 0
C64: Gastos safeguard Perú | D64: =SUBTOTAL(9,D65:D69) -> 6724.07 | E64: =SUBTOTAL(9,E65:E69) -> 1891.3338
C65: Pago Fiorella Maribel chavez Torriani -Safeguard Nómina Julio | D65: ='BCP SOLES BCP'!F286 -> 3562.39 | E65: =D65/$D$6 -> 1002.0224 | F65: 45866 | G65: Cancelado
C66: Pago Claudia Anabel cardenas -Safeguard Nómina Julio | D66: ='BCP SOLES BCP'!F288 -> 3027.61 | E66: =D66/$D$6 -> 851.60047 | F66: 45866 | G66: Cancelado
C67: Pago póliza Nro 130541 seguro de vida Ley - Safeguard | D67: ='BCP SOLES BCP'!F305 -> 70 | E67: =D67/$D$6 -> 19.689469 | F67: 45870 | G67: Cancelado
C68: Pago póliza Nro 130541 seguro de vida Ley - Safeguard | D68: ='BCP SOLES BCP'!F309 -> 54.17 | E68: =D68/$D$6 -> 15.236836 | F68: 45873 | G68: Cancelado
C69: Gastos financieros | D69: ='BCP SOLES BCP'!F287+'BCP SOLES BCP'!F289+'BCP SOLES BCP'!F290 -> 9.9 | E69: =D69/$D$6 -> 2.7846535 | F69: 45874 | G69: Cancelado
C70: TOTAL EGRESOS | D70: =SUBTOTAL(9,D24:D69) -> 131060.34 | E70: =SUBTOTAL(9,E24:E69) -> 40096.279
C72: SALDO | D72: =D19-D70 -> 50406.747 | E72: =E19-E70 -> 11459.347
C73: % | D73: =IF($D$19=0,0,D72/$D$19) -> 0.27777349 | E73: =IF($E$19=0,0,E72/$E$19) -> 0.22227151
C76: Fecha Inicial | D76: Fecha Final | E76: Valor Valor S/Soles | F76: Valor USD
C77: 45839 | D77: 45844 | E77: =SUMIFS($D$23:$D$74,$F$23:$F$74,">="&C77,$F$23:$F$74,"<="&D77,$G$23:$G$74,$D$94) -> 0 | F77: =SUMIFS($E$23:$E$74,$F$23:$F$74,">="&C77,$F$23:$F$74,"<="&D77,$G$23:$G$74,$D$94) -> 0 | G77: Pólizas medicas y seguros
C78: 45845 | D78: 45851 | E78: =SUMIFS($D$23:$D$74,$F$23:$F$74,">="&C78,$F$23:$F$74,"<="&D78,$G$23:$G$74,$D$94) -> 0 | F78: =SUMIFS($E$23:$E$74,$F$23:$F$74,">="&C78,$F$23:$F$74,"<="&D78,$G$23:$G$74,$D$94) -> 0 | G78: IGSS, Retención 5ta Categoría
C79: 45852 | D79: 45858 | E79: =SUMIFS($D$23:$D$74,$F$23:$F$74,">="&C79,$F$23:$F$74,"<="&D79,$G$23:$G$74,$D$94) -> 0 | F79: =SUMIFS($E$23:$E$74,$F$23:$F$74,">="&C79,$F$23:$F$74,"<="&D79,$G$23:$G$74,$D$94) -> 0 | G79: Pago de renta IGV Junio
C80: 45859 | D80: 45865 | E80: =SUMIFS($D$23:$D$74,$F$23:$F$74,">="&C80,$F$23:$F$74,"<="&D80,$G$23:$G$74,$D$94) -> 0 | F80: =SUMIFS($E$23:$E$74,$F$23:$F$74,">="&C80,$F$23:$F$74,"<="&D80,$G$23:$G$74,$D$94) -> 0 | G80: Nóminas , reembolso, servicio Contable
C81: 45866 | D81: 45869 | E81: =SUMIFS($D$23:$D$74,$F$23:$F$74,">="&C81,$F$23:$F$74,"<="&D81,$G$23:$G$74,$D$94) -> 0 | F81: =SUMIFS($E$23:$E$74,$F$23:$F$74,">="&C81,$F$23:$F$74,"<="&D81,$G$23:$G$74,$D$94) -> 0 | G81: GMF
C82: 45870 | D82: 45874 | E82: =SUMIFS($D$23:$D$74,$F$23:$F$74,">="&C82,$F$23:$F$74,"<="&D82,$G$23:$G$74,$D$94) -> 0 | F82: =SUMIFS($E$23:$E$74,$F$23:$F$74,">="&C82,$F$23:$F$74,"<="&D82,$G$23:$G$74,$D$94) -> 0 | G82: Polizas Safeguard ,Rimac y Mapfre
C83: TOTAL EGRESOS | E83: =SUM(E77:E82) -> 0 | F83: =SUM(F77:F82) -> 0
J86: =F79+'BCP SOLES BCP'!J259 -> 0
C88: Bancos | E88: ='BCP SOLES BCP'!$G$300+('BCP USD BCP'!$G$299*$D$6) -> 66338.36 | F88: ='BCP USD BCP'!$G$299+('BCP SOLES BCP'!$G$300/$D$6) -> 18659.53
C89: Gastos y costos Periodo 01 al 20 Julio | E89: =SUM(E77:E79) -> 0 | F89: =SUM(F77:F79) -> 0
C90: Saldo | E90: =E88-E89 -> 66338.36 | F90: =F88-F89 -> 18659.53
D93: Cancelado | E93: =SUMIFS($D$23:$D$74,$F$23:$F$74,">="&C77,$F$23:$F$74,"<="&D82,$G$23:$G$74,$D$93) -> 131060.34 | F93: =SUMIFS($E$23:$E$74,$F$23:$F$74,">="&$C$77,$F$23:$F$74,"<="&$D$82,$G$23:$G$74,$D$93) -> 40096.279
D94: Sin Pagar | E94: =SUMIFS($D$23:$D$74,$F$23:$F$74,">="&C77,$F$23:$F$74,"<="&D82,$G$23:$G$74,$D$94) -> 0 | F94: =SUMIFS($E$23:$E$74,$F$23:$F$74,">="&$C$77,$F$23:$F$74,"<="&$D$81,$G$23:$G$74,$D$94) -> 0
D95: Total Egresos | E95: =SUM(E93:E94) -> 131060.34 | F95: =SUM(F93:F94) -> 40096.279
D96: Validación | E96: =D70-E95 -> 0 | F96: =E70-F95 -> 0
D99: Flujo Caja | E99: =D72 -> 50406.747
D100: Libro Bancos | E100: ='BCP SOLES BCP'!G309+('BCP USD BCP'!G144*$D$6) -> 50406.751
D101: Diferencia Soles | E101: =E99-E100 -> -0.0042166315
D102: Diferencia USD | E102: =E101/D6 -> -0.0011860462
C129: Préstamo S&P Col a Perú desde la cuenta de Panamá
C131: Pago de renta IGV Junio | D131: =D29 -> 1540.35 | E131: =D131/$D$6 -> 433.26676 | F131: 45852
C132: Cristhian Portugal Segovia -Europortage-Gratificación | D132: =D50 -> 7630 | E132: =D132/$D$6 -> 2146.1521 | F132: 45852
C133: Davis Cesar oporto figueroa -Europortage-Gratificación | D133: =D51 -> 5086.67 | E133: =D133/$D$6 -> 1430.769 | F133: 45852
C134: Prestamo de reembolso cliente | D134: =#REF! -> #REF! | E134: =D134/$D$6 -> #REF! | F134: 45856
C135: Total | D135: =SUM(D131:D134) -> #REF! | E135: =SUM(E131:E134) -> #REF!
C137: Saldo BCP 14 de julio | D137: ='BCP SOLES BCP'!G261 -> 3857.511 | E137: =D137/'Diferencia Cambio S&P'!S23 -> 1096.5068
C138: Préstamo Panamá | D138: =D135-D137 -> #REF! | E138: =D138/'Diferencia Cambio S&P'!S23 -> #REF!
C139: Redondeado | D139: =E139*'Diferencia Cambio S&P'!S23 -> 13720.2 | E139: 3900 | F139: =E139-E138 -> #REF!
C140: Total | D140: =D139+D137 -> 17577.711 | E140: =E139+E137 -> 4996.5068

Sheet FLUJO CAJA AGOSTO
D1: 42400
D4: Fecha de Elaboración: | E4: 45870
C6: Tasa de cambio: | D6: 3.52
D7: AGOSTO
D8: VALOR S/ Sol | E8: VALOR USD
C9: BANCOS | D9: =SUBTOTAL(9,D10:D12) -> 50375.276 | E9: =SUBTOTAL(9,E10:E12) -> 14311.158
C10: Bancos S/ Soles | D10: ='BCP SOLES BCP'!$G$309 -> 40117.433 | E10: =D10/$D$6 -> 11396.998
C11: Bancos USD | D11: =E11*$D$6 -> 10187.443 | E11: ='BCP USD BCP'!$G$144 -> 2894.16
C12: Devolución de dinero Delivery | D12: =E12*$D$6 -> 70.4 | E12: 20
C13: CLIENTES | D13: =SUBTOTAL(9,D14:D20) -> 215690.38 | E13: =SUBTOTAL(9,E14:E20) -> 61866.332
B14: Pagado | C14: Client: Safeguard-Factura Nro EB01-02 ( Cliente) | D14: =E14*3.44 -> 4413.0728 | E14: =1282.87 -> 1282.87 | G14: =E14+E15+E16 -> 22849.1
B15: Pagado | C15: Client: Safeguard-Factura Nro EB01-03 ( Cliente) | D15: =E15*3.44 -> 60586.966 | E15: 17612.49
B16: Pagado | C16: Client: Safeguard-Factura Nro EB01-04 ( Cliente) | D16: =E16*3.44 -> 13600.866 | E16: 3953.74
D17: =6249.86-181.07+41.34 -> 6110.13 | E17: =D17/D6 -> 1735.8324
B18: Pagado | C18: Client: Europortage-Factura Nro EB01-24 | D18: =$E$18*'Diferencia Cambio S&P'!$K$23 -> 88163.618 | E18: 25117.84
B19: Pagado | C19: Client: Remotepass-Factura Nro EB01-25 | D19: =E19*$D$6 -> 23907.77 | E19: 6791.98
B20: Sin Pagar | C20: Client: Yonyou xinfushe cloud technology co., limited-Factura Nro EB01-26 | D20: =E20*$D$6 -> 18907.962 | E20: 5371.58
C21: TOTAL INGRESOS | D21: =SUBTOTAL(9,D9:D20) -> 266065.66 | E21: =SUBTOTAL(9,E9:E20) -> 76177.49
B24: CUENTAS X PAGAR MES | D24: AGOSTO | F24: Fecha de Elaboración: | J24: 45870
B25: Factura | C25: PROVEEDOR | D25: VALOR S/Sol | E25: VALOR USD | F25: Fecha vencimiento | G25: Estado | J25: KPI
C26: SEGURIDAD IGSS | D26: =SUBTOTAL(9,D27:D29) -> 9411.88 | E26: =SUBTOTAL(9,E27:E29) -> 2673.8295
B27: 2220819158 | C27: Planilla de declaración y pago de aportes previsional-Braydi Yusset Vera Neyra y Davis Cesar Oporto Figueroa | D27: =3271.3+623.91 -> 3895.21 | E27: =D27/$D$6 -> 1106.5938 | F27: 45875 | G27: Cancelado | H27: =IF(OR(G27="Sin pagar",G27="Pagar"),_xlfn.SINGLE(NETWORKDAYS($J$24,F27,FestivosPerú!$A$2:$A$15)),0) -> 0 | I27: =NETWORKDAYS($J$24,F27,FestivosPerú!$A$2:$A$15) -> 3 | J27: =H27 -> 0
B28: 2516822828 | C28: Planilla de declaración y pago de aportes previsional Christian Portugal Segovia y Luis renato Sanchez Martinez | D28: =1654.07+410.08 -> 2064.15 | E28: =D28/$D$6 -> 586.40625 | F28: 45875 | G28: Cancelado | H28: =IF(OR(G28="Sin pagar",G28="Pagar"),_xlfn.SINGLE(NETWORKDAYS($J$24,F28,FestivosPerú!$A$2:$A$15)),0) -> 0 | I28: =NETWORKDAYS($J$24,F28,FestivosPerú!$A$2:$A$15) -> 3 | J28: =H28 -> 0
B29: 2609515342 | C29: Planilla de declaración y pago de aportes previsional Christiams Hebert Valle Gomez -Remotepass | D29: =2688.5+764.02 -> 3452.52 | E29: =D29/$D$6 -> 980.82955 | F29: 45875 | G29: Cancelado | H29: =IF(OR(G29="Sin pagar",G29="Pagar"),_xlfn.SINGLE(NETWORKDAYS($J$24,F29,FestivosPerú!$A$2:$A$15)),0) -> 0 | I29: =NETWORKDAYS($J$24,F29,FestivosPerú!$A$2:$A$15) -> 3 | J29: =H29 -> 0
C30: IMPUESTOS | D30: =SUBTOTAL(9,D31:D32) -> 15813 | E30: =SUBTOTAL(9,E31:E32) -> 4492.3295 | J30: =H30 -> 0
C31: Plame Essalud y Renta de Quinta Categoría (Retención) | D31: 13751 | E31: =D31/$D$6 -> 3906.5341 | F31: 45882 | G31: Cancelado | H31: =IF(OR(G31="Sin pagar",G31="Pagar"),_xlfn.SINGLE(NETWORKDAYS($J$24,F31,FestivosPerú!$A$2:$A$15)),0) -> 0 | I31: =NETWORKDAYS($J$24,F31,FestivosPerú!$A$2:$A$15) -> 8 | J31: =H31 -> 0
C32: Pago de renta IGV Julio | D32: 2062 | E32: =D32/$D$6 -> 585.79545 | F32: 45887 | G32: Cancelado | H32: =IF(OR(G32="Sin pagar",G32="Pagar"),_xlfn.SINGLE(NETWORKDAYS($J$24,F32,FestivosPerú!$A$2:$A$15)),0) -> 0 | I32: =NETWORKDAYS($J$24,F32,FestivosPerú!$A$2:$A$15) -> 11 | J32: =H32 -> 0 | M32: Outsorcing contable
C33: SERVICIOS OUTSORCING CONTABLE | D33: =SUBTOTAL(9,D34:D36) -> 3448.5 | E33: =SUBTOTAL(9,E34:E36) -> 979.6875 | J33: =H33 -> 0
B34: E001-661 | C34: Outsourcing contable servicio agosto a SG- Avanza | D34: 1416 | E34: =D34/$D$6 -> 402.27273 | F34: 45898 | G34: Cancelado | H34: =IF(OR(G34="Sin pagar",G34="Pagar"),_xlfn.SINGLE(NETWORKDAYS($J$24,F34,FestivosPerú!$A$2:$A$15)),0) -> 0 | I34: =NETWORKDAYS($J$24,F34,FestivosPerú!$A$2:$A$15) -> 20 | J34: =H34 -> 0
B35: E001-659 | C35: Outsourcing contable servicio agosto a S&P- Avanza | D35: 1416 | E35: =D35/$D$6 -> 402.27273 | F35: 45898 | G35: Cancelado | H35: =IF(OR(G35="Sin pagar",G35="Pagar"),_xlfn.SINGLE(NETWORKDAYS($J$24,F35,FestivosPerú!$A$2:$A$15)),0) -> 0 | I35: =NETWORKDAYS($J$24,F35,FestivosPerú!$A$2:$A$15) -> 20 | J35: =H35 -> 0
B36: E001-666 | C36: Gestiones administrativoas y bancarias a S&P | D36: 616.5 | E36: =D36/$D$6 -> 175.14205 | F36: 45898 | G36: Cancelado | H36: =IF(OR(G36="Sin pagar",G36="Pagar"),_xlfn.SINGLE(NETWORKDAYS($J$24,F36,FestivosPerú!$A$2:$A$15)),0) -> 0 | I36: =NETWORKDAYS($J$24,F36,FestivosPerú!$A$2:$A$15) -> 20 | J36: =H36 -> 0
C37: PÓLIZAS DE VIDA Y SEGUROS MÉDICO | D37: =SUBTOTAL(9,D38:D51) -> 11176.11 | E37: =SUBTOTAL(9,E38:E51) -> 3175.0313
B38: S/N | C38: Seguros de vida Rimac -Davis oporto | D38: 1613 | E38: =D38/$D$6 -> 458.23864 | F38: 45871 | G38: Cancelado | H38: =IF(OR(G38="Sin pagar",G38="Pagar"),_xlfn.SINGLE(NETWORKDAYS($J$24,F38,FestivosPerú!$A$2:$A$15)),0) -> 0 | I38: =NETWORKDAYS($J$24,F38,FestivosPerú!$A$2:$A$15) -> 1 | J38: =H38 -> 0
B39: S/N | C39: SCTR Pensiones recibo 162413259 | D39: =354.03 -> 354.03 | E39: =D39/$D$6 -> 100.5767 | F39: 45873 | G39: Cancelado | H39: =IF(OR(G39="Sin pagar",G39="Pagar"),_xlfn.SINGLE(NETWORKDAYS($J$24,F39,FestivosPerú!$A$2:$A$15)),0) -> 0 | I39: =NETWORKDAYS($J$24,F39,FestivosPerú!$A$2:$A$15) -> 2 | J39: =H39 -> 0
B40: S/N | C40: SCTR Salud recibo 162413267 | D40: =343.72 -> 343.72 | E40: =D40/$D$6 -> 97.647727 | F40: 45873 | G40: Cancelado | H40: =IF(OR(G40="Sin pagar",G40="Pagar"),_xlfn.SINGLE(NETWORKDAYS($J$24,F40,FestivosPerú!$A$2:$A$15)),0) -> 0 | I40: =NETWORKDAYS($J$24,F40,FestivosPerú!$A$2:$A$15) -> 2 | J40: =H40 -> 0
B41: S/N | C41: Seguros de vida Ley recibo 162427159 | D41: =118 -> 118 | E41: =D41/$D$6 -> 33.522727 | F41: 45873 | G41: Cancelado | H41: =IF(OR(G41="Sin pagar",G41="Pagar"),_xlfn.SINGLE(NETWORKDAYS($J$24,F41,FestivosPerú!$A$2:$A$15)),0) -> 0 | I41: =NETWORKDAYS($J$24,F41,FestivosPerú!$A$2:$A$15) -> 2 | J41: =H41 -> 0
B42: S/N | C42: SCTR Salud recibo 162427441- Ingreso Yon you | D42: 179.6 | E42: =D42/$D$6 -> 51.022727 | F42: 45873 | G42: Cancelado | H42: =IF(OR(G42="Sin pagar",G42="Pagar"),_xlfn.SINGLE(NETWORKDAYS($J$24,F42,FestivosPerú!$A$2:$A$15)),0) -> 0 | I42: =NETWORKDAYS($J$24,F42,FestivosPerú!$A$2:$A$15) -> 2 | J42: =H42 -> 0
B43: S/N | C43: Seguros de vida Rimac -Braydi Vera-Julio | D43: 2508 | E43: =D43/$D$6 -> 712.5 | F43: 45891 | G43: Cancelado | H43: =IF(OR(G43="Sin pagar",G43="Pagar"),_xlfn.SINGLE(NETWORKDAYS($J$24,F43,FestivosPerú!$A$2:$A$15)),0) -> 0 | I43: =NETWORKDAYS($J$24,F43,FestivosPerú!$A$2:$A$15) -> 15 | J43: =H43 -> 0
B44: S/N | C44: Seguros de vida Rimac -Braydi Vera-Agosto | D44: 2503.11 | E44: =D44/$D$6 -> 711.1108 | F44: 45891 | G44: Cancelado | H44: =IF(OR(G44="Sin pagar",G44="Pagar"),_xlfn.SINGLE(NETWORKDAYS($J$24,F44,FestivosPerú!$A$2:$A$15)),0) -> 0 | I44: =NETWORKDAYS($J$24,F44,FestivosPerú!$A$2:$A$15) -> 15 | J44: =H44 -> 0
B45: S/N | C45: SCTR Salud Europartage recibo 163943236-Septiembre | D45: =343.72 -> 343.72 | E45: =D45/$D$6 -> 97.647727 | F45: 45895 | G45: Cancelado | H45: =IF(OR(G45="Sin pagar",G45="Pagar"),_xlfn.SINGLE(NETWORKDAYS($J$24,F45,FestivosPerú!$A$2:$A$15)),0) -> 0 | I45: =NETWORKDAYS($J$24,F45,FestivosPerú!$A$2:$A$15) -> 17 | J45: =H45 -> 0
B46: S/N | C46: SCTR Pensiones europortage recibo 163943233 -Sep | D46: =354.03 -> 354.03 | E46: =D46/$D$6 -> 100.5767 | F46: 45895 | G46: Cancelado | H46: =IF(OR(G46="Sin pagar",G46="Pagar"),_xlfn.SINGLE(NETWORKDAYS($J$24,F46,FestivosPerú!$A$2:$A$15)),0) -> 0 | I46: =NETWORKDAYS($J$24,F46,FestivosPerú!$A$2:$A$15) -> 17 | J46: =H46 -> 0
B47: S/N | C47: Seguros de vida Europortage Ley recibo 163943397 -Sep | D47: =118 -> 118 | E47: =D47/$D$6 -> 33.522727 | F47: 45895 | G47: Cancelado | H47: =IF(OR(G47="Sin pagar",G47="Pagar"),_xlfn.SINGLE(NETWORKDAYS($J$24,F47,FestivosPerú!$A$2:$A$15)),0) -> 0 | I47: =NETWORKDAYS($J$24,F47,FestivosPerú!$A$2:$A$15) -> 17 | J47: =H47 -> 0
B48: S/N | C48: SCTR Salud recibo 163943342- Yon you | D48: 179.6 | E48: =D48/$D$6 -> 51.022727 | F48: 45895 | G48: Cancelado | H48: =IF(OR(G48="Sin pagar",G48="Pagar"),_xlfn.SINGLE(NETWORKDAYS($J$24,F48,FestivosPerú!$A$2:$A$15)),0) -> 0 | I48: =NETWORKDAYS($J$24,F48,FestivosPerú!$A$2:$A$15) -> 17 | J48: =H48 -> 0
B49: S/N | C49: Seguros de vida Rimac -Davis oporto | D49: 1613 | E49: =D49/$D$6 -> 458.23864 | F49: 45902 | G49: Cancelado | H49: =IF(OR(G49="Sin pagar",G49="Pagar"),_xlfn.SINGLE(NETWORKDAYS($J$24,F49,FestivosPerú!$A$2:$A$15)),0) -> 0 | I49: =NETWORKDAYS($J$24,F49,FestivosPerú!$A$2:$A$15) -> 22 | J49: =H49 -> 0
B50: S/N | C50: Seguros de vida Europortage Ley recibo 164092598 -Sep-Ingreso | D50: 22.3 | E50: =D50/$D$6 -> 6.3352273 | F50: 45904 | G50: Cancelado | H50: =IF(OR(G50="Sin pagar",G50="Pagar"),_xlfn.SINGLE(NETWORKDAYS($J$24,F50,FestivosPerú!$A$2:$A$15)),0) -> 0 | I50: =NETWORKDAYS($J$24,F50,FestivosPerú!$A$2:$A$15) -> 24 | J50: =H50 -> 0
B51: S/N | C51: Seguros de vida Rimac -Andrés Felipe Uribe ( primer mes)- Europortage | D51: 926 | E51: =D51/$D$6 -> 263.06818 | F51: 45904 | G51: Cancelado | H51: =IF(OR(G51="Sin pagar",G51="Pagar"),_xlfn.SINGLE(NETWORKDAYS($J$24,F51,FestivosPerú!$A$2:$A$15)),0) -> 0 | I51: =NETWORKDAYS($J$24,F51,FestivosPerú!$A$2:$A$15) -> 24 | J51: =H51 -> 0
C52: COSTOS FINANCIEROS | D52: =SUBTOTAL(9,D53:D53) -> 318.9792 | E52: =SUBTOTAL(9,E53:E53) -> 90.619091
C53: COSTOS FINANCIEROS | D53: =('BCP SOLES BCP'!$F$307+'BCP SOLES BCP'!$F$311+'BCP SOLES BCP'!$F$313+'BCP SOLES BCP'!$F$315+'BCP SOLES BCP'!$F$331+'BCP SOLES BCP'!$F$333+'BCP SOLES BCP'!$F$355+'BCP SOLES BCP'!$F$357+'BCP SOLES BCP'!$F$359+'BCP SOLES BCP'!$F$361+'BCP SOLES BCP'!$F$363+'BCP SOLES BCP'!$F$365+'BCP SOLES BCP'!$F$367+'BCP SOLES BCP'!$F$378+'BCP SOLES BCP'!$F$381+'BCP SOLES BCP'!$F$382+'BCP SOLES BCP'!$F$383)+(('BCP USD BCP'!F153+'BCP USD BCP'!F157+'BCP USD BCP'!F158+'BCP USD BCP'!F159+'BCP USD BCP'!F166+'BCP USD BCP'!F167+'BCP USD BCP'!F168+'BCP USD BCP'!F169)*$D$6)+'BCP SOLES BCP'!$F$387 -> 318.9792 | E53: =$D$53/$D$6 -> 90.619091 | F53: 45900 | G53: Cancelado | H53: =IF(OR(G53="Sin pagar",G53="Pagar"),_xlfn.SINGLE(NETWORKDAYS($J$24,F53,FestivosPerú!$A$2:$A$15)),0) -> 0 | I53: =NETWORKDAYS($J$24,F53,FestivosPerú!$A$2:$A$15) -> 20 | J53: =H53 -> 0
C54: NÓMINAS CLIENTES S&P | D54: =SUBTOTAL(9,D55:D59) -> 59750.582 | E54: =SUBTOTAL(9,E55:E59) -> 16974.597
B55: Soles | C55: Braydi Yusset Vera Neira-Europortage | D55: 13974.66 | E55: =D55/$D$6 -> 3970.0739 | F55: 45897 | G55: Cancelado | H55: =IF(OR(G55="Sin pagar",G55="Pagar"),_xlfn.SINGLE(NETWORKDAYS($J$24,F55,FestivosPerú!$A$2:$A$15)),0) -> 0 | I55: =NETWORKDAYS($J$24,F55,FestivosPerú!$A$2:$A$15) -> 19 | J55: =H55 -> 0
B56: Soles | C56: Cristhian Portugal Segovia -Europortage | D56: 10903.29 | E56: =D56/$D$6 -> 3097.5256 | F56: 45897 | G56: Cancelado | H56: =IF(OR(G56="Sin pagar",G56="Pagar"),_xlfn.SINGLE(NETWORKDAYS($J$24,F56,FestivosPerú!$A$2:$A$15)),0) -> 0 | I56: =NETWORKDAYS($J$24,F56,FestivosPerú!$A$2:$A$15) -> 19 | J56: =H56 -> 0
B57: Soles | C57: Davis Cesar oporto figueroa -Europortage | D57: 10983.9 | E57: =D57/$D$6 -> 3120.4261 | F57: 45897 | G57: Cancelado | H57: =IF(OR(G57="Sin pagar",G57="Pagar"),_xlfn.SINGLE(NETWORKDAYS($J$24,F57,FestivosPerú!$A$2:$A$15)),0) -> 0 | I57: =NETWORKDAYS($J$24,F57,FestivosPerú!$A$2:$A$15) -> 19 | J57: =H57 -> 0 | M57: =SUM(D55:D58)+SUM(D61:D63) -> 63490.27
B58: Soles | C58: Luis Renato Sanchez Perez -Yon Yuo | D58: 10354.79 | E58: =D58/$D$6 -> 2941.7017 | F58: 45897 | G58: Cancelado | H58: =IF(OR(G58="Sin pagar",G58="Pagar"),_xlfn.SINGLE(NETWORKDAYS($J$24,F58,FestivosPerú!$A$2:$A$15)),0) -> 0 | I58: =NETWORKDAYS($J$24,F58,FestivosPerú!$A$2:$A$15) -> 19 | J58: =H58 -> 0
B59: USD | C59: Christiams Hebert Valle Gomez -Remotepass | D59: =E59*D6 -> 13533.942 | E59: 3844.87 | F59: 45897 | G59: Cancelado | H59: =IF(OR(G59="Sin pagar",G59="Pagar"),_xlfn.SINGLE(NETWORKDAYS($J$24,F59,FestivosPerú!$A$2:$A$15)),0) -> 0 | I59: =NETWORKDAYS($J$24,F59,FestivosPerú!$A$2:$A$15) -> 19 | J59: =H59 -> 0
C60: REEMBOLSO | D60: =SUBTOTAL(9,D61:D63) -> 17273.63 | E60: =SUBTOTAL(9,E61:E63) -> 4907.2812
C61: Reembolso Braydi Yusset Vera Neira-Europortage | D61: 3741.84 | E61: =D61/$D$6 -> 1063.0227 | F61: 45897 | G61: Cancelado | H61: =IF(OR(G61="Sin pagar",G61="Pagar"),_xlfn.SINGLE(NETWORKDAYS($J$24,F61,FestivosPerú!$A$2:$A$15)),0) -> 0 | I61: =NETWORKDAYS($J$24,F61,FestivosPerú!$A$2:$A$15) -> 19 | J61: =H61 -> 0
C62: Reembolso Cristhian Portugal Segovia -Europortage | D62: 8445.52 | E62: =D62/$D$6 -> 2399.2955 | F62: 45897 | G62: Cancelado | H62: =IF(OR(G62="Sin pagar",G62="Pagar"),_xlfn.SINGLE(NETWORKDAYS($J$24,F62,FestivosPerú!$A$2:$A$15)),0) -> 0 | I62: =NETWORKDAYS($J$24,F62,FestivosPerú!$A$2:$A$15) -> 19 | J62: =H62 -> 0
C63: Reembolso Davis Cesar oporto figueroa -Europortage | D63: 5086.27 | E63: =D63/$D$6 -> 1444.9631 | F63: 45897 | G63: Cancelado | H63: =IF(OR(G63="Sin pagar",G63="Pagar"),_xlfn.SINGLE(NETWORKDAYS($J$24,F63,FestivosPerú!$A$2:$A$15)),0) -> 0 | I63: =NETWORKDAYS($J$24,F63,FestivosPerú!$A$2:$A$15) -> 19 | J63: =H63 -> 0
C64: IMPREVISTO | D64: =SUBTOTAL(9,D65:D68) -> 1760.73 | E64: =SUBTOTAL(9,E65:E68) -> 5286.5376
C65: Envío de token a Bogotá a telecrédito | D65: =E65*D6 -> 281.6 | E65: 80 | F65: 45891 | G65: Cancelado | H65: =IF(OR(G65="Sin pagar",G65="Pagar"),_xlfn.SINGLE(NETWORKDAYS($J$24,F65,FestivosPerú!$A$2:$A$15)),0) -> 0 | I65: =NETWORKDAYS($J$24,F65,FestivosPerú!$A$2:$A$15) -> 15 | J65: =H65 -> 0
C66: Pago exámenes de ingreso Europortage-Pend Fac | D66: 151.63 | E66: =D66*$D$6 -> 533.7376 | F66: 45895 | G66: Cancelado | H66: =IF(OR(G66="Sin pagar",G66="Pagar"),_xlfn.SINGLE(NETWORKDAYS($J$24,F66,FestivosPerú!$A$2:$A$15)),0) -> 0 | I66: =NETWORKDAYS($J$24,F66,FestivosPerú!$A$2:$A$15) -> 17 | J66: =H66 -> 0
B67: E001-995 | C67: Consultora SVC SAC - Implementación del Sistema gestión SST | D67: 1327.5 | E67: =D67*$D$6 -> 4672.8 | F67: 45898 | G67: Cancelado | H67: =IF(OR(G67="Sin pagar",G67="Pagar"),_xlfn.SINGLE(NETWORKDAYS($J$24,F67,FestivosPerú!$A$2:$A$15)),0) -> 0 | I67: =NETWORKDAYS($J$24,F67,FestivosPerú!$A$2:$A$15) -> 20 | J67: =H67 -> 0
C68: Devolucion de dinero a S&P Panamá | D68: =E68*D6 -> 0 | E68: =3900*0 -> 0 | F68: 45900 | G68: Cancelado | H68: =IF(OR(G68="Sin pagar",G68="Pagar"),_xlfn.SINGLE(NETWORKDAYS($J$24,F68,FestivosPerú!$A$2:$A$15)),0) -> 0 | I68: =NETWORKDAYS($J$24,F68,FestivosPerú!$A$2:$A$15) -> 20 | J68: =H68 -> 0
C69: COSTOS FINANCIEROS SAFEGUARD | D69: =SUBTOTAL(9,D70:D70) -> 2105.438 | E69: =SUBTOTAL(9,E70:E70) -> 598.1358
C70: COSTOS FINANCIEROS | D70: =('BCP SOLES BCP'!$F$320+'BCP SOLES BCP'!F327+'BCP SOLES BCP'!$F$329+'BCP SOLES BCP'!$F$326+'BCP SOLES BCP'!$F$337+'BCP SOLES BCP'!$F$339+'BCP SOLES BCP'!$F$341+'BCP SOLES BCP'!$F$344+'BCP SOLES BCP'!F347+'BCP SOLES BCP'!$F$348)+(('BCP USD BCP'!F149*'FLUJO CAJA AGOSTO'!$D$6))+2064.15 -> 2105.438 | E70: =$D$70/$D$6 -> 598.1358 | F70: 45900 | G70: Sin Pagar | H70: =IF(OR(G70="Sin pagar",G70="Pagar"),_xlfn.SINGLE(NETWORKDAYS($J$24,F70,FestivosPerú!$A$2:$A$15)),0) -> 20 | I70: =NETWORKDAYS($J$24,F70,FestivosPerú!$A$2:$A$15) -> 20 | J70: =H70 -> 20
C71: GASTOS SAFEGUARD PERÚ | D71: =SUBTOTAL(9,D72:D83) -> 3495.97 | E71: =SUBTOTAL(9,E72:E83) -> 993.1733
B72: S/N | C72: Planilla de declaración y pago de aportes previsional-Fiorella Maribel Chavez Torriani-Habitat | D72: =(401.94+0.8)+(55.07+0.11) -> 457.92 | E72: =D72/$D$6 -> 130.09091 | F72: 45882 | G72: Cancelado | H72: =IF(OR(G72="Sin pagar",G72="Pagar"),_xlfn.SINGLE(NETWORKDAYS($J$24,F72,FestivosPerú!$A$2:$A$15)),0) -> 0 | I72: =NETWORKDAYS($J$24,F72,FestivosPerú!$A$2:$A$15) -> 8 | J72: =H72 -> 0
B73: S/N | C73: Planilla de declaración y pago de aportes previsional-Claudia Anabel Vasquez Cardenas-Integra | D73: =(347.68+0.7)+(101.52+0.2) -> 450.1 | E73: =D73/$D$6 -> 127.86932 | F73: 45882 | G73: Cancelado | H73: =IF(OR(G73="Sin pagar",G73="Pagar"),_xlfn.SINGLE(NETWORKDAYS($J$24,F73,FestivosPerú!$A$2:$A$15)),0) -> 0 | I73: =NETWORKDAYS($J$24,F73,FestivosPerú!$A$2:$A$15) -> 8 | J73: =H73 -> 0
B74: S/N | C74: Envio de dinero a Selma Avanza para rendondear el valor y pagar planilla de aportes previsional | D74: 11.98 | E74: =D74/$D$6 -> 3.4034091 | F74: 45882 | G74: Cancelado | H74: =IF(OR(G74="Sin pagar",G74="Pagar"),_xlfn.SINGLE(NETWORKDAYS($J$24,F74,FestivosPerú!$A$2:$A$15)),0) -> 0 | I74: =NETWORKDAYS($J$24,F74,FestivosPerú!$A$2:$A$15) -> 8 | J74: =H74 -> 0
B75: S/N | C75: Plame Essalud y Renta de Quinta Categoría (Retención)-SG | D75: 675 | E75: =D75/$D$6 -> 191.76136 | F75: 45883 | G75: Cancelado | H75: =IF(OR(G75="Sin pagar",G75="Pagar"),_xlfn.SINGLE(NETWORKDAYS($J$24,F75,FestivosPerú!$A$2:$A$15)),0) -> 0 | I75: =NETWORKDAYS($J$24,F75,FestivosPerú!$A$2:$A$15) -> 9 | J75: =H75 -> 0
C76: Pago de renta IGV Julio | D76: 1536 | E76: =D76/$D$6 -> 436.36364 | F76: 45888 | G76: Cancelado | H76: =IF(OR(G76="Sin pagar",G76="Pagar"),_xlfn.SINGLE(NETWORKDAYS($J$24,F76,FestivosPerú!$A$2:$A$15)),0) -> 0 | I76: =NETWORKDAYS($J$24,F76,FestivosPerú!$A$2:$A$15) -> 12 | J76: =H76 -> 0 | M76: Outsorcing contable
C77: Penny test Angel Augusto Allauca Garcia | D77: 1 | E77: =D77/$D$6 -> 0.28409091 | F77: 45890 | G77: Cancelado | H77: =IF(OR(G77="Sin pagar",G77="Pagar"),_xlfn.SINGLE(NETWORKDAYS($J$24,F77,FestivosPerú!$A$2:$A$15)),0) -> 0 | I77: =NETWORKDAYS($J$24,F77,FestivosPerú!$A$2:$A$15) -> 14 | J77: =H77 -> 0
C78: Penny test Juan Ulises Aguirre Tacunan | D78: 1 | E78: =D78/$D$6 -> 0.28409091 | F78: 45890 | G78: Cancelado | H78: =IF(OR(G78="Sin pagar",G78="Pagar"),_xlfn.SINGLE(NETWORKDAYS($J$24,F78,FestivosPerú!$A$2:$A$15)),0) -> 0 | I78: =NETWORKDAYS($J$24,F78,FestivosPerú!$A$2:$A$15) -> 14 | J78: =H78 -> 0
C79: Penny test Esteban Gonzalo Arias Suárez | D79: 5.8 | E79: =D79/$D$6 -> 1.6477273 | F79: 45890 | G79: Cancelado | H79: =IF(OR(G79="Sin pagar",G79="Pagar"),_xlfn.SINGLE(NETWORKDAYS($J$24,F79,FestivosPerú!$A$2:$A$15)),0) -> 0 | I79: =NETWORKDAYS($J$24,F79,FestivosPerú!$A$2:$A$15) -> 14 | J79: =H79 -> 0
C80: Penny test David Eduardo Estela Guzman | D80: 5.8 | E80: =D80/$D$6 -> 1.6477273 | F80: 45891 | G80: Cancelado | H80: =IF(OR(G80="Sin pagar",G80="Pagar"),_xlfn.SINGLE(NETWORKDAYS($J$24,F80,FestivosPerú!$A$2:$A$15)),0) -> 0 | I80: =NETWORKDAYS($J$24,F80,FestivosPerú!$A$2:$A$15) -> 15 | J80: =H80 -> 0
B81: 2871306 | C81: Poliza vida Ley Fiorella Chavez - Claudia Anabel Vasquez | D81: 55.34 | E81: =D81/$D$6 -> 15.721591 | F81: 45897 | G81: Cancelado | H81: =IF(OR(G81="Sin pagar",G81="Pagar"),_xlfn.SINGLE(NETWORKDAYS($J$24,F81,FestivosPerú!$A$2:$A$15)),0) -> 0 | I81: =NETWORKDAYS($J$24,F81,FestivosPerú!$A$2:$A$15) -> 19 | J81: =H81 -> 0
B82: 2869454 | C82: Poliza vida Ley Juan Aguirre-Angel Allauca- Esteban Arias | D82: 226.03 | E82: =D82/$D$6 -> 64.213068 | F82: 45897 | G82: Cancelado | H82: =IF(OR(G82="Sin pagar",G82="Pagar"),_xlfn.SINGLE(NETWORKDAYS($J$24,F82,FestivosPerú!$A$2:$A$15)),0) -> 0 | I82: =NETWORKDAYS($J$24,F82,FestivosPerú!$A$2:$A$15) -> 19 | J82: =H82 -> 0
B83: 2855245 | C83: Poliza vida Ley David Giancarlo Estela Guzman | D83: 70 | E83: =D83/$D$6 -> 19.886364 | F83: 45897 | G83: Cancelado | H83: =IF(OR(G83="Sin pagar",G83="Pagar"),_xlfn.SINGLE(NETWORKDAYS($J$24,F83,FestivosPerú!$A$2:$A$15)),0) -> 0 | I83: =NETWORKDAYS($J$24,F83,FestivosPerú!$A$2:$A$15) -> 19 | J83: =H83 -> 0
C84: NÓMINAS -SAFEGUARD | D84: =SUBTOTAL(9,D85:D90) -> 46321.129 | E84: =SUBTOTAL(9,E85:E90) -> 13159.412
C85: Fiorella maribel chavez torriani | D85: 4749.859 | E85: =D85/$D$6 -> 1349.3917 | F85: 45896 | G85: Cancelado | H85: =IF(OR(G85="Sin pagar",G85="Pagar"),_xlfn.SINGLE(NETWORKDAYS($J$24,F85,FestivosPerú!$A$2:$A$15)),0) -> 0 | I85: =NETWORKDAYS($J$24,F85,FestivosPerú!$A$2:$A$15) -> 18 | J85: =H85 -> 0
C86: Claudia anabel vasquez cardenas | D86: 8458.3101 | E86: =D86/$D$6 -> 2402.929 | F86: 45897 | G86: Cancelado | H86: =IF(OR(G86="Sin pagar",G86="Pagar"),_xlfn.SINGLE(NETWORKDAYS($J$24,F86,FestivosPerú!$A$2:$A$15)),0) -> 0 | I86: =NETWORKDAYS($J$24,F86,FestivosPerú!$A$2:$A$15) -> 19 | J86: =H86 -> 0
C87: Juan ulises aguirre tacunan | D87: 10782.57 | E87: =D87/$D$6 -> 3063.2301 | F87: 45896 | G87: Cancelado | H87: =IF(OR(G87="Sin pagar",G87="Pagar"),_xlfn.SINGLE(NETWORKDAYS($J$24,F87,FestivosPerú!$A$2:$A$15)),0) -> 0 | I87: =NETWORKDAYS($J$24,F87,FestivosPerú!$A$2:$A$15) -> 18 | J87: =H87 -> 0
C88: Angel augusto allauca garcia | D88: 11437.26 | E88: =D88/$D$6 -> 3249.2216 | F88: 45896 | G88: Cancelado | H88: =IF(OR(G88="Sin pagar",G88="Pagar"),_xlfn.SINGLE(NETWORKDAYS($J$24,F88,FestivosPerú!$A$2:$A$15)),0) -> 0 | I88: =NETWORKDAYS($J$24,F88,FestivosPerú!$A$2:$A$15) -> 18 | J88: =H88 -> 0
C89: Esteban gonzalo arias suarez | D89: 5577.54 | E89: =D89/$D$6 -> 1584.5284 | F89: 45896 | G89: Cancelado | H89: =IF(OR(G89="Sin pagar",G89="Pagar"),_xlfn.SINGLE(NETWORKDAYS($J$24,F89,FestivosPerú!$A$2:$A$15)),0) -> 0 | I89: =NETWORKDAYS($J$24,F89,FestivosPerú!$A$2:$A$15) -> 18 | J89: =H89 -> 0
C90: David eduardo estela guzman | D90: 5315.59 | E90: =D90/$D$6 -> 1510.1108 | F90: 45896 | G90: Cancelado | H90: =IF(OR(G90="Sin pagar",G90="Pagar"),_xlfn.SINGLE(NETWORKDAYS($J$24,F90,FestivosPerú!$A$2:$A$15)),0) -> 0 | I90: =NETWORKDAYS($J$24,F90,FestivosPerú!$A$2:$A$15) -> 18 | J90: =H90 -> 0
C91: TOTAL EGRESOS | D91: =SUBTOTAL(9,D26:D90) -> 170875.95 | E91: =SUBTOTAL(9,E26:E90) -> 53330.634
C93: SALDO | D93: =D21-D91 -> 95189.711 | E93: =E21-E91 -> 22846.857
C94: % | D94: =IF($D$21=0,0,D93/$D$21) -> 0.35776775 | E94: =IF($E$21=0,0,E93/$E$21) -> 0.29991611
C97: 45870 | D97: 45872 | E97: =SUMIFS($D$25:$D$95,$F$25:$F$95,">="&C97,$F$25:$F$95,"<="&D97,$G$25:$G$95,$D$119) -> 0 | F97: =SUMIFS($D$25:$D$95,$F$25:$F$95,">="&D97,$F$25:$F$95,"<="&E97,$G$25:$G$95,$D$119) -> 0
C98: 45873 | D98: 45874 | E98: =SUMIFS($D$25:$D$95,$F$25:$F$95,">="&C98,$F$25:$F$95,"<="&D98,$G$25:$G$95,$D$119) -> 0 | F98: =SUMIFS($E$25:$E$95,$F$25:$F$95,">="&C98,$F$25:$F$95,"<="&D98,$G$25:$G$95,$D$119) -> 0
C99: 45875 | D99: 45875 | E99: =SUMIFS($D$25:$D$95,$F$25:$F$95,">="&C99,$F$25:$F$95,"<="&D99,$G$25:$G$95,$D$119) -> 0 | F99: =SUMIFS($E$25:$E$95,$F$25:$F$95,">="&C99,$F$25:$F$95,"<="&D99,$G$25:$G$95,$D$119) -> 0 | G99: Seguridad social IGSS
C100: 45876 | D100: 45879 | E100: =SUMIFS($D$25:$D$95,$F$25:$F$95,">="&C100,$F$25:$F$95,"<="&D100,$G$25:$G$95,$D$119) -> 0 | F100: =SUMIFS($E$25:$E$95,$F$25:$F$95,">="&C100,$F$25:$F$95,"<="&D100,$G$25:$G$95,$D$119) -> 0 | G100: Pólizas Previstas
C101: 45880 | D101: 45882 | E101: =SUMIFS($D$25:$D$95,$F$25:$F$95,">="&C101,$F$25:$F$95,"<="&D101,$G$25:$G$95,$D$119) -> 0 | F101: =SUMIFS($E$25:$E$95,$F$25:$F$95,">="&C101,$F$25:$F$95,"<="&D101,$G$25:$G$95,$D$119) -> 0 | G101: AFP Safeguard-Plame SG-Rimac Braydi Vera
C102: 45883 | D102: 45883 | E102: =SUMIFS($D$25:$D$95,$F$25:$F$95,">="&C102,$F$25:$F$95,"<="&D102,$G$25:$G$95,$D$119) -> 0 | F102: =SUMIFS($E$25:$E$95,$F$25:$F$95,">="&C102,$F$25:$F$95,"<="&D102,$G$25:$G$95,$D$119) -> 0 | G102: Plame Essalud y Renta de Quinta Categoría (Retención) renta Julio
C103: 45887 | D103: 45890 | E103: =SUMIFS($D$25:$D$95,$F$25:$F$95,">="&C103,$F$25:$F$95,"<="&D103,$G$25:$G$95,$D$119) -> 0 | F103: =SUMIFS($E$25:$E$95,$F$25:$F$95,">="&C103,$F$25:$F$95,"<="&D103,$G$25:$G$95,$D$119) -> 0
C104: 45891 | D104: 45891 | E104: =SUMIFS($D$25:$D$95,$F$25:$F$95,">="&C104,$F$25:$F$95,"<="&D104,$G$25:$G$95,$D$119) -> 0 | F104: =SUMIFS($E$25:$E$95,$F$25:$F$95,">="&C104,$F$25:$F$95,"<="&D104,$G$25:$G$95,$D$119) -> 0 | G104: Outsourcing contable servicio
C105: 45892 | D105: 45893 | E105: =SUMIFS($D$25:$D$95,$F$25:$F$95,">="&C105,$F$25:$F$95,"<="&D105,$G$25:$G$95,$D$119) -> 0 | F105: =SUMIFS($E$25:$E$95,$F$25:$F$95,">="&C105,$F$25:$F$95,"<="&D105,$G$25:$G$95,$D$119) -> 0
C106: 45894 | D106: 45900 | E106: =SUMIFS($D$25:$D$95,$F$25:$F$95,">="&C106,$F$25:$F$95,"<="&D106,$G$25:$G$95,$D$119) -> 2105.438 | F106: =SUMIFS($E$25:$E$95,$F$25:$F$95,">="&C106,$F$25:$F$95,"<="&D106,$G$25:$G$95,$D$119) -> 598.1358
C107: 45901 | D107: 45907 | E107: =SUMIFS($D$25:$D$95,$F$25:$F$95,">="&C107,$F$25:$F$95,"<="&D107,$G$25:$G$95,$D$119) -> 0 | F107: =SUMIFS($E$25:$E$95,$F$25:$F$95,">="&C107,$F$25:$F$95,"<="&D107,$G$25:$G$95,$D$119) -> 0
C108: TOTAL EGRESOS | E108: =SUM(E97:E107) -> 2105.438 | F108: =SUM(F97:F107) -> 598.1358
...

Sheet FLUJO CAJA SEPTIEMBRE
D1: 42400
D4: Fecha de Elaboración: | E4: 45901
C6: Tasa de cambio: | D6: 3.52
D7: SEPTIEMBRE
D8: VALOR S/ Sol | E8: VALOR USD
C9: BANCOS | D9: =SUBTOTAL(9,D10:D12) -> 102958.87 | E9: =SUBTOTAL(9,E10:E12) -> 29249.678
C10: Bancos S/ Soles | D10: ='BCP SOLES BCP'!$G$389-2746.43 -> 58538.413 | E10: =D10/$D$6 -> 16630.231
C11: Bancos USD | D11: =E11*$D$6 -> 35969.014 | E11: ='BCP USD BCP'!$G$172 -> 10218.47
C12: Devolución nómina mes de Septiembre Claudia Anabel Vasquez Cardenas -Safeguard | D12: 8451.44 | E12: =D12/$D$6 -> 2400.9773
C13: CLIENTES | D13: =SUBTOTAL(9,D14:D21) -> 374773.8 | E13: =SUBTOTAL(9,E14:E21) -> 106469.83
B14: Pagado | C14: Client: Safeguard-Factura Nro EB01-05 ( Cliente) | D14: =E14*$D$6 -> 13972.886 | E14: 3969.57 | J14: Facturado | M14: Pagado | N14: Saldo Deuda
B15: Sin Pagar | C15: Client: Safeguard-Factura Nro EB01-06 ( Cliente)-Abono | D15: =E15*$D$6 -> 206344.05 | E15: 58620.47 | G15: SG Cliente | J15: 67639.08 | M15: =SUM(E14:E16) -> 63639.52 | N15: =J15-M15 -> 3999.56 | O15: Este valor no se recibe ya que se consigna a la cuenta de global para pagar la guardiana
B16: Pagado | C16: Client: Safeguard-Factura Nro EB01-07( Cliente) | D16: =E16*$D$6 -> 3694.1696 | E16: 1049.48
B17: Pagado | C17: Client: Europortage-Factura Nro 001 | D17: =E17*$D$6 -> 100105.24 | E17: 28438.99 | J17: X recibir de los worke | M17: 63669.51 | N17: Descuento GMF | O17: =M17-M15 -> 29.99
B18: Pagado | C18: Client: Remotepass-Factura Nro 002 | D18: =E18*$D$6 -> 24241.994 | E18: 6886.93 | J18: Guardiana | M18: 3969.57
B19: Pagado | C19: Client: Yonyou xinfushe cloud technology co., limited-Factura Nro 003 | D19: =E19*$D$6 -> 19094.24 | E19: 5424.5 | J19: Total | M19: =SUM(M17:M18) -> 67639.08
B20: Pagado | C20: Client: Europortage-Factura Nro 004-Aidicional | D20: =E20*$D$6 -> 1953.4592 | E20: 554.96
B21: Pagado | C21: Client: Yonyou xinfushe cloud technology co., limited-Factura Nro 005 | D21: =E21*$D$6 -> 5367.7536 | E21: 1524.93
C22: TOTAL INGRESOS | D22: =SUBTOTAL(9,D9:D21) -> 477732.67 | E22: =SUBTOTAL(9,E9:E21) -> 135719.51
B25: CUENTAS X PAGAR MES | D25: SEPTIEMBRE | F25: Fecha de Elaboración: | J25: 45901
B26: Factura | C26: PROVEEDOR | D26: VALOR S/Sol | E26: VALOR USD | F26: Fecha vencimiento | G26: Estado | J26: KPI
C27: SEGURIDAD IGSS | D27: =SUBTOTAL(9,D28:D30) -> 9411.88 | E27: =SUBTOTAL(9,E28:E30) -> 2673.8295
B28: 2221299016 | C28: Planilla de declaración y pago de aportes previsional-Braydi Yusset Vera Neyra y Davis Cesar Oporto Figueroa | D28: =3271.3+623.91 -> 3895.21 | E28: =D28/$D$6 -> 1106.5938 | F28: 45905 | G28: Cancelado | H28: =IF(OR(G28="Sin pagar",G28="Pagar"),_xlfn.SINGLE(NETWORKDAYS($J$25,F28,FestivosPerú!$A$2:$A$15)),0) -> 0 | I28: =NETWORKDAYS($J$25,F28,FestivosPerú!$A$2:$A$15) -> 5 | J28: =H28 -> 0
B29: 2517102692 | C29: Planilla de declaración y pago de aportes previsional Christian Portugal Segovia y Luis renato Sanchez Martinez | D29: 3452.52 | E29: =D29/$D$6 -> 980.82955 | F29: 45905 | G29: Cancelado | H29: =IF(OR(G29="Sin pagar",G29="Pagar"),_xlfn.SINGLE(NETWORKDAYS($J$25,F29,FestivosPerú!$A$2:$A$15)),0) -> 0 | I29: =NETWORKDAYS($J$25,F29,FestivosPerú!$A$2:$A$15) -> 5 | J29: =H29 -> 0
B30: 2609613414 | C30: Planilla de declaración y pago de aportes previsional Christiams Hebert Valle Gomez -Remotepass | D30: 2064.15 | E30: =D30/$D$6 -> 586.40625 | F30: 45905 | G30: Cancelado | H30: =IF(OR(G30="Sin pagar",G30="Pagar"),_xlfn.SINGLE(NETWORKDAYS($J$25,F30,FestivosPerú!$A$2:$A$15)),0) -> 0 | I30: =NETWORKDAYS($J$25,F30,FestivosPerú!$A$2:$A$15) -> 5 | J30: =H30 -> 0
C31: IMPUESTOS | D31: =SUBTOTAL(9,D32:D33) -> 14224 | E31: =SUBTOTAL(9,E32:E33) -> 4040.9091 | J31: =H31 -> 0
C32: Plame Essalud y Renta de Quinta Categoría (Retención) | D32: 14185 | E32: =D32/$D$6 -> 4029.8295 | F32: 45915 | G32: Cancelado | H32: =IF(OR(G32="Sin pagar",G32="Pagar"),_xlfn.SINGLE(NETWORKDAYS($J$25,F32,FestivosPerú!$A$2:$A$15)),0) -> 0 | I32: =NETWORKDAYS($J$25,F32,FestivosPerú!$A$2:$A$15) -> 11 | J32: =H32 -> 0
C33: Pago de renta IGV agosto | D33: 39 | E33: =D33/$D$6 -> 11.079545 | F33: 45915 | G33: Cancelado | H33: =IF(OR(G33="Sin pagar",G33="Pagar"),_xlfn.SINGLE(NETWORKDAYS($J$25,F33,FestivosPerú!$A$2:$A$15)),0) -> 0 | I33: =NETWORKDAYS($J$25,F33,FestivosPerú!$A$2:$A$15) -> 11 | J33: =H33 -> 0 | M33: Outsorcing contable
C34: SERVICIOS OUTSORCING CONTABLE | D34: =SUBTOTAL(9,D35:D36) -> 2832 | E34: =SUBTOTAL(9,E35:E36) -> 804.54545 | J34: =H34 -> 0
B35: E001-679 | C35: Outsourcing contable servicio septiembre a SG- Avanza | D35: 1416 | E35: =D35/$D$6 -> 402.27273 | F35: 45929 | G35: Cancelado | H35: =IF(OR(G35="Sin pagar",G35="Pagar"),_xlfn.SINGLE(NETWORKDAYS($J$25,F35,FestivosPerú!$A$2:$A$15)),0) -> 0 | I35: =NETWORKDAYS($J$25,F35,FestivosPerú!$A$2:$A$15) -> 21 | J35: =H35 -> 0
B36: E001-682 | C36: Outsourcing contable servicio septiembre a S&P- Avanza | D36: 1416 | E36: =D36/$D$6 -> 402.27273 | F36: 45929 | G36: Cancelado | H36: =IF(OR(G36="Sin pagar",G36="Pagar"),_xlfn.SINGLE(NETWORKDAYS($J$25,F36,FestivosPerú!$A$2:$A$15)),0) -> 0 | I36: =NETWORKDAYS($J$25,F36,FestivosPerú!$A$2:$A$15) -> 21 | J36: =H36 -> 0
C37: PÓLIZAS DE VIDA Y SEGUROS MÉDICO | D37: =SUBTOTAL(9,D38:D45) -> 5173.07 | E37: =SUBTOTAL(9,E38:E45) -> 1469.6222
B38: S/N | C38: Seguros de vida Rimac -Davis oporto-Revisa si hay factura | D38: 1613 | E38: =D38/$D$6 -> 458.23864 | F38: 45902 | G38: Cancelado | H38: =IF(OR(G38="Sin pagar",G38="Pagar"),_xlfn.SINGLE(NETWORKDAYS($J$25,F38,FestivosPerú!$A$2:$A$15)),0) -> 0 | I38: =NETWORKDAYS($J$25,F38,FestivosPerú!$A$2:$A$15) -> 2 | J38: Revisa RIMAC
B39: S/N | C39: Seguros de vida Europortage Ley recibo 164092598 -Sep-Ingreso | D39: 22.3 | E39: =D39/$D$6 -> 6.3352273 | F39: 45904 | G39: Cancelado | H39: =IF(OR(G39="Sin pagar",G39="Pagar"),_xlfn.SINGLE(NETWORKDAYS($J$25,F39,FestivosPerú!$A$2:$A$15)),0) -> 0 | I39: =NETWORKDAYS($J$25,F39,FestivosPerú!$A$2:$A$15) -> 4 | J39: =H39 -> 0
B40: S/N | C40: Seguros de vida Rimac -Andrés Felipe Uribe ( primer mes)- Europortage Septiembre | D40: 926 | E40: =D40/$D$6 -> 263.06818 | F40: 45904 | G40: Cancelado | H40: =IF(OR(G40="Sin pagar",G40="Pagar"),_xlfn.SINGLE(NETWORKDAYS($J$25,F40,FestivosPerú!$A$2:$A$15)),0) -> 0 | I40: =NETWORKDAYS($J$25,F40,FestivosPerú!$A$2:$A$15) -> 4 | J40: =H40 -> 0
B41: S/N | C41: SCTR Salud Europartage recibo 164654347-Octubre | D41: 345.06 | E41: =D41/$D$6 -> 98.028409 | F41: 45924 | G41: Cancelado | H41: =IF(OR(G41="Sin pagar",G41="Pagar"),_xlfn.SINGLE(NETWORKDAYS($J$25,F41,FestivosPerú!$A$2:$A$15)),0) -> 0 | I41: =NETWORKDAYS($J$25,F41,FestivosPerú!$A$2:$A$15) -> 18 | J41: =H41 -> 0
B42: S/N | C42: SCTR Pensiones europortage recibo 164654343 -Octubre | D42: 355.41 | E42: =D42/$D$6 -> 100.96875 | F42: 45924 | G42: Cancelado | H42: =IF(OR(G42="Sin pagar",G42="Pagar"),_xlfn.SINGLE(NETWORKDAYS($J$25,F42,FestivosPerú!$A$2:$A$15)),0) -> 0 | I42: =NETWORKDAYS($J$25,F42,FestivosPerú!$A$2:$A$15) -> 18 | J42: =H42 -> 0
B43: S/N | C43: Seguros de vida Europortage Ley recibo 164654721 -Oct | D43: =118 -> 118 | E43: =D43/$D$6 -> 33.522727 | F43: 45924 | G43: Cancelado | H43: =IF(OR(G43="Sin pagar",G43="Pagar"),_xlfn.SINGLE(NETWORKDAYS($J$25,F43,FestivosPerú!$A$2:$A$15)),0) -> 0 | I43: =NETWORKDAYS($J$25,F43,FestivosPerú!$A$2:$A$15) -> 18 | J43: =H43 -> 0
B44: S/N | C44: SCTR Salud recibo 164654485- Yon you-Oct | D44: 180.3 | E44: =D44/$D$6 -> 51.221591 | F44: 45924 | G44: Cancelado | H44: =IF(OR(G44="Sin pagar",G44="Pagar"),_xlfn.SINGLE(NETWORKDAYS($J$25,F44,FestivosPerú!$A$2:$A$15)),0) -> 0 | I44: =NETWORKDAYS($J$25,F44,FestivosPerú!$A$2:$A$15) -> 18 | J44: =H44 -> 0
B45: S/N | C45: Seguros de vida Rimac -Davis oporto | D45: 1613 | E45: =D45/$D$6 -> 458.23864 | F45: 45932 | G45: Cancelado | H45: =IF(OR(G45="Sin pagar",G45="Pagar"),_xlfn.SINGLE(NETWORKDAYS($J$25,F45,FestivosPerú!$A$2:$A$15)),0) -> 0 | I45: =NETWORKDAYS($J$25,F45,FestivosPerú!$A$2:$A$15) -> 24 | J45: =H45 -> 0
C46: COSTOS FINANCIEROS | D46: =SUBTOTAL(9,D47:D47) -> 368.32025 | E46: =SUBTOTAL(9,E47:E47) -> 104.63644
C47: COSTOS FINANCIEROS | D47: =(('BCP USD BCP'!$F$172+'BCP USD BCP'!$F$178+'BCP USD BCP'!$F$182+'BCP USD BCP'!$F$184+'BCP USD BCP'!$F$185+'BCP USD BCP'!$F$192+'BCP USD BCP'!$F$194+'BCP USD BCP'!$F$195+'BCP USD BCP'!$F$198+'BCP USD BCP'!$F$199+'BCP USD BCP'!$F$201+'BCP USD BCP'!$F$202+6.5)*$D$6)+(('BCP SOLES BCP'!F387+'BCP SOLES BCP'!F400+'BCP SOLES BCP'!F401+'BCP SOLES BCP'!F428+'BCP SOLES BCP'!F429+'BCP SOLES BCP'!F455+'BCP SOLES BCP'!F457+'BCP SOLES BCP'!F459+'BCP SOLES BCP'!F461+'BCP SOLES BCP'!F463+'BCP SOLES BCP'!F465+'BCP SOLES BCP'!F467+'BCP SOLES BCP'!F469+'BCP SOLES BCP'!F471+'BCP SOLES BCP'!F474+20.25)) -> 368.32025 | E47: =$D$47/$D$6 -> 104.63644 | F47: 45930 | G47: Cancelado | H47: =IF(OR(G47="Sin pagar",G47="Pagar"),_xlfn.SINGLE(NETWORKDAYS($J$25,F47,FestivosPerú!$A$2:$A$15)),0) -> 0 | I47: =NETWORKDAYS($J$25,F47,FestivosPerú!$A$2:$A$15) -> 22 | J47: =H47 -> 0
C48: NÓMINAS CLIENTES S&P | D48: =SUBTOTAL(9,D49:D54) -> 69178.878 | E48: =SUBTOTAL(9,E49:E54) -> 19653.09
B49: Soles | C49: Braydi Yusset Vera Neira-Europortage | D49: 12509.14 | E49: =D49/$D$6 -> 3553.7331 | F49: 45926 | G49: Cancelado | H49: =IF(OR(G49="Sin pagar",G49="Pagar"),_xlfn.SINGLE(NETWORKDAYS($J$25,F49,FestivosPerú!$A$2:$A$15)),0) -> 0 | I49: =NETWORKDAYS($J$25,F49,FestivosPerú!$A$2:$A$15) -> 20 | J49: =H49 -> 0
B50: Soles | C50: Cristhian Portugal Segovia -Europortage | D50: 10250.391 | E50: =D50/$D$6 -> 2912.043 | F50: 45926 | G50: Cancelado | H50: =IF(OR(G50="Sin pagar",G50="Pagar"),_xlfn.SINGLE(NETWORKDAYS($J$25,F50,FestivosPerú!$A$2:$A$15)),0) -> 0 | I50: =NETWORKDAYS($J$25,F50,FestivosPerú!$A$2:$A$15) -> 20 | J50: =H50 -> 0
B51: Soles | C51: Davis Cesar oporto figueroa -Europortage | D51: 10380.278 | E51: =D51/$D$6 -> 2948.9425 | F51: 45926 | G51: Cancelado | H51: =IF(OR(G51="Sin pagar",G51="Pagar"),_xlfn.SINGLE(NETWORKDAYS($J$25,F51,FestivosPerú!$A$2:$A$15)),0) -> 0 | I51: =NETWORKDAYS($J$25,F51,FestivosPerú!$A$2:$A$15) -> 20 | J51: =H51 -> 0
B52: Soles | C52: Luis Renato Sanchez Perez -Yon Yuo | D52: 10138.901 | E52: =D52/$D$6 -> 2880.3696 | F52: 45926 | G52: Cancelado | H52: =IF(OR(G52="Sin pagar",G52="Pagar"),_xlfn.SINGLE(NETWORKDAYS($J$25,F52,FestivosPerú!$A$2:$A$15)),0) -> 0 | I52: =NETWORKDAYS($J$25,F52,FestivosPerú!$A$2:$A$15) -> 20 | J52: =H52 -> 0
B53: Soles | C53: Andres Felipe Uribe Avila -Europortage | D53: 11218.036 | E53: =D53/$D$6 -> 3186.942 | F53: 45926 | G53: Cancelado | H53: =IF(OR(G53="Sin pagar",G53="Pagar"),_xlfn.SINGLE(NETWORKDAYS($J$25,F53,FestivosPerú!$A$2:$A$15)),0) -> 0 | I53: =NETWORKDAYS($J$25,F53,FestivosPerú!$A$2:$A$15) -> 20 | J53: =H53 -> 0
B54: USD | C54: Christiams Hebert Valle Gomez -Remotepass | D54: =E54*D6 -> 14682.131 | E54: 4171.06 | F54: 45926 | G54: Cancelado | H54: =IF(OR(G54="Sin pagar",G54="Pagar"),_xlfn.SINGLE(NETWORKDAYS($J$25,F54,FestivosPerú!$A$2:$A$15)),0) -> 0 | I54: =NETWORKDAYS($J$25,F54,FestivosPerú!$A$2:$A$15) -> 20 | J54: =H54 -> 0
C55: REEMBOLSO | D55: =SUBTOTAL(9,D56:D59) -> 15006.03 | E55: =SUBTOTAL(9,E56:E59) -> 4263.0767
C56: Reembolso Braydi Yusset Vera Neira-Europortage | D56: 739.78 | E56: =D56/$D$6 -> 210.16477 | F56: 45926 | G56: Cancelado | H56: =IF(OR(G56="Sin pagar",G56="Pagar"),_xlfn.SINGLE(NETWORKDAYS($J$25,F56,FestivosPerú!$A$2:$A$15)),0) -> 0 | I56: =NETWORKDAYS($J$25,F56,FestivosPerú!$A$2:$A$15) -> 20 | J56: =H56 -> 0
C57: Reembolso Cristhian Portugal Segovia -Europortage | D57: 8154.23 | E57: =D57/$D$6 -> 2316.5426 | F57: 45926 | G57: Cancelado | H57: =IF(OR(G57="Sin pagar",G57="Pagar"),_xlfn.SINGLE(NETWORKDAYS($J$25,F57,FestivosPerú!$A$2:$A$15)),0) -> 0 | I57: =NETWORKDAYS($J$25,F57,FestivosPerú!$A$2:$A$15) -> 20 | J57: =H57 -> 0
C58: Reembolso Davis Cesar oporto figueroa -Europortage | D58: 912 | E58: =D58/$D$6 -> 259.09091 | F58: 45926 | G58: Cancelado | H58: =IF(OR(G58="Sin pagar",G58="Pagar"),_xlfn.SINGLE(NETWORKDAYS($J$25,F58,FestivosPerú!$A$2:$A$15)),0) -> 0 | I58: =NETWORKDAYS($J$25,F58,FestivosPerú!$A$2:$A$15) -> 20 | J58: =H58 -> 0
C59: Reembolso Luis Renato Sanchez Marinez -Yon Yuo | D59: 5200.02 | E59: =D59/$D$6 -> 1477.2784 | F59: 45926 | G59: Cancelado | H59: =IF(OR(G59="Sin pagar",G59="Pagar"),_xlfn.SINGLE(NETWORKDAYS($J$25,F59,FestivosPerú!$A$2:$A$15)),0) -> 0 | I59: =NETWORKDAYS($J$25,F59,FestivosPerú!$A$2:$A$15) -> 20 | J59: =H59 -> 0
C60: IMPREVISTO | D60: =SUBTOTAL(9,D61:D63) -> 3260 | E60: =SUBTOTAL(9,E61:E63) -> 5780
C61: Transferencia de dinero a cuenta BBVA-Saldo Inicial-Soles | D61: 1500 | E61: =D61*D6 -> 5280 | F61: 45925 | G61: Cancelado | H61: =IF(OR(G61="Sin pagar",G61="Pagar"),_xlfn.SINGLE(NETWORKDAYS($J$25,F61,FestivosPerú!$A$2:$A$15)),0) -> 0 | I61: =NETWORKDAYS($J$25,F61,FestivosPerú!$A$2:$A$15) -> 19 | J61: =H61 -> 0
C62: Transferencia de dinero a cuenta BBVA-Saldo Inicial-USD | D62: =E62*D6 -> 1760 | E62: 500 | F62: 45925 | G62: Cancelado | H62: =IF(OR(G62="Sin pagar",G62="Pagar"),_xlfn.SINGLE(NETWORKDAYS($J$25,F62,FestivosPerú!$A$2:$A$15)),0) -> 0 | I62: =NETWORKDAYS($J$25,F62,FestivosPerú!$A$2:$A$15) -> 19 | J62: =H62 -> 0
C63: Devolucion de dinero a S&P Panamá | D63: =E63*D6 -> 0 | E63: =3900*0 -> 0 | F63: 45930 | G63: Cancelado | H63: =IF(OR(G63="Sin pagar",G63="Pagar"),_xlfn.SINGLE(NETWORKDAYS($J$25,F63,FestivosPerú!$A$2:$A$15)),0) -> 0 | I63: =NETWORKDAYS($J$25,F63,FestivosPerú!$A$2:$A$15) -> 22 | J63: =H63 -> 0
C64: COSTOS FINANCIEROS SAFEGUARD | D64: =SUBTOTAL(9,D65:D65) -> 112.65 | E64: =SUBTOTAL(9,E65:E65) -> 32.002841
C65: COSTOS FINANCIEROS | D65: ='BCP SOLES BCP'!$F$396+'BCP SOLES BCP'!$F$410+'BCP SOLES BCP'!$F$413+'BCP SOLES BCP'!$F$415+'BCP SOLES BCP'!$F$431+'BCP SOLES BCP'!$F$433+'BCP SOLES BCP'!$F$437+'BCP SOLES BCP'!$F$440+'BCP SOLES BCP'!$F$444+'BCP SOLES BCP'!$F$446+'BCP SOLES BCP'!$F$448+'BCP SOLES BCP'!$F$449+'BCP SOLES BCP'!$F$452+'BCP SOLES BCP'!$F$453+43.13 -> 112.65 | E65: =D65/D6 -> 32.002841 | F65: 45930 | G65: Cancelado | H65: =IF(OR(G65="Sin pagar",G65="Pagar"),_xlfn.SINGLE(NETWORKDAYS($J$25,F65,FestivosPerú!$A$2:$A$15)),0) -> 0 | I65: =NETWORKDAYS($J$25,F65,FestivosPerú!$A$2:$A$15) -> 22 | J65: =H65 -> 0
C66: GASTOS SAFEGUARD PERÚ | D66: =SUBTOTAL(9,D67:D88) -> 33330.25 | E66: =SUBTOTAL(9,E67:E88) -> 9468.821
B67: 6495538605 | C67: Planilla de declaración y pago de aportes previsional-Habitat | D67: 609.95 | E67: =D67/$D$6 -> 173.28125 | F67: 45906 | G67: Cancelado | H67: =IF(OR(G67="Sin pagar",G67="Pagar"),_xlfn.SINGLE(NETWORKDAYS($J$25,F67,FestivosPerú!$A$2:$A$15)),0) -> 0 | I67: =NETWORKDAYS($J$25,F67,FestivosPerú!$A$2:$A$15) -> 5 | J67: =H67 -> 0
B68: 2495539016 | C68: Planilla de declaración y pago de aportes previsional-Integra | D68: 4527.28 | E68: =D68/$D$6 -> 1286.1591 | F68: 45906 | G68: Cancelado | H68: =IF(OR(G68="Sin pagar",G68="Pagar"),_xlfn.SINGLE(NETWORKDAYS($J$25,F68,FestivosPerú!$A$2:$A$15)),0) -> 0 | I68: =NETWORKDAYS($J$25,F68,FestivosPerú!$A$2:$A$15) -> 5 | J68: =H68 -> 0
B69: 5495540057 | C69: Planilla de declaración y pago de aportes previsional-Prima | D69: 1865.09 | E69: =D69/$D$6 -> 529.85511 | F69: 45906 | G69: Cancelado | H69: =IF(OR(G69="Sin pagar",G69="Pagar"),_xlfn.SINGLE(NETWORKDAYS($J$25,F69,FestivosPerú!$A$2:$A$15)),0) -> 0 | I69: =NETWORKDAYS($J$25,F69,FestivosPerú!$A$2:$A$15) -> 5 | J69: =H69 -> 0 | M69: =D67+D68+D69 -> 7002.32
B70: S/N | C70: Envio de dinero a Selma Avanza para rendondear el valor y pagar planilla de aportes previsional | D70: 7.68 | E70: =D70/$D$6 -> 2.1818182 | F70: 45905 | G70: Cancelado | H70: =IF(OR(G70="Sin pagar",G70="Pagar"),_xlfn.SINGLE(NETWORKDAYS($J$25,F70,FestivosPerú!$A$2:$A$15)),0) -> 0 | I70: =NETWORKDAYS($J$25,F70,FestivosPerú!$A$2:$A$15) -> 5 | J70: =H70 -> 0
B71: S/N | C71: Plame Essalud y Renta de Quinta Categoría (Retención)-SG | D71: 8439 | E71: =D71/$D$6 -> 2397.4432 | F71: 45905 | G71: Cancelado | H71: =IF(OR(G71="Sin pagar",G71="Pagar"),_xlfn.SINGLE(NETWORKDAYS($J$25,F71,FestivosPerú!$A$2:$A$15)),0) -> 0 | I71: =NETWORKDAYS($J$25,F71,FestivosPerú!$A$2:$A$15) -> 5 | J71: =H71 -> 0
B72: 1150159812 | C72: Pago de renta IGV Agosto | D72: 10753 | E72: =D72/$D$6 -> 3054.8295 | F72: 45915 | G72: Cancelado | H72: =IF(OR(G72="Sin pagar",G72="Pagar"),_xlfn.SINGLE(NETWORKDAYS($J$25,F72,FestivosPerú!$A$2:$A$15)),0) -> 0 | I72: =NETWORKDAYS($J$25,F72,FestivosPerú!$A$2:$A$15) -> 11 | J72: =H72 -> 0 | M72: Outsorcing contable
C73: Pago positiva-Pensión- Juan Ulises Aguirre - Martin Felix Garci | D73: 129.54 | E73: =D73/$D$6 -> 36.801136 | F73: 45922 | G73: Cancelado | H73: =IF(OR(G73="Sin pagar",G73="Pagar"),_xlfn.SINGLE(NETWORKDAYS($J$25,F73,FestivosPerú!$A$2:$A$15)),0) -> 0 | I73: =NETWORKDAYS($J$25,F73,FestivosPerú!$A$2:$A$15) -> 16 | J73: =H73 -> 0
C74: Pago positiva-EPS- Juan Ulises Aguirre - Martin Felix Garci | D74: 316.32 | E74: =D74/$D$6 -> 89.863636 | F74: 45922 | G74: Cancelado | H74: =IF(OR(G74="Sin pagar",G74="Pagar"),_xlfn.SINGLE(NETWORKDAYS($J$25,F74,FestivosPerú!$A$2:$A$15)),0) -> 0 | I74: =NETWORKDAYS($J$25,F74,FestivosPerú!$A$2:$A$15) -> 16 | J74: =H74 -> 0
B75: ES6375102-01 | C75: Pago Rimac-EPS | D75: 2243.89 | E75: =D75/$D$6 -> 637.46875 | F75: 45922 | G75: Cancelado | H75: =IF(OR(G75="Sin pagar",G75="Pagar"),_xlfn.SINGLE(NETWORKDAYS($J$25,F75,FestivosPerú!$A$2:$A$15)),0) -> 0 | I75: =NETWORKDAYS($J$25,F75,FestivosPerú!$A$2:$A$15) -> 16 | J75: =H75 -> 0
B76: F548 - 00455369 | C76: Pago Rimac-EPS-Olga Paredes | D76: 879.04 | E76: =D76/$D$6 -> 249.72727 | F76: 45922 | G76: Cancelado | H76: =IF(OR(G76="Sin pagar",G76="Pagar"),_xlfn.SINGLE(NETWORKDAYS($J$25,F76,FestivosPerú!$A$2:$A$15)),0) -> 0 | I76: =NETWORKDAYS($J$25,F76,FestivosPerú!$A$2:$A$15) -> 16 | J76: =H76 -> 0
B77: ES6391596-01 | C77: Pago Rimac-EPS-Natalia | D77: 233 | E77: =D77/$D$6 -> 66.193182 | F77: 45922 | G77: Cancelado | H77: =IF(OR(G77="Sin pagar",G77="Pagar"),_xlfn.SINGLE(NETWORKDAYS($J$25,F77,FestivosPerú!$A$2:$A$15)),0) -> 0 | I77: =NETWORKDAYS($J$25,F77,FestivosPerú!$A$2:$A$15) -> 16 | J77: =H77 -> 0
B78: F548 - 00447103 | C78: Pago Rimac-EPS-Olga Paredes | D78: 2438.94 | E78: =D78/$D$6 -> 692.88068 | F78: 45922 | G78: Cancelado | H78: =IF(OR(G78="Sin pagar",G78="Pagar"),_xlfn.SINGLE(NETWORKDAYS($J$25,F78,FestivosPerú!$A$2:$A$15)),0) -> 0 | I78: =NETWORKDAYS($J$25,F78,FestivosPerú!$A$2:$A$15) -> 16 | J78: =H78 -> 0
C79: Pago positiva-Pensión- Juan Ulises Aguirre | D79: 123.9 | E79: =D79/$D$6 -> 35.198864 | F79: 45922 | G79: Cancelado | H79: =IF(OR(G79="Sin pagar",G79="Pagar"),_xlfn.SINGLE(NETWORKDAYS($J$25,F79,FestivosPerú!$A$2:$A$15)),0) -> 0 | I79: =NETWORKDAYS($J$25,F79,FestivosPerú!$A$2:$A$15) -> 16 | J79: =H79 -> 0
C80: Pago positiva-EPS- Juan Ulises Aguirre | D80: 129.54 | E80: =D80/$D$6 -> 36.801136 | F80: 45922 | G80: Cancelado | H80: =IF(OR(G80="Sin pagar",G80="Pagar"),_xlfn.SINGLE(NETWORKDAYS($J$25,F80,FestivosPerú!$A$2:$A$15)),0) -> 0 | I80: =NETWORKDAYS($J$25,F80,FestivosPerú!$A$2:$A$15) -> 16 | J80: =H80 -> 0
C81: Penny test Adriana Jimena Elera Tejada | D81: 1 | E81: =D81/$D$6 -> 0.28409091 | F81: 45922 | G81: Cancelado | H81: =IF(OR(G81="Sin pagar",G81="Pagar"),_xlfn.SINGLE(NETWORKDAYS($J$25,F81,FestivosPerú!$A$2:$A$15)),0) -> 0 | I81: =NETWORKDAYS($J$25,F81,FestivosPerú!$A$2:$A$15) -> 16 | J81: =H81 -> 0
C82: Penny test Sergio Martin Gustin García | D82: =1+1.53 -> 2.53 | E82: =D82/$D$6 -> 0.71875 | F82: 45922 | G82: Cancelado | H82: =IF(OR(G82="Sin pagar",G82="Pagar"),_xlfn.SINGLE(NETWORKDAYS($J$25,F82,FestivosPerú!$A$2:$A$15)),0) -> 0 | I82: =NETWORKDAYS($J$25,F82,FestivosPerú!$A$2:$A$15) -> 16 | J82: =H82 -> 0
C83: Penny test Martín Rolando Felix García | D83: 5.3 | E83: =D83/$D$6 -> 1.5056818 | F83: 45922 | G83: Cancelado | H83: =IF(OR(G83="Sin pagar",G83="Pagar"),_xlfn.SINGLE(NETWORKDAYS($J$25,F83,FestivosPerú!$A$2:$A$15)),0) -> 0 | I83: =NETWORKDAYS($J$25,F83,FestivosPerú!$A$2:$A$15) -> 16 | J83: =H83 -> 0
C84: Penny test Olga Alejandro Paredes Paucarcaja | D84: 1 | E84: =D84/$D$6 -> 0.28409091 | F84: 45922 | G84: Cancelado | H84: =IF(OR(G84="Sin pagar",G84="Pagar"),_xlfn.SINGLE(NETWORKDAYS($J$25,F84,FestivosPerú!$A$2:$A$15)),0) -> 0 | I84: =NETWORKDAYS($J$25,F84,FestivosPerú!$A$2:$A$15) -> 16 | J84: =H84 -> 0
C85: Penny test Natalia Marianella Florian Parra | D85: 1 | E85: =D85/$D$6 -> 0.28409091 | F85: 45922 | G85: Cancelado | H85: =IF(OR(G85="Sin pagar",G85="Pagar"),_xlfn.SINGLE(NETWORKDAYS($J$25,F85,FestivosPerú!$A$2:$A$15)),0) -> 0 | I85: =NETWORKDAYS($J$25,F85,FestivosPerú!$A$2:$A$15) -> 16 | J85: =H85 -> 0
C86: Penny test Johanna Ximena Cordova Sanchez | D86: 5.3 | E86: =D86/$D$6 -> 1.5056818 | F86: 45922 | G86: Cancelado | H86: =IF(OR(G86="Sin pagar",G86="Pagar"),_xlfn.SINGLE(NETWORKDAYS($J$25,F86,FestivosPerú!$A$2:$A$15)),0) -> 0 | I86: =NETWORKDAYS($J$25,F86,FestivosPerú!$A$2:$A$15) -> 16 | J86: =H86 -> 0
B87: 18815106 | C87: Poliza vida Ley Johanna Ximena Cordova Sanchez | D87: 55.34 | E87: =D87/$D$6 -> 15.721591 | F87: 45924 | G87: Cancelado | H87: =IF(OR(G87="Sin pagar",G87="Pagar"),_xlfn.SINGLE(NETWORKDAYS($J$25,F87,FestivosPerú!$A$2:$A$15)),0) -> 0 | I87: =NETWORKDAYS($J$25,F87,FestivosPerú!$A$2:$A$15) -> 18 | J87: =H87 -> 0
B88: 18815106 | C88: Poliza vida Pacifico | D88: 562.61 | E88: =D88/$D$6 -> 159.83239 | F88: 45932 | G88: Cancelado | H88: =IF(OR(G88="Sin pagar",G88="Pagar"),_xlfn.SINGLE(NETWORKDAYS($J$25,F88,FestivosPerú!$A$2:$A$15)),0) -> 0 | I88: =NETWORKDAYS($J$25,F88,FestivosPerú!$A$2:$A$15) -> 24 | J88: =H88 -> 0
C89: NÓMINAS -SAFEGUARD | D89: =SUBTOTAL(9,D90:D101) -> 115539.25 | E89: =SUBTOTAL(9,E90:E101) -> 32823.65
C90: Fiorella maribel chavez torriani | D90: 4452.9878 | E90: =D90/$D$6 -> 1265.0533 | F90: 45926 | G90: Cancelado | H90: =IF(OR(G90="Sin pagar",G90="Pagar"),_xlfn.SINGLE(NETWORKDAYS($J$25,F90,FestivosPerú!$A$2:$A$15)),0) -> 0 | I90: =NETWORKDAYS($J$25,F90,FestivosPerú!$A$2:$A$15) -> 20 | J90: =H90 -> 0
C91: Claudia anabel vasquez cardenas | D91: 8451.4396 | E91: =D91/$D$6 -> 2400.9772 | F91: 45926 | G91: Cancelado | H91: =IF(OR(G91="Sin pagar",G91="Pagar"),_xlfn.SINGLE(NETWORKDAYS($J$25,F91,FestivosPerú!$A$2:$A$15)),0) -> 0 | I91: =NETWORKDAYS($J$25,F91,FestivosPerú!$A$2:$A$15) -> 20 | J91: =H91 -> 0
C92: Juan ulises aguirre tacunan | D92: 10187.784 | E92: =D92/$D$6 -> 2894.2567 | F92: 45926 | G92: Cancelado | H92: =IF(OR(G92="Sin pagar",G92="Pagar"),_xlfn.SINGLE(NETWORKDAYS($J$25,F92,FestivosPerú!$A$2:$A$15)),0) -> 0 | I92: =NETWORKDAYS($J$25,F92,FestivosPerú!$A$2:$A$15) -> 20 | J92: =H92 -> 0
C93: Angel augusto allauca garcia | D93: 9435.3723 | E93: =D93/$D$6 -> 2680.5035 | F93: 45926 | G93: Cancelado | H93: =IF(OR(G93="Sin pagar",G93="Pagar"),_xlfn.SINGLE(NETWORKDAYS($J$25,F93,FestivosPerú!$A$2:$A$15)),0) -> 0 | I93: =NETWORKDAYS($J$25,F93,FestivosPerú!$A$2:$A$15) -> 20 | J93: =H93 -> 0
C94: Esteban gonzalo arias suarez | D94: 5328.428 | E94: =D94/$D$6 -> 1513.7579 | F94: 45926 | G94: Cancelado | H94: =IF(OR(G94="Sin pagar",G94="Pagar"),_xlfn.SINGLE(NETWORKDAYS($J$25,F94,FestivosPerú!$A$2:$A$15)),0) -> 0 | I94: =NETWORKDAYS($J$25,F94,FestivosPerú!$A$2:$A$15) -> 20 | J94: =H94 -> 0
C95: David eduardo estela guzman | D95: 5326.2338 | E95: =D95/$D$6 -> 1513.1346 | F95: 45926 | G95: Cancelado | H95: =IF(OR(G95="Sin pagar",G95="Pagar"),_xlfn.SINGLE(NETWORKDAYS($J$25,F95,FestivosPerú!$A$2:$A$15)),0) -> 0 | I95: =NETWORKDAYS($J$25,F95,FestivosPerú!$A$2:$A$15) -> 20 | J95: =H95 -> 0
C96: Natalia Marianella Florian Parra | D96: 6647.25 | E96: =D96/$D$6 -> 1888.4233 | F96: 45926 | G96: Cancelado | H96: =IF(OR(G96="Sin pagar",G96="Pagar"),_xlfn.SINGLE(NETWORKDAYS($J$25,F96,FestivosPerú!$A$2:$A$15)),0) -> 0 | I96: =NETWORKDAYS($J$25,F96,FestivosPerú!$A$2:$A$15) -> 20 | J96: =H96 -> 0
C97: Sergio Martin Gustin García | D97: 15397.013 | E97: =D97/$D$6 -> 4374.1516 | F97: 45926 | G97: Cancelado | H97: =IF(OR(G97="Sin pagar",G97="Pagar"),_xlfn.SINGLE(NETWORKDAYS($J$25,F97,FestivosPerú!$A$2:$A$15)),0) -> 0 | I97: =NETWORKDAYS($J$25,F97,FestivosPerú!$A$2:$A$15) -> 20 | J97: =H97 -> 0
C98: Olga Alejandra Paredes Paucarcaja | D98: 12384.553 | E98: =D98/$D$6 -> 3518.3389 | F98: 45926 | G98: Cancelado | H98: =IF(OR(G98="Sin pagar",G98="Pagar"),_xlfn.SINGLE(NETWORKDAYS($J$25,F98,FestivosPerú!$A$2:$A$15)),0) -> 0 | I98: =NETWORKDAYS($J$25,F98,FestivosPerú!$A$2:$A$15) -> 20 | J98: =H98 -> 0
C99: Adriana Jimena Elera Tejada | D99: 19623.54 | E99: =D99/$D$6 -> 5574.8694 | F99: 45926 | G99: Cancelado | H99: =IF(OR(G99="Sin pagar",G99="Pagar"),_xlfn.SINGLE(NETWORKDAYS($J$25,F99,FestivosPerú!$A$2:$A$15)),0) -> 0 | I99: =NETWORKDAYS($J$25,F99,FestivosPerú!$A$2:$A$15) -> 20 | J99: =H99 -> 0
C100: Martin Rolando Felix García | D100: 15962.915 | E100: =D100/$D$6 -> 4534.9189 | F100: 45926 | G100: Cancelado | H100: =IF(OR(G100="Sin pagar",G100="Pagar"),_xlfn.SINGLE(NETWORKDAYS($J$25,F100,FestivosPerú!$A$2:$A$15)),0) -> 0 | I100: =NETWORKDAYS($J$25,F100,FestivosPerú!$A$2:$A$15) -> 20 | J100: =H100 -> 0
C101: Johanna Ximena Cordova Sanchez | D101: 2341.7325 | E101: =D101/$D$6 -> 665.26493 | F101: 45926 | G101: Cancelado | H101: =IF(OR(G101="Sin pagar",G101="Pagar"),_xlfn.SINGLE(NETWORKDAYS($J$25,F101,FestivosPerú!$A$2:$A$15)),0) -> 0 | I101: =NETWORKDAYS($J$25,F101,FestivosPerú!$A$2:$A$15) -> 20 | J101: =H101 -> 0
C102: REEMBOLSO -SAFEGUARD | D102: =SUBTOTAL(9,D103:D104) -> 14382.75 | E102: =SUBTOTAL(9,E103:E104) -> 4086.0085
C103: Juan Ulises Tucunan | D103: 10382.75 | E103: =D103/$D$6 -> 2949.6449 | F103: 45926 | G103: Cancelado | H103: =IF(OR(G103="Sin pagar",G103="Pagar"),_xlfn.SINGLE(NETWORKDAYS($J$25,F103,FestivosPerú!$A$2:$A$15)),0) -> 0 | I103: =NETWORKDAYS($J$25,F103,FestivosPerú!$A$2:$A$15) -> 20 | J103: =H103 -> 0
C104: Martin Rolando Felix Garcia | D104: 4000 | E104: =D104/$D$6 -> 1136.3636 | F104: 45926 | G104: Cancelado | H104: =IF(OR(G104="Sin pagar",G104="Pagar"),_xlfn.SINGLE(NETWORKDAYS($J$25,F104,FestivosPerú!$A$2:$A$15)),0) -> 0 | I104: =NETWORKDAYS($J$25,F104,FestivosPerú!$A$2:$A$15) -> 20 | J104: =H104 -> 0
C105: TOTAL EGRESOS | D105: =SUBTOTAL(9,D27:D104) -> 282819.08 | E105: =SUBTOTAL(9,E27:E104) -> 85200.192
...

Sheet FLUJO CAJA OCTUBRE 2025
D1: 42400
D4: Fecha de Elaboración: | E4: 45931
C6: Tasa de cambio: | D6: 3.31
D7: OCTUBRE
D8: VALOR S/ Sol | E8: VALOR USD
C9: BANCOS | D9: =SUBTOTAL(9,D10:D11) -> 183998.26 | E9: =SUBTOTAL(9,E10:E11) -> 55588.599
C10: Bancos S/ Soles | D10: ='BCP SOLES BCP'!$G$482 -> 11951.808 | E10: =D10/$D$6 -> 3610.8181
C11: Bancos USD | D11: =E11*$D$6 -> 172046.45 | E11: ='BCP USD BCP'!$G$204 -> 51977.78
C12: CLIENTES | D12: =SUBTOTAL(9,D13:D17) -> 499985.62 | E12: =SUBTOTAL(9,E13:E17) -> 150698.5
B13: Pagado | C13: Client: Remotepass-Factura Nro 008 | D13: =$E$13*'Diferencia Cambio S&P'!$K$34 -> 22424.039 | E13: ='BCP USD BCP'!E212 -> 6758.3 | F13: 6776.3 | G13: =E13-F13 -> -18 | J13: GMF
B14: Pagado | C14: Client: Europortage-Factura Nro 009 | D14: =$E$14*'Diferencia Cambio S&P'!$K$35 -> 98572.803 | E14: ='BCP USD BCP'!E213 -> 29708.5 | F14: 29848.5 | G14: =E14-F14 -> -140 | J14: GMF
B15: Pagado | C15: Client: Safeguard-Factura Nro EB01-010( Cliente) | D15: =$E$15*'Diferencia Cambio Global'!$K$11 -> 314138.24 | E15: ='BCP USD BCP'!E214+'BCP USD BCP'!$E$218+'BCP USD BCP'!$E$220 -> 94648.46 | F15: 94678.47 | G15: =E15-F15 -> -30.01 | J15: GMF
B16: Pagado | C16: Client: Safeguard-Factura Nro EB01-011( Cliente)-Renovación póliza | D16: =$E$16*'Diferencia Cambio Global'!$K$12 -> 46563.685 | E16: ='BCP USD BCP'!E253 -> 14071.83
B17: Pagado | C17: Client: Yonyou xinfushe cloud technology co., Factura Nro 012 | D17: =$E$17*'Diferencia Cambio S&P'!$K$36 -> 18286.858 | E17: ='BCP USD BCP'!$E$216 -> 5511.41
C18: TOTAL INGRESOS | D18: =SUBTOTAL(9,D9:D17) -> 683983.89 | E18: =SUBTOTAL(9,E9:E17) -> 206287.1 | G18: =E16+E17+14240.67 -> 33823.91 | J18: =G18/E18 -> 0.16396522
B21: CUENTAS X PAGAR MES | D21: OCTUBRE | F21: Fecha de Elaboración: | J21: 45931
B22: Factura | C22: PROVEEDOR | D22: VALOR S/Sol | E22: VALOR USD | F22: Fecha vencimiento | G22: Estado | J22: KPI
C23: SEGURIDAD IGSS | D23: =SUBTOTAL(9,D24:D26) -> 10441.37 | E23: =SUBTOTAL(9,E24:E26) -> 3154.4924
B24: 2221486801 | C24: Planilla de declaración y pago de aportes previsional-Braydi Yusset Vera Neyra y Davis Cesar Oporto Figueroa | D24: 4941.25 | E24: =D24/$D$6 -> 1492.8248 | F24: 45936 | G24: Cancelado | H24: =IF(OR(G24="Sin pagar",G24="Pagar"),(_xlfn.SINGLE(NETWORKDAYS($J$21,F24,FestivosPerú!$A$2:$A$15))),0) -> 0 | I24: =NETWORKDAYS($J$21,F24,FestivosPerú!$A$2:$A$15) -> 4 | J24: =H24 -> 0 | M24: AFP NET Selecciona debito BCP | Q24: =3271.3+623.91 -> 3895.21 | R24: =Q24/$Q$27 -> 0.41386099 | S24: =$Q$28*R24 -> 4366.2335
B25: 2517215180 | C25: Planilla de declaración y pago de aportes previsional Christian Portugal Segovia y Luis renato Sanchez Martinez | D25: 3452.52 | E25: =D25/$D$6 -> 1043.0574 | F25: 45936 | G25: Cancelado | H25: =IF(OR(G25="Sin pagar",G25="Pagar"),(_xlfn.SINGLE(NETWORKDAYS($J$21,F25,FestivosPerú!$A$2:$A$15))),0) -> 0 | I25: =NETWORKDAYS($J$21,F25,FestivosPerú!$A$2:$A$15) -> 4 | J25: =H25 -> 0 | Q25: 3452.52 | R25: =Q25/$Q$27 -> 0.36682576 | S25: =$Q$28*R25 -> 3870.0117
B26: 2609686375 | C26: Planilla de declaración y pago de aportes previsional Christiams Hebert Valle Gomez -Remotepass | D26: 2047.6 | E26: =D26/$D$6 -> 618.61027 | F26: 45936 | G26: Cancelado | H26: =IF(OR(G26="Sin pagar",G26="Pagar"),(_xlfn.SINGLE(NETWORKDAYS($J$21,F26,FestivosPerú!$A$2:$A$15))),0) -> 0 | I26: =NETWORKDAYS($J$21,F26,FestivosPerú!$A$2:$A$15) -> 4 | J26: =H26 -> 0 | Q26: 2064.15 | R26: =Q26/$Q$27 -> 0.21931325 | S26: =$Q$28*R26 -> 2313.7548
C27: IMPUESTOS | D27: =SUBTOTAL(9,D28:D29) -> 17883 | E27: =SUBTOTAL(9,E28:E29) -> 5402.719 | H27: =IF(OR(G27="Sin pagar",G27="Pagar"),(_xlfn.SINGLE(NETWORKDAYS($J$21,F27,FestivosPerú!$A$2:$A$15))),0) -> 0 | J27: =H27 -> 0 | Q27: =SUM(Q24:Q26) -> 9411.88 | R27: =SUM(R24:R26) -> 1 | S27: =SUM(S24:S26) -> 10550
C28: Plame Essalud y Renta de Quinta Categoría (Retención) | D28: 17771 | E28: =D28/$D$6 -> 5368.8822 | F28: 45945 | G28: Cancelado | H28: =IF(OR(G28="Sin pagar",G28="Pagar"),(_xlfn.SINGLE(NETWORKDAYS($J$21,F28,FestivosPerú!$A$2:$A$15))),0) -> 0 | I28: =NETWORKDAYS($J$21,F28,FestivosPerú!$A$2:$A$15) -> 10 | J28: =H28 -> 0 | M28: Sunat-presentación PDF-Winzip | Q28: 10550
C29: Pago de renta IGV Septiembre | D29: 112 | E29: =D29/$D$6 -> 33.836858 | F29: 45946 | G29: Cancelado | H29: =IF(OR(G29="Sin pagar",G29="Pagar"),(_xlfn.SINGLE(NETWORKDAYS($J$21,F29,FestivosPerú!$A$2:$A$15))),0) -> 0 | I29: =NETWORKDAYS($J$21,F29,FestivosPerú!$A$2:$A$15) -> 11 | J29: =H29 -> 0 | M29: Outsorcing contable-Presenta contadora y debito automatico a la cta
C30: SERVICIOS OUTSORCING CONTABLE | D30: =SUBTOTAL(9,D31:D33) -> 3304 | E30: =SUBTOTAL(9,E31:E33) -> 998.18731 | H30: =IF(OR(G30="Sin pagar",G30="Pagar"),(_xlfn.SINGLE(NETWORKDAYS($J$21,F30,FestivosPerú!$A$2:$A$15))),0) -> 0 | J30: =H30 -> 0
B31: E001-690 | C31: Outsourcing contable servicio de traslado Septiembre | D31: 472 | E31: =D31/$D$6 -> 142.59819 | F31: 45940 | G31: Cancelado | H31: =IF(OR(G31="Sin pagar",G31="Pagar"),(_xlfn.SINGLE(NETWORKDAYS($J$21,F31,FestivosPerú!$A$2:$A$15))),0) -> 0 | I31: =NETWORKDAYS($J$21,F31,FestivosPerú!$A$2:$A$15) -> 7 | J31: =H31 -> 0
B32: E001-703 | C32: Outsourcing contable servicio septiembre a SG- Avanza | D32: 1416 | E32: =D32/$D$6 -> 427.79456 | F32: 45960 | G32: Cancelado | H32: =IF(OR(G32="Sin pagar",G32="Pagar"),(_xlfn.SINGLE(NETWORKDAYS($J$21,F32,FestivosPerú!$A$2:$A$15))),0) -> 0 | I32: =NETWORKDAYS($J$21,F32,FestivosPerú!$A$2:$A$15) -> 21 | J32: =H32 -> 0
B33: E001-706 | C33: Outsourcing contable servicio septiembre a S&P- Avanza | D33: 1416 | E33: =D33/$D$6 -> 427.79456 | F33: 45960 | G33: Cancelado | H33: =IF(OR(G33="Sin pagar",G33="Pagar"),(_xlfn.SINGLE(NETWORKDAYS($J$21,F33,FestivosPerú!$A$2:$A$15))),0) -> 0 | I33: =NETWORKDAYS($J$21,F33,FestivosPerú!$A$2:$A$15) -> 21 | J33: =H33 -> 0
C34: PÓLIZAS DE VIDA Y SEGUROS MÉDICO | D34: =SUBTOTAL(9,D35:D39) -> 1924.32 | E34: =SUBTOTAL(9,E35:E39) -> 581.36556 | H34: =IF(OR(G34="Sin pagar",G34="Pagar"),(_xlfn.SINGLE(NETWORKDAYS($J$21,F34,FestivosPerú!$A$2:$A$15))),0) -> 0
B35: S/N | C35: Seguros de vida Rimac -Andrés Felipe Uribe ( segundo mes)- Europortage-Octubre | D35: 926 | E35: =D35/$D$6 -> 279.75831 | F35: 45940 | G35: Cancelado | H35: =IF(OR(G35="Sin pagar",G35="Pagar"),(_xlfn.SINGLE(NETWORKDAYS($J$21,F35,FestivosPerú!$A$2:$A$15))),0) -> 0 | I35: =NETWORKDAYS($J$21,F35,FestivosPerú!$A$2:$A$15) -> 7 | J35: =H35 -> 0
B36: S/N | C36: SCTR Salud Europartage recibo 165581817-Nov | D36: 344.88 | E36: =D36/$D$6 -> 104.19335 | F36: 45953 | G36: Cancelado | H36: =IF(OR(G36="Sin pagar",G36="Pagar"),(_xlfn.SINGLE(NETWORKDAYS($J$21,F36,FestivosPerú!$A$2:$A$15))),0) -> 0 | I36: =NETWORKDAYS($J$21,F36,FestivosPerú!$A$2:$A$15) -> 16 | J36: =H36 -> 0
B37: S/N | C37: SCTR Pensiones europortage recibo 165581808 -Nov | D37: 355.23 | E37: =D37/$D$6 -> 107.32024 | F37: 45953 | G37: Cancelado | H37: =IF(OR(G37="Sin pagar",G37="Pagar"),(_xlfn.SINGLE(NETWORKDAYS($J$21,F37,FestivosPerú!$A$2:$A$15))),0) -> 0 | I37: =NETWORKDAYS($J$21,F37,FestivosPerú!$A$2:$A$15) -> 16 | J37: =H37 -> 0
B38: S/N | C38: Seguros de vida Europortage Ley recibo 165581788 -Nov | D38: =118 -> 118 | E38: =D38/$D$6 -> 35.649547 | F38: 45953 | G38: Cancelado | H38: =IF(OR(G38="Sin pagar",G38="Pagar"),(_xlfn.SINGLE(NETWORKDAYS($J$21,F38,FestivosPerú!$A$2:$A$15))),0) -> 0 | I38: =NETWORKDAYS($J$21,F38,FestivosPerú!$A$2:$A$15) -> 16 | J38: =H38 -> 0
B39: S/N | C39: SCTR Salud recibo 165581766- Yon you-Nov | D39: 180.21 | E39: =D39/$D$6 -> 54.444109 | F39: 45953 | G39: Cancelado | H39: =IF(OR(G39="Sin pagar",G39="Pagar"),(_xlfn.SINGLE(NETWORKDAYS($J$21,F39,FestivosPerú!$A$2:$A$15))),0) -> 0 | I39: =NETWORKDAYS($J$21,F39,FestivosPerú!$A$2:$A$15) -> 16 | J39: =H39 -> 0
C40: COSTOS FINANCIEROS | D40: =SUBTOTAL(9,D41:D41) -> 426.13 | E40: =SUBTOTAL(9,E41:E41) -> 128.74018 | H40: =IF(OR(G40="Sin pagar",G40="Pagar"),(_xlfn.SINGLE(NETWORKDAYS($J$21,F40,FestivosPerú!$A$2:$A$15))),0) -> 0
C41: COSTOS FINANCIEROS | D41: =('BCP SOLES BCP'!$F$482+'BCP SOLES BCP'!$F$489+'BCP SOLES BCP'!$F$495+'BCP SOLES BCP'!$F$499+'BCP SOLES BCP'!$F$544+'BCP SOLES BCP'!$F$546+'BCP SOLES BCP'!$F$548+'BCP SOLES BCP'!$F$550+'BCP SOLES BCP'!$F$561+'BCP SOLES BCP'!$F$563+'BCP SOLES BCP'!$F$565+'BCP SOLES BCP'!$F$567+'BCP SOLES BCP'!$F$580+'BCP SOLES BCP'!$F$582+'BCP SOLES BCP'!$F$584+'BCP SOLES BCP'!$F$585+'BCP SOLES BCP'!$F$587+'BCP SOLES BCP'!$F$589+'BCP SOLES BCP'!$F$590+'BCP SOLES BCP'!$F$593+'BCP SOLES BCP'!$F$596+'BCP SOLES BCP'!$F$597+('BCP SOLES BCP'!$F$605+'BCP SOLES BCP'!$F$606/2)+'BCP SOLES BCP'!$F$610)+(('BCP USD BCP'!F209/2)+'BCP USD BCP'!F217+('BCP USD BCP'!F222/2)+'BCP USD BCP'!F233+'BCP USD BCP'!F234+'BCP USD BCP'!F247+'BCP USD BCP'!F251+'BCP USD BCP'!F252+('BCP USD BCP'!F257+'BCP USD BCP'!F258/2)) -> 426.13 | E41: =$D$41/$D$6 -> 128.74018 | F41: 45961 | G41: Cancelado | H41: =IF(OR(G41="Sin pagar",G41="Pagar"),(_xlfn.SINGLE(NETWORKDAYS($J$21,F41,FestivosPerú!$A$2:$A$15))),0) -> 0 | I41: =NETWORKDAYS($J$21,F41,FestivosPerú!$A$2:$A$15) -> 22 | J41: =H41 -> 0
C42: NÓMINAS CLIENTES S&P | D42: =SUBTOTAL(9,D43:D48) -> 66282.127 | E42: =SUBTOTAL(9,E43:E48) -> 20024.812 | H42: =IF(OR(G42="Sin pagar",G42="Pagar"),(_xlfn.SINGLE(NETWORKDAYS($J$21,F42,FestivosPerú!$A$2:$A$15))),0) -> 0
B43: Soles | C43: Braydi Yusset Vera Neira-Europortage | D43: 13619.1 | E43: =D43/$D$6 -> 4114.5317 | F43: 45958 | G43: Cancelado | H43: =IF(OR(G43="Sin pagar",G43="Pagar"),(_xlfn.SINGLE(NETWORKDAYS($J$21,F43,FestivosPerú!$A$2:$A$15))),0) -> 0 | I43: =NETWORKDAYS($J$21,F43,FestivosPerú!$A$2:$A$15) -> 19 | J43: =H43 -> 0
B44: Soles | C44: Cristhian Portugal Segovia -Europortage | D44: 10740.14 | E44: =D44/$D$6 -> 3244.7553 | F44: 45958 | G44: Cancelado | H44: =IF(OR(G44="Sin pagar",G44="Pagar"),(_xlfn.SINGLE(NETWORKDAYS($J$21,F44,FestivosPerú!$A$2:$A$15))),0) -> 0 | I44: =NETWORKDAYS($J$21,F44,FestivosPerú!$A$2:$A$15) -> 19 | J44: =H44 -> 0
B45: Soles | C45: Davis Cesar oporto figueroa -Europortage | D45: 10833.07 | E45: =D45/$D$6 -> 3272.8308 | F45: 45958 | G45: Cancelado | H45: =IF(OR(G45="Sin pagar",G45="Pagar"),(_xlfn.SINGLE(NETWORKDAYS($J$21,F45,FestivosPerú!$A$2:$A$15))),0) -> 0 | I45: =NETWORKDAYS($J$21,F45,FestivosPerú!$A$2:$A$15) -> 19 | J45: =H45 -> 0
B46: Soles | C46: Luis Renato Sanchez Perez -Yon Yuo | D46: 10410.11 | E46: =D46/$D$6 -> 3145.0483 | F46: 45958 | G46: Cancelado | H46: =IF(OR(G46="Sin pagar",G46="Pagar"),(_xlfn.SINGLE(NETWORKDAYS($J$21,F46,FestivosPerú!$A$2:$A$15))),0) -> 0 | I46: =NETWORKDAYS($J$21,F46,FestivosPerú!$A$2:$A$15) -> 19 | J46: =H46 -> 0
B47: Soles | C47: Andres Felipe Uribe Avila -Europortage | D47: 7234.52 | E47: =D47/$D$6 -> 2185.6556 | F47: 45959 | G47: Cancelado | H47: =IF(OR(G47="Sin pagar",G47="Pagar"),(_xlfn.SINGLE(NETWORKDAYS($J$21,F47,FestivosPerú!$A$2:$A$15))),0) -> 0 | I47: =NETWORKDAYS($J$21,F47,FestivosPerú!$A$2:$A$15) -> 20 | J47: =H47 -> 0
B48: USD | C48: Christiams Hebert Valle Gomez -Remotepass | D48: =$E$48*$D$6 -> 13445.187 | E48: 4061.99 | F48: 45958 | G48: Cancelado | H48: =IF(OR(G48="Sin pagar",G48="Pagar"),(_xlfn.SINGLE(NETWORKDAYS($J$21,F48,FestivosPerú!$A$2:$A$15))),0) -> 0 | I48: =NETWORKDAYS($J$21,F48,FestivosPerú!$A$2:$A$15) -> 19 | J48: =H48 -> 0
C49: REEMBOLSO | D49: =SUBTOTAL(9,D50:D52) -> 17272.31 | E49: =SUBTOTAL(9,E50:E52) -> 5218.2205 | H49: =IF(OR(G49="Sin pagar",G49="Pagar"),(_xlfn.SINGLE(NETWORKDAYS($J$21,F49,FestivosPerú!$A$2:$A$15))),0) -> 0
C50: Reembolso Braydi Yusset Vera Neira-Europortage | D50: 7919.53 | E50: =D50/$D$6 -> 2392.6073 | F50: 45958 | G50: Cancelado | H50: =IF(OR(G50="Sin pagar",G50="Pagar"),(_xlfn.SINGLE(NETWORKDAYS($J$21,F50,FestivosPerú!$A$2:$A$15))),0) -> 0 | I50: =NETWORKDAYS($J$21,F50,FestivosPerú!$A$2:$A$15) -> 19 | J50: =H50 -> 0
C51: Reembolso Cristhian Portugal Segovia -Europortage | D51: 8719.88 | E51: =D51/$D$6 -> 2634.4048 | F51: 45958 | G51: Cancelado | H51: =IF(OR(G51="Sin pagar",G51="Pagar"),(_xlfn.SINGLE(NETWORKDAYS($J$21,F51,FestivosPerú!$A$2:$A$15))),0) -> 0 | I51: =NETWORKDAYS($J$21,F51,FestivosPerú!$A$2:$A$15) -> 19 | J51: =H51 -> 0
C52: Reembolso Davis Cesar oporto figueroa -Europortage | D52: 632.9 | E52: =D52/$D$6 -> 191.20846 | F52: 45958 | G52: Cancelado | H52: =IF(OR(G52="Sin pagar",G52="Pagar"),(_xlfn.SINGLE(NETWORKDAYS($J$21,F52,FestivosPerú!$A$2:$A$15))),0) -> 0 | I52: =NETWORKDAYS($J$21,F52,FestivosPerú!$A$2:$A$15) -> 19 | J52: =H52 -> 0
C53: IMPREVISTO | D53: =SUBTOTAL(9,D54:D54) -> 0 | E53: =SUBTOTAL(9,E54:E54) -> 0 | H53: =IF(OR(G53="Sin pagar",G53="Pagar"),(_xlfn.SINGLE(NETWORKDAYS($J$21,F53,FestivosPerú!$A$2:$A$15))),0) -> 0
C54: Devolucion de dinero a S&P Panamá | D54: =$E$54*$D$6 -> 0 | E54: =3900*0 -> 0 | F54: 45961 | G54: Cancelado | H54: =IF(OR(G54="Sin pagar",G54="Pagar"),(_xlfn.SINGLE(NETWORKDAYS($J$21,F54,FestivosPerú!$A$2:$A$15))),0) -> 0 | I54: =NETWORKDAYS($J$21,F54,FestivosPerú!$A$2:$A$15) -> 22 | J54: =H54 -> 0
C55: COSTOS FINANCIEROS SAFEGUARD | D55: =SUBTOTAL(9,D56:D56) -> 145.13 | E55: =SUBTOTAL(9,E56:E56) -> 43.845921 | H55: =IF(OR(G55="Sin pagar",G55="Pagar"),(_xlfn.SINGLE(NETWORKDAYS($J$21,F55,FestivosPerú!$A$2:$A$15))),0) -> 0
C56: COSTOS FINANCIEROS | D56: =(('BCP SOLES BCP'!$F$492+'BCP SOLES BCP'!$F$494+'BCP SOLES BCP'!$F$502+'BCP SOLES BCP'!$F$506+'BCP SOLES BCP'!$F$515+'BCP SOLES BCP'!$F$528+'BCP SOLES BCP'!$F$530+'BCP SOLES BCP'!$F$532+'BCP SOLES BCP'!$F$535+'BCP SOLES BCP'!$F$537+'BCP SOLES BCP'!$F$538+'BCP SOLES BCP'!$F$569+'BCP SOLES BCP'!$F$570+'BCP SOLES BCP'!$F$577+'BCP SOLES BCP'!$F$578+'BCP SOLES BCP'!$F$599+'BCP SOLES BCP'!$F$600+'BCP SOLES BCP'!$F$604+('BCP SOLES BCP'!$F$605+'BCP SOLES BCP'!$F$606/2)))+(('BCP USD BCP'!F209/2)+'BCP USD BCP'!F215+'BCP USD BCP'!F219+'BCP USD BCP'!F221+('BCP USD BCP'!F222/2)+'BCP USD BCP'!F230+'BCP USD BCP'!F246+('BCP USD BCP'!F247/2)+'BCP USD BCP'!F254+('BCP USD BCP'!F257+'BCP USD BCP'!F258)/2)+41.3 -> 145.13 | E56: =D56/D6 -> 43.845921 | F56: 45961 | G56: Cancelado | H56: =IF(OR(G56="Sin pagar",G56="Pagar"),(_xlfn.SINGLE(NETWORKDAYS($J$21,F56,FestivosPerú!$A$2:$A$15))),0) -> 0 | I56: =NETWORKDAYS($J$21,F56,FestivosPerú!$A$2:$A$15) -> 22 | J56: =H56 -> 0
C57: SEGURIDAD IGSS | D57: =SUBTOTAL(9,D58:D61) -> 17550.62 | E57: =SUBTOTAL(9,E58:E61) -> 5302.3021 | H57: =IF(OR(G57="Sin pagar",G57="Pagar"),(_xlfn.SINGLE(NETWORKDAYS($J$21,F57,FestivosPerú!$A$2:$A$15))),0) -> 0
B58: 2609693703 | C58: Planilla de declaración y pago de aportes previsional-Habitat | D58: =5013.45+635.22 -> 5648.67 | E58: =D58/$D$6 -> 1706.5468 | F58: 45937 | G58: Cancelado | H58: =IF(OR(G58="Sin pagar",G58="Pagar"),(_xlfn.SINGLE(NETWORKDAYS($J$21,F58,FestivosPerú!$A$2:$A$15))),0) -> 0 | I58: =NETWORKDAYS($J$21,F58,FestivosPerú!$A$2:$A$15) -> 5 | J58: =H58 -> 0 | M58: Transferencia a la cta BBVA - mirar selma como se paga
B59: 2221507476 | C59: Planilla de declaración y pago de aportes previsional-Integra | D59: =3902.11+883.82 -> 4785.93 | E59: =D59/$D$6 -> 1445.9003 | F59: 45937 | G59: Cancelado | H59: =IF(OR(G59="Sin pagar",G59="Pagar"),(_xlfn.SINGLE(NETWORKDAYS($J$21,F59,FestivosPerú!$A$2:$A$15))),0) -> 0 | I59: =NETWORKDAYS($J$21,F59,FestivosPerú!$A$2:$A$15) -> 5 | J59: =H59 -> 0
B60: 2517226428 | C60: Planilla de declaración y pago de aportes previsional-Prima | D60: =3598.07+643.59 -> 4241.66 | E60: =D60/$D$6 -> 1281.4683 | F60: 45937 | G60: Cancelado | H60: =IF(OR(G60="Sin pagar",G60="Pagar"),(_xlfn.SINGLE(NETWORKDAYS($J$21,F60,FestivosPerú!$A$2:$A$15))),0) -> 0 | I60: =NETWORKDAYS($J$21,F60,FestivosPerú!$A$2:$A$15) -> 5 | J60: =H60 -> 0
B61: 2314312780 | C61: Planilla de declaración y pago de aportes previsional-Profuturo | D61: =2316.02+558.34 -> 2874.36 | E61: =D61/$D$6 -> 868.38671 | F61: 45937 | G61: Cancelado | H61: =IF(OR(G61="Sin pagar",G61="Pagar"),(_xlfn.SINGLE(NETWORKDAYS($J$21,F61,FestivosPerú!$A$2:$A$15))),0) -> 0 | I61: =NETWORKDAYS($J$21,F61,FestivosPerú!$A$2:$A$15) -> 5 | J61: =H61 -> 0
C62: IMPUESTOS | D62: =SUBTOTAL(9,D63:D64) -> 69561 | E62: =SUBTOTAL(9,E63:E64) -> 21015.408 | H62: =IF(OR(G62="Sin pagar",G62="Pagar"),(_xlfn.SINGLE(NETWORKDAYS($J$21,F62,FestivosPerú!$A$2:$A$15))),0) -> 0 | J62: =H62 -> 0
B63: S/N | C63: Plame Essalud y Renta de Quinta Categoría (Retención)-SG | D63: 32927 | E63: =D63/$D$6 -> 9947.7341 | F63: 45947 | G63: Cancelado | H63: =IF(OR(G63="Sin pagar",G63="Pagar"),(_xlfn.SINGLE(NETWORKDAYS($J$21,F63,FestivosPerú!$A$2:$A$15))),0) -> 0 | I63: =NETWORKDAYS($J$21,F63,FestivosPerú!$A$2:$A$15) -> 12 | J63: =H63 -> 0 | M63: Entrar Sunat -busca impuesto-debito T
B64: 1150159812 | C64: Pago de renta IGV Septiembre | D64: 36634 | E64: =D64/$D$6 -> 11067.674 | F64: 45947 | G64: Cancelado | H64: =IF(OR(G64="Sin pagar",G64="Pagar"),(_xlfn.SINGLE(NETWORKDAYS($J$21,F64,FestivosPerú!$A$2:$A$15))),0) -> 0 | I64: =NETWORKDAYS($J$21,F64,FestivosPerú!$A$2:$A$15) -> 12 | J64: =H64 -> 0 | M64: Por NPS que da OC -Ingresa a BCP y pagar servicios buscar Sunat/Pago con NPS y con el Nro
C65: PÓLIZAS DE VIDA Y SEGUROS MÉDICO | D65: =SUBTOTAL(9,D66:D70) -> 3473.82 | E65: =SUBTOTAL(9,E66:E70) -> 1049.4924 | H65: =IF(OR(G65="Sin pagar",G65="Pagar"),(_xlfn.SINGLE(NETWORKDAYS($J$21,F65,FestivosPerú!$A$2:$A$15))),0) -> 0
B66: F548 - 00464579 | C66: Pago Rimac-EPS | D66: 2434.16 | E66: =D66/$D$6 -> 735.39577 | F66: 45954 | G66: Cancelado | H66: =IF(OR(G66="Sin pagar",G66="Pagar"),(_xlfn.SINGLE(NETWORKDAYS($J$21,F66,FestivosPerú!$A$2:$A$15))),0) -> 0 | I66: =NETWORKDAYS($J$21,F66,FestivosPerú!$A$2:$A$15) -> 17 | J66: =H66 -> 0
B67: 338725425 | C67: Pago positiva-Pensión- Poliza 30404323 Juan Ulises Aguirre | D67: 123.9 | E67: =D67/$D$6 -> 37.432024 | F67: 45954 | G67: Cancelado | H67: =IF(OR(G67="Sin pagar",G67="Pagar"),(_xlfn.SINGLE(NETWORKDAYS($J$21,F67,FestivosPerú!$A$2:$A$15))),0) -> 0 | I67: =NETWORKDAYS($J$21,F67,FestivosPerú!$A$2:$A$15) -> 17 | J67: =H67 -> 0
B68: 806680667 | C68: Pago positiva-EPS- Juan Ulises Aguirre | D68: 152.26 | E68: =D68/$D$6 -> 46 | F68: 45954 | G68: Cancelado | H68: =IF(OR(G68="Sin pagar",G68="Pagar"),(_xlfn.SINGLE(NETWORKDAYS($J$21,F68,FestivosPerú!$A$2:$A$15))),0) -> 0 | I68: =NETWORKDAYS($J$21,F68,FestivosPerú!$A$2:$A$15) -> 17 | J68: =H68 -> 0
B69: 2929869 | C69: Poliza vida Pacifico -18815106 | D69: 763.5 | E69: =D69/$D$6 -> 230.66465 | F69: 45954 | G69: Cancelado | H69: =IF(OR(G69="Sin pagar",G69="Pagar"),(_xlfn.SINGLE(NETWORKDAYS($J$21,F69,FestivosPerú!$A$2:$A$15))),0) -> 0 | I69: =NETWORKDAYS($J$21,F69,FestivosPerú!$A$2:$A$15) -> 17 | J69: =H69 -> 0
B70: F548 - 00466375 | C70: Pago Rimac-EPS | D70: =393*0 -> 0 | E70: =D70/$D$6 -> 0 | F70: 45961 | G70: Cancelado | H70: =IF(OR(G70="Sin pagar",G70="Pagar"),(_xlfn.SINGLE(NETWORKDAYS($J$21,F70,FestivosPerú!$A$2:$A$15))),0) -> 0 | I70: =NETWORKDAYS($J$21,F70,FestivosPerú!$A$2:$A$15) -> 22 | J70: =H70 -> 0
C71: NÓMINAS -SAFEGUARD | D71: =SUBTOTAL(9,D72:D84) -> 160076.32 | E71: =SUBTOTAL(9,E72:E84) -> 48361.425 | H71: =IF(OR(G71="Sin pagar",G71="Pagar"),(_xlfn.SINGLE(NETWORKDAYS($J$21,F71,FestivosPerú!$A$2:$A$15))),0) -> 0
C72: Juan Ulises Aguirre Tacunan | D72: 10061.644 | E72: =D72/$D$6 -> 3039.7715 | F72: 45958 | G72: Cancelado | H72: =IF(OR(G72="Sin pagar",G72="Pagar"),(_xlfn.SINGLE(NETWORKDAYS($J$21,F72,FestivosPerú!$A$2:$A$15))),0) -> 0 | I72: =NETWORKDAYS($J$21,F72,FestivosPerú!$A$2:$A$15) -> 19 | J72: =H72 -> 0
C73: Angel Augusto Allauca Garcia | D73: 9435.4637 | E73: =D73/$D$6 -> 2850.5933 | F73: 45958 | G73: Cancelado | H73: =IF(OR(G73="Sin pagar",G73="Pagar"),(_xlfn.SINGLE(NETWORKDAYS($J$21,F73,FestivosPerú!$A$2:$A$15))),0) -> 0 | I73: =NETWORKDAYS($J$21,F73,FestivosPerú!$A$2:$A$15) -> 19 | J73: =H73 -> 0
C74: Natalia Marianella Florian Parra | D74: 6647.24 | E74: =D74/$D$6 -> 2008.2296 | F74: 45958 | G74: Cancelado | H74: =IF(OR(G74="Sin pagar",G74="Pagar"),(_xlfn.SINGLE(NETWORKDAYS($J$21,F74,FestivosPerú!$A$2:$A$15))),0) -> 0 | I74: =NETWORKDAYS($J$21,F74,FestivosPerú!$A$2:$A$15) -> 19 | J74: =H74 -> 0
C75: Adriana Jimena Elera Tejada | D75: 19623.624 | E75: =D75/$D$6 -> 5928.5872 | F75: 45958 | G75: Cancelado | H75: =IF(OR(G75="Sin pagar",G75="Pagar"),(_xlfn.SINGLE(NETWORKDAYS($J$21,F75,FestivosPerú!$A$2:$A$15))),0) -> 0 | I75: =NETWORKDAYS($J$21,F75,FestivosPerú!$A$2:$A$15) -> 19 | J75: =H75 -> 0
C76: Abraham Luis Enrique Vela Trujillo | D76: 14192.834 | E76: =D76/$D$6 -> 4287.8652 | F76: 45958 | G76: Cancelado | H76: =IF(OR(G76="Sin pagar",G76="Pagar"),(_xlfn.SINGLE(NETWORKDAYS($J$21,F76,FestivosPerú!$A$2:$A$15))),0) -> 0 | I76: =NETWORKDAYS($J$21,F76,FestivosPerú!$A$2:$A$15) -> 19 | J76: =H76 -> 0
C77: Fiorella maribel chavez torriani | D77: 4452.9878 | E77: =D77/$D$6 -> 1345.3135 | F77: 45958 | G77: Cancelado | H77: =IF(OR(G77="Sin pagar",G77="Pagar"),(_xlfn.SINGLE(NETWORKDAYS($J$21,F77,FestivosPerú!$A$2:$A$15))),0) -> 0 | I77: =NETWORKDAYS($J$21,F77,FestivosPerú!$A$2:$A$15) -> 19 | J77: =H77 -> 0
C78: Esteban Gonzalo Arias Suarez | D78: 5328.4236 | E78: =D78/$D$6 -> 1609.7957 | F78: 45958 | G78: Cancelado | H78: =IF(OR(G78="Sin pagar",G78="Pagar"),(_xlfn.SINGLE(NETWORKDAYS($J$21,F78,FestivosPerú!$A$2:$A$15))),0) -> 0 | I78: =NETWORKDAYS($J$21,F78,FestivosPerú!$A$2:$A$15) -> 19 | J78: =H78 -> 0
C79: David Eduardo Estela Guzman | D79: 5311.5903 | E79: =D79/$D$6 -> 1604.7101 | F79: 45958 | G79: Cancelado | H79: =IF(OR(G79="Sin pagar",G79="Pagar"),(_xlfn.SINGLE(NETWORKDAYS($J$21,F79,FestivosPerú!$A$2:$A$15))),0) -> 0 | I79: =NETWORKDAYS($J$21,F79,FestivosPerú!$A$2:$A$15) -> 19 | J79: =H79 -> 0
C80: Sergio Martin Gustin García | D80: 39008.324 | E80: =D80/$D$6 -> 11784.992 | F80: 45958 | G80: Cancelado | H80: =IF(OR(G80="Sin pagar",G80="Pagar"),(_xlfn.SINGLE(NETWORKDAYS($J$21,F80,FestivosPerú!$A$2:$A$15))),0) -> 0 | I80: =NETWORKDAYS($J$21,F80,FestivosPerú!$A$2:$A$15) -> 19 | J80: =H80 -> 0
C81: Olga Alejandra Paredes Paucarcaja | D81: 12384.644 | E81: =D81/$D$6 -> 3741.5842 | F81: 45958 | G81: Cancelado | H81: =IF(OR(G81="Sin pagar",G81="Pagar"),(_xlfn.SINGLE(NETWORKDAYS($J$21,F81,FestivosPerú!$A$2:$A$15))),0) -> 0 | I81: =NETWORKDAYS($J$21,F81,FestivosPerú!$A$2:$A$15) -> 19 | J81: =H81 -> 0
C82: Martin Rolando Felix García | D82: 12084.347 | E82: =D82/$D$6 -> 3650.8602 | F82: 45958 | G82: Cancelado | H82: =IF(OR(G82="Sin pagar",G82="Pagar"),(_xlfn.SINGLE(NETWORKDAYS($J$21,F82,FestivosPerú!$A$2:$A$15))),0) -> 0 | I82: =NETWORKDAYS($J$21,F82,FestivosPerú!$A$2:$A$15) -> 19 | J82: =H82 -> 0
C83: Johanna Ximena Cordova Sanchez | D83: 7805.7918 | E83: =D83/$D$6 -> 2358.2452 | F83: 45960 | G83: Cancelado | H83: =IF(OR(G83="Sin pagar",G83="Pagar"),(_xlfn.SINGLE(NETWORKDAYS($J$21,F83,FestivosPerú!$A$2:$A$15))),0) -> 0 | I83: =NETWORKDAYS($J$21,F83,FestivosPerú!$A$2:$A$15) -> 21 | J83: =H83 -> 0 | M83: 7807.32 | N83: =M83-E83 -> 5449.0748
C84: Melissa Lizeth Guadalupe Huertas | D84: 13739.404 | E84: =D84/$D$6 -> 4150.8773 | F84: 45959 | G84: Cancelado | H84: =IF(OR(G84="Sin pagar",G84="Pagar"),(_xlfn.SINGLE(NETWORKDAYS($J$21,F84,FestivosPerú!$A$2:$A$15))),0) -> 0 | I84: =NETWORKDAYS($J$21,F84,FestivosPerú!$A$2:$A$15) -> 20 | J84: =H84 -> 0
C85: REEMBOLSO -SAFEGUARD | D85: =SUBTOTAL(9,D86:D92) -> 14914.868 | E85: =SUBTOTAL(9,E86:E92) -> 4506.0024 | H85: =IF(OR(G85="Sin pagar",G85="Pagar"),(_xlfn.SINGLE(NETWORKDAYS($J$21,F85,FestivosPerú!$A$2:$A$15))),0) -> 0
C86: Juan Ulises Aguirre Tucunan -Soles | D86: 790.7 | E86: =D86/$D$6 -> 238.88218 | F86: 45958 | G86: Cancelado | H86: =IF(OR(G86="Sin pagar",G86="Pagar"),(_xlfn.SINGLE(NETWORKDAYS($J$21,F86,FestivosPerú!$A$2:$A$15))),0) -> 0 | I86: =NETWORKDAYS($J$21,F86,FestivosPerú!$A$2:$A$15) -> 19 | J86: =H86 -> 0
C87: Sergio Martin Gustin García-Soles | D87: 215 | E87: =D87/$D$6 -> 64.954683 | F87: 45958 | G87: Cancelado | H87: =IF(OR(G87="Sin pagar",G87="Pagar"),(_xlfn.SINGLE(NETWORKDAYS($J$21,F87,FestivosPerú!$A$2:$A$15))),0) -> 0 | I87: =NETWORKDAYS($J$21,F87,FestivosPerú!$A$2:$A$15) -> 19 | J87: =H87 -> 0
C88: Abraham Luis Enrique Vela Trujillo-Soles | D88: 605.81 | E88: =D88/$D$6 -> 183.02417 | F88: 45958 | G88: Cancelado | H88: =IF(OR(G88="Sin pagar",G88="Pagar"),(_xlfn.SINGLE(NETWORKDAYS($J$21,F88,FestivosPerú!$A$2:$A$15))),0) -> 0 | I88: =NETWORKDAYS($J$21,F88,FestivosPerú!$A$2:$A$15) -> 19 | J88: =H88 -> 0
C89: Martin Rolando Felix García -Soles | D89: 5500 | E89: =D89/$D$6 -> 1661.6314 | F89: 45960 | G89: Cancelado | H89: =IF(OR(G89="Sin pagar",G89="Pagar"),(_xlfn.SINGLE(NETWORKDAYS($J$21,F89,FestivosPerú!$A$2:$A$15))),0) -> 0 | I89: =NETWORKDAYS($J$21,F89,FestivosPerú!$A$2:$A$15) -> 21 | J89: =H89 -> 0
C90: Juan Ulises Aguirre Tucunan -USD | D90: =E90*$D$6 -> 5446.4726 | E90: 1645.46 | F90: 45958 | G90: Cancelado | H90: =IF(OR(G90="Sin pagar",G90="Pagar"),(_xlfn.SINGLE(NETWORKDAYS($J$21,F90,FestivosPerú!$A$2:$A$15))),0) -> 0 | I90: =NETWORKDAYS($J$21,F90,FestivosPerú!$A$2:$A$15) -> 19 | J90: =H90 -> 0
C91: Sergio Martin Gustin García-USD | D91: =E91*$D$6 -> 288.632 | E91: 87.2 | F91: 45959 | G91: Cancelado | H91: =IF(OR(G91="Sin pagar",G91="Pagar"),(_xlfn.SINGLE(NETWORKDAYS($J$21,F91,FestivosPerú!$A$2:$A$15))),0) -> 0 | I91: =NETWORKDAYS($J$21,F91,FestivosPerú!$A$2:$A$15) -> 20 | J91: =H91 -> 0
C92: Abraham Luis Enrique Vela Trujillo-USD | D92: =E92*$D$6 -> 2068.2535 | E92: 624.85 | F92: 45959 | G92: Cancelado | H92: =IF(OR(G92="Sin pagar",G92="Pagar"),(_xlfn.SINGLE(NETWORKDAYS($J$21,F92,FestivosPerú!$A$2:$A$15))),0) -> 0 | I92: =NETWORKDAYS($J$21,F92,FestivosPerú!$A$2:$A$15) -> 20 | J92: =H92 -> 0
C93: IMPREVISTO | D93: =SUBTOTAL(9,D94:D95) -> 39159.96 | E93: =SUBTOTAL(9,E94:E95) -> 15823.771 | H93: =IF(OR(G93="Sin pagar",G93="Pagar"),(_xlfn.SINGLE(NETWORKDAYS($J$21,F93,FestivosPerú!$A$2:$A$15))),0) -> 0
B94: E001-1040 | C94: Consultora SVC SAC - Implementación del Sistema gestión SST SAFEGUARD GLOBAL PERU | D94: 1327.5 | E94: =D94*$D$6 -> 4394.025 | F94: 45939 | G94: Cancelado | H94: =IF(OR(G94="Sin pagar",G94="Pagar"),(_xlfn.SINGLE(NETWORKDAYS($J$21,F94,FestivosPerú!$A$2:$A$15))),0) -> 0 | I94: =NETWORKDAYS($J$21,F94,FestivosPerú!$A$2:$A$15) -> 6 | J94: =H94 -> 0
B95: S/N | C95: Renovación Póliza Safeguard Perú | D95: 37832.46 | E95: =D95/$D$6 -> 11429.746 | F95: 45960 | G95: Cancelado | H95: =IF(OR(G95="Sin pagar",G95="Pagar"),(_xlfn.SINGLE(NETWORKDAYS($J$21,F95,FestivosPerú!$A$2:$A$15))),0) -> 0 | I95: =NETWORKDAYS($J$21,F95,FestivosPerú!$A$2:$A$15) -> 21 | J95: =H95 -> 0
C96: TOTAL EGRESOS | D96: =SUBTOTAL(9,D23:D95) -> 422414.97 | E96: =SUBTOTAL(9,E23:E95) -> 131610.78
C98: SALDO | D98: =D18-D96 -> 261568.91 | E98: =E18-E96 -> 74676.315
C99: % | D99: =IF($D$18=0,0,D98/$D$18) -> 0.3824197 | E99: =IF($E$18=0,0,E98/$E$18) -> 0.36200187
C102: 45931 | D102: 45935 | E102: =SUMIFS($D$22:$D$100,$F$22:$F$100,">="&C102,$F$22:$F$100,"<="&D102,$G$22:$G$100,$D$120) -> 0 | F102: =SUMIFS($D$22:$D$100,$F$22:$F$100,">="&C102,$F$22:$F$100,"<="&D102,$G$22:$G$100,$D$120) -> 0 | G102: Planilla de declaración
C103: 45936 | D103: 45936 | E103: =SUMIFS($D$22:$D$100,$F$22:$F$100,">="&C103,$F$22:$F$100,"<="&D103,$G$22:$G$100,$D$120) -> 0 | F103: =SUMIFS($E$22:$E$100,$F$22:$F$100,">="&C103,$F$22:$F$100,"<="&D103,$G$22:$G$100,$D$120) -> 0 | G103: Planilla de declaración y pago de aportes previsional
C104: 45937 | D104: 45942 | E104: =SUMIFS($D$22:$D$100,$F$22:$F$100,">="&C104,$F$22:$F$100,"<="&D104,$G$22:$G$100,$D$120) -> 0 | F104: =SUMIFS($E$22:$E$100,$F$22:$F$100,">="&C104,$F$22:$F$100,"<="&D104,$G$22:$G$100,$D$120) -> 0 | G104: Plame Essalud y Renta de Quinta Categoría (Retención)
C105: 45943 | D105: 45943 | E105: =SUMIFS($D$22:$D$100,$F$22:$F$100,">="&C105,$F$22:$F$100,"<="&D105,$G$22:$G$100,$D$120) -> 0 | F105: =SUMIFS($E$22:$E$100,$F$22:$F$100,">="&C105,$F$22:$F$100,"<="&D105,$G$22:$G$100,$D$120) -> 0
C106: 45944 | D106: 45944 | E106: =SUMIFS($D$22:$D$100,$F$22:$F$100,">="&C106,$F$22:$F$100,"<="&D106,$G$22:$G$100,$D$120) -> 0 | F106: =SUMIFS($E$22:$E$100,$F$22:$F$100,">="&C106,$F$22:$F$100,"<="&D106,$G$22:$G$100,$D$120) -> 0 | G106: Renta Agosto S&P
C107: 45945 | D107: 45949 | E107: =SUMIFS($D$22:$D$100,$F$22:$F$100,">="&C107,$F$22:$F$100,"<="&D107,$G$22:$G$100,$D$120) -> 0 | F107: =SUMIFS($E$22:$E$100,$F$22:$F$100,">="&C107,$F$22:$F$100,"<="&D107,$G$22:$G$100,$D$120) -> 0 | G107: Previstos
C108: 45950 | D108: 45956 | E108: =SUMIFS($D$22:$D$100,$F$22:$F$100,">="&C108,$F$22:$F$100,"<="&D108,$G$22:$G$100,$D$120) -> 0 | F108: =SUMIFS($E$22:$E$100,$F$22:$F$100,">="&C108,$F$22:$F$100,"<="&D108,$G$22:$G$100,$D$120) -> 0 | G108: Pólizas Positiva-Rimac-Pacifico
...

Sheet FLUJO CAJA NOVIEMBRE
D1: 42400
D4: Fecha de Elaboración: | E4: 45962
C6: Tasa de cambio: | D6: 3.31
D7: NOVIEMBRE
D8: VALOR S/ Sol | E8: VALOR USD
C9: BANCOS | D9: =SUBTOTAL(9,D10:D12) -> 261979.93 | E9: =SUBTOTAL(9,E10:E12) -> 79148.015
C10: Bancos S/ Soles | D10: ='BCP SOLES BCP'!$G$610 -> 234887.31 | E10: =D10/$D$6 -> 70962.932
C11: Bancos USD | D11: =E11*$D$6 -> 26681.613 | E11: ='BCP USD BCP'!$G$261 -> 8060.9104
C12: Devolución de dinero por avanza por pago CTS de la señora Fiorella Chavez-Safeguard | D12: ='BCP SOLES BCP'!$E$667 -> 411.01 | E12: =D12/D6 -> 124.17221
C13: CLIENTES | D13: =SUBTOTAL(9,D14:D23) -> 850909.78 | E13: =SUBTOTAL(9,E14:E23) -> 292587.47
B14: Sin Pagar | C14: Client: Safeguard-Factura Nro EB01-013( Cliente) SS e impuestos Claudia Vasquez ( Sept-Oct) | D14: =$E$14*3.2 -> 0 | E14: =2554.83*0 -> 0 | M14: =G14-J14 -> 0
B15: Pagado | C15: Client: Safeguard-Factura Nro EB01-015( Cliente)-CTS | D15: =E15/'Diferencia Cambio Global'!$K$13 -> 11389.372 | E15: ='Diferencia Cambio Global'!J13 -> 37550.76
B16: Pagado | C16: Client: Remotepass-Factura Nro 016 | D16: =E16*3.2 -> 20928.96 | E16: =6776.3-E19 -> 6540.3
D18: =E18*D6 -> 97930.918 | E18: 29586.38
B19: Pagado | C19: Client: Remotepass-Reembolso gastos Nro 034 | D19: =E19*3.2 -> 755.2 | E19: 236
B20: Pagado | C20: Client: Europortage-Factura Nro 017 | D20: =E20*3.2 -> 91089.344 | E20: ='BCP USD BCP'!E280-E21 -> 28465.42 | F20: 29459.42
B21: Pagado | C21: Client: Europortage-Reembolso gastos Nro 035 | D21: =E21*3.2 -> 3020.8 | E21: 944
B22: Pagado | C22: Client: Yonyou xinfushe cloud technology co., Factura Nro 020 | D22: =E22*3.2 -> 19510.368 | E22: =6096.99 -> 6096.99
B23: Pagado | C23: Client: Safeguard-Factura Nro EB01-016( Cliente) | D23: =E23*$D$6 -> 606284.82 | E23: ='BCP USD BCP'!E276+'BCP USD BCP'!E277 -> 183167.62 | F23: 183197.61 | G23: =+E23-F23 -> -29.99 | J23: Gasto financieros
C24: TOTAL INGRESOS | D24: =SUBTOTAL(9,D9:D23) -> 1112889.7 | E24: =SUBTOTAL(9,E9:E23) -> 371735.48
B27: CUENTAS X PAGAR MES | D27: NOVIEMBRE | F27: Fecha de Elaboración: | J27: 45962
B28: Factura | C28: PROVEEDOR | D28: VALOR S/Sol | E28: VALOR USD | F28: Fecha vencimiento | G28: Estado | J28: KPI
C29: SEGURIDAD IGSS | D29: =SUBTOTAL(9,D30:D32) -> 10516.72 | E29: =SUBTOTAL(9,E30:E32) -> 3177.2568
B30: 2221860127 | C30: Planilla de declaración y pago de aportes previsional Integra | D30: =4191.3+749.79 -> 4941.09 | E30: =D30/$D$6 -> 1492.7764 | F30: 45968 | G30: Cancelado | H30: =IF(OR(G30="Sin pagar",G30="Pagar"),(_xlfn.SINGLE(NETWORKDAYS($J$27,F30,FestivosPerú!$A$2:$A$15))),0) -> 0 | I30: =NETWORKDAYS($J$27,F30,FestivosPerú!$A$2:$A$15) -> 5 | J30: =H30 -> 0 | M30: AFP NET Selecciona debito BCP
B31: 2517434836 | C31: Planilla de declaración y pago de aportes previsional Prima | D31: =3452.52+108.63 -> 3561.15 | E31: =D31/$D$6 -> 1075.8761 | F31: 45968 | G31: Cancelado | H31: =IF(OR(G31="Sin pagar",G31="Pagar"),(_xlfn.SINGLE(NETWORKDAYS($J$27,F31,FestivosPerú!$A$2:$A$15))),0) -> 0 | I31: =NETWORKDAYS($J$27,F31,FestivosPerú!$A$2:$A$15) -> 5 | J31: =H31 -> 0
B32: 2609826962 | C32: Planilla de declaración y pago de aportes previsiona Habitat | D32: =1610.79+403.69 -> 2014.48 | E32: =D32/$D$6 -> 608.60423 | F32: 45968 | G32: Cancelado | H32: =IF(OR(G32="Sin pagar",G32="Pagar"),(_xlfn.SINGLE(NETWORKDAYS($J$27,F32,FestivosPerú!$A$2:$A$15))),0) -> 0 | I32: =NETWORKDAYS($J$27,F32,FestivosPerú!$A$2:$A$15) -> 5 | J32: =H32 -> 0
C33: IMPUESTOS | D33: =SUBTOTAL(9,D34:D35) -> 15569.27 | E33: =SUBTOTAL(9,E34:E35) -> 4703.7069 | H33: =IF(OR(G33="Sin pagar",G33="Pagar"),(_xlfn.SINGLE(NETWORKDAYS($J$27,F33,FestivosPerú!$A$2:$A$15))),0) -> 0 | J33: =H33 -> 0
C34: Plame Essalud y Renta de Quinta Categoría (Retención)-S&P | D34: 15456 | E34: =D34/$D$6 -> 4669.4864 | F34: 45975 | G34: Cancelado | H34: =IF(OR(G34="Sin pagar",G34="Pagar"),(_xlfn.SINGLE(NETWORKDAYS($J$27,F34,FestivosPerú!$A$2:$A$15))),0) -> 0 | I34: =NETWORKDAYS($J$27,F34,FestivosPerú!$A$2:$A$15) -> 10 | J34: =H34 -> 0 | M34: Sunat-presentación PDF-Winzip
C35: Pago de renta IGV Octubre | D35: 113.27 | E35: =D35/$D$6 -> 34.220544 | F35: 45974 | G35: Cancelado | H35: =IF(OR(G35="Sin pagar",G35="Pagar"),(_xlfn.SINGLE(NETWORKDAYS($J$27,F35,FestivosPerú!$A$2:$A$15))),0) -> 0 | I35: =NETWORKDAYS($J$27,F35,FestivosPerú!$A$2:$A$15) -> 9 | J35: =H35 -> 0 | M35: Outsorcing contable-Presenta contadora y debito automatico a la cta
C36: CTS S&P | D36: =SUBTOTAL(9,D37:D49) -> 42997.12 | E36: =SUBTOTAL(9,E37:E49) -> 11654.416 | H36: =IF(OR(G36="Sin pagar",G36="Pagar"),(_xlfn.SINGLE(NETWORKDAYS($J$27,F36,FestivosPerú!$A$2:$A$15))),0) -> 0
B37: BCP-ODT | C37: Braydi Yusset Vera Neira-Europortage | D37: 9356.5 | E37: =D37/$D$6 -> 2826.7372 | F37: 45973 | G37: Cancelado | H37: =IF(OR(G37="Sin pagar",G37="Pagar"),(_xlfn.SINGLE(NETWORKDAYS($J$27,F37,FestivosPerú!$A$2:$A$15))),0) -> 0 | I37: =NETWORKDAYS($J$27,F37,FestivosPerú!$A$2:$A$15) -> 8 | J37: =H37 -> 0 | M37: Sacar Soporte
B38: BCP-ODT | C38: Cristhian Portugal Segovia -Europortage | D38: 7000 | E38: =D38/$D$6 -> 2114.8036 | F38: 45973 | G38: Cancelado | H38: =IF(OR(G38="Sin pagar",G38="Pagar"),(_xlfn.SINGLE(NETWORKDAYS($J$27,F38,FestivosPerú!$A$2:$A$15))),0) -> 0 | I38: =NETWORKDAYS($J$27,F38,FestivosPerú!$A$2:$A$15) -> 8 | J38: =H38 -> 0 | M38: Sacar Soporte
B39: Caja arequipa | C39: Davis Cesar oporto figueroa -Europortage | D39: 7000 | E39: =D39/$D$6 -> 2114.8036 | F39: 45974 | G39: Cancelado | H39: =IF(OR(G39="Sin pagar",G39="Pagar"),(_xlfn.SINGLE(NETWORKDAYS($J$27,F39,FestivosPerú!$A$2:$A$15))),0) -> 0 | I39: =NETWORKDAYS($J$27,F39,FestivosPerú!$A$2:$A$15) -> 9 | J39: =H39 -> 0 | M39: Sacar Soporte
B40: BCP-ODT | C40: Luis Renato Sanchez Perez -Yon Yuo | D40: 4295 | E40: =D40/$D$6 -> 1297.5831 | F40: 45974 | G40: Cancelado | H40: =IF(OR(G40="Sin pagar",G40="Pagar"),(_xlfn.SINGLE(NETWORKDAYS($J$27,F40,FestivosPerú!$A$2:$A$15))),0) -> 0 | I40: =NETWORKDAYS($J$27,F40,FestivosPerú!$A$2:$A$15) -> 9 | J40: =H40 -> 0 | M40: Sacar Soporte
B41: BBVA-ODT | C41: Andres Felipe Uribe Avila -Europortage | D41: 1533.34 | E41: =D41/$D$6 -> 463.24471 | F41: 45974 | G41: Cancelado | H41: =IF(OR(G41="Sin pagar",G41="Pagar"),(_xlfn.SINGLE(NETWORKDAYS($J$27,F41,FestivosPerú!$A$2:$A$15))),0) -> 0 | I41: =NETWORKDAYS($J$27,F41,FestivosPerú!$A$2:$A$15) -> 9 | J41: =H41 -> 0 | M41: Sacar Soporte
B42: BBVA-USD-ODT | C42: Christiams Hebert Valle Gomez -Remotepass | D42: =$E$42*$D$6 -> 5305.2018 | E42: 1602.78 | F42: 45973 | G42: Cancelado | H42: =IF(OR(G42="Sin pagar",G42="Pagar"),(_xlfn.SINGLE(NETWORKDAYS($J$27,F42,FestivosPerú!$A$2:$A$15))),0) -> 0 | I42: =NETWORKDAYS($J$27,F42,FestivosPerú!$A$2:$A$15) -> 8 | J42: =H42 -> 0 | M42: Sacar Soporte
B43: BCP-ODT | C43: Braydi Yusset Vera Neira-Europortage-Ajuste | D43: 1299.5106 | E43: =D43/$D$6 -> 392.60138 | F43: 45975 | G43: Cancelado | H43: =IF(OR(G43="Sin pagar",G43="Pagar"),(_xlfn.SINGLE(NETWORKDAYS($J$27,F43,FestivosPerú!$A$2:$A$15))),0) -> 0 | I43: =NETWORKDAYS($J$27,F43,FestivosPerú!$A$2:$A$15) -> 10 | J43: =H43 -> 0 | M43: Sacar Soporte
B44: BCP-ODT | C44: Cristhian Portugal Segovia -Europortage-Ajuste | D44: 583.33333 | E44: =D44/$D$6 -> 176.23364 | F44: 45975 | G44: Cancelado | H44: =IF(OR(G44="Sin pagar",G44="Pagar"),(_xlfn.SINGLE(NETWORKDAYS($J$27,F44,FestivosPerú!$A$2:$A$15))),0) -> 0 | I44: =NETWORKDAYS($J$27,F44,FestivosPerú!$A$2:$A$15) -> 10 | J44: =H44 -> 0 | M44: Sacar Soporte
B45: Caja arequipa | C45: Davis Cesar oporto figueroa -Europortage-Ajuste | D45: 388.88889 | E45: =D45/$D$6 -> 117.48909 | F45: 45975 | G45: Cancelado | H45: =IF(OR(G45="Sin pagar",G45="Pagar"),(_xlfn.SINGLE(NETWORKDAYS($J$27,F45,FestivosPerú!$A$2:$A$15))),0) -> 0 | I45: =NETWORKDAYS($J$27,F45,FestivosPerú!$A$2:$A$15) -> 10 | J45: =H45 -> 0 | M45: Sacar Soporte
B46: BCP-ODT | C46: Luis Renato Sanchez Perez -Yon Yuo-Ajuste | D46: 37.673333 | E46: =D46/$D$6 -> 11.381672 | F46: 45975 | G46: Cancelado | H46: =IF(OR(G46="Sin pagar",G46="Pagar"),(_xlfn.SINGLE(NETWORKDAYS($J$27,F46,FestivosPerú!$A$2:$A$15))),0) -> 0 | I46: =NETWORKDAYS($J$27,F46,FestivosPerú!$A$2:$A$15) -> 10 | J46: =H46 -> 0 | M46: Sacar Soporte
B47: BBVA-USD-ODT | C47: Christiams Hebert Valle Gomez -Remotepass-Ajuste | D47: =$E$42*$D$6 -> 5305.2018 | E47: 267.13 | F47: 45987 | G47: Cancelado | H47: =IF(OR(G47="Sin pagar",G47="Pagar"),(_xlfn.SINGLE(NETWORKDAYS($J$27,F47,FestivosPerú!$A$2:$A$15))),0) -> 0 | I47: =NETWORKDAYS($J$27,F47,FestivosPerú!$A$2:$A$15) -> 18 | J47: =H47 -> 0 | M47: Sacar Soporte
B48: BCP-ODT | C48: Luis Renato Sanchez Perez -Yon Yuo-Ajuste | D48: 722.11 | E48: =D48/$D$6 -> 218.16012 | F48: 45987 | G48: Cancelado | H48: =IF(OR(G48="Sin pagar",G48="Pagar"),(_xlfn.SINGLE(NETWORKDAYS($J$27,F48,FestivosPerú!$A$2:$A$15))),0) -> 0 | I48: =NETWORKDAYS($J$27,F48,FestivosPerú!$A$2:$A$15) -> 18 | J48: =H48 -> 0 | M48: Sacar Soporte
B49: BBVA-ODT | C49: Andres Felipe Uribe Avila -Europortage-Ajuste | D49: 170.36 | E49: =D49/$D$6 -> 51.468278 | F49: 45988 | G49: Cancelado | H49: =IF(OR(G49="Sin pagar",G49="Pagar"),(_xlfn.SINGLE(NETWORKDAYS($J$27,F49,FestivosPerú!$A$2:$A$15))),0) -> 0 | I49: =NETWORKDAYS($J$27,F49,FestivosPerú!$A$2:$A$15) -> 19 | J49: =H49 -> 0 | M49: Sacar Soporte
C50: SERVICIOS OUTSORCING CONTABLE | D50: =SUBTOTAL(9,D51:D53) -> 4012 | E50: =SUBTOTAL(9,E51:E53) -> 1212.0846 | H50: =IF(OR(G50="Sin pagar",G50="Pagar"),(_xlfn.SINGLE(NETWORKDAYS($J$27,F50,FestivosPerú!$A$2:$A$15))),0) -> 0 | J50: =H50 -> 0
B51: E001-713 | C51: Pago CTS Safeguar y S&P mes de noviembre | D51: 1180 | E51: =D51/$D$6 -> 356.49547 | F51: 45981 | G51: Cancelado | H51: =IF(OR(G51="Sin pagar",G51="Pagar"),(_xlfn.SINGLE(NETWORKDAYS($J$27,F51,FestivosPerú!$A$2:$A$15))),0) -> 0 | I51: =NETWORKDAYS($J$27,F51,FestivosPerú!$A$2:$A$15) -> 14 | J51: =H51 -> 0
B52: E001-733 | C52: Outsourcing contable servicio septiembre a SG- Avanza | D52: 1416 | E52: =D52/$D$6 -> 427.79456 | F52: 45988 | G52: Cancelado | H52: =IF(OR(G52="Sin pagar",G52="Pagar"),(_xlfn.SINGLE(NETWORKDAYS($J$27,F52,FestivosPerú!$A$2:$A$15))),0) -> 0 | I52: =NETWORKDAYS($J$27,F52,FestivosPerú!$A$2:$A$15) -> 19 | J52: =H52 -> 0
B53: E001-726 | C53: Outsourcing contable servicio septiembre a S&P- Avanza | D53: 1416 | E53: =D53/$D$6 -> 427.79456 | F53: 45988 | G53: Cancelado | H53: =IF(OR(G53="Sin pagar",G53="Pagar"),(_xlfn.SINGLE(NETWORKDAYS($J$27,F53,FestivosPerú!$A$2:$A$15))),0) -> 0 | I53: =NETWORKDAYS($J$27,F53,FestivosPerú!$A$2:$A$15) -> 19 | J53: =H53 -> 0
C54: PÓLIZAS DE VIDA Y SEGUROS MÉDICO | D54: =SUBTOTAL(9,D55:D60) -> 3536.48 | E54: =SUBTOTAL(9,E56:E60) -> 581.36556 | H54: =IF(OR(G54="Sin pagar",G54="Pagar"),(_xlfn.SINGLE(NETWORKDAYS($J$27,F54,FestivosPerú!$A$2:$A$15))),0) -> 0
C55: Pago Seguros de vida Ley recibo Rimac Davis oporto | D55: 1612.16 | E55: =D55/$D$6 -> 487.0574 | F55: 45962 | G55: Cancelado | M55: Débito automático-Conseguir factura
B56: S/N | C56: Seguros de vida Rimac -Andrés Felipe Uribe ( 3er mes)- Europortage-Nov | D56: 926 | E56: =D56/$D$6 -> 279.75831 | F56: 45972 | G56: Cancelado | H56: =IF(OR(G56="Sin pagar",G56="Pagar"),(_xlfn.SINGLE(NETWORKDAYS($J$27,F56,FestivosPerú!$A$2:$A$15))),0) -> 0 | I56: =NETWORKDAYS($J$27,F56,FestivosPerú!$A$2:$A$15) -> 7 | J56: =H56 -> 0
B57: F052-01734497 | C57: SCTR Salud Europartage recibo 166547249-Dic | D57: 344.88 | E57: =D57/$D$6 -> 104.19335 | F57: 45987 | G57: Cancelado | H57: =IF(OR(G57="Sin pagar",G57="Pagar"),(_xlfn.SINGLE(NETWORKDAYS($J$27,F57,FestivosPerú!$A$2:$A$15))),0) -> 0 | I57: =NETWORKDAYS($J$27,F57,FestivosPerú!$A$2:$A$15) -> 18 | J57: =H57 -> 0
B58: F052-01965812 | C58: SCTR Pensiones europortage recibo 166547248 -Dic | D58: 355.23 | E58: =D58/$D$6 -> 107.32024 | F58: 45987 | G58: Cancelado | H58: =IF(OR(G58="Sin pagar",G58="Pagar"),(_xlfn.SINGLE(NETWORKDAYS($J$27,F58,FestivosPerú!$A$2:$A$15))),0) -> 0 | I58: =NETWORKDAYS($J$27,F58,FestivosPerú!$A$2:$A$15) -> 18 | J58: =H58 -> 0
B59: F052-01965811 | C59: Seguros de vida Europortage Ley recibo 166547316 -Dic | D59: =118 -> 118 | E59: =D59/$D$6 -> 35.649547 | F59: 45987 | G59: Cancelado | H59: =IF(OR(G59="Sin pagar",G59="Pagar"),(_xlfn.SINGLE(NETWORKDAYS($J$27,F59,FestivosPerú!$A$2:$A$15))),0) -> 0 | I59: =NETWORKDAYS($J$27,F59,FestivosPerú!$A$2:$A$15) -> 18 | J59: =H59 -> 0
B60: F052-01965813 | C60: SCTR Salud recibo 166547298- Yon you-Dic | D60: 180.21 | E60: =D60/$D$6 -> 54.444109 | F60: 45987 | G60: Cancelado | H60: =IF(OR(G60="Sin pagar",G60="Pagar"),(_xlfn.SINGLE(NETWORKDAYS($J$27,F60,FestivosPerú!$A$2:$A$15))),0) -> 0 | I60: =NETWORKDAYS($J$27,F60,FestivosPerú!$A$2:$A$15) -> 18 | J60: =H60 -> 0
C61: COSTOS FINANCIEROS | D61: =SUBTOTAL(9,D62:D63) -> 161.9276 | E61: =SUBTOTAL(9,E62:E63) -> 48.920725 | H61: =IF(OR(G61="Sin pagar",G61="Pagar"),(_xlfn.SINGLE(NETWORKDAYS($J$27,F61,FestivosPerú!$A$2:$A$15))),0) -> 0
C62: Costos financieros Soles | D62: =(('BCP SOLES BCP'!F610+'BCP SOLES BCP'!F631+'BCP SOLES BCP'!F635+'BCP SOLES BCP'!F644+'BCP SOLES BCP'!F652+'BCP SOLES BCP'!F661+'BCP SOLES BCP'!F663+'BCP SOLES BCP'!F664/2+'BCP SOLES BCP'!F678+'BCP SOLES BCP'!F693+'BCP SOLES BCP'!F694+'BCP SOLES BCP'!F696+'BCP SOLES BCP'!F697+'BCP SOLES BCP'!F700+'BCP SOLES BCP'!F701+'BCP SOLES BCP'!F710+'BCP SOLES BCP'!F713/2+'BCP SOLES BCP'!F714))+'BBVA SOLES'!F20+'BBVA SOLES'!F28+('BBVA SOLES'!F36/2) -> 89.24 | E62: =$D$62/$D$6 -> 26.960725 | F62: 45991 | G62: Cancelado | H62: =IF(OR(G62="Sin pagar",G62="Pagar"),(_xlfn.SINGLE(NETWORKDAYS($J$27,F62,FestivosPerú!$A$2:$A$15))),0) -> 0 | I62: =NETWORKDAYS($J$27,F62,FestivosPerú!$A$2:$A$15) -> 20 | J62: =H62 -> 0
C63: Costos financieros USD | D63: =E63*D6 -> 72.6876 | E63: =('BCP USD BCP'!F261/2)+'BCP USD BCP'!F263+('BCP USD BCP'!F275/2)+'BCP USD BCP'!F281+('BCP USD BCP'!F282/2)+('BCP USD BCP'!F283/2)+'BCP USD BCP'!F296+'BCP USD BCP'!F297+'BCP USD BCP'!F301+('BCP USD BCP'!F302/2)+('BCP USD BCP'!F303/2)+'BBVA USD'!F15+('BBVA USD'!F16/2) -> 21.96 | F63: 45991 | G63: Cancelado | H63: =IF(OR(G63="Sin pagar",G63="Pagar"),(_xlfn.SINGLE(NETWORKDAYS($J$27,F63,FestivosPerú!$A$2:$A$15))),0) -> 0 | I63: =NETWORKDAYS($J$27,F63,FestivosPerú!$A$2:$A$15) -> 20 | J63: =H63 -> 0
C64: NÓMINAS CLIENTES S&P | D64: =SUBTOTAL(9,D65:D70) -> 67373.123 | E64: =SUBTOTAL(9,E65:E70) -> 20354.418 | H64: =IF(OR(G64="Sin pagar",G64="Pagar"),(_xlfn.SINGLE(NETWORKDAYS($J$27,F64,FestivosPerú!$A$2:$A$15))),0) -> 0
B65: Soles | C65: Braydi Yusset Vera Neira-Europortage | D65: 14314.77 | E65: =D65/$D$6 -> 4324.7039 | F65: 45988 | G65: Cancelado | H65: =IF(OR(G65="Sin pagar",G65="Pagar"),(_xlfn.SINGLE(NETWORKDAYS($J$27,F65,FestivosPerú!$A$2:$A$15))),0) -> 0 | I65: =NETWORKDAYS($J$27,F65,FestivosPerú!$A$2:$A$15) -> 19 | J65: =H65 -> 0
B66: Soles | C66: Cristhian Portugal Segovia -Europortage | D66: 11107.4 | E66: =D66/$D$6 -> 3355.71 | F66: 45988 | G66: Cancelado | H66: =IF(OR(G66="Sin pagar",G66="Pagar"),(_xlfn.SINGLE(NETWORKDAYS($J$27,F66,FestivosPerú!$A$2:$A$15))),0) -> 0 | I66: =NETWORKDAYS($J$27,F66,FestivosPerú!$A$2:$A$15) -> 19 | J66: =H66 -> 0
B67: Soles | C67: Davis Cesar oporto figueroa -Europortage | D67: 10944.19 | E67: =D67/$D$6 -> 3306.4018 | F67: 45988 | G67: Cancelado | H67: =IF(OR(G67="Sin pagar",G67="Pagar"),(_xlfn.SINGLE(NETWORKDAYS($J$27,F67,FestivosPerú!$A$2:$A$15))),0) -> 0 | I67: =NETWORKDAYS($J$27,F67,FestivosPerú!$A$2:$A$15) -> 19 | J67: =H67 -> 0
B68: Soles | C68: Luis Renato Sanchez Perez -Yon Yuo | D68: 10701.13 | E68: =D68/$D$6 -> 3232.9698 | F68: 45988 | G68: Cancelado | H68: =IF(OR(G68="Sin pagar",G68="Pagar"),(_xlfn.SINGLE(NETWORKDAYS($J$27,F68,FestivosPerú!$A$2:$A$15))),0) -> 0 | I68: =NETWORKDAYS($J$27,F68,FestivosPerú!$A$2:$A$15) -> 19 | J68: =H68 -> 0
B69: Soles | C69: Andres Felipe Uribe Avila -Europortage | D69: =7140.76+3 -> 7143.76 | E69: =D69/$D$6 -> 2158.2356 | F69: 45988 | G69: Cancelado | H69: =IF(OR(G69="Sin pagar",G69="Pagar"),(_xlfn.SINGLE(NETWORKDAYS($J$27,F69,FestivosPerú!$A$2:$A$15))),0) -> 0 | I69: =NETWORKDAYS($J$27,F69,FestivosPerú!$A$2:$A$15) -> 19 | J69: =H69 -> 0
B70: USD | C70: Christiams Hebert Valle Gomez -Remotepass | D70: =E70*D6 -> 13161.873 | E70: 3976.3967 | F70: 45988 | G70: Cancelado | H70: =IF(OR(G70="Sin pagar",G70="Pagar"),(_xlfn.SINGLE(NETWORKDAYS($J$27,F70,FestivosPerú!$A$2:$A$15))),0) -> 0 | I70: =NETWORKDAYS($J$27,F70,FestivosPerú!$A$2:$A$15) -> 19 | J70: =H70 -> 0
C71: REEMBOLSO | D71: =SUBTOTAL(9,D72:D75) -> 15685.61 | E71: =SUBTOTAL(9,E72:E75) -> 4738.855 | H71: =IF(OR(G71="Sin pagar",G71="Pagar"),(_xlfn.SINGLE(NETWORKDAYS($J$27,F71,FestivosPerú!$A$2:$A$15))),0) -> 0
C72: Reembolso Braydi Yusset Vera Neira-Europortage | D72: 3406.28 | E72: =D72/$D$6 -> 1029.0876 | F72: 45987 | G72: Cancelado | H72: =IF(OR(G72="Sin pagar",G72="Pagar"),(_xlfn.SINGLE(NETWORKDAYS($J$27,F72,FestivosPerú!$A$2:$A$15))),0) -> 0 | I72: =NETWORKDAYS($J$27,F72,FestivosPerú!$A$2:$A$15) -> 18 | J72: =H72 -> 0
C73: Reembolso Cristhian Portugal Segovia -Europortage | D73: 9497.52 | E73: =D73/$D$6 -> 2869.3414 | F73: 45987 | G73: Cancelado | H73: =IF(OR(G73="Sin pagar",G73="Pagar"),(_xlfn.SINGLE(NETWORKDAYS($J$27,F73,FestivosPerú!$A$2:$A$15))),0) -> 0 | I73: =NETWORKDAYS($J$27,F73,FestivosPerú!$A$2:$A$15) -> 18 | J73: =H73 -> 0
C74: Reembolso Davis Cesar oporto figueroa -Europortage | D74: 701.08 | E74: =D74/$D$6 -> 211.80665 | F74: 45987 | G74: Cancelado | H74: =IF(OR(G74="Sin pagar",G74="Pagar"),(_xlfn.SINGLE(NETWORKDAYS($J$27,F74,FestivosPerú!$A$2:$A$15))),0) -> 0 | I74: =NETWORKDAYS($J$27,F74,FestivosPerú!$A$2:$A$15) -> 18 | J74: =H74 -> 0
C75: Reembolso Luis Renato Sanchez Perez -Yon Yuo | D75: 2080.73 | E75: =D75/$D$6 -> 628.61934 | F75: 45987 | G75: Cancelado | H75: =IF(OR(G75="Sin pagar",G75="Pagar"),(_xlfn.SINGLE(NETWORKDAYS($J$27,F75,FestivosPerú!$A$2:$A$15))),0) -> 0 | I75: =NETWORKDAYS($J$27,F75,FestivosPerú!$A$2:$A$15) -> 18 | J75: =H75 -> 0
C76: IMPREVISTO | D76: =SUBTOTAL(9,D77:D78) -> 1158.5 | E76: =SUBTOTAL(9,E77:E78) -> 350 | H76: =IF(OR(G76="Sin pagar",G76="Pagar"),(_xlfn.SINGLE(NETWORKDAYS($J$27,F76,FestivosPerú!$A$2:$A$15))),0) -> 0
C77: Prestamo dinero empleado Eurportage | D77: =E77*$D$6 -> 1158.5 | E77: 350 | F77: 45995 | G77: Sin Pagar | H77: =IF(OR(G77="Sin pagar",G77="Pagar"),(_xlfn.SINGLE(NETWORKDAYS($J$27,F77,FestivosPerú!$A$2:$A$15))),0) -> 24 | I77: =NETWORKDAYS($J$27,F77,FestivosPerú!$A$2:$A$15) -> 24 | J77: =H77 -> 24
C78: Devolucion de dinero a S&P Panamá | D78: =$E$78*$D$6 -> 0 | E78: =3900*0 -> 0 | F78: 45991 | G78: Cancelado | H78: =IF(OR(G78="Sin pagar",G78="Pagar"),(_xlfn.SINGLE(NETWORKDAYS($J$27,F78,FestivosPerú!$A$2:$A$15))),0) -> 0 | I78: =NETWORKDAYS($J$27,F78,FestivosPerú!$A$2:$A$15) -> 20 | J78: =H78 -> 0
C79: COSTOS FINANCIEROS SAFEGUARD | D79: =SUBTOTAL(9,D80:D81) -> 131.6696 | E79: =SUBTOTAL(9,E80:E81) -> 39.779335 | H79: =IF(OR(G79="Sin pagar",G79="Pagar"),(_xlfn.SINGLE(NETWORKDAYS($J$27,F79,FestivosPerú!$A$2:$A$15))),0) -> 0
C80: Costos financieros Soles | D80: ='BCP SOLES BCP'!F619+'BCP SOLES BCP'!F622+'BCP SOLES BCP'!F624+'BCP SOLES BCP'!F629+'BCP SOLES BCP'!F666+'BCP SOLES BCP'!F685+'BCP SOLES BCP'!F687+'BCP SOLES BCP'!F688+'BCP SOLES BCP'!F690+'BCP SOLES BCP'!F691+'BCP SOLES BCP'!F703+'BCP SOLES BCP'!F705+('BCP SOLES BCP'!F713/2)+('BCP SOLES BCP'!F714/2)+'BBVA SOLES'!F17+'BBVA SOLES'!F18+'BBVA SOLES'!F22+'BBVA SOLES'!F25+'BBVA SOLES'!F26+'BBVA SOLES'!F30+'BBVA SOLES'!F31+'BBVA SOLES'!F33 -> 68.25 | E80: =D80/D6 -> 20.619335 | F80: 45991 | G80: Cancelado | H80: =IF(OR(G80="Sin pagar",G80="Pagar"),(_xlfn.SINGLE(NETWORKDAYS($J$27,F80,FestivosPerú!$A$2:$A$15))),0) -> 0 | I80: =NETWORKDAYS($J$27,F80,FestivosPerú!$A$2:$A$15) -> 20 | J80: =H80 -> 0
C81: Costos financieros USD | D81: =E81*$D$6 -> 63.4196 | E81: =('BCP USD BCP'!F261/2)+'BCP USD BCP'!F265+'BCP USD BCP'!F278+'BCP USD BCP'!F294+('BCP USD BCP'!F302/2)+('BCP USD BCP'!F303/2) -> 19.16 | F81: 45991 | G81: Cancelado | H81: =IF(OR(G81="Sin pagar",G81="Pagar"),(_xlfn.SINGLE(NETWORKDAYS($J$27,F81,FestivosPerú!$A$2:$A$15))),0) -> 0 | I81: =NETWORKDAYS($J$27,F81,FestivosPerú!$A$2:$A$15) -> 20 | J81: =H81 -> 0
C82: SEGURIDAD IGSS | D82: =SUBTOTAL(9,D83:D86) -> 26739.38 | E82: =SUBTOTAL(9,E83:E86) -> 8078.3625 | H82: =IF(OR(G82="Sin pagar",G82="Pagar"),(_xlfn.SINGLE(NETWORKDAYS($J$27,F82,FestivosPerú!$A$2:$A$15))),0) -> 0
B83: 2609693703 | C83: Planilla de declaración y pago de aportes previsional-Habitat | D83: =8232.77+1108.2 -> 9340.97 | E83: =D83/$D$6 -> 2822.0453 | F83: 45973 | G83: Cancelado | H83: =IF(OR(G83="Sin pagar",G83="Pagar"),(_xlfn.SINGLE(NETWORKDAYS($J$27,F83,FestivosPerú!$A$2:$A$15))),0) -> 0 | I83: =NETWORKDAYS($J$27,F83,FestivosPerú!$A$2:$A$15) -> 8 | J83: =H83 -> 0 | M83: Sacar soporte
B84: 2221507476 | C84: Planilla de declaración y pago de aportes previsional-Integra | D84: =4522.37+969.07 -> 5491.44 | E84: =D84/$D$6 -> 1659.0453 | F84: 45973 | G84: Cancelado | H84: =IF(OR(G84="Sin pagar",G84="Pagar"),(_xlfn.SINGLE(NETWORKDAYS($J$27,F84,FestivosPerú!$A$2:$A$15))),0) -> 0 | I84: =NETWORKDAYS($J$27,F84,FestivosPerú!$A$2:$A$15) -> 8 | J84: =H84 -> 0
B85: 2517226428 | C85: Planilla de declaración y pago de aportes previsional-Prima | D85: =8200.3+1389.05 -> 9589.35 | E85: =D85/$D$6 -> 2897.0846 | F85: 45973 | G85: Cancelado | H85: =IF(OR(G85="Sin pagar",G85="Pagar"),(_xlfn.SINGLE(NETWORKDAYS($J$27,F85,FestivosPerú!$A$2:$A$15))),0) -> 0 | I85: =NETWORKDAYS($J$27,F85,FestivosPerú!$A$2:$A$15) -> 8 | J85: =H85 -> 0
B86: 2314312780 | C86: Planilla de declaración y pago de aportes previsional-Profuturo | D86: =1839.69+477.93 -> 2317.62 | E86: =D86/$D$6 -> 700.18731 | F86: 45973 | G86: Cancelado | H86: =IF(OR(G86="Sin pagar",G86="Pagar"),(_xlfn.SINGLE(NETWORKDAYS($J$27,F86,FestivosPerú!$A$2:$A$15))),0) -> 0 | I86: =NETWORKDAYS($J$27,F86,FestivosPerú!$A$2:$A$15) -> 8 | J86: =H86 -> 0
