Workbook

Sheet BAC SAN JOSE COLONES  
D1: BAC SAN JOSE COLONES | E1: INGRESO | F1: SALIDA | G1: SALDO
A2: FECHA | D2: CUENTA S&P | G2: 0
D3: BENEFICIARIO - CLIENTE DETALLES
A5: 44926 | D5: SALDO 31 DE DICIEMBRE 2021 | G5: 84354.37
A6: 44927 | E6: 0 | F6: 0 | G6: =G5+E6-F6 -> 84354.37
A7: 44937 | D7: TRANSFER DE FONDOS CTA USD A COLONES $ 300 USD | E7: 172500 | G7: =G6+E7-F7 -> 256854.37
A8: 44937 | D8: SERVICIOS ADM MES DE ENERO ALEJANDRO ECHAVARRIA | F8: 105000 | G8: =G7+E8-F8 -> 151854.37
A9: 44937 | D9: PAGO DE COMPRA DE CAFÉ VB ED FORERO | F9: 77000 | G9: =G8+E9-F9 -> 74854.37
A10: 44937 | D10: PAGO DE TRANSFERENCIA SINPE BAC SAN JOSE | F10: 1767 | G10: =G9+E10-F10 -> 73087.37
A11: 44946 | D11: PAGO DE RECARGA DE FACTURAS ELECTRONICAS A GTI | F11: 13560 | G11: =G10+E11-F11 -> 59527.37
A12: 44957 | G12: =G11+E12-F12 -> 59527.37
A13: 44958 | D13: TRANSFER DE FONDOS CTA USD A COLONES $ 700 USD | E13: 384300 | G13: =G12+E13-F13 -> 443827.37
A14: 44958 | D14: SERVICIOS ADM MES DE ENERO ALEJANDRO ECHAVARRIA | F14: 105000 | G14: =G13+E14-F14 -> 338827.37
A15: 44958 | D15: PAGO DE COMPRA DE CAFÉ VB ED FORERO | F15: 77000 | G15: =G14+E15-F15 -> 261827.37
A16: 44958 | D16: PAGO DE TRANSFERENCIA SINPE BAC SAN JOSE | F16: 422.25 | G16: =G15+E16-F16 -> 261405.12
A17: 44958 | D17: MINISTERIO DE HACIENDA IMP DE SOCIEDADES 2023 | F17: 231173 | G17: =G16+E17-F17 -> 30232.12
A18: 44985 | G18: =G17+E18-F18 -> 30232.12
A19: 44987 | D19: TRANSFER DE FONDOS CTA USD A COLONES $ 300 USD | E19: 165600 | G19: =G18+E19-F19 -> 195832.12
A20: 44987 | D20: SERVICIOS ADM MES DE ENERO ALEJANDRO ECHAVARRIA | F20: 105000 | G20: =G19+E20-F20 -> 90832.12
A21: 44987 | D21: PAGO DE COMPRA DE CAFÉ VB ED FORERO | F21: 77000 | G21: =G20+E21-F21 -> 13832.12
A22: 44987 | D22: PAGO DE TRANSFERENCIA SINPE BAC SAN JOSE | F22: 424.5 | G22: =G21+E22-F22 -> 13407.62
A23: 45016 | D23: COMISION SALDO MINIMO | F23: 3000 | G23: =G22+E23-F23 -> 10407.62
A24: 45016 | G24: =G23+E24-F24 -> 10407.62
A25: 45040 | D25: TRANSFER DE FONDOS CTA USD A COLONES $ 200 USD | E25: 105200 | G25: =G24+E25-F25 -> 115607.62
A26: 45040 | D26: PAGO DE COMPRA DE CAFÉ VB ED FORERO | F26: 77000 | G26: =G25+E26-F26 -> 38607.62
A27: 45040 | D27: PAGO DE TRANSFERENCIA SINPE BAC SAN JOSE | F27: 1620 | G27: =G26+E27-F27 -> 36987.62
A28: 45046 | D28: COMISION SALDO MINIMO | F28: 3000 | G28: =G27+E28-F28 -> 33987.62
A29: 45046 | G29: =G28+E29-F29 -> 33987.62
A30: 45047 | D30: TRANSFER DE FONDOS CTA USD A COLONES $ 200 USD | E30: 107600 | G30: =G29+E30-F30 -> 141587.62
A31: 45048 | D31: PAGO DE COMPRA DE CAFÉ VB ED FORERO | F31: 77000 | G31: =G30+E31-F31 -> 64587.62
A32: 45049 | D32: PAGO DE TRANSFERENCIA SINPE BAC SAN JOSE | F32: 414 | G32: =G31+E32-F32 -> 64173.62
A33: 45077 | G33: =G32+E33-F33 -> 64173.62
A34: 45082 | D34: TRANSFER DE FONDOS CTA USD A COLONES $ 300 USD | E34: 160800 | G34: =G33+E34-F34 -> 224973.62
A35: 45082 | D35: SERVICIOS ADM MES DE JUNIO ALEJANDRO ECHAVARRIA | F35: 105000 | G35: =G34+E35-F35 -> 119973.62
A36: 45082 | D36: PAGO DE COMPRA DE CAFÉ VB ED FORERO | F36: 77000 | G36: =G35+E36-F36 -> 42973.62
A37: 45082 | D37: PAGO DE TRANSFERENCIA SINPE BAC SAN JOSE | F37: 412.5 | G37: =G36+E37-F37 -> 42561.12
A38: 45105 | D38: TRANSFER DE FONDOS CTA USD A COLONES $ 1400 USD TC 540 | E38: 756000 | G38: =G37+E38-F38 -> 798561.12
A39: 45105 | D39: NOMINA PRISCILLA POLSON MES DE JUNIO | F39: 752248 | G39: =G38+E39-F39 -> 46313.12
A40: 45107 | G40: =G39+E40-F40 -> 46313.12
A41: 45110 | D41: TRANSFER DE FONDOS CTA USD A COLONES $ 300 USD | E41: 161700 | G41: =G40+E41-F41 -> 208013.12
A42: 45110 | D42: SERVICIOS ADM MES DE JULIO ALEJANDRO ECHAVARRIA | F42: 105000 | G42: =G41+E42-F42 -> 103013.12
A43: 45112 | D43: PAGO DE COMPRA DE CAFÉ VB ED FORERO | F43: 77000 | G43: =G42+E43-F43 -> 26013.12
A44: 45112 | D44: PAGO DE TRANSFERENCIA SINPE BAC SAN JOSE | F44: 414.75 | G44: =G43+E44-F44 -> 25598.37
A45: 45124 | D45: TRANSFER DE FONDOS CTA USD A COLONES $ 300 USD TC 531 | E45: 159300 | G45: =G44+E45-F45 -> 184898.37
A46: 45124 | D46: PAGO RETENFUENTE | F46: 173438 | G46: =G45+E46-F46 -> 11460.37
A47: 45135 | D47: TRANSFER DE FONDOS CTA USD A COLONES $ 3000 USD TC 538 PARA PAGO NOMINA PRISCILLA | E47: 1614000 | G47: =G46+E47-F47 -> 1625460.4
A48: 45135 | D48: NOMINA PRISCILLA POLSON MES DE JULIO | F48: 1359495 | G48: =G47+E48-F48 -> 265965.37
A49: 45138 | G49: =G48+E49-F49 -> 265965.37
A50: 45140 | D50: TRANSFER DE FONDOS CTA USD A COLONES $ 3500 USD TC 539 PARA PAGO DE CCSS Y RETENFUENTE MES DE JULIO | E50: 1886500 | G50: =G49+E50-F50 -> 2152465.4
A51: 45140 | D51: SERVICIOS ADM MES DE AGOSTO ALEJANDRO ECHAVARRIA | F51: 105000 | G51: =G50+E51-F51 -> 2047465.4
A52: 45140 | D52: PAGO DE COMPRA DE CAFÉ VB ED FORERO | F52: 77000 | G52: =G51+E52-F52 -> 1970465.4
A53: 45140 | D53: PAGO DE TRANSFERENCIA SINPE BAC SAN JOSE | F53: 414.75 | G53: =G52+E53-F53 -> 1970050.6
A54: 45153 | D54: PAGO RETENFUENTE | F54: 173438 | G54: =G53+E54-F54 -> 1796612.6
A55: 45153 | D55: PAGO CCSS MES DE JULIO | F55: 1420311 | G55: =G54+E55-F55 -> 376301.62
A56: 45168 | D56: TRANSFER DE FONDOS CTA USD A COLONES $ 3000 USD TC 531 PARA PAGO NOMINA PRISCILLA | E56: 1593000 | G56: =G55+E56-F56 -> 1969301.6
A57: 45168 | D57: NOMINA PRISCILLA POLSON MES DE AGOSTO | F57: 1553351 | G57: =G56+E57-F57 -> 415950.62
A58: 45169 | D58: INTERESES GENERADOS | E58: 86.32 | G58: =G57+E58-F58 -> 416036.94
A59: 45170 | G59: =G58+E59-F59 -> 416036.94
A60: 45171 | D60: SERVICIOS ADM MES DE SEPT ALEJANDRO ECHAVARRIA | F60: 105000 | G60: =G59+E60-F60 -> 311036.94
A61: 45175 | D61: TRANSFER DE FONDOS CTA USD A COLONES $ 10000 USD TC 530 PARA PAGO DE CCSS -RETENFUENTE MES DE AGOSTO | E61: 5300000 | G61: =G60+E61-F61 -> 5611036.9
A62: 45175 | D62: PAGO DE COMPRA DE CAFÉ VB ED FORERO | F62: 77000 | G62: =G61+E62-F62 -> 5534036.9
A63: 45175 | D63: PAGO DE TRANSFERENCIA SINPE BAC SAN JOSE | F63: 408 | G63: =G62+E63-F63 -> 5533628.9
A64: 45187 | D64: PAGO RETENFUENTE MES DE AGOSTO | F64: 1470328 | G64: =G63+E64-F64 -> 4063300.9
A65: 45187 | D65: PAGO CCSS MES DE AGOSTO | F65: 3978915 | G65: =G64+E65-F65 -> 84385.94
A66: 45197 | D66: TRANSFER DE FONDOS CTA USD A COLONES $ 3000 USD TC 525 PARA PAGO DE NOMINA PRISCILLA | E66: 1575000 | G66: =G65+E66-F66 -> 1659385.9
A67: 45197 | D67: PAGO DE POLIZA DE RIESGOS DEL TRABAJO | F67: 106299 | G67: =G66+E67-F67 -> 1553086.9
A68: 45197 | D68: PAGO DE TRANSFERENCIA SINPE BAC SAN JOSE | F68: 404.25 | G68: =G67+E68-F68 -> 1552682.7
A69: 45197 | D69: NOMINA PRISCILLA POLSON MES DE SEPT | F69: 1323637.3 | G69: =G68+E69-F69 -> 229045.39
A70: 45199 | D70: INTERESES DEVENGADOS | E70: 376.39 | F70: 0 | G70: =G69+E70-F70 -> 229421.78
A71: 45199 | G71: =G70+E71-F71 -> 229421.78
A72: 45200 | G72: =G71+E72-F72 -> 229421.78
A73: 45208 | D73: SERVICIOS ADM MES DE OCT ALEJANDRO ECHAVARRIA | F73: 105000 | G73: =G72+E73-F73 -> 124421.78
A74: 45208 | D74: PAGO DE COMPRA DE CAFÉ VB ED FORERO | F74: 77000 | G74: =G73+E74-F74 -> 47421.78
A75: 45208 | D75: PAGO DE TRANSFERENCIA SINPE BAC SAN JOSE | F75: 408 | G75: =G74+E75-F75 -> 47013.78
A76: 45208 | D76: TRANSFER DE FONDOS CTA USD A COLONES $ 9000 USD TC 530 PARA PAGO DE -CCSS | E76: 4770000 | G76: =G75+E76-F76 -> 4817013.8
A77: 45208 | D77: PAGO CCSS MES DE SEPTIEMBRE | F77: 3567699 | G77: =G76+E77-F77 -> 1249314.8
A78: 45208 | D78: PAGO CCSS PLANILLA ADICIONAL DE LOS MESES DE MAYO Y JUNIO 2023 | F78: 1207610 | G78: =G77+E78-F78 -> 41704.78
A79: 45215 | D79: TRANSFER DE FONDOS CTA USD A COLONES $ 2000 USD TC 524 PARA PAGO DE RETENFUENTES | E79: 1048000 | G79: =G78+E79-F79 -> 1089704.8
A80: 45215 | D80: PAGO DE RETENFUENTE MES DE SEPTIEMBRE | F80: 1030601 | G80: =G79+E80-F80 -> 59103.78
A81: 45226 | D81: TRANSFER DE FONDOS CTA USD A COLONES $ 2700 USD TC 526 PARA PAGO DE NOMINA PRISCILLA | E81: 1420200 | G81: =G80+E81-F81 -> 1479303.8
A82: 45226 | D82: NOMINA PRISCILLA POLSON MES DE OCTUBRE | F82: 1412637.3 | G82: =G81+E82-F82 -> 66666.48
A83: 45227 | G83: =G82+E83-F83 -> 66666.48
A84: 45230 | G84: =G83+E84-F84 -> 66666.48
A85: 45231 | G85: =G84+E85-F85 -> 66666.48
A86: 45232 | D86: SERVICIOS ADM MES DE OCT ALEJANDRO ECHAVARRIA | F86: 105000 | G86: =G85+E86-F86 -> -38333.52
A87: 45232 | D87: PAGO DE COMPRA DE CAFÉ VB ED FORERO | F87: 77000 | G87: =G86+E87-F87 -> -115333.52
A88: 45232 | D88: PAGO DE TRANSFERENCIA SINPE BAC SAN JOSE | F88: 406.5 | G88: =G87+E88-F88 -> -115740.02
A89: 45232 | D89: TRANSFER DE FONDOS CTA USD A COLONES $ 300 USD TC 528 PARA PAGOS ADM OPERACIÓN | E89: 158400 | G89: =G88+E89-F89 -> 42659.98
A90: 45238 | D90: TRANSFER DE FONDOS CTA USD A COLONES $ 8200 USD TC 526 PARA PAGO DE RETENFUENTES Y CCSS MES DE OCTUBRE | E90: 4313200 | G90: =G89+E90-F90 -> 4355860
A91: 45238 | D91: PAGO CCSS MES DE OCTUBRE | F91: 3283097 | G91: =G90+E91-F91 -> 1072763
A92: 45243 | D92: PAGO DE RETENFUENTE MES DE OCTUBRE | F92: 923115 | G92: =G91+E92-F92 -> 149647.98
A93: 45259 | D93: TRANSFERENCIA A CUENTA COLONES S&P FACTURA DE TATIANA ARAYA POCHET-CZ-CR006 | E93: 2393076 | G93: =G92+E93-F93 -> 2542724
A94: 45259 | D94: TRANSFERENCIA A CUENTA COLONES S&P FACTURA DE JONATHAN SALAZAR-STARLIGHT-CR003 | E94: 1010394 | G94: =G93+E94-F94 -> 3553118
A95: 45259 | D95: TRANSFERENCIA A CUENTA COLONES S&P FACTURA DE ESTIVEN SALAZAR-TC1-CR005. | E95: 69714.75 | G95: =G94+E95-F95 -> 3622832.7
A96: 45259 | D96: TRANSFERENCIA A CUENTA DE COLONES S&P FACTURA DE PRISCILLA GRACE POLSON-ALUMINATI-CR004 | E96: 2889189.3 | G96: =G95+E96-F96 -> 6512022
A97: 45259 | D97: NOMINA NOVIEMBRE Y AGUINALDO 2023 PRISCILLA GRACE POLSON-ALUMINATI-CR004 | F97: 2183095.6 | G97: =G96+E97-F97 -> 4328926.4
A98: 45260 | D98: INTERESES GENERADOS | E98: 48.1 | G98: =G97+E98-F98 -> 4328974.5
A99: 45260 | G99: =G98+E99-F99 -> 4328974.5
A100: 45261 | G100: =G99+E100-F100 -> 4328974.5
A101: 45265 | D101: PAGO CCSS NOVIEMBRE DOC 23120506232070405150 | F101: 3076777 | G101: =G100+E101-F101 -> 1252197.5
...

Sheet BAC SAN JOSE USD
A1: FECHA | D1: BAC SAN JOSE DOLARES | E1: INGRESO | F1: SALIDA | G1: SALDO
D2: CUENTA S&P | G2: 0
D3: BENEFICIARIO - CLIENTE DETALLES
D5: SALDO 31 DE DICIEMBRE 2022 | G5: 4726.85
A6: 44937 | D6: TRANSFERENCIA CUENTA COLONES | E6: 0 | F6: 300 | G6: =G5+E6-F6 -> 4426.85
A7: 44957 | G7: =G6+E7-F7 -> 4426.85
A8: 44958 | D8: TRANSFER DE FONDOS A CUENTA COLONES | F8: 700 | G8: =G7+E8-F8 -> 3726.85
A9: 44985 | G9: =G8+E9-F9 -> 3726.85
A10: 44986 | D10: TRANSFERENCIA CUENTA COLONES | F10: 300 | G10: =G9+E10-F10 -> 3426.85
A11: 44988 | D11: TRANSFERENCIA COMPRA DE COMPUTADORA GUATEMALA VB RICARDO ARAMBULO | F11: 2640 | G11: =G10+E11-F11 -> 786.85
A12: 44988 | D12: COMISION TRANSFER INTERNACIONAL | F12: 30 | G12: =G11+E12-F12 -> 756.85
A13: 45016 | D13: TRANSFER DE FONDOS A CUENTA COLONES | G13: =G12+E13-F13 -> 756.85
A14: 45040 | D14: TRANSFERENCIA CUENTA COLONES | F14: 200 | G14: =G13+E14-F14 -> 556.85
A15: 45046 | G15: =G14+E15-F15 -> 556.85
A16: 45047 | G16: =G15+E16-F16 -> 556.85
A17: 45051 | D17: TRANSFERENCIA CUENTA COLONES | F17: 200 | G17: =G16+E17-F17 -> 356.85
A18: 45076 | D18: TRANSFER SOLUTIONS AND PAYRROL COLOMBIA | E18: 980 | G18: =G17+E18-F18 -> 1336.85
A19: 45076 | D19: COMISION TRANSFERENCIA INTERNACIONAL | F19: 20 | G19: =G18+E19-F19 -> 1316.85
A20: 45077 | G20: =G19+E20-F20 -> 1316.85
A21: 45078 | D21: NOMINA JONATHAN SALAZAR GARCIA MES DE MAYO | F21: 1243.06 | G21: =G20+E21-F21 -> 73.79
A22: 45079 | D22: REMORFIST FACT 082 | E22: 1931.89 | G22: =G21+E22-F22 -> 2005.68
A23: 45079 | D23: COMISION TRANSFERENCIA INTERNACIONAL | F23: 20 | G23: =G22+E23-F23 -> 1985.68
A24: 45104 | D24: TRANSFERENCIA CUENTA COLONES | F24: 300 | G24: =G23+E24-F24 -> 1685.68
A25: 45104 | D25: REMORFIST FACT 083 | E25: 5473.67 | G25: =G24+E25-F25 -> 7159.35
A26: 45104 | D26: REMORFIST FACT 084 | E26: 2117.21 | G26: =G25+E26-F26 -> 9276.56
A27: 45104 | D27: COMISION TRANSFERENCIA INTERNACIONAL | F27: 20 | G27: =G26+E27-F27 -> 9256.56
A28: 45104 | D28: COMISION TRANSFERENCIA INTERNACIONAL | F28: 20 | G28: =G27+E28-F28 -> 9236.56
A29: 45105 | D29: NOMINA JONATHAN SALAZAR GARCIA MES DE JUNIO | F29: 3407.11 | G29: =G28+E29-F29 -> 5829.45
A30: 45105 | D30: TRANSFERENCIA CUENTA COLONES | F30: 1400 | G30: =G29+E30-F30 -> 4429.45
A31: 45107 | D31: COMISION SALDO MINIMO | F31: 6 | G31: =G30+E31-F31 -> 4423.45
A32: 45107 | G32: =G31+E32-F32 -> 4423.45
A33: 45110 | D33: TRANSFERENCIA CUENTA COLONES | F33: 300 | G33: =G32+E33-F33 -> 4123.45
A34: 45124 | D34: TRANSFERENCIA CUENTA COLONES | F34: 300 | G34: =G33+E34-F34 -> 3823.45
A35: 45128 | D35: REMORFIST FACT 085 | E35: 4076.02 | G35: =G34+E35-F35 -> 7899.47
A36: 45128 | D36: REMORFIST FACT 086 | E36: 5473.67 | G36: =G35+E36-F36 -> 13373.14
A37: 45128 | D37: COMISION TRANSFERENCIA INTERNACIONAL | F37: 20 | G37: =G36+E37-F37 -> 13353.14
A38: 45128 | D38: COMISION TRANSFERENCIA INTERNACIONAL | F38: 20 | G38: =G37+E38-F38 -> 13333.14
A39: 45135 | D39: TRANSFERENCIA CUENTA COLONES | F39: 3000 | G39: =G38+E39-F39 -> 10333.14
A40: 45135 | D40: NOMINA JONATHAN SALAZAR GARCIA MES DE JULIO | F40: 3407.11 | G40: =G39+E40-F40 -> 6926.03
A41: 45138 | G41: =G40+E41-F41 -> 6926.03
A42: 45139 | D42: TRANSFERENCIA CUENTA COLONES | F42: 3500 | G42: =G41+E42-F42 -> 3426.03
A43: 45168 | D43: REMORFIST FACT 088 | E43: 4094.49 | G43: =G42+E43-F43 -> 7520.52
A44: 45168 | D44: REMORFIST FACT 089 | E44: 1010.67 | G44: =G43+E44-F44 -> 8531.19
A45: 45168 | D45: REMORFIST FACT 087 | E45: 7921.13 | G45: =G44+E45-F45 -> 16452.32
A46: 45168 | D46: COMISION TRANSFERENCIA INTERNACIONAL | F46: 20 | G46: =G45+E46-F46 -> 16432.32
A47: 45168 | D47: COMISION TRANSFERENCIA INTERNACIONAL | F47: 20 | G47: =G46+E47-F47 -> 16412.32
A48: 45168 | D48: COMISION TRANSFERENCIA INTERNACIONAL | F48: 20 | G48: =G47+E48-F48 -> 16392.32
A49: 45168 | D49: REEM DE GASTOS JONATHAN GARCIA | F49: 2447.46 | G49: =G48+E49-F49 -> 13944.86
A50: 45168 | D50: NOMINA JONATHAN SALAZAR GARCIA MES DE AGOSTO | F50: 3400.03 | G50: =G49+E50-F50 -> 10544.83
A51: 45168 | D51: TRANSFERENCIA CUENTA COLONES | F51: 3000 | G51: =G50+E51-F51 -> 7544.83
A52: 45168 | D52: NOMINA ESTIVEN GONZALO SALAZAR MES DE AGOSTO | F52: 595.53 | G52: =G51+E52-F52 -> 6949.3
A53: 45168 | D53: COMISION SINPE | F53: 0.75 | G53: =G52+E53-F53 -> 6948.55
A54: 45169 | G54: =G53+E54-F54 -> 6948.55
A55: 45170 | D55: REMORFIST FACT 090 | E55: 16357.67 | G55: =G54+E55-F55 -> 23306.22
A56: 45170 | D56: COMISION TRANSFERENCIA INTERNACIONAL | F56: 24.53 | G56: =G55+E56-F56 -> 23281.69
A57: 45170 | D57: TRANSFERENCIA CUENTA COLONES | F57: 10000 | G57: =G56+E57-F57 -> 13281.69
A58: 45170 | D58: TRANSFERENCIA NOMINA DE TATIANA ARAYA MES DE AGOSTO | F58: 5000 | G58: =G57+E58-F58 -> 8281.69
A59: 45170 | D59: TRANSFERENCIA NOMINA DE TATIANA ARAYA MES DE AGOSTO | F59: 4085.39 | G59: =G58+E59-F59 -> 4196.3
A60: 45191 | D60: REMORFIST FACT 095 | E60: 4193.78 | G60: =G59+E60-F60 -> 8390.08
A61: 45191 | D61: REMORFIST FACT 091 | E61: 5479.59 | G61: =G60+E61-F61 -> 13869.67
A62: 45191 | D62: COMISION TRANSFERENCIA INTERNACIONAL | F62: 20 | G62: =G61+E62-F62 -> 13849.67
A63: 45191 | D63: COMISION TRANSFERENCIA INTERNACIONAL | F63: 20 | G63: =G62+E63-F63 -> 13829.67
A64: 45194 | D64: REMORFIST FACT 093 | E64: 2713.4 | G64: =G63+E64-F64 -> 16543.07
A65: 45194 | D65: REMORFIST FACT 094 | E65: 11203.46 | G65: =G64+E65-F65 -> 27746.53
A66: 45194 | D66: COMISION TRANSFERENCIA INTERNACIONAL | F66: 20 | G66: =G65+E66-F66 -> 27726.53
A67: 45194 | D67: COMISION TRANSFERENCIA INTERNACIONAL | F67: 20 | G67: =G66+E67-F67 -> 27706.53
A68: 45196 | D68: TRANSFER COLONES | F68: 3000 | G68: =G67+E68-F68 -> 24706.53
A69: 45197 | D69: TRANSFERENCIA NOMINA DE TATIANA ARAYA MES DE SEPT | F69: 6488.59 | G69: =G68+E69-F69 -> 18217.94
A70: 45197 | D70: NOMINA JONATHAN SALAZAR GARCIA MES DE SEPT | F70: 3400.03 | G70: =G69+E70-F70 -> 14817.91
A71: 45197 | D71: NOMINA ESTIVEN GONZALO SALAZAR MES DE SEPT | F71: 1586.6 | G71: =G70+E71-F71 -> 13231.31
A72: 45197 | D72: COMISION SINPE | F72: 0.75 | G72: =G71+E72-F72 -> 13230.56
A73: 45197 | D73: NOMINA ESTIVEN GONZALO SALAZAR MES DE SEPT DIF MENOR VR PAGADO | F73: 174.73 | G73: =G72+E73-F73 -> 13055.83
A74: 45197 | D74: COMISION SINPE | F74: 0.75 | G74: =G73+E74-F74 -> 13055.08
A75: 45199 | G75: =G74+E75-F75 -> 13055.08
A76: 45208 | D76: TRANSFER DE FONDOS CTA USD A COLONES $ 9000 USD TC 530 PARA PAGO DE -CCSS | F76: 9000 | G76: =G75+E76-F76 -> 4055.08
A77: 45209 | D77: PAGO DE FACTURAS PENDIENTES DE SAFEGUARD POLIZAS COSTA RICA | E77: 2500 | G77: =G76+E77-F77 -> 6555.08
A78: 45209 | D78: COMISION TRANSFERENCIA INTERNACIONAL | F78: 20 | G78: =G77+E78-F78 -> 6535.08
A79: 45215 | D79: TRANSFER DE FONDOS CTA USD A COLONES $ 2000 USD TC 524 PARA PAGO DE RETENFUENTES | F79: 2000 | G79: =G78+E79-F79 -> 4535.08
A80: 45222 | D80: REMORFIST FACT 096 | E80: 5479.59 | G80: =G79+E80-F80 -> 10014.67
A81: 45222 | D81: REMORFIST FACT 099 | E81: 11203.46 | G81: =G80+E81-F81 -> 21218.13
A82: 45222 | D82: REMORFIST FACT 098 | E82: 2713.4 | G82: =G81+E82-F82 -> 23931.53
A83: 45222 | D83: REMORFIST FACT 097 | E83: 4175.44 | G83: =G82+E83-F83 -> 28106.97
A84: 45222 | D84: COMISION TRANSFERENCIA INTERNACIONAL | F84: 20 | G84: =G83+E84-F84 -> 28086.97
A85: 45222 | D85: COMISION TRANSFERENCIA INTERNACIONAL | F85: 20 | G85: =G84+E85-F85 -> 28066.97
A86: 45222 | D86: COMISION TRANSFERENCIA INTERNACIONAL | F86: 20 | G86: =G85+E86-F86 -> 28046.97
A87: 45222 | D87: COMISION TRANSFERENCIA INTERNACIONAL | F87: 20 | G87: =G86+E87-F87 -> 28026.97
A88: 45226 | D88: TRANSFERENCIA NOMINA DE TATIANA ARAYA MES DE OCTUBRE | F88: 6488.59 | G88: =G87+E88-F88 -> 21538.38
A89: 45226 | D89: NOMINA JONATHAN SALAZAR GARCIA MES DE OCTUBRE | F89: 3400.03 | G89: =G88+E89-F89 -> 18138.35
A90: 45226 | D90: NOMINA ESTIVEN GONZALO SALAZAR MES DE OCTUBRE | F90: 1761.33 | G90: =G89+E90-F90 -> 16377.02
A91: 45226 | D91: COMISION SINPE STIVEN | F91: 0.75 | G91: =G90+E91-F91 -> 16376.27
A92: 45226 | D92: TRANSFER DE FONDOS CTA USD A COLONES $ 2700 USD TC 526 PARA PAGO DE NOMINA PRISCILLA | F92: 2700 | G92: =G91+E92-F92 -> 13676.27
A93: 45230 | G93: =G92+E93-F93 -> 13676.27
A94: 45232 | D94: TRANSFER DE FONDOS CTA USD A COLONES $ 300 USD TC 528 PARA PAGOS ADM OPERACIÓN | F94: 300 | G94: =G93+E94-F94 -> 13376.27
A95: 45238 | D95: TRANSFER DE FONDOS CTA USD A COLONES $ 8200 USD TC 526 PARA PAGO DE RETENFUENTES Y CCSS MES DE OCTUBRE | F95: 8200 | G95: =G94+E95-F95 -> 5176.27
A96: 45257 | D96: COMISION TRANSFERENCIA INTERNACIONAL-JONATHAN ALONSO SALAZAR GARCIA-STARLIGHT-CR003 | F96: 20 | G96: =G95+E96-F96 -> 5156.27
A97: 45257 | D97: COMISION TRANSFERENCIA INTERNACIONAL -ESTIVEN GONZALO SALAZAR VILLEGAS -TC1-CR005 | F97: 20 | G97: =G96+E97-F97 -> 5136.27
A98: 45257 | D98: COMISION TRANSFERENCIA INTERNACIONAL -TATIANA ARAYA POCHET, -CZ-CR006 | F98: 21.63 | G98: =G97+E98-F98 -> 5114.64
A99: 45257 | D99: COMISION TRANSFERENCIA INTERNACIONAL -PRISCILLA GRACE POLSON-ALUMINATI-CR004 | F99: 20 | G99: =G98+E99-F99 -> 5094.64
A100: 45257 | D100: REMORFIST FACT 100-JONATHAN ALONSO SALAZAR GARCIA-STARLIGHT-CR003 | E100: 7678.67 | G100: =G99+E100-F100 -> 12773.31
A101: 45257 | D101: REMORFIST FACT 102-ESTIVEN GONZALO SALAZAR VILLEGAS -TC1-CR005 | E101: 1196.9 | G101: =G100+E101-F101 -> 13970.21
...

Sheet FLUJO CAJA ABRIL
D1: 42400
D4: Fecha de Elaboración: | E4: 45385
C6: Tasa de cambio: | D6: 501
D7: ABRIL
D8: VALOR ₡ CRC | E8: VALOR USD
C9: BANCOS | D9: =SUBTOTAL(9,D10:D11) -> 9666655.2 | E9: =SUBTOTAL(9,E10:E11) -> 19294.721
C10: Bancos ₡ CRC | D10: ='BAC SAN JOSE COLONES '!$G$155 -> 5804661.6 | E10: =D10/$D$6 -> 11586.151
C11: Bancos USD | D11: ='BAC SAN JOSE USD'!$G$162*'FLUJO CAJA ABRIL'!$D$6 -> 3861993.6 | E11: =D11/$D$6 -> 7708.57
C12: CLIENTES | D12: =SUBTOTAL(9,D13:D16) -> 16450881 | E12: =SUBTOTAL(9,E13:E16) -> 32836.09
C13: Client: Remorfist-Client-Starlight SS | D13: =E13*$D$6 -> 5099608.9 | E13: 10178.86
C14: Client: Remorfist-Client: Aluminati | D14: =E14*$D$6 -> 4506364.7 | E14: 8994.74
C15: Client: Remorfist - Client: TC1SS | D15: =E15*$D$6 -> 1239904.9 | E15: 2474.86
C16: Remorfist - Client: CZ SS | D16: =E16*$D$6 -> 5605002.6 | E16: 11187.63
C17: TOTAL INGRESOS | D17: =SUBTOTAL(9,D9:D16) -> 26117536 | E17: =SUBTOTAL(9,E9:E16) -> 52130.811
B20: CUENTAS X PAGAR MES | D20: ABRIL
B21: Factura | C21: PROVEEDOR | D21: VALOR ₡ CRC | E21: VALOR USD | F21: Fecha vencimiento | G21: Estado | J21: KPI
C22: SEGURIDAD IGSS | D22: =SUBTOTAL(9,D23:D23) -> 4490553 | E22: =SUBTOTAL(9,E23:E23) -> 8963.1796
B23: 176206200 | C23: Pago CCSS marzo | D23: 4490553 | E23: =D23/$D$6 -> 8963.1796 | F23: 45406 | G23: Cancelado | H23: =IF(OR(G23="Sin pagar",G23="Pagar"),_xlfn.SINGLE(NETWORKDAYS($E$4,F23,'Festivos CR'!$A$3:$A$15)),0) -> 0 | I23: =NETWORKDAYS($E$4,F23,'Festivos CR'!$A$3:$A$15) -> 15 | J23: =H23 -> 0
C24: IMPUESTOS | D24: =SUBTOTAL(9,D25:D26) -> 1096496 | E24: =SUBTOTAL(9,E25:E26) -> 2188.6148 | J24: =H24 -> 0
C25: Retención en la fuente | D25: 985183 | E25: =D25/$D$6 -> 1966.4331 | F25: 45393 | G25: Cancelado | H25: =IF(OR(G25="Sin pagar",G25="Pagar"),_xlfn.SINGLE(NETWORKDAYS($E$4,F25,'Festivos CR'!$A$3:$A$15)),0) -> 0 | I25: =NETWORKDAYS($E$4,F25,'Festivos CR'!$A$3:$A$15) -> 6 | J25: =H25 -> 0
C26: Rte fte por declaración de remesas al exterior Facturación S&P Colombia a S&P CR | D26: 111313 | E26: =D26/$D$6 -> 222.18164 | F26: 45393 | G26: Cancelado | H26: =IF(OR(G26="Sin pagar",G26="Pagar"),_xlfn.SINGLE(NETWORKDAYS($E$4,F26,'Festivos CR'!$A$3:$A$15)),0) -> 0 | I26: =NETWORKDAYS($E$4,F26,'Festivos CR'!$A$3:$A$15) -> 6 | J26: =H26 -> 0
C27: SERVICIOS PROFESIONALES -REPRESENTACIÓN LEGAL | D27: =SUBTOTAL(9,D28:D29) -> 365700 | E27: =SUBTOTAL(9,E28:E29) -> 729.94012 | J27: =H27 -> 0
B28: 55 | C28: Fabian Leonardo Ulloa -Certificación de cuenta BAC | D28: 178500 | E28: =D28/$D$6 -> 356.28743 | F28: 45390 | G28: Cancelado | H28: =IF(OR(G28="Sin pagar",G28="Pagar"),_xlfn.SINGLE(NETWORKDAYS($E$4,F28,'Festivos CR'!$A$3:$A$15)),0) -> 0 | I28: =NETWORKDAYS($E$4,F28,'Festivos CR'!$A$3:$A$15) -> 4 | J28: =H28 -> 0
B29: 14 | C29: Alejandro Echavarria apoyo admon Febrero, Marzo y abril | D29: 187200 | E29: =D29/$D$6 -> 373.65269 | F29: 45406 | G29: Cancelado | H29: =IF(OR(G29="Sin pagar",G29="Pagar"),_xlfn.SINGLE(NETWORKDAYS($E$4,F29,'Festivos CR'!$A$3:$A$15)),0) -> 0 | I29: =NETWORKDAYS($E$4,F29,'Festivos CR'!$A$3:$A$15) -> 15 | J29: =H29 -> 0
C30: GASTOS DE OFICINA | D30: =SUBTOTAL(9,D31:D31) -> 77000 | E30: =SUBTOTAL(9,E31:E31) -> 153.69261
B31: 54 | C31: Compra de café | D31: 77000 | E31: =D31/$D$6 -> 153.69261 | F31: 45383 | G31: Cancelado | H31: =IF(OR(G31="Sin pagar",G31="Pagar"),_xlfn.SINGLE(NETWORKDAYS($E$4,F31,'Festivos CR'!$A$3:$A$15)),0) -> 0 | I31: =NETWORKDAYS($E$4,F31,'Festivos CR'!$A$3:$A$15) -> -3 | J31: =H31 -> 0
C32: COBROS ENTRE SUCURSALES | D32: =SUBTOTAL(9,D33:D34) -> 0 | E32: =SUBTOTAL(9,E33:E34) -> 0
B33: 4699 | C33: Cobro S&P a sucursal Enero a marzo | D33: =E33*$D$6*0 -> 0 | E33: =880*0 -> 0 | F33: 45443 | G33: Sin Pagar | H33: =IF(OR(G33="Sin pagar",G33="Pagar"),_xlfn.SINGLE(NETWORKDAYS($E$4,F33,'Festivos CR'!$A$3:$A$15)),0) -> 41 | I33: =NETWORKDAYS($E$4,F33,'Festivos CR'!$A$3:$A$15) -> 41 | J33: =H33 -> 41
B34: 4777 | C34: Cobro S&P a sucursal Abril | D34: =E34*$D$6*0 -> 0 | E34: =720*0 -> 0 | F34: 45496 | G34: Sin Pagar | H34: =IF(OR(G34="Sin pagar",G34="Pagar"),_xlfn.SINGLE(NETWORKDAYS($E$4,F34,'Festivos CR'!$A$3:$A$15)),0) -> 78 | I34: =NETWORKDAYS($E$4,F34,'Festivos CR'!$A$3:$A$15) -> 78 | J34: =H34 -> 78
C35: COSTOS FINANCIEROS | D35: =SUBTOTAL(9,D36:D36) -> 0.071197605 | E35: =SUBTOTAL(9,E36:E36) -> 35.67
C36: COSTOS FINANCIEROS | D36: =E36/$D$6 -> 0.071197605 | E36: 35.67 | F36: 45412 | G36: Cancelado | H36: =IF(OR(G36="Sin pagar",G36="Pagar"),_xlfn.SINGLE(NETWORKDAYS($E$4,F36,'Festivos CR'!$A$3:$A$15)),0) -> 0 | I36: =NETWORKDAYS($E$4,F36,'Festivos CR'!$A$3:$A$15) -> 19 | J36: =H36 -> 0
C37: NÓMINAS | D37: =SUBTOTAL(9,D38:D43) -> 10255109 | E37: =SUBTOTAL(9,E38:E43) -> 20482.591
C38: Jhoel González González-Starlight-CR003 | D38: 1612916.3 | E38: =D38/500 -> 3225.8327 | F38: 45412 | G38: Cancelado | H38: =IF(OR(G38="Sin pagar",G38="Pagar"),_xlfn.SINGLE(NETWORKDAYS($E$4,F38,'Festivos CR'!$A$3:$A$15)),0) -> 0 | I38: =NETWORKDAYS($E$4,F38,'Festivos CR'!$A$3:$A$15) -> 19 | J38: =H38 -> 0
C39: Jonathan Salazar García -Starlight-CR003 | D39: =E39*500 -> 1721625 | E39: 3443.25 | F39: 45412 | G39: Cancelado | H39: =IF(OR(G39="Sin pagar",G39="Pagar"),_xlfn.SINGLE(NETWORKDAYS($E$4,F39,'Festivos CR'!$A$3:$A$15)),0) -> 0 | I39: =NETWORKDAYS($E$4,F39,'Festivos CR'!$A$3:$A$15) -> 19 | J39: =H39 -> 0
C40: Priscilla Grace Polson -Aluminati-CR004 | D40: 1410537.3 | E40: =D40/501 -> 2815.4437 | F40: 45412 | G40: Cancelado | H40: =IF(OR(G40="Sin pagar",G40="Pagar"),_xlfn.SINGLE(NETWORKDAYS($E$4,F40,'Festivos CR'!$A$3:$A$15)),0) -> 0 | I40: =NETWORKDAYS($E$4,F40,'Festivos CR'!$A$3:$A$15) -> 19 | J40: =H40 -> 0
C41: José Roberto Aguilar Barrante-Aluminati-CR004 | D41: 1410537.3 | E41: =D41/501 -> 2815.4437 | F41: 45412 | G41: Cancelado | H41: =IF(OR(G41="Sin pagar",G41="Pagar"),_xlfn.SINGLE(NETWORKDAYS($E$4,F41,'Festivos CR'!$A$3:$A$15)),0) -> 0 | I41: =NETWORKDAYS($E$4,F41,'Festivos CR'!$A$3:$A$15) -> 19 | J41: =H41 -> 0
C42: Sebastían Gerardo Salazar, -TC1SS | D42: 803970 | E42: =D42/501 -> 1604.7305 | F42: 45412 | G42: Cancelado | H42: =IF(OR(G42="Sin pagar",G42="Pagar"),_xlfn.SINGLE(NETWORKDAYS($E$4,F42,'Festivos CR'!$A$3:$A$15)),0) -> 0 | I42: =NETWORKDAYS($E$4,F42,'Festivos CR'!$A$3:$A$15) -> 19 | J42: =H42 -> 0
C43: Tatiana Araya Pochet-CZ-CR006 | D43: =E43*501 -> 3295522.9 | E43: 6577.89 | F43: 45412 | G43: Cancelado | H43: =IF(OR(G43="Sin pagar",G43="Pagar"),_xlfn.SINGLE(NETWORKDAYS($E$4,F43,'Festivos CR'!$A$3:$A$15)),0) -> 0 | I43: =NETWORKDAYS($E$4,F43,'Festivos CR'!$A$3:$A$15) -> 19 | J43: =H43 -> 0
C44: IMPREVISTO | D44: =SUBTOTAL(9,D45:D45) -> 0 | E44: =SUBTOTAL(9,E45:E45) -> 0
D45: 0 | E45: =D45/$D$6 -> 0 | F45: 45412 | G45: Cancelado | H45: =IF(OR(G45="Sin pagar",G45="Pagar"),_xlfn.SINGLE(NETWORKDAYS($E$4,F45,'Festivos CR'!$A$3:$A$15)),0) -> 0 | I45: =NETWORKDAYS($E$4,F45,'Festivos CR'!$A$3:$A$15) -> 19 | J45: =H45 -> 0
C46: TOTAL EGRESOS | D46: =SUBTOTAL(9,D22:D45) -> 16284858 | E46: =SUBTOTAL(9,E22:E45) -> 32553.688
C48: SALDO | D48: =D17-D46 -> 9832678.4 | E48: =E17-E46 -> 19577.123
C49: % | D49: =IF($D$17=0,0,D48/$D$17) -> 0.37647802 | E49: =IF($E$17=0,0,E48/$E$17) -> 0.37553844
C53: Fecha Inicial | D53: Fecha Final | E53: Valor VALOR ₡ CRC | F53: Valor VALOR USD
C54: 45383 | D54: 45389 | E54: =SUMIFS($D$21:$D$51,$F$21:$F$51,">="&C54,$F$21:$F$51,"<="&D54,$G$21:$G$51,$D$69) -> 0 | F54: =SUMIFS($E$21:$E$51,$F$21:$F$51,">="&C54,$F$21:$F$51,"<="&D54,$G$21:$G$51,$D$69) -> 0
C55: 45390 | D55: 45396 | E55: =SUMIFS($D$21:$D$51,$F$21:$F$51,">="&C55,$F$21:$F$51,"<="&D55,$G$21:$G$51,$D$69) -> 0 | F55: =SUMIFS($E$21:$E$51,$F$21:$F$51,">="&C55,$F$21:$F$51,"<="&D55,$G$21:$G$51,$D$69) -> 0
C56: 45397 | D56: 45403 | E56: =SUMIFS($D$21:$D$51,$F$21:$F$51,">="&C56,$F$21:$F$51,"<="&D56,$G$21:$G$51,$D$69) -> 0 | F56: =SUMIFS($E$21:$E$51,$F$21:$F$51,">="&C56,$F$21:$F$51,"<="&D56,$G$21:$G$51,$D$69) -> 0
C57: 45404 | D57: 45410 | E57: =SUMIFS($D$21:$D$51,$F$21:$F$51,">="&C57,$F$21:$F$51,"<="&D57,$G$21:$G$51,$D$69) -> 0 | F57: =SUMIFS($E$21:$E$51,$F$21:$F$51,">="&C57,$F$21:$F$51,"<="&D57,$G$21:$G$51,$D$69) -> 0
C58: 45411 | D58: 45412 | E58: =SUMIFS($D$21:$D$51,$F$21:$F$51,">="&C58,$F$21:$F$51,"<="&D58,$G$21:$G$51,$D$69) -> 0 | F58: =SUMIFS($E$21:$E$51,$F$21:$F$51,">="&C58,$F$21:$F$51,"<="&D58,$G$21:$G$51,$D$69) -> 0
C59: 45413 | D59: 45443 | E59: =SUMIFS($D$21:$D$51,$F$21:$F$51,">="&C59,$F$21:$F$51,"<="&D59,$G$21:$G$51,$D$69) -> 0 | F59: =SUMIFS($E$21:$E$51,$F$21:$F$51,">="&C59,$F$21:$F$51,"<="&D59,$G$21:$G$51,$D$69) -> 0
C60: TOTAL EGRESOS | E60: =SUM(E54:E59) -> 0 | F60: =SUM(F54:F59) -> 0
C63: Bancos | E63: =$D$9 -> 9666655.2 | F63: =$E$9 -> 19294.721
C64: Gastos y costos Periodo 01 al 26 Abril (SS-Impuesto) | E64: =SUM($E$54:$E$57) -> 0 | F64: =SUM($F$54:$F$57) -> 0
C65: Saldo | E65: =E63-E64 -> 9666655.2 | F65: =F63-F64 -> 19294.721
D68: Cancelado | E68: =SUMIFS($D$21:$D$51,$F$21:$F$51,">="&C54,$F$21:$F$51,"<="&D58,$G$21:$G$51,$D$68) -> 16284858 | F68: =SUMIFS($E$21:$E$51,$F$21:$F$51,">="&C54,$F$21:$F$51,"<="&D59,$G$21:$G$51,$D$68) -> 32553.688
D69: Sin Pagar | E69: =SUMIFS($D$21:$D$51,$F$21:$F$51,">="&C54,$F$21:$F$51,"<="&D59,$G$21:$G$51,$D$69) -> 0 | F69: =SUMIFS($E$21:$E$51,$F$21:$F$51,">="&C54,$F$21:$F$51,"<="&D59,$G$21:$G$51,$D$69) -> 0
D70: Total Egresos | E70: =SUM(E68:E69) -> 16284858 | F70: =SUM(F68:F69) -> 32553.688
D71: Validación | E71: =E70-D46 -> 0 | F71: =F70-E46 -> 0
F74: Saldo CRC
D75: Saldo 30 abril QTQ | E75: =F75/521 -> 10125.559 | F75: 5275416
D76: Saldo 30 abril USD | E76: 9451.56
D77: Total | E77: =SUM(E75:E76) -> 19577.119

Sheet FLUJO CAJA MAYO
D1: 42400
D4: Fecha de Elaboración: | E4: 45415
C6: Tasa de cambio: | D6: 521
D7: MAYO
D8: VALOR ₡ CRC | E8: VALOR USD
C9: BANCOS | D9: =SUBTOTAL(9,D10:D11) -> 10199679 | E9: =SUBTOTAL(9,E10:E11) -> 19577.119
C10: Bancos ₡ CRC | D10: ='BAC SAN JOSE COLONES '!$G$174 -> 5275416 | E10: =D10/$D$6 -> 10125.559
C11: Bancos USD | D11: ='BAC SAN JOSE USD'!$G$172*'FLUJO CAJA MAYO'!$D$6 -> 4924262.8 | E11: =D11/$D$6 -> 9451.56
C12: CLIENTES | D12: =SUBTOTAL(9,D13:D17) -> 17809249 | E12: =SUBTOTAL(9,E13:E17) -> 34182.819
C13: Client: Remorfist-Client-Starlight SS -Factura Nro 126 | D13: =E13*$D$6 -> 5566149.5 | E13: =CONVERSIONES!$C$87+CONVERSIONES!$D$87 -> 10683.588
C14: Client: Remorfist-Client: Aluminati-Factura Nro 127 | D14: =E14*$D$6 -> 4621343.3 | E14: =(CONVERSIONES!$E$87+CONVERSIONES!$F$87-142) -> 8870.1407
C15: Client: Remorfist - Client: TC1SS-Factura Nro 128 | D15: =E15*$D$6 -> 520854.12 | E15: =CONVERSIONES!$G$87 -> 999.72
C16: Remorfist - Client: CZ SS-Factura Nro 131 | D16: =E16*$D$6 -> 5833282.7 | E16: =CONVERSIONES!$H$87 -> 11196.32
C17: Remorfist - Client: PLLC- Factura Nro 130 | D17: =E17*$D$6 -> 1267619.1 | E17: =CONVERSIONES!$I$87 -> 2433.05
C18: TOTAL INGRESOS | D18: =SUBTOTAL(9,D9:D17) -> 28008927 | E18: =SUBTOTAL(9,E9:E17) -> 53759.938
B21: CUENTAS X PAGAR MES | D21: MAYO
B22: Factura | C22: PROVEEDOR | D22: VALOR ₡ CRC | E22: VALOR USD | F22: Fecha vencimiento | G22: Estado | J22: KPI
C23: SEGURIDAD IGSS | D23: =SUBTOTAL(9,D24:D24) -> 4718443 | E23: =SUBTOTAL(9,E24:E24) -> 9056.5125
B24: 176206200 | C24: Pago CCSS abril | D24: 4718443 | E24: =D24/$D$6 -> 9056.5125 | F24: 45422 | G24: Cancelado | H24: =IF(OR(G24="Sin pagar",G24="Pagar"),_xlfn.SINGLE(NETWORKDAYS($E$4,F24,'Festivos CR'!$A$3:$A$15)),0) -> 0 | I24: =NETWORKDAYS($E$4,F24,'Festivos CR'!$A$3:$A$15) -> 6 | J24: =H24 -> 0
C25: IMPUESTOS | D25: =SUBTOTAL(9,D26:D27) -> 1139287.6 | E25: =SUBTOTAL(9,E26:E27) -> 2186.7325 | J25: =H25 -> 0
C26: Retención en la fuente | D26: 1029558.6 | E26: =D26/$D$6 -> 1976.1202 | F26: 45422 | G26: Cancelado | H26: =IF(OR(G26="Sin pagar",G26="Pagar"),_xlfn.SINGLE(NETWORKDAYS($E$4,F26,'Festivos CR'!$A$3:$A$15)),0) -> 0 | I26: =NETWORKDAYS($E$4,F26,'Festivos CR'!$A$3:$A$15) -> 6 | J26: =H26 -> 0
C27: Rte fte por declaración de remesas al exterior Facturación S&P Colombia a S&P CR | D27: 109729 | E27: =D27/$D$6 -> 210.61228 | F27: 45422 | G27: Cancelado | H27: =IF(OR(G27="Sin pagar",G27="Pagar"),_xlfn.SINGLE(NETWORKDAYS($E$4,F27,'Festivos CR'!$A$3:$A$15)),0) -> 0 | I27: =NETWORKDAYS($E$4,F27,'Festivos CR'!$A$3:$A$15) -> 6 | J27: =H27 -> 0
C28: SERVICIOS PROFESIONALES -REPRESENTACIÓN LEGAL | D28: =SUBTOTAL(9,D29:D29) -> 62400 | E28: =SUBTOTAL(9,E29:E29) -> 119.76967 | J28: =H28 -> 0
C29: Servicios profesionales Alejandro Echavarria Mayo | D29: 62400 | E29: =D29/$D$6 -> 119.76967 | F29: 45440 | G29: Cancelado | H29: =IF(OR(G29="Sin pagar",G29="Pagar"),_xlfn.SINGLE(NETWORKDAYS($E$4,F29,'Festivos CR'!$A$3:$A$15)),0) -> 0 | I29: =NETWORKDAYS($E$4,F29,'Festivos CR'!$A$3:$A$15) -> 18 | J29: =H29 -> 0
C30: GASTOS DE OFICINA | D30: =SUBTOTAL(9,D31:D31) -> 77000 | E30: =SUBTOTAL(9,E31:E31) -> 147.79271
B31: 54 | C31: Compra de café | D31: 77000 | E31: =D31/$D$6 -> 147.79271 | F31: 45415 | G31: Cancelado | H31: =IF(OR(G31="Sin pagar",G31="Pagar"),_xlfn.SINGLE(NETWORKDAYS($E$4,F31,'Festivos CR'!$A$3:$A$15)),0) -> 0 | I31: =NETWORKDAYS($E$4,F31,'Festivos CR'!$A$3:$A$15) -> 1 | J31: =H31 -> 0
C32: COBROS ENTRE SUCURSALES | D32: =SUBTOTAL(9,D33:D35) -> 0 | E32: =SUBTOTAL(9,E33:E35) -> 0
B33: 4699 | C33: Cobro S&P a sucursal Enero a marzo | D33: =E33*$D$6*0 -> 0 | E33: =880*0 -> 0 | F33: 45443 | G33: Cancelado | H33: =IF(OR(G33="Sin pagar",G33="Pagar"),_xlfn.SINGLE(NETWORKDAYS($E$4,F33,'Festivos CR'!$A$3:$A$15)),0) -> 0 | I33: =NETWORKDAYS($E$4,F33,'Festivos CR'!$A$3:$A$15) -> 21 | J33: =H33 -> 0
B34: 4777 | C34: Cobro S&P a sucursal Abril | D34: =E34*$D$6*0 -> 0 | E34: =720*0 -> 0 | F34: 45443 | G34: Cancelado | H34: =IF(OR(G34="Sin pagar",G34="Pagar"),_xlfn.SINGLE(NETWORKDAYS($E$4,F34,'Festivos CR'!$A$3:$A$15)),0) -> 0 | I34: =NETWORKDAYS($E$4,F34,'Festivos CR'!$A$3:$A$15) -> 21 | J34: =H34 -> 0
B35: 4777 | C35: Cobro S&P a sucursal Mayo | D35: =E35*$D$6*0 -> 0 | E35: =720*0 -> 0 | H35: =IF(OR(G47="Sin pagar",G47="Pagar"),_xlfn.SINGLE(NETWORKDAYS($E$4,F47,'Festivos CR'!$A$3:$A$15)),0) -> 0 | I35: =NETWORKDAYS($E$4,F47,'Festivos CR'!$A$3:$A$15) -> 21 | J35: =H35 -> 0
C36: COSTOS FINANCIEROS | D36: =SUBTOTAL(9,D37:D37) -> 430.47 | E36: =SUBTOTAL(9,E37:E37) -> 0.826238
C37: COSTOS FINANCIEROS | D37: =(386.25+386.25)-342.03 -> 430.47 | E37: =D37/D6 -> 0.826238 | F37: 45443 | G37: Cancelado | H37: =IF(OR(G37="Sin pagar",G37="Pagar"),_xlfn.SINGLE(NETWORKDAYS($E$4,F37,'Festivos CR'!$A$3:$A$15)),0) -> 0 | I37: =NETWORKDAYS($E$4,F37,'Festivos CR'!$A$3:$A$15) -> 21 | J37: =H37 -> 0
C38: NÓMINAS | D38: =SUBTOTAL(9,D39:D45) -> 10824358 | E38: =SUBTOTAL(9,E39:E45) -> 20776.119
C39: Jhoel González González-Starlight-CR003 | D39: 1612916.3 | E39: =D39/$D$6 -> 3095.8087 | F39: 45440 | G39: Cancelado | H39: =IF(OR(G39="Sin pagar",G39="Pagar"),_xlfn.SINGLE(NETWORKDAYS($E$4,F39,'Festivos CR'!$A$3:$A$15)),0) -> 0 | I39: =NETWORKDAYS($E$4,F39,'Festivos CR'!$A$3:$A$15) -> 18 | J39: =H39 -> 0
C40: Jonathan Salazar García -Starlight-CR003 | D40: =E40*$D$6 -> 1771728.2 | E40: 3400.63 | F40: 45440 | G40: Cancelado | H40: =IF(OR(G40="Sin pagar",G40="Pagar"),_xlfn.SINGLE(NETWORKDAYS($E$4,F40,'Festivos CR'!$A$3:$A$15)),0) -> 0 | I40: =NETWORKDAYS($E$4,F40,'Festivos CR'!$A$3:$A$15) -> 18 | J40: =H40 -> 0
C41: Priscilla Grace Polson -Aluminati-CR004 | D41: 1410537.3 | E41: =D41/$D$6 -> 2707.3653 | F41: 45440 | G41: Cancelado | H41: =IF(OR(G41="Sin pagar",G41="Pagar"),_xlfn.SINGLE(NETWORKDAYS($E$4,F41,'Festivos CR'!$A$3:$A$15)),0) -> 0 | I41: =NETWORKDAYS($E$4,F41,'Festivos CR'!$A$3:$A$15) -> 18 | J41: =H41 -> 0
C42: José Roberto Aguilar Barrante-Aluminati-CR004 | D42: 1410537.3 | E42: =D42/$D$6 -> 2707.3653 | F42: 45440 | G42: Cancelado | H42: =IF(OR(G42="Sin pagar",G42="Pagar"),_xlfn.SINGLE(NETWORKDAYS($E$4,F42,'Festivos CR'!$A$3:$A$15)),0) -> 0 | I42: =NETWORKDAYS($E$4,F42,'Festivos CR'!$A$3:$A$15) -> 18 | J42: =H42 -> 0
C43: Sebastían Gerardo Salazar, -Liquidación -TC1 Corp | D43: 417000 | E43: =D43/$D$6 -> 800.38388 | F43: 45440 | G43: Cancelado | H43: =IF(OR(G43="Sin pagar",G43="Pagar"),_xlfn.SINGLE(NETWORKDAYS($E$4,F43,'Festivos CR'!$A$3:$A$15)),0) -> 0 | I43: =NETWORKDAYS($E$4,F43,'Festivos CR'!$A$3:$A$15) -> 18 | J43: =H43 -> 0
C44: Sheryl Gertrudiz Cambronero Estrada-lorez & Prada PPLC | D44: 786551.54 | E44: =D44/$D$6 -> 1509.6959 | F44: 45440 | G44: Cancelado | H44: =IF(OR(G44="Sin pagar",G44="Pagar"),_xlfn.SINGLE(NETWORKDAYS($E$4,F44,'Festivos CR'!$A$3:$A$15)),0) -> 0 | I44: =NETWORKDAYS($E$4,F44,'Festivos CR'!$A$3:$A$15) -> 18 | J44: =H44 -> 0
C45: Tatiana Araya Pochet-CZ-CR006 | D45: =E45*$D$6 -> 3415087.3 | E45: 6554.87 | F45: 45440 | G45: Cancelado | H45: =IF(OR(G45="Sin pagar",G45="Pagar"),_xlfn.SINGLE(NETWORKDAYS($E$4,F45,'Festivos CR'!$A$3:$A$15)),0) -> 0 | I45: =NETWORKDAYS($E$4,F45,'Festivos CR'!$A$3:$A$15) -> 18 | J45: =H45 -> 0
C46: IMPREVISTO | D46: =SUBTOTAL(9,D47:D47) -> 0 | E46: =SUBTOTAL(9,E47:E47) -> 0
D47: 0 | E47: =D47/$D$6 -> 0 | F47: 45443 | G47: Cancelado | H47: =IF(OR(#REF!="Sin pagar",#REF!="Pagar"),_xlfn.SINGLE(NETWORKDAYS($E$4,#REF!,'Festivos CR'!$A$3:$A$15)),0) -> #REF! | I47: =NETWORKDAYS($E$4,#REF!,'Festivos CR'!$A$3:$A$15) -> #REF!
C48: TOTAL EGRESOS | D48: =SUBTOTAL(9,D23:D47) -> 16821919 | E48: =SUBTOTAL(9,E23:E47) -> 32287.753
C50: SALDO | D50: =D18-D48 -> 11187008 | E50: =E18-E48 -> 21472.185
C51: % | D51: =IF($D$18=0,0,D50/$D$18) -> 0.39940867 | E51: =IF($E$18=0,0,E50/$E$18) -> 0.39940867
C55: Fecha Inicial | D55: Fecha Final | E55: Valor VALOR ₡ CRC | F55: Valor VALOR USD
C56: 45413 | D56: 45417 | E56: =SUMIFS($D$22:$D$53,$F$22:$F$53,">="&C56,$F$22:$F$53,"<="&D56,$G$22:$G$53,$D$70) -> 0 | F56: =SUMIFS($E$22:$E$53,$F$22:$F$53,">="&C56,$F$22:$F$53,"<="&D56,$G$22:$G$53,$D$70) -> 0
C57: 45418 | D57: 45425 | E57: =SUMIFS($D$22:$D$53,$F$22:$F$53,">="&C57,$F$22:$F$53,"<="&D57,$G$22:$G$53,$D$70) -> 0 | F57: =SUMIFS($E$22:$E$53,$F$22:$F$53,">="&C57,$F$22:$F$53,"<="&D57,$G$22:$G$53,$D$70) -> 0
C58: 45426 | D58: 45431 | E58: =SUMIFS($D$22:$D$53,$F$22:$F$53,">="&C58,$F$22:$F$53,"<="&D58,$G$22:$G$53,$D$70) -> 0 | F58: =SUMIFS($E$22:$E$53,$F$22:$F$53,">="&C58,$F$22:$F$53,"<="&D58,$G$22:$G$53,$D$70) -> 0
C59: 45432 | D59: 45438 | E59: =SUMIFS($D$22:$D$53,$F$22:$F$53,">="&C59,$F$22:$F$53,"<="&D59,$G$22:$G$53,$D$70) -> 0 | F59: =SUMIFS($E$22:$E$53,$F$22:$F$53,">="&C59,$F$22:$F$53,"<="&D59,$G$22:$G$53,$D$70) -> 0
C60: 45439 | D60: 45443 | E60: =SUMIFS($D$22:$D$53,$F$22:$F$53,">="&C60,$F$22:$F$53,"<="&D60,$G$22:$G$53,$D$70) -> 0 | F60: =SUMIFS($E$22:$E$53,$F$22:$F$53,">="&C60,$F$22:$F$53,"<="&D60,$G$22:$G$53,$D$70) -> 0
C61: TOTAL EGRESOS | E61: =SUM(E56:E60) -> 0 | F61: =SUM(F56:F60) -> 0
C64: Bancos | E64: =('BAC SAN JOSE COLONES '!$G$176)+('BAC SAN JOSE USD'!G173*'FLUJO CAJA MAYO'!$D$6) -> 10122679 | F64: =$E$9 -> 19577.119
C65: Gastos y costos Periodo 01 al 26 mayo (SS-Impuesto) | E65: =SUM($E$56:$E$59) -> 0 | F65: =SUM($F$56:$F$59) -> 0
C66: Saldo | E66: =E64-E65 -> 10122679 | F66: =F64-F65 -> 19577.119
D69: Cancelado | E69: =SUMIFS($D$22:$D$53,$F$22:$F$53,">="&C56,$F$22:$F$53,"<="&D60,$G$22:$G$53,$D$69) -> 16821919 | F69: =SUMIFS($E$22:$E$53,$F$22:$F$53,">="&C56,$F$22:$F$53,"<="&D60,$G$22:$G$53,$D$69) -> 32287.753
D70: Sin Pagar | E70: =SUMIFS($D$22:$D$53,$F$22:$F$53,">="&C56,$F$22:$F$53,"<="&D60,$G$22:$G$53,$D$70) -> 0 | F70: =SUMIFS($E$22:$E$53,$F$22:$F$53,">="&C56,$F$22:$F$53,"<="&D60,$G$22:$G$53,$D$70) -> 0
D71: Total Egresos | E71: =SUM(E69:E70) -> 16821919 | F71: =SUM(F69:F70) -> 32287.753
D72: Validación | E72: =D48-E71 -> 0 | F72: =F71-E48 -> 0
F77: Saldo CRC
D78: Saldo 31 Mayo QTQ | E78: =F78/522 -> 13415.843 | F78: ='BAC SAN JOSE COLONES '!$G$191 -> 7003070.3
D79: Saldo 31 Mayo USD | E79: ='BAC SAN JOSE USD'!G180 -> 8056.56
D80: Total | E80: =SUM(E78:E79) -> 21472.403

Sheet FLUJO CAJA JUNIO 
D1: 42400
D4: Fecha de Elaboración: | E4: 45448
C6: Tasa de cambio: | D6: 519
D7: JUNIO
D8: VALOR ₡ CRC | E8: VALOR USD
C9: BANCOS | D9: =SUBTOTAL(9,D10:D11) -> 11184425 | E9: =SUBTOTAL(9,E10:E11) -> 21549.952
C10: Bancos ₡ CRC | D10: ='BAC SAN JOSE COLONES '!$G$191 -> 7003070.3 | E10: =D10/$D$6 -> 13493.392
C11: Bancos USD | D11: ='BAC SAN JOSE USD'!$G$180*'FLUJO CAJA JUNIO '!$D$6 -> 4181354.6 | E11: =D11/$D$6 -> 8056.56
C12: CLIENTES | D12: =SUBTOTAL(9,D13:D17) -> 17395560 | E12: =SUBTOTAL(9,E13:E17) -> 33473.042
C13: Client: Remorfist-Client-Starlight SS -Factura Nro 131 | D13: =E13*519 -> 5409010.8 | E13: =CONVERSIONES!$C$106+CONVERSIONES!$D$106 -> 10421.986
C14: Client: Remorfist-Client: Aluminati-Factura Nro 132 | D14: =E14*520 -> 4455235.7 | E14: =CONVERSIONES!$E$106+CONVERSIONES!$F$106 -> 8567.7609
C15: Remorfist - Client: CZ SS-Factura Nro 133 | D15: =E15*520 -> 5814099.2 | E15: =CONVERSIONES!$G$106 -> 11180.96
C16: Remorfist - Client: PLLC- Factura Nro 134 | D16: =E16*520 -> 1197801.6 | E16: =CONVERSIONES!$H$106 -> 2303.4646
C17: Client: Remorfist-Client-Starlight SS -Factura Nro 135 | D17: =E17*520 -> 519412.4 | E17: =CONVERSIONES!$I$106 -> 998.87
C18: TOTAL INGRESOS | D18: =SUBTOTAL(9,D9:D17) -> 28579985 | E18: =SUBTOTAL(9,E9:E17) -> 55022.993
B21: CUENTAS X PAGAR MES | D21: JUNIO
B22: Factura | C22: PROVEEDOR | D22: VALOR ₡ CRC | E22: VALOR USD | F22: Fecha vencimiento | G22: Estado | J22: KPI
C23: SEGURIDAD IGSS | D23: =SUBTOTAL(9,D24:D24) -> 4806878 | E23: =SUBTOTAL(9,E24:E24) -> 9261.8073
B24: 176206200 | C24: Pago CCSS Mayo | D24: 4806878 | E24: =D24/$D$6 -> 9261.8073 | F24: 45450 | G24: Cancelado | H24: =IF(OR(G24="Sin pagar",G24="Pagar"),_xlfn.SINGLE(NETWORKDAYS($E$4,F24,'Festivos CR'!$A$3:$A$15)),0) -> 0 | I24: =NETWORKDAYS($E$4,F24,'Festivos CR'!$A$3:$A$15) -> 3 | J24: =H24 -> 0
C25: IMPUESTOS | D25: =SUBTOTAL(9,D26:D27) -> 1174829.7 | E25: =SUBTOTAL(9,E26:E27) -> 2263.641 | J25: =H25 -> 0
C26: Retención en la fuente | D26: 1092316.7 | E26: =D26/$D$6 -> 2104.6564 | F26: 45457 | G26: Cancelado | H26: =IF(OR(G26="Sin pagar",G26="Pagar"),_xlfn.SINGLE(NETWORKDAYS($E$4,F26,'Festivos CR'!$A$3:$A$15)),0) -> 0 | I26: =NETWORKDAYS($E$4,F26,'Festivos CR'!$A$3:$A$15) -> 8 | J26: =H26 -> 0
C27: Rte fte por declaración de remesas al exterior Facturación S&P Colombia a S&P CR | D27: 82513 | E27: =D27/$D$6 -> 158.98459 | F27: 45457 | G27: Cancelado | H27: =IF(OR(G27="Sin pagar",G27="Pagar"),_xlfn.SINGLE(NETWORKDAYS($E$4,F27,'Festivos CR'!$A$3:$A$15)),0) -> 0 | I27: =NETWORKDAYS($E$4,F27,'Festivos CR'!$A$3:$A$15) -> 8 | J27: =H27 -> 0
C28: SERVICIOS PROFESIONALES -REPRESENTACIÓN LEGAL | D28: =SUBTOTAL(9,D29:D29) -> 62400 | E28: =SUBTOTAL(9,E29:E29) -> 120.23121 | J28: =H28 -> 0
B29: 16 | C29: Servicios profesionales Alejandro Echavarria Junio | D29: 62400 | E29: =D29/$D$6 -> 120.23121 | F29: 45471 | G29: Cancelado | H29: =IF(OR(G29="Sin pagar",G29="Pagar"),_xlfn.SINGLE(NETWORKDAYS($E$4,F29,'Festivos CR'!$A$3:$A$15)),0) -> 0 | I29: =NETWORKDAYS($E$4,F29,'Festivos CR'!$A$3:$A$15) -> 18 | J29: =H29 -> 0
C30: GASTOS DE OFICINA | D30: =SUBTOTAL(9,D31:D31) -> 77000 | E30: =SUBTOTAL(9,E31:E31) -> 148.36224
B31: 55 | C31: Compra de café | D31: 77000 | E31: =D31/$D$6 -> 148.36224 | F31: 45447 | G31: Cancelado | H31: =IF(OR(G31="Sin pagar",G31="Pagar"),_xlfn.SINGLE(NETWORKDAYS($E$4,F31,'Festivos CR'!$A$3:$A$15)),0) -> 0 | I31: =NETWORKDAYS($E$4,F31,'Festivos CR'!$A$3:$A$15) -> -2 | J31: =H31 -> 0
C32: COBROS ENTRE SUCURSALES | D32: =SUBTOTAL(9,D33:D36) -> 0 | E32: =SUBTOTAL(9,E33:E36) -> 0
B33: 4699 | C33: Cobro S&P a sucursal Enero a marzo | D33: =E33*$D$6*0 -> 0 | E33: =880*0 -> 0 | F33: 45504 | G33: Cancelado | H33: =IF(OR(G33="Sin pagar",G33="Pagar"),_xlfn.SINGLE(NETWORKDAYS($E$4,F33,'Festivos CR'!$A$3:$A$15)),0) -> 0 | I33: =NETWORKDAYS($E$4,F33,'Festivos CR'!$A$3:$A$15) -> 40 | J33: =H33 -> 0
B34: 4777 | C34: Cobro S&P a sucursal Abril | D34: =E34*$D$6*0 -> 0 | E34: =720*0 -> 0 | F34: 45504 | G34: Cancelado | H34: =IF(OR(G34="Sin pagar",G34="Pagar"),_xlfn.SINGLE(NETWORKDAYS($E$4,F34,'Festivos CR'!$A$3:$A$15)),0) -> 0 | I34: =NETWORKDAYS($E$4,F34,'Festivos CR'!$A$3:$A$15) -> 40 | J34: =H34 -> 0
B35: 4878 | C35: Cobro S&P a sucursal Mayo | D35: =E35*$D$6*0 -> 0 | E35: =720*0 -> 0 | F35: 45504 | G35: Cancelado | H35: =IF(OR(G48="Sin pagar",G48="Pagar"),_xlfn.SINGLE(NETWORKDAYS($E$4,F48,'Festivos CR'!$A$3:$A$15)),0) -> 0 | I35: =NETWORKDAYS($E$4,F48,'Festivos CR'!$A$3:$A$15) -> 18 | J35: =H35 -> 0
B36: XXXX | C36: Cobro S&P a sucursal Junio | D36: =E36*$D$6*0 -> 0 | E36: =720*0 -> 0 | F36: 45504 | G36: Cancelado | H36: =IF(OR(G49="Sin pagar",G49="Pagar"),_xlfn.SINGLE(NETWORKDAYS($E$4,F49,'Festivos CR'!$A$3:$A$15)),0) -> 0 | I36: =NETWORKDAYS($E$4,F49,'Festivos CR'!$A$3:$A$15) -> -32458 | J36: =H36 -> 0
C37: COSTOS FINANCIEROS | D37: =SUBTOTAL(9,D38:D38) -> 403.5 | E37: =SUBTOTAL(9,E38:E38) -> 0.77745665
C38: COSTOS FINANCIEROS | D38: 403.5 | E38: =D38/D6 -> 0.77745665 | F38: 45473 | G38: Cancelado | H38: =IF(OR(G38="Sin pagar",G38="Pagar"),_xlfn.SINGLE(NETWORKDAYS($E$4,F38,'Festivos CR'!$A$3:$A$15)),0) -> 0 | I38: =NETWORKDAYS($E$4,F38,'Festivos CR'!$A$3:$A$15) -> 18 | J38: =H38 -> 0
C39: NÓMINAS | D39: =SUBTOTAL(9,D40:D46) -> 10706121 | E39: =SUBTOTAL(9,E40:E46) -> 20628.365
B40: CRC | C40: Jhoel González González-Starlight-CR003 | D40: 1612916.3 | E40: =D40/$D$6 -> 3107.7386 | F40: 45471 | G40: Cancelado | H40: =IF(OR(G40="Sin pagar",G40="Pagar"),_xlfn.SINGLE(NETWORKDAYS($E$4,F40,'Festivos CR'!$A$3:$A$15)),0) -> 0 | I40: =NETWORKDAYS($E$4,F40,'Festivos CR'!$A$3:$A$15) -> 18 | J40: =H40 -> 0
B41: USD | C41: Jonathan Salazar García -Starlight-CR003 | D41: =E41*$D$6 -> 1768653.4 | E41: 3407.81 | F41: 45471 | G41: Cancelado | H41: =IF(OR(G41="Sin pagar",G41="Pagar"),_xlfn.SINGLE(NETWORKDAYS($E$4,F41,'Festivos CR'!$A$3:$A$15)),0) -> 0 | I41: =NETWORKDAYS($E$4,F41,'Festivos CR'!$A$3:$A$15) -> 18 | J41: =H41 -> 0
B42: CRC | C42: Daniel Nazario Casto Vindas-Starlight-CR003 | D42: 326417.87 | E42: =D42/$D$6 -> 628.93617 | F42: 45471 | G42: Cancelado | H42: =IF(OR(G42="Sin pagar",G42="Pagar"),_xlfn.SINGLE(NETWORKDAYS($E$4,F42,'Festivos CR'!$A$3:$A$15)),0) -> 0 | I42: =NETWORKDAYS($E$4,F42,'Festivos CR'!$A$3:$A$15) -> 18 | J42: =H42 -> 0
B43: CRC | C43: Priscilla Grace Polson -Aluminati-CR004 | D43: 1410537.3 | E43: =D43/$D$6 -> 2717.7983 | F43: 45471 | G43: Cancelado | H43: =IF(OR(G43="Sin pagar",G43="Pagar"),_xlfn.SINGLE(NETWORKDAYS($E$4,F43,'Festivos CR'!$A$3:$A$15)),0) -> 0 | I43: =NETWORKDAYS($E$4,F43,'Festivos CR'!$A$3:$A$15) -> 18 | J43: =H43 -> 0
B44: CRC | C44: José Roberto Aguilar Barrante-Aluminati-CR004 | D44: 1410537.3 | E44: =D44/$D$6 -> 2717.7983 | F44: 45471 | G44: Cancelado | H44: =IF(OR(G44="Sin pagar",G44="Pagar"),_xlfn.SINGLE(NETWORKDAYS($E$4,F44,'Festivos CR'!$A$3:$A$15)),0) -> 0 | I44: =NETWORKDAYS($E$4,F44,'Festivos CR'!$A$3:$A$15) -> 18 | J44: =H44 -> 0
B45: CRC | C45: Sheryl Gertrudiz Cambronero Estrada-lorez & Prada PPLC | D45: 786551.54 | E45: =D45/$D$6 -> 1515.5136 | F45: 45471 | G45: Cancelado | H45: =IF(OR(G45="Sin pagar",G45="Pagar"),_xlfn.SINGLE(NETWORKDAYS($E$4,F45,'Festivos CR'!$A$3:$A$15)),0) -> 0 | I45: =NETWORKDAYS($E$4,F45,'Festivos CR'!$A$3:$A$15) -> 18 | J45: =H45 -> 0
B46: USD | C46: Tatiana Araya Pochet-CZ-CR006 | D46: =E46*$D$6 -> 3390507.6 | E46: 6532.77 | F46: 45471 | G46: Cancelado | H46: =IF(OR(G46="Sin pagar",G46="Pagar"),_xlfn.SINGLE(NETWORKDAYS($E$4,F46,'Festivos CR'!$A$3:$A$15)),0) -> 0 | I46: =NETWORKDAYS($E$4,F46,'Festivos CR'!$A$3:$A$15) -> 18 | J46: =H46 -> 0
C47: IMPREVISTO | D47: =SUBTOTAL(9,D48:D48) -> 0 | E47: =SUBTOTAL(9,E48:E48) -> 0
D48: 0 | E48: =D48/$D$6 -> 0 | F48: 45473 | G48: Cancelado | H48: =IF(OR(#REF!="Sin pagar",#REF!="Pagar"),_xlfn.SINGLE(NETWORKDAYS($E$4,#REF!,'Festivos CR'!$A$3:$A$15)),0) -> #REF! | I48: =NETWORKDAYS($E$4,#REF!,'Festivos CR'!$A$3:$A$15) -> #REF!
C49: TOTAL EGRESOS | D49: =SUBTOTAL(9,D23:D48) -> 16827633 | E49: =SUBTOTAL(9,E23:E48) -> 32423.184
C51: SALDO | D51: =D18-D49 -> 11752352 | E51: =E18-E49 -> 22599.809
C52: % | D52: =IF($D$18=0,0,D51/$D$18) -> 0.41120918 | E52: =IF($E$18=0,0,E51/$E$18) -> 0.41073391
C56: Fecha Inicial | D56: Fecha Final | E56: Valor VALOR ₡ CRC | F56: Valor VALOR USD
C57: 45446 | D57: 45452 | E57: =SUMIFS($D$22:$D$54,$F$22:$F$54,">="&C57,$F$22:$F$54,"<="&D57,$G$22:$G$54,$D$70) -> 0 | F57: =SUMIFS($E$22:$E$54,$F$22:$F$54,">="&C57,$F$22:$F$54,"<="&D57,$G$22:$G$54,$D$70) -> 0
C58: 45453 | D58: 45459 | E58: =SUMIFS($D$22:$D$54,$F$22:$F$54,">="&C58,$F$22:$F$54,"<="&D58,$G$22:$G$54,$D$70) -> 0 | F58: =SUMIFS($E$22:$E$54,$F$22:$F$54,">="&C58,$F$22:$F$54,"<="&D58,$G$22:$G$54,$D$70) -> 0
C59: 45460 | D59: 45466 | E59: =SUMIFS($D$22:$D$54,$F$22:$F$54,">="&C59,$F$22:$F$54,"<="&D59,$G$22:$G$54,$D$70) -> 0 | F59: =SUMIFS($E$22:$E$54,$F$22:$F$54,">="&C59,$F$22:$F$54,"<="&D59,$G$22:$G$54,$D$70) -> 0
C60: 45467 | D60: 45473 | E60: =SUMIFS($D$22:$D$54,$F$22:$F$54,">="&C60,$F$22:$F$54,"<="&D60,$G$22:$G$54,$D$70) -> 0 | F60: =SUMIFS($E$22:$E$54,$F$22:$F$54,">="&C60,$F$22:$F$54,"<="&D60,$G$22:$G$54,$D$70) -> 0
C61: TOTAL EGRESOS | E61: =SUM(E57:E60) -> 0 | F61: =SUM(F57:F60) -> 0
C64: Bancos | E64: =943958.78+(41529.6*520) -> 22539351 | F64: =E64/517 -> 43596.423
C65: Gastos y costos Periodo 10 al 23 Junio (SS-Impuesto) | E65: =E60 -> 0 | F65: =F60 -> 0
C66: Saldo | E66: =E64-E65 -> 22539351 | F66: =F64-F65 -> 43596.423
D69: Cancelado | E69: =SUMIFS($D$22:$D$54,$F$22:$F$54,">="&C57,$F$22:$F$54,"<="&$D$60,$G$22:$G$54,$D$69) -> 16827633 | F69: =SUMIFS($E$22:$E$54,$F$22:$F$54,">="&C57,$F$22:$F$54,"<="&D60,$G$22:$G$54,$D$69) -> 32423.184
D70: Sin Pagar | E70: =SUMIFS($D$22:$D$54,$F$22:$F$54,">="&C57,$F$22:$F$54,"<="&$D$60,$G$22:$G$54,$D$70) -> 0 | F70: =SUMIFS($E$22:$E$54,$F$22:$F$54,">="&C57,$F$22:$F$54,"<="&D60,$G$22:$G$54,$D$70) -> 0
D71: Total Egresos | E71: =SUM(E69:E70) -> 16827633 | F71: =SUM(F69:F70) -> 32423.184
D72: Validación | E72: =D49-E71 -> 0 | F72: =F71-E49 -> 0
D75: Flujo Caja | E75: =D51 -> 11752352
D76: Libro Bancos | E76: ='BAC SAN JOSE COLONES '!G207+('BAC SAN JOSE USD'!G190*$D$6) -> 11752303
D77: Diferencia | E77: =E75-E76 -> 48.743892 | F77: =+E77/D6 -> 0.093918867

Sheet FLUJO CAJA JULIO 
D1: 42400
D4: Fecha de Elaboración: | E4: 45474
C6: Tasa de cambio: | D6: 522
D7: JULIO
D8: VALOR ₡ CRC | E8: VALOR USD
C9: BANCOS | D9: =SUBTOTAL(9,D10:D11) -> 11779308 | E9: =SUBTOTAL(9,E10:E11) -> 22565.724
C10: Bancos ₡ CRC | D10: ='BAC SAN JOSE COLONES '!G207 -> 7080494.5 | E10: =D10/$D$6 -> 13564.166
C11: Bancos USD | D11: ='BAC SAN JOSE USD'!G190*$D$6 -> 4698813.5 | E11: =D11/$D$6 -> 9001.5584
C12: CLIENTES | D12: =SUBTOTAL(9,D13:D16) -> 19014768 | E12: =SUBTOTAL(9,E13:E16) -> 36426.759
C13: Client: Remorfist-Client-Starlight SS -Factura Nro 140 | D13: =E13*$D$6 -> 7515256.3 | E13: =CONVERSIONES!$C$124+CONVERSIONES!$D$124+CONVERSIONES!$E$124 -> 14397.043
C14: Client: Remorfist-Client: Aluminati-Factura Nro 141 | D14: =E14*$D$6 -> 4454090.3 | E14: =CONVERSIONES!$F$124+CONVERSIONES!$G$124 -> 8532.74
C15: Remorfist - Client: CZ SS-Factura Nro 138 | D15: =E15*$D$6 -> 5842986.1 | E15: =CONVERSIONES!$H$124 -> 11193.46
C16: Remorfist - Client: PLLC- Factura Nro 139 | D16: =E16*$D$6 -> 1202435.6 | E16: =CONVERSIONES!$I$124 -> 2303.5165
C17: TOTAL INGRESOS | D17: =SUBTOTAL(9,D9:D16) -> 30794076 | E17: =SUBTOTAL(9,E9:E16) -> 58992.483
B20: CUENTAS X PAGAR MES | D20: JULIO
B21: Factura | C21: PROVEEDOR | D21: VALOR ₡ CRC | E21: VALOR USD | F21: Fecha vencimiento | G21: Estado | J21: KPI
C22: SEGURIDAD IGSS | D22: =SUBTOTAL(9,D23:D23) -> 5040051.5 | E22: =SUBTOTAL(9,E23:E23) -> 9655.271
B23: 176206200 | C23: Pago CCSS Junio | D23: 5040051.5 | E23: =D23/$D$6 -> 9655.271 | F23: 45482 | G23: Cancelado | H23: =IF(OR(G23="Sin pagar",G23="Pagar"),_xlfn.SINGLE(NETWORKDAYS($E$4,F23,'Festivos CR'!$A$3:$A$15)),0) -> 0 | I23: =NETWORKDAYS($E$4,F23,'Festivos CR'!$A$3:$A$15) -> 7 | J23: =H23 -> 0
C24: IMPUESTOS | D24: =SUBTOTAL(9,D25:D26) -> 1121832.4 | E24: =SUBTOTAL(9,E25:E26) -> 2149.1043 | J24: =H24 -> 0
C25: Retención en la fuente | D25: 1098581.4 | E25: =D25/$D$6 -> 2104.5622 | F25: 45482 | G25: Cancelado | H25: =IF(OR(G25="Sin pagar",G25="Pagar"),_xlfn.SINGLE(NETWORKDAYS($E$4,F25,'Festivos CR'!$A$3:$A$15)),0) -> 0 | I25: =NETWORKDAYS($E$4,F25,'Festivos CR'!$A$3:$A$15) -> 7 | J25: =H25 -> 0
C26: Rte fte por declaración de remesas al exterior Facturación S&P Colombia a S&P CR | D26: 23251 | E26: =D26/$D$6 -> 44.542146 | F26: 45482 | G26: Cancelado | H26: =IF(OR(G26="Sin pagar",G26="Pagar"),_xlfn.SINGLE(NETWORKDAYS($E$4,F26,'Festivos CR'!$A$3:$A$15)),0) -> 0 | I26: =NETWORKDAYS($E$4,F26,'Festivos CR'!$A$3:$A$15) -> 7 | J26: =H26 -> 0
C27: SERVICIOS PROFESIONALES -REPRESENTACIÓN LEGAL | D27: =SUBTOTAL(9,D28:D28) -> 62400 | E27: =SUBTOTAL(9,E28:E28) -> 119.54023 | J27: =H27 -> 0
B28: 17 | C28: Servicios profesionales Alejandro Echavarria Junio | D28: 62400 | E28: =D28/$D$6 -> 119.54023 | F28: 45499 | G28: Cancelado | H28: =IF(OR(G28="Sin pagar",G28="Pagar"),_xlfn.SINGLE(NETWORKDAYS($E$4,F28,'Festivos CR'!$A$3:$A$15)),0) -> 0 | I28: =NETWORKDAYS($E$4,F28,'Festivos CR'!$A$3:$A$15) -> 19 | J28: =H28 -> 0
C29: GASTOS DE OFICINA | D29: =SUBTOTAL(9,D30:D30) -> 77000 | E29: =SUBTOTAL(9,E30:E30) -> 147.50958
B30: 57 | C30: Compra de café | D30: 77000 | E30: =D30/$D$6 -> 147.50958 | F30: 45475 | G30: Cancelado | H30: =IF(OR(G30="Sin pagar",G30="Pagar"),_xlfn.SINGLE(NETWORKDAYS($E$4,F30,'Festivos CR'!$A$3:$A$15)),0) -> 0 | I30: =NETWORKDAYS($E$4,F30,'Festivos CR'!$A$3:$A$15) -> 2 | J30: =H30 -> 0
C31: COBROS ENTRE SUCURSALES | D31: =SUBTOTAL(9,D32:D35) -> 0 | E31: =SUBTOTAL(9,E32:E35) -> 0
B32: 4699 | C32: Cobro S&P a sucursal Enero a marzo | D32: =E32*$D$6*0 -> 0 | E32: =880*0 -> 0 | F32: 45504 | G32: Cancelado | H32: =IF(OR(G32="Sin pagar",G32="Pagar"),_xlfn.SINGLE(NETWORKDAYS($E$4,F32,'Festivos CR'!$A$3:$A$15)),0) -> 0 | I32: =NETWORKDAYS($E$4,F32,'Festivos CR'!$A$3:$A$15) -> 22 | J32: =H32 -> 0
B33: 4777 | C33: Cobro S&P a sucursal Abril | D33: =E33*$D$6*0 -> 0 | E33: =720*0 -> 0 | F33: 45504 | G33: Cancelado | H33: =IF(OR(G33="Sin pagar",G33="Pagar"),_xlfn.SINGLE(NETWORKDAYS($E$4,F33,'Festivos CR'!$A$3:$A$15)),0) -> 0 | I33: =NETWORKDAYS($E$4,F33,'Festivos CR'!$A$3:$A$15) -> 22 | J33: =H33 -> 0
B34: 4878 | C34: Cobro S&P a sucursal Mayo | D34: =E34*$D$6*0 -> 0 | E34: =720*0 -> 0 | F34: 45504 | G34: Cancelado | H34: =IF(OR(G47="Sin pagar",G47="Pagar"),_xlfn.SINGLE(NETWORKDAYS($E$4,F47,'Festivos CR'!$A$3:$A$15)),0) -> 0 | I34: =NETWORKDAYS($E$4,F47,'Festivos CR'!$A$3:$A$15) -> 21 | J34: =H34 -> 0
B35: 4957 | C35: Cobro S&P a sucursal Junio | D35: =E35*$D$6*0 -> 0 | E35: =330*0 -> 0 | F35: 45504 | G35: Cancelado | H35: =IF(OR(G48="Sin pagar",G48="Pagar"),_xlfn.SINGLE(NETWORKDAYS($E$4,F48,'Festivos CR'!$A$3:$A$15)),0) -> 0 | I35: =NETWORKDAYS($E$4,F48,'Festivos CR'!$A$3:$A$15) -> -32476 | J35: =H35 -> 0
C36: COSTOS FINANCIEROS | D36: =SUBTOTAL(9,D37:D37) -> 399.75 | E36: =SUBTOTAL(9,E37:E37) -> 0.7658046
C37: COSTOS FINANCIEROS | D37: 399.75 | E37: =D37/D6 -> 0.7658046 | F37: 45504 | G37: Cancelado | H37: =IF(OR(G37="Sin pagar",G37="Pagar"),_xlfn.SINGLE(NETWORKDAYS($E$4,F37,'Festivos CR'!$A$3:$A$15)),0) -> 0 | I37: =NETWORKDAYS($E$4,F37,'Festivos CR'!$A$3:$A$15) -> 22 | J37: =H37 -> 0
C38: NÓMINAS | D38: =SUBTOTAL(9,D39:D45) -> 11737204 | E38: =SUBTOTAL(9,E39:E45) -> 22485.065
B39: CRC | C39: Jhoel González González-Starlight-CR003 | D39: 1612916.3 | E39: =D39/$D$6 -> 3089.878 | F39: 45499 | G39: Cancelado | H39: =IF(OR(G39="Sin pagar",G39="Pagar"),_xlfn.SINGLE(NETWORKDAYS($E$4,F39,'Festivos CR'!$A$3:$A$15)),0) -> 0 | I39: =NETWORKDAYS($E$4,F39,'Festivos CR'!$A$3:$A$15) -> 19 | J39: =H39 -> 0
B40: USD | C40: Jonathan Salazar García -Starlight-CR003 | D40: =E40*$D$6 -> 1779832.1 | E40: 3409.64 | F40: 45499 | G40: Cancelado | H40: =IF(OR(G40="Sin pagar",G40="Pagar"),_xlfn.SINGLE(NETWORKDAYS($E$4,F40,'Festivos CR'!$A$3:$A$15)),0) -> 0 | I40: =NETWORKDAYS($E$4,F40,'Festivos CR'!$A$3:$A$15) -> 19 | J40: =H40 -> 0
B41: CRC | C41: Daniel Nazario Casto Vindas-Starlight-CR003 | D41: 1325079.4 | E41: =D41/$D$6 -> 2538.4662 | F41: 45499 | G41: Cancelado | H41: =IF(OR(G41="Sin pagar",G41="Pagar"),_xlfn.SINGLE(NETWORKDAYS($E$4,F41,'Festivos CR'!$A$3:$A$15)),0) -> 0 | I41: =NETWORKDAYS($E$4,F41,'Festivos CR'!$A$3:$A$15) -> 19 | J41: =H41 -> 0
B42: CRC | C42: Priscilla Grace Polson -Aluminati-CR004 | D42: 1410537.3 | E42: =D42/$D$6 -> 2702.1787 | F42: 45499 | G42: Cancelado | H42: =IF(OR(G42="Sin pagar",G42="Pagar"),_xlfn.SINGLE(NETWORKDAYS($E$4,F42,'Festivos CR'!$A$3:$A$15)),0) -> 0 | I42: =NETWORKDAYS($E$4,F42,'Festivos CR'!$A$3:$A$15) -> 19 | J42: =H42 -> 0
B43: CRC | C43: José Roberto Aguilar Barrante-Aluminati-CR004 | D43: 1410537.3 | E43: =D43/$D$6 -> 2702.1787 | F43: 45499 | G43: Cancelado | H43: =IF(OR(G43="Sin pagar",G43="Pagar"),_xlfn.SINGLE(NETWORKDAYS($E$4,F43,'Festivos CR'!$A$3:$A$15)),0) -> 0 | I43: =NETWORKDAYS($E$4,F43,'Festivos CR'!$A$3:$A$15) -> 19 | J43: =H43 -> 0
B44: CRC | C44: Sheryl Gertrudiz Cambronero Estrada-lorez & Prada PPLC | D44: 786551.54 | E44: =D44/$D$6 -> 1506.8037 | F44: 45499 | G44: Cancelado | H44: =IF(OR(G44="Sin pagar",G44="Pagar"),_xlfn.SINGLE(NETWORKDAYS($E$4,F44,'Festivos CR'!$A$3:$A$15)),0) -> 0 | I44: =NETWORKDAYS($E$4,F44,'Festivos CR'!$A$3:$A$15) -> 19 | J44: =H44 -> 0
B45: USD | C45: Tatiana Araya Pochet-CZ-CR006 | D45: =E45*$D$6 -> 3411750.2 | E45: 6535.92 | F45: 45499 | G45: Cancelado | H45: =IF(OR(G45="Sin pagar",G45="Pagar"),_xlfn.SINGLE(NETWORKDAYS($E$4,F45,'Festivos CR'!$A$3:$A$15)),0) -> 0 | I45: =NETWORKDAYS($E$4,F45,'Festivos CR'!$A$3:$A$15) -> 19 | J45: =H45 -> 0
C46: IMPREVISTO | D46: =SUBTOTAL(9,D47:D47) -> 0 | E46: =SUBTOTAL(9,E47:E47) -> 0
D47: 0 | E47: =D47/$D$6 -> 0 | F47: 45503 | G47: Cancelado | H47: =IF(OR(#REF!="Sin pagar",#REF!="Pagar"),_xlfn.SINGLE(NETWORKDAYS($E$4,#REF!,'Festivos CR'!$A$3:$A$15)),0) -> #REF! | I47: =NETWORKDAYS($E$4,#REF!,'Festivos CR'!$A$3:$A$15) -> #REF!
C48: TOTAL EGRESOS | D48: =SUBTOTAL(9,D22:D47) -> 18038888 | E48: =SUBTOTAL(9,E22:E47) -> 34557.256
C50: SALDO | D50: =D17-D48 -> 12755188 | E50: =E17-E48 -> 24435.227
C51: % | D51: =IF($D$17=0,0,D50/$D$17) -> 0.41420916 | E51: =IF($E$17=0,0,E50/$E$17) -> 0.41420916
C55: Fecha Inicial | D55: Fecha Final | E55: Valor VALOR ₡ CRC | F55: Valor VALOR USD
C56: 45474 | D56: 45480 | E56: =SUMIFS($D$21:$D$53,$F$21:$F$53,">="&C56,$F$21:$F$53,"<="&D56,$G$21:$G$53,$D$70) -> 0 | F56: =SUMIFS($E$21:$E$53,$F$21:$F$53,">="&C56,$F$21:$F$53,"<="&D56,$G$21:$G$53,$D$70) -> 0
C57: 45481 | D57: 45487 | E57: =SUMIFS($D$21:$D$53,$F$21:$F$53,">="&C57,$F$21:$F$53,"<="&D57,$G$21:$G$53,$D$70) -> 0 | F57: =SUMIFS($E$21:$E$53,$F$21:$F$53,">="&C57,$F$21:$F$53,"<="&D57,$G$21:$G$53,$D$70) -> 0 | G57: CCSS
C58: 45488 | D58: 45494 | E58: =SUMIFS($D$21:$D$53,$F$21:$F$53,">="&C58,$F$21:$F$53,"<="&D58,$G$21:$G$53,$D$70) -> 0 | F58: =SUMIFS($E$21:$E$53,$F$21:$F$53,">="&C58,$F$21:$F$53,"<="&D58,$G$21:$G$53,$D$70) -> 0 | G58: Impuestos Rte Fte
C59: 45495 | D59: 45501 | E59: =SUMIFS($D$21:$D$53,$F$21:$F$53,">="&C59,$F$21:$F$53,"<="&D59,$G$21:$G$53,$D$70) -> 0 | F59: =SUMIFS($E$21:$E$53,$F$21:$F$53,">="&C59,$F$21:$F$53,"<="&D59,$G$21:$G$53,$D$70) -> 0 | G59: Nóminas y gastos admon
C60: 45502 | D60: 45504 | E60: =SUMIFS($D$21:$D$53,$F$21:$F$53,">="&C60,$F$21:$F$53,"<="&D60,$G$21:$G$53,$D$70) -> 0 | F60: =SUMIFS($E$21:$E$53,$F$21:$F$53,">="&C60,$F$21:$F$53,"<="&D60,$G$21:$G$53,$D$70) -> 0
C61: TOTAL EGRESOS | E61: =SUM(E56:E60) -> 0 | F61: =SUM(F56:F60) -> 0
C64: Bancos | E64: =('BAC SAN JOSE COLONES '!$G$212)+('BAC SAN JOSE USD'!$G$190*$D$6) -> 5641542.2 | F64: =E64/$D$6 -> 10807.552
C65: Gastos y costos Periodo01 al 15 Julio (SS-Impuesto) | E65: =SUM(E56:E58) -> 0 | F65: =SUM(F56:F58) -> 0
C66: Saldo | E66: =E64-E65 -> 5641542.2 | F66: =F64-F65 -> 10807.552
D69: Cancelado | E69: =SUMIFS($D$21:$D$53,$F$21:$F$53,">="&C56,$F$21:$F$53,"<="&$D$60,$G$21:$G$53,$D$69) -> 18038888 | F69: =SUMIFS($E$21:$E$53,$F$21:$F$53,">="&C56,$F$21:$F$53,"<="&D60,$G$21:$G$53,$D$69) -> 34557.256
D70: Sin Pagar | E70: =SUMIFS($D$21:$D$53,$F$21:$F$53,">="&C56,$F$21:$F$53,"<="&$D$60,$G$21:$G$53,$D$70) -> 0 | F70: =SUMIFS($E$21:$E$53,$F$21:$F$53,">="&C56,$F$21:$F$53,"<="&D60,$G$21:$G$53,$D$70) -> 0
D71: Total Egresos | E71: =SUM(E69:E70) -> 18038888 | F71: =SUM(F69:F70) -> 34557.256
D72: Validación | E72: =D48-E71 -> 0 | F72: =F71-E48 -> 0
D75: Flujo Caja | E75: =D50 -> 12755188
D76: Libro Bancos | E76: =('BAC SAN JOSE USD'!G197*$D$6)+'BAC SAN JOSE COLONES '!G221 -> 12755156
D77: Diferencia | E77: =E76-E75 -> -32.506935

Sheet FLUJO CAJA AGOSTO
D1: 42400
D4: Fecha de Elaboración: | E4: 45505
C6: Tasa de cambio: | D6: 518
D7: AGOSTO
D8: VALOR ₡ CRC | E8: VALOR USD
C9: BANCOS | D9: =SUBTOTAL(9,D10:D11) -> 12715370 | E9: =SUBTOTAL(9,E10:E11) -> 24547.046
C10: Bancos ₡ CRC | D10: ='BAC SAN JOSE COLONES '!$G$221 -> 7563057.3 | E10: =D10/$D$6 -> 14600.497
C11: Bancos USD | D11: =E11*$D$6 -> 5152312.5 | E11: ='BAC SAN JOSE USD'!$G$196 -> 9946.5492
C12: CLIENTES | D12: =SUBTOTAL(9,D13:D17) -> 19822836 | E12: =SUBTOTAL(9,E13:E17) -> 38716.476
C13: Client: Remorfist-Client-Starlight SS -Factura Nro 142 | D13: =E13*CONVERSIONES!$C$146 -> 7402756.9 | E13: =CONVERSIONES!$C$142+CONVERSIONES!$D$142+CONVERSIONES!$E$142 -> 14458.51
C14: Client: Remorfist-Client: Aluminati-Factura Nro 143 | D14: =E14*CONVERSIONES!$C$146 -> 4401268 | E14: =CONVERSIONES!$F$142+CONVERSIONES!$G$142 -> 8596.2266
C15: Remorfist - Client: CZ SS-Factura Nro 144 | D15: =E15*CONVERSIONES!$C$146 -> 5733611.5 | E15: =CONVERSIONES!$H$142 -> 11198.46
C16: Remorfist - Client: PLLC- Factura Nro 145 | D16: =E16*CONVERSIONES!$C$146 -> 1190476.8 | E16: =CONVERSIONES!$I$142 -> 2325.15
C17: Client: Remorfist-Client-Starlight SS -Factura Nro 146-Offcycle | D17: =E17*CONVERSIONES!$C$146 -> 1094722.6 | E17: =CONVERSIONES!$J$142 -> 2138.13
C18: TOTAL INGRESOS | D18: =SUBTOTAL(9,D9:D17) -> 32538206 | E18: =SUBTOTAL(9,E9:E17) -> 63263.522
B21: CUENTAS X PAGAR MES | D21: AGOSTO
B22: Factura | C22: PROVEEDOR | D22: VALOR ₡ CRC | E22: VALOR USD | F22: Fecha vencimiento | G22: Estado | J22: KPI
C23: SEGURIDAD IGSS | D23: =SUBTOTAL(9,D24:D24) -> 5377274 | E23: =SUBTOTAL(9,E24:E24) -> 10380.838
B24: 202407-3102766975-1 | C24: Pago CCSS Julio | D24: 5377274 | E24: =D24/$D$6 -> 10380.838 | F24: 45513 | G24: Cancelado | H24: =IF(OR(G24="Sin pagar",G24="Pagar"),_xlfn.SINGLE(NETWORKDAYS($E$4,F24,'Festivos CR'!$A$3:$A$15)),0) -> 0 | I24: =NETWORKDAYS($E$4,F24,'Festivos CR'!$A$3:$A$15) -> 6 | J24: =H24 -> 0
C25: IMPUESTOS | D25: =SUBTOTAL(9,D26:D27) -> 1235035 | E25: =SUBTOTAL(9,E26:E27) -> 2384.2375 | J25: =H25 -> 0
C26: Retención en la fuente | D26: 1166839 | E26: =D26/$D$6 -> 2252.5849 | F26: 45516 | G26: Cancelado | H26: =IF(OR(G26="Sin pagar",G26="Pagar"),_xlfn.SINGLE(NETWORKDAYS($E$4,F26,'Festivos CR'!$A$3:$A$15)),0) -> 0 | I26: =NETWORKDAYS($E$4,F26,'Festivos CR'!$A$3:$A$15) -> 7 | J26: =H26 -> 0
C27: Rte fte por declaración de remesas al exterior Facturación S&P Colombia a S&P CR | D27: 68196 | E27: =D27/$D$6 -> 131.65251 | F27: 45516 | G27: Cancelado | H27: =IF(OR(G27="Sin pagar",G27="Pagar"),_xlfn.SINGLE(NETWORKDAYS($E$4,F27,'Festivos CR'!$A$3:$A$15)),0) -> 0 | I27: =NETWORKDAYS($E$4,F27,'Festivos CR'!$A$3:$A$15) -> 7 | J27: =H27 -> 0
C28: SERVICIOS PROFESIONALES -REPRESENTACIÓN LEGAL | D28: =SUBTOTAL(9,D29:D29) -> 62400 | E28: =SUBTOTAL(9,E29:E29) -> 120.46332 | J28: =H28 -> 0
B29: 18 | C29: Servicios profesionales Alejandro Echavarria Agosto | D29: 62400 | E29: =D29/$D$6 -> 120.46332 | F29: 45531 | G29: Cancelado | H29: =IF(OR(G29="Sin pagar",G29="Pagar"),_xlfn.SINGLE(NETWORKDAYS($E$4,F29,'Festivos CR'!$A$3:$A$15)),0) -> 0 | I29: =NETWORKDAYS($E$4,F29,'Festivos CR'!$A$3:$A$15) -> 17 | J29: =H29 -> 0
C30: GASTOS DE OFICINA | D30: =SUBTOTAL(9,D31:D31) -> 77000 | E30: =SUBTOTAL(9,E31:E31) -> 148.64865
B31: 58 | C31: Compra de café | D31: 77000 | E31: =D31/$D$6 -> 148.64865 | F31: 45512 | G31: Cancelado | H31: =IF(OR(G31="Sin pagar",G31="Pagar"),_xlfn.SINGLE(NETWORKDAYS($E$4,F31,'Festivos CR'!$A$3:$A$15)),0) -> 0 | I31: =NETWORKDAYS($E$4,F31,'Festivos CR'!$A$3:$A$15) -> 5 | J31: =H31 -> 0
C32: COBROS ENTRE SUCURSALES | D32: =SUBTOTAL(9,D33:D38) -> 0 | E32: =SUBTOTAL(9,E33:E38) -> 0 | M32: Facturado | N32: Cruzado | O32: 0
B33: 4699 | C33: Cobro S&P a sucursal Enero a marzo | D33: =E33*$D$6 -> 0 | E33: =(228818/3888.02)*$O$32 -> 0 | F33: 45535 | G33: Cancelado | H33: =IF(OR(G33="Sin pagar",G33="Pagar"),_xlfn.SINGLE(NETWORKDAYS($E$4,F33,'Festivos CR'!$A$3:$A$15)),0) -> 0 | I33: =NETWORKDAYS($E$4,F33,'Festivos CR'!$A$3:$A$15) -> 20 | J33: =H33 -> 0 | M33: 880 | N33: =M33-E33 -> 880
B34: 4777 | C34: Cobro S&P a sucursal Abril | D34: =E34*$D$6 -> 0 | E34: =(160718/3924.82)*$O$32 -> 0 | F34: 45535 | G34: Cancelado | H34: =IF(OR(G34="Sin pagar",G34="Pagar"),_xlfn.SINGLE(NETWORKDAYS($E$4,F34,'Festivos CR'!$A$3:$A$15)),0) -> 0 | I34: =NETWORKDAYS($E$4,F34,'Festivos CR'!$A$3:$A$15) -> 20 | J34: =H34 -> 0 | M34: 720 | N34: =M34-E34 -> 720
B35: 4878 | C35: Cobro S&P a sucursal Mayo | D35: =E35*$D$6 -> 0 | E35: =(205400/3829.59)*$O$32 -> 0 | F35: 45535 | G35: Cancelado | H35: =IF(OR(G50="Sin pagar",G50="Pagar"),_xlfn.SINGLE(NETWORKDAYS($E$4,F50,'Festivos CR'!$A$3:$A$15)),0) -> 0 | I35: =NETWORKDAYS($E$4,F50,'Festivos CR'!$A$3:$A$15) -> -3 | J35: =H35 -> 0 | M35: 645 | N35: =M35-E35 -> 645
B36: 4957 | C36: Cobro S&P a sucursal Junio | D36: =E36*$D$6 -> 0 | E36: 0 | F36: 45535 | G36: Cancelado | H36: =IF(OR(G51="Sin pagar",G51="Pagar"),_xlfn.SINGLE(NETWORKDAYS($E$4,F51,'Festivos CR'!$A$3:$A$15)),0) -> 0 | I36: =NETWORKDAYS($E$4,F51,'Festivos CR'!$A$3:$A$15) -> -32498 | J36: =H36 -> 0 | M36: 330 | N36: 330
B37: 4957 | C37: Cobro S&P a sucursal Julio | D37: =E37*$D$6 -> 0 | E37: =515*$O$32 -> 0 | F37: 45535 | G37: Cancelado | H37: =IF(OR(G52="Sin pagar",G52="Pagar"),_xlfn.SINGLE(NETWORKDAYS($E$4,F52,'Festivos CR'!$A$3:$A$15)),0) -> 0 | I37: =NETWORKDAYS($E$4,F52,'Festivos CR'!$A$3:$A$15) -> -32498 | J37: =H37 -> 0 | M37: 550 | N37: 0
B38: 5160 | C38: Cobro S&P a sucursal Agosto | D38: =E38*$D$6 -> 0 | E38: =755*0 -> 0 | F38: 45535 | G38: Cancelado | H38: =IF(OR(G53="Sin pagar",G53="Pagar"),_xlfn.SINGLE(NETWORKDAYS($E$4,F53,'Festivos CR'!$A$3:$A$15)),0) -> 0 | I38: =NETWORKDAYS($E$4,F53,'Festivos CR'!$A$3:$A$15) -> -32498 | J38: =H38 -> 0 | M38: 550 | N38: 0
C39: COSTOS FINANCIEROS | D39: =SUBTOTAL(9,D40:D40) -> 59521.68 | E39: =SUBTOTAL(9,E40:E40) -> 114.90672 | M39: =SUM(M33:M37) -> 3125 | N39: =SUM(N33:N37) -> 2575 | O39: Saldo | P39: =M39-N39 -> 550
C40: COSTOS FINANCIEROS | D40: 59521.68 | E40: =D40/D6 -> 114.90672 | F40: 45534 | G40: Cancelado | H40: =IF(OR(G40="Sin pagar",G40="Pagar"),_xlfn.SINGLE(NETWORKDAYS($E$4,F40,'Festivos CR'!$A$3:$A$15)),0) -> 0 | I40: =NETWORKDAYS($E$4,F40,'Festivos CR'!$A$3:$A$15) -> 20 | J40: =H40 -> 0
C41: NÓMINAS | D41: =SUBTOTAL(9,D42:D48) -> 12225663 | E41: =SUBTOTAL(9,E42:E48) -> 23878.248
B42: CRC | C42: Jhoel González González-Starlight-CR003 | D42: 1612916.3 | E42: =D42/CONVERSIONES!$C$146 -> 3150.2272 | F42: 45532 | G42: Cancelado | H42: =IF(OR(G42="Sin pagar",G42="Pagar"),_xlfn.SINGLE(NETWORKDAYS($E$4,F42,'Festivos CR'!$A$3:$A$15)),0) -> 0 | I42: =NETWORKDAYS($E$4,F42,'Festivos CR'!$A$3:$A$15) -> 18 | J42: =H42 -> 0
B43: USD | C43: Jonathan Salazar García -Starlight-CR003 | D43: =E43*CONVERSIONES!$C$146 -> 2333562.9 | E43: 4557.74 | F43: 45532 | G43: Cancelado | H43: =IF(OR(G43="Sin pagar",G43="Pagar"),_xlfn.SINGLE(NETWORKDAYS($E$4,F43,'Festivos CR'!$A$3:$A$15)),0) -> 0 | I43: =NETWORKDAYS($E$4,F43,'Festivos CR'!$A$3:$A$15) -> 18 | J43: =H43 -> 0
B44: CRC | C44: Daniel Nazario Casto Vindas-Starlight-CR003 | D44: 1325079.4 | E44: =D44/CONVERSIONES!$C$146 -> 2588.0456 | F44: 45532 | G44: Cancelado | H44: =IF(OR(G44="Sin pagar",G44="Pagar"),_xlfn.SINGLE(NETWORKDAYS($E$4,F44,'Festivos CR'!$A$3:$A$15)),0) -> 0 | I44: =NETWORKDAYS($E$4,F44,'Festivos CR'!$A$3:$A$15) -> 18 | J44: =H44 -> 0
B45: CRC | C45: Priscilla Grace Polson -Aluminati-CR004 | D45: 1410537.3 | E45: =D45/CONVERSIONES!$C$146 -> 2754.9557 | F45: 45532 | G45: Cancelado | H45: =IF(OR(G45="Sin pagar",G45="Pagar"),_xlfn.SINGLE(NETWORKDAYS($E$4,F45,'Festivos CR'!$A$3:$A$15)),0) -> 0 | I45: =NETWORKDAYS($E$4,F45,'Festivos CR'!$A$3:$A$15) -> 18 | J45: =H45 -> 0
B46: CRC | C46: José Roberto Aguilar Barrante-Aluminati-CR004 | D46: 1410537.3 | E46: =D46/CONVERSIONES!$C$146 -> 2754.9557 | F46: 45532 | G46: Cancelado | H46: =IF(OR(G46="Sin pagar",G46="Pagar"),_xlfn.SINGLE(NETWORKDAYS($E$4,F46,'Festivos CR'!$A$3:$A$15)),0) -> 0 | I46: =NETWORKDAYS($E$4,F46,'Festivos CR'!$A$3:$A$15) -> 18 | J46: =H46 -> 0
B47: CRC | C47: Sheryl Gertrudiz Cambronero Estrada-lorez & Prada PPLC | D47: 786551.54 | E47: =D47/CONVERSIONES!$C$146 -> 1536.2335 | F47: 45532 | G47: Cancelado | H47: =IF(OR(G47="Sin pagar",G47="Pagar"),_xlfn.SINGLE(NETWORKDAYS($E$4,F47,'Festivos CR'!$A$3:$A$15)),0) -> 0 | I47: =NETWORKDAYS($E$4,F47,'Festivos CR'!$A$3:$A$15) -> 18 | J47: =H47 -> 0
B48: USD | C48: Tatiana Araya Pochet-CZ-CR006 | D48: =E48*CONVERSIONES!$C$146 -> 3346478.1 | E48: 6536.09 | F48: 45532 | G48: Cancelado | H48: =IF(OR(G48="Sin pagar",G48="Pagar"),_xlfn.SINGLE(NETWORKDAYS($E$4,F48,'Festivos CR'!$A$3:$A$15)),0) -> 0 | I48: =NETWORKDAYS($E$4,F48,'Festivos CR'!$A$3:$A$15) -> 18 | J48: =H48 -> 0
C49: IMPREVISTO | D49: =SUBTOTAL(9,D50:D50) -> 0 | E49: =SUBTOTAL(9,E50:E50) -> 0
D50: 0 | E50: =D50/$D$6 -> 0 | F50: 45503 | G50: Cancelado | H50: =IF(OR(#REF!="Sin pagar",#REF!="Pagar"),_xlfn.SINGLE(NETWORKDAYS($E$4,#REF!,'Festivos CR'!$A$3:$A$15)),0) -> #REF! | I50: =NETWORKDAYS($E$4,#REF!,'Festivos CR'!$A$3:$A$15) -> #REF!
C51: TOTAL EGRESOS | D51: =SUBTOTAL(9,D23:D50) -> 19036893 | E51: =SUBTOTAL(9,E23:E50) -> 37027.342
C53: SALDO | D53: =D18-D51 -> 13501312 | E53: =E18-E51 -> 26236.18
C54: % | D54: =IF($D$18=0,0,D53/$D$18) -> 0.41493721 | E54: =IF($E$18=0,0,E53/$E$18) -> 0.41471261
C58: Fecha Inicial | D58: Fecha Final | E58: Valor VALOR ₡ CRC | F58: Valor VALOR USD
C59: 45505 | D59: 45508 | E59: =SUMIFS($D$22:$D$56,$F$22:$F$56,">="&C59,$F$22:$F$56,"<="&D59,$G$22:$G$56,$D$73) -> 0 | F59: =SUMIFS($E$22:$E$56,$F$22:$F$56,">="&C59,$F$22:$F$56,"<="&D59,$G$22:$G$56,$D$73) -> 0
C60: 45509 | D60: 45515 | E60: =SUMIFS($D$22:$D$56,$F$22:$F$56,">="&C60,$F$22:$F$56,"<="&D60,$G$22:$G$56,$D$73) -> 0 | F60: =SUMIFS($E$22:$E$56,$F$22:$F$56,">="&C60,$F$22:$F$56,"<="&D60,$G$22:$G$56,$D$73) -> 0 | G60: CCSS e impuestos
C61: 45516 | D61: 45522 | E61: =SUMIFS($D$22:$D$56,$F$22:$F$56,">="&C61,$F$22:$F$56,"<="&D61,$G$22:$G$56,$D$73) -> 0 | F61: =SUMIFS($E$22:$E$56,$F$22:$F$56,">="&C61,$F$22:$F$56,"<="&D61,$G$22:$G$56,$D$73) -> 0
C62: 45523 | D62: 45529 | E62: =SUMIFS($D$22:$D$56,$F$22:$F$56,">="&C62,$F$22:$F$56,"<="&D62,$G$22:$G$56,$D$73) -> 0 | F62: =SUMIFS($E$22:$E$56,$F$22:$F$56,">="&C62,$F$22:$F$56,"<="&D62,$G$22:$G$56,$D$73) -> 0
C63: 45530 | D63: 45535 | E63: =SUMIFS($D$22:$D$56,$F$22:$F$56,">="&C63,$F$22:$F$56,"<="&D63,$G$22:$G$56,$D$73) -> 0 | F63: =SUMIFS($E$22:$E$56,$F$22:$F$56,">="&C63,$F$22:$F$56,"<="&D63,$G$22:$G$56,$D$73) -> 0 | G63: Nóminas y gastos admon
C64: TOTAL EGRESOS | E64: =SUM(E59:E63) -> 0 | F64: =SUM(F59:F63) -> 0
C67: Bancos | E67: ='BAC SAN JOSE COLONES '!G236+('BAC SAN JOSE USD'!G203*$D$6) -> 13567483 | F67: =E67/517 -> 26242.714
C68: Gastos y costos Periodo 26 al 30 Agosto | E68: =SUM(E59:E61) -> 0 | F68: =SUM(F59:F61) -> 0
C69: Saldo | E69: =E67-E68 -> 13567483 | F69: =F67-F68 -> 26242.714 | G69: =F69-E53 -> 6.534074
D72: Cancelado | E72: =SUMIFS($D$22:$D$56,$F$22:$F$56,">="&C59,$F$22:$F$56,"<="&$D$63,$G$22:$G$56,$D$72) -> 19036893 | F72: =SUMIFS($E$22:$E$56,$F$22:$F$56,">="&C59,$F$22:$F$56,"<="&D63,$G$22:$G$56,$D$72) -> 37027.342
D73: Sin Pagar | E73: =SUMIFS($D$22:$D$56,$F$22:$F$56,">="&C59,$F$22:$F$56,"<="&$D$63,$G$22:$G$56,$D$73) -> 0 | F73: =SUMIFS($E$22:$E$56,$F$22:$F$56,">="&C59,$F$22:$F$56,"<="&D63,$G$22:$G$56,$D$73) -> 0
D74: Total Egresos | E74: =SUM(E72:E73) -> 19036893 | F74: =SUM(F72:F73) -> 37027.342
D75: Validación | E75: =D51-E74 -> 0 | F75: =F74-E51 -> 0
D78: Flujo Caja | E78: =D53 -> 13501312
D79: Libro Bancos | E79: ='BAC SAN JOSE COLONES '!$G$236+('BAC SAN JOSE USD'!$G$203*CONVERSIONES!$C$146) -> 13501324
D80: Diferencia | E80: =E79-E78 -> 11.988897
E81: =E80/518 -> 0.023144589

Sheet FLUJO CAJA SEPTIEMBRE
D1: 42400
D4: Fecha de Elaboración: | E4: 45536
C6: Tasa de cambio: | D6: 522
D7: SEPTIEMBRE
D8: VALOR ₡ CRC | E8: VALOR USD
C9: BANCOS | D9: =SUBTOTAL(9,D10:D11) -> 13534196 | E9: =SUBTOTAL(9,E10:E11) -> 25927.578
C10: Bancos ₡ CRC | D10: ='BAC SAN JOSE COLONES '!$G$239 -> 7778335.2 | E10: =D10/$D$6 -> 14901.025
C11: Bancos USD | D11: =E11*$D$6 -> 5755860.7 | E11: ='BAC SAN JOSE USD'!G203 -> 11026.553
C12: CLIENTES | D12: =SUBTOTAL(9,D13:D16) -> 20839583 | E12: =SUBTOTAL(9,E13:E16) -> 40543.935
C13: Client: Remorfist-Client-Starlight SS -Factura Nro 147 | D13: =E13*CONVERSIONES!$C$165 -> 9387150.2 | E13: =CONVERSIONES!$C$161+CONVERSIONES!$D$161+CONVERSIONES!$E$161 -> 18262.938
C14: Client: Remorfist-Client: Aluminati-Factura Nro 148 | D14: =E14*CONVERSIONES!$F$165 -> 4484535.9 | E14: =CONVERSIONES!F161+CONVERSIONES!G161 -> 8724.7781
C15: Remorfist - Client: CZ SS-Factura Nro 149 | D15: =$E$15*CONVERSIONES!$H$165 -> 5755641.3 | E15: =CONVERSIONES!H161 -> 11197.746
C16: Remorfist - Client: PLLC- Factura Nro 150 | D16: =$E$16*CONVERSIONES!$I$165 -> 1212255.2 | E16: =CONVERSIONES!$I$161 -> 2358.4732
C17: TOTAL INGRESOS | D17: =SUBTOTAL(9,D9:D16) -> 34373779 | E17: =SUBTOTAL(9,E9:E16) -> 66471.513
B20: CUENTAS X PAGAR MES | D20: AGOSTO
B21: Factura | C21: PROVEEDOR | D21: VALOR ₡ CRC | E21: VALOR USD | F21: Fecha vencimiento | G21: Estado | J21: KPI
C22: SEGURIDAD IGSS | D22: =SUBTOTAL(9,D23:D23) -> 5659227 | E22: =SUBTOTAL(9,E23:E23) -> 10841.431
B23: 202408-3102766975-1 | C23: Pago CCSS Agosto | D23: 5659227 | E23: =D23/$D$6 -> 10841.431 | F23: 45548 | G23: Cancelado | H23: =IF(OR(G23="Sin pagar",G23="Pagar"),_xlfn.SINGLE(NETWORKDAYS($E$4,F23,'Festivos CR'!$A$3:$A$15)),0) -> 0 | I23: =NETWORKDAYS($E$4,F23,'Festivos CR'!$A$3:$A$15) -> 10 | J23: =H23 -> 0
C24: IMPUESTOS | D24: =SUBTOTAL(9,D25:D26) -> 1412173.9 | E24: =SUBTOTAL(9,E25:E26) -> 2705.314 | J24: =H24 -> 0
C25: Retención en la fuente | D25: 1313132.9 | E25: =D25/$D$6 -> 2515.5803 | F25: 45548 | G25: Cancelado | H25: =IF(OR(G25="Sin pagar",G25="Pagar"),_xlfn.SINGLE(NETWORKDAYS($E$4,F25,'Festivos CR'!$A$3:$A$15)),0) -> 0 | I25: =NETWORKDAYS($E$4,F25,'Festivos CR'!$A$3:$A$15) -> 10 | J25: =H25 -> 0
C26: Rte fte por declaración de remesas al exterior Facturación S&P Colombia a S&P CR | D26: 99041 | E26: =D26/$D$6 -> 189.73372 | F26: 45548 | G26: Cancelado | H26: =IF(OR(G26="Sin pagar",G26="Pagar"),_xlfn.SINGLE(NETWORKDAYS($E$4,F26,'Festivos CR'!$A$3:$A$15)),0) -> 0 | I26: =NETWORKDAYS($E$4,F26,'Festivos CR'!$A$3:$A$15) -> 10 | J26: =H26 -> 0
C27: SERVICIOS PROFESIONALES -REPRESENTACIÓN LEGAL | D27: =SUBTOTAL(9,D28:D28) -> 62400 | E27: =SUBTOTAL(9,E28:E28) -> 119.54023 | J27: =H27 -> 0
B28: 19 | C28: Servicios profesionales Alejandro Echavarria Agosto | D28: 62400 | E28: =D28/$D$6 -> 119.54023 | F28: 45561 | G28: Cancelado | H28: =IF(OR(G28="Sin pagar",G28="Pagar"),_xlfn.SINGLE(NETWORKDAYS($E$4,F28,'Festivos CR'!$A$3:$A$15)),0) -> 0 | I28: =NETWORKDAYS($E$4,F28,'Festivos CR'!$A$3:$A$15) -> 19 | J28: =H28 -> 0
C29: GASTOS DE OFICINA | D29: =SUBTOTAL(9,D30:D31) -> 628208 | E29: =SUBTOTAL(9,E30:E31) -> 1203.4636
B30: 58 | C30: Compra de café | D30: 77000 | E30: =D30/$D$6 -> 147.50958 | F30: 45538 | G30: Cancelado | H30: =IF(OR(G30="Sin pagar",G30="Pagar"),_xlfn.SINGLE(NETWORKDAYS($E$4,F30,'Festivos CR'!$A$3:$A$15)),0) -> 0 | I30: =NETWORKDAYS($E$4,F30,'Festivos CR'!$A$3:$A$15) -> 2 | J30: =H30 -> 0
B31: 4024882 | C31: Renovación seguro Riesgo de trabajo del INS | D31: 551208 | E31: =D31/$D$6 -> 1055.954 | F31: 45548 | G31: Cancelado | H31: =IF(OR(G31="Sin pagar",G31="Pagar"),_xlfn.SINGLE(NETWORKDAYS($E$4,F31,'Festivos CR'!$A$3:$A$15)),0) -> 0 | I31: =NETWORKDAYS($E$4,F31,'Festivos CR'!$A$3:$A$15) -> 10 | J31: =H31 -> 0
C32: COBROS ENTRE SUCURSALES | D32: =SUBTOTAL(9,D33:D39) -> 0 | E32: =SUBTOTAL(9,E33:E39) -> 0 | M32: Facturado | N32: Cruzado | O32: 0
B33: 4699 | C33: Cobro S&P a sucursal Enero a marzo | D33: =E33*$D$6 -> 0 | E33: =(228818/3888.02)*$O$32 -> 0 | F33: 45565 | G33: Cancelado | H33: =IF(OR(G33="Sin pagar",G33="Pagar"),_xlfn.SINGLE(NETWORKDAYS($E$4,F33,'Festivos CR'!$A$3:$A$15)),0) -> 0 | I33: =NETWORKDAYS($E$4,F33,'Festivos CR'!$A$3:$A$15) -> 21 | J33: =H33 -> 0 | M33: 880 | N33: =M33-E33 -> 880
B34: 4777 | C34: Cobro S&P a sucursal Abril | D34: =E34*$D$6 -> 0 | E34: =(160718/3924.82)*$O$32 -> 0 | F34: 45565 | G34: Cancelado | H34: =IF(OR(G34="Sin pagar",G34="Pagar"),_xlfn.SINGLE(NETWORKDAYS($E$4,F34,'Festivos CR'!$A$3:$A$15)),0) -> 0 | I34: =NETWORKDAYS($E$4,F34,'Festivos CR'!$A$3:$A$15) -> 21 | J34: =H34 -> 0 | M34: 720 | N34: =M34-E34 -> 720
B35: 4878 | C35: Cobro S&P a sucursal Mayo | D35: =E35*$D$6 -> 0 | E35: =(205400/3829.59)*$O$32 -> 0 | F35: 45565 | G35: Cancelado | H35: =IF(OR(G51="Sin pagar",G51="Pagar"),_xlfn.SINGLE(NETWORKDAYS($E$4,F51,'Festivos CR'!$A$3:$A$15)),0) -> 0 | I35: =NETWORKDAYS($E$4,F51,'Festivos CR'!$A$3:$A$15) -> 21 | J35: =H35 -> 0 | M35: 645 | N35: =M35-E35 -> 645
B36: 4957 | C36: Cobro S&P a sucursal Junio | D36: =E36*$D$6 -> 0 | E36: 0 | F36: 45565 | G36: Cancelado | H36: =IF(OR(G52="Sin pagar",G52="Pagar"),_xlfn.SINGLE(NETWORKDAYS($E$4,F52,'Festivos CR'!$A$3:$A$15)),0) -> 0 | I36: =NETWORKDAYS($E$4,F52,'Festivos CR'!$A$3:$A$15) -> -32517 | J36: =H36 -> 0 | M36: 330 | N36: 330
B37: 4957 | C37: Cobro S&P a sucursal Julio | D37: =E37*$D$6 -> 0 | E37: =515*$O$32 -> 0 | F37: 45565 | G37: Cancelado | H37: =IF(OR(G53="Sin pagar",G53="Pagar"),_xlfn.SINGLE(NETWORKDAYS($E$4,F53,'Festivos CR'!$A$3:$A$15)),0) -> 0 | I37: =NETWORKDAYS($E$4,F53,'Festivos CR'!$A$3:$A$15) -> -32517 | J37: =H37 -> 0 | M37: 550 | N37: 0
B38: 5160 | C38: Cobro S&P a sucursal Agosto | D38: =E38*$D$6 -> 0 | E38: =755*0 -> 0 | F38: 45565 | G38: Cancelado | H38: =IF(OR(G54="Sin pagar",G54="Pagar"),_xlfn.SINGLE(NETWORKDAYS($E$4,F54,'Festivos CR'!$A$3:$A$15)),0) -> 0 | I38: =NETWORKDAYS($E$4,F54,'Festivos CR'!$A$3:$A$15) -> -32517 | J38: =H38 -> 0 | M38: 550 | N38: 0
B39: 5283 | C39: Cobro S&P a sucursal Agosto | D39: =E39*$D$6 -> 0 | E39: =515*0 -> 0 | F39: 45565 | G39: Cancelado | H39: =IF(OR(G55="Sin pagar",G55="Pagar"),_xlfn.SINGLE(NETWORKDAYS($E$4,F55,'Festivos CR'!$A$3:$A$15)),0) -> 0 | I39: =NETWORKDAYS($E$4,F55,'Festivos CR'!$A$3:$A$15) -> -32517 | J39: =H39 -> 0 | M39: 550 | N39: 0
C40: COSTOS FINANCIEROS | D40: =SUBTOTAL(9,D41:D41) -> 11279.25 | E40: =SUBTOTAL(9,E41:E41) -> 21.607759 | M40: =SUM(M33:M37) -> 3125 | N40: =SUM(N33:N37) -> 2575 | O40: Saldo | P40: =M40-N40 -> 550
C41: COSTOS FINANCIEROS | D41: =(('BAC SAN JOSE COLONES '!$F$239+'BAC SAN JOSE COLONES '!$F$244)+(CONVERSIONES!$J$160*CONVERSIONES!$H$155))-9909 -> 11279.25 | E41: =D41/D6 -> 21.607759 | F41: 45565 | G41: Cancelado | H41: =IF(OR(G41="Sin pagar",G41="Pagar"),_xlfn.SINGLE(NETWORKDAYS($E$4,F41,'Festivos CR'!$A$3:$A$15)),0) -> 0 | I41: =NETWORKDAYS($E$4,F41,'Festivos CR'!$A$3:$A$15) -> 21 | J41: =H41 -> 0
C42: NÓMINAS | D42: =SUBTOTAL(9,D43:D49) -> 12697662 | E42: =SUBTOTAL(9,E43:E49) -> 14538.95
B43: CRC | C43: Jhoel González González-Starlight-CR003 | D43: 1612916.3 | E43: =CONVERSIONES!$C$165 -> 514 | F43: 45562 | G43: Cancelado | H43: =IF(OR(G43="Sin pagar",G43="Pagar"),_xlfn.SINGLE(NETWORKDAYS($E$4,F43,'Festivos CR'!$A$3:$A$15)),0) -> 0 | I43: =NETWORKDAYS($E$4,F43,'Festivos CR'!$A$3:$A$15) -> 20 | J43: =H43 -> 0
B44: USD | C44: Jonathan Salazar García -Starlight-CR003 | D44: =E44*CONVERSIONES!$C$165 -> 2790315.8 | E44: 5428.63 | F44: 45562 | G44: Cancelado | H44: =IF(OR(G44="Sin pagar",G44="Pagar"),_xlfn.SINGLE(NETWORKDAYS($E$4,F44,'Festivos CR'!$A$3:$A$15)),0) -> 0 | I44: =NETWORKDAYS($E$4,F44,'Festivos CR'!$A$3:$A$15) -> 20 | J44: =H44 -> 0
B45: CRC | C45: Daniel Nazario Casto Vindas-Starlight-CR003 | D45: 1325079.4 | E45: =CONVERSIONES!$C$165 -> 514 | F45: 45562 | G45: Cancelado | H45: =IF(OR(G45="Sin pagar",G45="Pagar"),_xlfn.SINGLE(NETWORKDAYS($E$4,F45,'Festivos CR'!$A$3:$A$15)),0) -> 0 | I45: =NETWORKDAYS($E$4,F45,'Festivos CR'!$A$3:$A$15) -> 20 | J45: =H45 -> 0
B46: CRC | C46: Priscilla Grace Polson -Aluminati-CR004 | D46: 1410537.3 | E46: =CONVERSIONES!$C$165 -> 514 | F46: 45562 | G46: Cancelado | H46: =IF(OR(G46="Sin pagar",G46="Pagar"),_xlfn.SINGLE(NETWORKDAYS($E$4,F46,'Festivos CR'!$A$3:$A$15)),0) -> 0 | I46: =NETWORKDAYS($E$4,F46,'Festivos CR'!$A$3:$A$15) -> 20 | J46: =H46 -> 0
B47: CRC | C47: José Roberto Aguilar Barrante-Aluminati-CR004 | D47: 1410537.3 | E47: =CONVERSIONES!$C$165 -> 514 | F47: 45562 | G47: Cancelado | H47: =IF(OR(G47="Sin pagar",G47="Pagar"),_xlfn.SINGLE(NETWORKDAYS($E$4,F47,'Festivos CR'!$A$3:$A$15)),0) -> 0 | I47: =NETWORKDAYS($E$4,F47,'Festivos CR'!$A$3:$A$15) -> 20 | J47: =H47 -> 0
B48: CRC | C48: Sheryl Gertrudiz Cambronero Estrada-lorez & Prada PPLC | D48: 786551.54 | E48: =CONVERSIONES!$C$165 -> 514 | F48: 45562 | G48: Cancelado | H48: =IF(OR(G48="Sin pagar",G48="Pagar"),_xlfn.SINGLE(NETWORKDAYS($E$4,F48,'Festivos CR'!$A$3:$A$15)),0) -> 0 | I48: =NETWORKDAYS($E$4,F48,'Festivos CR'!$A$3:$A$15) -> 20 | J48: =H48 -> 0
B49: USD | C49: Tatiana Araya Pochet-CZ-CR006 | D49: =E49*CONVERSIONES!$C$165 -> 3361724.5 | E49: 6540.32 | F49: 45562 | G49: Cancelado | H49: =IF(OR(G49="Sin pagar",G49="Pagar"),_xlfn.SINGLE(NETWORKDAYS($E$4,F49,'Festivos CR'!$A$3:$A$15)),0) -> 0 | I49: =NETWORKDAYS($E$4,F49,'Festivos CR'!$A$3:$A$15) -> 20 | J49: =H49 -> 0
C50: IMPREVISTO | D50: =SUBTOTAL(9,D51:D51) -> 0 | E50: =SUBTOTAL(9,E51:E51) -> 0
D51: 0 | E51: =D51/$D$6 -> 0 | F51: 45565 | G51: Cancelado | H51: =IF(OR(#REF!="Sin pagar",#REF!="Pagar"),_xlfn.SINGLE(NETWORKDAYS($E$4,#REF!,'Festivos CR'!$A$3:$A$15)),0) -> #REF! | I51: =NETWORKDAYS($E$4,#REF!,'Festivos CR'!$A$3:$A$15) -> #REF!
C52: TOTAL EGRESOS | D52: =SUBTOTAL(9,D22:D51) -> 20470950 | E52: =SUBTOTAL(9,E22:E51) -> 29430.307
C54: SALDO | D54: =D17-D52 -> 13902828 | E54: =E17-E52 -> 37041.207
C55: % | D55: =IF($D$17=0,0,D54/$D$17) -> 0.40446028 | E55: =IF($E$17=0,0,E54/$E$17) -> 0.55724934
C59: Fecha Inicial | D59: Fecha Final | E59: Valor VALOR ₡ CRC | F59: Valor VALOR USD
C60: 45537 | D60: 45543 | E60: =SUMIFS($D$21:$D$57,$F$21:$F$57,">="&C60,$F$21:$F$57,"<="&D60,$G$21:$G$57,$D$73) -> 0 | F60: =SUMIFS($E$21:$E$57,$F$21:$F$57,">="&C60,$F$21:$F$57,"<="&D60,$G$21:$G$57,$D$73) -> 0
C61: 45544 | D61: 45550 | E61: =SUMIFS($D$21:$D$57,$F$21:$F$57,">="&C61,$F$21:$F$57,"<="&D61,$G$21:$G$57,$D$73) -> 0 | F61: =SUMIFS($E$21:$E$57,$F$21:$F$57,">="&C61,$F$21:$F$57,"<="&D61,$G$21:$G$57,$D$73) -> 0 | G61: CCSS e impuestos y renovación póliza Riesgo de trabajo
C62: 45551 | D62: 45557 | E62: =SUMIFS($D$21:$D$57,$F$21:$F$57,">="&C62,$F$21:$F$57,"<="&D62,$G$21:$G$57,$D$73) -> 0 | F62: =SUMIFS($E$21:$E$57,$F$21:$F$57,">="&C62,$F$21:$F$57,"<="&D62,$G$21:$G$57,$D$73) -> 0
C63: 45558 | D63: 45565 | E63: =SUMIFS($D$21:$D$57,$F$21:$F$57,">="&C63,$F$21:$F$57,"<="&D63,$G$21:$G$57,$D$73) -> 0 | F63: =SUMIFS($E$21:$E$57,$F$21:$F$57,">="&C63,$F$21:$F$57,"<="&D63,$G$21:$G$57,$D$73) -> 0 | G63: Nóminas y gastos admon
C64: TOTAL EGRESOS | E64: =SUM(E60:E63) -> 0 | F64: =SUM(F60:F63) -> 0
C67: Bancos | E67: ='BAC SAN JOSE COLONES '!$G$250+(('BAC SAN JOSE USD'!G203*526)) -> 15359898 | F67: =E67/526 -> 29201.328
C68: Gastos y costos Periodo 02 al 22 Septiembre | E68: =SUM(E60:E62) -> 0 | F68: =SUM(F60:F62) -> 0
C69: Saldo | E69: =E67-E68 -> 15359898 | F69: =F67-F68 -> 29201.328
D72: Cancelado | E72: =SUMIFS($D$21:$D$57,$F$21:$F$57,">="&C60,$F$21:$F$57,"<="&D63,$G$21:$G$57,$D$72) -> 20470950 | F72: =SUMIFS($E$21:$E$57,$F$21:$F$57,">="&C60,$F$21:$F$57,"<="&$D$63,$G$21:$G$57,$D$72) -> 29430.307
D73: Sin Pagar | E73: =SUMIFS($D$21:$D$57,$F$21:$F$57,">="&C60,$F$21:$F$57,"<="&D63,$G$21:$G$57,$D$73) -> 0 | F73: =SUMIFS($E$21:$E$57,$F$21:$F$57,">="&$C$60,$F$21:$F$57,"<="&$D$63,$G$21:$G$57,$D$73) -> 0
D74: Total Egresos | E74: =SUM(E72:E73) -> 20470950 | F74: =SUM(F72:F73) -> 29430.307
D75: Validación | E75: =D52-E74 -> 0 | F75: =F74-E52 -> 0
D78: Flujo Caja | E78: =D54 -> 13902828
D79: Libro Bancos | E79: ='BAC SAN JOSE COLONES '!$G$253+('BAC SAN JOSE USD'!$G$210*CONVERSIONES!$C$165) -> 13902829
D80: Diferencia | E80: =E78-E79 -> -0.48592998 | F80: =E80/514 -> -0.00094538906

Sheet FLUJO CAJA OCTUBRE 
D1: 42400
D4: Fecha de Elaboración: | E4: 45601
C6: Tasa de cambio: | D6: 511
D7: OCTUBRE
D8: VALOR ₡ CRC | E8: VALOR USD
C9: BANCOS | D9: =SUBTOTAL(9,D10:D11) -> 13869749 | E9: =SUBTOTAL(9,E10:E12) -> 32689.246
C10: Bancos ₡ CRC | D10: ='BAC SAN JOSE COLONES '!$G$253 -> 8235183 | E10: =D10/$D$6 -> 16115.818
C11: Bancos USD | D11: =E11*$D$6 -> 5634566.1 | E11: ='BAC SAN JOSE USD'!G210 -> 11026.548
C12: Ingreso | D12: =E12*$D$6 -> 2834455.6 | E12: 5546.8799
C13: CLIENTES | D13: =SUBTOTAL(9,D14:D18) -> 21438410 | E13: =SUBTOTAL(9,E14:E18) -> 42368.399
B14: Pagado | C14: Client: Remorfist-Client-Starlight SS -Factura Nro 151 | D14: =E14*CONVERSIONES!$C$183 -> 7392526.7 | E14: =CONVERSIONES!$C$179+CONVERSIONES!$D$179+CONVERSIONES!$E$179 -> 14609.737
B15: Pagado | C15: Client: Remorfist-Client: Aluminati-Factura Nro 152 | D15: =E15*CONVERSIONES!$C$183 -> 4423104.3 | E15: =CONVERSIONES!$F$179+CONVERSIONES!$G$179 -> 8741.3129
B16: Pagado | C16: Remorfist - Client: CZ SS-Factura Nro 153 | D16: =E16*CONVERSIONES!$C$183 -> 5666059.3 | E16: =CONVERSIONES!$H$179 -> 11197.746
B17: Pagado | C17: Remorfist - Client: PLLC- Factura Nro 154 | D17: =E17*CONVERSIONES!$C$183 -> 1195578.6 | E17: =CONVERSIONES!$I$179 -> 2362.8037
B18: Pagado | C18: Advancio - Client: PLLC- Factura Nro 155 | D18: =E18*CONVERSIONES!$J$183 -> 2761140.8 | E18: =CONVERSIONES!$J$179 -> 5456.8
C19: TOTAL INGRESOS | D19: =SUBTOTAL(9,D9:D17) -> 35381474 | E19: =SUBTOTAL(9,E9:E17) -> 69600.845
B22: CUENTAS X PAGAR MES | D22: AGOSTO
B23: Factura | C23: PROVEEDOR | D23: VALOR ₡ CRC | E23: VALOR USD | F23: Fecha vencimiento | G23: Estado | J23: KPI
C24: SEGURIDAD IGSS | D24: =SUBTOTAL(9,D25:D25) -> 5909923 | E24: =SUBTOTAL(9,E25:E25) -> 11565.407
B25: 202408-3102766975-1 | C25: Pago CCSS Agosto | D25: 5909923 | E25: =D25/$D$6 -> 11565.407 | F25: 45579 | G25: Cancelado | H25: =IF(OR(G25="Sin pagar",G25="Pagar"),_xlfn.SINGLE(NETWORKDAYS($E$4,F25,'Festivos CR'!$A$3:$A$15)),0) -> 0 | I25: =NETWORKDAYS($E$4,F25,'Festivos CR'!$A$3:$A$15) -> -17 | J25: =H25 -> 0
C26: IMPUESTOS | D26: =SUBTOTAL(9,D27:D28) -> 1508002 | E26: =SUBTOTAL(9,E27:E28) -> 2951.0802 | F26: , | J26: =H26 -> 0
C27: Retención en la fuente | D27: 1440883 | E27: =D27/$D$6 -> 2819.7319 | F27: 45579 | G27: Cancelado | H27: =IF(OR(G27="Sin pagar",G27="Pagar"),_xlfn.SINGLE(NETWORKDAYS($E$4,F27,'Festivos CR'!$A$3:$A$15)),0) -> 0 | I27: =NETWORKDAYS($E$4,F27,'Festivos CR'!$A$3:$A$15) -> -17 | J27: =H27 -> 0
C28: Rte fte por declaración de remesas al exterior Facturación S&P Colombia a S&P CR | D28: 67119 | E28: =D28/$D$6 -> 131.34834 | F28: 45579 | G28: Cancelado | H28: =IF(OR(G28="Sin pagar",G28="Pagar"),_xlfn.SINGLE(NETWORKDAYS($E$4,F28,'Festivos CR'!$A$3:$A$15)),0) -> 0 | I28: =NETWORKDAYS($E$4,F28,'Festivos CR'!$A$3:$A$15) -> -17 | J28: =H28 -> 0
C29: SERVICIOS PROFESIONALES -REPRESENTACIÓN LEGAL | D29: =SUBTOTAL(9,D30:D30) -> 62400 | E29: =SUBTOTAL(9,E30:E30) -> 122.1135 | J29: =H29 -> 0
B30: 20 | C30: Servicios profesionales Alejandro Echavarria Octubre | D30: 62400 | E30: =D30/$D$6 -> 122.1135 | F30: 45590 | G30: Cancelado | H30: =IF(OR(G30="Sin pagar",G30="Pagar"),_xlfn.SINGLE(NETWORKDAYS($E$4,F30,'Festivos CR'!$A$3:$A$15)),0) -> 0 | I30: =NETWORKDAYS($E$4,F30,'Festivos CR'!$A$3:$A$15) -> -8 | J30: =H30 -> 0
C31: GASTOS DE OFICINA | D31: =SUBTOTAL(9,D32:D32) -> 77000 | E31: =SUBTOTAL(9,E32:E32) -> 150.68493
B32: 58 | C32: Compra de café | D32: 77000 | E32: =D32/$D$6 -> 150.68493 | F32: 45567 | G32: Cancelado | H32: =IF(OR(G32="Sin pagar",G32="Pagar"),_xlfn.SINGLE(NETWORKDAYS($E$4,F32,'Festivos CR'!$A$3:$A$15)),0) -> 0 | I32: =NETWORKDAYS($E$4,F32,'Festivos CR'!$A$3:$A$15) -> -25 | J32: =H32 -> 0
C33: COBROS ENTRE SUCURSALES | D33: =SUBTOTAL(9,D34:D36) -> 0 | E33: =SUBTOTAL(9,E34:E36) -> 0
B34: 5059 | C34: Cobro S&P a sucursal Julio | D34: =E34*$D$6 -> 0 | E34: =515*0 -> 0 | F34: 45596 | G34: Sin Pagar | H34: =IF(OR(G34="Sin pagar",G34="Pagar"),_xlfn.SINGLE(NETWORKDAYS($E$4,F34,'Festivos CR'!$A$3:$A$15)),0) -> -4 | I34: =NETWORKDAYS($E$4,F34,'Festivos CR'!$A$3:$A$15) -> -4 | J34: =H34 -> -4
B35: 5160 | C35: Cobro S&P a sucursal Agosto | D35: =E35*$D$6 -> 0 | E35: =755*0 -> 0 | F35: 45596 | G35: Sin Pagar | H35: =IF(OR(G35="Sin pagar",G35="Pagar"),_xlfn.SINGLE(NETWORKDAYS($E$4,F35,'Festivos CR'!$A$3:$A$15)),0) -> -4 | I35: =NETWORKDAYS($E$4,F35,'Festivos CR'!$A$3:$A$15) -> -4 | J35: =H35 -> -4
B36: 5283 | C36: Cobro S&P a sucursal Septiembre | D36: =E36*$D$6 -> 0 | E36: =515*0 -> 0 | F36: 45596 | G36: Sin Pagar | H36: =IF(OR(G36="Sin pagar",G36="Pagar"),_xlfn.SINGLE(NETWORKDAYS($E$4,F36,'Festivos CR'!$A$3:$A$15)),0) -> -4 | I36: =NETWORKDAYS($E$4,F36,'Festivos CR'!$A$3:$A$15) -> -4 | J36: =H36 -> -4
C37: COSTOS FINANCIEROS | D37: =SUBTOTAL(9,D38:D38) -> 172870 | E37: =SUBTOTAL(9,E38:E38) -> 77.054795
C38: COSTOS FINANCIEROS | D38: =39375+133495 -> 172870 | E38: =39375/D6 -> 77.054795 | F38: 45595 | G38: Cancelado | H38: =IF(OR(G38="Sin pagar",G38="Pagar"),_xlfn.SINGLE(NETWORKDAYS($E$4,F38,'Festivos CR'!$A$3:$A$15)),0) -> 0 | I38: =NETWORKDAYS($E$4,F38,'Festivos CR'!$A$3:$A$15) -> -5 | J38: =H38 -> 0
C39: NÓMINAS | D39: =SUBTOTAL(9,D40:D47) -> 13203900 | E39: =SUBTOTAL(9,E40:E47) -> 26182.392
B40: CRC | C40: Jhoel González González-Starlight-CR003 | D40: 1612916.3 | E40: =D40/CONVERSIONES!$C$183 -> 3187.5817 | F40: 45593 | G40: Cancelado | H40: =IF(OR(G40="Sin pagar",G40="Pagar"),_xlfn.SINGLE(NETWORKDAYS($E$4,F40,'Festivos CR'!$A$3:$A$15)),0) -> 0 | I40: =NETWORKDAYS($E$4,F40,'Festivos CR'!$A$3:$A$15) -> -7 | J40: =H40 -> 0
B41: USD | C41: Jonathan Salazar García -Starlight-CR003 | D41: =$E$41*CONVERSIONES!$C$83 -> 1683392.9 | E41: 3414.59 | F41: 45593 | G41: Cancelado | H41: =IF(OR(G41="Sin pagar",G41="Pagar"),_xlfn.SINGLE(NETWORKDAYS($E$4,F41,'Festivos CR'!$A$3:$A$15)),0) -> 0 | I41: =NETWORKDAYS($E$4,F41,'Festivos CR'!$A$3:$A$15) -> -7 | J41: =H41 -> 0
B42: CRC | C42: Daniel Nazario Casto Vindas-Starlight-CR003 | D42: 1325079.4 | E42: =D42/CONVERSIONES!$C$183 -> 2618.7339 | F42: 45593 | G42: Cancelado | H42: =IF(OR(G42="Sin pagar",G42="Pagar"),_xlfn.SINGLE(NETWORKDAYS($E$4,F42,'Festivos CR'!$A$3:$A$15)),0) -> 0 | I42: =NETWORKDAYS($E$4,F42,'Festivos CR'!$A$3:$A$15) -> -7 | J42: =H42 -> 0
B43: CRC | C43: Priscilla Grace Polson -Aluminati-CR004 | D43: 1410537.3 | E43: =$D$43/CONVERSIONES!$C$183 -> 2787.6231 | F43: 45593 | G43: Cancelado | H43: =IF(OR(G43="Sin pagar",G43="Pagar"),_xlfn.SINGLE(NETWORKDAYS($E$4,F43,'Festivos CR'!$A$3:$A$15)),0) -> 0 | I43: =NETWORKDAYS($E$4,F43,'Festivos CR'!$A$3:$A$15) -> -7 | J43: =H43 -> 0
B44: CRC | C44: José Roberto Aguilar Barrante-Aluminati-CR004 | D44: 1410537.3 | E44: =$D$44/CONVERSIONES!$C$183 -> 2787.6231 | F44: 45593 | G44: Cancelado | H44: =IF(OR(G44="Sin pagar",G44="Pagar"),_xlfn.SINGLE(NETWORKDAYS($E$4,F44,'Festivos CR'!$A$3:$A$15)),0) -> 0 | I44: =NETWORKDAYS($E$4,F44,'Festivos CR'!$A$3:$A$15) -> -7 | J44: =H44 -> 0
B45: CRC | C45: Sheryl Gertrudiz Cambronero Estrada-lorez & Prada PPLC | D45: 786551.54 | E45: =$D$45/CONVERSIONES!$C$183 -> 1554.4497 | F45: 45593 | G45: Cancelado | H45: =IF(OR(G45="Sin pagar",G45="Pagar"),_xlfn.SINGLE(NETWORKDAYS($E$4,F45,'Festivos CR'!$A$3:$A$15)),0) -> 0 | I45: =NETWORKDAYS($E$4,F45,'Festivos CR'!$A$3:$A$15) -> -7 | J45: =H45 -> 0
B46: USD | C46: Tatiana Araya Pochet-CZ-CR006 | D46: =$E$46*CONVERSIONES!$C$183 -> 3311496.8 | E46: 6544.46 | F46: 45593 | G46: Cancelado | H46: =IF(OR(G46="Sin pagar",G46="Pagar"),_xlfn.SINGLE(NETWORKDAYS($E$4,F46,'Festivos CR'!$A$3:$A$15)),0) -> 0 | I46: =NETWORKDAYS($E$4,F46,'Festivos CR'!$A$3:$A$15) -> -7 | J46: =H46 -> 0
B47: USD | C47: José Alvardo -Advanció | D47: =$E$47*CONVERSIONES!$C$183 -> 1663389 | E47: =CONVERSIONES!J180 -> 3287.33
C48: IMPREVISTO | D48: =SUBTOTAL(9,D49:D49) -> 0 | E48: =SUBTOTAL(9,E49:E49) -> 0
D49: 0 | E49: =D49/$D$6 -> 0 | F49: 45565 | G49: Cancelado | H49: =IF(OR(#REF!="Sin pagar",#REF!="Pagar"),_xlfn.SINGLE(NETWORKDAYS($E$4,#REF!,'Festivos CR'!$A$3:$A$15)),0) -> #REF! | I49: =NETWORKDAYS($E$4,#REF!,'Festivos CR'!$A$3:$A$15) -> #REF!
C50: TOTAL EGRESOS | D50: =SUBTOTAL(9,D24:D49) -> 20934095 | E50: =SUBTOTAL(9,E24:E49) -> 41048.732
C52: SALDO | D52: =D19-D50 -> 14447378 | E52: =E19-E50 -> 28552.113
C53: % | D53: =IF($D$19=0,0,D52/$D$19) -> 0.40833173 | E53: =IF($E$19=0,0,E52/$E$19) -> 0.41022653
C57: Fecha Inicial | D57: Fecha Final | E57: Valor VALOR ₡ CRC | F57: Valor VALOR USD
C58: 45566 | D58: 45571 | E58: =SUMIFS($D$23:$D$55,$F$23:$F$55,">="&C58,$F$23:$F$55,"<="&D58,$G$23:$G$55,#REF!) -> 0 | F58: =SUMIFS($E$23:$E$55,$F$23:$F$55,">="&C58,$F$23:$F$55,"<="&D58,$G$23:$G$55,#REF!) -> 0 | G58: Compra Café
C59: 45572 | D59: 45578 | E59: =SUMIFS($D$23:$D$55,$F$23:$F$55,">="&C59,$F$23:$F$55,"<="&D59,$G$23:$G$55,#REF!) -> 0 | F59: =SUMIFS($E$23:$E$55,$F$23:$F$55,">="&C59,$F$23:$F$55,"<="&D59,$G$23:$G$55,#REF!) -> 0
C60: 45579 | D60: 45585 | E60: =SUMIFS($D$23:$D$55,$F$23:$F$55,">="&C60,$F$23:$F$55,"<="&D60,$G$23:$G$55,#REF!) -> 0 | F60: =SUMIFS($E$23:$E$55,$F$23:$F$55,">="&C60,$F$23:$F$55,"<="&D60,$G$23:$G$55,#REF!) -> 0 | G60: CCSS e impuestos y renovación póliza Riesgo de trabajo
C61: 45586 | D61: 45592 | E61: =SUMIFS($D$23:$D$55,$F$23:$F$55,">="&C61,$F$23:$F$55,"<="&D61,$G$23:$G$55,#REF!) -> 0 | F61: =SUMIFS($E$23:$E$55,$F$23:$F$55,">="&C61,$F$23:$F$55,"<="&D61,$G$23:$G$55,#REF!) -> 0 | G61: Servicios Profesionales Alejandro y Divisas
C62: 45593 | D62: 46691 | E62: =SUMIFS($D$23:$D$55,$F$23:$F$55,">="&C62,$F$23:$F$55,"<="&D62,$G$23:$G$55,#REF!) -> 0 | F62: =SUMIFS($E$23:$E$55,$F$23:$F$55,">="&C62,$F$23:$F$55,"<="&D62,$G$23:$G$55,#REF!) -> 0 | G62: Nóminas y gastos admon
C63: TOTAL EGRESOS | E63: =SUM(E58:E62) -> 0 | F63: =SUM(F58:F62) -> 0
C66: Bancos | E66: ='BAC SAN JOSE COLONES '!$G$269+('BAC SAN JOSE USD'!$G$221*CONVERSIONES!$C$183) -> 14447369 | F66: =E66/CONVERSIONES!$C$183 -> 28552.113
C67: Gastos y costos Periodo 01 al 31 Octubre | E67: =SUM(E58:E61) -> 0 | F67: =SUM(F58:F61) -> 0
C68: Saldo | E68: =E66-E67 -> 14447369 | F68: =F66-F67 -> 28552.113 | J68: =F68-E52 -> 0
E70: Flujo Caja | F70: =D52 -> 14447378
E71: Libro Bancos | F71: =('BAC SAN JOSE USD'!$G$221*CONVERSIONES!$C$183)+'BAC SAN JOSE COLONES '!$G$269 -> 14447369
E72: Diferencia | F72: =F70-F71 -> 9.197237

Sheet FLUJO CAJA NOVIEMBRE
D1: 42400
D4: Fecha de Elaboración: | E4: 45598
C6: Tasa de cambio: | D6: 506
D7: NOVIEMBRE
D8: VALOR ₡ CRC | E8: VALOR USD
C9: BANCOS | D9: =SUBTOTAL(9,D10:D11) -> 14369981 | E9: =SUBTOTAL(9,E10:E11) -> 28399.173
C10: Bancos ₡ CRC | D10: ='BAC SAN JOSE COLONES '!$G$269-'BAC SAN JOSE COLONES '!$F$271-'BAC SAN JOSE COLONES '!$F$272 -> 8722237.9 | E10: =D10/$D$6 -> 17237.624
C11: Bancos USD | D11: =E11*$D$6 -> 5647743.4 | E11: ='BAC SAN JOSE USD'!$G$221 -> 11161.548
C12: CLIENTES | D12: =SUBTOTAL(9,D13:D17) -> 20430754 | E12: =SUBTOTAL(9,E13:E17) -> 37183.073
B13: Pagado | C13: Client: Remorfist-Client-Starlight SS -Factura Nro 156 | D13: =E13*CONVERSIONES!$C$191 -> 4647993.2 | E13: =CONVERSIONES!$C$197+CONVERSIONES!$D$197 -> 9258.9505
B14: Pagado | C14: Client: Remorfist-Client: Aluminati-Factura Nro 157 | D14: =E14*CONVERSIONES!$F$191 -> 7195053.9 | E14: =CONVERSIONES!$E$197+CONVERSIONES!$F$197+CONVERSIONES!$G$197 -> 14332.777
B15: Pagado | C15: Remorfist - Client: CZ SS-Factura Nro 158 | D15: =E15*CONVERSIONES!$H$191 -> 5621268.3 | E15: =CONVERSIONES!$H$197 -> 11197.746
B16: Pagado | C16: Remorfist - Client: PLLC- Factura Nro 159 | D16: =$E$16*CONVERSIONES!$I$191 -> 1201587.1 | E16: =CONVERSIONES!$I$197 -> 2393.5997
B17: Sin Pagar | C17: Advancio - Client: PLLC- Factura Nro 160 | D17: 1764852 | E17: =CONVERSIONES!$J$193*0 -> 0
C18: TOTAL INGRESOS | D18: =SUBTOTAL(9,D9:D17) -> 34800736 | E18: =SUBTOTAL(9,E9:E17) -> 65582.245
B21: CUENTAS X PAGAR MES | D21: NOVIEMBRE
B22: Factura | C22: PROVEEDOR | D22: VALOR ₡ CRC | E22: VALOR USD | F22: Fecha vencimiento | G22: Estado | J22: KPI
C23: SEGURIDAD IGSS | D23: =SUBTOTAL(9,D24:D24) -> 6075608 | E23: =SUBTOTAL(9,E24:E24) -> 12007.13
B24: 777720241042561160-1 | C24: Pago CCSS Octubre | D24: 6075608 | E24: =D24/$D$6 -> 12007.13 | F24: 45608 | G24: Cancelado | H24: =IF(OR(G24="Sin pagar",G24="Pagar"),_xlfn.SINGLE(NETWORKDAYS($E$4,F24,'Festivos CR'!$A$3:$A$15)),0) -> 0 | I24: =NETWORKDAYS($E$4,F24,'Festivos CR'!$A$3:$A$15) -> 7 | J24: =H24 -> 0
C25: IMPUESTOS | D25: =SUBTOTAL(9,D26:D27) -> 1343624 | E25: =SUBTOTAL(9,E26:E27) -> 2655.3834 | F25: , | J25: =H25 -> 0
C26: Retención en la fuente | D26: 1286621 | E26: =D26/$D$6 -> 2542.7292 | F26: 45608 | G26: Cancelado | H26: =IF(OR(G26="Sin pagar",G26="Pagar"),_xlfn.SINGLE(NETWORKDAYS($E$4,F26,'Festivos CR'!$A$3:$A$15)),0) -> 0 | I26: =NETWORKDAYS($E$4,F26,'Festivos CR'!$A$3:$A$15) -> 7 | J26: =H26 -> 0
C27: Rte fte por declaración de remesas al exterior Facturación S&P Colombia a S&P CR | D27: 57003 | E27: =D27/$D$6 -> 112.65415 | F27: 45608 | G27: Cancelado | H27: =IF(OR(G27="Sin pagar",G27="Pagar"),_xlfn.SINGLE(NETWORKDAYS($E$4,F27,'Festivos CR'!$A$3:$A$15)),0) -> 0 | I27: =NETWORKDAYS($E$4,F27,'Festivos CR'!$A$3:$A$15) -> 7 | J27: =H27 -> 0
C28: SERVICIOS PROFESIONALES -REPRESENTACIÓN LEGAL | D28: =SUBTOTAL(9,D29:D29) -> 62400 | E28: =SUBTOTAL(9,E29:E29) -> 123.32016 | J28: =H28 -> 0
B29: 21 | C29: Servicios profesionales Alejandro Echavarria Noviembrew | D29: 62400 | E29: =D29/$D$6 -> 123.32016 | F29: 45611 | G29: Cancelado | H29: =IF(OR(G29="Sin pagar",G29="Pagar"),_xlfn.SINGLE(NETWORKDAYS($E$4,F29,'Festivos CR'!$A$3:$A$15)),0) -> 0 | I29: =NETWORKDAYS($E$4,F29,'Festivos CR'!$A$3:$A$15) -> 10 | J29: =H29 -> 0
C30: GASTOS DE OFICINA | D30: =SUBTOTAL(9,D31:D31) -> 77000 | E30: =SUBTOTAL(9,E31:E31) -> 152.17391
B31: 61 | C31: Compra de café | D31: 77000 | E31: =D31/$D$6 -> 152.17391 | F31: 45601 | G31: Cancelado | H31: =IF(OR(G31="Sin pagar",G31="Pagar"),_xlfn.SINGLE(NETWORKDAYS($E$4,F31,'Festivos CR'!$A$3:$A$15)),0) -> 0 | I31: =NETWORKDAYS($E$4,F31,'Festivos CR'!$A$3:$A$15) -> 2 | J31: =H31 -> 0
C32: COBROS ENTRE SUCURSALES | D32: =SUBTOTAL(9,D33:D35) -> 903210 | E32: =SUBTOTAL(9,E33:E36) -> 2225
B33: 5059 | C33: Cobro S&P a sucursal Julio | D33: =E33*$D$6 -> 260590 | E33: =515 -> 515 | F33: 45603 | G33: Cancelado | H33: =IF(OR(G33="Sin pagar",G33="Pagar"),_xlfn.SINGLE(NETWORKDAYS($E$4,F33,'Festivos CR'!$A$3:$A$15)),0) -> 0 | I33: =NETWORKDAYS($E$4,F33,'Festivos CR'!$A$3:$A$15) -> 4 | J33: =H33 -> 0
B34: 5160 | C34: Cobro S&P a sucursal Agosto | D34: =E34*$D$6 -> 382030 | E34: =755 -> 755 | F34: 45603 | G34: Cancelado | H34: =IF(OR(G34="Sin pagar",G34="Pagar"),_xlfn.SINGLE(NETWORKDAYS($E$4,F34,'Festivos CR'!$A$3:$A$15)),0) -> 0 | I34: =NETWORKDAYS($E$4,F34,'Festivos CR'!$A$3:$A$15) -> 4 | J34: =H34 -> 0
B35: 5283 | C35: Cobro S&P a sucursal Septiembre | D35: =E35*$D$6 -> 260590 | E35: =515 -> 515 | F35: 45603 | G35: Cancelado | H35: =IF(OR(G35="Sin pagar",G35="Pagar"),_xlfn.SINGLE(NETWORKDAYS($E$4,F35,'Festivos CR'!$A$3:$A$15)),0) -> 0 | I35: =NETWORKDAYS($E$4,F35,'Festivos CR'!$A$3:$A$15) -> 4 | J35: =H35 -> 0
B36: 5383 | C36: Cobro S&P a sucursal Octubre | D36: =E36*$D$6 -> 222640 | E36: 440 | F36: 45603 | G36: Cancelado | H36: =IF(OR(G36="Sin pagar",G36="Pagar"),_xlfn.SINGLE(NETWORKDAYS($E$4,F36,'Festivos CR'!$A$3:$A$15)),0) -> 0 | I36: =NETWORKDAYS($E$4,F36,'Festivos CR'!$A$3:$A$15) -> 4 | J36: =H36 -> 0
C37: COSTOS FINANCIEROS | D37: =SUBTOTAL(9,D38:D38) -> 39375 | E37: =SUBTOTAL(9,E38:E38) -> 77.816206
C38: COSTOS FINANCIEROS | D38: 39375 | E38: =D38/D6 -> 77.816206 | F38: 45626 | G38: Cancelado | H38: =IF(OR(G38="Sin pagar",G38="Pagar"),_xlfn.SINGLE(NETWORKDAYS($E$4,F38,'Festivos CR'!$A$3:$A$15)),0) -> 0 | I38: =NETWORKDAYS($E$4,F38,'Festivos CR'!$A$3:$A$15) -> 20 | J38: =H38 -> 0
C39: NÓMINAS | D39: =SUBTOTAL(9,D40:D47) -> 13223501 | E39: =SUBTOTAL(9,E40:E47) -> 26592.16
B40: CRC | C40: Jhoel González González-Starlight-CR003 | D40: 1612916.3 | E40: =CONVERSIONES!E198 -> 3417.34 | F40: 45624 | G40: Cancelado | H40: =IF(OR(G40="Sin pagar",G40="Pagar"),_xlfn.SINGLE(NETWORKDAYS($E$4,F40,'Festivos CR'!$A$3:$A$15)),0) -> 0 | I40: =NETWORKDAYS($E$4,F40,'Festivos CR'!$A$3:$A$15) -> 19 | J40: =H40 -> 0
B41: USD | C41: Jonathan Salazar García -Starlight-CR003 | D41: =E41*CONVERSIONES!$C$201 -> 3338939.6 | E41: 6664.55 | F41: 45624 | G41: Cancelado | H41: =IF(OR(G41="Sin pagar",G41="Pagar"),_xlfn.SINGLE(NETWORKDAYS($E$4,F41,'Festivos CR'!$A$3:$A$15)),0) -> 0 | I41: =NETWORKDAYS($E$4,F41,'Festivos CR'!$A$3:$A$15) -> 19 | J41: =H41 -> 0
B42: CRC | C42: Daniel Nazario Casto Vindas-Starlight-CR003 | D42: 1325079.4 | E42: =D42/CONVERSIONES!$C$201 -> 2644.869 | F42: 45624 | G42: Cancelado | H42: =IF(OR(G42="Sin pagar",G42="Pagar"),_xlfn.SINGLE(NETWORKDAYS($E$4,F42,'Festivos CR'!$A$3:$A$15)),0) -> 0 | I42: =NETWORKDAYS($E$4,F42,'Festivos CR'!$A$3:$A$15) -> 19 | J42: =H42 -> 0
B43: CRC | C43: Priscilla Grace Polson -Aluminati-CR004 | D43: 1410537.3 | E43: =$D$43/CONVERSIONES!$C$201 -> 2815.4437 | F43: 45624 | G43: Cancelado | H43: =IF(OR(G43="Sin pagar",G43="Pagar"),_xlfn.SINGLE(NETWORKDAYS($E$4,F43,'Festivos CR'!$A$3:$A$15)),0) -> 0 | I43: =NETWORKDAYS($E$4,F43,'Festivos CR'!$A$3:$A$15) -> 19 | J43: =H43 -> 0
B44: CRC | C44: José Roberto Aguilar Barrante-Aluminati-CR004 | D44: 1410537.3 | E44: =$D$44/CONVERSIONES!$C$201 -> 2815.4437 | F44: 45624 | G44: Cancelado | H44: =IF(OR(G44="Sin pagar",G44="Pagar"),_xlfn.SINGLE(NETWORKDAYS($E$4,F44,'Festivos CR'!$A$3:$A$15)),0) -> 0 | I44: =NETWORKDAYS($E$4,F44,'Festivos CR'!$A$3:$A$15) -> 19 | J44: =H44 -> 0
B45: CRC | C45: Sheryl Gertrudiz Cambronero Estrada-lorez & Prada PPLC | D45: 786551.54 | E45: =$D$45/CONVERSIONES!$C$201 -> 1569.9632 | F45: 45624 | G45: Cancelado | H45: =IF(OR(G45="Sin pagar",G45="Pagar"),_xlfn.SINGLE(NETWORKDAYS($E$4,F45,'Festivos CR'!$A$3:$A$15)),0) -> 0 | I45: =NETWORKDAYS($E$4,F45,'Festivos CR'!$A$3:$A$15) -> 19 | J45: =H45 -> 0
B46: USD | C46: Tatiana Araya Pochet-CZ-CR006 | D46: =E46*CONVERSIONES!$C$201 -> 3338939.6 | E46: =CONVERSIONES!H198 -> 6664.55 | F46: 45624 | G46: Cancelado | H46: =IF(OR(G46="Sin pagar",G46="Pagar"),_xlfn.SINGLE(NETWORKDAYS($E$4,F46,'Festivos CR'!$A$3:$A$15)),0) -> 0 | I46: =NETWORKDAYS($E$4,F46,'Festivos CR'!$A$3:$A$15) -> 19 | J46: =H46 -> 0
B47: USD | C47: José Alvardo -Advanció | D47: =$E$47*CONVERSIONES!$C$183 -> 0 | E47: =CONVERSIONES!J180*0 -> 0 | F47: 45624 | G47: Sin Pagar | H47: =IF(OR(G47="Sin pagar",G47="Pagar"),_xlfn.SINGLE(NETWORKDAYS($E$4,F47,'Festivos CR'!$A$3:$A$15)),0) -> 19 | I47: =NETWORKDAYS($E$4,F47,'Festivos CR'!$A$3:$A$15) -> 19 | J47: =H47 -> 19
C48: IMPREVISTO | D48: =SUBTOTAL(9,D49:D49) -> 0 | E48: =SUBTOTAL(9,E49:E49) -> 0
D49: 0 | E49: =D49/$D$6 -> 0 | F49: 45626 | G49: Cancelado | H49: =IF(OR(#REF!="Sin pagar",#REF!="Pagar"),_xlfn.SINGLE(NETWORKDAYS($E$4,#REF!,'Festivos CR'!$A$3:$A$15)),0) -> #REF! | I49: =NETWORKDAYS($E$4,#REF!,'Festivos CR'!$A$3:$A$15) -> #REF!
C50: TOTAL EGRESOS | D50: =SUBTOTAL(9,D23:D49) -> 21947358 | E50: =SUBTOTAL(9,E23:E49) -> 43832.984
C52: SALDO | D52: =D18-D50 -> 12853378 | E52: =E18-E50 -> 21749.261
C53: % | D53: =IF($D$18=0,0,D52/$D$18) -> 0.36934213 | E53: =IF($E$18=0,0,E52/$E$18) -> 0.33163338
C57: Fecha Inicial | D57: Fecha Final | E57: Valor VALOR ₡ CRC | F57: Valor VALOR USD
C58: 45597 | D58: 45606 | E58: =SUMIFS($D$22:$D$55,$F$22:$F$55,">="&C58,$F$22:$F$55,"<="&D58,$G$22:$G$55,$D$71) -> 0 | F58: =SUMIFS($E$22:$E$55,$F$22:$F$55,">="&C58,$F$22:$F$55,"<="&D58,$G$22:$G$55,$D$71) -> 0 | G58: Envío de divisas
C59: 45607 | D59: 45613 | E59: =SUMIFS($D$22:$D$55,$F$22:$F$55,">="&C59,$F$22:$F$55,"<="&D59,$G$22:$G$55,$D$71) -> 0 | F59: =SUMIFS($E$22:$E$55,$F$22:$F$55,">="&C59,$F$22:$F$55,"<="&D59,$G$22:$G$55,$D$71) -> 0 | G59: CCSS e impuestos
C60: 45614 | D60: 45620 | E60: =SUMIFS($D$22:$D$55,$F$22:$F$55,">="&C60,$F$22:$F$55,"<="&D60,$G$22:$G$55,$D$71) -> 0 | F60: =SUMIFS($E$22:$E$55,$F$22:$F$55,">="&C60,$F$22:$F$55,"<="&D60,$G$22:$G$55,$D$71) -> 0 | G60: Servicios Profesionales Alejandro
C61: 45621 | D61: 45626 | E61: =SUMIFS($D$22:$D$55,$F$22:$F$55,">="&C61,$F$22:$F$55,"<="&D61,$G$22:$G$55,$D$71) -> 0 | F61: =SUMIFS($E$22:$E$55,$F$22:$F$55,">="&C61,$F$22:$F$55,"<="&D61,$G$22:$G$55,$D$71) -> 0 | G61: Nóminas
C62: TOTAL EGRESOS | E62: =SUM(E58:E61) -> 0 | F62: =SUM(F58:F61) -> 0
C65: Bancos | E65: ='BAC SAN JOSE COLONES '!$G$286+('BAC SAN JOSE USD'!$G$232*CONVERSIONES!$C$183) -> 10673970 | F65: =E65/CONVERSIONES!$C$183 -> 21094.802
C66: Gastos y costos Periodo 01 al 24 Noviembre | E66: =SUM(E58:E60) -> 0 | F66: =SUM(F58:F60) -> 0
C67: Saldo | E67: =E65-E66 -> 10673970 | F67: =F65-F66 -> 21094.802
D70: Cancelado | E70: =SUMIFS($D$22:$D$55,$F$22:$F$55,">="&C58,$F$22:$F$55,"<="&$D$61,$G$22:$G$55,$D$70) -> 21947358 | F70: =SUMIFS($E$22:$E$55,$F$22:$F$55,">="&C58,$F$22:$F$55,"<="&D61,$G$22:$G$55,$D$70) -> 43832.984
D71: Sin Pagar | E71: =SUMIFS($D$22:$D$55,$F$22:$F$55,">="&C58,$F$22:$F$55,"<="&$D$61,$G$22:$G$55,$D$71) -> 0 | F71: =SUMIFS($E$22:$E$55,$F$22:$F$55,">="&C58,$F$22:$F$55,"<="&D61,$G$22:$G$55,$D$71) -> 0
D72: Total Egresos | E72: =SUM(E70:E71) -> 21947358 | F72: =SUM(F70:F71) -> 43832.984
D73: Validación | E73: =D50-E72 -> 0 | F73: =F72-E50 -> 0
E76: Flujo Caja | F76: =D52 -> 12853378
E77: Libro Bancos | F77: ='BAC SAN JOSE COLONES '!G284+('BAC SAN JOSE USD'!G230*513) -> 12853378
E78: Diferencia | F78: =F76-F77 -> 0.13680702

Sheet FLUJO CAJA DICIEMBRE
D1: 42400
D4: Fecha de Elaboración: | E4: 45628
C6: Tasa de cambio: | D6: 513
D7: DICIEMBRE
D8: VALOR ₡ CRC | E8: VALOR USD
C9: BANCOS | D9: =SUBTOTAL(9,D10:D11) -> 15978425 | E9: =SUBTOTAL(9,E10:E11) -> 31147.028
C10: Bancos ₡ CRC | D10: ='BAC SAN JOSE COLONES '!$G$284+61676+2979332 -> 10840540 | E10: =D10/$D$6 -> 21131.657
C11: Bancos USD | D11: =E11*$D$6 -> 5137885.2 | E11: ='BAC SAN JOSE USD'!$G$230+163.82 -> 10015.371
C12: CLIENTES | D12: =SUBTOTAL(9,D13:D18) -> 35165983 | E12: =SUBTOTAL(9,E13:E18) -> 70261.933
B13: Pagado | C13: Advancio - Client: PLLC- Factura Nro XXX | D13: =E13*CONVERSIONES!$J$201 -> 3496328.8 | E13: =CONVERSIONES!J197 -> 7049.05
B14: Pagado | C14: Client: Remorfist-Client-Starlight SS -Factura Nro XXX | D14: =E14*CONVERSIONES!$C$219 -> 12500058 | E14: =(CONVERSIONES!$C$215+CONVERSIONES!$D$215+CONVERSIONES!$E$215) -> 24950.216
B15: Pagado | C15: Client: Remorfist-Client: Aluminati-Factura Nro XXX | D15: =E15*CONVERSIONES!$C$219 -> 7414368.1 | E15: =(CONVERSIONES!$F$215+CONVERSIONES!$G$215) -> 14799.138
B16: Pagado | C16: Remorfist - Client: CZ SS-Factura Nro XXX | D16: =E16*CONVERSIONES!$C$219 -> 10023660 | E16: =CONVERSIONES!$H$215 -> 20007.306
B17: Pagado | C17: Remorfist - Client: PLLC- Factura Nro XXX | D17: =E17*CONVERSIONES!$C$219 -> 1731568 | E17: =CONVERSIONES!I215 -> 3456.2236
B18: Pagado | C18: Advancio - Client: Factura Nro XXX | D18: =E18*CONVERSIONES!$C$219 -> 0 | E18: =(7453.5-1506.73)*0 -> 0
C19: TOTAL INGRESOS | D19: =SUBTOTAL(9,D9:D18) -> 51144408 | E19: =SUBTOTAL(9,E9:E18) -> 101408.96
B22: CUENTAS X PAGAR MES | D22: DICIEMBRE
B23: Factura | C23: PROVEEDOR | D23: VALOR ₡ CRC | E23: VALOR USD | F23: Fecha vencimiento | G23: Estado | J23: KPI
C24: SEGURIDAD IGSS | D24: =SUBTOTAL(9,D25:D25) -> 6231287 | E24: =SUBTOTAL(9,E25:E25) -> 12146.758
B25: 777720241143125012-1 | C25: Pago CCSS Noviembre | D25: 6231287 | E25: =D25/$D$6 -> 12146.758 | F25: 45638 | G25: Cancelado | H25: =IF(OR(G25="Sin pagar",G25="Pagar"),_xlfn.SINGLE(NETWORKDAYS($E$4,F25,'Festivos CR'!$A$3:$A$15)),0) -> 0 | I25: =NETWORKDAYS($E$4,F25,'Festivos CR'!$A$3:$A$15) -> 9 | J25: =H25 -> 0
C26: IMPUESTOS | D26: =SUBTOTAL(9,D27:D28) -> 1353221 | E26: =SUBTOTAL(9,E27:E28) -> 2637.8577 | F26: , | J26: =H26 -> 0
C27: Retención en la fuente | D27: 1297345 | E27: =D27/$D$6 -> 2528.9376 | F27: 45638 | G27: Cancelado | H27: =IF(OR(G27="Sin pagar",G27="Pagar"),_xlfn.SINGLE(NETWORKDAYS($E$4,F27,'Festivos CR'!$A$3:$A$15)),0) -> 0 | I27: =NETWORKDAYS($E$4,F27,'Festivos CR'!$A$3:$A$15) -> 9 | J27: =H27 -> 0
C28: Rte fte por declaración de remesas al exterior Facturación S&P Colombia a S&P CR | D28: 55876 | E28: =D28/$D$6 -> 108.92008 | F28: 45638 | G28: Cancelado | H28: =IF(OR(G28="Sin pagar",G28="Pagar"),_xlfn.SINGLE(NETWORKDAYS($E$4,F28,'Festivos CR'!$A$3:$A$15)),0) -> 0 | I28: =NETWORKDAYS($E$4,F28,'Festivos CR'!$A$3:$A$15) -> 9 | J28: =H28 -> 0
C29: SERVICIOS PROFESIONALES -REPRESENTACIÓN LEGAL | D29: =SUBTOTAL(9,D30:D30) -> 62400 | E29: =SUBTOTAL(9,E30:E30) -> 121.63743 | J29: =H29 -> 0
B30: 22 | C30: Servicios profesionales Alejandro Echavarria Diciembre | D30: 62400 | E30: =D30/$D$6 -> 121.63743 | F30: 45645 | G30: Cancelado | H30: =IF(OR(G30="Sin pagar",G30="Pagar"),_xlfn.SINGLE(NETWORKDAYS($E$4,F30,'Festivos CR'!$A$3:$A$15)),0) -> 0 | I30: =NETWORKDAYS($E$4,F30,'Festivos CR'!$A$3:$A$15) -> 14 | J30: =H30 -> 0
C31: GASTOS DE OFICINA | D31: =SUBTOTAL(9,D32:D33) -> 391642 | E31: =SUBTOTAL(9,E32:E33) -> 763.4347
B32: 62 | C32: Compra de café | D32: 77000 | E32: =D32/$D$6 -> 150.09747 | F32: 45631 | G32: Cancelado | H32: =IF(OR(G32="Sin pagar",G32="Pagar"),_xlfn.SINGLE(NETWORKDAYS($E$4,F32,'Festivos CR'!$A$3:$A$15)),0) -> 0 | I32: =NETWORKDAYS($E$4,F32,'Festivos CR'!$A$3:$A$15) -> 4 | J32: =H32 -> 0
C33: Pago primas póliza de riesgo de trabajo NRO 4024882 -INS del 01/10/23 al 30/09/24 | D33: 314642 | E33: =D33/$D$6 -> 613.33723 | F33: 45644 | G33: Cancelado | H33: =IF(OR(G33="Sin pagar",G33="Pagar"),_xlfn.SINGLE(NETWORKDAYS($E$4,F33,'Festivos CR'!$A$3:$A$15)),0) -> 0 | I33: =NETWORKDAYS($E$4,F33,'Festivos CR'!$A$3:$A$15) -> 13 | J33: =H33 -> 0
C34: COBROS ENTRE SUCURSALES | D34: =SUBTOTAL(9,D35:D36) -> 0 | E34: =SUBTOTAL(9,E35:E36) -> 0
B35: 5483 | C35: Cobro S&P a sucursal Noviembre | D35: =E35*$D$6 -> 0 | E35: =440*0 -> 0 | F35: 45657 | G35: Cancelado | H35: =IF(OR(G35="Sin pagar",G35="Pagar"),_xlfn.SINGLE(NETWORKDAYS($E$4,F35,'Festivos CR'!$A$3:$A$15)),0) -> 0 | I35: =NETWORKDAYS($E$4,F35,'Festivos CR'!$A$3:$A$15) -> 20 | J35: =H35 -> 0
B36: 5582 | C36: Cobro S&P a sucursal Diciembre | D36: =E36*$D$6 -> 0 | E36: =440*0 -> 0 | F36: 45657 | G36: Cancelado | H36: =IF(OR(G36="Sin pagar",G36="Pagar"),_xlfn.SINGLE(NETWORKDAYS($E$4,F36,'Festivos CR'!$A$3:$A$15)),0) -> 0 | I36: =NETWORKDAYS($E$4,F36,'Festivos CR'!$A$3:$A$15) -> 20 | J36: =H36 -> 0
C37: COSTOS FINANCIEROS | D37: =SUBTOTAL(9,D38:D38) -> 300.56 | E37: =SUBTOTAL(9,E38:E38) -> 0.58588694
C38: COSTOS FINANCIEROS | D38: 300.56 | E38: =D38/D6 -> 0.58588694 | F38: 45656 | G38: Cancelado | H38: =IF(OR(G38="Sin pagar",G38="Pagar"),_xlfn.SINGLE(NETWORKDAYS($E$4,F38,'Festivos CR'!$A$3:$A$15)),0) -> 0 | I38: =NETWORKDAYS($E$4,F38,'Festivos CR'!$A$3:$A$15) -> 20 | J38: =H38 -> 0
C39: NÓMINAS | D39: =SUBTOTAL(9,D40:D56) -> 28117836 | E39: =SUBTOTAL(9,E40:E56) -> 56253.353
B40: USD | C40: José Alvardo -Advanció-Noviembre | D40: =$E$40*CONVERSIONES!$C$183 -> 2033447 | E40: 4018.67 | F40: 45630 | G40: Cancelado | H40: =IF(OR(G40="Sin pagar",G40="Pagar"),_xlfn.SINGLE(NETWORKDAYS($E$4,F40,'Festivos CR'!$A$3:$A$15)),0) -> 0 | I40: =NETWORKDAYS($E$4,F40,'Festivos CR'!$A$3:$A$15) -> 3 | J40: =H40 -> 0
B41: CRC | C41: Jhoel González González-Starlight-CR003-Aguinaldo | D41: 1779646.9 | E41: =D41/CONVERSIONES!$C$219 -> 3552.1894 | F41: 45645 | G41: Cancelado | H41: =IF(OR(G41="Sin pagar",G41="Pagar"),_xlfn.SINGLE(NETWORKDAYS($E$4,F41,'Festivos CR'!$A$3:$A$15)),0) -> 0 | I41: =NETWORKDAYS($E$4,F41,'Festivos CR'!$A$3:$A$15) -> 14 | J41: =H41 -> 0
B42: USD | C42: Jonathan Salazar García -Starlight-CR003-Aguinaldo | D42: =E42*CONVERSIONES!$C$219 -> 2577234.2 | E42: 5144.18 | F42: 45645 | G42: Cancelado | H42: =IF(OR(G42="Sin pagar",G42="Pagar"),_xlfn.SINGLE(NETWORKDAYS($E$4,F42,'Festivos CR'!$A$3:$A$15)),0) -> 0 | I42: =NETWORKDAYS($E$4,F42,'Festivos CR'!$A$3:$A$15) -> 14 | J42: =H42 -> 0
B43: CRC | C43: Daniel Nazario Casto Vindas-Starlight-CR003-Aguinaldo | D43: 682962.65 | E43: =D43/CONVERSIONES!$C$219 -> 1363.1989 | F43: 45645 | G43: Cancelado | H43: =IF(OR(G43="Sin pagar",G43="Pagar"),_xlfn.SINGLE(NETWORKDAYS($E$4,F43,'Festivos CR'!$A$3:$A$15)),0) -> 0 | I43: =NETWORKDAYS($E$4,F43,'Festivos CR'!$A$3:$A$15) -> 14 | J43: =H43 -> 0
B44: CRC | C44: Priscilla Grace Polson -Aluminati-CR004-Aguinaldo | D44: 1681000 | E44: =D44/CONVERSIONES!$C$219 -> 3355.2894 | F44: 45645 | G44: Cancelado | H44: =IF(OR(G44="Sin pagar",G44="Pagar"),_xlfn.SINGLE(NETWORKDAYS($E$4,F44,'Festivos CR'!$A$3:$A$15)),0) -> 0 | I44: =NETWORKDAYS($E$4,F44,'Festivos CR'!$A$3:$A$15) -> 14 | J44: =H44 -> 0
B45: CRC | C45: José Roberto Aguilar Barrante-Aluminati-CR004-Aguinaldo | D45: 1214055.6 | E45: =D45/CONVERSIONES!$C$219 -> 2423.2646 | F45: 45645 | G45: Cancelado | H45: =IF(OR(G45="Sin pagar",G45="Pagar"),_xlfn.SINGLE(NETWORKDAYS($E$4,F45,'Festivos CR'!$A$3:$A$15)),0) -> 0 | I45: =NETWORKDAYS($E$4,F45,'Festivos CR'!$A$3:$A$15) -> 14 | J45: =H45 -> 0
B46: CRC | C46: Sheryl Gertrudiz Cambronero Estrada-lorez & Prada PPLC-Aguinaldo | D46: 513625.58 | E46: =D46/CONVERSIONES!$C$219 -> 1025.2008 | F46: 45645 | G46: Cancelado | H46: =IF(OR(G46="Sin pagar",G46="Pagar"),_xlfn.SINGLE(NETWORKDAYS($E$4,F46,'Festivos CR'!$A$3:$A$15)),0) -> 0 | I46: =NETWORKDAYS($E$4,F46,'Festivos CR'!$A$3:$A$15) -> 14 | J46: =H46 -> 0
B47: USD | C47: Tatiana Araya Pochet-CZ-CR006-Aguinaldo | D47: =E47*CONVERSIONES!$C$219 -> 4333650 | E47: 8650 | F47: 45645 | G47: Cancelado | H47: =IF(OR(G47="Sin pagar",G47="Pagar"),_xlfn.SINGLE(NETWORKDAYS($E$4,F47,'Festivos CR'!$A$3:$A$15)),0) -> 0 | I47: =NETWORKDAYS($E$4,F47,'Festivos CR'!$A$3:$A$15) -> 14 | J47: =H47 -> 0
B48: USD | C48: José Alvardo -Advanció-Aguinaldo | D48: =E48*CONVERSIONES!$C$219 -> 375750 | E48: 750 | F48: 45645 | G48: Cancelado | H48: =IF(OR(G48="Sin pagar",G48="Pagar"),_xlfn.SINGLE(NETWORKDAYS($E$4,F48,'Festivos CR'!$A$3:$A$15)),0) -> 0 | I48: =NETWORKDAYS($E$4,F48,'Festivos CR'!$A$3:$A$15) -> 14 | J48: =H48 -> 0
B49: CRC | C49: Jhoel González González-Starlight-CR003 | D49: =1612916.33 -> 1612916.3 | E49: =CONVERSIONES!E198 -> 3417.34 | F49: 45653 | G49: Cancelado | H49: =IF(OR(G49="Sin pagar",G49="Pagar"),_xlfn.SINGLE(NETWORKDAYS($E$4,F49,'Festivos CR'!$A$3:$A$15)),0) -> 0 | I49: =NETWORKDAYS($E$4,F49,'Festivos CR'!$A$3:$A$15) -> 19 | J49: =H49 -> 0
B50: USD | C50: Jonathan Salazar García -Starlight-CR003 | D50: =E50*CONVERSIONES!$C$201 -> 1713269.7 | E50: 3419.7 | F50: 45653 | G50: Cancelado | H50: =IF(OR(G50="Sin pagar",G50="Pagar"),_xlfn.SINGLE(NETWORKDAYS($E$4,F50,'Festivos CR'!$A$3:$A$15)),0) -> 0 | I50: =NETWORKDAYS($E$4,F50,'Festivos CR'!$A$3:$A$15) -> 19 | J50: =H50 -> 0
B51: CRC | C51: Daniel Nazario Casto Vindas-Starlight-CR003 | D51: =1325079.36 -> 1325079.4 | E51: =D51/CONVERSIONES!$C$201 -> 2644.869 | F51: 45653 | G51: Cancelado | H51: =IF(OR(G51="Sin pagar",G51="Pagar"),_xlfn.SINGLE(NETWORKDAYS($E$4,F51,'Festivos CR'!$A$3:$A$15)),0) -> 0 | I51: =NETWORKDAYS($E$4,F51,'Festivos CR'!$A$3:$A$15) -> 19 | J51: =H51 -> 0
B52: CRC | C52: Priscilla Grace Polson -Aluminati-CR004 | D52: =1410537.3 -> 1410537.3 | E52: =$D$52/CONVERSIONES!$C$201 -> 2815.4437 | F52: 45653 | G52: Cancelado | H52: =IF(OR(G52="Sin pagar",G52="Pagar"),_xlfn.SINGLE(NETWORKDAYS($E$4,F52,'Festivos CR'!$A$3:$A$15)),0) -> 0 | I52: =NETWORKDAYS($E$4,F52,'Festivos CR'!$A$3:$A$15) -> 19 | J52: =H52 -> 0
B53: CRC | C53: José Roberto Aguilar Barrante-Aluminati-CR004 | D53: =1410537.3 -> 1410537.3 | E53: =$D$53/CONVERSIONES!$C$201 -> 2815.4437 | F53: 45653 | G53: Cancelado | H53: =IF(OR(G53="Sin pagar",G53="Pagar"),_xlfn.SINGLE(NETWORKDAYS($E$4,F53,'Festivos CR'!$A$3:$A$15)),0) -> 0 | I53: =NETWORKDAYS($E$4,F53,'Festivos CR'!$A$3:$A$15) -> 19 | J53: =H53 -> 0
B54: CRC | C54: Sheryl Gertrudiz Cambronero Estrada-lorez & Prada PPLC | D54: =786551.54 -> 786551.54 | E54: =$D$54/CONVERSIONES!$C$201 -> 1569.9632 | F54: 45653 | G54: Cancelado | H54: =IF(OR(G54="Sin pagar",G54="Pagar"),_xlfn.SINGLE(NETWORKDAYS($E$4,F54,'Festivos CR'!$A$3:$A$15)),0) -> 0 | I54: =NETWORKDAYS($E$4,F54,'Festivos CR'!$A$3:$A$15) -> 19 | J54: =H54 -> 0
B55: USD | C55: Tatiana Araya Pochet-CZ-CR006 | D55: =E55*CONVERSIONES!$C$201 -> 3252361.7 | E55: 6491.74 | F55: 45653 | G55: Cancelado | H55: =IF(OR(G55="Sin pagar",G55="Pagar"),_xlfn.SINGLE(NETWORKDAYS($E$4,F55,'Festivos CR'!$A$3:$A$15)),0) -> 0 | I55: =NETWORKDAYS($E$4,F55,'Festivos CR'!$A$3:$A$15) -> 19 | J55: =H55 -> 0
B56: USD | C56: José Alvardo -Advanció | D56: =$E$56*CONVERSIONES!$C$183 -> 1415211.2 | E56: 2796.86 | F56: 45653 | G56: Cancelado | H56: =IF(OR(G56="Sin pagar",G56="Pagar"),_xlfn.SINGLE(NETWORKDAYS($E$4,F56,'Festivos CR'!$A$3:$A$15)),0) -> 0 | I56: =NETWORKDAYS($E$4,F56,'Festivos CR'!$A$3:$A$15) -> 19 | J56: =H56 -> 0
C57: IMPREVISTO | D57: =SUBTOTAL(9,D58:D58) -> 0 | E57: =SUBTOTAL(9,E58:E58) -> 0
D58: 0 | E58: =D58/$D$6 -> 0 | F58: 45656 | G58: Cancelado | H58: =IF(OR(#REF!="Sin pagar",#REF!="Pagar"),_xlfn.SINGLE(NETWORKDAYS($E$4,#REF!,'Festivos CR'!$A$3:$A$15)),0) -> #REF! | I58: =NETWORKDAYS($E$4,#REF!,'Festivos CR'!$A$3:$A$15) -> #REF!
C59: TOTAL EGRESOS | D59: =SUBTOTAL(9,D24:D58) -> 36156687 | E59: =SUBTOTAL(9,E24:E58) -> 71923.627
C61: SALDO | D61: =D19-D59 -> 14987722 | E61: =E19-E59 -> 29485.334
C62: % | D62: =IF($D$19=0,0,D61/$D$19) -> 0.29304712 | E62: =IF($E$19=0,0,E61/$E$19) -> 0.29075669
C66: Fecha Inicial | D66: Fecha Final | E66: Valor VALOR ₡ CRC | F66: Valor VALOR USD
C67: 45627 | D67: 45634 | E67: =SUMIFS($D$23:$D$64,$F$23:$F$64,">="&C67,$F$23:$F$64,"<="&D67,$G$23:$G$64,$D$81) -> 0 | F67: =SUMIFS($E$23:$E$64,$F$23:$F$64,">="&C67,$F$23:$F$64,"<="&D67,$G$23:$G$64,$D$81) -> 0 | G67: Café y pago nómina Advancio Nov
C68: 45635 | D68: 45641 | E68: =SUMIFS($D$23:$D$64,$F$23:$F$64,">="&C68,$F$23:$F$64,"<="&D68,$G$23:$G$64,$D$81) -> 0 | F68: =SUMIFS($E$23:$E$64,$F$23:$F$64,">="&C68,$F$23:$F$64,"<="&D68,$G$23:$G$64,$D$81) -> 0 | G68: CCSS e impuestos y envío divisas
C69: 45642 | D69: 45648 | E69: =SUMIFS($D$23:$D$64,$F$23:$F$64,">="&C69,$F$23:$F$64,"<="&D69,$G$23:$G$64,$D$81) -> 0 | F69: =SUMIFS($E$23:$E$64,$F$23:$F$64,">="&C69,$F$23:$F$64,"<="&D69,$G$23:$G$64,$D$81) -> 0 | G69: Servicios Profesionales Alejandro
C70: 45649 | D70: 45653 | E70: =SUMIFS($D$23:$D$64,$F$23:$F$64,">="&C70,$F$23:$F$64,"<="&D70,$G$23:$G$64,$D$81) -> 0 | F70: =SUMIFS($E$23:$E$64,$F$23:$F$64,">="&C70,$F$23:$F$64,"<="&D70,$G$23:$G$64,$D$81) -> 0 | G70: Nóminas
C71: 45656 | D71: 45657 | E71: =SUMIFS($D$23:$D$64,$F$23:$F$64,">="&C71,$F$23:$F$64,"<="&D71,$G$23:$G$64,$D$81) -> 0 | F71: =SUMIFS($E$23:$E$64,$F$23:$F$64,">="&C71,$F$23:$F$64,"<="&D71,$G$23:$G$64,$D$81) -> 0 | G71: GMF
C72: TOTAL EGRESOS | E72: =SUM(E67:E71) -> 0 | F72: =SUM(F67:F71) -> 0
C75: Bancos | E75: ='BAC SAN JOSE COLONES '!$G$350+('BAC SAN JOSE USD'!$G$250*'FLUJO CAJA DICIEMBRE'!$D$6) -> 29646998 | F75: =E75/D6 -> 57791.419
C76: Gastos y costos Periodo 27 al 30 de diciembre | E76: =SUM(E70:E71) -> 0 | F76: =SUM(F70:F71) -> 0
C77: Saldo | E77: =E75-E76 -> 29646998 | F77: =F75-F76 -> 57791.419
D80: Cancelado | E80: =SUMIFS($D$23:$D$64,$F$23:$F$64,">="&C67,$F$23:$F$64,"<="&$D$71,$G$23:$G$64,$D$80) -> 36156687 | F80: =SUMIFS($E$23:$E$64,$F$23:$F$64,">="&C67,$F$23:$F$64,"<="&D71,$G$23:$G$64,$D$80) -> 71923.627
D81: Sin Pagar | E81: =SUMIFS($D$23:$D$64,$F$23:$F$64,">="&C67,$F$23:$F$64,"<="&$D$71,$G$23:$G$64,$D$81) -> 0 | F81: =SUMIFS($E$23:$E$64,$F$23:$F$64,">="&C67,$F$23:$F$64,"<="&D71,$G$23:$G$64,$D$81) -> 0
D82: Total Egresos | E82: =SUM(E80:E81) -> 36156687 | F82: =SUM(F80:F81) -> 71923.627
D83: Validación | E83: =D59-E82 -> 0 | F83: =F82-E59 -> 0
D85: Flujo Caja | E85: =D61 -> 14987722
D86: Libro Bancos | E86: ='BAC SAN JOSE COLONES '!G307+('BAC SAN JOSE USD'!G247*$D$6) -> 14987722
D87: Diferencia | E87: =E85-E86 -> -0.13588709

Sheet FLUJO CAJA ENERO
D1: 42400
D4: Fecha de Elaboración: | E4: 45658
C6: Tasa de cambio: | D6: 517
D7: ENERO
D8: VALOR ₡ CRC | E8: VALOR USD
C9: BANCOS | D9: =SUBTOTAL(9,D10:D11) -> 15060724 | E9: =SUBTOTAL(9,E10:E11) -> 29130.994
C10: Bancos ₡ CRC | D10: ='BAC SAN JOSE COLONES '!$G$307 -> 5625173.7 | E10: =D10/$D$6 -> 10880.413
C11: Bancos USD | D11: =E11*$D$6 -> 9435550.3 | E11: ='BAC SAN JOSE USD'!$G$247 -> 18250.581
C12: CLIENTES | D12: =SUBTOTAL(9,D13:D13) -> 18656397 | E12: =SUBTOTAL(9,E13:E13) -> 37462.644
B13: Pagado | C13: Client: Remorfist-Factura Nro 163 | D13: =$E$13*CONVERSIONES!$C$278 -> 18656397 | E13: =CONVERSIONES!J274 -> 37462.644
C14: TOTAL INGRESOS | D14: =SUBTOTAL(9,D9:D13) -> 33717121 | E14: =SUBTOTAL(9,E9:E13) -> 66593.639
B17: CUENTAS X PAGAR MES | D17: DICIEMBRE
B18: Factura | C18: PROVEEDOR | D18: VALOR ₡ CRC | E18: VALOR USD | F18: Fecha vencimiento | G18: Estado | J18: KPI
C19: SEGURIDAD IGSS | D19: =SUBTOTAL(9,D20:D20) -> 5919496 | E19: =SUBTOTAL(9,E20:E20) -> 11449.702
B20: 777720241243772018-1 | C20: Pago CCSS Diciembre | D20: 5919496 | E20: =D20/$D$6 -> 11449.702 | F20: 45670 | G20: Cancelado | H20: =IF(OR(G20="Sin pagar",G20="Pagar"),_xlfn.SINGLE(NETWORKDAYS($E$4,F20,'Festivos CR'!$A$3:$A$29)),0) -> 0 | I20: =NETWORKDAYS($E$4,F20,'Festivos CR'!$A$3:$A$29) -> 8 | J20: =H20 -> 0
C21: IMPUESTOS | D21: =SUBTOTAL(9,D22:D23) -> 1299395.5 | E21: =SUBTOTAL(9,E22:E23) -> 2513.3374 | J21: =H21 -> 0
C22: Retención en la fuente | D22: 1243933.5 | E22: =D22/$D$6 -> 2406.0609 | F22: 45670 | G22: Cancelado | H22: =IF(OR(G22="Sin pagar",G22="Pagar"),_xlfn.SINGLE(NETWORKDAYS($E$4,F22,'Festivos CR'!$A$3:$A$29)),0) -> 0 | I22: =NETWORKDAYS($E$4,F22,'Festivos CR'!$A$3:$A$29) -> 8 | J22: =H22 -> 0
C23: Rte fte por declaración de remesas al exterior Facturación S&P Colombia a S&P CR Fact 5582 | D23: =55462 -> 55462 | E23: =D23/$D$6 -> 107.2766 | F23: 45672 | G23: Cancelado | H23: =IF(OR(G23="Sin pagar",G23="Pagar"),_xlfn.SINGLE(NETWORKDAYS($E$4,F23,'Festivos CR'!$A$3:$A$29)),0) -> 0 | I23: =NETWORKDAYS($E$4,F23,'Festivos CR'!$A$3:$A$29) -> 10 | J23: =H23 -> 0
C24: Impuesto a sociedades | D24: 138660 | E24: =D24/$D$6 -> 268.20116 | F24: 45672 | G24: Cancelado | H24: =IF(OR(G24="Sin pagar",G24="Pagar"),_xlfn.SINGLE(NETWORKDAYS($E$4,F24,'Festivos CR'!$A$3:$A$29)),0) -> 0 | I24: =NETWORKDAYS($E$4,F24,'Festivos CR'!$A$3:$A$29) -> 10 | J24: =H24 -> 0
C25: SERVICIOS PROFESIONALES -REPRESENTACIÓN LEGAL | D25: =SUBTOTAL(9,D26:D27) -> 79350 | E25: =SUBTOTAL(9,E26:E27) -> 153.48162 | J25: =H25 -> 0
B26: 23 | C26: Servicios profesionales Alejandro Echavarria Apoyo computadores advancio | D26: 16950 | E26: =D26/$D$6 -> 32.7853 | F26: 45685 | G26: Cancelado | H26: =IF(OR(G26="Sin pagar",G26="Pagar"),_xlfn.SINGLE(NETWORKDAYS($E$4,F26,'Festivos CR'!$A$3:$A$29)),0) -> 0 | I26: =NETWORKDAYS($E$4,F26,'Festivos CR'!$A$3:$A$29) -> 19 | J26: =H26 -> 0
B27: 24 | C27: Servicios profesionales Alejandro Echavarria Enero | D27: 62400 | E27: =D27/$D$6 -> 120.69632 | F27: 45685 | G27: Cancelado | H27: =IF(OR(G27="Sin pagar",G27="Pagar"),_xlfn.SINGLE(NETWORKDAYS($E$4,F27,'Festivos CR'!$A$3:$A$29)),0) -> 0 | I27: =NETWORKDAYS($E$4,F27,'Festivos CR'!$A$3:$A$29) -> 19 | J27: =H27 -> 0
C28: GASTOS DE OFICINA | D28: =SUBTOTAL(9,D29:D30) -> 13899 | E28: =SUBTOTAL(9,E29:E30) -> 26.883946
B29: 62 | C29: Compra de café | D29: =77000*0 -> 0 | E29: =D29/$D$6 -> 0 | F29: 45322 | G29: Cancelado | H29: =IF(OR(G29="Sin pagar",G29="Pagar"),_xlfn.SINGLE(NETWORKDAYS($E$4,F29,'Festivos CR'!$A$3:$A$29)),0) -> 0 | I29: =NETWORKDAYS($E$4,F29,'Festivos CR'!$A$3:$A$29) -> -231 | J29: =H29 -> 0
B30: 00100001010001521906 | C30: Recarga de facturas electronica a GTI -Plan Prepago 24 documentos | D30: 13899 | E30: =D30/$D$6 -> 26.883946 | F30: 45672 | G30: Cancelado | H30: =IF(OR(G30="Sin pagar",G30="Pagar"),_xlfn.SINGLE(NETWORKDAYS($E$4,F30,'Festivos CR'!$A$3:$A$29)),0) -> 0 | I30: =NETWORKDAYS($E$4,F30,'Festivos CR'!$A$3:$A$29) -> 10 | J30: =H30 -> 0
C31: COBROS ENTRE SUCURSALES | D31: =SUBTOTAL(9,D32:D33) -> 0 | E31: =SUBTOTAL(9,E32:E33) -> 0
B32: 5483 | C32: Cobro S&P a sucursal Noviembre | D32: =E32*$D$6 -> 0 | E32: =440*0 -> 0 | F32: 45688 | G32: Cancelado | H32: =IF(OR(G32="Sin pagar",G32="Pagar"),_xlfn.SINGLE(NETWORKDAYS($E$4,F32,'Festivos CR'!$A$3:$A$29)),0) -> 0 | I32: =NETWORKDAYS($E$4,F32,'Festivos CR'!$A$3:$A$29) -> 22 | J32: =H32 -> 0
B33: 5582 | C33: Cobro S&P a sucursal Diciembre | D33: =E33*$D$6 -> 0 | E33: =440*0 -> 0 | F33: 45688 | G33: Cancelado | H33: =IF(OR(G33="Sin pagar",G33="Pagar"),_xlfn.SINGLE(NETWORKDAYS($E$4,F33,'Festivos CR'!$A$3:$A$29)),0) -> 0 | I33: =NETWORKDAYS($E$4,F33,'Festivos CR'!$A$3:$A$29) -> 22 | J33: =H33 -> 0
C34: COSTOS FINANCIEROS | D34: =SUBTOTAL(9,D35:D35) -> 36556.56 | E34: =SUBTOTAL(9,E35:E35) -> 70.709014
C35: COSTOS FINANCIEROS | D35: 36556.56 | E35: =D35/D6 -> 70.709014 | F35: 45688 | G35: Cancelado | H35: =IF(OR(G35="Sin pagar",G35="Pagar"),_xlfn.SINGLE(NETWORKDAYS($E$4,F35,'Festivos CR'!$A$3:$A$29)),0) -> 0 | I35: =NETWORKDAYS($E$4,F35,'Festivos CR'!$A$3:$A$29) -> 22 | J35: =H35 -> 0
C36: NÓMINAS | D36: =SUBTOTAL(9,D37:D43) -> 11540376 | E36: =SUBTOTAL(9,E37:E43) -> 23232.63
B37: CRC | C37: Jhoel González González-Starlight-CR003 | D37: 1612916.3 | E37: =CONVERSIONES!E198 -> 3417.34 | F37: 45685 | G37: Cancelado | H37: =IF(OR(G37="Sin pagar",G37="Pagar"),_xlfn.SINGLE(NETWORKDAYS($E$4,F37,'Festivos CR'!$A$3:$A$29)),0) -> 0 | I37: =NETWORKDAYS($E$4,F37,'Festivos CR'!$A$3:$A$29) -> 19 | J37: =H37 -> 0
B38: USD | C38: Jonathan Salazar García -Starlight-CR003 | D38: =E38*CONVERSIONES!$C$201 -> 1712723.6 | E38: 3418.61 | F38: 45685 | G38: Cancelado | H38: =IF(OR(G38="Sin pagar",G38="Pagar"),_xlfn.SINGLE(NETWORKDAYS($E$4,F38,'Festivos CR'!$A$3:$A$29)),0) -> 0 | I38: =NETWORKDAYS($E$4,F38,'Festivos CR'!$A$3:$A$29) -> 19 | J38: =H38 -> 0
B39: CRC | C39: Daniel Nazario Casto Vindas-Starlight-CR003 | D39: 1325079.4 | E39: =D39/CONVERSIONES!$C$201 -> 2644.869 | F39: 45685 | G39: Cancelado | H39: =IF(OR(G39="Sin pagar",G39="Pagar"),_xlfn.SINGLE(NETWORKDAYS($E$4,F39,'Festivos CR'!$A$3:$A$29)),0) -> 0 | I39: =NETWORKDAYS($E$4,F39,'Festivos CR'!$A$3:$A$29) -> 19 | J39: =H39 -> 0
B40: CRC | C40: Priscilla Grace Polson -Aluminati-CR004 | D40: 1410537.3 | E40: =$D$40/CONVERSIONES!$C$201 -> 2815.4437 | F40: 45685 | G40: Cancelado | H40: =IF(OR(G40="Sin pagar",G40="Pagar"),_xlfn.SINGLE(NETWORKDAYS($E$4,F40,'Festivos CR'!$A$3:$A$29)),0) -> 0 | I40: =NETWORKDAYS($E$4,F40,'Festivos CR'!$A$3:$A$29) -> 19 | J40: =H40 -> 0
B41: CRC | C41: José Roberto Aguilar Barrante-Aluminati-CR004 | D41: 1410537.3 | E41: =$D$41/CONVERSIONES!$C$201 -> 2815.4437 | F41: 45685 | G41: Cancelado | H41: =IF(OR(G41="Sin pagar",G41="Pagar"),_xlfn.SINGLE(NETWORKDAYS($E$4,F41,'Festivos CR'!$A$3:$A$29)),0) -> 0 | I41: =NETWORKDAYS($E$4,F41,'Festivos CR'!$A$3:$A$29) -> 19 | J41: =H41 -> 0
B42: CRC | C42: Sheryl Gertrudiz Cambronero Estrada-lorez & Prada PPLC | D42: 786551.54 | E42: =$D$42/CONVERSIONES!$C$201 -> 1569.9632 | F42: 45685 | G42: Cancelado | H42: =IF(OR(G42="Sin pagar",G42="Pagar"),_xlfn.SINGLE(NETWORKDAYS($E$4,F42,'Festivos CR'!$A$3:$A$29)),0) -> 0 | I42: =NETWORKDAYS($E$4,F42,'Festivos CR'!$A$3:$A$29) -> 19 | J42: =H42 -> 0
B43: USD | C43: Tatiana Araya Pochet-CZ-CR006 | D43: =E43*CONVERSIONES!$C$201 -> 3282031 | E43: 6550.96 | F43: 45685 | G43: Cancelado | H43: =IF(OR(G43="Sin pagar",G43="Pagar"),_xlfn.SINGLE(NETWORKDAYS($E$4,F43,'Festivos CR'!$A$3:$A$29)),0) -> 0 | I43: =NETWORKDAYS($E$4,F43,'Festivos CR'!$A$3:$A$29) -> 19 | J43: =H43 -> 0
C44: IMPREVISTO | D44: =SUBTOTAL(9,D45:D45) -> 0 | E44: =SUBTOTAL(9,E45:E45) -> 0
D45: 0 | E45: =D45/$D$6 -> 0 | F45: 45688 | G45: Cancelado | H45: =IF(OR(G45="Sin pagar",G45="Pagar"),_xlfn.SINGLE(NETWORKDAYS($E$4,F45,'Festivos CR'!$A$3:$A$29)),0) -> 0 | I45: =NETWORKDAYS($E$4,F45,'Festivos CR'!$A$3:$A$29) -> 22
C46: TOTAL EGRESOS | D46: =SUBTOTAL(9,D19:D45) -> 19027733 | E46: =SUBTOTAL(9,E19:E45) -> 37714.945
C48: SALDO | D48: =D14-D46 -> 14689387 | E48: =E14-E46 -> 28878.694
C49: % | D49: =IF($D$14=0,0,D48/$D$14) -> 0.43566553 | E49: =IF($E$14=0,0,E48/$E$14) -> 0.43365544
C53: Fecha Inicial | D53: Fecha Final | E53: Valor VALOR ₡ CRC | F53: Valor VALOR USD
C54: 45658 | D54: 45662 | E54: =SUMIFS($D$18:$D$51,$F$18:$F$51,">="&C54,$F$18:$F$51,"<="&D54,$G$18:$G$51,$D$68) -> 0 | F54: =SUMIFS($E$18:$E$51,$F$18:$F$51,">="&C54,$F$18:$F$51,"<="&D54,$G$18:$G$51,$D$68) -> 0
C55: 45663 | D55: 45669 | E55: =SUMIFS($D$18:$D$51,$F$18:$F$51,">="&C55,$F$18:$F$51,"<="&D55,$G$18:$G$51,$D$68) -> 0 | F55: =SUMIFS($E$18:$E$51,$F$18:$F$51,">="&C55,$F$18:$F$51,"<="&D55,$G$18:$G$51,$D$68) -> 0 | G55: CCSS e impuestos
C56: 45670 | D56: 45676 | E56: =SUMIFS($D$18:$D$51,$F$18:$F$51,">="&C56,$F$18:$F$51,"<="&D56,$G$18:$G$51,$D$68) -> 0 | F56: =SUMIFS($E$18:$E$51,$F$18:$F$51,">="&C56,$F$18:$F$51,"<="&D56,$G$18:$G$51,$D$68) -> 0 | G56: Recarga facxtura e impuestos sociedades CR
C57: 45677 | D57: 45683 | E57: =SUMIFS($D$18:$D$51,$F$18:$F$51,">="&C57,$F$18:$F$51,"<="&D57,$G$18:$G$51,$D$68) -> 0 | F57: =SUMIFS($E$18:$E$51,$F$18:$F$51,">="&C57,$F$18:$F$51,"<="&D57,$G$18:$G$51,$D$68) -> 0 | G57: Servicios Profesionales Alejandro
C58: 45684 | D58: 45688 | E58: =SUMIFS($D$18:$D$51,$F$18:$F$51,">="&C58,$F$18:$F$51,"<="&D58,$G$18:$G$51,$D$68) -> 0 | F58: =SUMIFS($E$18:$E$51,$F$18:$F$51,">="&C58,$F$18:$F$51,"<="&D58,$G$18:$G$51,$D$68) -> 0 | G58: Nóminas, Cobros entre sucursales y GMF
C59: TOTAL EGRESOS | E59: =SUM(E54:E58) -> 0 | F59: =SUM(F54:F58) -> 0
C62: Bancos | E62: ='BAC SAN JOSE COLONES '!$G$350+('BAC SAN JOSE USD'!$G$279*'FLUJO CAJA ENERO'!$D$6) -> 39293654 | F62: =$E$62/CONVERSIONES!$C$278 -> 78902.919
C63: Gastos y costos Periodo 27 al 30 de diciembre | E63: =SUM(E54:E57) -> 0 | F63: =SUM(F54:F57) -> 0
C64: Saldo | E64: =E62-E63 -> 39293654 | F64: =F62-F63 -> 78902.919
D67: Cancelado | E67: =SUMIFS($D$18:$D$51,$F$18:$F$51,">="&C54,$F$18:$F$51,"<="&$D$58,$G$18:$G$51,$D$67) -> 19027733 | F67: =SUMIFS($E$18:$E$51,$F$18:$F$51,">="&C54,$F$18:$F$51,"<="&D58,$G$18:$G$51,$D$67) -> 37714.945
D68: Sin Pagar | E68: =SUMIFS($D$18:$D$51,$F$18:$F$51,">="&C54,$F$18:$F$51,"<="&$D$58,$G$18:$G$51,$D$68) -> 0 | F68: =SUMIFS($E$18:$E$51,$F$18:$F$51,">="&C54,$F$18:$F$51,"<="&D58,$G$18:$G$51,$D$68) -> 0
D69: Total Egresos | E69: =SUM(E67:E68) -> 19027733 | F69: =SUM(F67:F68) -> 37714.945
D70: Validación | E70: =D46-E69 -> 0 | F70: =F69-E46 -> 0
D73: Flujo Caja | E73: =D48 -> 14689387
D74: Libro Bancos | E74: ='BAC SAN JOSE COLONES '!$G$327+('BAC SAN JOSE USD'!$G$256*$D$6) -> 14689387
D75: Diferencia CRC | E75: =E73-E74 -> 0.40888888
D76: Diferencia USD | E76: =E75/D6 -> 0.00079088758

Sheet FLUJO CAJA FEBRERO
D1: 42400
D4: Fecha de Elaboración: | E4: 45692
C6: Tasa de cambio: | D6: 502.98
D7: FEBRERO
D8: VALOR ₡ CRC | E8: VALOR USD
C9: BANCOS | D9: =SUBTOTAL(9,D10:D12) -> 14106479 | E9: =SUBTOTAL(9,E10:E12) -> 28045.805
C10: Bancos ₡ CRC | D10: ='BAC SAN JOSE COLONES '!$G$328 -> 6744908 | E10: =D10/$D$6 -> 13409.893
D11: -367470 | E11: =D11/$D$6 -> -730.58571
C12: Bancos USD | D12: =E12*$D$6 -> 7729040.8 | E12: ='BAC SAN JOSE USD'!$G$257 -> 15366.497
C13: CLIENTES | D13: =SUBTOTAL(9,D14:D14) -> 18873855 | E13: =SUBTOTAL(9,E14:E14) -> 37823.357
B14: Pagado | C14: Client: Remorfist-Factura Nro 165 | D14: =$E$14*CONVERSIONES!$C$297 -> 18873855 | E14: =CONVERSIONES!$L$289 -> 37823.357
C15: TOTAL INGRESOS | D15: =SUBTOTAL(9,D9:D14) -> 32980334 | E15: =SUBTOTAL(9,E9:E14) -> 65869.162
B18: CUENTAS X PAGAR MES | D18: DICIEMBRE
B19: Factura | C19: PROVEEDOR | D19: VALOR ₡ CRC | E19: VALOR USD | F19: Fecha vencimiento | G19: Estado | J19: KPI
C20: SEGURIDAD IGSS | D20: =SUBTOTAL(9,D21:D21) -> 5281620 | E20: =SUBTOTAL(9,E21:E21) -> 10500.656
B21: 777720250144439895-1 | C21: Pago CCSS Enero | D21: 5281620 | E21: =D21/$D$6 -> 10500.656 | F21: 45702 | G21: Cancelado | H21: =IF(OR(G21="Sin pagar",G21="Pagar"),_xlfn.SINGLE(NETWORKDAYS($E$4,F21,'Festivos CR'!$A$3:$A$29)),0) -> 0 | I21: =NETWORKDAYS($E$4,F21,'Festivos CR'!$A$3:$A$29) -> 9 | J21: =H21 -> 0
C22: IMPUESTOS | D22: =SUBTOTAL(9,D23:D24) -> 1173809 | E22: =SUBTOTAL(9,E23:E24) -> 2333.7091 | J22: =H22 -> 0
B23: 1034713384345 | C23: Retención en la fuente | D23: 1124960 | E23: =D23/$D$6 -> 2236.5899 | F23: 45702 | G23: Cancelado | H23: =IF(OR(G23="Sin pagar",G23="Pagar"),_xlfn.SINGLE(NETWORKDAYS($E$4,F23,'Festivos CR'!$A$3:$A$29)),0) -> 0 | I23: =NETWORKDAYS($E$4,F23,'Festivos CR'!$A$3:$A$29) -> 9 | J23: =H23 -> 0
B24: 1034404248911 | C24: Rte fte por declaración de remesas al exterior Facturación S&P Colombia a S&P CR Fact 5652 | D24: 48849 | E24: =D24/$D$6 -> 97.11917 | F24: 45704 | G24: Cancelado | H24: =IF(OR(G24="Sin pagar",G24="Pagar"),_xlfn.SINGLE(NETWORKDAYS($E$4,F24,'Festivos CR'!$A$3:$A$29)),0) -> 0 | I24: =NETWORKDAYS($E$4,F24,'Festivos CR'!$A$3:$A$29) -> 9 | J24: =H24 -> 0
C25: SERVICIOS PROFESIONALES -REPRESENTACIÓN LEGAL | D25: =SUBTOTAL(9,D26:D27) -> 77400.02 | E25: =SUBTOTAL(9,E26:E26) -> 124.0606 | J25: =H25 -> 0
B26: 25 | C26: Servicios profesionales Alejandro Echavarria Enero | D26: 62400 | E26: =D26/$D$6 -> 124.0606 | F26: 45714 | G26: Cancelado | H26: =IF(OR(G26="Sin pagar",G26="Pagar"),_xlfn.SINGLE(NETWORKDAYS($E$4,F26,'Festivos CR'!$A$3:$A$29)),0) -> 0 | I26: =NETWORKDAYS($E$4,F26,'Festivos CR'!$A$3:$A$29) -> 17 | J26: =H26 -> 0
B27: 26 | C27: Servicios profesionales Alejandro Echavarria Recolección de laptop de Advancio y envio a México por DHL | D27: 15000.02 | E27: =D27/$D$6 -> 29.822299 | F27: 45714 | G27: Cancelado | H27: =IF(OR(G27="Sin pagar",G27="Pagar"),_xlfn.SINGLE(NETWORKDAYS($E$4,F27,'Festivos CR'!$A$3:$A$29)),0) -> 0 | I27: =NETWORKDAYS($E$4,F27,'Festivos CR'!$A$3:$A$29) -> 17 | J27: =H27 -> 0
C28: GASTOS DE OFICINA | D28: =SUBTOTAL(9,D29:D29) -> 0 | E28: =SUBTOTAL(9,E29:E29) -> 0
B29: 62 | C29: Compra de café | D29: =77000*2*0 -> 0 | E29: =D29/$D$6 -> 0 | F29: 45716 | G29: Cancelado | H29: =IF(OR(G29="Sin pagar",G29="Pagar"),_xlfn.SINGLE(NETWORKDAYS($E$4,F29,'Festivos CR'!$A$3:$A$29)),0) -> 0 | I29: =NETWORKDAYS($E$4,F29,'Festivos CR'!$A$3:$A$29) -> 19 | J29: =H29 -> 0
C30: COBROS ENTRE SUCURSALES | D30: =SUBTOTAL(9,D31:D32) -> 0 | E30: =SUBTOTAL(9,E31:E32) -> 0
B31: 5483 | C31: Cobro S&P a sucursal Noviembre | D31: =E31*$D$6 -> 0 | E31: =440*0 -> 0 | F31: 45716 | G31: Cancelado | H31: =IF(OR(G31="Sin pagar",G31="Pagar"),_xlfn.SINGLE(NETWORKDAYS($E$4,F31,'Festivos CR'!$A$3:$A$29)),0) -> 0 | I31: =NETWORKDAYS($E$4,F31,'Festivos CR'!$A$3:$A$29) -> 19 | J31: =H31 -> 0
B32: 5582 | C32: Cobro S&P a sucursal Diciembre | D32: =E32*$D$6 -> 0 | E32: =440*0 -> 0 | F32: 45716 | G32: Cancelado | H32: =IF(OR(G32="Sin pagar",G32="Pagar"),_xlfn.SINGLE(NETWORKDAYS($E$4,F32,'Festivos CR'!$A$3:$A$29)),0) -> 0 | I32: =NETWORKDAYS($E$4,F32,'Festivos CR'!$A$3:$A$29) -> 19 | J32: =H32 -> 0
C33: COSTOS FINANCIEROS | D33: =SUBTOTAL(9,D34:D34) -> 36000 | E33: =SUBTOTAL(9,E34:E34) -> 71.573422
C34: COSTOS FINANCIEROS | D34: 36000 | E34: =D34/D6 -> 71.573422 | F34: 45716 | G34: Cancelado | H34: =IF(OR(G34="Sin pagar",G34="Pagar"),_xlfn.SINGLE(NETWORKDAYS($E$4,F34,'Festivos CR'!$A$3:$A$29)),0) -> 0 | I34: =NETWORKDAYS($E$4,F34,'Festivos CR'!$A$3:$A$29) -> 19 | J34: =H34 -> 0
C35: NÓMINAS | D35: =SUBTOTAL(9,D36:D42) -> 11643186 | E35: =SUBTOTAL(9,E36:E42) -> 23333.039
B36: CRC | C36: Jhoel González González-Starlight-CR003 | D36: 1612916.3 | E36: =$D$36/CONVERSIONES!$C$297 -> 3232.2973 | F36: 45716 | G36: Cancelado | H36: =IF(OR(G36="Sin pagar",G36="Pagar"),_xlfn.SINGLE(NETWORKDAYS($E$4,F36,'Festivos CR'!$A$3:$A$29)),0) -> 0 | I36: =NETWORKDAYS($E$4,F36,'Festivos CR'!$A$3:$A$29) -> 19 | J36: =H36 -> 0
B37: USD | C37: Jonathan Salazar García -Starlight-CR003 | D37: =E37*CONVERSIONES!$C$297 -> 1706909.3 | E37: 3420.66 | F37: 45716 | G37: Cancelado | H37: =IF(OR(G37="Sin pagar",G37="Pagar"),_xlfn.SINGLE(NETWORKDAYS($E$4,F37,'Festivos CR'!$A$3:$A$29)),0) -> 0 | I37: =NETWORKDAYS($E$4,F37,'Festivos CR'!$A$3:$A$29) -> 19 | J37: =H37 -> 0
B38: CRC | C38: Daniel Nazario Casto Vindas-Starlight-CR003 | D38: 1325079.4 | E38: =D38/CONVERSIONES!$C$297 -> 2655.4697 | F38: 45716 | G38: Cancelado | H38: =IF(OR(G38="Sin pagar",G38="Pagar"),_xlfn.SINGLE(NETWORKDAYS($E$4,F38,'Festivos CR'!$A$3:$A$29)),0) -> 0 | I38: =NETWORKDAYS($E$4,F38,'Festivos CR'!$A$3:$A$29) -> 19 | J38: =H38 -> 0
B39: CRC | C39: Priscilla Grace Polson -Aluminati-CR004 | D39: 1410537.3 | E39: =$D$39/CONVERSIONES!$C$297 -> 2826.7281 | F39: 45716 | G39: Cancelado | H39: =IF(OR(G39="Sin pagar",G39="Pagar"),_xlfn.SINGLE(NETWORKDAYS($E$4,F39,'Festivos CR'!$A$3:$A$29)),0) -> 0 | I39: =NETWORKDAYS($E$4,F39,'Festivos CR'!$A$3:$A$29) -> 19 | J39: =H39 -> 0
B40: CRC | C40: José Roberto Aguilar Barrante-Aluminati-CR004 | D40: 1410537.3 | E40: =$D$40/CONVERSIONES!$C$297 -> 2826.7281 | F40: 45716 | G40: Cancelado | H40: =IF(OR(G40="Sin pagar",G40="Pagar"),_xlfn.SINGLE(NETWORKDAYS($E$4,F40,'Festivos CR'!$A$3:$A$29)),0) -> 0 | I40: =NETWORKDAYS($E$4,F40,'Festivos CR'!$A$3:$A$29) -> 19 | J40: =H40 -> 0
B41: CRC | C41: Sheryl Gertrudiz Cambronero Estrada-lorez & Prada PPLC | D41: 786551.54 | E41: =$D$41/CONVERSIONES!$C$297 -> 1576.2556 | F41: 45716 | G41: Cancelado | H41: =IF(OR(G41="Sin pagar",G41="Pagar"),_xlfn.SINGLE(NETWORKDAYS($E$4,F41,'Festivos CR'!$A$3:$A$29)),0) -> 0 | I41: =NETWORKDAYS($E$4,F41,'Festivos CR'!$A$3:$A$29) -> 19 | J41: =H41 -> 0
B42: USD | C42: Tatiana Araya Pochet-CZ-CR006 | D42: =E42*CONVERSIONES!$C$297 -> 3390655.1 | E42: 6794.9 | F42: 45716 | G42: Cancelado | H42: =IF(OR(G42="Sin pagar",G42="Pagar"),_xlfn.SINGLE(NETWORKDAYS($E$4,F42,'Festivos CR'!$A$3:$A$29)),0) -> 0 | I42: =NETWORKDAYS($E$4,F42,'Festivos CR'!$A$3:$A$29) -> 19 | J42: =H42 -> 0
C43: IMPREVISTO | D43: =SUBTOTAL(9,D44:D44) -> 11000 | E43: =SUBTOTAL(9,E44:E44) -> 21.869657
C44: Envio de anticipo de dinero a Alejandro envío de un PC de Costa Rica a México | D44: 11000 | E44: =D44/$D$6 -> 21.869657 | F44: 45709 | G44: Cancelado | H44: =IF(OR(G44="Sin pagar",G44="Pagar"),_xlfn.SINGLE(NETWORKDAYS($E$4,F44,'Festivos CR'!$A$3:$A$29)),0) -> 0 | I44: =NETWORKDAYS($E$4,F44,'Festivos CR'!$A$3:$A$29) -> 14
C45: TOTAL EGRESOS | D45: =SUBTOTAL(9,D20:D44) -> 18223015 | E45: =SUBTOTAL(9,E20:E44) -> 36414.73
C47: SALDO | D47: =D15-D45 -> 14757319 | E47: =E15-E45 -> 29454.432
C48: % | D48: =IF($D$15=0,0,D47/$D$15) -> 0.44745813 | E48: =IF($E$15=0,0,E47/$E$15) -> 0.44716573
C52: Fecha Inicial | D52: Fecha Final | E52: Valor VALOR ₡ CRC | F52: Valor VALOR USD
C53: 45689 | D53: 45697 | E53: =SUMIFS($D$19:$D$50,$F$19:$F$50,">="&C53,$F$19:$F$50,"<="&D53,$G$19:$G$50,$D$66) -> 0 | F53: =SUMIFS($E$19:$E$50,$F$19:$F$50,">="&C53,$F$19:$F$50,"<="&D53,$G$19:$G$50,$D$66) -> 0
C54: 45698 | D54: 45704 | E54: =SUMIFS($D$19:$D$50,$F$19:$F$50,">="&C54,$F$19:$F$50,"<="&D54,$G$19:$G$50,$D$66) -> 0 | F54: =SUMIFS($E$19:$E$50,$F$19:$F$50,">="&C54,$F$19:$F$50,"<="&D54,$G$19:$G$50,$D$66) -> 0 | G54: CCSS e impuestos
C55: 45705 | D55: 45711 | E55: =SUMIFS($D$19:$D$50,$F$19:$F$50,">="&C55,$F$19:$F$50,"<="&D55,$G$19:$G$50,$D$66) -> 0 | F55: =SUMIFS($E$19:$E$50,$F$19:$F$50,">="&C55,$F$19:$F$50,"<="&D55,$G$19:$G$50,$D$66) -> 0
C56: 45712 | D56: 45716 | E56: =SUMIFS($D$19:$D$50,$F$19:$F$50,">="&C56,$F$19:$F$50,"<="&D56,$G$19:$G$50,$D$66) -> 0 | F56: =SUMIFS($E$19:$E$50,$F$19:$F$50,">="&C56,$F$19:$F$50,"<="&D56,$G$19:$G$50,$D$66) -> 0 | G56: Servicios Profesionales Alejandro Nóminas, Cobros entre sucursales y GMF
C57: TOTAL EGRESOS | E57: =SUM(E53:E56) -> 0 | F57: =SUM(F53:F56) -> 0
C60: Bancos | E60: ='BAC SAN JOSE COLONES '!$G$409+('BAC SAN JOSE USD'!$G$270*$D$6) -> 48129058 | F60: =('BAC SAN JOSE COLONES '!$G$409/$D$6)+'BAC SAN JOSE USD'!$G$270 -> 95687.817
C61: Gastos y costos Periodo 01 al 23 de febrero | E61: =SUM(E53:E55) -> 0 | F61: =SUM(F53:F55) -> 0
C62: Saldo | E62: =E60-E61 -> 48129058 | F62: =F60-F61 -> 95687.817
D65: Cancelado | E65: =SUMIFS($D$19:$D$50,$F$19:$F$50,">="&C53,$F$19:$F$50,"<="&$D$56,$G$19:$G$50,$D$65) -> 18223015 | F65: =SUMIFS($E$19:$E$50,$F$19:$F$50,">="&C53,$F$19:$F$50,"<="&$D$56,$G$19:$G$50,$D$65) -> 36414.73
D66: Sin Pagar | E66: =SUMIFS($D$19:$D$50,$F$19:$F$50,">="&C53,$F$19:$F$50,"<="&$D$56,$G$19:$G$50,$D$66) -> 0 | F66: =SUMIFS($E$19:$E$50,$F$19:$F$50,">="&C53,$F$19:$F$50,"<="&D56,$G$19:$G$50,$D$66) -> 0
D67: Total Egresos | E67: =SUM(E65:E66) -> 18223015 | F67: =SUM(F65:F66) -> 36414.73
D68: Validación | E68: =(D45-E67)*0 -> 0 | F68: =F67-E45 -> 0
D71: Flujo Caja | E71: =D47 -> 14757319
D72: Libro Bancos | E72: ='BAC SAN JOSE COLONES '!$G$341+('BAC SAN JOSE USD'!$G$264*'FLUJO CAJA FEBRERO'!$D$6) -> 14757319
D73: Diferencia CRC | E73: =E71-E72 -> 0.024787951
D74: Diferencia USD | E74: =E73/D6 -> 4.9282181e-05

Sheet FLUJO CAJA MARZO
D1: 42400
D4: Fecha de Elaboración: | E4: 45719
C6: Tasa de cambio: | D6: 513
D7: MARZO
D8: VALOR ₡ CRC | E8: VALOR USD
C9: BANCOS | D9: =SUBTOTAL(9,D10:D11) -> 15106179 | E9: =SUBTOTAL(9,E10:E11) -> 29446.743
C10: Bancos ₡ CRC | D10: ='BAC SAN JOSE COLONES '!$G$341+196137 -> 7287091.1 | E10: =D10/$D$6 -> 14204.856
C11: Bancos USD | D11: =E11*$D$6 -> 7819088.2 | E11: ='BAC SAN JOSE USD'!$G$264 -> 15241.887
C12: CLIENTES | D12: =SUBTOTAL(9,D13:D14) -> 31545126 | E12: =SUBTOTAL(9,E13:E14) -> 63856.53
B13: Pagado | C13: Client: Remorfist-Factura Nro 166 | D13: =$E$13*494 -> 22754924 | E13: 46062.6
B14: Pagado | C14: Client: Buttergloble PTE LTD-Factura Nro 167 | D14: =$E$14*494 -> 8790201.4 | E14: 17793.93
C15: TOTAL INGRESOS | D15: =SUBTOTAL(9,D9:D14) -> 46651305 | E15: =SUBTOTAL(9,E9:E14) -> 93303.273
B18: CUENTAS X PAGAR MES | D18: MARZO
B19: Factura | C19: PROVEEDOR | D19: VALOR ₡ CRC | E19: VALOR USD | F19: Fecha vencimiento | G19: Estado | J19: KPI
C20: SEGURIDAD IGSS | D20: =SUBTOTAL(9,D21:D21) -> 5350815 | E20: =SUBTOTAL(9,E21:E21) -> 10430.439
B21: 777720250245086683-1 | C21: Pago CCSS Enero | D21: 5350815 | E21: =D21/$D$6 -> 10430.439 | F21: 45726 | G21: Cancelado | H21: =IF(OR(G21="Sin pagar",G21="Pagar"),_xlfn.SINGLE(NETWORKDAYS($E$4,F21,'Festivos CR'!$A$3:$A$29)),0) -> 0 | I21: =NETWORKDAYS($E$4,F21,'Festivos CR'!$A$3:$A$29) -> 6 | J21: =H21 -> 0
C22: IMPUESTOS | D22: =SUBTOTAL(9,D23:D25) -> 1949921 | E22: =SUBTOTAL(9,E23:E25) -> 3801.0156 | J22: =H22 -> 0
B23: 1034713465317 | C23: Retención en la fuente | D23: 1157777 | E23: =D23/$D$6 -> 2256.8752 | F23: 45726 | G23: Cancelado | H23: =IF(OR(G23="Sin pagar",G23="Pagar"),_xlfn.SINGLE(NETWORKDAYS($E$4,F23,'Festivos CR'!$A$3:$A$29)),0) -> 0 | I23: =NETWORKDAYS($E$4,F23,'Festivos CR'!$A$3:$A$29) -> 6 | J23: =H23 -> 0
B24: 1034713465317 | C24: Rte fte por declaración de remesas al exterior Facturación S&P Colombia a S&P CR Fact 5728 | D24: 82060 | E24: =D24/$D$6 -> 159.96101 | F24: 45726 | G24: Cancelado | H24: =IF(OR(G24="Sin pagar",G24="Pagar"),_xlfn.SINGLE(NETWORKDAYS($E$4,F24,'Festivos CR'!$A$3:$A$29)),0) -> 0 | I24: =NETWORKDAYS($E$4,F24,'Festivos CR'!$A$3:$A$29) -> 6 | J24: =H24 -> 0
B25: 1012679722582 | C25: Rte fte por declaración de remesas al exterior Facturación S&P Colombia a S&P CR Fact 5728 | D25: 710084 | E25: =D25/$D$6 -> 1384.1793 | F25: 45733 | G25: Cancelado | H25: =IF(OR(G25="Sin pagar",G25="Pagar"),_xlfn.SINGLE(NETWORKDAYS($E$4,F25,'Festivos CR'!$A$3:$A$29)),0) -> 0 | I25: =NETWORKDAYS($E$4,F25,'Festivos CR'!$A$3:$A$29) -> 11 | J25: =H25 -> 0
C26: SERVICIOS PROFESIONALES -REPRESENTACIÓN LEGAL | D26: =SUBTOTAL(9,D28:D28) -> 62400 | E26: =SUBTOTAL(9,E28:E28) -> 121.63743 | J26: =H26 -> 0
B27: 298 | C27: Honorarios profesionales -revisión migratoria Cristian Chacon Castillo | D27: 28823 | E27: =D27/510.14 -> 56.500176 | F27: 45730 | G27: Cancelado | H27: =IF(OR(G27="Sin pagar",G27="Pagar"),_xlfn.SINGLE(NETWORKDAYS($E$4,F27,'Festivos CR'!$A$3:$A$29)),0) -> 0 | I27: =NETWORKDAYS($E$4,F27,'Festivos CR'!$A$3:$A$29) -> 10 | J27: =H27 -> 0
B28: 28 | C28: Servicios profesionales Alejandro Echavarria Enero | D28: 62400 | E28: =D28/$D$6 -> 121.63743 | F28: 45743 | G28: Cancelado | H28: =IF(OR(G28="Sin pagar",G28="Pagar"),_xlfn.SINGLE(NETWORKDAYS($E$4,F28,'Festivos CR'!$A$3:$A$29)),0) -> 0 | I28: =NETWORKDAYS($E$4,F28,'Festivos CR'!$A$3:$A$29) -> 19 | J28: =H28 -> 0
C29: GASTOS DE OFICINA | D29: =SUBTOTAL(9,D30:D30) -> 0 | E29: =SUBTOTAL(9,E30:E30) -> 0
B30: 62 | C30: Compra de café | D30: =77000*3*0 -> 0 | E30: =D30/$D$6 -> 0 | F30: 45747 | G30: Cancelado | H30: =IF(OR(G30="Sin pagar",G30="Pagar"),_xlfn.SINGLE(NETWORKDAYS($E$4,F30,'Festivos CR'!$A$3:$A$29)),0) -> 0 | I30: =NETWORKDAYS($E$4,F30,'Festivos CR'!$A$3:$A$29) -> 21 | J30: =H30 -> 0
C31: COBROS ENTRE SUCURSALES | D31: =SUBTOTAL(9,D32:D32) -> 0 | E31: =SUBTOTAL(9,E32:E32) -> 0
D32: =E32*$D$6 -> 0 | E32: =440*0 -> 0 | F32: 45747 | G32: Cancelado | H32: =IF(OR(G32="Sin pagar",G32="Pagar"),_xlfn.SINGLE(NETWORKDAYS($E$4,F32,'Festivos CR'!$A$3:$A$29)),0) -> 0 | I32: =NETWORKDAYS($E$4,F32,'Festivos CR'!$A$3:$A$29) -> 21 | J32: =H32 -> 0
C33: COSTOS FINANCIEROS | D33: =SUBTOTAL(9,D34:D34) -> 34211.97 | E33: =SUBTOTAL(9,E34:E34) -> 66.69
C34: COSTOS FINANCIEROS | D34: =E34*D6 -> 34211.97 | E34: =66.69 -> 66.69 | F34: 45747 | G34: Cancelado | H34: =IF(OR(G34="Sin pagar",G34="Pagar"),_xlfn.SINGLE(NETWORKDAYS($E$4,F34,'Festivos CR'!$A$3:$A$29)),0) -> 0 | I34: =NETWORKDAYS($E$4,F34,'Festivos CR'!$A$3:$A$29) -> 21 | J34: =H34 -> 0
C35: NÓMINAS | D35: =SUBTOTAL(9,D36:D44) -> 18827477 | E35: =SUBTOTAL(9,E36:E44) -> 30009.294
B36: CRC | C36: Jhoel González González-Starlight-CR003 | D36: 1612916.3 | E36: =$D$36/CONVERSIONES!$C$297 -> 3232.2973 | F36: 45744 | G36: Cancelado | H36: =IF(OR(G36="Sin pagar",G36="Pagar"),_xlfn.SINGLE(NETWORKDAYS($E$4,F36,'Festivos CR'!$A$3:$A$29)),0) -> 0 | I36: =NETWORKDAYS($E$4,F36,'Festivos CR'!$A$3:$A$29) -> 20 | J36: =H36 -> 0
B37: USD | C37: Jonathan Salazar García -Starlight-CR003 | D37: =E37*CONVERSIONES!$C$297 -> 1706909.3 | E37: 3420.66 | F37: 45744 | G37: Cancelado | H37: =IF(OR(G37="Sin pagar",G37="Pagar"),_xlfn.SINGLE(NETWORKDAYS($E$4,F37,'Festivos CR'!$A$3:$A$29)),0) -> 0 | I37: =NETWORKDAYS($E$4,F37,'Festivos CR'!$A$3:$A$29) -> 20 | J37: =H37 -> 0
B38: CRC | C38: Daniel Nazario Casto Vindas-Starlight-CR003 | D38: 1325079.4 | E38: =D38/CONVERSIONES!$C$297 -> 2655.4697 | F38: 45744 | G38: Cancelado | H38: =IF(OR(G38="Sin pagar",G38="Pagar"),_xlfn.SINGLE(NETWORKDAYS($E$4,F38,'Festivos CR'!$A$3:$A$29)),0) -> 0 | I38: =NETWORKDAYS($E$4,F38,'Festivos CR'!$A$3:$A$29) -> 20 | J38: =H38 -> 0
B39: CRC | C39: Priscilla Grace Polson -Aluminati-CR004 | D39: 1410537.3 | E39: =$D$39/CONVERSIONES!$C$297 -> 2826.7281 | F39: 45744 | G39: Cancelado | H39: =IF(OR(G39="Sin pagar",G39="Pagar"),_xlfn.SINGLE(NETWORKDAYS($E$4,F39,'Festivos CR'!$A$3:$A$29)),0) -> 0 | I39: =NETWORKDAYS($E$4,F39,'Festivos CR'!$A$3:$A$29) -> 20 | J39: =H39 -> 0
B40: CRC | C40: José Roberto Aguilar Barrante-Aluminati-CR004 | D40: 1410537.3 | E40: =$D$40/CONVERSIONES!$C$297 -> 2826.7281 | F40: 45744 | G40: Cancelado | H40: =IF(OR(G40="Sin pagar",G40="Pagar"),_xlfn.SINGLE(NETWORKDAYS($E$4,F40,'Festivos CR'!$A$3:$A$29)),0) -> 0 | I40: =NETWORKDAYS($E$4,F40,'Festivos CR'!$A$3:$A$29) -> 20 | J40: =H40 -> 0
B41: CRC | C41: Sheryl Gertrudiz Cambronero Estrada-lorez & Prada PPLC | D41: 786551.54 | E41: =$D$41/CONVERSIONES!$C$297 -> 1576.2556 | F41: 45744 | G41: Cancelado | H41: =IF(OR(G41="Sin pagar",G41="Pagar"),_xlfn.SINGLE(NETWORKDAYS($E$4,F41,'Festivos CR'!$A$3:$A$29)),0) -> 0 | I41: =NETWORKDAYS($E$4,F41,'Festivos CR'!$A$3:$A$29) -> 20 | J41: =H41 -> 0
B42: USD | C42: Tatiana Araya Pochet-CZ-CR006 | D42: =E42*CONVERSIONES!$C$297 -> 3390655.1 | E42: 6794.9 | F42: 45744 | G42: Cancelado | H42: =IF(OR(G42="Sin pagar",G42="Pagar"),_xlfn.SINGLE(NETWORKDAYS($E$4,F42,'Festivos CR'!$A$3:$A$29)),0) -> 0 | I42: =NETWORKDAYS($E$4,F42,'Festivos CR'!$A$3:$A$29) -> 20 | J42: =H42 -> 0
B43: USD | C43: Bernal Fallas Barboza | D43: =E43*CONVERSIONES!$C$297 -> 2544900 | E43: 5100 | F43: 45744 | G43: Cancelado | H43: =IF(OR(G43="Sin pagar",G43="Pagar"),_xlfn.SINGLE(NETWORKDAYS($E$4,F43,'Festivos CR'!$A$3:$A$29)),0) -> 0 | I43: =NETWORKDAYS($E$4,F43,'Festivos CR'!$A$3:$A$29) -> 20 | J43: =H43 -> 0
B44: CRC | C44: Ricardo Manuel Garro Ruiz-Bipo | D44: 4639390.9 | E44: =$D$41/CONVERSIONES!$C$297 -> 1576.2556 | F44: 45744 | G44: Cancelado | H44: =IF(OR(G44="Sin pagar",G44="Pagar"),_xlfn.SINGLE(NETWORKDAYS($E$4,F44,'Festivos CR'!$A$3:$A$29)),0) -> 0 | I44: =NETWORKDAYS($E$4,F44,'Festivos CR'!$A$3:$A$29) -> 20 | J44: =H44 -> 0
C45: IMPREVISTO | D45: =SUBTOTAL(9,D46:D46) -> 0 | E45: =SUBTOTAL(9,E46:E46) -> 0
D46: 0 | E46: =D46/$D$6 -> 0 | F46: 45747 | G46: Cancelado | H46: =IF(OR(G46="Sin pagar",G46="Pagar"),_xlfn.SINGLE(NETWORKDAYS($E$4,F46,'Festivos CR'!$A$3:$A$29)),0) -> 0 | I46: =NETWORKDAYS($E$4,F46,'Festivos CR'!$A$3:$A$29) -> 21
C47: TOTAL EGRESOS | D47: =SUBTOTAL(9,D20:D46) -> 26253648 | E47: =SUBTOTAL(9,E20:E46) -> 44485.576
C49: SALDO | D49: =D15-D47 -> 20397657 | E49: =E15-E47 -> 48817.697
C50: % | D50: =IF($D$15=0,0,D49/$D$15) -> 0.43723658 | E50: =IF($E$15=0,0,E49/$E$15) -> 0.52321527
C54: Fecha Inicial | D54: Fecha Final | E54: Valor VALOR ₡ CRC | F54: Valor VALOR USD
C55: 45717 | D55: 45725 | E55: =SUMIFS($D$19:$D$52,$F$19:$F$52,">="&C55,$F$19:$F$52,"<="&D55,$G$19:$G$52,$D$68) -> 0 | F55: =SUMIFS($E$19:$E$52,$F$19:$F$52,">="&C55,$F$19:$F$52,"<="&D55,$G$19:$G$52,$D$68) -> 0
C56: 45726 | D56: 45732 | E56: =SUMIFS($D$19:$D$52,$F$19:$F$52,">="&C56,$F$19:$F$52,"<="&D56,$G$19:$G$52,$D$68) -> 0 | F56: =SUMIFS($E$19:$E$52,$F$19:$F$52,">="&C56,$F$19:$F$52,"<="&D56,$G$19:$G$52,$D$68) -> 0 | G56: CCSS e impuestos
C57: 45733 | D57: 45739 | E57: =SUMIFS($D$19:$D$52,$F$19:$F$52,">="&C57,$F$19:$F$52,"<="&D57,$G$19:$G$52,$D$68) -> 0 | F57: =SUMIFS($E$19:$E$52,$F$19:$F$52,">="&C57,$F$19:$F$52,"<="&D57,$G$19:$G$52,$D$68) -> 0 | G57: Servicios Alejandro
C58: 45740 | D58: 45747 | E58: =SUMIFS($D$19:$D$52,$F$19:$F$52,">="&C58,$F$19:$F$52,"<="&D58,$G$19:$G$52,$D$68) -> 0 | F58: =SUMIFS($E$19:$E$52,$F$19:$F$52,">="&C58,$F$19:$F$52,"<="&D58,$G$19:$G$52,$D$68) -> 0 | G58: Nóminas, GMF
C59: TOTAL EGRESOS | E59: =SUM(E55:E58) -> 0 | F59: =SUM(F55:F58) -> 0
C62: Bancos | E62: ='BAC SAN JOSE COLONES '!$G$409+('BAC SAN JOSE USD'!$G$270*$D$6) -> 48910937 | F62: =('BAC SAN JOSE COLONES '!$G$409/$D$6)+'BAC SAN JOSE USD'!$G$270 -> 95342.956
C63: Gastos y costos Periodo 01 al 23 de Marzo | E63: =SUM(E55:E57) -> 0 | F63: =SUM(F55:F57) -> 0
C64: Saldo | E64: =E62-E63 -> 48910937 | F64: =F62-F63 -> 95342.956
D67: Cancelado | E67: =SUMIFS($D$19:$D$52,$F$19:$F$52,">="&C55,$F$19:$F$52,"<="&$D$58,$G$19:$G$52,$D$67) -> 26253648 | F67: =SUMIFS($E$19:$E$52,$F$19:$F$52,">="&C55,$F$19:$F$52,"<="&$D$58,$G$19:$G$52,$D$67) -> 44485.576
D68: Sin Pagar | E68: =SUMIFS($D$19:$D$52,$F$19:$F$52,">="&C55,$F$19:$F$52,"<="&$D$58,$G$19:$G$52,$D$68) -> 0 | F68: =SUMIFS($E$19:$E$52,$F$19:$F$52,">="&C55,$F$19:$F$52,"<="&D58,$G$19:$G$52,$D$68) -> 0
D69: Total Egresos | E69: =SUM(E67:E68) -> 26253648 | F69: =SUM(F67:F68) -> 44485.576
D70: Validación | E70: =(D47-E69)*0 -> 0 | F70: =F69-E47 -> 0
D73: Flujo Caja | E73: =$D$49 -> 20397657
D74: Libro Bancos | E74: ='BAC SAN JOSE COLONES '!$G$358+('BAC SAN JOSE USD'!$G$276*$D$6) -> 20397657
D75: Diferencia CRC | E75: =E73-E74 -> 0.13
D76: Diferencia USD | E76: =E75/D6 -> 0.0002534113

Sheet FLUJO CAJA ABRIL 2025
D1: 42400
D4: Fecha de Elaboración: | E4: 45748
C6: Tasa de cambio: | D6: 499
D7: ABRIL
D8: VALOR ₡ CRC | E8: VALOR USD
C9: BANCOS | D9: =SUBTOTAL(9,D10:D11) -> 20181251 | E9: =SUBTOTAL(9,E10:E11) -> 40443.388
C10: Bancos ₡ CRC | D10: ='BAC SAN JOSE COLONES '!G358 -> 12467915 | E10: =D10/$D$6 -> 24985.801
C11: Bancos USD | D11: =E11*$D$6 -> 7713336.1 | E11: ='BAC SAN JOSE USD'!$G$276 -> 15457.587
C12: CLIENTES | D12: =SUBTOTAL(9,D13:D15) -> 38919096 | E12: =SUBTOTAL(9,E13:E15) -> 77888.902
B13: Pagado | C13: Client: Remorfist-Factura Nro 168 | D13: =E13*'DIFERENCIA CAMBI'!$O$96 -> 30128452 | E13: =SUM('DIFERENCIA CAMBI'!$G$96:$G$102) -> 60377.66
B14: Pagado | C14: Client: Buttergloble PTE LTD-Factura Nro 169 | D14: =E14*502 -> 8790643.2 | E14: ='DIFERENCIA CAMBI'!N103 -> 17511.241
B15: Sin Pagar | C15: Client: Advancio-Factura Nro 170 | D15: =(E15*'DIFERENCIA CAMBI'!$E$96)*0 -> 0 | E15: =400*0 -> 0
C16: TOTAL INGRESOS | D16: =SUBTOTAL(9,D9:D15) -> 59100346 | E16: =SUBTOTAL(9,E9:E15) -> 118332.29
B19: CUENTAS X PAGAR MES | D19: ABRIL
B20: Factura | C20: PROVEEDOR | D20: VALOR ₡ CRC | E20: VALOR USD | F20: Fecha vencimiento | G20: Estado | J20: KPI
C21: SEGURIDAD IGSS | D21: =SUBTOTAL(9,D22:D22) -> 8888377 | E21: =SUBTOTAL(9,E22:E22) -> 17812.379
B22: 777720250245086683-1 | C22: Pago CCSS Marzo | D22: 8888377 | E22: =D22/$D$6 -> 17812.379 | F22: 45761 | G22: Cancelado | H22: =IF(OR(G22="Sin pagar",G22="Pagar"),_xlfn.SINGLE(NETWORKDAYS($E$4,F22,'Festivos CR'!$A$3:$A$29)),0) -> 0 | I22: =NETWORKDAYS($E$4,F22,'Festivos CR'!$A$3:$A$29) -> 9 | J22: =H22 -> 0
C23: IMPUESTOS | D23: =SUBTOTAL(9,D24:D25) -> 2675281.8 | E23: =SUBTOTAL(9,E24:E25) -> 5361.2862 | J23: =H23 -> 0
B24: 1034713627744 | C24: Retención en la fuente | D24: 2596681.8 | E24: =D24/$D$6 -> 5203.7711 | F24: 45761 | G24: Cancelado | H24: =IF(OR(G24="Sin pagar",G24="Pagar"),_xlfn.SINGLE(NETWORKDAYS($E$4,F24,'Festivos CR'!$A$3:$A$29)),0) -> 0 | I24: =NETWORKDAYS($E$4,F24,'Festivos CR'!$A$3:$A$29) -> 9 | J24: =H24 -> 0
B25: 1034404279702 | C25: Rte fte por declaración de remesas al exterior Facturación S&P Colombia a S&P CR Fact 5811 | D25: 78600 | E25: =D25/$D$6 -> 157.51503 | F25: 45761 | G25: Cancelado | H25: =IF(OR(G25="Sin pagar",G25="Pagar"),_xlfn.SINGLE(NETWORKDAYS($E$4,F25,'Festivos CR'!$A$3:$A$29)),0) -> 0 | I25: =NETWORKDAYS($E$4,F25,'Festivos CR'!$A$3:$A$29) -> 9 | J25: =H25 -> 0
C26: SERVICIOS PROFESIONALES -REPRESENTACIÓN LEGAL | D26: =SUBTOTAL(9,D27:D27) -> 21456 | E26: =SUBTOTAL(9,E27:E27) -> 42.997996 | J26: =H26 -> 0
B27: 29 | C27: Servicios profesionales Alejandro Echavarria Enero | D27: 21456 | E27: =D27/$D$6 -> 42.997996 | F27: 45762 | G27: Cancelado | H27: =IF(OR(G27="Sin pagar",G27="Pagar"),_xlfn.SINGLE(NETWORKDAYS($E$4,F27,'Festivos CR'!$A$3:$A$29)),0) -> 0 | I27: =NETWORKDAYS($E$4,F27,'Festivos CR'!$A$3:$A$29) -> 10 | J27: =H27 -> 0
C28: GASTOS DE OFICINA | D28: =SUBTOTAL(9,D29:D29) -> 0 | E28: =SUBTOTAL(9,E29:E29) -> 0
B29: 62 | C29: Compra de café | D29: =77000*4*0 -> 0 | E29: =D29/$D$6 -> 0 | F29: 45777 | G29: Cancelado | H29: =IF(OR(G29="Sin pagar",G29="Pagar"),_xlfn.SINGLE(NETWORKDAYS($E$4,F29,'Festivos CR'!$A$3:$A$29)),0) -> 0 | I29: =NETWORKDAYS($E$4,F29,'Festivos CR'!$A$3:$A$29) -> 19 | J29: =H29 -> 0
C30: COBROS ENTRE SUCURSALES | D30: =SUBTOTAL(9,D31:D31) -> 0 | E30: =SUBTOTAL(9,E31:E31) -> 0
D31: =E31*$D$6 -> 0 | E31: =440*0 -> 0 | F31: 45747 | G31: Cancelado | H31: =IF(OR(G31="Sin pagar",G31="Pagar"),_xlfn.SINGLE(NETWORKDAYS($E$4,F31,'Festivos CR'!$A$3:$A$29)),0) -> 0 | I31: =NETWORKDAYS($E$4,F31,'Festivos CR'!$A$3:$A$29) -> -2 | J31: =H31 -> 0
C32: COSTOS FINANCIEROS | D32: =SUBTOTAL(9,D33:D33) -> 99263.25 | E32: =SUBTOTAL(9,E33:E33) -> 0.75
C33: COSTOS FINANCIEROS | D33: =374.25+98889 -> 99263.25 | E33: 0.75 | F33: 45777 | G33: Cancelado | H33: =IF(OR(G33="Sin pagar",G33="Pagar"),_xlfn.SINGLE(NETWORKDAYS($E$4,F33,'Festivos CR'!$A$3:$A$29)),0) -> 0 | I33: =NETWORKDAYS($E$4,F33,'Festivos CR'!$A$3:$A$29) -> 19 | J33: =H33 -> 0
C34: NÓMINAS | D34: =SUBTOTAL(9,D35:D43) -> 22389696 | E34: =SUBTOTAL(9,E35:E43) -> 37134.654
B35: CRC | C35: Jhoel González González-Starlight-CR003 | D35: 1612916.3 | E35: =$D$35/CONVERSIONES!$C$297 -> 3232.2973 | F35: 45775 | G35: Cancelado | H35: =IF(OR(G35="Sin pagar",G35="Pagar"),_xlfn.SINGLE(NETWORKDAYS($E$4,F35,'Festivos CR'!$A$3:$A$29)),0) -> 0 | I35: =NETWORKDAYS($E$4,F35,'Festivos CR'!$A$3:$A$29) -> 17 | J35: =H35 -> 0
B36: USD | C36: Jonathan Salazar García -Starlight-CR003 | D36: =E36*CONVERSIONES!$C$297 -> 1706909.3 | E36: 3420.66 | F36: 45775 | G36: Cancelado | H36: =IF(OR(G36="Sin pagar",G36="Pagar"),_xlfn.SINGLE(NETWORKDAYS($E$4,F36,'Festivos CR'!$A$3:$A$29)),0) -> 0 | I36: =NETWORKDAYS($E$4,F36,'Festivos CR'!$A$3:$A$29) -> 17 | J36: =H36 -> 0
B37: CRC | C37: Daniel Nazario Casto Vindas-Starlight-CR003 | D37: 1325079.4 | E37: =D37/CONVERSIONES!$C$297 -> 2655.4697 | F37: 45775 | G37: Cancelado | H37: =IF(OR(G37="Sin pagar",G37="Pagar"),_xlfn.SINGLE(NETWORKDAYS($E$4,F37,'Festivos CR'!$A$3:$A$29)),0) -> 0 | I37: =NETWORKDAYS($E$4,F37,'Festivos CR'!$A$3:$A$29) -> 17 | J37: =H37 -> 0
B38: CRC | C38: Priscilla Grace Polson -Aluminati-CR004 | D38: 1410537.3 | E38: =$D$38/CONVERSIONES!$C$297 -> 2826.7281 | F38: 45776 | G38: Cancelado | H38: =IF(OR(G38="Sin pagar",G38="Pagar"),_xlfn.SINGLE(NETWORKDAYS($E$4,F38,'Festivos CR'!$A$3:$A$29)),0) -> 0 | I38: =NETWORKDAYS($E$4,F38,'Festivos CR'!$A$3:$A$29) -> 18 | J38: =H38 -> 0
B39: CRC | C39: José Roberto Aguilar Barrante-Aluminati-CR004 | D39: 1410537.3 | E39: =$D$39/CONVERSIONES!$C$297 -> 2826.7281 | F39: 45776 | G39: Cancelado | H39: =IF(OR(G39="Sin pagar",G39="Pagar"),_xlfn.SINGLE(NETWORKDAYS($E$4,F39,'Festivos CR'!$A$3:$A$29)),0) -> 0 | I39: =NETWORKDAYS($E$4,F39,'Festivos CR'!$A$3:$A$29) -> 18 | J39: =H39 -> 0
B40: CRC | C40: Sheryl Gertrudiz Cambronero Estrada-lorez & Prada PPLC | D40: 786551.54 | E40: =$D$40/CONVERSIONES!$C$297 -> 1576.2556 | F40: 45776 | G40: Cancelado | H40: =IF(OR(G40="Sin pagar",G40="Pagar"),_xlfn.SINGLE(NETWORKDAYS($E$4,F40,'Festivos CR'!$A$3:$A$29)),0) -> 0 | I40: =NETWORKDAYS($E$4,F40,'Festivos CR'!$A$3:$A$29) -> 18 | J40: =H40 -> 0
B41: USD | C41: Tatiana Araya Pochet-CZ-CR006 | D41: =E41*CONVERSIONES!$C$297 -> 6961748.6 | E41: 13951.4 | F41: 45777 | G41: Cancelado | H41: =IF(OR(G41="Sin pagar",G41="Pagar"),_xlfn.SINGLE(NETWORKDAYS($E$4,F41,'Festivos CR'!$A$3:$A$29)),0) -> 0 | I41: =NETWORKDAYS($E$4,F41,'Festivos CR'!$A$3:$A$29) -> 19 | J41: =H41 -> 0
B42: USD | C42: Bernal Fallas Barboza | D42: =E42*CONVERSIONES!$C$297 -> 2529361.1 | E42: 5068.86 | F42: 45775 | G42: Cancelado | H42: =IF(OR(G42="Sin pagar",G42="Pagar"),_xlfn.SINGLE(NETWORKDAYS($E$4,F42,'Festivos CR'!$A$3:$A$29)),0) -> 0 | I42: =NETWORKDAYS($E$4,F42,'Festivos CR'!$A$3:$A$29) -> 17 | J42: =H42 -> 0
B43: CRC | C43: Ricardo Manuel Garro Ruiz-Bipo | D43: 4646054.9 | E43: =$D$40/CONVERSIONES!$C$297 -> 1576.2556 | F43: 45775 | G43: Cancelado | H43: =IF(OR(G43="Sin pagar",G43="Pagar"),_xlfn.SINGLE(NETWORKDAYS($E$4,F43,'Festivos CR'!$A$3:$A$29)),0) -> 0 | I43: =NETWORKDAYS($E$4,F43,'Festivos CR'!$A$3:$A$29) -> 17 | J43: =H43 -> 0
C44: IMPREVISTO | D44: =SUBTOTAL(9,D45:D45) -> 0 | E44: =SUBTOTAL(9,E45:E45) -> 0
D45: 0 | E45: =D45/$D$6 -> 0 | F45: 45747 | G45: Cancelado | H45: =IF(OR(G45="Sin pagar",G45="Pagar"),_xlfn.SINGLE(NETWORKDAYS($E$4,F45,'Festivos CR'!$A$3:$A$29)),0) -> 0 | I45: =NETWORKDAYS($E$4,F45,'Festivos CR'!$A$3:$A$29) -> -2
C46: TOTAL EGRESOS | D46: =SUBTOTAL(9,D21:D45) -> 34074074 | E46: =SUBTOTAL(9,E21:E45) -> 60352.067
C48: SALDO | D48: =D16-D46 -> 25026272 | E48: =E16-E46 -> 57980.223
C49: % | D49: =IF($D$16=0,0,D48/$D$16) -> 0.42345391 | E49: =IF($E$16=0,0,E48/$E$16) -> 0.48997803
C53: Fecha Inicial | D53: Fecha Final | E53: Valor VALOR ₡ CRC | F53: Valor VALOR USD
C54: 45748 | D54: 45753 | E54: =SUMIFS($D$20:$D$51,$F$20:$F$51,">="&C54,$F$20:$F$51,"<="&D54,$G$20:$G$51,$D$68) -> 0 | F54: =SUMIFS($E$20:$E$51,$F$20:$F$51,">="&C54,$F$20:$F$51,"<="&D54,$G$20:$G$51,$D$68) -> 0
C55: 45754 | D55: 45760 | E55: =SUMIFS($D$20:$D$51,$F$20:$F$51,">="&C55,$F$20:$F$51,"<="&D55,$G$20:$G$51,$D$68) -> 0 | F55: =SUMIFS($E$20:$E$51,$F$20:$F$51,">="&C55,$F$20:$F$51,"<="&D55,$G$20:$G$51,$D$68) -> 0 | G55: CCSS e impuestos | J55: Feriado el viernes 11 de abril
C56: 45761 | D56: 45767 | E56: =SUMIFS($D$20:$D$51,$F$20:$F$51,">="&C56,$F$20:$F$51,"<="&D56,$G$20:$G$51,$D$68) -> 0 | F56: =SUMIFS($E$20:$E$51,$F$20:$F$51,">="&C56,$F$20:$F$51,"<="&D56,$G$20:$G$51,$D$68) -> 0
C57: 45768 | D57: 45774 | E57: =SUMIFS($D$20:$D$51,$F$20:$F$51,">="&C57,$F$20:$F$51,"<="&D57,$G$20:$G$51,$D$68) -> 0 | F57: =SUMIFS($E$20:$E$51,$F$20:$F$51,">="&C57,$F$20:$F$51,"<="&D57,$G$20:$G$51,$D$68) -> 0
C58: 45775 | D58: 45777 | E58: =SUMIFS($D$20:$D$51,$F$20:$F$51,">="&C58,$F$20:$F$51,"<="&D58,$G$20:$G$51,$D$68) -> 0 | F58: =SUMIFS($E$20:$E$51,$F$20:$F$51,">="&C58,$F$20:$F$51,"<="&D58,$G$20:$G$51,$D$68) -> 0 | G58: Nóminas, GMF, Serv Alejandro
C59: TOTAL EGRESOS | E59: =SUM(E54:E58) -> 0 | F59: =SUM(F54:F58) -> 0
C62: Bancos | E62: ='BAC SAN JOSE COLONES '!G358+('BAC SAN JOSE USD'!G276*'FLUJO CAJA ABRIL 2025'!$D$6) -> 20181251 | F62: =('BAC SAN JOSE COLONES '!G358/$D$6)+'BAC SAN JOSE USD'!$G$276 -> 40443.388
C63: Gastos y costos Periodo 01 al 27 de Abril | E63: =SUM(E54:E57) -> 0 | F63: =SUM(F54:F57) -> 0
C64: Saldo | E64: =E62-E63 -> 20181251 | F64: =F62-F63 -> 40443.388
D67: Cancelado | E67: =SUMIFS($D$20:$D$51,$F$20:$F$51,">="&C54,$F$20:$F$51,"<="&$D$58,$G$20:$G$51,$D$67) -> 34074074 | F67: =SUMIFS($E$20:$E$51,$F$20:$F$51,">="&C54,$F$20:$F$51,"<="&$D$58,$G$20:$G$51,$D$67) -> 60352.067
D68: Sin Pagar | E68: =SUMIFS($D$20:$D$51,$F$20:$F$51,">="&C54,$F$20:$F$51,"<="&$D$58,$G$20:$G$51,$D$68) -> 0 | F68: =SUMIFS($E$20:$E$51,$F$20:$F$51,">="&C54,$F$20:$F$51,"<="&D58,$G$20:$G$51,$D$68) -> 0
D69: Total Egresos | E69: =SUM(E67:E68) -> 34074074 | F69: =SUM(F67:F68) -> 60352.067
D70: Validación | E70: =(D46-E69)*0 -> 0 | F70: =F69-E46 -> 0
D74: Flujo Caja | E74: =$D$48 -> 25026272
D75: Libro Bancos | E75: ='BAC SAN JOSE COLONES '!$G$376+('BAC SAN JOSE USD'!$G$294*$D$6) -> 25026272
D76: Diferencia CRC | E76: =E74-E75 -> 0.42666666
D77: Diferencia USD | E77: =E76/D6 -> 0.0008550434

Sheet FLUJO CAJA MAYO 2025
D1: 42400
D4: Fecha de Elaboración: | E4: 45778
C6: Tasa de cambio: | D6: 503
D7: MAYO
D8: VALOR ₡ CRC | E8: VALOR USD
C9: BANCOS | D9: =SUBTOTAL(9,D10:D11) -> 32252773 | E9: =SUBTOTAL(9,E10:E11) -> 64120.822
C10: Bancos ₡ CRC | D10: ='BAC SAN JOSE COLONES '!$G$373 -> 907177.81 | E10: =$D$10/$D$6 -> 1803.5344
C11: Bancos USD | D11: =E11*$D$6 -> 31345596 | E11: ='BAC SAN JOSE USD'!$G$290 -> 62317.287
C12: CLIENTES | D12: =SUBTOTAL(9,D13:D14) -> 31306547 | E12: =SUBTOTAL(9,E13:E14) -> 62363.64
B13: Pagado | C13: Client: Remorfist-Factura Nro 171-172 (Daniel Castro) | D13: =$E$13*CONVERSIONES!$C$396 -> 22485288 | E13: ='BAC SAN JOSE USD'!$E$295 -> 44791.41
B14: Pagado | C14: Client: Buttergloble PTE LTD-Factura Nro 173 | D14: =$E$14*CONVERSIONES!$C$413 -> 8821259.5 | E14: ='BAC SAN JOSE USD'!$E$297 -> 17572.23
C15: TOTAL INGRESOS | D15: =SUBTOTAL(9,D9:D14) -> 63559321 | E15: =SUBTOTAL(9,E9:E14) -> 126484.46
B18: CUENTAS X PAGAR MES | D18: MAYO
B19: Factura | C19: PROVEEDOR | D19: VALOR ₡ CRC | E19: VALOR USD | F19: Fecha vencimiento | G19: Estado | J19: KPI
C20: SEGURIDAD IGSS | D20: =SUBTOTAL(9,D21:D21) -> 10805599 | E20: =SUBTOTAL(9,E21:E21) -> 21482.304
B21: 777720250245086683-1 | C21: Pago CCSS Abril | D21: 10805599 | E21: =D21/$D$6 -> 21482.304 | F21: 45790 | G21: Cancelado | H21: =IF(OR(G21="Sin pagar",G21="Pagar"),_xlfn.SINGLE(NETWORKDAYS($E$4,F21,'Festivos CR'!$A$3:$A$29)),0) -> 0 | I21: =NETWORKDAYS($E$4,F21,'Festivos CR'!$A$3:$A$29) -> 8 | J21: =H21 -> 0
C22: IMPUESTOS | D22: =SUBTOTAL(9,D23:D24) -> 4019000.4 | E22: =SUBTOTAL(9,E23:E24) -> 7988.712 | J22: =H22 -> 0
B23: 1034713727792 | C23: Retención en la fuente | D23: 3939728.4 | E23: =D23/$D$6 -> 7832.462 | F23: 45790 | G23: Cancelado | H23: =IF(OR(G23="Sin pagar",G23="Pagar"),_xlfn.SINGLE(NETWORKDAYS($E$4,F23,'Festivos CR'!$A$3:$A$29)),0) -> 0 | I23: =NETWORKDAYS($E$4,F23,'Festivos CR'!$A$3:$A$29) -> 8 | J23: =H23 -> 0
B24: 1034404293377 | C24: Rte fte por declaración de remesas al exterior Facturación S&P Colombia a S&P CR Fact 5898 | D24: 79272 | E24: 156.25 | F24: 45790 | G24: Cancelado | H24: =IF(OR(G24="Sin pagar",G24="Pagar"),_xlfn.SINGLE(NETWORKDAYS($E$4,F24,'Festivos CR'!$A$3:$A$29)),0) -> 0 | I24: =NETWORKDAYS($E$4,F24,'Festivos CR'!$A$3:$A$29) -> 8 | J24: =H24 -> 0
C25: SERVICIOS PROFESIONALES -REPRESENTACIÓN LEGAL | D25: =SUBTOTAL(9,D26:D27) -> 203650 | E25: =SUBTOTAL(9,E26:E27) -> 404.87078 | J25: =H25 -> 0
B26: 30 | C26: Servicios profesionales Alejandro Echavarria Enero | D26: 62400 | E26: =D26/$D$6 -> 124.05567 | F26: 45786 | G26: Cancelado | H26: =IF(OR(G26="Sin pagar",G26="Pagar"),_xlfn.SINGLE(NETWORKDAYS($E$4,F26,'Festivos CR'!$A$3:$A$29)),0) -> 0 | I26: =NETWORKDAYS($E$4,F26,'Festivos CR'!$A$3:$A$29) -> 6 | J26: =H26 -> 0
B27: 1753 | C27: Servicios de contabilidad/ estados para actualización | D27: 141250 | E27: =D27/$D$6 -> 280.81511 | F27: 45789 | G27: Cancelado | H27: =IF(OR(G27="Sin pagar",G27="Pagar"),_xlfn.SINGLE(NETWORKDAYS($E$4,F27,'Festivos CR'!$A$3:$A$29)),0) -> 0 | I27: =NETWORKDAYS($E$4,F27,'Festivos CR'!$A$3:$A$29) -> 7 | J27: =H27 -> 0
C28: GASTOS DE OFICINA | D28: =SUBTOTAL(9,D29:D29) -> 0 | E28: =SUBTOTAL(9,E29:E29) -> 0
B29: 62 | C29: Compra de café | D29: =77000*5*0 -> 0 | E29: =D29/$D$6 -> 0 | F29: 45808 | G29: Cancelado | H29: =IF(OR(G29="Sin pagar",G29="Pagar"),_xlfn.SINGLE(NETWORKDAYS($E$4,F29,'Festivos CR'!$A$3:$A$29)),0) -> 0 | I29: =NETWORKDAYS($E$4,F29,'Festivos CR'!$A$3:$A$29) -> 21 | J29: =H29 -> 0
C30: COBROS ENTRE SUCURSALES | D30: =SUBTOTAL(9,D31:D31) -> 0 | E30: =SUBTOTAL(9,E31:E31) -> 0
D31: =E31*$D$6 -> 0 | E31: =440*0 -> 0 | F31: 45808 | G31: Cancelado | H31: =IF(OR(G31="Sin pagar",G31="Pagar"),_xlfn.SINGLE(NETWORKDAYS($E$4,F31,'Festivos CR'!$A$3:$A$29)),0) -> 0 | I31: =NETWORKDAYS($E$4,F31,'Festivos CR'!$A$3:$A$29) -> 21 | J31: =H31 -> 0
C32: COSTOS FINANCIEROS | D32: =SUBTOTAL(9,D33:D33) -> 226412.83 | E32: =SUBTOTAL(9,E33:E33) -> 450.12491
C33: COSTOS FINANCIEROS | D33: =E33*D6 -> 226412.83 | E33: 450.12491 | F33: 45808 | G33: Cancelado | H33: =IF(OR(G33="Sin pagar",G33="Pagar"),_xlfn.SINGLE(NETWORKDAYS($E$4,F33,'Festivos CR'!$A$3:$A$29)),0) -> 0 | I33: =NETWORKDAYS($E$4,F33,'Festivos CR'!$A$3:$A$29) -> 21 | J33: =H33 -> 0
C34: NÓMINAS | D34: =SUBTOTAL(9,D35:D43) -> 20230669 | E34: =SUBTOTAL(9,E35:E43) -> 40314.452
B35: CRC | C35: Jhoel González González-Starlight-CR003-Liquidación | D35: 2870669.5 | E35: =D35/CONVERSIONES!$C$396 -> 5718.4651 | F35: 45783 | G35: Cancelado | H35: =IF(OR(G35="Sin pagar",G35="Pagar"),_xlfn.SINGLE(NETWORKDAYS($E$4,F35,'Festivos CR'!$A$3:$A$29)),0) -> 0 | I35: =NETWORKDAYS($E$4,F35,'Festivos CR'!$A$3:$A$29) -> 3 | J35: =H35 -> 0
B36: CRC | C36: Daniel Nazario Casto Vindas-Starlight-CR003-Liquidación | D36: 1195250.1 | E36: =D36/CONVERSIONES!$C$297 -> 2395.2908 | F36: 45789 | G36: Cancelado | H36: =IF(OR(G36="Sin pagar",G36="Pagar"),_xlfn.SINGLE(NETWORKDAYS($E$4,F36,'Festivos CR'!$A$3:$A$29)),0) -> 0 | I36: =NETWORKDAYS($E$4,F36,'Festivos CR'!$A$3:$A$29) -> 7 | J36: =H36 -> 0
B37: USD | C37: Jonathan Salazar García -Starlight-CR003 | D37: =E37*CONVERSIONES!$C$396 -> 1711177.4 | E37: 3408.72 | F37: 45805 | G37: Cancelado | H37: =IF(OR(G37="Sin pagar",G37="Pagar"),_xlfn.SINGLE(NETWORKDAYS($E$4,F37,'Festivos CR'!$A$3:$A$29)),0) -> 0 | I37: =NETWORKDAYS($E$4,F37,'Festivos CR'!$A$3:$A$29) -> 19 | J37: =H37 -> 0
B38: CRC | C38: Priscilla Grace Polson -Aluminati-CR004 | D38: 1405538.3 | E38: =D38/CONVERSIONES!$C$396 -> 2799.8771 | F38: 45805 | G38: Cancelado | H38: =IF(OR(G38="Sin pagar",G38="Pagar"),_xlfn.SINGLE(NETWORKDAYS($E$4,F38,'Festivos CR'!$A$3:$A$29)),0) -> 0 | I38: =NETWORKDAYS($E$4,F38,'Festivos CR'!$A$3:$A$29) -> 19 | J38: =H38 -> 0
B39: CRC | C39: José Roberto Aguilar Barrante-Aluminati-CR004 | D39: 1405538.3 | E39: =D39/CONVERSIONES!$C$396 -> 2799.8771 | F39: 45805 | G39: Cancelado | H39: =IF(OR(G39="Sin pagar",G39="Pagar"),_xlfn.SINGLE(NETWORKDAYS($E$4,F39,'Festivos CR'!$A$3:$A$29)),0) -> 0 | I39: =NETWORKDAYS($E$4,F39,'Festivos CR'!$A$3:$A$29) -> 19 | J39: =H39 -> 0
B40: CRC | C40: Sheryl Gertrudiz Cambronero Estrada-lorez & Prada PPLC | D40: 786551.54 | E40: =D40/CONVERSIONES!$C$396 -> 1566.8357 | F40: 45805 | G40: Cancelado | H40: =IF(OR(G40="Sin pagar",G40="Pagar"),_xlfn.SINGLE(NETWORKDAYS($E$4,F40,'Festivos CR'!$A$3:$A$29)),0) -> 0 | I40: =NETWORKDAYS($E$4,F40,'Festivos CR'!$A$3:$A$29) -> 19 | J40: =H40 -> 0
B41: USD | C41: Tatiana Araya Pochet-CZ-CR006 | D41: =E41*CONVERSIONES!$C$396 -> 3338104.2 | E41: 6649.61 | F41: 45805 | G41: Cancelado | H41: =IF(OR(G41="Sin pagar",G41="Pagar"),_xlfn.SINGLE(NETWORKDAYS($E$4,F41,'Festivos CR'!$A$3:$A$29)),0) -> 0 | I41: =NETWORKDAYS($E$4,F41,'Festivos CR'!$A$3:$A$29) -> 19 | J41: =H41 -> 0
B42: USD | C42: Bernal Fallas Barboza | D42: =E42*CONVERSIONES!$C$396 -> 2879984 | E42: 5737.02 | F42: 45805 | G42: Cancelado | H42: =IF(OR(G42="Sin pagar",G42="Pagar"),_xlfn.SINGLE(NETWORKDAYS($E$4,F42,'Festivos CR'!$A$3:$A$29)),0) -> 0 | I42: =NETWORKDAYS($E$4,F42,'Festivos CR'!$A$3:$A$29) -> 19 | J42: =H42 -> 0
B43: CRC | C43: Ricardo Manuel Garro Ruiz-Bipo | D43: 4637855.8 | E43: =D43/CONVERSIONES!$C$396 -> 9238.7565 | F43: 45805 | G43: Cancelado | H43: =IF(OR(G43="Sin pagar",G43="Pagar"),_xlfn.SINGLE(NETWORKDAYS($E$4,F43,'Festivos CR'!$A$3:$A$29)),0) -> 0 | I43: =NETWORKDAYS($E$4,F43,'Festivos CR'!$A$3:$A$29) -> 19 | J43: =H43 -> 0
C44: IMPREVISTO | D44: =SUBTOTAL(9,D45:D46) -> 7272554.2 | E44: =SUBTOTAL(9,E45:E46) -> 14458.358
C45: Devolución de dinero a casa Matriz prestamo Nom Tatia | D45: =$E$45*$D$6 -> 7017554.2 | E45: 13951.4 | F45: 45778 | G45: Cancelado | H45: =IF(OR(G45="Sin pagar",G45="Pagar"),_xlfn.SINGLE(NETWORKDAYS($E$4,F45,'Festivos CR'!$A$3:$A$29)),0) -> 0 | I45: =NETWORKDAYS($E$4,F45,'Festivos CR'!$A$3:$A$29) -> 0 | J45: =H45 -> 0 | M45: =E45*4210.84 -> 58747113
C46: Distribución Utilidades Alejandro-menos 15% | D46: 255000 | E46: =D46/$D$6 -> 506.95825 | F46: 45791 | G46: Cancelado | H46: =IF(OR(G46="Sin pagar",G46="Pagar"),_xlfn.SINGLE(NETWORKDAYS($E$4,F46,'Festivos CR'!$A$3:$A$29)),0) -> 0 | I46: =NETWORKDAYS($E$4,F46,'Festivos CR'!$A$3:$A$29) -> 9 | J46: =H46 -> 0
C47: TOTAL EGRESOS | D47: =SUBTOTAL(9,D20:D46) -> 42757886 | E47: =SUBTOTAL(9,E20:E46) -> 85098.823
C49: SALDO | D49: =D15-D47 -> 20801435 | E49: =E15-E47 -> 41385.639
C50: % | D50: =IF($D$15=0,0,D49/$D$15) -> 0.32727592 | E50: =IF($E$15=0,0,E49/$E$15) -> 0.32719939
C54: Fecha Inicial | D54: Fecha Final | E54: Valor VALOR ₡ CRC | F54: Valor VALOR USD
C55: 45778 | D55: 45781 | E55: =SUMIFS($D$19:$D$52,$F$19:$F$52,">="&C55,$F$19:$F$52,"<="&D55,$G$19:$G$52,$D$69) -> 0 | F55: =SUMIFS($E$19:$E$52,$F$19:$F$52,">="&C55,$F$19:$F$52,"<="&D55,$G$19:$G$52,$D$69) -> 0
C56: 45782 | D56: 45788 | E56: =SUMIFS($D$19:$D$52,$F$19:$F$52,">="&C56,$F$19:$F$52,"<="&D56,$G$19:$G$52,$D$69) -> 0 | F56: =SUMIFS($E$19:$E$52,$F$19:$F$52,">="&C56,$F$19:$F$52,"<="&D56,$G$19:$G$52,$D$69) -> 0 | G56: Liquidaciones Starlight
C57: 45789 | D57: 45795 | E57: =SUMIFS($D$19:$D$52,$F$19:$F$52,">="&C57,$F$19:$F$52,"<="&D57,$G$19:$G$52,$D$69) -> 0 | F57: =SUMIFS($E$19:$E$52,$F$19:$F$52,">="&C57,$F$19:$F$52,"<="&D57,$G$19:$G$52,$D$69) -> 0 | G57: CCSS e impuestos
C58: 45796 | D58: 45802 | E58: =SUMIFS($D$19:$D$52,$F$19:$F$52,">="&C58,$F$19:$F$52,"<="&D58,$G$19:$G$52,$D$69) -> 0 | F58: =SUMIFS($E$19:$E$52,$F$19:$F$52,">="&C58,$F$19:$F$52,"<="&D58,$G$19:$G$52,$D$69) -> 0
C59: 45803 | D59: 45808 | E59: =SUMIFS($D$19:$D$52,$F$19:$F$52,">="&C59,$F$19:$F$52,"<="&D59,$G$19:$G$52,$D$69) -> 0 | F59: =SUMIFS($E$19:$E$52,$F$19:$F$52,">="&C59,$F$19:$F$52,"<="&D59,$G$19:$G$52,$D$69) -> 0 | G59: Nóminas, GMF, Serv Alejandro
C60: TOTAL EGRESOS | E60: =SUM(E55:E59) -> 0 | F60: =SUM(F55:F59) -> 0
C63: Bancos | E63: ='BAC SAN JOSE COLONES '!$G$500+('BAC SAN JOSE USD'!$G$350*$D$6) -> 30791676 | F63: ='BAC SAN JOSE USD'!$G$350+('BAC SAN JOSE COLONES '!$G$500/$D$6) -> 61216.056
C64: Gastos y costos Periodo 01 al 25 de Mayo | E64: =SUM(E55:E59) -> 0 | F64: =SUM(F55:F59) -> 0
C65: Saldo | E65: =E63-E64 -> 30791676 | F65: =F63-F64 -> 61216.056
D68: Cancelado | E68: =SUMIFS($D$19:$D$52,$F$19:$F$52,">="&C55,$F$19:$F$52,"<="&$D$59,$G$19:$G$52,$D$68) -> 42757886 | F68: =SUMIFS($E$19:$E$52,$F$19:$F$52,">="&C55,$F$19:$F$52,"<="&$D$59,$G$19:$G$52,$D$68) -> 85098.823
D69: Sin Pagar | E69: =SUMIFS($D$19:$D$52,$F$19:$F$52,">="&C55,$F$19:$F$52,"<="&$D$59,$G$19:$G$52,$D$69) -> 0 | F69: =SUMIFS($E$19:$E$52,$F$19:$F$52,">="&C55,$F$19:$F$52,"<="&D59,$G$19:$G$52,$D$69) -> 0
D70: Total Egresos | E70: =SUM(E68:E69) -> 42757886 | F70: =SUM(F68:F69) -> 85098.823
D71: Validación | E71: =(D47-E70)*0 -> 0 | F71: =F70-E47 -> 0
D74: Flujo Caja | E74: =D49 -> 20801435
D75: Libro Bancos | E75: =('BAC SAN JOSE USD'!$G$304*$D$6)+'BAC SAN JOSE COLONES '!$G$392 -> 20801436
D76: Diferencia CRC | E76: =E75-E74 -> 0.72
D77: Diferencia USD | E77: =E76/D6 -> 0.0014314115

Sheet FLUJO CAJA JUNIO 2025 
D1: 42400
D4: Fecha de Elaboración: | E4: 45809
C6: Tasa de cambio: | D6: 503
D7: JUNIO
D8: VALOR ₡ CRC | E8: VALOR USD
C9: BANCOS | D9: =SUBTOTAL(9,D10:D11) -> 20660500 | E9: =SUBTOTAL(9,E10:E11) -> 41074.552
C10: Bancos ₡ CRC | D10: ='BAC SAN JOSE COLONES '!$G$392-140936.09 -> 18310621 | E10: =$D$10/$D$6 -> 36402.825
C11: Bancos USD | D11: =$E$11*$D$6 -> 2349878.9 | E11: ='BAC SAN JOSE USD'!$G$304 -> 4671.7273
C12: CLIENTES | D12: =SUBTOTAL(9,D13:D17) -> 27957346 | E12: =SUBTOTAL(9,E13:E17) -> 55797.65
B13: Pagado | C13: Client: Remorfist-Factura Nro 174 ( Ingreso Bernal Fallas) | D13: =$E$13*$D$6 -> 684935.1 | E13: ='BAC SAN JOSE USD'!$E$306 -> 1361.7
B14: Pagado | C14: Client: : Remorfist-Factura Nro 175 | D14: =E14*CONVERSIONES!$C$438 -> 18363684 | E14: ='BAC SAN JOSE USD'!E310 -> 36654.06
B15: Pagado | C15: Client: Buttergloble PTE LTD-Factura Nro 176 | D15: =$E$15*CONVERSIONES!$C$473 -> 8790485.9 | E15: =('BAC SAN JOSE USD'!$E$308-'BAC SAN JOSE USD'!$F$309) -> 17545.88
B16: Pagado | C16: Client: : Remorfist-Factura Nro 177 | D16: =E16*501 -> 68141.01 | E16: ='BAC SAN JOSE USD'!$E$311 -> 136.01
B17: Pagado | C17: Client: : Advancio-Factura Nro 164 | D17: =E17*501 -> 50100 | E17: 100
C18: TOTAL INGRESOS | D18: =SUBTOTAL(9,D9:D17) -> 48617845 | E18: =SUBTOTAL(9,E9:E17) -> 96872.202
B21: CUENTAS X PAGAR MES | D21: JUNIO
B22: Factura | C22: PROVEEDOR | D22: VALOR ₡ CRC | E22: VALOR USD | F22: Fecha vencimiento | G22: Estado | J22: KPI
C23: SEGURIDAD IGSS | D23: =SUBTOTAL(9,D24:D24) -> 7917247 | E23: =SUBTOTAL(9,E24:E24) -> 15740.054
B24: 777720250547036477-1 | C24: Pago CCSS Mayo | D24: 7917247 | E24: =D24/$D$6 -> 15740.054 | F24: 45820 | G24: Cancelado | H24: =IF(OR(G24="Sin pagar",G24="Pagar"),_xlfn.SINGLE(NETWORKDAYS($E$4,F24,'Festivos CR'!$A$3:$A$29)),0) -> 0 | I24: =NETWORKDAYS($E$4,F24,'Festivos CR'!$A$3:$A$29) -> 9 | J24: =H24 -> 0
C25: IMPUESTOS | D25: =SUBTOTAL(9,D26:D27) -> 2626897 | E25: =SUBTOTAL(9,E26:E27) -> 5157.6049 | J25: =H25 -> 0
B26: 1034713845986 | C26: Retención en la fuente | D26: 2547119 | E26: =D26/$D$6 -> 5063.8549 | F26: 45820 | G26: Cancelado | H26: =IF(OR(G26="Sin pagar",G26="Pagar"),_xlfn.SINGLE(NETWORKDAYS($E$4,F26,'Festivos CR'!$A$3:$A$29)),0) -> 0 | I26: =NETWORKDAYS($E$4,F26,'Festivos CR'!$A$3:$A$29) -> 9 | J26: =H26 -> 0
B27: 10344404309802 | C27: Rte fte por declaración de remesas al exterior Facturación S&P Colombia a S&P CR Fact 5898 | D27: 79778 | E27: =468.75*20% -> 93.75 | F27: 45820 | G27: Cancelado | H27: =IF(OR(G27="Sin pagar",G27="Pagar"),_xlfn.SINGLE(NETWORKDAYS($E$4,F27,'Festivos CR'!$A$3:$A$29)),0) -> 0 | I27: =NETWORKDAYS($E$4,F27,'Festivos CR'!$A$3:$A$29) -> 9 | J27: =H27 -> 0
C28: SERVICIOS PROFESIONALES -REPRESENTACIÓN LEGAL | D28: =SUBTOTAL(9,D29:D29) -> 62400 | E28: =SUBTOTAL(9,E29:E29) -> 124.05567 | J28: =H28 -> 0
B29: 31 | C29: Servicios profesionales Alejandro Echavarria Enero | D29: 62400 | E29: =D29/$D$6 -> 124.05567 | F29: 45820 | G29: Cancelado | H29: =IF(OR(G29="Sin pagar",G29="Pagar"),_xlfn.SINGLE(NETWORKDAYS($E$4,F29,'Festivos CR'!$A$3:$A$29)),0) -> 0 | I29: =NETWORKDAYS($E$4,F29,'Festivos CR'!$A$3:$A$29) -> 9 | J29: =H29 -> 0
C30: GASTOS DE OFICINA | D30: =SUBTOTAL(9,D31:D31) -> 0 | E30: =SUBTOTAL(9,E31:E31) -> 0
B31: 62 | C31: Compra de café | D31: =77000*6*0 -> 0 | E31: =D31/$D$6 -> 0 | F31: 45838 | G31: Cancelado | H31: =IF(OR(G31="Sin pagar",G31="Pagar"),_xlfn.SINGLE(NETWORKDAYS($E$4,F31,'Festivos CR'!$A$3:$A$29)),0) -> 0 | I31: =NETWORKDAYS($E$4,F31,'Festivos CR'!$A$3:$A$29) -> 21 | J31: =H31 -> 0
C32: COBROS ENTRE SUCURSALES | D32: =SUBTOTAL(9,D33:D33) -> 0 | E32: =SUBTOTAL(9,E33:E33) -> 0
D33: =E33*$D$6 -> 0 | E33: =440*0 -> 0 | F33: 45838 | G33: Cancelado | H33: =IF(OR(G33="Sin pagar",G33="Pagar"),_xlfn.SINGLE(NETWORKDAYS($E$4,F33,'Festivos CR'!$A$3:$A$29)),0) -> 0 | I33: =NETWORKDAYS($E$4,F33,'Festivos CR'!$A$3:$A$29) -> 21 | J33: =H33 -> 0
C34: COSTOS FINANCIEROS | D34: =SUBTOTAL(9,D35:D35) -> 0 | E34: =SUBTOTAL(9,E35:E35) -> 0
C35: COSTOS FINANCIEROS | D35: 0 | E35: 0 | F35: 45838 | G35: Cancelado | H35: =IF(OR(G35="Sin pagar",G35="Pagar"),_xlfn.SINGLE(NETWORKDAYS($E$4,F35,'Festivos CR'!$A$3:$A$29)),0) -> 0 | I35: =NETWORKDAYS($E$4,F35,'Festivos CR'!$A$3:$A$29) -> 21 | J35: =H35 -> 0
C36: NÓMINAS | D36: =SUBTOTAL(9,D37:D44) -> 15852186 | E36: =SUBTOTAL(9,E37:E44) -> 31578.06
B37: USD | C37: Tatiana Araya Pochet-CZ-CR006 | D37: =E37*CONVERSIONES!$C$396 -> 3348731.6 | E37: 6670.78 | F37: 45834 | G37: Cancelado | H37: =IF(OR(G37="Sin pagar",G37="Pagar"),_xlfn.SINGLE(NETWORKDAYS($E$4,F37,'Festivos CR'!$A$3:$A$29)),0) -> 0 | I37: =NETWORKDAYS($E$4,F37,'Festivos CR'!$A$3:$A$29) -> 19 | J37: =H37 -> 0
B38: USD | C38: Bernal Fallas Barboza | D38: =E38*CONVERSIONES!$C$396 -> 2540240.5 | E38: 5060.24 | F38: 45834 | G38: Cancelado | H38: =IF(OR(G38="Sin pagar",G38="Pagar"),_xlfn.SINGLE(NETWORKDAYS($E$4,F38,'Festivos CR'!$A$3:$A$29)),0) -> 0 | I38: =NETWORKDAYS($E$4,F38,'Festivos CR'!$A$3:$A$29) -> 19 | J38: =H38 -> 0
B39: USD | C39: Jonathan Salazar García -Starlight-CR003 | D39: =E39*CONVERSIONES!$C$396 -> 1716132.2 | E39: 3418.59 | F39: 45834 | G39: Cancelado | H39: =IF(OR(G39="Sin pagar",G39="Pagar"),_xlfn.SINGLE(NETWORKDAYS($E$4,F39,'Festivos CR'!$A$3:$A$29)),0) -> 0 | I39: =NETWORKDAYS($E$4,F39,'Festivos CR'!$A$3:$A$29) -> 19 | J39: =H39 -> 0
B40: USD | C40: Cesar de Jesus Alvarado Castro -Bipo-CR010 | D40: =E40*CONVERSIONES!$C$396 -> 0 | E40: =531.22*0 -> 0 | F40: 45835 | G40: Sin Pagar | H40: =IF(OR(G40="Sin pagar",G40="Pagar"),_xlfn.SINGLE(NETWORKDAYS($E$4,F40,'Festivos CR'!$A$3:$A$29)),0) -> 20 | I40: =NETWORKDAYS($E$4,F40,'Festivos CR'!$A$3:$A$29) -> 20 | J40: =H40 -> 20
B41: CRC | C41: Priscilla Grace Polson -Aluminati-CR004 | D41: 1409287.6 | E41: =D41/CONVERSIONES!$C$396 -> 2807.3457 | F41: 45834 | G41: Cancelado | H41: =IF(OR(G41="Sin pagar",G41="Pagar"),_xlfn.SINGLE(NETWORKDAYS($E$4,F41,'Festivos CR'!$A$3:$A$29)),0) -> 0 | I41: =NETWORKDAYS($E$4,F41,'Festivos CR'!$A$3:$A$29) -> 19 | J41: =H41 -> 0
B42: CRC | C42: José Roberto Aguilar Barrante-Aluminati-CR004 | D42: 1409287.6 | E42: =D42/CONVERSIONES!$C$396 -> 2807.3457 | F42: 45834 | G42: Cancelado | H42: =IF(OR(G42="Sin pagar",G42="Pagar"),_xlfn.SINGLE(NETWORKDAYS($E$4,F42,'Festivos CR'!$A$3:$A$29)),0) -> 0 | I42: =NETWORKDAYS($E$4,F42,'Festivos CR'!$A$3:$A$29) -> 19 | J42: =H42 -> 0
B43: CRC | C43: Sheryl Gertrudiz Cambronero Estrada-lorez & Prada PPLC | D43: 786551.54 | E43: =D43/CONVERSIONES!$C$396 -> 1566.8357 | F43: 45834 | G43: Cancelado | H43: =IF(OR(G43="Sin pagar",G43="Pagar"),_xlfn.SINGLE(NETWORKDAYS($E$4,F43,'Festivos CR'!$A$3:$A$29)),0) -> 0 | I43: =NETWORKDAYS($E$4,F43,'Festivos CR'!$A$3:$A$29) -> 19 | J43: =H43 -> 0
B44: CRC | C44: Ricardo Manuel Garro Ruiz-Bipo | D44: 4641955.3 | E44: =D44/CONVERSIONES!$C$396 -> 9246.923 | F44: 45834 | G44: Cancelado | H44: =IF(OR(G44="Sin pagar",G44="Pagar"),_xlfn.SINGLE(NETWORKDAYS($E$4,F44,'Festivos CR'!$A$3:$A$29)),0) -> 0 | I44: =NETWORKDAYS($E$4,F44,'Festivos CR'!$A$3:$A$29) -> 19 | J44: =H44 -> 0
C45: IMPREVISTO | D45: =SUBTOTAL(9,D46:D46) -> 0 | E45: =SUBTOTAL(9,E46:E46) -> 0
C46: Imprevisto | D46: 0 | E46: =D46/$D$6 -> 0 | F46: 45838 | G46: Cancelado | H46: =IF(OR(G46="Sin pagar",G46="Pagar"),_xlfn.SINGLE(NETWORKDAYS($E$4,F46,'Festivos CR'!$A$3:$A$29)),0) -> 0 | I46: =NETWORKDAYS($E$4,F46,'Festivos CR'!$A$3:$A$29) -> 21 | J46: =H46 -> 0
C47: TOTAL EGRESOS | D47: =SUBTOTAL(9,D23:D46) -> 26458730 | E47: =SUBTOTAL(9,E23:E46) -> 52599.774
C49: SALDO | D49: =D18-D47 -> 22159115 | E49: =E18-E47 -> 44272.427
C50: % | D50: =IF($D$18=0,0,D49/$D$18) -> 0.45578152 | E50: =IF($E$18=0,0,E49/$E$18) -> 0.4570189
C54: Fecha Inicial | D54: Fecha Final | E54: Valor VALOR ₡ CRC | F54: Valor VALOR USD
C55: 45809 | D55: 45816 | E55: =SUMIFS($D$22:$D$52,$F$22:$F$52,">="&C55,$F$22:$F$52,"<="&D55,$G$22:$G$52,$D$68) -> 0 | F55: =SUMIFS($E$22:$E$52,$F$22:$F$52,">="&C55,$F$22:$F$52,"<="&D55,$G$22:$G$52,$D$68) -> 0
C56: 45817 | D56: 45823 | E56: =SUMIFS($D$22:$D$52,$F$22:$F$52,">="&C56,$F$22:$F$52,"<="&D56,$G$22:$G$52,$D$68) -> 0 | F56: =SUMIFS($E$22:$E$52,$F$22:$F$52,">="&C56,$F$22:$F$52,"<="&D56,$G$22:$G$52,$D$68) -> 0 | G56: SS, Taxes , Serv alejandro
C57: 45824 | D57: 45830 | E57: =SUMIFS($D$22:$D$52,$F$22:$F$52,">="&C57,$F$22:$F$52,"<="&D57,$G$22:$G$52,$D$68) -> 0 | F57: =SUMIFS($E$22:$E$52,$F$22:$F$52,">="&C57,$F$22:$F$52,"<="&D57,$G$22:$G$52,$D$68) -> 0
C58: 45831 | D58: 45838 | E58: =SUMIFS($D$22:$D$52,$F$22:$F$52,">="&C58,$F$22:$F$52,"<="&D58,$G$22:$G$52,$D$68) -> 0 | F58: =SUMIFS($E$22:$E$52,$F$22:$F$52,">="&C58,$F$22:$F$52,"<="&D58,$G$22:$G$52,$D$68) -> 0 | G58: Salario
C59: TOTAL EGRESOS | E59: =SUM(E55:E58) -> 0 | F59: =SUM(F55:F58) -> 0
C62: Bancos | E62: ='BAC SAN JOSE COLONES '!$G$500+('BAC SAN JOSE USD'!$G$350*$D$6) -> 30791676 | F62: ='BAC SAN JOSE USD'!$G$350+('BAC SAN JOSE COLONES '!$G$500/$D$6) -> 61216.056
C63: Gastos y costos Periodo 01 al 22 de Junio | E63: =SUM(E55:E57) -> 0 | F63: =SUM(F55:F57) -> 0
C64: Saldo | E64: =E62-E63 -> 30791676 | F64: =F62-F63 -> 61216.056
D67: Cancelado | E67: =SUMIFS($D$22:$D$52,$F$22:$F$52,">="&C55,$F$22:$F$52,"<="&D58,$G$22:$G$52,$D$67) -> 26458730 | F67: =SUMIFS($E$22:$E$52,$F$22:$F$52,">="&$C$55,$F$22:$F$52,"<="&$D$58,$G$22:$G$52,$D$67) -> 52599.774
D68: Sin Pagar | E68: =SUMIFS($D$22:$D$52,$F$22:$F$52,">="&C55,$F$22:$F$52,"<="&D58,$G$22:$G$52,$D$68) -> 0 | F68: =SUMIFS($E$22:$E$52,$F$22:$F$52,">="&C55,$F$22:$F$52,"<="&$D$58,$G$22:$G$52,$D$68) -> 0
D69: Total Egresos | E69: =SUM(E67:E68) -> 26458730 | F69: =SUM(F67:F68) -> 52599.774
D70: Validación | E70: =(D47-E69)*0 -> 0 | F70: =F69-E47 -> 0
D74: Flujo Caja | E74: =D49 -> 22159115
D75: Libro Bancos | E75: ='BAC SAN JOSE COLONES '!G405+('BAC SAN JOSE USD'!G320*$D$6) -> 22159115
D76: Diferencia CRC | E76: =E75-E74 -> -0.00059879199
D77: Diferencia USD | E77: =E76/D6 -> -1.1904413e-06

Sheet FLUJO CAJA JULIO 2025
D1: 42400
D4: Fecha de Elaboración: | E4: 45839
C6: Tasa de cambio: | D6: 499
D7: JULIO
D8: VALOR ₡ CRC | E8: VALOR USD
C9: BANCOS | D9: =SUBTOTAL(9,D10:D12) -> 22320917 | E9: =SUBTOTAL(9,E10:E12) -> 44731.296
C10: Bancos ₡ CRC | D10: ='BAC SAN JOSE COLONES '!$G$405 -> 19020452 | E10: =$D$10/$D$6 -> 38117.139
C11: Bancos USD | D11: =$E$11*$D$6 -> 3113703.6 | E11: ='BAC SAN JOSE USD'!$G$320 -> 6239.887
D12: 186760.74 | E12: =D12/D6 -> 374.27003
C13: CLIENTES | D13: =SUBTOTAL(9,D14:D18) -> 36150376 | E13: =SUBTOTAL(9,E14:E18) -> 72737.175
B14: Sin Pagar | C14: Client: Buttergloble PTE LTD-Factura Nro 178-Cesar de jesus Alvarado - Doncheng | D14: =$E$14*$D$6 -> 0 | E14: =CONVERSIONES!$C$494*0 -> 0
B15: Sin Pagar | C15: Client: Buttergloble PTE LTD-Factura Nro 179-Edward Gerardo Chavez - Doncheng | D15: =E15*D6 -> 0 | E15: =CONVERSIONES!$E$494*0 -> 0
B16: Pagado | C16: Client: BIPO -July 2025 -Factura 180 -Ricardo Manuel Garro Ruiz | D16: ='DIFERENCIA CAMBI'!F121 -> 9327167.1 | E16: =D16/'DIFERENCIA CAMBI'!E121 -> 18766.936
B17: Sin Pagar | C17: Client:BIPO -July 2025-Factura 181 Edward Gerardo Chavez Cesar de jesus Alvarado | D17: =E17*'DIFERENCIA CAMBI'!E122 -> 0 | E17: ='DIFERENCIA CAMBI'!G122*0 -> 0
B18: Pagado | C18: Client: : Remorfist-Factura Nro 182 | D18: =E18*'DIFERENCIA CAMBI'!E129 -> 26823209 | E18: =('DIFERENCIA CAMBI'!$G$123+'DIFERENCIA CAMBI'!$G$124+'DIFERENCIA CAMBI'!$G$125+'DIFERENCIA CAMBI'!$G$126+'DIFERENCIA CAMBI'!$G$127+'DIFERENCIA CAMBI'!$G$128+'DIFERENCIA CAMBI'!$G$129) -> 53970.239
C19: TOTAL INGRESOS | D19: =SUBTOTAL(9,D9:D18) -> 58471292 | E19: =SUBTOTAL(9,E9:E18) -> 117468.47
B22: CUENTAS X PAGAR MES | D22: JULIO
B23: Factura | C23: PROVEEDOR | D23: VALOR ₡ CRC | E23: VALOR USD | F23: Fecha vencimiento | G23: Estado | J23: KPI
C24: SEGURIDAD IGSS | D24: =SUBTOTAL(9,D25:D25) -> 7740863 | E24: =SUBTOTAL(9,E25:E25) -> 15512.752
B25: 777720250647709476-1 | C25: Pago CCSS Junio | D25: 7740863 | E25: =D25/$D$6 -> 15512.752 | F25: 45849 | G25: Cancelado | H25: =IF(OR(G25="Sin pagar",G25="Pagar"),_xlfn.SINGLE(NETWORKDAYS($E$4,F25,'Festivos CR'!$A$3:$A$29)),0) -> 0 | I25: =NETWORKDAYS($E$4,F25,'Festivos CR'!$A$3:$A$29) -> 9 | J25: =H25 -> 0
C26: IMPUESTOS | D26: =SUBTOTAL(9,D27:D29) -> 2509140 | E26: =SUBTOTAL(9,E27:E29) -> 5028.3367 | J26: =H26 -> 0
B27: 1034713962012 | C27: Retención en la fuente | D27: 2398432 | E27: =D27/$D$6 -> 4806.477 | F27: 45849 | G27: Cancelado | H27: =IF(OR(G27="Sin pagar",G27="Pagar"),_xlfn.SINGLE(NETWORKDAYS($E$4,F27,'Festivos CR'!$A$3:$A$29)),0) -> 0 | I27: =NETWORKDAYS($E$4,F27,'Festivos CR'!$A$3:$A$29) -> 9 | J27: =H27 -> 0
B28: 1034404325534 | C28: Rte fte por declaración de remesas al exterior Facturación S&P Colombia a S&P CR Fact 6068 | D28: 65708 | E28: =D28/$D$6 -> 131.67936 | F28: 45849 | G28: Cancelado | H28: =IF(OR(G28="Sin pagar",G28="Pagar"),_xlfn.SINGLE(NETWORKDAYS($E$4,F28,'Festivos CR'!$A$3:$A$29)),0) -> 0 | I28: =NETWORKDAYS($E$4,F28,'Festivos CR'!$A$3:$A$29) -> 9 | J28: =H28 -> 0
B29: 1034204029022 | C29: Rte fte Pago de dividendos | D29: 45000 | E29: =D29/$D$6 -> 90.180361 | F29: 45849 | G29: Cancelado | H29: =IF(OR(G29="Sin pagar",G29="Pagar"),_xlfn.SINGLE(NETWORKDAYS($E$4,F29,'Festivos CR'!$A$3:$A$29)),0) -> 0 | I29: =NETWORKDAYS($E$4,F29,'Festivos CR'!$A$3:$A$29) -> 9 | J29: =H29 -> 0
C30: SERVICIOS PROFESIONALES -REPRESENTACIÓN LEGAL | D30: =SUBTOTAL(9,D31:D31) -> 112774 | E30: =SUBTOTAL(9,E31:E31) -> 226 | J30: =H30 -> 0
B31: 33 | C31: Servicios profesionales Alejandro Echavarria Julio | D31: =E31*D6 -> 112774 | E31: 226 | F31: 45855 | G31: Cancelado | H31: =IF(OR(G31="Sin pagar",G31="Pagar"),_xlfn.SINGLE(NETWORKDAYS($E$4,F31,'Festivos CR'!$A$3:$A$29)),0) -> 0 | I31: =NETWORKDAYS($E$4,F31,'Festivos CR'!$A$3:$A$29) -> 13 | J31: =H31 -> 0
C32: GASTOS DE OFICINA | D32: =SUBTOTAL(9,D33:D33) -> 0 | E32: =SUBTOTAL(9,E33:E33) -> 0
B33: 62 | C33: Compra de café | D33: =77000*7*0 -> 0 | E33: =D33/$D$6 -> 0 | F33: 45869 | G33: Cancelado | H33: =IF(OR(G33="Sin pagar",G33="Pagar"),_xlfn.SINGLE(NETWORKDAYS($E$4,F33,'Festivos CR'!$A$3:$A$29)),0) -> 0 | I33: =NETWORKDAYS($E$4,F33,'Festivos CR'!$A$3:$A$29) -> 22 | J33: =H33 -> 0
C34: COBROS ENTRE SUCURSALES | D34: =SUBTOTAL(9,D35:D35) -> 0 | E34: =SUBTOTAL(9,E35:E35) -> 0
D35: =E35*$D$6 -> 0 | E35: =440*0 -> 0 | F35: 45869 | G35: Cancelado | H35: =IF(OR(G35="Sin pagar",G35="Pagar"),_xlfn.SINGLE(NETWORKDAYS($E$4,F35,'Festivos CR'!$A$3:$A$29)),0) -> 0 | I35: =NETWORKDAYS($E$4,F35,'Festivos CR'!$A$3:$A$29) -> 22 | J35: =H35 -> 0
C36: COSTOS FINANCIEROS | D36: =SUBTOTAL(9,D37:D37) -> 0 | E36: =SUBTOTAL(9,E37:E37) -> 0
C37: COSTOS FINANCIEROS | D37: 0 | E37: 0 | F37: 45869 | G37: Cancelado | H37: =IF(OR(G37="Sin pagar",G37="Pagar"),_xlfn.SINGLE(NETWORKDAYS($E$4,F37,'Festivos CR'!$A$3:$A$29)),0) -> 0 | I37: =NETWORKDAYS($E$4,F37,'Festivos CR'!$A$3:$A$29) -> 22 | J37: =H37 -> 0
C38: NÓMINAS | D38: =SUBTOTAL(9,D39:D52) -> 24098834 | E38: =SUBTOTAL(9,E39:E52) -> 48005.646
B39: USD | C39: Cesar de Jesus Alvarado Castro -Bipo-CR010 | D39: =E39*CONVERSIONES!$C$396 -> 266672.44 | E39: 531.22 | F39: 45855 | G39: Cancelado | H39: =IF(OR(G39="Sin pagar",G39="Pagar"),_xlfn.SINGLE(NETWORKDAYS($E$4,F39,'Festivos CR'!$A$3:$A$29)),0) -> 0 | I39: =NETWORKDAYS($E$4,F39,'Festivos CR'!$A$3:$A$29) -> 13 | J39: =H39 -> 0
B40: USD | C40: Edward Gerardo chaves chacon -Bipo-CR010 | D40: =E40*CONVERSIONES!$C$396 -> 64722.86 | E40: 128.93 | F40: 45855 | G40: Cancelado | H40: =IF(OR(G40="Sin pagar",G40="Pagar"),_xlfn.SINGLE(NETWORKDAYS($E$4,F40,'Festivos CR'!$A$3:$A$29)),0) -> 0 | I40: =NETWORKDAYS($E$4,F40,'Festivos CR'!$A$3:$A$29) -> 13 | J40: =H40 -> 0
B41: USD | C41: Tatiana Araya Pochet-CZ-CR006 | D41: =E41*CONVERSIONES!$C$396 -> 3348947.4 | E41: 6671.21 | F41: 45866 | G41: Cancelado | H41: =IF(OR(G41="Sin pagar",G41="Pagar"),_xlfn.SINGLE(NETWORKDAYS($E$4,F41,'Festivos CR'!$A$3:$A$29)),0) -> 0 | I41: =NETWORKDAYS($E$4,F41,'Festivos CR'!$A$3:$A$29) -> 19 | J41: =H41 -> 0
B42: USD | C42: Bernal Fallas Barboza | D42: =E42*CONVERSIONES!$C$396 -> 2540456.3 | E42: 5060.67 | F42: 45866 | G42: Cancelado | H42: =IF(OR(G42="Sin pagar",G42="Pagar"),_xlfn.SINGLE(NETWORKDAYS($E$4,F42,'Festivos CR'!$A$3:$A$29)),0) -> 0 | I42: =NETWORKDAYS($E$4,F42,'Festivos CR'!$A$3:$A$29) -> 19 | J42: =H42 -> 0
B43: USD | C43: Jonathan Salazar García -Starlight-CR003 | D43: =E43*CONVERSIONES!$C$396 -> 1716102.1 | E43: 3418.53 | F43: 45866 | G43: Cancelado | H43: =IF(OR(G43="Sin pagar",G43="Pagar"),_xlfn.SINGLE(NETWORKDAYS($E$4,F43,'Festivos CR'!$A$3:$A$29)),0) -> 0 | I43: =NETWORKDAYS($E$4,F43,'Festivos CR'!$A$3:$A$29) -> 19 | J43: =H43 -> 0
B44: USD | C44: Angel Alberto Torres GOnzalez -Skelling Aotomation US LLC-CR003 | D44: =E44*CONVERSIONES!$C$396 -> 3098881.1 | E44: 6173.07 | F44: 45866 | G44: Cancelado | H44: =IF(OR(G44="Sin pagar",G44="Pagar"),_xlfn.SINGLE(NETWORKDAYS($E$4,F44,'Festivos CR'!$A$3:$A$29)),0) -> 0 | I44: =NETWORKDAYS($E$4,F44,'Festivos CR'!$A$3:$A$29) -> 19 | J44: =H44 -> 0
B45: USD | C45: Edward Gerardo chaves chacon -Bipo-CR010 | D45: =E45*CONVERSIONES!$C$396 -> 1775348.1 | E45: 3536.55 | F45: 45866 | G45: Cancelado | H45: =IF(OR(G45="Sin pagar",G45="Pagar"),_xlfn.SINGLE(NETWORKDAYS($E$4,F45,'Festivos CR'!$A$3:$A$29)),0) -> 0 | I45: =NETWORKDAYS($E$4,F45,'Festivos CR'!$A$3:$A$29) -> 19 | J45: =H45 -> 0
B46: CRC | C46: Priscilla Grace Polson -Aluminati-CR004 | D46: 1409287.6 | E46: =D46/CONVERSIONES!$C$396 -> 2807.3457 | F46: 45866 | G46: Cancelado | H46: =IF(OR(G46="Sin pagar",G46="Pagar"),_xlfn.SINGLE(NETWORKDAYS($E$4,F46,'Festivos CR'!$A$3:$A$29)),0) -> 0 | I46: =NETWORKDAYS($E$4,F46,'Festivos CR'!$A$3:$A$29) -> 19 | J46: =H46 -> 0
B47: CRC | C47: José Roberto Aguilar Barrante-Aluminati-CR004 | D47: 1409287.6 | E47: =D47/CONVERSIONES!$C$396 -> 2807.3457 | F47: 45866 | G47: Cancelado | H47: =IF(OR(G47="Sin pagar",G47="Pagar"),_xlfn.SINGLE(NETWORKDAYS($E$4,F47,'Festivos CR'!$A$3:$A$29)),0) -> 0 | I47: =NETWORKDAYS($E$4,F47,'Festivos CR'!$A$3:$A$29) -> 19 | J47: =H47 -> 0
B48: CRC | C48: Sheryl Gertrudiz Cambronero Estrada-lorez & Prada PPLC | D48: 786551.54 | E48: =D48/CONVERSIONES!$C$396 -> 1566.8357 | F48: 45866 | G48: Cancelado | H48: =IF(OR(G48="Sin pagar",G48="Pagar"),_xlfn.SINGLE(NETWORKDAYS($E$4,F48,'Festivos CR'!$A$3:$A$29)),0) -> 0 | I48: =NETWORKDAYS($E$4,F48,'Festivos CR'!$A$3:$A$29) -> 19 | J48: =H48 -> 0
B49: CRC | C49: María Fernanda Mora Mora -Central Business Solutions INC-CR014 | D49: 575515.22 | E49: =D49/CONVERSIONES!$C$396 -> 1146.4447 | F49: 45866 | G49: Cancelado | H49: =IF(OR(G49="Sin pagar",G49="Pagar"),_xlfn.SINGLE(NETWORKDAYS($E$4,F49,'Festivos CR'!$A$3:$A$29)),0) -> 0 | I49: =NETWORKDAYS($E$4,F49,'Festivos CR'!$A$3:$A$29) -> 19 | J49: =H49 -> 0
B50: CRC | C50: Adriana Barboza Quiroz -Remofisrt - Onewell LLC-CR014 | D50: 421042.07 | E50: =D50/CONVERSIONES!$C$396 -> 838.72922 | F50: 45867 | G50: Cancelado | H50: =IF(OR(G50="Sin pagar",G50="Pagar"),_xlfn.SINGLE(NETWORKDAYS($E$4,F50,'Festivos CR'!$A$3:$A$29)),0) -> 0 | I50: =NETWORKDAYS($E$4,F50,'Festivos CR'!$A$3:$A$29) -> 20 | J50: =H50 -> 0
B51: CRC | C51: Ricardo Manuel Garro Ruiz-Bipo | D51: 4646054.9 | E51: =D51/CONVERSIONES!$C$396 -> 9255.0894 | F51: 45867 | G51: Cancelado | H51: =IF(OR(G51="Sin pagar",G51="Pagar"),_xlfn.SINGLE(NETWORKDAYS($E$4,F51,'Festivos CR'!$A$3:$A$29)),0) -> 0 | I51: =NETWORKDAYS($E$4,F51,'Festivos CR'!$A$3:$A$29) -> 20 | J51: =H51 -> 0
B52: CRC | C52: Gilberto Esteban Solano Melendez-Berkheimer Enterprises LLC -CR009 | D52: 2039964.9 | E52: =D52/CONVERSIONES!$C$396 -> 4063.6751 | F52: 45867 | G52: Cancelado | H52: =IF(OR(G52="Sin pagar",G52="Pagar"),_xlfn.SINGLE(NETWORKDAYS($E$4,F52,'Festivos CR'!$A$3:$A$29)),0) -> 0 | I52: =NETWORKDAYS($E$4,F52,'Festivos CR'!$A$3:$A$29) -> 20 | J52: =H52 -> 0
C53: IMPREVISTO | D53: =SUBTOTAL(9,D54:D56) -> 592502.28 | E53: =SUBTOTAL(9,E54:E56) -> 1187.3793
C54: Cobro token mensual | D54: ='BAC SAN JOSE COLONES '!F407 -> 512 | E54: =D54/$D$6 -> 1.0260521 | F54: 45839 | G54: Cancelado | H54: =IF(OR(G54="Sin pagar",G54="Pagar"),_xlfn.SINGLE(NETWORKDAYS($E$4,F54,'Festivos CR'!$A$3:$A$29)),0) -> 0 | I54: =NETWORKDAYS($E$4,F54,'Festivos CR'!$A$3:$A$29) -> 1 | J54: =H54 -> 0
C55: Reembolso Gastos José Roberto Aguilar Barrante-Aluminati | D55: =$E$55*$D$6 -> 67868.99 | E55: 136.01 | F55: 45852 | G55: Cancelado | H55: =IF(OR(G55="Sin pagar",G55="Pagar"),_xlfn.SINGLE(NETWORKDAYS($E$4,F55,'Festivos CR'!$A$3:$A$29)),0) -> 0 | I55: =NETWORKDAYS($E$4,F55,'Festivos CR'!$A$3:$A$29) -> 10 | J55: =H55 -> 0
C56: Reembolso Gastos Ricardo Manuel Garro Ruiz-BIPO-CATL | D56: 524121.29 | E56: =D56/D6 -> 1050.3433 | F56: 45873 | G56: Cancelado | H56: =IF(OR(G56="Sin pagar",G56="Pagar"),_xlfn.SINGLE(NETWORKDAYS($E$4,F56,'Festivos CR'!$A$3:$A$29)),0) -> 0 | I56: =NETWORKDAYS($E$4,F56,'Festivos CR'!$A$3:$A$29) -> 24 | J56: =H56 -> 0
C57: TOTAL EGRESOS | D57: =SUBTOTAL(9,D24:D56) -> 35054113 | E57: =SUBTOTAL(9,E24:E56) -> 69960.113
C59: SALDO | D59: =D19-D57 -> 23417179 | E59: =E19-E57 -> 47508.357
C60: % | D60: =IF($D$19=0,0,D59/$D$19) -> 0.40049019 | E60: =IF($E$19=0,0,E59/$E$19) -> 0.40443497
C64: Fecha Inicial | D64: Fecha Final | E64: Valor VALOR ₡ CRC | F64: Valor VALOR USD
C65: 45839 | D65: 45844 | E65: =SUMIFS($D$23:$D$62,$F$23:$F$62,">="&C65,$F$23:$F$62,"<="&D65,$G$23:$G$62,$D$80) -> 0 | F65: =SUMIFS($E$23:$E$62,$F$23:$F$62,">="&C65,$F$23:$F$62,"<="&D65,$G$23:$G$62,$D$80) -> 0 | G65: Nomina Ingreso Remofirst
C66: 45845 | D66: 45851 | E66: =SUMIFS($D$23:$D$62,$F$23:$F$62,">="&C66,$F$23:$F$62,"<="&D66,$G$23:$G$62,$D$80) -> 0 | F66: =SUMIFS($E$23:$E$62,$F$23:$F$62,">="&C66,$F$23:$F$62,"<="&D66,$G$23:$G$62,$D$80) -> 0 | G66: SS, Taxes
C67: 45852 | D67: 45858 | E67: =SUMIFS($D$23:$D$62,$F$23:$F$62,">="&C67,$F$23:$F$62,"<="&D67,$G$23:$G$62,$D$80) -> 0 | F67: =SUMIFS($E$23:$E$62,$F$23:$F$62,">="&C67,$F$23:$F$62,"<="&D67,$G$23:$G$62,$D$80) -> 0 | G67: Serv alejandro
C68: 45859 | D68: 45865 | E68: =SUMIFS($D$23:$D$62,$F$23:$F$62,">="&C68,$F$23:$F$62,"<="&D68,$G$23:$G$62,$D$80) -> 0 | F68: =SUMIFS($E$23:$E$62,$F$23:$F$62,">="&C68,$F$23:$F$62,"<="&D68,$G$23:$G$62,$D$80) -> 0
C69: 45866 | D69: 45869 | E69: =SUMIFS($D$23:$D$62,$F$23:$F$62,">="&C69,$F$23:$F$62,"<="&D69,$G$23:$G$62,$D$80) -> 0 | F69: =SUMIFS($E$23:$E$62,$F$23:$F$62,">="&C69,$F$23:$F$62,"<="&D69,$G$23:$G$62,$D$80) -> 0 | G69: Nóminas
C70: 45870 | D70: 45874 | E70: =SUMIFS($D$23:$D$62,$F$23:$F$62,">="&C70,$F$23:$F$62,"<="&D70,$G$23:$G$62,$D$80) -> 0 | F70: =SUMIFS($E$23:$E$62,$F$23:$F$62,">="&C70,$F$23:$F$62,"<="&D70,$G$23:$G$62,$D$80) -> 0
C71: TOTAL EGRESOS | E71: =SUM(E65:E70) -> 0 | F71: =SUM(F65:F70) -> 0
C74: Bancos | E74: ='BAC SAN JOSE COLONES '!$G$500+('BAC SAN JOSE USD'!$G$350*$D$6) -> 30611208 | F74: ='BAC SAN JOSE USD'!$G$350+('BAC SAN JOSE COLONES '!$G$500/$D$6) -> 61345.105
C75: Gastos y costos Periodo 01 al 27 Julio | E75: =SUM(E65:E68) -> 0 | F75: =SUM(F65:F68) -> 0
C76: Saldo | E76: =E74-E75 -> 30611208 | F76: =F74-F75 -> 61345.105
D79: Cancelado | E79: =SUMIFS($D$23:$D$62,$F$23:$F$62,">="&C65,$F$23:$F$62,"<="&D70,$G$23:$G$62,$D$79) -> 35054113 | F79: =SUMIFS($E$23:$E$62,$F$23:$F$62,">="&$C$65,$F$23:$F$62,"<="&$D$70,$G$23:$G$62,$D$79) -> 69960.113
D80: Sin Pagar | E80: =SUMIFS($D$23:$D$62,$F$23:$F$62,">="&C65,$F$23:$F$62,"<="&D70,$G$23:$G$62,$D$80) -> 0 | F80: =SUMIFS($E$23:$E$62,$F$23:$F$62,">="&C65,$F$23:$F$62,"<="&$D$70,$G$23:$G$62,$D$80) -> 0
D81: Total Egresos | E81: =SUM(E79:E80) -> 35054113 | F81: =SUM(F79:F80) -> 69960.113
D82: Validación | E82: =(D57-E81)*0 -> 0 | F82: =F81-E57 -> 0
D86: Flujo Caja | E86: =D59 -> 23417179
D87: Libro Bancos | E87: ='BAC SAN JOSE COLONES '!$G$425+('BAC SAN JOSE USD'!$G$340*$D$6) -> 23417179
D88: Diferencia CRC | E88: =E87-E86 -> 0
D89: Diferencia USD | E89: =E88/D6 -> 0

Sheet FLUJO CAJA AGOSTO 2025
D1: 42400
D4: Fecha de Elaboración: | E4: 45870
C6: Tasa de cambio: | D6: 499
D7: AGOSTO
D8: VALOR ₡ CRC | E8: VALOR USD
C9: BANCOS | D9: =SUBTOTAL(9,D10:D11) -> 23417179 | E9: =SUBTOTAL(9,E10:E11) -> 46928.214
C10: Bancos ₡ CRC | D10: ='BAC SAN JOSE COLONES '!$G$425 -> 20208740 | E10: =$D$10/$D$6 -> 40498.477
C11: Bancos USD | D11: =$E$11*$D$6 -> 3208438.8 | E11: ='BAC SAN JOSE USD'!$G$340 -> 6429.737
C12: CLIENTES | D12: =SUBTOTAL(9,D13:D24) -> 53360219 | E12: =SUBTOTAL(9,E13:E24) -> 106978.06
B13: Pagado | C13: Client: Buttergloble PTE LTD-Factura Nro 178-Cesar de jesus Alvarado - Doncheng | D13: =$E$13*$D$6 -> 483421.22 | E13: =CONVERSIONES!$C$494 -> 968.78
B14: Pagado | C14: Client: Buttergloble PTE LTD-Factura Nro 179-Edward Gerardo Chavez - Doncheng | D14: =E14*D6 -> 177788.71 | E14: =CONVERSIONES!$E$494 -> 356.29
B15: Pagado | C15: Client:BIPO -July 2025-Factura 181 Edward Gerardo Chavez Cesar de jesus Alvarado | D15: =E15*'DIFERENCIA CAMBI'!E122 -> 3455807.1 | E15: ='DIFERENCIA CAMBI'!G122 -> 6953.3342
B16: Pagado | C16: Client: : Remorfist-Factura Nro 183-Onboarding | D16: =E16*497 -> 1997383.4 | E16: 4018.88 | F16: ****
B17: Pagado | C17: Client: : Remorfist-Factura Nro 184 | D17: =E17*$D$6 -> 32198725 | E17: =CONVERSIONES!T547 -> 64526.503 | F17: **** | G17: =E16+E17+E23 -> 68656.793
B18: Pagado | C18: BIPO -August 2025 Ricardo Manuel Garro Ruiz- Factura Nro 185 | D18: =E18*$D$6 -> 9514648.4 | E18: ='DIFERENCIA CAMBI'!G139 -> 19067.432 | G18: ='BAC SAN JOSE USD'!E366 -> 68656.79
B19: Pagado | C19: BIPO August 2025 Edward Gerardo Chavez- Factura Nro 186 | D19: =E19*$D$6 -> 2998795.4 | E19: ='DIFERENCIA CAMBI'!G140 -> 6009.61 | G19: =+G18-G17 -> -0.0031
D20: -523335.37 | E20: =$D$20/$D$6 -> -1048.7683
B21: Pagado | C21: BIPO August 2025 Luis Angel Vega- Factura Nro 187 | D21: =E21*$D$6 -> 2808037.7 | E21: ='DIFERENCIA CAMBI'!G141 -> 5627.33
B22: Pagado | C22: Client: : Remorfist-Factura Nro 189 | D22: =E22*$D$6 -> 193242.74 | E22: ='DIFERENCIA CAMBI'!G143 -> 387.26
B23: Pagado | C23: Client: : Remorfist-Factura Nro 188-Termination | D23: =E23*500 -> 55705 | E23: 111.41 | F23: ****
B24: Sin Pagar | C24: BIPO -August 2025 Oscar Josue Perez -Sany - Fact Nro 190 | D24: =E24*$D$6 -> 0 | E24: =725.78*0 -> 0
C25: TOTAL INGRESOS | D25: =SUBTOTAL(9,D9:D24) -> 76777398 | E25: =SUBTOTAL(9,E9:E24) -> 153906.27
B28: CUENTAS X PAGAR MES | D28: AGOSTO
B29: Factura | C29: PROVEEDOR | D29: VALOR ₡ CRC | E29: VALOR USD | F29: Fecha vencimiento | G29: Estado | J29: KPI
C30: SEGURIDAD IGSS | D30: =SUBTOTAL(9,D31:D31) -> 11489421 | E30: =SUBTOTAL(9,E31:E31) -> 23024.892
B31: 7777202507483870007777202507483857321 | C31: Pago CCSS Junio | D31: 11489421 | E31: =D31/$D$6 -> 23024.892 | F31: 45881 | G31: Cancelado | H31: =IF(OR(G31="Sin pagar",G31="Pagar"),_xlfn.SINGLE(NETWORKDAYS($E$4,F31,'Festivos CR'!$A$3:$A$29)),0) -> 0 | I31: =NETWORKDAYS($E$4,F31,'Festivos CR'!$A$3:$A$29) -> 8 | J31: =H31 -> 0
C32: IMPUESTOS | D32: =SUBTOTAL(9,D33:D34) -> 3429320 | E32: =SUBTOTAL(9,E33:E34) -> 7127.3098 | J32: =H32 -> 0
B33: 1034714093463 | C33: Retención en la fuente | D33: 3336269 | E33: =D33/$D$6 -> 6685.9098 | F33: 45883 | G33: Cancelado | H33: =IF(OR(G33="Sin pagar",G33="Pagar"),_xlfn.SINGLE(NETWORKDAYS($E$4,F33,'Festivos CR'!$A$3:$A$29)),0) -> 0 | I33: =NETWORKDAYS($E$4,F33,'Festivos CR'!$A$3:$A$29) -> 10 | J33: =H33 -> 0
B34: 1034404343743 | C34: Rte fte por declaración de remesas al exterior Facturación S&P Colombia a S&P CR Fact 6162 | D34: 93051 | E34: =551.75*0.8 -> 441.4 | F34: 45883 | G34: Cancelado | H34: =IF(OR(G34="Sin pagar",G34="Pagar"),_xlfn.SINGLE(NETWORKDAYS($E$4,F34,'Festivos CR'!$A$3:$A$29)),0) -> 0 | I34: =NETWORKDAYS($E$4,F34,'Festivos CR'!$A$3:$A$29) -> 10 | J34: =H34 -> 0
C35: SERVICIOS PROFESIONALES -REPRESENTACIÓN LEGAL | D35: =SUBTOTAL(9,D36:D36) -> 112774 | E35: =SUBTOTAL(9,E36:E36) -> 226 | J35: =H35 -> 0
B36: 34 | C36: Servicios profesionales Alejandro Echavarria Julio | D36: =E36*D6 -> 112774 | E36: 226 | F36: 45883 | G36: Cancelado | H36: =IF(OR(G36="Sin pagar",G36="Pagar"),_xlfn.SINGLE(NETWORKDAYS($E$4,F36,'Festivos CR'!$A$3:$A$29)),0) -> 0 | I36: =NETWORKDAYS($E$4,F36,'Festivos CR'!$A$3:$A$29) -> 10 | J36: =H36 -> 0
C37: GASTOS DE OFICINA | D37: =SUBTOTAL(9,D38:D38) -> 0 | E37: =SUBTOTAL(9,E38:E38) -> 0
B38: 62 | C38: Compra de café | D38: =77000*8*0 -> 0 | E38: =D38/$D$6 -> 0 | F38: 45900 | G38: Cancelado | H38: =IF(OR(G38="Sin pagar",G38="Pagar"),_xlfn.SINGLE(NETWORKDAYS($E$4,F38,'Festivos CR'!$A$3:$A$29)),0) -> 0 | I38: =NETWORKDAYS($E$4,F38,'Festivos CR'!$A$3:$A$29) -> 20 | J38: =H38 -> 0
C39: COBROS ENTRE SUCURSALES | D39: =SUBTOTAL(9,D40:D40) -> 0 | E39: =SUBTOTAL(9,E40:E40) -> 0
B40: Varias Fac | C40: Solutions & Payroll SAS 5811-5898-5981-6062-6162 | D40: =E40*$D$6 -> 0 | E40: =((390.81+468.75+468.75+386.75+551.75)*0.8)*0 -> 0 | F40: 45899 | G40: Cancelado | H40: =IF(OR(G40="Sin pagar",G40="Pagar"),_xlfn.SINGLE(NETWORKDAYS($E$4,F40,'Festivos CR'!$A$3:$A$29)),0) -> 0 | I40: =NETWORKDAYS($E$4,F40,'Festivos CR'!$A$3:$A$29) -> 20 | J40: =H40 -> 0
C41: COSTOS FINANCIEROS | D41: =SUBTOTAL(9,D42:D42) -> 19960 | E41: =SUBTOTAL(9,E42:E42) -> 40
C42: COSTOS FINANCIEROS | D42: =E42*D6 -> 19960 | E42: 40 | F42: 45900 | G42: Cancelado | H42: =IF(OR(G42="Sin pagar",G42="Pagar"),_xlfn.SINGLE(NETWORKDAYS($E$4,F42,'Festivos CR'!$A$3:$A$29)),0) -> 0 | I42: =NETWORKDAYS($E$4,F42,'Festivos CR'!$A$3:$A$29) -> 20 | J42: =H42 -> 0
C43: NÓMINAS | D43: =SUBTOTAL(9,D44:D58) -> 28024656 | E43: =SUBTOTAL(9,E44:E58) -> 55826.008
